Workbook

Sheet Grid_cost_Base
A1: Base Scenario
A2: =Cost_of_ELCgen!A149 -> Calculations | C2: =Cost_of_ELCgen!C149 -> 2020 | D2: =Cost_of_ELCgen!D149 -> 2021 | E2: =Cost_of_ELCgen!E149 -> 2022 | F2: =Cost_of_ELCgen!F149 -> 2023 | G2: =Cost_of_ELCgen!G149 -> 2024 | H2: =Cost_of_ELCgen!H149 -> 2025 | I2: =Cost_of_ELCgen!I149 -> 2026 | J2: =Cost_of_ELCgen!J149 -> 2027 | ... AG2: =Cost_of_ELCgen!AG149 -> 2050
A3: =Cost_of_ELCgen!A150 -> Operating O&M costs | C3: =Cost_of_ELCgen!C150 -> 3983.2719 | D3: =Cost_of_ELCgen!D150 -> 4094.6976 | E3: =Cost_of_ELCgen!E150 -> 4526.0522 | F3: =Cost_of_ELCgen!F150 -> 4486.0345 | G3: =Cost_of_ELCgen!G150 -> 4730.4563 | H3: =Cost_of_ELCgen!H150 -> 4392.5777 | I3: =Cost_of_ELCgen!I150 -> 4461.4024 | J3: =Cost_of_ELCgen!J150 -> 4529.1519 | ... AG3: =Cost_of_ELCgen!AG150 -> 9963.7135
A4: =Cost_of_ELCgen!A151 -> Annualized Investment costs | C4: =Cost_of_ELCgen!C151 -> 234.83856 | D4: =Cost_of_ELCgen!D151 -> 756.46065 | E4: =Cost_of_ELCgen!E151 -> 918.84101 | F4: =Cost_of_ELCgen!F151 -> 1006.569 | G4: =Cost_of_ELCgen!G151 -> 1158.3122 | H4: =Cost_of_ELCgen!H151 -> 1276.2681 | I4: =Cost_of_ELCgen!I151 -> 1548.5939 | J4: =Cost_of_ELCgen!J151 -> 1822.3775 | ... AG4: =Cost_of_ELCgen!AG151 -> 10340.388
A5: =Cost_of_ELCgen!A152 -> CO2 costs | C5: =Cost_of_ELCgen!C152 -> 0 | D5: =Cost_of_ELCgen!D152 -> 0 | E5: =Cost_of_ELCgen!E152 -> 0 | F5: =Cost_of_ELCgen!F152 -> 0 | G5: =Cost_of_ELCgen!G152 -> 0 | H5: =Cost_of_ELCgen!H152 -> 0 | I5: =Cost_of_ELCgen!I152 -> 0 | J5: =Cost_of_ELCgen!J152 -> 0 | ... AG5: =Cost_of_ELCgen!AG152 -> 0
A6: =Cost_of_ELCgen!A153 -> Total Costs (Million USD) | C6: =Cost_of_ELCgen!C153 -> 4218.1105 | D6: =Cost_of_ELCgen!D153 -> 4851.1582 | E6: =Cost_of_ELCgen!E153 -> 5444.8932 | F6: =Cost_of_ELCgen!F153 -> 5492.6035 | G6: =Cost_of_ELCgen!G153 -> 5888.7685 | H6: =Cost_of_ELCgen!H153 -> 5668.8458 | I6: =Cost_of_ELCgen!I153 -> 6009.9962 | J6: =Cost_of_ELCgen!J153 -> 6351.5293 | ... AG6: =Cost_of_ELCgen!AG153 -> 20304.101
A7: =Cost_of_ELCgen!A154 -> Generation (PJ->GWh), Before Transmission losses | C7: =Cost_of_ELCgen!C154 -> 101777.5 | D7: =Cost_of_ELCgen!D154 -> 106114.19 | E7: =Cost_of_ELCgen!E154 -> 111516.75 | F7: =Cost_of_ELCgen!F154 -> 118003.75 | G7: =Cost_of_ELCgen!G154 -> 126941.64 | H7: =Cost_of_ELCgen!H154 -> 121202.19 | I7: =Cost_of_ELCgen!I154 -> 127495.36 | J7: =Cost_of_ELCgen!J154 -> 133792.56 | ... AG7: =Cost_of_ELCgen!AG154 -> 338911.81
A8: =Cost_of_ELCgen!A155 -> Average electricity cost (USD/kWh) | C8: =Cost_of_ELCgen!C155 -> 0.04144443 | D8: =Cost_of_ELCgen!D155 -> 0.045716393 | E8: =Cost_of_ELCgen!E155 -> 0.048825788 | F8: =Cost_of_ELCgen!F155 -> 0.046546008 | G8: =Cost_of_ELCgen!G155 -> 0.046389574 | H8: =Cost_of_ELCgen!H155 -> 0.046771808 | I8: =Cost_of_ELCgen!I155 -> 0.04713894 | J8: =Cost_of_ELCgen!J155 -> 0.047472965 | ... AG8: =Cost_of_ELCgen!AG155 -> 0.059909691

Sheet Investments_Base
A1: Base Scenario
A3: Variable | C3: 2020 | D3: 2021 | E3: 2022 | F3: 2023 | G3: 2024 | H3: 2025 | I3: 2026 | J3: 2027 | K3: 2028 | L3: 2029 | M3: 2030 | N3: 2031 | O3: 2032 | P3: 2033 | Q3: 2034 | R3: 2035 | S3: 2036 | T3: 2037 | U3: 2038 | V3: 2039 | W3: 2040 | X3: 2041 | Y3: 2042 | Z3: 2043 | AA3: 2044 | AB3: 2045 | AC3: 2046 | AD3: 2047 | AE3: 2048 | AF3: 2049 | AG3: 2050
A4: ='Capital Annualized Costs Base'!A22 -> Total Capital Investments (Million USD) | B4: ='Capital Annualized Costs Base'!B22 -> 0 | C4: ='Capital Annualized Costs Base'!C22 -> 4747.952 | D4: ='Capital Annualized Costs Base'!D22 -> 10006.783 | E4: ='Capital Annualized Costs Base'!E22 -> 2531.4872 | F4: ='Capital Annualized Costs Base'!F22 -> 1576.1906 | G4: ='Capital Annualized Costs Base'!G22 -> 2362.6025 | H4: ='Capital Annualized Costs Base'!H22 -> 1897.1058 | ... AG4: ='Capital Annualized Costs Base'!AG22 -> 10786.751
A5: ='Capital Annualized Costs Base'!A43 -> Total Annualized Investments (Million USD) | B5: ='Capital Annualized Costs Base'!B43 -> 0 | C5: ='Capital Annualized Costs Base'!C43 -> 234.83856 | D5: ='Capital Annualized Costs Base'!D43 -> 756.46065 | E5: ='Capital Annualized Costs Base'!E43 -> 918.84101 | F5: ='Capital Annualized Costs Base'!F43 -> 1006.569 | G5: ='Capital Annualized Costs Base'!G43 -> 1158.3122 | H5: ='Capital Annualized Costs Base'!H43 -> 1276.2681 | ... AG5: ='Capital Annualized Costs Base'!AG43 -> 10340.388

Sheet Capital Annualized Costs Base
A1: Base Scenario
A3: Capital Investments (M.USD) | C3: 2020 | D3: 2021 | E3: 2022 | F3: 2023 | G3: 2024 | H3: 2025 | I3: 2026 | J3: 2027 | K3: 2028 | L3: 2029 | M3: 2030 | N3: 2031 | O3: 2032 | P3: 2033 | Q3: 2034 | R3: 2035 | S3: 2036 | T3: 2037 | U3: 2038 | V3: 2039 | W3: 2040 | X3: 2041 | Y3: 2042 | Z3: 2043 | AA3: 2044 | AB3: 2045 | AC3: 2046 | AD3: 2047 | AE3: 2048 | AF3: 2049 | AG3: 2050
A4: PHL_POW_CHP_BIOM_OLD | C4: =SUMIFS(Capital_Investments!C$2:C$10000,Capital_Investments!$B$2:$B$10000,$A4) -> 0 | D4: =SUMIFS(Capital_Investments!D$2:D$10000,Capital_Investments!$B$2:$B$10000,$A4) -> 0 | E4: =SUMIFS(Capital_Investments!E$2:E$10000,Capital_Investments!$B$2:$B$10000,$A4) -> 369 | F4: =SUMIFS(Capital_Investments!F$2:F$10000,Capital_Investments!$B$2:$B$10000,$A4) -> 27 | G4: =SUMIFS(Capital_Investments!G$2:G$10000,Capital_Investments!$B$2:$B$10000,$A4) -> 44.55 | H4: =SUMIFS(Capital_Investments!H$2:H$10000,Capital_Investments!$B$2:$B$10000,$A4) -> 0 | I4: =SUMIFS(Capital_Investments!I$2:I$10000,Capital_Investments!$B$2:$B$10000,$A4) -> 0 | J4: =SUMIFS(Capital_Investments!J$2:J$10000,Capital_Investments!$B$2:$B$10000,$A4) -> 0 | ... AG4: =SUMIFS(Capital_Investments!AG$2:AG$10000,Capital_Investments!$B$2:$B$10000,$A4) -> 0
A5: PHL_POW_CHP_COAL_OLD | C5: =SUMIFS(Capital_Investments!C$2:C$10000,Capital_Investments!$B$2:$B$10000,$A5) -> 0 | D5: =SUMIFS(Capital_Investments!D$2:D$10000,Capital_Investments!$B$2:$B$10000,$A5) -> 0 | E5: =SUMIFS(Capital_Investments!E$2:E$10000,Capital_Investments!$B$2:$B$10000,$A5) -> 0 | F5: =SUMIFS(Capital_Investments!F$2:F$10000,Capital_Investments!$B$2:$B$10000,$A5) -> 0 | G5: =SUMIFS(Capital_Investments!G$2:G$10000,Capital_Investments!$B$2:$B$10000,$A5) -> 0 | H5: =SUMIFS(Capital_Investments!H$2:H$10000,Capital_Investments!$B$2:$B$10000,$A5) -> 0 | I5: =SUMIFS(Capital_Investments!I$2:I$10000,Capital_Investments!$B$2:$B$10000,$A5) -> 0 | J5: =SUMIFS(Capital_Investments!J$2:J$10000,Capital_Investments!$B$2:$B$10000,$A5) -> 0 | ... AG5: =SUMIFS(Capital_Investments!AG$2:AG$10000,Capital_Investments!$B$2:$B$10000,$A5) -> 0
A6: PHL_POW_GEO_OLD | C6: =SUMIFS(Capital_Investments!C$2:C$10000,Capital_Investments!$B$2:$B$10000,$A6) -> 0 | D6: =SUMIFS(Capital_Investments!D$2:D$10000,Capital_Investments!$B$2:$B$10000,$A6) -> 0 | E6: =SUMIFS(Capital_Investments!E$2:E$10000,Capital_Investments!$B$2:$B$10000,$A6) -> 16.28 | F6: =SUMIFS(Capital_Investments!F$2:F$10000,Capital_Investments!$B$2:$B$10000,$A6) -> 1236.7766 | G6: =SUMIFS(Capital_Investments!G$2:G$10000,Capital_Investments!$B$2:$B$10000,$A6) -> 29.5789 | H6: =SUMIFS(Capital_Investments!H$2:H$10000,Capital_Investments!$B$2:$B$10000,$A6) -> 157.08 | I6: =SUMIFS(Capital_Investments!I$2:I$10000,Capital_Investments!$B$2:$B$10000,$A6) -> 3668.8451 | J6: =SUMIFS(Capital_Investments!J$2:J$10000,Capital_Investments!$B$2:$B$10000,$A6) -> 3695.1112 | ... AG6: =SUMIFS(Capital_Investments!AG$2:AG$10000,Capital_Investments!$B$2:$B$10000,$A6) -> 20.0948
A7: PHL_POW_PP_BIOM_CCS | C7: =SUMIFS(Capital_Investments!C$2:C$10000,Capital_Investments!$B$2:$B$10000,$A7) -> 0 | D7: =SUMIFS(Capital_Investments!D$2:D$10000,Capital_Investments!$B$2:$B$10000,$A7) -> 0 | E7: =SUMIFS(Capital_Investments!E$2:E$10000,Capital_Investments!$B$2:$B$10000,$A7) -> 0 | F7: =SUMIFS(Capital_Investments!F$2:F$10000,Capital_Investments!$B$2:$B$10000,$A7) -> 0 | G7: =SUMIFS(Capital_Investments!G$2:G$10000,Capital_Investments!$B$2:$B$10000,$A7) -> 0 | H7: =SUMIFS(Capital_Investments!H$2:H$10000,Capital_Investments!$B$2:$B$10000,$A7) -> 0 | I7: =SUMIFS(Capital_Investments!I$2:I$10000,Capital_Investments!$B$2:$B$10000,$A7) -> 0 | J7: =SUMIFS(Capital_Investments!J$2:J$10000,Capital_Investments!$B$2:$B$10000,$A7) -> 0 | ... AG7: =SUMIFS(Capital_Investments!AG$2:AG$10000,Capital_Investments!$B$2:$B$10000,$A7) -> 0
A8: PHL_POW_PP_COAL | C8: =SUMIFS(Capital_Investments!C$2:C$10000,Capital_Investments!$B$2:$B$10000,$A8) -> 0 | D8: =SUMIFS(Capital_Investments!D$2:D$10000,Capital_Investments!$B$2:$B$10000,$A8) -> 1595 | E8: =SUMIFS(Capital_Investments!E$2:E$10000,Capital_Investments!$B$2:$B$10000,$A8) -> 1692.68 | F8: =SUMIFS(Capital_Investments!F$2:F$10000,Capital_Investments!$B$2:$B$10000,$A8) -> 0 | G8: =SUMIFS(Capital_Investments!G$2:G$10000,Capital_Investments!$B$2:$B$10000,$A8) -> 1320 | H8: =SUMIFS(Capital_Investments!H$2:H$10000,Capital_Investments!$B$2:$B$10000,$A8) -> 0 | I8: =SUMIFS(Capital_Investments!I$2:I$10000,Capital_Investments!$B$2:$B$10000,$A8) -> 0 | J8: =SUMIFS(Capital_Investments!J$2:J$10000,Capital_Investments!$B$2:$B$10000,$A8) -> 0 | ... AG8: =SUMIFS(Capital_Investments!AG$2:AG$10000,Capital_Investments!$B$2:$B$10000,$A8) -> 0
A9: PHL_POW_PP_COAL_CCS | C9: =SUMIFS(Capital_Investments!C$2:C$10000,Capital_Investments!$B$2:$B$10000,$A9) -> 0 | D9: =SUMIFS(Capital_Investments!D$2:D$10000,Capital_Investments!$B$2:$B$10000,$A9) -> 0 | E9: =SUMIFS(Capital_Investments!E$2:E$10000,Capital_Investments!$B$2:$B$10000,$A9) -> 0 | F9: =SUMIFS(Capital_Investments!F$2:F$10000,Capital_Investments!$B$2:$B$10000,$A9) -> 0 | G9: =SUMIFS(Capital_Investments!G$2:G$10000,Capital_Investments!$B$2:$B$10000,$A9) -> 0 | H9: =SUMIFS(Capital_Investments!H$2:H$10000,Capital_Investments!$B$2:$B$10000,$A9) -> 0 | I9: =SUMIFS(Capital_Investments!I$2:I$10000,Capital_Investments!$B$2:$B$10000,$A9) -> 0 | J9: =SUMIFS(Capital_Investments!J$2:J$10000,Capital_Investments!$B$2:$B$10000,$A9) -> 0 | ... AG9: =SUMIFS(Capital_Investments!AG$2:AG$10000,Capital_Investments!$B$2:$B$10000,$A9) -> 0
A10: PHL_POW_PP_H2 | C10: =SUMIFS(Capital_Investments!C$2:C$10000,Capital_Investments!$B$2:$B$10000,$A10) -> 0 | D10: =SUMIFS(Capital_Investments!D$2:D$10000,Capital_Investments!$B$2:$B$10000,$A10) -> 0 | E10: =SUMIFS(Capital_Investments!E$2:E$10000,Capital_Investments!$B$2:$B$10000,$A10) -> 0 | F10: =SUMIFS(Capital_Investments!F$2:F$10000,Capital_Investments!$B$2:$B$10000,$A10) -> 0 | G10: =SUMIFS(Capital_Investments!G$2:G$10000,Capital_Investments!$B$2:$B$10000,$A10) -> 0 | H10: =SUMIFS(Capital_Investments!H$2:H$10000,Capital_Investments!$B$2:$B$10000,$A10) -> 0 | I10: =SUMIFS(Capital_Investments!I$2:I$10000,Capital_Investments!$B$2:$B$10000,$A10) -> 0 | J10: =SUMIFS(Capital_Investments!J$2:J$10000,Capital_Investments!$B$2:$B$10000,$A10) -> 0 | ... AG10: =SUMIFS(Capital_Investments!AG$2:AG$10000,Capital_Investments!$B$2:$B$10000,$A10) -> 0
A11: PHL_POW_PP_HY_LA | C11: =SUMIFS(Capital_Investments!C$2:C$10000,Capital_Investments!$B$2:$B$10000,$A11) -> 4389.9544 | D11: =SUMIFS(Capital_Investments!D$2:D$10000,Capital_Investments!$B$2:$B$10000,$A11) -> 7663.7159 | E11: =SUMIFS(Capital_Investments!E$2:E$10000,Capital_Investments!$B$2:$B$10000,$A11) -> 47.7 | F11: =SUMIFS(Capital_Investments!F$2:F$10000,Capital_Investments!$B$2:$B$10000,$A11) -> 140.4 | G11: =SUMIFS(Capital_Investments!G$2:G$10000,Capital_Investments!$B$2:$B$10000,$A11) -> 105.6 | H11: =SUMIFS(Capital_Investments!H$2:H$10000,Capital_Investments!$B$2:$B$10000,$A11) -> 0 | I11: =SUMIFS(Capital_Investments!I$2:I$10000,Capital_Investments!$B$2:$B$10000,$A11) -> 0 | J11: =SUMIFS(Capital_Investments!J$2:J$10000,Capital_Investments!$B$2:$B$10000,$A11) -> 0 | ... AG11: =SUMIFS(Capital_Investments!AG$2:AG$10000,Capital_Investments!$B$2:$B$10000,$A11) -> 0
A12: PHL_POW_PP_NGCC | C12: =SUMIFS(Capital_Investments!C$2:C$10000,Capital_Investments!$B$2:$B$10000,$A12) -> 0 | D12: =SUMIFS(Capital_Investments!D$2:D$10000,Capital_Investments!$B$2:$B$10000,$A12) -> 0 | E12: =SUMIFS(Capital_Investments!E$2:E$10000,Capital_Investments!$B$2:$B$10000,$A12) -> 0 | F12: =SUMIFS(Capital_Investments!F$2:F$10000,Capital_Investments!$B$2:$B$10000,$A12) -> 0 | G12: =SUMIFS(Capital_Investments!G$2:G$10000,Capital_Investments!$B$2:$B$10000,$A12) -> 0 | H12: =SUMIFS(Capital_Investments!H$2:H$10000,Capital_Investments!$B$2:$B$10000,$A12) -> 1056 | I12: =SUMIFS(Capital_Investments!I$2:I$10000,Capital_Investments!$B$2:$B$10000,$A12) -> 0 | J12: =SUMIFS(Capital_Investments!J$2:J$10000,Capital_Investments!$B$2:$B$10000,$A12) -> 0 | ... AG12: =SUMIFS(Capital_Investments!AG$2:AG$10000,Capital_Investments!$B$2:$B$10000,$A12) -> 4144.2266
A13: PHL_POW_PP_NGCC_CCS | C13: =SUMIFS(Capital_Investments!C$2:C$10000,Capital_Investments!$B$2:$B$10000,$A13) -> 0 | D13: =SUMIFS(Capital_Investments!D$2:D$10000,Capital_Investments!$B$2:$B$10000,$A13) -> 0 | E13: =SUMIFS(Capital_Investments!E$2:E$10000,Capital_Investments!$B$2:$B$10000,$A13) -> 0 | F13: =SUMIFS(Capital_Investments!F$2:F$10000,Capital_Investments!$B$2:$B$10000,$A13) -> 0 | G13: =SUMIFS(Capital_Investments!G$2:G$10000,Capital_Investments!$B$2:$B$10000,$A13) -> 0 | H13: =SUMIFS(Capital_Investments!H$2:H$10000,Capital_Investments!$B$2:$B$10000,$A13) -> 0 | I13: =SUMIFS(Capital_Investments!I$2:I$10000,Capital_Investments!$B$2:$B$10000,$A13) -> 0 | J13: =SUMIFS(Capital_Investments!J$2:J$10000,Capital_Investments!$B$2:$B$10000,$A13) -> 0 | ... AG13: =SUMIFS(Capital_Investments!AG$2:AG$10000,Capital_Investments!$B$2:$B$10000,$A13) -> 0
A14: PHL_POW_PP_NU | C14: =SUMIFS(Capital_Investments!C$2:C$10000,Capital_Investments!$B$2:$B$10000,$A14) -> 0 | D14: =SUMIFS(Capital_Investments!D$2:D$10000,Capital_Investments!$B$2:$B$10000,$A14) -> 0 | E14: =SUMIFS(Capital_Investments!E$2:E$10000,Capital_Investments!$B$2:$B$10000,$A14) -> 0 | F14: =SUMIFS(Capital_Investments!F$2:F$10000,Capital_Investments!$B$2:$B$10000,$A14) -> 0 | G14: =SUMIFS(Capital_Investments!G$2:G$10000,Capital_Investments!$B$2:$B$10000,$A14) -> 0 | H14: =SUMIFS(Capital_Investments!H$2:H$10000,Capital_Investments!$B$2:$B$10000,$A14) -> 0 | I14: =SUMIFS(Capital_Investments!I$2:I$10000,Capital_Investments!$B$2:$B$10000,$A14) -> 0 | J14: =SUMIFS(Capital_Investments!J$2:J$10000,Capital_Investments!$B$2:$B$10000,$A14) -> 0 | ... AG14: =SUMIFS(Capital_Investments!AG$2:AG$10000,Capital_Investments!$B$2:$B$10000,$A14) -> 0
A15: PHL_POW_PP_NUSMR | C15: =SUMIFS(Capital_Investments!C$2:C$10000,Capital_Investments!$B$2:$B$10000,$A15) -> 0 | D15: =SUMIFS(Capital_Investments!D$2:D$10000,Capital_Investments!$B$2:$B$10000,$A15) -> 0 | E15: =SUMIFS(Capital_Investments!E$2:E$10000,Capital_Investments!$B$2:$B$10000,$A15) -> 0 | F15: =SUMIFS(Capital_Investments!F$2:F$10000,Capital_Investments!$B$2:$B$10000,$A15) -> 0 | G15: =SUMIFS(Capital_Investments!G$2:G$10000,Capital_Investments!$B$2:$B$10000,$A15) -> 0 | H15: =SUMIFS(Capital_Investments!H$2:H$10000,Capital_Investments!$B$2:$B$10000,$A15) -> 0 | I15: =SUMIFS(Capital_Investments!I$2:I$10000,Capital_Investments!$B$2:$B$10000,$A15) -> 0 | J15: =SUMIFS(Capital_Investments!J$2:J$10000,Capital_Investments!$B$2:$B$10000,$A15) -> 0 | ... AG15: =SUMIFS(Capital_Investments!AG$2:AG$10000,Capital_Investments!$B$2:$B$10000,$A15) -> 0
... A21: PHL_POW_TD | C21: =SUMIFS(Capital_Investments!C$2:C$10000,Capital_Investments!$B$2:$B$10000,$A21) -> 0 | D21: =SUMIFS(Capital_Investments!D$2:D$10000,Capital_Investments!$B$2:$B$10000,$A21) -> 0 | E21: =SUMIFS(Capital_Investments!E$2:E$10000,Capital_Investments!$B$2:$B$10000,$A21) -> 0 | F21: =SUMIFS(Capital_Investments!F$2:F$10000,Capital_Investments!$B$2:$B$10000,$A21) -> 0 | G21: =SUMIFS(Capital_Investments!G$2:G$10000,Capital_Investments!$B$2:$B$10000,$A21) -> 0 | H21: =SUMIFS(Capital_Investments!H$2:H$10000,Capital_Investments!$B$2:$B$10000,$A21) -> 459.6972 | I21: =SUMIFS(Capital_Investments!I$2:I$10000,Capital_Investments!$B$2:$B$10000,$A21) -> 1316.7722 | J21: =SUMIFS(Capital_Investments!J$2:J$10000,Capital_Investments!$B$2:$B$10000,$A21) -> 1316.7722 | ... AG21: =SUMIFS(Capital_Investments!AG$2:AG$10000,Capital_Investments!$B$2:$B$10000,$A21) -> 3100.4506
A22: Total Capital Investments (Million USD) | C22: =SUM(C4:C21) -> 4747.952 | D22: =SUM(D4:D21) -> 10006.783 | E22: =SUM(E4:E21) -> 2531.4872 | F22: =SUM(F4:F21) -> 1576.1906 | G22: =SUM(G4:G21) -> 2362.6025 | H22: =SUM(H4:H21) -> 1897.1058 | I22: =SUM(I4:I21) -> 4985.6173 | J22: =SUM(J4:J21) -> 5011.8834 | ... AG22: =SUM(AG4:AG21) -> 10786.751
A24: Annualized Investment Cost (M.USD) | C24: 2020 | D24: 2021 | E24: 2022 | F24: 2023 | G24: 2024 | H24: 2025 | I24: 2026 | J24: 2027 | K24: 2028 | L24: 2029 | M24: 2030 | N24: 2031 | O24: 2032 | P24: 2033 | Q24: 2034 | R24: 2035 | S24: 2036 | T24: 2037 | U24: 2038 | V24: 2039 | W24: 2040 | X24: 2041 | Y24: 2042 | Z24: 2043 | AA24: 2044 | AB24: 2045 | AC24: 2046 | AD24: 2047 | AE24: 2048 | AF24: 2049 | AG24: 2050
A25: PHL_POW_CHP_BIOM_OLD | C25: =SUMIFS(Annualized_Investments!C$2:C$9989,Annualized_Investments!$B$2:$B$9989,$A25) -> 0 | D25: =SUMIFS(Annualized_Investments!D$2:D$9989,Annualized_Investments!$B$2:$B$9989,$A25) -> 0 | E25: =SUMIFS(Annualized_Investments!E$2:E$9989,Annualized_Investments!$B$2:$B$9989,$A25) -> 20.480611 | F25: =SUMIFS(Annualized_Investments!F$2:F$9989,Annualized_Investments!$B$2:$B$9989,$A25) -> 21.979192 | G25: =SUMIFS(Annualized_Investments!G$2:G$9989,Annualized_Investments!$B$2:$B$9989,$A25) -> 24.451851 | H25: =SUMIFS(Annualized_Investments!H$2:H$9989,Annualized_Investments!$B$2:$B$9989,$A25) -> 24.451851 | I25: =SUMIFS(Annualized_Investments!I$2:I$9989,Annualized_Investments!$B$2:$B$9989,$A25) -> 24.451851 | J25: =SUMIFS(Annualized_Investments!J$2:J$9989,Annualized_Investments!$B$2:$B$9989,$A25) -> 24.451851 | ... AG25: =SUMIFS(Annualized_Investments!AG$2:AG$9989,Annualized_Investments!$B$2:$B$9989,$A25) -> 24.451851
A26: PHL_POW_CHP_COAL_OLD | C26: =SUMIFS(Annualized_Investments!C$2:C$9989,Annualized_Investments!$B$2:$B$9989,$A26) -> 0 | D26: =SUMIFS(Annualized_Investments!D$2:D$9989,Annualized_Investments!$B$2:$B$9989,$A26) -> 0 | E26: =SUMIFS(Annualized_Investments!E$2:E$9989,Annualized_Investments!$B$2:$B$9989,$A26) -> 0 | F26: =SUMIFS(Annualized_Investments!F$2:F$9989,Annualized_Investments!$B$2:$B$9989,$A26) -> 0 | G26: =SUMIFS(Annualized_Investments!G$2:G$9989,Annualized_Investments!$B$2:$B$9989,$A26) -> 0 | H26: =SUMIFS(Annualized_Investments!H$2:H$9989,Annualized_Investments!$B$2:$B$9989,$A26) -> 0 | I26: =SUMIFS(Annualized_Investments!I$2:I$9989,Annualized_Investments!$B$2:$B$9989,$A26) -> 0 | J26: =SUMIFS(Annualized_Investments!J$2:J$9989,Annualized_Investments!$B$2:$B$9989,$A26) -> 0 | ... AG26: =SUMIFS(Annualized_Investments!AG$2:AG$9989,Annualized_Investments!$B$2:$B$9989,$A26) -> 0
A27: PHL_POW_GEO_OLD | C27: =SUMIFS(Annualized_Investments!C$2:C$9989,Annualized_Investments!$B$2:$B$9989,$A27) -> 0 | D27: =SUMIFS(Annualized_Investments!D$2:D$9989,Annualized_Investments!$B$2:$B$9989,$A27) -> 0 | E27: =SUMIFS(Annualized_Investments!E$2:E$9989,Annualized_Investments!$B$2:$B$9989,$A27) -> 0.90358901 | F27: =SUMIFS(Annualized_Investments!F$2:F$9989,Annualized_Investments!$B$2:$B$9989,$A27) -> 69.548414 | G27: =SUMIFS(Annualized_Investments!G$2:G$9989,Annualized_Investments!$B$2:$B$9989,$A27) -> 71.190132 | H27: =SUMIFS(Annualized_Investments!H$2:H$9989,Annualized_Investments!$B$2:$B$9989,$A27) -> 79.908545 | I27: =SUMIFS(Annualized_Investments!I$2:I$9989,Annualized_Investments!$B$2:$B$9989,$A27) -> 283.54049 | J27: =SUMIFS(Annualized_Investments!J$2:J$9989,Annualized_Investments!$B$2:$B$9989,$A27) -> 488.63029 | ... AG27: =SUMIFS(Annualized_Investments!AG$2:AG$9989,Annualized_Investments!$B$2:$B$9989,$A27) -> 956.97402
A28: PHL_POW_PP_BIOM_CCS | C28: =SUMIFS(Annualized_Investments!C$2:C$9989,Annualized_Investments!$B$2:$B$9989,$A28) -> 0 | D28: =SUMIFS(Annualized_Investments!D$2:D$9989,Annualized_Investments!$B$2:$B$9989,$A28) -> 0 | E28: =SUMIFS(Annualized_Investments!E$2:E$9989,Annualized_Investments!$B$2:$B$9989,$A28) -> 0 | F28: =SUMIFS(Annualized_Investments!F$2:F$9989,Annualized_Investments!$B$2:$B$9989,$A28) -> 0 | G28: =SUMIFS(Annualized_Investments!G$2:G$9989,Annualized_Investments!$B$2:$B$9989,$A28) -> 0 | H28: =SUMIFS(Annualized_Investments!H$2:H$9989,Annualized_Investments!$B$2:$B$9989,$A28) -> 0 | I28: =SUMIFS(Annualized_Investments!I$2:I$9989,Annualized_Investments!$B$2:$B$9989,$A28) -> 0 | J28: =SUMIFS(Annualized_Investments!J$2:J$9989,Annualized_Investments!$B$2:$B$9989,$A28) -> 0 | ... AG28: =SUMIFS(Annualized_Investments!AG$2:AG$9989,Annualized_Investments!$B$2:$B$9989,$A28) -> 0
A29: PHL_POW_PP_COAL | C29: =SUMIFS(Annualized_Investments!C$2:C$9989,Annualized_Investments!$B$2:$B$9989,$A29) -> 0 | D29: =SUMIFS(Annualized_Investments!D$2:D$9989,Annualized_Investments!$B$2:$B$9989,$A29) -> 107.78016 | E29: =SUMIFS(Annualized_Investments!E$2:E$9989,Annualized_Investments!$B$2:$B$9989,$A29) -> 222.16093 | F29: =SUMIFS(Annualized_Investments!F$2:F$9989,Annualized_Investments!$B$2:$B$9989,$A29) -> 222.16093 | G29: =SUMIFS(Annualized_Investments!G$2:G$9989,Annualized_Investments!$B$2:$B$9989,$A29) -> 311.3583 | H29: =SUMIFS(Annualized_Investments!H$2:H$9989,Annualized_Investments!$B$2:$B$9989,$A29) -> 311.3583 | I29: =SUMIFS(Annualized_Investments!I$2:I$9989,Annualized_Investments!$B$2:$B$9989,$A29) -> 311.3583 | J29: =SUMIFS(Annualized_Investments!J$2:J$9989,Annualized_Investments!$B$2:$B$9989,$A29) -> 311.3583 | ... AG29: =SUMIFS(Annualized_Investments!AG$2:AG$9989,Annualized_Investments!$B$2:$B$9989,$A29) -> 3898.5044
A30: PHL_POW_PP_COAL_CCS | C30: =SUMIFS(Annualized_Investments!C$2:C$9989,Annualized_Investments!$B$2:$B$9989,$A30) -> 0 | D30: =SUMIFS(Annualized_Investments!D$2:D$9989,Annualized_Investments!$B$2:$B$9989,$A30) -> 0 | E30: =SUMIFS(Annualized_Investments!E$2:E$9989,Annualized_Investments!$B$2:$B$9989,$A30) -> 0 | F30: =SUMIFS(Annualized_Investments!F$2:F$9989,Annualized_Investments!$B$2:$B$9989,$A30) -> 0 | G30: =SUMIFS(Annualized_Investments!G$2:G$9989,Annualized_Investments!$B$2:$B$9989,$A30) -> 0 | H30: =SUMIFS(Annualized_Investments!H$2:H$9989,Annualized_Investments!$B$2:$B$9989,$A30) -> 0 | I30: =SUMIFS(Annualized_Investments!I$2:I$9989,Annualized_Investments!$B$2:$B$9989,$A30) -> 0 | J30: =SUMIFS(Annualized_Investments!J$2:J$9989,Annualized_Investments!$B$2:$B$9989,$A30) -> 0 | ... AG30: =SUMIFS(Annualized_Investments!AG$2:AG$9989,Annualized_Investments!$B$2:$B$9989,$A30) -> 0
A31: PHL_POW_PP_H2 | C31: =SUMIFS(Annualized_Investments!C$2:C$9989,Annualized_Investments!$B$2:$B$9989,$A31) -> 0 | D31: =SUMIFS(Annualized_Investments!D$2:D$9989,Annualized_Investments!$B$2:$B$9989,$A31) -> 0 | E31: =SUMIFS(Annualized_Investments!E$2:E$9989,Annualized_Investments!$B$2:$B$9989,$A31) -> 0 | F31: =SUMIFS(Annualized_Investments!F$2:F$9989,Annualized_Investments!$B$2:$B$9989,$A31) -> 0 | G31: =SUMIFS(Annualized_Investments!G$2:G$9989,Annualized_Investments!$B$2:$B$9989,$A31) -> 0 | H31: =SUMIFS(Annualized_Investments!H$2:H$9989,Annualized_Investments!$B$2:$B$9989,$A31) -> 0 | I31: =SUMIFS(Annualized_Investments!I$2:I$9989,Annualized_Investments!$B$2:$B$9989,$A31) -> 0 | J31: =SUMIFS(Annualized_Investments!J$2:J$9989,Annualized_Investments!$B$2:$B$9989,$A31) -> 0 | ... AG31: =SUMIFS(Annualized_Investments!AG$2:AG$9989,Annualized_Investments!$B$2:$B$9989,$A31) -> 0
A32: PHL_POW_PP_HY_LA | C32: =SUMIFS(Annualized_Investments!C$2:C$9989,Annualized_Investments!$B$2:$B$9989,$A32) -> 210.64731 | D32: =SUMIFS(Annualized_Investments!D$2:D$9989,Annualized_Investments!$B$2:$B$9989,$A32) -> 578.3826 | E32: =SUMIFS(Annualized_Investments!E$2:E$9989,Annualized_Investments!$B$2:$B$9989,$A32) -> 580.67144 | F32: =SUMIFS(Annualized_Investments!F$2:F$9989,Annualized_Investments!$B$2:$B$9989,$A32) -> 587.40838 | G32: =SUMIFS(Annualized_Investments!G$2:G$9989,Annualized_Investments!$B$2:$B$9989,$A32) -> 592.47549 | H32: =SUMIFS(Annualized_Investments!H$2:H$9989,Annualized_Investments!$B$2:$B$9989,$A32) -> 592.47549 | I32: =SUMIFS(Annualized_Investments!I$2:I$9989,Annualized_Investments!$B$2:$B$9989,$A32) -> 592.47549 | J32: =SUMIFS(Annualized_Investments!J$2:J$9989,Annualized_Investments!$B$2:$B$9989,$A32) -> 592.47549 | ... AG32: =SUMIFS(Annualized_Investments!AG$2:AG$9989,Annualized_Investments!$B$2:$B$9989,$A32) -> 592.47549
A33: PHL_POW_PP_NGCC | C33: =SUMIFS(Annualized_Investments!C$2:C$9989,Annualized_Investments!$B$2:$B$9989,$A33) -> 0 | D33: =SUMIFS(Annualized_Investments!D$2:D$9989,Annualized_Investments!$B$2:$B$9989,$A33) -> 0 | E33: =SUMIFS(Annualized_Investments!E$2:E$9989,Annualized_Investments!$B$2:$B$9989,$A33) -> 0 | F33: =SUMIFS(Annualized_Investments!F$2:F$9989,Annualized_Investments!$B$2:$B$9989,$A33) -> 0 | G33: =SUMIFS(Annualized_Investments!G$2:G$9989,Annualized_Investments!$B$2:$B$9989,$A33) -> 0 | H33: =SUMIFS(Annualized_Investments!H$2:H$9989,Annualized_Investments!$B$2:$B$9989,$A33) -> 71.3579 | I33: =SUMIFS(Annualized_Investments!I$2:I$9989,Annualized_Investments!$B$2:$B$9989,$A33) -> 71.3579 | J33: =SUMIFS(Annualized_Investments!J$2:J$9989,Annualized_Investments!$B$2:$B$9989,$A33) -> 71.3579 | ... AG33: =SUMIFS(Annualized_Investments!AG$2:AG$9989,Annualized_Investments!$B$2:$B$9989,$A33) -> 832.4559
A34: PHL_POW_PP_NGCC_CCS | C34: =SUMIFS(Annualized_Investments!C$2:C$9989,Annualized_Investments!$B$2:$B$9989,$A34) -> 0 | D34: =SUMIFS(Annualized_Investments!D$2:D$9989,Annualized_Investments!$B$2:$B$9989,$A34) -> 0 | E34: =SUMIFS(Annualized_Investments!E$2:E$9989,Annualized_Investments!$B$2:$B$9989,$A34) -> 0 | F34: =SUMIFS(Annualized_Investments!F$2:F$9989,Annualized_Investments!$B$2:$B$9989,$A34) -> 0 | G34: =SUMIFS(Annualized_Investments!G$2:G$9989,Annualized_Investments!$B$2:$B$9989,$A34) -> 0 | H34: =SUMIFS(Annualized_Investments!H$2:H$9989,Annualized_Investments!$B$2:$B$9989,$A34) -> 0 | I34: =SUMIFS(Annualized_Investments!I$2:I$9989,Annualized_Investments!$B$2:$B$9989,$A34) -> 0 | J34: =SUMIFS(Annualized_Investments!J$2:J$9989,Annualized_Investments!$B$2:$B$9989,$A34) -> 0 | ... AG34: =SUMIFS(Annualized_Investments!AG$2:AG$9989,Annualized_Investments!$B$2:$B$9989,$A34) -> 0
A35: PHL_POW_PP_NU | C35: =SUMIFS(Annualized_Investments!C$2:C$9989,Annualized_Investments!$B$2:$B$9989,$A35) -> 0 | D35: =SUMIFS(Annualized_Investments!D$2:D$9989,Annualized_Investments!$B$2:$B$9989,$A35) -> 0 | E35: =SUMIFS(Annualized_Investments!E$2:E$9989,Annualized_Investments!$B$2:$B$9989,$A35) -> 0 | F35: =SUMIFS(Annualized_Investments!F$2:F$9989,Annualized_Investments!$B$2:$B$9989,$A35) -> 0 | G35: =SUMIFS(Annualized_Investments!G$2:G$9989,Annualized_Investments!$B$2:$B$9989,$A35) -> 0 | H35: =SUMIFS(Annualized_Investments!H$2:H$9989,Annualized_Investments!$B$2:$B$9989,$A35) -> 0 | I35: =SUMIFS(Annualized_Investments!I$2:I$9989,Annualized_Investments!$B$2:$B$9989,$A35) -> 0 | J35: =SUMIFS(Annualized_Investments!J$2:J$9989,Annualized_Investments!$B$2:$B$9989,$A35) -> 0 | ... AG35: =SUMIFS(Annualized_Investments!AG$2:AG$9989,Annualized_Investments!$B$2:$B$9989,$A35) -> 0
A36: PHL_POW_PP_NUSMR | C36: =SUMIFS(Annualized_Investments!C$2:C$9989,Annualized_Investments!$B$2:$B$9989,$A36) -> 0 | D36: =SUMIFS(Annualized_Investments!D$2:D$9989,Annualized_Investments!$B$2:$B$9989,$A36) -> 0 | E36: =SUMIFS(Annualized_Investments!E$2:E$9989,Annualized_Investments!$B$2:$B$9989,$A36) -> 0 | F36: =SUMIFS(Annualized_Investments!F$2:F$9989,Annualized_Investments!$B$2:$B$9989,$A36) -> 0 | G36: =SUMIFS(Annualized_Investments!G$2:G$9989,Annualized_Investments!$B$2:$B$9989,$A36) -> 0 | H36: =SUMIFS(Annualized_Investments!H$2:H$9989,Annualized_Investments!$B$2:$B$9989,$A36) -> 0 | I36: =SUMIFS(Annualized_Investments!I$2:I$9989,Annualized_Investments!$B$2:$B$9989,$A36) -> 0 | J36: =SUMIFS(Annualized_Investments!J$2:J$9989,Annualized_Investments!$B$2:$B$9989,$A36) -> 0 | ... AG36: =SUMIFS(Annualized_Investments!AG$2:AG$9989,Annualized_Investments!$B$2:$B$9989,$A36) -> 0
... A42: PHL_POW_TD | C42: =SUMIFS(Annualized_Investments!C$2:C$9989,Annualized_Investments!$B$2:$B$9989,$A42) -> 0 | D42: =SUMIFS(Annualized_Investments!D$2:D$9989,Annualized_Investments!$B$2:$B$9989,$A42) -> 0 | E42: =SUMIFS(Annualized_Investments!E$2:E$9989,Annualized_Investments!$B$2:$B$9989,$A42) -> 0 | F42: =SUMIFS(Annualized_Investments!F$2:F$9989,Annualized_Investments!$B$2:$B$9989,$A42) -> 0 | G42: =SUMIFS(Annualized_Investments!G$2:G$9989,Annualized_Investments!$B$2:$B$9989,$A42) -> 0 | H42: =SUMIFS(Annualized_Investments!H$2:H$9989,Annualized_Investments!$B$2:$B$9989,$A42) -> 23.98163 | I42: =SUMIFS(Annualized_Investments!I$2:I$9989,Annualized_Investments!$B$2:$B$9989,$A42) -> 92.675423 | J42: =SUMIFS(Annualized_Investments!J$2:J$9989,Annualized_Investments!$B$2:$B$9989,$A42) -> 161.36922 | ... AG42: =SUMIFS(Annualized_Investments!AG$2:AG$9989,Annualized_Investments!$B$2:$B$9989,$A42) -> 2425.2209
A43: Total Annualized Investments (Million USD) | C43: =SUM(C25:C42) -> 234.83856 | D43: =SUM(D25:D42) -> 756.46065 | E43: =SUM(E25:E42) -> 918.84101 | F43: =SUM(F25:F42) -> 1006.569 | G43: =SUM(G25:G42) -> 1158.3122 | H43: =SUM(H25:H42) -> 1276.2681 | I43: =SUM(I25:I42) -> 1548.5939 | J43: =SUM(J25:J42) -> 1822.3775 | ... AG43: =SUM(AG25:AG42) -> 10340.388

Sheet Emissions_Base
A1: Base Scenario
A2: Annual Technology Emission by Mode (Mton)
A3: Emission / Tehcnology | B3: 2020 | C3: 2021 | D3: 2022 | E3: 2023 | F3: 2024 | G3: 2025 | H3: 2026 | I3: 2027 | J3: 2028 | K3: 2029 | L3: 2030 | M3: 2031 | N3: 2032 | O3: 2033 | P3: 2034 | Q3: 2035 | R3: 2036 | S3: 2037 | T3: 2038 | U3: 2039 | V3: 2040 | W3: 2041 | X3: 2042 | Y3: 2043 | Z3: 2044 | AA3: 2045 | AB3: 2046 | AC3: 2047 | AD3: 2048 | AE3: 2049 | AF3: 2050 | AG3: 2051 | AH3: 2052 | AI3: 2053
A4: CO2e | B4: 97.2368 | C4: 131.5557 | D4: 137.9661 | E4: 144.619 | F4: 150.3491 | G4: 151.1062 | H4: 150.8597 | I4: 150.5671 | J4: 150.1164 | K4: 154.7755 | L4: 145.0963 | M4: 151.6215 | N4: 156.9237 | O4: 163.4155 | P4: 169.8313 | Q4: 174.0025 | R4: 180.5801 | S4: 188.6045 | T4: 195.4138 | U4: 201.8656 | V4: 186.7888 | W4: 193.3593 | X4: 200.2802 | Y4: 207.2126 | Z4: 214.1706 | AA4: 221.3431 | AB4: 228.4428 | AC4: 235.847 | AD4: 241.5861 | AE4: 250.149 | AF4: 250.8429 | AG4: 257.5413 | AH4: 264.6515 | AI4: 270.8016
A5: PHL_POW_BH2_NG | B5: 0 | C5: 0 | D5: 0 | E5: 0 | F5: 0 | G5: 0 | H5: 0 | I5: 0 | J5: 0 | K5: 0 | L5: 0 | M5: 0 | N5: 0 | O5: 0 | P5: 0 | Q5: 0 | R5: 0 | S5: 0 | T5: 0 | U5: 0 | V5: 0 | W5: 0 | X5: 0 | Y5: 0 | Z5: 0 | AA5: 0 | AB5: 0 | AC5: 0 | AD5: 0 | AE5: 0 | AF5: 0 | AG5: 0 | AH5: 0 | AI5: 0
A6: PHL_POW_DAC | B6: 0 | C6: 0 | D6: 0 | E6: 0 | F6: 0 | G6: 0 | H6: 0 | I6: 0 | J6: 0 | K6: 0 | L6: 0 | M6: 0 | N6: 0 | O6: 0 | P6: 0 | Q6: 0 | R6: 0 | S6: 0 | T6: 0 | U6: 0 | V6: 0 | W6: 0 | X6: 0 | Y6: 0 | Z6: 0 | AA6: 0 | AB6: 0 | AC6: 0 | AD6: 0 | AE6: 0 | AF6: 0 | AG6: 0 | AH6: 0 | AI6: 0
A7: PHL_POW_PP_BIOM_CCS | B7: 0 | C7: 0 | D7: 0 | E7: 0 | F7: 0 | G7: 0 | H7: 0 | I7: 0 | J7: 0 | K7: 0 | L7: 0 | M7: 0 | N7: 0 | O7: 0 | P7: 0 | Q7: 0 | R7: 0 | S7: 0 | T7: 0 | U7: 0 | V7: 0 | W7: 0 | X7: 0 | Y7: 0 | Z7: 0 | AA7: 0 | AB7: 0 | AC7: 0 | AD7: 0 | AE7: 0 | AF7: 0 | AG7: 0 | AH7: 0 | AI7: 0
A8: PHL_POW_PP_COAL_CCS | B8: 0 | C8: 0 | D8: 0 | E8: 0 | F8: 0 | G8: 0 | H8: 0 | I8: 0 | J8: 0 | K8: 0 | L8: 0 | M8: 0 | N8: 0 | O8: 0 | P8: 0 | Q8: 0 | R8: 0 | S8: 0 | T8: 0 | U8: 0 | V8: 0 | W8: 0 | X8: 0 | Y8: 0 | Z8: 0 | AA8: 0 | AB8: 0 | AC8: 0 | AD8: 0 | AE8: 0 | AF8: 0 | AG8: 0 | AH8: 0 | AI8: 0
A9: PHL_POW_PP_NGCC_CCS | B9: 0 | C9: 0 | D9: 0 | E9: 0 | F9: 0 | G9: 0 | H9: 0 | I9: 0 | J9: 0 | K9: 0 | L9: 0 | M9: 0 | N9: 0 | O9: 0 | P9: 0 | Q9: 0 | R9: 0 | S9: 0 | T9: 0 | U9: 0 | V9: 0 | W9: 0 | X9: 0 | Y9: 0 | Z9: 0 | AA9: 0 | AB9: 0 | AC9: 0 | AD9: 0 | AE9: 0 | AF9: 0 | AG9: 0 | AH9: 0 | AI9: 0
A10: PHL_PRO_PROC_COAL | B10: 70.5467 | C10: 112.3876 | D10: 117.9528 | E10: 126.6881 | F10: 133.5806 | G10: 142.1723 | H10: 141.8203 | I10: 141.4247 | J10: 140.883 | K10: 144.8708 | L10: 134.7112 | M10: 140.9753 | N10: 147.7748 | O10: 154.2032 | P10: 160.5989 | Q10: 164.8825 | R10: 171.2105 | S10: 178.9858 | T10: 185.5265 | U10: 191.2802 | V10: 175.0678 | W10: 180.7849 | X10: 187.1638 | Y10: 193.5562 | Z10: 199.9614 | AA10: 206.5778 | AB10: 213.0192 | AC10: 219.751 | AD10: 224.7584 | AE10: 231.557 | AF10: 230.0622 | AG10: 235.8958 | AH10: 242.1372 | AI10: 247.4222
A11: PHL_PRO_PROC_NG | B11: 7.3094 | C11: 8.444 | D11: 8.1301 | E11: 7.8004 | F11: 14.1071 | G11: 8.1137 | H11: 8.2129 | I11: 8.3096 | J11: 8.3941 | K11: 9.0587 | L11: 9.5481 | M11: 9.8014 | N11: 8.2963 | O11: 8.3519 | P11: 8.536 | Q11: 9.12 | R11: 9.3696 | S11: 9.6187 | T11: 9.8873 | U11: 10.5854 | V11: 11.721 | W11: 12.5744 | X11: 13.1164 | Y11: 13.6564 | Z11: 14.2092 | AA11: 14.7653 | AB11: 15.4236 | AC11: 16.096 | AD11: 16.8277 | AE11: 18.592 | AF11: 20.7807 | AG11: 21.6455 | AH11: 22.5143 | AI11: 23.3794
A12: PHL_PRO_PROC_OIL | B12: 19.3807 | C12: 10.7241 | D12: 11.8832 | E12: 10.1305 | F12: 2.6614 | G12: 0.8202 | H12: 0.8265 | I12: 0.8328 | J12: 0.8393 | K12: 0.846 | L12: 0.837 | M12: 0.8448 | N12: 0.8526 | O12: 0.8604 | P12: 0.6964 | Q12: 0 | R12: 0 | S12: 0 | T12: 0 | U12: 0 | V12: 0 | W12: 0 | X12: 0 | Y12: 0 | Z12: 0 | AA12: 0 | AB12: 0 | AC12: 0 | AD12: 0 | AE12: 0 | AF12: 0 | AG12: 0 | AH12: 0 | AI12: 0
A13: PM2_5 | B13: 64.8365 | C13: 67.0945 | D13: 69.3282 | E13: 71.561 | F13: 73.7941 | G13: 76.0273 | H13: 78.6275 | I13: 81.2264 | J13: 83.8274 | K13: 86.4267 | L13: 89.0258 | M13: 92.001 | N13: 94.9764 | O13: 97.9517 | P13: 100.9271 | Q13: 103.9035 | R13: 107.3876 | S13: 110.8702 | T13: 114.3552 | U13: 117.8384 | V13: 121.3227 | W13: 125.2588 | X13: 129.1936 | Y13: 133.1299 | Z13: 137.0669 | AA13: 141.003 | AB13: 145.1994 | AC13: 149.396 | AD13: 153.5948 | AE13: 157.7921 | AF13: 161.9885 | AG13: 166.1783 | AH13: 170.3666 | AI13: 174.555
A14: PHL_HOU_COOK_BIOM | B14: 0.0026 | C14: 0 | D14: 0 | E14: 0 | F14: 0 | G14: 0 | H14: 0 | I14: 0 | J14: 0 | K14: 0 | L14: 0 | M14: 0 | N14: 0 | O14: 0 | P14: 0 | Q14: 0 | R14: 0 | S14: 0 | T14: 0 | U14: 0 | V14: 0 | W14: 0 | X14: 0 | Y14: 0 | Z14: 0 | AA14: 0 | AB14: 0 | AC14: 0 | AD14: 0 | AE14: 0 | AF14: 0 | AG14: 0 | AH14: 0 | AI14: 0
... A30: PHL_TRA_VAN_LIQ | B30: 5.773 | C30: 6.1101 | D30: 6.4472 | E30: 6.7844 | F30: 7.1215 | G30: 7.4586 | H30: 7.874 | I30: 8.2886 | J30: 8.704 | K30: 9.1186 | L30: 9.5333 | M30: 10.0308 | N30: 10.5276 | O30: 11.0252 | P30: 11.5227 | Q30: 12.0195 | R30: 12.6271 | S30: 13.2339 | T30: 13.8415 | U30: 14.4483 | V30: 15.0559 | W30: 15.7627 | X30: 16.4695 | Y30: 17.1763 | Z30: 17.8839 | AA30: 18.5907 | AB30: 19.3603 | AC30: 20.1298 | AD30: 20.9002 | AE30: 21.6698 | AF30: 22.4394 | AG30: 23.2174 | AH30: 23.9948 | AI30: 24.7721

Sheet Cost_of_ELCgen
A1: Philippines
A3: AnnualFixedOperatingCost + AnnualVariableOperating Cost (Million USD) | C3: 2020 | D3: 2021 | E3: 2022 | F3: 2023 | G3: 2024 | H3: 2025 | I3: 2026 | J3: 2027 | K3: 2028 | L3: 2029 | M3: 2030 | N3: 2031 | O3: 2032 | P3: 2033 | Q3: 2034 | R3: 2035 | S3: 2036 | T3: 2037 | U3: 2038 | V3: 2039 | W3: 2040 | X3: 2041 | Y3: 2042 | Z3: 2043 | AA3: 2044 | AB3: 2045 | AC3: 2046 | AD3: 2047 | AE3: 2048 | AF3: 2049 | AG3: 2050
A4: TOTAL (Fixed & Variable) | C4: =SUM(C6:C9)+SUM(C38:C54) -> 12310.832 | D4: =SUM(D6:D9)+SUM(D38:D54) -> 6254.3036 | E4: =SUM(E6:E9)+SUM(E38:E54) -> 6397.9269 | F4: =SUM(F6:F9)+SUM(F38:F54) -> 6631.6216 | G4: =SUM(G6:G9)+SUM(G38:G54) -> 7950.2843 | H4: =SUM(H6:H9)+SUM(H38:H54) -> 6861.098 | I4: =SUM(I6:I9)+SUM(I38:I54) -> 6982.7317 | J4: =SUM(J6:J9)+SUM(J38:J54) -> 7103.3257 | ... AG4: =SUM(AG6:AG9)+SUM(AG38:AG54) -> 6782.1796
A5: VARIABLE
A6: PHL_PRO_EXTR_NG | C6: =SUMIFS(Variable!C$2:C$9992,Variable!$B$2:$B$9992,$A6) -> 1261.3245 | D6: =SUMIFS(Variable!D$2:D$9992,Variable!$B$2:$B$9992,$A6) -> 1462.7943 | E6: =SUMIFS(Variable!E$2:E$9992,Variable!$B$2:$B$9992,$A6) -> 1414.0287 | F6: =SUMIFS(Variable!F$2:F$9992,Variable!$B$2:$B$9992,$A6) -> 1362.0854 | G6: =SUMIFS(Variable!G$2:G$9992,Variable!$B$2:$B$9992,$A6) -> 2473.1051 | H6: =SUMIFS(Variable!H$2:H$9992,Variable!$B$2:$B$9992,$A6) -> 1428.0187 | I6: =SUMIFS(Variable!I$2:I$9992,Variable!$B$2:$B$9992,$A6) -> 1451.1501 | J6: =SUMIFS(Variable!J$2:J$9992,Variable!$B$2:$B$9992,$A6) -> 1473.8243 | ... AG6: =SUMIFS(Variable!AG$2:AG$9992,Variable!$B$2:$B$9992,$A6) -> 3862.2493
A7: PHL_PRO_EXTR_OIL | C7: =SUMIFS(Variable!C$2:C$9992,Variable!$B$2:$B$9992,$A7) -> 3103.7145 | D7: =SUMIFS(Variable!D$2:D$9992,Variable!$B$2:$B$9992,$A7) -> 0 | E7: =SUMIFS(Variable!E$2:E$9992,Variable!$B$2:$B$9992,$A7) -> 0 | F7: =SUMIFS(Variable!F$2:F$9992,Variable!$B$2:$B$9992,$A7) -> 0 | G7: =SUMIFS(Variable!G$2:G$9992,Variable!$B$2:$B$9992,$A7) -> 0 | H7: =SUMIFS(Variable!H$2:H$9992,Variable!$B$2:$B$9992,$A7) -> 0 | I7: =SUMIFS(Variable!I$2:I$9992,Variable!$B$2:$B$9992,$A7) -> 0 | J7: =SUMIFS(Variable!J$2:J$9992,Variable!$B$2:$B$9992,$A7) -> 0 | ... AG7: =SUMIFS(Variable!AG$2:AG$9992,Variable!$B$2:$B$9992,$A7) -> 0
A8: PHL_PRO_EXTR_COAL | C8: =SUMIFS(Variable!C$2:C$9992,Variable!$B$2:$B$9992,$A8) -> 2023.5934 | D8: =SUMIFS(Variable!D$2:D$9992,Variable!$B$2:$B$9992,$A8) -> 3235.0883 | E8: =SUMIFS(Variable!E$2:E$9992,Variable!$B$2:$B$9992,$A8) -> 3407.1523 | F8: =SUMIFS(Variable!F$2:F$9992,Variable!$B$2:$B$9992,$A8) -> 3672.2302 | G8: =SUMIFS(Variable!G$2:G$9992,Variable!$B$2:$B$9992,$A8) -> 3885.4627 | H8: =SUMIFS(Variable!H$2:H$9992,Variable!$B$2:$B$9992,$A8) -> 4149.6797 | I8: =SUMIFS(Variable!I$2:I$9992,Variable!$B$2:$B$9992,$A8) -> 4153.678 | J8: =SUMIFS(Variable!J$2:J$9992,Variable!$B$2:$B$9992,$A8) -> 4156.3261 | ... AG8: =SUMIFS(Variable!AG$2:AG$9992,Variable!$B$2:$B$9992,$A8) -> 0
A9: PHL_PRO_PROC_BIOM | C9: =SUMIFS(Variable!C$2:C$9992,Variable!$B$2:$B$9992,$A9) -> 4868.8589 | D9: =SUMIFS(Variable!D$2:D$9992,Variable!$B$2:$B$9992,$A9) -> 361.0288 | E9: =SUMIFS(Variable!E$2:E$9992,Variable!$B$2:$B$9992,$A9) -> 332.901 | F9: =SUMIFS(Variable!F$2:F$9992,Variable!$B$2:$B$9992,$A9) -> 353.1743 | G9: =SUMIFS(Variable!G$2:G$9992,Variable!$B$2:$B$9992,$A9) -> 333.2395 | H9: =SUMIFS(Variable!H$2:H$9992,Variable!$B$2:$B$9992,$A9) -> 0 | I9: =SUMIFS(Variable!I$2:I$9992,Variable!$B$2:$B$9992,$A9) -> 0 | J9: =SUMIFS(Variable!J$2:J$9992,Variable!$B$2:$B$9992,$A9) -> 0 | ... AG9: =SUMIFS(Variable!AG$2:AG$9992,Variable!$B$2:$B$9992,$A9) -> 71.597
A10: PHL_POW_CHP_BIOM_OLD | C10: =SUMIFS(Variable!C$2:C$9992,Variable!$B$2:$B$9992,$A10) -> 0.0004 | D10: =SUMIFS(Variable!D$2:D$9992,Variable!$B$2:$B$9992,$A10) -> 0.0005 | E10: =SUMIFS(Variable!E$2:E$9992,Variable!$B$2:$B$9992,$A10) -> 0.0005 | F10: =SUMIFS(Variable!F$2:F$9992,Variable!$B$2:$B$9992,$A10) -> 0.0005 | G10: =SUMIFS(Variable!G$2:G$9992,Variable!$B$2:$B$9992,$A10) -> 0.0005 | H10: =SUMIFS(Variable!H$2:H$9992,Variable!$B$2:$B$9992,$A10) -> 0 | I10: =SUMIFS(Variable!I$2:I$9992,Variable!$B$2:$B$9992,$A10) -> 0 | J10: =SUMIFS(Variable!J$2:J$9992,Variable!$B$2:$B$9992,$A10) -> 0 | ... AG10: =SUMIFS(Variable!AG$2:AG$9992,Variable!$B$2:$B$9992,$A10) -> 0.0001
A11: PHL_POW_CHP_COAL_OLD | C11: =SUMIFS(Variable!C$2:C$9992,Variable!$B$2:$B$9992,$A11) -> 0.0209 | D11: =SUMIFS(Variable!D$2:D$9992,Variable!$B$2:$B$9992,$A11) -> 0.0223 | E11: =SUMIFS(Variable!E$2:E$9992,Variable!$B$2:$B$9992,$A11) -> 0.0239 | F11: =SUMIFS(Variable!F$2:F$9992,Variable!$B$2:$B$9992,$A11) -> 0.0266 | G11: =SUMIFS(Variable!G$2:G$9992,Variable!$B$2:$B$9992,$A11) -> 0.0286 | H11: =SUMIFS(Variable!H$2:H$9992,Variable!$B$2:$B$9992,$A11) -> 0.0263 | I11: =SUMIFS(Variable!I$2:I$9992,Variable!$B$2:$B$9992,$A11) -> 0.0258 | J11: =SUMIFS(Variable!J$2:J$9992,Variable!$B$2:$B$9992,$A11) -> 0.0254 | ... AG11: =SUMIFS(Variable!AG$2:AG$9992,Variable!$B$2:$B$9992,$A11) -> 0.01
A12: PHL_POW_GEO_OLD | C12: =SUMIFS(Variable!C$2:C$9992,Variable!$B$2:$B$9992,$A12) -> 0.0039 | D12: =SUMIFS(Variable!D$2:D$9992,Variable!$B$2:$B$9992,$A12) -> 0.0036 | E12: =SUMIFS(Variable!E$2:E$9992,Variable!$B$2:$B$9992,$A12) -> 0.0038 | F12: =SUMIFS(Variable!F$2:F$9992,Variable!$B$2:$B$9992,$A12) -> 0.0039 | G12: =SUMIFS(Variable!G$2:G$9992,Variable!$B$2:$B$9992,$A12) -> 0.0039 | H12: =SUMIFS(Variable!H$2:H$9992,Variable!$B$2:$B$9992,$A12) -> 0.004 | I12: =SUMIFS(Variable!I$2:I$9992,Variable!$B$2:$B$9992,$A12) -> 0.0066 | J12: =SUMIFS(Variable!J$2:J$9992,Variable!$B$2:$B$9992,$A12) -> 0.0093 | ... AG12: =SUMIFS(Variable!AG$2:AG$9992,Variable!$B$2:$B$9992,$A12) -> 0.0126
A13: PHL_POW_PP_BIOM_CCS | C13: =SUMIFS(Variable!C$2:C$9992,Variable!$B$2:$B$9992,$A13) -> 0 | D13: =SUMIFS(Variable!D$2:D$9992,Variable!$B$2:$B$9992,$A13) -> 0 | E13: =SUMIFS(Variable!E$2:E$9992,Variable!$B$2:$B$9992,$A13) -> 0 | F13: =SUMIFS(Variable!F$2:F$9992,Variable!$B$2:$B$9992,$A13) -> 0 | G13: =SUMIFS(Variable!G$2:G$9992,Variable!$B$2:$B$9992,$A13) -> 0 | H13: =SUMIFS(Variable!H$2:H$9992,Variable!$B$2:$B$9992,$A13) -> 0 | I13: =SUMIFS(Variable!I$2:I$9992,Variable!$B$2:$B$9992,$A13) -> 0 | J13: =SUMIFS(Variable!J$2:J$9992,Variable!$B$2:$B$9992,$A13) -> 0 | ... AG13: =SUMIFS(Variable!AG$2:AG$9992,Variable!$B$2:$B$9992,$A13) -> 0
A14: PHL_POW_PP_COAL | C14: =SUMIFS(Variable!C$2:C$9992,Variable!$B$2:$B$9992,$A14) -> 0 | D14: =SUMIFS(Variable!D$2:D$9992,Variable!$B$2:$B$9992,$A14) -> 0 | E14: =SUMIFS(Variable!E$2:E$9992,Variable!$B$2:$B$9992,$A14) -> 0 | F14: =SUMIFS(Variable!F$2:F$9992,Variable!$B$2:$B$9992,$A14) -> 0 | G14: =SUMIFS(Variable!G$2:G$9992,Variable!$B$2:$B$9992,$A14) -> 0 | H14: =SUMIFS(Variable!H$2:H$9992,Variable!$B$2:$B$9992,$A14) -> 0.0066 | I14: =SUMIFS(Variable!I$2:I$9992,Variable!$B$2:$B$9992,$A14) -> 0.0066 | J14: =SUMIFS(Variable!J$2:J$9992,Variable!$B$2:$B$9992,$A14) -> 0.0066 | ... AG14: =SUMIFS(Variable!AG$2:AG$9992,Variable!$B$2:$B$9992,$A14) -> 0.0576
A15: PHL_POW_PP_COAL_CCS | C15: =SUMIFS(Variable!C$2:C$9992,Variable!$B$2:$B$9992,$A15) -> 0 | D15: =SUMIFS(Variable!D$2:D$9992,Variable!$B$2:$B$9992,$A15) -> 0 | E15: =SUMIFS(Variable!E$2:E$9992,Variable!$B$2:$B$9992,$A15) -> 0 | F15: =SUMIFS(Variable!F$2:F$9992,Variable!$B$2:$B$9992,$A15) -> 0 | G15: =SUMIFS(Variable!G$2:G$9992,Variable!$B$2:$B$9992,$A15) -> 0 | H15: =SUMIFS(Variable!H$2:H$9992,Variable!$B$2:$B$9992,$A15) -> 0 | I15: =SUMIFS(Variable!I$2:I$9992,Variable!$B$2:$B$9992,$A15) -> 0 | J15: =SUMIFS(Variable!J$2:J$9992,Variable!$B$2:$B$9992,$A15) -> 0 | ... AG15: =SUMIFS(Variable!AG$2:AG$9992,Variable!$B$2:$B$9992,$A15) -> 0
A16: PHL_POW_PP_H2 | C16: =SUMIFS(Variable!C$2:C$9992,Variable!$B$2:$B$9992,$A16) -> 0 | D16: =SUMIFS(Variable!D$2:D$9992,Variable!$B$2:$B$9992,$A16) -> 0 | E16: =SUMIFS(Variable!E$2:E$9992,Variable!$B$2:$B$9992,$A16) -> 0 | F16: =SUMIFS(Variable!F$2:F$9992,Variable!$B$2:$B$9992,$A16) -> 0 | G16: =SUMIFS(Variable!G$2:G$9992,Variable!$B$2:$B$9992,$A16) -> 0 | H16: =SUMIFS(Variable!H$2:H$9992,Variable!$B$2:$B$9992,$A16) -> 0 | I16: =SUMIFS(Variable!I$2:I$9992,Variable!$B$2:$B$9992,$A16) -> 0 | J16: =SUMIFS(Variable!J$2:J$9992,Variable!$B$2:$B$9992,$A16) -> 0 | ... AG16: =SUMIFS(Variable!AG$2:AG$9992,Variable!$B$2:$B$9992,$A16) -> 0
A17: PHL_POW_PP_HY_LA | C17: =SUMIFS(Variable!C$2:C$9992,Variable!$B$2:$B$9992,$A17) -> 0.0026 | D17: =SUMIFS(Variable!D$2:D$9992,Variable!$B$2:$B$9992,$A17) -> 0.0033 | E17: =SUMIFS(Variable!E$2:E$9992,Variable!$B$2:$B$9992,$A17) -> 0.0036 | F17: =SUMIFS(Variable!F$2:F$9992,Variable!$B$2:$B$9992,$A17) -> 0.0037 | G17: =SUMIFS(Variable!G$2:G$9992,Variable!$B$2:$B$9992,$A17) -> 0.0039 | H17: =SUMIFS(Variable!H$2:H$9992,Variable!$B$2:$B$9992,$A17) -> 0.0039 | I17: =SUMIFS(Variable!I$2:I$9992,Variable!$B$2:$B$9992,$A17) -> 0.0039 | J17: =SUMIFS(Variable!J$2:J$9992,Variable!$B$2:$B$9992,$A17) -> 0.0039 | ... AG17: =SUMIFS(Variable!AG$2:AG$9992,Variable!$B$2:$B$9992,$A17) -> 0.0039
... A27: PHL_POW_TD | C27: =SUMIFS(Variable!C$2:C$9992,Variable!$B$2:$B$9992,$A27) -> 0.03 | D27: =SUMIFS(Variable!D$2:D$9992,Variable!$B$2:$B$9992,$A27) -> 0.03 | E27: =SUMIFS(Variable!E$2:E$9992,Variable!$B$2:$B$9992,$A27) -> 0.0315 | F27: =SUMIFS(Variable!F$2:F$9992,Variable!$B$2:$B$9992,$A27) -> 0.033 | G27: =SUMIFS(Variable!G$2:G$9992,Variable!$B$2:$B$9992,$A27) -> 0.0345 | H27: =SUMIFS(Variable!H$2:H$9992,Variable!$B$2:$B$9992,$A27) -> 0.0357 | I27: =SUMIFS(Variable!I$2:I$9992,Variable!$B$2:$B$9992,$A27) -> 0.0375 | J27: =SUMIFS(Variable!J$2:J$9992,Variable!$B$2:$B$9992,$A27) -> 0.0394 | ... AG27: =SUMIFS(Variable!AG$2:AG$9992,Variable!$B$2:$B$9992,$A27) -> 0.0998
A29: Only grid-connected
A30: Coal | C30: =SUM(C225,C228:C229)*C120 -> 1994.5146 | D30: =SUM(D225,D228:D229)*D120 -> 2135.6274 | E30: =SUM(E225,E228:E229)*E120 -> 2295.2728 | F30: =SUM(F225,F228:F229)*F120 -> 2558.2788 | G30: =SUM(G225,G228:G229)*G120 -> 2763.4081 | H30: =SUM(H225,H228:H229)*H120 -> 3015.7323 | I30: =SUM(I225,I228:I229)*I120 -> 2987.7498 | J30: =SUM(J225,J228:J229)*J120 -> 2958.135 | ... AG30: =SUM(AG225,AG228:AG229)*AG120 -> 5884.9224
A31: Natural gas | C31: =SUM(C232:C233)*C122 -> 0 | D31: =SUM(D232:D233)*D122 -> 0 | E31: =SUM(E232:E233)*E122 -> 0 | F31: =SUM(F232:F233)*F122 -> 0 | G31: =SUM(G232:G233)*G122 -> 0 | H31: =SUM(H232:H233)*H122 -> 93.366323 | I31: =SUM(I232:I233)*I122 -> 95.665644 | J31: =SUM(J232:J233)*J122 -> 97.754021 | ... AG31: =SUM(AG232:AG233)*AG122 -> 1158.6393
A32: Oil | C32: =C239*C121 -> 647.30077 | D32: =D239*D121 -> 430.62415 | E32: =E239*E121 -> 682.23713 | F32: =F239*F121 -> 358.88757 | G32: =G239*G121 -> 375.2526 | H32: =H239*H121 -> 0 | I32: =I239*I121 -> 0 | J32: =J239*J121 -> 0 | ... AG32: =AG239*AG121 -> 0
A33: Biomass | C33: =SUM(C224,C227)*C123 -> 288.0496 | D33: =SUM(D224,D227)*D123 -> 332.9856 | E33: =SUM(E224,E227)*E123 -> 304.6256 | F33: =SUM(F224,F227)*F123 -> 324.6608 | G33: =SUM(G224,G227)*G123 -> 333.2384 | H33: =SUM(H224,H227)*H123 -> 0 | I33: =SUM(I224,I227)*I123 -> 0 | J33: =SUM(J224,J227)*J123 -> 0 | ... AG33: =SUM(AG224,AG227)*AG123 -> 71.5968
A34: Uranium | C34: =C241*C124 -> 0 | D34: =D241*D124 -> 0 | E34: =E241*E124 -> 0 | F34: =F241*F124 -> 0 | G34: =G241*G124 -> 0 | H34: =H241*H124 -> 0 | I34: =I241*I124 -> 0 | J34: =J241*J124 -> 0 | ... AG34: =AG241*AG124 -> 0
A35: TOTAL (Fixed & Variable) | C35: =SUM(C38:C55)+SUM(C30:C34)+SUM(C10:C27) -> 3983.2719 | D35: =SUM(D38:D55)+SUM(D30:D34)+SUM(D10:D27) -> 4094.6976 | E35: =SUM(E38:E55)+SUM(E30:E34)+SUM(E10:E27) -> 4526.0522 | F35: =SUM(F38:F55)+SUM(F30:F34)+SUM(F10:F27) -> 4486.0345 | G35: =SUM(G38:G55)+SUM(G30:G34)+SUM(G10:G27) -> 4730.4563 | H35: =SUM(H38:H55)+SUM(H30:H34)+SUM(H10:H27) -> 4392.5777 | I35: =SUM(I38:I55)+SUM(I30:I34)+SUM(I10:I27) -> 4461.4024 | J35: =SUM(J38:J55)+SUM(J30:J34)+SUM(J10:J27) -> 4529.1519 | ... AG35: =SUM(AG38:AG55)+SUM(AG30:AG34)+SUM(AG10:AG27) -> 9963.7135
A37: FIXED | C37: 2020 | D37: 2021 | E37: 2022 | F37: 2023 | G37: 2024 | H37: 2025 | I37: 2026 | J37: 2027 | K37: 2028 | L37: 2029 | M37: 2030 | N37: 2031 | O37: 2032 | P37: 2033 | Q37: 2034 | R37: 2035 | S37: 2036 | T37: 2037 | U37: 2038 | V37: 2039 | W37: 2040 | X37: 2041 | Y37: 2042 | Z37: 2043 | AA37: 2044 | AB37: 2045 | AC37: 2046 | AD37: 2047 | AE37: 2048 | AF37: 2049 | AG37: 2050
A38: PHL_POW_CHP_BIOM_OLD | C38: =SUMIFS(Fixed!C$2:C$10000,Fixed!$B$2:$B$10000,$A38) -> 44.748 | D38: =SUMIFS(Fixed!D$2:D$10000,Fixed!$B$2:$B$10000,$A38) -> 44.748 | E38: =SUMIFS(Fixed!E$2:E$10000,Fixed!$B$2:$B$10000,$A38) -> 52.128 | F38: =SUMIFS(Fixed!F$2:F$10000,Fixed!$B$2:$B$10000,$A38) -> 52.668 | G38: =SUMIFS(Fixed!G$2:G$10000,Fixed!$B$2:$B$10000,$A38) -> 53.559 | H38: =SUMIFS(Fixed!H$2:H$10000,Fixed!$B$2:$B$10000,$A38) -> 53.559 | I38: =SUMIFS(Fixed!I$2:I$10000,Fixed!$B$2:$B$10000,$A38) -> 53.559 | J38: =SUMIFS(Fixed!J$2:J$10000,Fixed!$B$2:$B$10000,$A38) -> 53.559 | ... AG38: =SUMIFS(Fixed!AG$2:AG$10000,Fixed!$B$2:$B$10000,$A38) -> 45.693
A39: PHL_POW_CHP_COAL_OLD | C39: =SUMIFS(Fixed!C$2:C$10000,Fixed!$B$2:$B$10000,$A39) -> 491.0355 | D39: =SUMIFS(Fixed!D$2:D$10000,Fixed!$B$2:$B$10000,$A39) -> 491.0355 | E39: =SUMIFS(Fixed!E$2:E$10000,Fixed!$B$2:$B$10000,$A39) -> 491.0355 | F39: =SUMIFS(Fixed!F$2:F$10000,Fixed!$B$2:$B$10000,$A39) -> 491.0355 | G39: =SUMIFS(Fixed!G$2:G$10000,Fixed!$B$2:$B$10000,$A39) -> 464.0355 | H39: =SUMIFS(Fixed!H$2:H$10000,Fixed!$B$2:$B$10000,$A39) -> 464.0355 | I39: =SUMIFS(Fixed!I$2:I$10000,Fixed!$B$2:$B$10000,$A39) -> 464.0355 | J39: =SUMIFS(Fixed!J$2:J$10000,Fixed!$B$2:$B$10000,$A39) -> 464.0355 | ... AG39: =SUMIFS(Fixed!AG$2:AG$10000,Fixed!$B$2:$B$10000,$A39) -> 286.461
A40: PHL_POW_GEO_OLD | C40: =SUMIFS(Fixed!C$2:C$10000,Fixed!$B$2:$B$10000,$A40) -> 144.394 | D40: =SUMIFS(Fixed!D$2:D$10000,Fixed!$B$2:$B$10000,$A40) -> 144.394 | E40: =SUMIFS(Fixed!E$2:E$10000,Fixed!$B$2:$B$10000,$A40) -> 144.8195 | F40: =SUMIFS(Fixed!F$2:F$10000,Fixed!$B$2:$B$10000,$A40) -> 140.8618 | G40: =SUMIFS(Fixed!G$2:G$10000,Fixed!$B$2:$B$10000,$A40) -> 141.6349 | H40: =SUMIFS(Fixed!H$2:H$10000,Fixed!$B$2:$B$10000,$A40) -> 145.7404 | I40: =SUMIFS(Fixed!I$2:I$10000,Fixed!$B$2:$B$10000,$A40) -> 241.6307 | J40: =SUMIFS(Fixed!J$2:J$10000,Fixed!$B$2:$B$10000,$A40) -> 338.2075 | ... AG40: =SUMIFS(Fixed!AG$2:AG$10000,Fixed!$B$2:$B$10000,$A40) -> 460
A41: PHL_POW_PP_BIOM_CCS | C41: =SUMIFS(Fixed!C$2:C$10000,Fixed!$B$2:$B$10000,$A41) -> 0 | D41: =SUMIFS(Fixed!D$2:D$10000,Fixed!$B$2:$B$10000,$A41) -> 0 | E41: =SUMIFS(Fixed!E$2:E$10000,Fixed!$B$2:$B$10000,$A41) -> 0 | F41: =SUMIFS(Fixed!F$2:F$10000,Fixed!$B$2:$B$10000,$A41) -> 0 | G41: =SUMIFS(Fixed!G$2:G$10000,Fixed!$B$2:$B$10000,$A41) -> 0 | H41: =SUMIFS(Fixed!H$2:H$10000,Fixed!$B$2:$B$10000,$A41) -> 0 | I41: =SUMIFS(Fixed!I$2:I$10000,Fixed!$B$2:$B$10000,$A41) -> 0 | J41: =SUMIFS(Fixed!J$2:J$10000,Fixed!$B$2:$B$10000,$A41) -> 0 | ... AG41: =SUMIFS(Fixed!AG$2:AG$10000,Fixed!$B$2:$B$10000,$A41) -> 0
A42: PHL_POW_PP_COAL | C42: =SUMIFS(Fixed!C$2:C$10000,Fixed!$B$2:$B$10000,$A42) -> 0 | D42: =SUMIFS(Fixed!D$2:D$10000,Fixed!$B$2:$B$10000,$A42) -> 32.877 | E42: =SUMIFS(Fixed!E$2:E$10000,Fixed!$B$2:$B$10000,$A42) -> 67.7675 | F42: =SUMIFS(Fixed!F$2:F$10000,Fixed!$B$2:$B$10000,$A42) -> 67.7675 | G42: =SUMIFS(Fixed!G$2:G$10000,Fixed!$B$2:$B$10000,$A42) -> 94.9761 | H42: =SUMIFS(Fixed!H$2:H$10000,Fixed!$B$2:$B$10000,$A42) -> 94.9761 | I42: =SUMIFS(Fixed!I$2:I$10000,Fixed!$B$2:$B$10000,$A42) -> 94.9761 | J42: =SUMIFS(Fixed!J$2:J$10000,Fixed!$B$2:$B$10000,$A42) -> 94.9761 | ... AG42: =SUMIFS(Fixed!AG$2:AG$10000,Fixed!$B$2:$B$10000,$A42) -> 1189.1915
A43: PHL_POW_PP_COAL_CCS | C43: =SUMIFS(Fixed!C$2:C$10000,Fixed!$B$2:$B$10000,$A43) -> 0 | D43: =SUMIFS(Fixed!D$2:D$10000,Fixed!$B$2:$B$10000,$A43) -> 0 | E43: =SUMIFS(Fixed!E$2:E$10000,Fixed!$B$2:$B$10000,$A43) -> 0 | F43: =SUMIFS(Fixed!F$2:F$10000,Fixed!$B$2:$B$10000,$A43) -> 0 | G43: =SUMIFS(Fixed!G$2:G$10000,Fixed!$B$2:$B$10000,$A43) -> 0 | H43: =SUMIFS(Fixed!H$2:H$10000,Fixed!$B$2:$B$10000,$A43) -> 0 | I43: =SUMIFS(Fixed!I$2:I$10000,Fixed!$B$2:$B$10000,$A43) -> 0 | J43: =SUMIFS(Fixed!J$2:J$10000,Fixed!$B$2:$B$10000,$A43) -> 0 | ... AG43: =SUMIFS(Fixed!AG$2:AG$10000,Fixed!$B$2:$B$10000,$A43) -> 0
A44: PHL_POW_PP_H2 | C44: =SUMIFS(Fixed!C$2:C$10000,Fixed!$B$2:$B$10000,$A44) -> 0 | D44: =SUMIFS(Fixed!D$2:D$10000,Fixed!$B$2:$B$10000,$A44) -> 0 | E44: =SUMIFS(Fixed!E$2:E$10000,Fixed!$B$2:$B$10000,$A44) -> 0 | F44: =SUMIFS(Fixed!F$2:F$10000,Fixed!$B$2:$B$10000,$A44) -> 0 | G44: =SUMIFS(Fixed!G$2:G$10000,Fixed!$B$2:$B$10000,$A44) -> 0 | H44: =SUMIFS(Fixed!H$2:H$10000,Fixed!$B$2:$B$10000,$A44) -> 0 | I44: =SUMIFS(Fixed!I$2:I$10000,Fixed!$B$2:$B$10000,$A44) -> 0 | J44: =SUMIFS(Fixed!J$2:J$10000,Fixed!$B$2:$B$10000,$A44) -> 0 | ... AG44: =SUMIFS(Fixed!AG$2:AG$10000,Fixed!$B$2:$B$10000,$A44) -> 0
A45: PHL_POW_PP_HY_LA | C45: =SUMIFS(Fixed!C$2:C$10000,Fixed!$B$2:$B$10000,$A45) -> 191.6825 | D45: =SUMIFS(Fixed!D$2:D$10000,Fixed!$B$2:$B$10000,$A45) -> 287.1673 | E45: =SUMIFS(Fixed!E$2:E$10000,Fixed!$B$2:$B$10000,$A45) -> 287.7616 | F45: =SUMIFS(Fixed!F$2:F$10000,Fixed!$B$2:$B$10000,$A45) -> 289.5109 | G45: =SUMIFS(Fixed!G$2:G$10000,Fixed!$B$2:$B$10000,$A45) -> 290.8266 | H45: =SUMIFS(Fixed!H$2:H$10000,Fixed!$B$2:$B$10000,$A45) -> 290.8266 | I45: =SUMIFS(Fixed!I$2:I$10000,Fixed!$B$2:$B$10000,$A45) -> 290.8266 | J45: =SUMIFS(Fixed!J$2:J$10000,Fixed!$B$2:$B$10000,$A45) -> 290.8266 | ... AG45: =SUMIFS(Fixed!AG$2:AG$10000,Fixed!$B$2:$B$10000,$A45) -> 289.9744
A46: PHL_POW_PP_NGCC | C46: =SUMIFS(Fixed!C$2:C$10000,Fixed!$B$2:$B$10000,$A46) -> 0 | D46: =SUMIFS(Fixed!D$2:D$10000,Fixed!$B$2:$B$10000,$A46) -> 0 | E46: =SUMIFS(Fixed!E$2:E$10000,Fixed!$B$2:$B$10000,$A46) -> 0 | F46: =SUMIFS(Fixed!F$2:F$10000,Fixed!$B$2:$B$10000,$A46) -> 0 | G46: =SUMIFS(Fixed!G$2:G$10000,Fixed!$B$2:$B$10000,$A46) -> 0 | H46: =SUMIFS(Fixed!H$2:H$10000,Fixed!$B$2:$B$10000,$A46) -> 19.0192 | I46: =SUMIFS(Fixed!I$2:I$10000,Fixed!$B$2:$B$10000,$A46) -> 19.0192 | J46: =SUMIFS(Fixed!J$2:J$10000,Fixed!$B$2:$B$10000,$A46) -> 19.0192 | ... AG46: =SUMIFS(Fixed!AG$2:AG$10000,Fixed!$B$2:$B$10000,$A46) -> 221.8762
A47: PHL_POW_PP_NGCC_CCS | C47: =SUMIFS(Fixed!C$2:C$10000,Fixed!$B$2:$B$10000,$A47) -> 0 | D47: =SUMIFS(Fixed!D$2:D$10000,Fixed!$B$2:$B$10000,$A47) -> 0 | E47: =SUMIFS(Fixed!E$2:E$10000,Fixed!$B$2:$B$10000,$A47) -> 0 | F47: =SUMIFS(Fixed!F$2:F$10000,Fixed!$B$2:$B$10000,$A47) -> 0 | G47: =SUMIFS(Fixed!G$2:G$10000,Fixed!$B$2:$B$10000,$A47) -> 0 | H47: =SUMIFS(Fixed!H$2:H$10000,Fixed!$B$2:$B$10000,$A47) -> 0 | I47: =SUMIFS(Fixed!I$2:I$10000,Fixed!$B$2:$B$10000,$A47) -> 0 | J47: =SUMIFS(Fixed!J$2:J$10000,Fixed!$B$2:$B$10000,$A47) -> 0 | ... AG47: =SUMIFS(Fixed!AG$2:AG$10000,Fixed!$B$2:$B$10000,$A47) -> 0
A48: PHL_POW_PP_NU | C48: =SUMIFS(Fixed!C$2:C$10000,Fixed!$B$2:$B$10000,$A48) -> 0 | D48: =SUMIFS(Fixed!D$2:D$10000,Fixed!$B$2:$B$10000,$A48) -> 0 | E48: =SUMIFS(Fixed!E$2:E$10000,Fixed!$B$2:$B$10000,$A48) -> 0 | F48: =SUMIFS(Fixed!F$2:F$10000,Fixed!$B$2:$B$10000,$A48) -> 0 | G48: =SUMIFS(Fixed!G$2:G$10000,Fixed!$B$2:$B$10000,$A48) -> 0 | H48: =SUMIFS(Fixed!H$2:H$10000,Fixed!$B$2:$B$10000,$A48) -> 0 | I48: =SUMIFS(Fixed!I$2:I$10000,Fixed!$B$2:$B$10000,$A48) -> 0 | J48: =SUMIFS(Fixed!J$2:J$10000,Fixed!$B$2:$B$10000,$A48) -> 0 | ... AG48: =SUMIFS(Fixed!AG$2:AG$10000,Fixed!$B$2:$B$10000,$A48) -> 0
A49: PHL_POW_PP_NUSMR | C49: =SUMIFS(Fixed!C$2:C$10000,Fixed!$B$2:$B$10000,$A49) -> 0 | D49: =SUMIFS(Fixed!D$2:D$10000,Fixed!$B$2:$B$10000,$A49) -> 0 | E49: =SUMIFS(Fixed!E$2:E$10000,Fixed!$B$2:$B$10000,$A49) -> 0 | F49: =SUMIFS(Fixed!F$2:F$10000,Fixed!$B$2:$B$10000,$A49) -> 0 | G49: =SUMIFS(Fixed!G$2:G$10000,Fixed!$B$2:$B$10000,$A49) -> 0 | H49: =SUMIFS(Fixed!H$2:H$10000,Fixed!$B$2:$B$10000,$A49) -> 0 | I49: =SUMIFS(Fixed!I$2:I$10000,Fixed!$B$2:$B$10000,$A49) -> 0 | J49: =SUMIFS(Fixed!J$2:J$10000,Fixed!$B$2:$B$10000,$A49) -> 0 | ... AG49: =SUMIFS(Fixed!AG$2:AG$10000,Fixed!$B$2:$B$10000,$A49) -> 0
... A55: PHL_POW_TD | C55: =SUMIFS(Fixed!C$2:C$10000,Fixed!$B$2:$B$10000,$A55) -> 0 | D55: =SUMIFS(Fixed!D$2:D$10000,Fixed!$B$2:$B$10000,$A55) -> 0 | E55: =SUMIFS(Fixed!E$2:E$10000,Fixed!$B$2:$B$10000,$A55) -> 0 | F55: =SUMIFS(Fixed!F$2:F$10000,Fixed!$B$2:$B$10000,$A55) -> 0 | G55: =SUMIFS(Fixed!G$2:G$10000,Fixed!$B$2:$B$10000,$A55) -> 0 | H55: =SUMIFS(Fixed!H$2:H$10000,Fixed!$B$2:$B$10000,$A55) -> 0 | I55: =SUMIFS(Fixed!I$2:I$10000,Fixed!$B$2:$B$10000,$A55) -> 0 | J55: =SUMIFS(Fixed!J$2:J$10000,Fixed!$B$2:$B$10000,$A55) -> 0 | ... AG55: =SUMIFS(Fixed!AG$2:AG$10000,Fixed!$B$2:$B$10000,$A55) -> 0
A58: Capital Investments (M.USD) | C58: 2020 | D58: 2021 | E58: 2022 | F58: 2023 | G58: 2024 | H58: 2025 | I58: 2026 | J58: 2027 | K58: 2028 | L58: 2029 | M58: 2030 | N58: 2031 | O58: 2032 | P58: 2033 | Q58: 2034 | R58: 2035 | S58: 2036 | T58: 2037 | U58: 2038 | V58: 2039 | W58: 2040 | X58: 2041 | Y58: 2042 | Z58: 2043 | AA58: 2044 | AB58: 2045 | AC58: 2046 | AD58: 2047 | AE58: 2048 | AF58: 2049 | AG58: 2050
A59: PHL_POW_CHP_BIOM_OLD | C59: =SUMIFS(Capital_Investments!C$2:C$10000,Capital_Investments!$B$2:$B$10000,$A59) -> 0 | D59: =SUMIFS(Capital_Investments!D$2:D$10000,Capital_Investments!$B$2:$B$10000,$A59) -> 0 | E59: =SUMIFS(Capital_Investments!E$2:E$10000,Capital_Investments!$B$2:$B$10000,$A59) -> 369 | F59: =SUMIFS(Capital_Investments!F$2:F$10000,Capital_Investments!$B$2:$B$10000,$A59) -> 27 | G59: =SUMIFS(Capital_Investments!G$2:G$10000,Capital_Investments!$B$2:$B$10000,$A59) -> 44.55 | H59: =SUMIFS(Capital_Investments!H$2:H$10000,Capital_Investments!$B$2:$B$10000,$A59) -> 0 | I59: =SUMIFS(Capital_Investments!I$2:I$10000,Capital_Investments!$B$2:$B$10000,$A59) -> 0 | J59: =SUMIFS(Capital_Investments!J$2:J$10000,Capital_Investments!$B$2:$B$10000,$A59) -> 0 | ... AG59: =SUMIFS(Capital_Investments!AG$2:AG$10000,Capital_Investments!$B$2:$B$10000,$A59) -> 0
A60: PHL_POW_CHP_COAL_OLD | C60: =SUMIFS(Capital_Investments!C$2:C$10000,Capital_Investments!$B$2:$B$10000,$A60) -> 0 | D60: =SUMIFS(Capital_Investments!D$2:D$10000,Capital_Investments!$B$2:$B$10000,$A60) -> 0 | E60: =SUMIFS(Capital_Investments!E$2:E$10000,Capital_Investments!$B$2:$B$10000,$A60) -> 0 | F60: =SUMIFS(Capital_Investments!F$2:F$10000,Capital_Investments!$B$2:$B$10000,$A60) -> 0 | G60: =SUMIFS(Capital_Investments!G$2:G$10000,Capital_Investments!$B$2:$B$10000,$A60) -> 0 | H60: =SUMIFS(Capital_Investments!H$2:H$10000,Capital_Investments!$B$2:$B$10000,$A60) -> 0 | I60: =SUMIFS(Capital_Investments!I$2:I$10000,Capital_Investments!$B$2:$B$10000,$A60) -> 0 | J60: =SUMIFS(Capital_Investments!J$2:J$10000,Capital_Investments!$B$2:$B$10000,$A60) -> 0 | ... AG60: =SUMIFS(Capital_Investments!AG$2:AG$10000,Capital_Investments!$B$2:$B$10000,$A60) -> 0
A61: PHL_POW_GEO_OLD | C61: =SUMIFS(Capital_Investments!C$2:C$10000,Capital_Investments!$B$2:$B$10000,$A61) -> 0 | D61: =SUMIFS(Capital_Investments!D$2:D$10000,Capital_Investments!$B$2:$B$10000,$A61) -> 0 | E61: =SUMIFS(Capital_Investments!E$2:E$10000,Capital_Investments!$B$2:$B$10000,$A61) -> 16.28 | F61: =SUMIFS(Capital_Investments!F$2:F$10000,Capital_Investments!$B$2:$B$10000,$A61) -> 1236.7766 | G61: =SUMIFS(Capital_Investments!G$2:G$10000,Capital_Investments!$B$2:$B$10000,$A61) -> 29.5789 | H61: =SUMIFS(Capital_Investments!H$2:H$10000,Capital_Investments!$B$2:$B$10000,$A61) -> 157.08 | I61: =SUMIFS(Capital_Investments!I$2:I$10000,Capital_Investments!$B$2:$B$10000,$A61) -> 3668.8451 | J61: =SUMIFS(Capital_Investments!J$2:J$10000,Capital_Investments!$B$2:$B$10000,$A61) -> 3695.1112 | ... AG61: =SUMIFS(Capital_Investments!AG$2:AG$10000,Capital_Investments!$B$2:$B$10000,$A61) -> 20.0948
A62: PHL_POW_PP_BIOM_CCS | C62: =SUMIFS(Capital_Investments!C$2:C$10000,Capital_Investments!$B$2:$B$10000,$A62) -> 0 | D62: =SUMIFS(Capital_Investments!D$2:D$10000,Capital_Investments!$B$2:$B$10000,$A62) -> 0 | E62: =SUMIFS(Capital_Investments!E$2:E$10000,Capital_Investments!$B$2:$B$10000,$A62) -> 0 | F62: =SUMIFS(Capital_Investments!F$2:F$10000,Capital_Investments!$B$2:$B$10000,$A62) -> 0 | G62: =SUMIFS(Capital_Investments!G$2:G$10000,Capital_Investments!$B$2:$B$10000,$A62) -> 0 | H62: =SUMIFS(Capital_Investments!H$2:H$10000,Capital_Investments!$B$2:$B$10000,$A62) -> 0 | I62: =SUMIFS(Capital_Investments!I$2:I$10000,Capital_Investments!$B$2:$B$10000,$A62) -> 0 | J62: =SUMIFS(Capital_Investments!J$2:J$10000,Capital_Investments!$B$2:$B$10000,$A62) -> 0 | ... AG62: =SUMIFS(Capital_Investments!AG$2:AG$10000,Capital_Investments!$B$2:$B$10000,$A62) -> 0
A63: PHL_POW_PP_COAL | C63: =SUMIFS(Capital_Investments!C$2:C$10000,Capital_Investments!$B$2:$B$10000,$A63) -> 0 | D63: =SUMIFS(Capital_Investments!D$2:D$10000,Capital_Investments!$B$2:$B$10000,$A63) -> 1595 | E63: =SUMIFS(Capital_Investments!E$2:E$10000,Capital_Investments!$B$2:$B$10000,$A63) -> 1692.68 | F63: =SUMIFS(Capital_Investments!F$2:F$10000,Capital_Investments!$B$2:$B$10000,$A63) -> 0 | G63: =SUMIFS(Capital_Investments!G$2:G$10000,Capital_Investments!$B$2:$B$10000,$A63) -> 1320 | H63: =SUMIFS(Capital_Investments!H$2:H$10000,Capital_Investments!$B$2:$B$10000,$A63) -> 0 | I63: =SUMIFS(Capital_Investments!I$2:I$10000,Capital_Investments!$B$2:$B$10000,$A63) -> 0 | J63: =SUMIFS(Capital_Investments!J$2:J$10000,Capital_Investments!$B$2:$B$10000,$A63) -> 0 | ... AG63: =SUMIFS(Capital_Investments!AG$2:AG$10000,Capital_Investments!$B$2:$B$10000,$A63) -> 0
A64: PHL_POW_PP_COAL_CCS | C64: =SUMIFS(Capital_Investments!C$2:C$10000,Capital_Investments!$B$2:$B$10000,$A64) -> 0 | D64: =SUMIFS(Capital_Investments!D$2:D$10000,Capital_Investments!$B$2:$B$10000,$A64) -> 0 | E64: =SUMIFS(Capital_Investments!E$2:E$10000,Capital_Investments!$B$2:$B$10000,$A64) -> 0 | F64: =SUMIFS(Capital_Investments!F$2:F$10000,Capital_Investments!$B$2:$B$10000,$A64) -> 0 | G64: =SUMIFS(Capital_Investments!G$2:G$10000,Capital_Investments!$B$2:$B$10000,$A64) -> 0 | H64: =SUMIFS(Capital_Investments!H$2:H$10000,Capital_Investments!$B$2:$B$10000,$A64) -> 0 | I64: =SUMIFS(Capital_Investments!I$2:I$10000,Capital_Investments!$B$2:$B$10000,$A64) -> 0 | J64: =SUMIFS(Capital_Investments!J$2:J$10000,Capital_Investments!$B$2:$B$10000,$A64) -> 0 | ... AG64: =SUMIFS(Capital_Investments!AG$2:AG$10000,Capital_Investments!$B$2:$B$10000,$A64) -> 0
A65: PHL_POW_PP_H2 | C65: =SUMIFS(Capital_Investments!C$2:C$10000,Capital_Investments!$B$2:$B$10000,$A65) -> 0 | D65: =SUMIFS(Capital_Investments!D$2:D$10000,Capital_Investments!$B$2:$B$10000,$A65) -> 0 | E65: =SUMIFS(Capital_Investments!E$2:E$10000,Capital_Investments!$B$2:$B$10000,$A65) -> 0 | F65: =SUMIFS(Capital_Investments!F$2:F$10000,Capital_Investments!$B$2:$B$10000,$A65) -> 0 | G65: =SUMIFS(Capital_Investments!G$2:G$10000,Capital_Investments!$B$2:$B$10000,$A65) -> 0 | H65: =SUMIFS(Capital_Investments!H$2:H$10000,Capital_Investments!$B$2:$B$10000,$A65) -> 0 | I65: =SUMIFS(Capital_Investments!I$2:I$10000,Capital_Investments!$B$2:$B$10000,$A65) -> 0 | J65: =SUMIFS(Capital_Investments!J$2:J$10000,Capital_Investments!$B$2:$B$10000,$A65) -> 0 | ... AG65: =SUMIFS(Capital_Investments!AG$2:AG$10000,Capital_Investments!$B$2:$B$10000,$A65) -> 0
A66: PHL_POW_PP_HY_LA | C66: =SUMIFS(Capital_Investments!C$2:C$10000,Capital_Investments!$B$2:$B$10000,$A66) -> 4389.9544 | D66: =SUMIFS(Capital_Investments!D$2:D$10000,Capital_Investments!$B$2:$B$10000,$A66) -> 7663.7159 | E66: =SUMIFS(Capital_Investments!E$2:E$10000,Capital_Investments!$B$2:$B$10000,$A66) -> 47.7 | F66: =SUMIFS(Capital_Investments!F$2:F$10000,Capital_Investments!$B$2:$B$10000,$A66) -> 140.4 | G66: =SUMIFS(Capital_Investments!G$2:G$10000,Capital_Investments!$B$2:$B$10000,$A66) -> 105.6 | H66: =SUMIFS(Capital_Investments!H$2:H$10000,Capital_Investments!$B$2:$B$10000,$A66) -> 0 | I66: =SUMIFS(Capital_Investments!I$2:I$10000,Capital_Investments!$B$2:$B$10000,$A66) -> 0 | J66: =SUMIFS(Capital_Investments!J$2:J$10000,Capital_Investments!$B$2:$B$10000,$A66) -> 0 | ... AG66: =SUMIFS(Capital_Investments!AG$2:AG$10000,Capital_Investments!$B$2:$B$10000,$A66) -> 0
A67: PHL_POW_PP_NGCC | C67: =SUMIFS(Capital_Investments!C$2:C$10000,Capital_Investments!$B$2:$B$10000,$A67) -> 0 | D67: =SUMIFS(Capital_Investments!D$2:D$10000,Capital_Investments!$B$2:$B$10000,$A67) -> 0 | E67: =SUMIFS(Capital_Investments!E$2:E$10000,Capital_Investments!$B$2:$B$10000,$A67) -> 0 | F67: =SUMIFS(Capital_Investments!F$2:F$10000,Capital_Investments!$B$2:$B$10000,$A67) -> 0 | G67: =SUMIFS(Capital_Investments!G$2:G$10000,Capital_Investments!$B$2:$B$10000,$A67) -> 0 | H67: =SUMIFS(Capital_Investments!H$2:H$10000,Capital_Investments!$B$2:$B$10000,$A67) -> 1056 | I67: =SUMIFS(Capital_Investments!I$2:I$10000,Capital_Investments!$B$2:$B$10000,$A67) -> 0 | J67: =SUMIFS(Capital_Investments!J$2:J$10000,Capital_Investments!$B$2:$B$10000,$A67) -> 0 | ... AG67: =SUMIFS(Capital_Investments!AG$2:AG$10000,Capital_Investments!$B$2:$B$10000,$A67) -> 4144.2266
A68: PHL_POW_PP_NGCC_CCS | C68: =SUMIFS(Capital_Investments!C$2:C$10000,Capital_Investments!$B$2:$B$10000,$A68) -> 0 | D68: =SUMIFS(Capital_Investments!D$2:D$10000,Capital_Investments!$B$2:$B$10000,$A68) -> 0 | E68: =SUMIFS(Capital_Investments!E$2:E$10000,Capital_Investments!$B$2:$B$10000,$A68) -> 0 | F68: =SUMIFS(Capital_Investments!F$2:F$10000,Capital_Investments!$B$2:$B$10000,$A68) -> 0 | G68: =SUMIFS(Capital_Investments!G$2:G$10000,Capital_Investments!$B$2:$B$10000,$A68) -> 0 | H68: =SUMIFS(Capital_Investments!H$2:H$10000,Capital_Investments!$B$2:$B$10000,$A68) -> 0 | I68: =SUMIFS(Capital_Investments!I$2:I$10000,Capital_Investments!$B$2:$B$10000,$A68) -> 0 | J68: =SUMIFS(Capital_Investments!J$2:J$10000,Capital_Investments!$B$2:$B$10000,$A68) -> 0 | ... AG68: =SUMIFS(Capital_Investments!AG$2:AG$10000,Capital_Investments!$B$2:$B$10000,$A68) -> 0
A69: PHL_POW_PP_NU | C69: =SUMIFS(Capital_Investments!C$2:C$10000,Capital_Investments!$B$2:$B$10000,$A69) -> 0 | D69: =SUMIFS(Capital_Investments!D$2:D$10000,Capital_Investments!$B$2:$B$10000,$A69) -> 0 | E69: =SUMIFS(Capital_Investments!E$2:E$10000,Capital_Investments!$B$2:$B$10000,$A69) -> 0 | F69: =SUMIFS(Capital_Investments!F$2:F$10000,Capital_Investments!$B$2:$B$10000,$A69) -> 0 | G69: =SUMIFS(Capital_Investments!G$2:G$10000,Capital_Investments!$B$2:$B$10000,$A69) -> 0 | H69: =SUMIFS(Capital_Investments!H$2:H$10000,Capital_Investments!$B$2:$B$10000,$A69) -> 0 | I69: =SUMIFS(Capital_Investments!I$2:I$10000,Capital_Investments!$B$2:$B$10000,$A69) -> 0 | J69: =SUMIFS(Capital_Investments!J$2:J$10000,Capital_Investments!$B$2:$B$10000,$A69) -> 0 | ... AG69: =SUMIFS(Capital_Investments!AG$2:AG$10000,Capital_Investments!$B$2:$B$10000,$A69) -> 0
A70: PHL_POW_PP_NUSMR | C70: =SUMIFS(Capital_Investments!C$2:C$10000,Capital_Investments!$B$2:$B$10000,$A70) -> 0 | D70: =SUMIFS(Capital_Investments!D$2:D$10000,Capital_Investments!$B$2:$B$10000,$A70) -> 0 | E70: =SUMIFS(Capital_Investments!E$2:E$10000,Capital_Investments!$B$2:$B$10000,$A70) -> 0 | F70: =SUMIFS(Capital_Investments!F$2:F$10000,Capital_Investments!$B$2:$B$10000,$A70) -> 0 | G70: =SUMIFS(Capital_Investments!G$2:G$10000,Capital_Investments!$B$2:$B$10000,$A70) -> 0 | H70: =SUMIFS(Capital_Investments!H$2:H$10000,Capital_Investments!$B$2:$B$10000,$A70) -> 0 | I70: =SUMIFS(Capital_Investments!I$2:I$10000,Capital_Investments!$B$2:$B$10000,$A70) -> 0 | J70: =SUMIFS(Capital_Investments!J$2:J$10000,Capital_Investments!$B$2:$B$10000,$A70) -> 0 | ... AG70: =SUMIFS(Capital_Investments!AG$2:AG$10000,Capital_Investments!$B$2:$B$10000,$A70) -> 0
... A76: PHL_POW_TD | C76: =SUMIFS(Capital_Investments!C$2:C$10000,Capital_Investments!$B$2:$B$10000,$A76) -> 0 | D76: =SUMIFS(Capital_Investments!D$2:D$10000,Capital_Investments!$B$2:$B$10000,$A76) -> 0 | E76: =SUMIFS(Capital_Investments!E$2:E$10000,Capital_Investments!$B$2:$B$10000,$A76) -> 0 | F76: =SUMIFS(Capital_Investments!F$2:F$10000,Capital_Investments!$B$2:$B$10000,$A76) -> 0 | G76: =SUMIFS(Capital_Investments!G$2:G$10000,Capital_Investments!$B$2:$B$10000,$A76) -> 0 | H76: =SUMIFS(Capital_Investments!H$2:H$10000,Capital_Investments!$B$2:$B$10000,$A76) -> 459.6972 | I76: =SUMIFS(Capital_Investments!I$2:I$10000,Capital_Investments!$B$2:$B$10000,$A76) -> 1316.7722 | J76: =SUMIFS(Capital_Investments!J$2:J$10000,Capital_Investments!$B$2:$B$10000,$A76) -> 1316.7722 | ... AG76: =SUMIFS(Capital_Investments!AG$2:AG$10000,Capital_Investments!$B$2:$B$10000,$A76) -> 3100.4506
A79: Annualized Investment Cost (M.USD) | C79: 2020 | D79: 2021 | E79: 2022 | F79: 2023 | G79: 2024 | H79: 2025 | I79: 2026 | J79: 2027 | K79: 2028 | L79: 2029 | M79: 2030 | N79: 2031 | O79: 2032 | P79: 2033 | Q79: 2034 | R79: 2035 | S79: 2036 | T79: 2037 | U79: 2038 | V79: 2039 | W79: 2040 | X79: 2041 | Y79: 2042 | Z79: 2043 | AA79: 2044 | AB79: 2045 | AC79: 2046 | AD79: 2047 | AE79: 2048 | AF79: 2049 | AG79: 2050
A80: PHL_POW_CHP_BIOM_OLD | C80: =SUMIFS(Annualized_Investments!C$2:C$9989,Annualized_Investments!$B$2:$B$9989,$A80) -> 0 | D80: =SUMIFS(Annualized_Investments!D$2:D$9989,Annualized_Investments!$B$2:$B$9989,$A80) -> 0 | E80: =SUMIFS(Annualized_Investments!E$2:E$9989,Annualized_Investments!$B$2:$B$9989,$A80) -> 20.480611 | F80: =SUMIFS(Annualized_Investments!F$2:F$9989,Annualized_Investments!$B$2:$B$9989,$A80) -> 21.979192 | G80: =SUMIFS(Annualized_Investments!G$2:G$9989,Annualized_Investments!$B$2:$B$9989,$A80) -> 24.451851 | H80: =SUMIFS(Annualized_Investments!H$2:H$9989,Annualized_Investments!$B$2:$B$9989,$A80) -> 24.451851 | I80: =SUMIFS(Annualized_Investments!I$2:I$9989,Annualized_Investments!$B$2:$B$9989,$A80) -> 24.451851 | J80: =SUMIFS(Annualized_Investments!J$2:J$9989,Annualized_Investments!$B$2:$B$9989,$A80) -> 24.451851 | ... AG80: =SUMIFS(Annualized_Investments!AG$2:AG$9989,Annualized_Investments!$B$2:$B$9989,$A80) -> 24.451851
A81: PHL_POW_CHP_COAL_OLD | C81: =SUMIFS(Annualized_Investments!C$2:C$9989,Annualized_Investments!$B$2:$B$9989,$A81) -> 0 | D81: =SUMIFS(Annualized_Investments!D$2:D$9989,Annualized_Investments!$B$2:$B$9989,$A81) -> 0 | E81: =SUMIFS(Annualized_Investments!E$2:E$9989,Annualized_Investments!$B$2:$B$9989,$A81) -> 0 | F81: =SUMIFS(Annualized_Investments!F$2:F$9989,Annualized_Investments!$B$2:$B$9989,$A81) -> 0 | G81: =SUMIFS(Annualized_Investments!G$2:G$9989,Annualized_Investments!$B$2:$B$9989,$A81) -> 0 | H81: =SUMIFS(Annualized_Investments!H$2:H$9989,Annualized_Investments!$B$2:$B$9989,$A81) -> 0 | I81: =SUMIFS(Annualized_Investments!I$2:I$9989,Annualized_Investments!$B$2:$B$9989,$A81) -> 0 | J81: =SUMIFS(Annualized_Investments!J$2:J$9989,Annualized_Investments!$B$2:$B$9989,$A81) -> 0 | ... AG81: =SUMIFS(Annualized_Investments!AG$2:AG$9989,Annualized_Investments!$B$2:$B$9989,$A81) -> 0
A82: PHL_POW_GEO_OLD | C82: =SUMIFS(Annualized_Investments!C$2:C$9989,Annualized_Investments!$B$2:$B$9989,$A82) -> 0 | D82: =SUMIFS(Annualized_Investments!D$2:D$9989,Annualized_Investments!$B$2:$B$9989,$A82) -> 0 | E82: =SUMIFS(Annualized_Investments!E$2:E$9989,Annualized_Investments!$B$2:$B$9989,$A82) -> 0.90358901 | F82: =SUMIFS(Annualized_Investments!F$2:F$9989,Annualized_Investments!$B$2:$B$9989,$A82) -> 69.548414 | G82: =SUMIFS(Annualized_Investments!G$2:G$9989,Annualized_Investments!$B$2:$B$9989,$A82) -> 71.190132 | H82: =SUMIFS(Annualized_Investments!H$2:H$9989,Annualized_Investments!$B$2:$B$9989,$A82) -> 79.908545 | I82: =SUMIFS(Annualized_Investments!I$2:I$9989,Annualized_Investments!$B$2:$B$9989,$A82) -> 283.54049 | J82: =SUMIFS(Annualized_Investments!J$2:J$9989,Annualized_Investments!$B$2:$B$9989,$A82) -> 488.63029 | ... AG82: =SUMIFS(Annualized_Investments!AG$2:AG$9989,Annualized_Investments!$B$2:$B$9989,$A82) -> 956.97402
A83: PHL_POW_PP_BIOM_CCS | C83: =SUMIFS(Annualized_Investments!C$2:C$9989,Annualized_Investments!$B$2:$B$9989,$A83) -> 0 | D83: =SUMIFS(Annualized_Investments!D$2:D$9989,Annualized_Investments!$B$2:$B$9989,$A83) -> 0 | E83: =SUMIFS(Annualized_Investments!E$2:E$9989,Annualized_Investments!$B$2:$B$9989,$A83) -> 0 | F83: =SUMIFS(Annualized_Investments!F$2:F$9989,Annualized_Investments!$B$2:$B$9989,$A83) -> 0 | G83: =SUMIFS(Annualized_Investments!G$2:G$9989,Annualized_Investments!$B$2:$B$9989,$A83) -> 0 | H83: =SUMIFS(Annualized_Investments!H$2:H$9989,Annualized_Investments!$B$2:$B$9989,$A83) -> 0 | I83: =SUMIFS(Annualized_Investments!I$2:I$9989,Annualized_Investments!$B$2:$B$9989,$A83) -> 0 | J83: =SUMIFS(Annualized_Investments!J$2:J$9989,Annualized_Investments!$B$2:$B$9989,$A83) -> 0 | ... AG83: =SUMIFS(Annualized_Investments!AG$2:AG$9989,Annualized_Investments!$B$2:$B$9989,$A83) -> 0
A84: PHL_POW_PP_COAL | C84: =SUMIFS(Annualized_Investments!C$2:C$9989,Annualized_Investments!$B$2:$B$9989,$A84) -> 0 | D84: =SUMIFS(Annualized_Investments!D$2:D$9989,Annualized_Investments!$B$2:$B$9989,$A84) -> 107.78016 | E84: =SUMIFS(Annualized_Investments!E$2:E$9989,Annualized_Investments!$B$2:$B$9989,$A84) -> 222.16093 | F84: =SUMIFS(Annualized_Investments!F$2:F$9989,Annualized_Investments!$B$2:$B$9989,$A84) -> 222.16093 | G84: =SUMIFS(Annualized_Investments!G$2:G$9989,Annualized_Investments!$B$2:$B$9989,$A84) -> 311.3583 | H84: =SUMIFS(Annualized_Investments!H$2:H$9989,Annualized_Investments!$B$2:$B$9989,$A84) -> 311.3583 | I84: =SUMIFS(Annualized_Investments!I$2:I$9989,Annualized_Investments!$B$2:$B$9989,$A84) -> 311.3583 | J84: =SUMIFS(Annualized_Investments!J$2:J$9989,Annualized_Investments!$B$2:$B$9989,$A84) -> 311.3583 | ... AG84: =SUMIFS(Annualized_Investments!AG$2:AG$9989,Annualized_Investments!$B$2:$B$9989,$A84) -> 3898.5044
A85: PHL_POW_PP_COAL_CCS | C85: =SUMIFS(Annualized_Investments!C$2:C$9989,Annualized_Investments!$B$2:$B$9989,$A85) -> 0 | D85: =SUMIFS(Annualized_Investments!D$2:D$9989,Annualized_Investments!$B$2:$B$9989,$A85) -> 0 | E85: =SUMIFS(Annualized_Investments!E$2:E$9989,Annualized_Investments!$B$2:$B$9989,$A85) -> 0 | F85: =SUMIFS(Annualized_Investments!F$2:F$9989,Annualized_Investments!$B$2:$B$9989,$A85) -> 0 | G85: =SUMIFS(Annualized_Investments!G$2:G$9989,Annualized_Investments!$B$2:$B$9989,$A85) -> 0 | H85: =SUMIFS(Annualized_Investments!H$2:H$9989,Annualized_Investments!$B$2:$B$9989,$A85) -> 0 | I85: =SUMIFS(Annualized_Investments!I$2:I$9989,Annualized_Investments!$B$2:$B$9989,$A85) -> 0 | J85: =SUMIFS(Annualized_Investments!J$2:J$9989,Annualized_Investments!$B$2:$B$9989,$A85) -> 0 | ... AG85: =SUMIFS(Annualized_Investments!AG$2:AG$9989,Annualized_Investments!$B$2:$B$9989,$A85) -> 0
A86: PHL_POW_PP_H2 | C86: =SUMIFS(Annualized_Investments!C$2:C$9989,Annualized_Investments!$B$2:$B$9989,$A86) -> 0 | D86: =SUMIFS(Annualized_Investments!D$2:D$9989,Annualized_Investments!$B$2:$B$9989,$A86) -> 0 | E86: =SUMIFS(Annualized_Investments!E$2:E$9989,Annualized_Investments!$B$2:$B$9989,$A86) -> 0 | F86: =SUMIFS(Annualized_Investments!F$2:F$9989,Annualized_Investments!$B$2:$B$9989,$A86) -> 0 | G86: =SUMIFS(Annualized_Investments!G$2:G$9989,Annualized_Investments!$B$2:$B$9989,$A86) -> 0 | H86: =SUMIFS(Annualized_Investments!H$2:H$9989,Annualized_Investments!$B$2:$B$9989,$A86) -> 0 | I86: =SUMIFS(Annualized_Investments!I$2:I$9989,Annualized_Investments!$B$2:$B$9989,$A86) -> 0 | J86: =SUMIFS(Annualized_Investments!J$2:J$9989,Annualized_Investments!$B$2:$B$9989,$A86) -> 0 | ... AG86: =SUMIFS(Annualized_Investments!AG$2:AG$9989,Annualized_Investments!$B$2:$B$9989,$A86) -> 0
A87: PHL_POW_PP_HY_LA | C87: =SUMIFS(Annualized_Investments!C$2:C$9989,Annualized_Investments!$B$2:$B$9989,$A87) -> 210.64731 | D87: =SUMIFS(Annualized_Investments!D$2:D$9989,Annualized_Investments!$B$2:$B$9989,$A87) -> 578.3826 | E87: =SUMIFS(Annualized_Investments!E$2:E$9989,Annualized_Investments!$B$2:$B$9989,$A87) -> 580.67144 | F87: =SUMIFS(Annualized_Investments!F$2:F$9989,Annualized_Investments!$B$2:$B$9989,$A87) -> 587.40838 | G87: =SUMIFS(Annualized_Investments!G$2:G$9989,Annualized_Investments!$B$2:$B$9989,$A87) -> 592.47549 | H87: =SUMIFS(Annualized_Investments!H$2:H$9989,Annualized_Investments!$B$2:$B$9989,$A87) -> 592.47549 | I87: =SUMIFS(Annualized_Investments!I$2:I$9989,Annualized_Investments!$B$2:$B$9989,$A87) -> 592.47549 | J87: =SUMIFS(Annualized_Investments!J$2:J$9989,Annualized_Investments!$B$2:$B$9989,$A87) -> 592.47549 | ... AG87: =SUMIFS(Annualized_Investments!AG$2:AG$9989,Annualized_Investments!$B$2:$B$9989,$A87) -> 592.47549
A88: PHL_POW_PP_NGCC | C88: =SUMIFS(Annualized_Investments!C$2:C$9989,Annualized_Investments!$B$2:$B$9989,$A88) -> 0 | D88: =SUMIFS(Annualized_Investments!D$2:D$9989,Annualized_Investments!$B$2:$B$9989,$A88) -> 0 | E88: =SUMIFS(Annualized_Investments!E$2:E$9989,Annualized_Investments!$B$2:$B$9989,$A88) -> 0 | F88: =SUMIFS(Annualized_Investments!F$2:F$9989,Annualized_Investments!$B$2:$B$9989,$A88) -> 0 | G88: =SUMIFS(Annualized_Investments!G$2:G$9989,Annualized_Investments!$B$2:$B$9989,$A88) -> 0 | H88: =SUMIFS(Annualized_Investments!H$2:H$9989,Annualized_Investments!$B$2:$B$9989,$A88) -> 71.3579 | I88: =SUMIFS(Annualized_Investments!I$2:I$9989,Annualized_Investments!$B$2:$B$9989,$A88) -> 71.3579 | J88: =SUMIFS(Annualized_Investments!J$2:J$9989,Annualized_Investments!$B$2:$B$9989,$A88) -> 71.3579 | ... AG88: =SUMIFS(Annualized_Investments!AG$2:AG$9989,Annualized_Investments!$B$2:$B$9989,$A88) -> 832.4559
A89: PHL_POW_PP_NGCC_CCS | C89: =SUMIFS(Annualized_Investments!C$2:C$9989,Annualized_Investments!$B$2:$B$9989,$A89) -> 0 | D89: =SUMIFS(Annualized_Investments!D$2:D$9989,Annualized_Investments!$B$2:$B$9989,$A89) -> 0 | E89: =SUMIFS(Annualized_Investments!E$2:E$9989,Annualized_Investments!$B$2:$B$9989,$A89) -> 0 | F89: =SUMIFS(Annualized_Investments!F$2:F$9989,Annualized_Investments!$B$2:$B$9989,$A89) -> 0 | G89: =SUMIFS(Annualized_Investments!G$2:G$9989,Annualized_Investments!$B$2:$B$9989,$A89) -> 0 | H89: =SUMIFS(Annualized_Investments!H$2:H$9989,Annualized_Investments!$B$2:$B$9989,$A89) -> 0 | I89: =SUMIFS(Annualized_Investments!I$2:I$9989,Annualized_Investments!$B$2:$B$9989,$A89) -> 0 | J89: =SUMIFS(Annualized_Investments!J$2:J$9989,Annualized_Investments!$B$2:$B$9989,$A89) -> 0 | ... AG89: =SUMIFS(Annualized_Investments!AG$2:AG$9989,Annualized_Investments!$B$2:$B$9989,$A89) -> 0
A90: PHL_POW_PP_NU | C90: =SUMIFS(Annualized_Investments!C$2:C$9989,Annualized_Investments!$B$2:$B$9989,$A90) -> 0 | D90: =SUMIFS(Annualized_Investments!D$2:D$9989,Annualized_Investments!$B$2:$B$9989,$A90) -> 0 | E90: =SUMIFS(Annualized_Investments!E$2:E$9989,Annualized_Investments!$B$2:$B$9989,$A90) -> 0 | F90: =SUMIFS(Annualized_Investments!F$2:F$9989,Annualized_Investments!$B$2:$B$9989,$A90) -> 0 | G90: =SUMIFS(Annualized_Investments!G$2:G$9989,Annualized_Investments!$B$2:$B$9989,$A90) -> 0 | H90: =SUMIFS(Annualized_Investments!H$2:H$9989,Annualized_Investments!$B$2:$B$9989,$A90) -> 0 | I90: =SUMIFS(Annualized_Investments!I$2:I$9989,Annualized_Investments!$B$2:$B$9989,$A90) -> 0 | J90: =SUMIFS(Annualized_Investments!J$2:J$9989,Annualized_Investments!$B$2:$B$9989,$A90) -> 0 | ... AG90: =SUMIFS(Annualized_Investments!AG$2:AG$9989,Annualized_Investments!$B$2:$B$9989,$A90) -> 0
A91: PHL_POW_PP_NUSMR | C91: =SUMIFS(Annualized_Investments!C$2:C$9989,Annualized_Investments!$B$2:$B$9989,$A91) -> 0 | D91: =SUMIFS(Annualized_Investments!D$2:D$9989,Annualized_Investments!$B$2:$B$9989,$A91) -> 0 | E91: =SUMIFS(Annualized_Investments!E$2:E$9989,Annualized_Investments!$B$2:$B$9989,$A91) -> 0 | F91: =SUMIFS(Annualized_Investments!F$2:F$9989,Annualized_Investments!$B$2:$B$9989,$A91) -> 0 | G91: =SUMIFS(Annualized_Investments!G$2:G$9989,Annualized_Investments!$B$2:$B$9989,$A91) -> 0 | H91: =SUMIFS(Annualized_Investments!H$2:H$9989,Annualized_Investments!$B$2:$B$9989,$A91) -> 0 | I91: =SUMIFS(Annualized_Investments!I$2:I$9989,Annualized_Investments!$B$2:$B$9989,$A91) -> 0 | J91: =SUMIFS(Annualized_Investments!J$2:J$9989,Annualized_Investments!$B$2:$B$9989,$A91) -> 0 | ... AG91: =SUMIFS(Annualized_Investments!AG$2:AG$9989,Annualized_Investments!$B$2:$B$9989,$A91) -> 0
... A97: PHL_POW_TD | C97: =SUMIFS(Annualized_Investments!C$2:C$9989,Annualized_Investments!$B$2:$B$9989,$A97) -> 0 | D97: =SUMIFS(Annualized_Investments!D$2:D$9989,Annualized_Investments!$B$2:$B$9989,$A97) -> 0 | E97: =SUMIFS(Annualized_Investments!E$2:E$9989,Annualized_Investments!$B$2:$B$9989,$A97) -> 0 | F97: =SUMIFS(Annualized_Investments!F$2:F$9989,Annualized_Investments!$B$2:$B$9989,$A97) -> 0 | G97: =SUMIFS(Annualized_Investments!G$2:G$9989,Annualized_Investments!$B$2:$B$9989,$A97) -> 0 | H97: =SUMIFS(Annualized_Investments!H$2:H$9989,Annualized_Investments!$B$2:$B$9989,$A97) -> 23.98163 | I97: =SUMIFS(Annualized_Investments!I$2:I$9989,Annualized_Investments!$B$2:$B$9989,$A97) -> 92.675423 | J97: =SUMIFS(Annualized_Investments!J$2:J$9989,Annualized_Investments!$B$2:$B$9989,$A97) -> 161.36922 | ... AG97: =SUMIFS(Annualized_Investments!AG$2:AG$9989,Annualized_Investments!$B$2:$B$9989,$A97) -> 2425.2209
A100: Annual Production by Technology (PJ) | C100: 2020 | D100: 2021 | E100: 2022 | F100: 2023 | G100: 2024 | H100: 2025 | I100: 2026 | J100: 2027 | K100: 2028 | L100: 2029 | M100: 2030 | N100: 2031 | O100: 2032 | P100: 2033 | Q100: 2034 | R100: 2035 | S100: 2036 | T100: 2037 | U100: 2038 | V100: 2039 | W100: 2040 | X100: 2041 | Y100: 2042 | Z100: 2043 | AA100: 2044 | AB100: 2045 | AC100: 2046 | AD100: 2047 | AE100: 2048 | AF100: 2049 | AG100: 2050
A101: PHL_POW_CHP_BIOM_OLD | C101: =SUMIFS(AnnualProduction!D$2:D$9923,AnnualProduction!$B$2:$B$9923,$A101) -> 4.5001 | D101: =SUMIFS(AnnualProduction!E$2:E$9923,AnnualProduction!$B$2:$B$9923,$A101) -> 5.2021 | E101: =SUMIFS(AnnualProduction!F$2:F$9923,AnnualProduction!$B$2:$B$9923,$A101) -> 4.7592 | F101: =SUMIFS(AnnualProduction!G$2:G$9923,AnnualProduction!$B$2:$B$9923,$A101) -> 5.072 | G101: =SUMIFS(AnnualProduction!H$2:H$9923,AnnualProduction!$B$2:$B$9923,$A101) -> 5.2059 | H101: =SUMIFS(AnnualProduction!I$2:I$9923,AnnualProduction!$B$2:$B$9923,$A101) -> 0 | I101: =SUMIFS(AnnualProduction!J$2:J$9923,AnnualProduction!$B$2:$B$9923,$A101) -> 0 | J101: =SUMIFS(AnnualProduction!K$2:K$9923,AnnualProduction!$B$2:$B$9923,$A101) -> 0 | ... AG101: =SUMIFS(AnnualProduction!AH$2:AH$9923,AnnualProduction!$B$2:$B$9923,$A101) -> 1.1186
A102: PHL_POW_CHP_COAL_OLD | C102: =SUMIFS(AnnualProduction!D$2:D$9923,AnnualProduction!$B$2:$B$9923,$A102) -> 209.4481 | D102: =SUMIFS(AnnualProduction!E$2:E$9923,AnnualProduction!$B$2:$B$9923,$A102) -> 223.3868 | E102: =SUMIFS(AnnualProduction!F$2:F$9923,AnnualProduction!$B$2:$B$9923,$A102) -> 239.1476 | F102: =SUMIFS(AnnualProduction!G$2:G$9923,AnnualProduction!$B$2:$B$9923,$A102) -> 265.5137 | G102: =SUMIFS(AnnualProduction!H$2:H$9923,AnnualProduction!$B$2:$B$9923,$A102) -> 285.6921 | H102: =SUMIFS(AnnualProduction!I$2:I$9923,AnnualProduction!$B$2:$B$9923,$A102) -> 262.5129 | I102: =SUMIFS(AnnualProduction!J$2:J$9923,AnnualProduction!$B$2:$B$9923,$A102) -> 258.4477 | J102: =SUMIFS(AnnualProduction!K$2:K$9923,AnnualProduction!$B$2:$B$9923,$A102) -> 254.247 | ... AG102: =SUMIFS(AnnualProduction!AH$2:AH$9923,AnnualProduction!$B$2:$B$9923,$A102) -> 100.4414
A103: PHL_POW_GEO_OLD | C103: =SUMIFS(AnnualProduction!D$2:D$9923,AnnualProduction!$B$2:$B$9923,$A103) -> 38.8084 | D103: =SUMIFS(AnnualProduction!E$2:E$9923,AnnualProduction!$B$2:$B$9923,$A103) -> 36.0582 | E103: =SUMIFS(AnnualProduction!F$2:F$9923,AnnualProduction!$B$2:$B$9923,$A103) -> 37.5303 | F103: =SUMIFS(AnnualProduction!G$2:G$9923,AnnualProduction!$B$2:$B$9923,$A103) -> 38.628 | G103: =SUMIFS(AnnualProduction!H$2:H$9923,AnnualProduction!$B$2:$B$9923,$A103) -> 38.8398 | H103: =SUMIFS(AnnualProduction!I$2:I$9923,AnnualProduction!$B$2:$B$9923,$A103) -> 39.9666 | I103: =SUMIFS(AnnualProduction!J$2:J$9923,AnnualProduction!$B$2:$B$9923,$A103) -> 66.261 | J103: =SUMIFS(AnnualProduction!K$2:K$9923,AnnualProduction!$B$2:$B$9923,$A103) -> 92.745 | ... AG103: =SUMIFS(AnnualProduction!AH$2:AH$9923,AnnualProduction!$B$2:$B$9923,$A103) -> 126.0005
A104: PHL_POW_PP_BIOM_CCS | C104: =SUMIFS(AnnualProduction!D$2:D$9923,AnnualProduction!$B$2:$B$9923,$A104) -> 0 | D104: =SUMIFS(AnnualProduction!E$2:E$9923,AnnualProduction!$B$2:$B$9923,$A104) -> 0 | E104: =SUMIFS(AnnualProduction!F$2:F$9923,AnnualProduction!$B$2:$B$9923,$A104) -> 0 | F104: =SUMIFS(AnnualProduction!G$2:G$9923,AnnualProduction!$B$2:$B$9923,$A104) -> 0 | G104: =SUMIFS(AnnualProduction!H$2:H$9923,AnnualProduction!$B$2:$B$9923,$A104) -> 0 | H104: =SUMIFS(AnnualProduction!I$2:I$9923,AnnualProduction!$B$2:$B$9923,$A104) -> 0 | I104: =SUMIFS(AnnualProduction!J$2:J$9923,AnnualProduction!$B$2:$B$9923,$A104) -> 0 | J104: =SUMIFS(AnnualProduction!K$2:K$9923,AnnualProduction!$B$2:$B$9923,$A104) -> 0 | ... AG104: =SUMIFS(AnnualProduction!AH$2:AH$9923,AnnualProduction!$B$2:$B$9923,$A104) -> 0
A105: PHL_POW_PP_COAL | C105: =SUMIFS(AnnualProduction!D$2:D$9923,AnnualProduction!$B$2:$B$9923,$A105) -> 0 | D105: =SUMIFS(AnnualProduction!E$2:E$9923,AnnualProduction!$B$2:$B$9923,$A105) -> 0 | E105: =SUMIFS(AnnualProduction!F$2:F$9923,AnnualProduction!$B$2:$B$9923,$A105) -> 0 | F105: =SUMIFS(AnnualProduction!G$2:G$9923,AnnualProduction!$B$2:$B$9923,$A105) -> 0 | G105: =SUMIFS(AnnualProduction!H$2:H$9923,AnnualProduction!$B$2:$B$9923,$A105) -> 0 | H105: =SUMIFS(AnnualProduction!I$2:I$9923,AnnualProduction!$B$2:$B$9923,$A105) -> 66.0492 | I105: =SUMIFS(AnnualProduction!J$2:J$9923,AnnualProduction!$B$2:$B$9923,$A105) -> 66.0492 | J105: =SUMIFS(AnnualProduction!K$2:K$9923,AnnualProduction!$B$2:$B$9923,$A105) -> 66.0492 | ... AG105: =SUMIFS(AnnualProduction!AH$2:AH$9923,AnnualProduction!$B$2:$B$9923,$A105) -> 576.2554
A106: PHL_POW_PP_COAL_CCS | C106: =SUMIFS(AnnualProduction!D$2:D$9923,AnnualProduction!$B$2:$B$9923,$A106) -> 0 | D106: =SUMIFS(AnnualProduction!E$2:E$9923,AnnualProduction!$B$2:$B$9923,$A106) -> 0 | E106: =SUMIFS(AnnualProduction!F$2:F$9923,AnnualProduction!$B$2:$B$9923,$A106) -> 0 | F106: =SUMIFS(AnnualProduction!G$2:G$9923,AnnualProduction!$B$2:$B$9923,$A106) -> 0 | G106: =SUMIFS(AnnualProduction!H$2:H$9923,AnnualProduction!$B$2:$B$9923,$A106) -> 0 | H106: =SUMIFS(AnnualProduction!I$2:I$9923,AnnualProduction!$B$2:$B$9923,$A106) -> 0 | I106: =SUMIFS(AnnualProduction!J$2:J$9923,AnnualProduction!$B$2:$B$9923,$A106) -> 0 | J106: =SUMIFS(AnnualProduction!K$2:K$9923,AnnualProduction!$B$2:$B$9923,$A106) -> 0 | ... AG106: =SUMIFS(AnnualProduction!AH$2:AH$9923,AnnualProduction!$B$2:$B$9923,$A106) -> 0
A107: PHL_POW_PP_H2 | C107: =SUMIFS(AnnualProduction!D$2:D$9923,AnnualProduction!$B$2:$B$9923,$A107) -> 0 | D107: =SUMIFS(AnnualProduction!E$2:E$9923,AnnualProduction!$B$2:$B$9923,$A107) -> 0 | E107: =SUMIFS(AnnualProduction!F$2:F$9923,AnnualProduction!$B$2:$B$9923,$A107) -> 0 | F107: =SUMIFS(AnnualProduction!G$2:G$9923,AnnualProduction!$B$2:$B$9923,$A107) -> 0 | G107: =SUMIFS(AnnualProduction!H$2:H$9923,AnnualProduction!$B$2:$B$9923,$A107) -> 0 | H107: =SUMIFS(AnnualProduction!I$2:I$9923,AnnualProduction!$B$2:$B$9923,$A107) -> 0 | I107: =SUMIFS(AnnualProduction!J$2:J$9923,AnnualProduction!$B$2:$B$9923,$A107) -> 0 | J107: =SUMIFS(AnnualProduction!K$2:K$9923,AnnualProduction!$B$2:$B$9923,$A107) -> 0 | ... AG107: =SUMIFS(AnnualProduction!AH$2:AH$9923,AnnualProduction!$B$2:$B$9923,$A107) -> 0
A108: PHL_POW_PP_HY_LA | C108: =SUMIFS(AnnualProduction!D$2:D$9923,AnnualProduction!$B$2:$B$9923,$A108) -> 25.8852 | D108: =SUMIFS(AnnualProduction!E$2:E$9923,AnnualProduction!$B$2:$B$9923,$A108) -> 33.0658 | E108: =SUMIFS(AnnualProduction!F$2:F$9923,AnnualProduction!$B$2:$B$9923,$A108) -> 36.3061 | F108: =SUMIFS(AnnualProduction!G$2:G$9923,AnnualProduction!$B$2:$B$9923,$A108) -> 37.0338 | G108: =SUMIFS(AnnualProduction!H$2:H$9923,AnnualProduction!$B$2:$B$9923,$A108) -> 39.2718 | H108: =SUMIFS(AnnualProduction!I$2:I$9923,AnnualProduction!$B$2:$B$9923,$A108) -> 39.2718 | I108: =SUMIFS(AnnualProduction!J$2:J$9923,AnnualProduction!$B$2:$B$9923,$A108) -> 39.2718 | J108: =SUMIFS(AnnualProduction!K$2:K$9923,AnnualProduction!$B$2:$B$9923,$A108) -> 39.2718 | ... AG108: =SUMIFS(AnnualProduction!AH$2:AH$9923,AnnualProduction!$B$2:$B$9923,$A108) -> 39.1566
A109: PHL_POW_PP_NGCC | C109: =SUMIFS(AnnualProduction!D$2:D$9923,AnnualProduction!$B$2:$B$9923,$A109) -> 0 | D109: =SUMIFS(AnnualProduction!E$2:E$9923,AnnualProduction!$B$2:$B$9923,$A109) -> 0 | E109: =SUMIFS(AnnualProduction!F$2:F$9923,AnnualProduction!$B$2:$B$9923,$A109) -> 0 | F109: =SUMIFS(AnnualProduction!G$2:G$9923,AnnualProduction!$B$2:$B$9923,$A109) -> 0 | G109: =SUMIFS(AnnualProduction!H$2:H$9923,AnnualProduction!$B$2:$B$9923,$A109) -> 0 | H109: =SUMIFS(AnnualProduction!I$2:I$9923,AnnualProduction!$B$2:$B$9923,$A109) -> 5.5426 | I109: =SUMIFS(AnnualProduction!J$2:J$9923,AnnualProduction!$B$2:$B$9923,$A109) -> 5.6578 | J109: =SUMIFS(AnnualProduction!K$2:K$9923,AnnualProduction!$B$2:$B$9923,$A109) -> 5.7598 | ... AG109: =SUMIFS(AnnualProduction!AH$2:AH$9923,AnnualProduction!$B$2:$B$9923,$A109) -> 65.1113
A110: PHL_POW_PP_NGCC_CCS | C110: =SUMIFS(AnnualProduction!D$2:D$9923,AnnualProduction!$B$2:$B$9923,$A110) -> 0 | D110: =SUMIFS(AnnualProduction!E$2:E$9923,AnnualProduction!$B$2:$B$9923,$A110) -> 0 | E110: =SUMIFS(AnnualProduction!F$2:F$9923,AnnualProduction!$B$2:$B$9923,$A110) -> 0 | F110: =SUMIFS(AnnualProduction!G$2:G$9923,AnnualProduction!$B$2:$B$9923,$A110) -> 0 | G110: =SUMIFS(AnnualProduction!H$2:H$9923,AnnualProduction!$B$2:$B$9923,$A110) -> 0 | H110: =SUMIFS(AnnualProduction!I$2:I$9923,AnnualProduction!$B$2:$B$9923,$A110) -> 0 | I110: =SUMIFS(AnnualProduction!J$2:J$9923,AnnualProduction!$B$2:$B$9923,$A110) -> 0 | J110: =SUMIFS(AnnualProduction!K$2:K$9923,AnnualProduction!$B$2:$B$9923,$A110) -> 0 | ... AG110: =SUMIFS(AnnualProduction!AH$2:AH$9923,AnnualProduction!$B$2:$B$9923,$A110) -> 0
A111: PHL_POW_PP_NU | C111: =SUMIFS(AnnualProduction!D$2:D$9923,AnnualProduction!$B$2:$B$9923,$A111) -> 0 | D111: =SUMIFS(AnnualProduction!E$2:E$9923,AnnualProduction!$B$2:$B$9923,$A111) -> 0 | E111: =SUMIFS(AnnualProduction!F$2:F$9923,AnnualProduction!$B$2:$B$9923,$A111) -> 0 | F111: =SUMIFS(AnnualProduction!G$2:G$9923,AnnualProduction!$B$2:$B$9923,$A111) -> 0 | G111: =SUMIFS(AnnualProduction!H$2:H$9923,AnnualProduction!$B$2:$B$9923,$A111) -> 0 | H111: =SUMIFS(AnnualProduction!I$2:I$9923,AnnualProduction!$B$2:$B$9923,$A111) -> 0 | I111: =SUMIFS(AnnualProduction!J$2:J$9923,AnnualProduction!$B$2:$B$9923,$A111) -> 0 | J111: =SUMIFS(AnnualProduction!K$2:K$9923,AnnualProduction!$B$2:$B$9923,$A111) -> 0 | ... AG111: =SUMIFS(AnnualProduction!AH$2:AH$9923,AnnualProduction!$B$2:$B$9923,$A111) -> 0
A112: PHL_POW_PP_NUSMR | C112: =SUMIFS(AnnualProduction!D$2:D$9923,AnnualProduction!$B$2:$B$9923,$A112) -> 0 | D112: =SUMIFS(AnnualProduction!E$2:E$9923,AnnualProduction!$B$2:$B$9923,$A112) -> 0 | E112: =SUMIFS(AnnualProduction!F$2:F$9923,AnnualProduction!$B$2:$B$9923,$A112) -> 0 | F112: =SUMIFS(AnnualProduction!G$2:G$9923,AnnualProduction!$B$2:$B$9923,$A112) -> 0 | G112: =SUMIFS(AnnualProduction!H$2:H$9923,AnnualProduction!$B$2:$B$9923,$A112) -> 0 | H112: =SUMIFS(AnnualProduction!I$2:I$9923,AnnualProduction!$B$2:$B$9923,$A112) -> 0 | I112: =SUMIFS(AnnualProduction!J$2:J$9923,AnnualProduction!$B$2:$B$9923,$A112) -> 0 | J112: =SUMIFS(AnnualProduction!K$2:K$9923,AnnualProduction!$B$2:$B$9923,$A112) -> 0 | ... AG112: =SUMIFS(AnnualProduction!AH$2:AH$9923,AnnualProduction!$B$2:$B$9923,$A112) -> 0
... A117: PHL_POW_CHP_NG_OLD | C117: =SUMIFS(AnnualProduction!D$2:D$9923,AnnualProduction!$B$2:$B$9923,$A117) -> 70.2 | D117: =SUMIFS(AnnualProduction!E$2:E$9923,AnnualProduction!$B$2:$B$9923,$A117) -> 68.6158 | E117: =SUMIFS(AnnualProduction!F$2:F$9923,AnnualProduction!$B$2:$B$9923,$A117) -> 64.3818 | F117: =SUMIFS(AnnualProduction!G$2:G$9923,AnnualProduction!$B$2:$B$9923,$A117) -> 60.0051 | G117: =SUMIFS(AnnualProduction!H$2:H$9923,AnnualProduction!$B$2:$B$9923,$A117) -> 64.969 | H117: =SUMIFS(AnnualProduction!I$2:I$9923,AnnualProduction!$B$2:$B$9923,$A117) -> 1.1774 | I117: =SUMIFS(AnnualProduction!J$2:J$9923,AnnualProduction!$B$2:$B$9923,$A117) -> 1.4884 | J117: =SUMIFS(AnnualProduction!K$2:K$9923,AnnualProduction!$B$2:$B$9923,$A117) -> 1.773 | ... AG117: =SUMIFS(AnnualProduction!AH$2:AH$9923,AnnualProduction!$B$2:$B$9923,$A117) -> 0
A118: RE% | C118: =SUM(C101,C103,C104,C107:C108,C113:C115)/SUM(C101:C117) -> 0.21249703 | D118: =SUM(D101,D103,D104,D107:D108,D113:D115)/SUM(D101:D117) -> 0.22038758 | E118: =SUM(E101,E103,E104,E107:E108,E113:E115)/SUM(E101:E117) -> 0.22134916 | F118: =SUM(F101,F103,F104,F107:F108,F113:F115)/SUM(F101:F117) -> 0.22268807 | G118: =SUM(G101,G103,G104,G107:G108,G113:G115)/SUM(G101:G117) -> 0.22210075 | H118: =SUM(H101,H103,H104,H107:H108,H113:H115)/SUM(H101:H117) -> 0.23158226 | I118: =SUM(I101,I103,I104,I107:I108,I113:I115)/SUM(I101:I117) -> 0.27743972 | J118: =SUM(J101,J103,J104,J107:J108,J113:J115)/SUM(J101:J117) -> 0.31936713 | ... AG118: =SUM(AG101,AG103,AG104,AG107:AG108,AG113:AG115)/SUM(AG101:AG117) -> 0.39200169
A119: Variable Cost of imported fuels
A120: Price of coal as commodity | B120: MUSD/PJ | C120: 3.0333429 | D120: 3.0452852 | E120: 3.0572275 | F120: 3.0691698 | G120: 3.0811121 | H120: 3.0930544 | I120: 3.1049967 | J120: 3.116939 | K120: 3.1288812 | L120: 3.1408235 | M120: 3.1527658 | N120: 3.1909812 | O120: 3.2291965 | P120: 3.2674119 | Q120: 3.3056272 | R120: 3.3438426 | S120: 3.3820579 | T120: 3.4202732 | U120: 3.4584886 | V120: 3.4967039 | W120: 3.5349193 | X120: 3.5420846 | Y120: 3.54925 | Z120: 3.5564154 | AA120: 3.5635808 | AB120: 3.5707462 | AC120: 3.5779115 | AD120: 3.5850769 | AE120: 3.5922423 | AF120: 3.5994077 | AG120: 3.606573
A121: Price of oil as commodity | B121: MUSD/PJ | C121: 13.950989 | D121: 14.184819 | E121: 14.418649 | F121: 14.652479 | G121: 14.886309 | H121: 15.120139 | I121: 15.35397 | J121: 15.5878 | K121: 15.82163 | L121: 16.05546 | M121: 16.28929 | N121: 16.643976 | O121: 16.998662 | P121: 17.353349 | Q121: 17.708035 | R121: 18.062721 | S121: 18.417407 | T121: 18.772093 | U121: 19.126779 | V121: 19.481466 | W121: 19.836152 | X121: 19.985908 | Y121: 20.135664 | Z121: 20.285421 | AA121: 20.435177 | AB121: 20.584934 | AC121: 20.73469 | AD121: 20.884446 | AE121: 21.034203 | AF121: 21.183959 | AG121: 21.333715
A122: Price of natural gas as commodity | B122: MUSD/PJ | C122: 9.9837585 | D122: 10.021974 | E122: 10.060189 | F122: 10.098405 | G122: 10.13662 | H122: 10.174835 | I122: 10.213051 | J122: 10.251266 | K122: 10.289481 | L122: 10.327697 | M122: 10.365912 | N122: 10.401739 | O122: 10.437566 | P122: 10.473393 | Q122: 10.509219 | R122: 10.545046 | S122: 10.580873 | T122: 10.6167 | U122: 10.652527 | V122: 10.688354 | W122: 10.724181 | X122: 10.726569 | Y122: 10.728958 | Z122: 10.731346 | AA122: 10.733735 | AB122: 10.736123 | AC122: 10.738512 | AD122: 10.7409 | AE122: 10.743288 | AF122: 10.745677 | AG122: 10.748065
A123: Price of biomass as commodity | B123: MUSD/PJ | C123: 16 | D123: 16 | E123: 16 | F123: 16 | G123: 16 | H123: 16 | I123: 16 | J123: 16 | K123: 16 | L123: 16 | M123: 16 | N123: 16 | O123: 16 | P123: 16 | Q123: 16 | R123: 16 | S123: 16 | T123: 16 | U123: 16 | V123: 16 | W123: 16 | X123: 16 | Y123: 16 | Z123: 16 | AA123: 16 | AB123: 16 | AC123: 16 | AD123: 16 | AE123: 16 | AF123: 16 | AG123: 16
A124: Price of urankium as a commodity | B124: MUSD/PJ | C124: 0.481 | D124: 0.481 | E124: 0.481 | F124: 0.481 | G124: 0.481 | H124: 0.481 | I124: 0.5004 | J124: 0.5198 | K124: 0.5392 | L124: 0.5586 | M124: 0.578 | N124: 0.5733 | O124: 0.5686 | P124: 0.5639 | Q124: 0.5592 | R124: 0.5545 | S124: 0.5498 | T124: 0.5451 | U124: 0.5404 | V124: 0.5357 | W124: 0.531 | X124: 0.5435 | Y124: 0.556 | Z124: 0.5685 | AA124: 0.581 | AB124: 0.5935 | AC124: 0.606 | AD124: 0.6185 | AE124: 0.631 | AF124: 0.6435 | AG124: 0.656 | AH124: 0.656 | AI124: 0.656 | AJ124: 0.656
A128: New Capacity (GW) | C128: 2020 | D128: 2021 | E128: 2022 | F128: 2023 | G128: 2024 | H128: 2025 | I128: 2026 | J128: 2027 | K128: 2028 | L128: 2029 | M128: 2030 | N128: 2031 | O128: 2032 | P128: 2033 | Q128: 2034 | R128: 2035 | S128: 2036 | T128: 2037 | U128: 2038 | V128: 2039 | W128: 2040 | X128: 2041 | Y128: 2042 | Z128: 2043 | AA128: 2044 | AB128: 2045 | AC128: 2046 | AD128: 2047 | AE128: 2048 | AF128: 2049 | AG128: 2050
A129: PHL_POW_CHP_BIOM_OLD | C129: =SUMIFS('New Capacity'!C$2:C$10000,'New Capacity'!$B$2:$B$10000,$A129) -> 0 | D129: =SUMIFS('New Capacity'!D$2:D$10000,'New Capacity'!$B$2:$B$10000,$A129) -> 0 | E129: =SUMIFS('New Capacity'!E$2:E$10000,'New Capacity'!$B$2:$B$10000,$A129) -> 0.082 | F129: =SUMIFS('New Capacity'!F$2:F$10000,'New Capacity'!$B$2:$B$10000,$A129) -> 0.006 | G129: =SUMIFS('New Capacity'!G$2:G$10000,'New Capacity'!$B$2:$B$10000,$A129) -> 0.0099 | H129: =SUMIFS('New Capacity'!H$2:H$10000,'New Capacity'!$B$2:$B$10000,$A129) -> 0 | I129: =SUMIFS('New Capacity'!I$2:I$10000,'New Capacity'!$B$2:$B$10000,$A129) -> 0 | J129: =SUMIFS('New Capacity'!J$2:J$10000,'New Capacity'!$B$2:$B$10000,$A129) -> 0 | ... AG129: =SUMIFS('New Capacity'!AG$2:AG$10000,'New Capacity'!$B$2:$B$10000,$A129) -> 0
A130: PHL_POW_CHP_COAL_OLD | C130: =SUMIFS('New Capacity'!C$2:C$10000,'New Capacity'!$B$2:$B$10000,$A130) -> 0 | D130: =SUMIFS('New Capacity'!D$2:D$10000,'New Capacity'!$B$2:$B$10000,$A130) -> 0 | E130: =SUMIFS('New Capacity'!E$2:E$10000,'New Capacity'!$B$2:$B$10000,$A130) -> 0 | F130: =SUMIFS('New Capacity'!F$2:F$10000,'New Capacity'!$B$2:$B$10000,$A130) -> 0 | G130: =SUMIFS('New Capacity'!G$2:G$10000,'New Capacity'!$B$2:$B$10000,$A130) -> 0 | H130: =SUMIFS('New Capacity'!H$2:H$10000,'New Capacity'!$B$2:$B$10000,$A130) -> 0 | I130: =SUMIFS('New Capacity'!I$2:I$10000,'New Capacity'!$B$2:$B$10000,$A130) -> 0 | J130: =SUMIFS('New Capacity'!J$2:J$10000,'New Capacity'!$B$2:$B$10000,$A130) -> 0 | ... AG130: =SUMIFS('New Capacity'!AG$2:AG$10000,'New Capacity'!$B$2:$B$10000,$A130) -> 0
A131: PHL_POW_GEO_OLD | C131: =SUMIFS('New Capacity'!C$2:C$10000,'New Capacity'!$B$2:$B$10000,$A131) -> 0 | D131: =SUMIFS('New Capacity'!D$2:D$10000,'New Capacity'!$B$2:$B$10000,$A131) -> 0 | E131: =SUMIFS('New Capacity'!E$2:E$10000,'New Capacity'!$B$2:$B$10000,$A131) -> 0.0037 | F131: =SUMIFS('New Capacity'!F$2:F$10000,'New Capacity'!$B$2:$B$10000,$A131) -> 0.2811 | G131: =SUMIFS('New Capacity'!G$2:G$10000,'New Capacity'!$B$2:$B$10000,$A131) -> 0.0067 | H131: =SUMIFS('New Capacity'!H$2:H$10000,'New Capacity'!$B$2:$B$10000,$A131) -> 0.0357 | I131: =SUMIFS('New Capacity'!I$2:I$10000,'New Capacity'!$B$2:$B$10000,$A131) -> 0.8338 | J131: =SUMIFS('New Capacity'!J$2:J$10000,'New Capacity'!$B$2:$B$10000,$A131) -> 0.8398 | ... AG131: =SUMIFS('New Capacity'!AG$2:AG$10000,'New Capacity'!$B$2:$B$10000,$A131) -> 0.0046
A132: PHL_POW_PP_BIOM_CCS | C132: =SUMIFS('New Capacity'!C$2:C$10000,'New Capacity'!$B$2:$B$10000,$A132) -> 0 | D132: =SUMIFS('New Capacity'!D$2:D$10000,'New Capacity'!$B$2:$B$10000,$A132) -> 0 | E132: =SUMIFS('New Capacity'!E$2:E$10000,'New Capacity'!$B$2:$B$10000,$A132) -> 0 | F132: =SUMIFS('New Capacity'!F$2:F$10000,'New Capacity'!$B$2:$B$10000,$A132) -> 0 | G132: =SUMIFS('New Capacity'!G$2:G$10000,'New Capacity'!$B$2:$B$10000,$A132) -> 0 | H132: =SUMIFS('New Capacity'!H$2:H$10000,'New Capacity'!$B$2:$B$10000,$A132) -> 0 | I132: =SUMIFS('New Capacity'!I$2:I$10000,'New Capacity'!$B$2:$B$10000,$A132) -> 0 | J132: =SUMIFS('New Capacity'!J$2:J$10000,'New Capacity'!$B$2:$B$10000,$A132) -> 0 | ... AG132: =SUMIFS('New Capacity'!AG$2:AG$10000,'New Capacity'!$B$2:$B$10000,$A132) -> 0
A133: PHL_POW_PP_COAL | C133: =SUMIFS('New Capacity'!C$2:C$10000,'New Capacity'!$B$2:$B$10000,$A133) -> 0 | D133: =SUMIFS('New Capacity'!D$2:D$10000,'New Capacity'!$B$2:$B$10000,$A133) -> 0.725 | E133: =SUMIFS('New Capacity'!E$2:E$10000,'New Capacity'!$B$2:$B$10000,$A133) -> 0.7694 | F133: =SUMIFS('New Capacity'!F$2:F$10000,'New Capacity'!$B$2:$B$10000,$A133) -> 0 | G133: =SUMIFS('New Capacity'!G$2:G$10000,'New Capacity'!$B$2:$B$10000,$A133) -> 0.6 | H133: =SUMIFS('New Capacity'!H$2:H$10000,'New Capacity'!$B$2:$B$10000,$A133) -> 0 | I133: =SUMIFS('New Capacity'!I$2:I$10000,'New Capacity'!$B$2:$B$10000,$A133) -> 0 | J133: =SUMIFS('New Capacity'!J$2:J$10000,'New Capacity'!$B$2:$B$10000,$A133) -> 0 | ... AG133: =SUMIFS('New Capacity'!AG$2:AG$10000,'New Capacity'!$B$2:$B$10000,$A133) -> 0
A134: PHL_POW_PP_COAL_CCS | C134: =SUMIFS('New Capacity'!C$2:C$10000,'New Capacity'!$B$2:$B$10000,$A134) -> 0 | D134: =SUMIFS('New Capacity'!D$2:D$10000,'New Capacity'!$B$2:$B$10000,$A134) -> 0 | E134: =SUMIFS('New Capacity'!E$2:E$10000,'New Capacity'!$B$2:$B$10000,$A134) -> 0 | F134: =SUMIFS('New Capacity'!F$2:F$10000,'New Capacity'!$B$2:$B$10000,$A134) -> 0 | G134: =SUMIFS('New Capacity'!G$2:G$10000,'New Capacity'!$B$2:$B$10000,$A134) -> 0 | H134: =SUMIFS('New Capacity'!H$2:H$10000,'New Capacity'!$B$2:$B$10000,$A134) -> 0 | I134: =SUMIFS('New Capacity'!I$2:I$10000,'New Capacity'!$B$2:$B$10000,$A134) -> 0 | J134: =SUMIFS('New Capacity'!J$2:J$10000,'New Capacity'!$B$2:$B$10000,$A134) -> 0 | ... AG134: =SUMIFS('New Capacity'!AG$2:AG$10000,'New Capacity'!$B$2:$B$10000,$A134) -> 0
A135: PHL_POW_PP_H2 | C135: =SUMIFS('New Capacity'!C$2:C$10000,'New Capacity'!$B$2:$B$10000,$A135) -> 0 | D135: =SUMIFS('New Capacity'!D$2:D$10000,'New Capacity'!$B$2:$B$10000,$A135) -> 0 | E135: =SUMIFS('New Capacity'!E$2:E$10000,'New Capacity'!$B$2:$B$10000,$A135) -> 0 | F135: =SUMIFS('New Capacity'!F$2:F$10000,'New Capacity'!$B$2:$B$10000,$A135) -> 0 | G135: =SUMIFS('New Capacity'!G$2:G$10000,'New Capacity'!$B$2:$B$10000,$A135) -> 0 | H135: =SUMIFS('New Capacity'!H$2:H$10000,'New Capacity'!$B$2:$B$10000,$A135) -> 0 | I135: =SUMIFS('New Capacity'!I$2:I$10000,'New Capacity'!$B$2:$B$10000,$A135) -> 0 | J135: =SUMIFS('New Capacity'!J$2:J$10000,'New Capacity'!$B$2:$B$10000,$A135) -> 0 | ... AG135: =SUMIFS('New Capacity'!AG$2:AG$10000,'New Capacity'!$B$2:$B$10000,$A135) -> 0
A136: PHL_POW_PP_HY_LA | C136: =SUMIFS('New Capacity'!C$2:C$10000,'New Capacity'!$B$2:$B$10000,$A136) -> 1.4633 | D136: =SUMIFS('New Capacity'!D$2:D$10000,'New Capacity'!$B$2:$B$10000,$A136) -> 2.5546 | E136: =SUMIFS('New Capacity'!E$2:E$10000,'New Capacity'!$B$2:$B$10000,$A136) -> 0.0159 | F136: =SUMIFS('New Capacity'!F$2:F$10000,'New Capacity'!$B$2:$B$10000,$A136) -> 0.0468 | G136: =SUMIFS('New Capacity'!G$2:G$10000,'New Capacity'!$B$2:$B$10000,$A136) -> 0.0352 | H136: =SUMIFS('New Capacity'!H$2:H$10000,'New Capacity'!$B$2:$B$10000,$A136) -> 0 | I136: =SUMIFS('New Capacity'!I$2:I$10000,'New Capacity'!$B$2:$B$10000,$A136) -> 0 | J136: =SUMIFS('New Capacity'!J$2:J$10000,'New Capacity'!$B$2:$B$10000,$A136) -> 0 | ... AG136: =SUMIFS('New Capacity'!AG$2:AG$10000,'New Capacity'!$B$2:$B$10000,$A136) -> 0
A137: PHL_POW_PP_NGCC | C137: =SUMIFS('New Capacity'!C$2:C$10000,'New Capacity'!$B$2:$B$10000,$A137) -> 0 | D137: =SUMIFS('New Capacity'!D$2:D$10000,'New Capacity'!$B$2:$B$10000,$A137) -> 0 | E137: =SUMIFS('New Capacity'!E$2:E$10000,'New Capacity'!$B$2:$B$10000,$A137) -> 0 | F137: =SUMIFS('New Capacity'!F$2:F$10000,'New Capacity'!$B$2:$B$10000,$A137) -> 0 | G137: =SUMIFS('New Capacity'!G$2:G$10000,'New Capacity'!$B$2:$B$10000,$A137) -> 0 | H137: =SUMIFS('New Capacity'!H$2:H$10000,'New Capacity'!$B$2:$B$10000,$A137) -> 0.88 | I137: =SUMIFS('New Capacity'!I$2:I$10000,'New Capacity'!$B$2:$B$10000,$A137) -> 0 | J137: =SUMIFS('New Capacity'!J$2:J$10000,'New Capacity'!$B$2:$B$10000,$A137) -> 0 | ... AG137: =SUMIFS('New Capacity'!AG$2:AG$10000,'New Capacity'!$B$2:$B$10000,$A137) -> 3.4535
A138: PHL_POW_PP_NGCC_CCS | C138: =SUMIFS('New Capacity'!C$2:C$10000,'New Capacity'!$B$2:$B$10000,$A138) -> 0 | D138: =SUMIFS('New Capacity'!D$2:D$10000,'New Capacity'!$B$2:$B$10000,$A138) -> 0 | E138: =SUMIFS('New Capacity'!E$2:E$10000,'New Capacity'!$B$2:$B$10000,$A138) -> 0 | F138: =SUMIFS('New Capacity'!F$2:F$10000,'New Capacity'!$B$2:$B$10000,$A138) -> 0 | G138: =SUMIFS('New Capacity'!G$2:G$10000,'New Capacity'!$B$2:$B$10000,$A138) -> 0 | H138: =SUMIFS('New Capacity'!H$2:H$10000,'New Capacity'!$B$2:$B$10000,$A138) -> 0 | I138: =SUMIFS('New Capacity'!I$2:I$10000,'New Capacity'!$B$2:$B$10000,$A138) -> 0 | J138: =SUMIFS('New Capacity'!J$2:J$10000,'New Capacity'!$B$2:$B$10000,$A138) -> 0 | ... AG138: =SUMIFS('New Capacity'!AG$2:AG$10000,'New Capacity'!$B$2:$B$10000,$A138) -> 0
A139: PHL_POW_PP_NU | C139: =SUMIFS('New Capacity'!C$2:C$10000,'New Capacity'!$B$2:$B$10000,$A139) -> 0 | D139: =SUMIFS('New Capacity'!D$2:D$10000,'New Capacity'!$B$2:$B$10000,$A139) -> 0 | E139: =SUMIFS('New Capacity'!E$2:E$10000,'New Capacity'!$B$2:$B$10000,$A139) -> 0 | F139: =SUMIFS('New Capacity'!F$2:F$10000,'New Capacity'!$B$2:$B$10000,$A139) -> 0 | G139: =SUMIFS('New Capacity'!G$2:G$10000,'New Capacity'!$B$2:$B$10000,$A139) -> 0 | H139: =SUMIFS('New Capacity'!H$2:H$10000,'New Capacity'!$B$2:$B$10000,$A139) -> 0 | I139: =SUMIFS('New Capacity'!I$2:I$10000,'New Capacity'!$B$2:$B$10000,$A139) -> 0 | J139: =SUMIFS('New Capacity'!J$2:J$10000,'New Capacity'!$B$2:$B$10000,$A139) -> 0 | ... AG139: =SUMIFS('New Capacity'!AG$2:AG$10000,'New Capacity'!$B$2:$B$10000,$A139) -> 0
A140: PHL_POW_PP_NUSMR | C140: =SUMIFS('New Capacity'!C$2:C$10000,'New Capacity'!$B$2:$B$10000,$A140) -> 0 | D140: =SUMIFS('New Capacity'!D$2:D$10000,'New Capacity'!$B$2:$B$10000,$A140) -> 0 | E140: =SUMIFS('New Capacity'!E$2:E$10000,'New Capacity'!$B$2:$B$10000,$A140) -> 0 | F140: =SUMIFS('New Capacity'!F$2:F$10000,'New Capacity'!$B$2:$B$10000,$A140) -> 0 | G140: =SUMIFS('New Capacity'!G$2:G$10000,'New Capacity'!$B$2:$B$10000,$A140) -> 0 | H140: =SUMIFS('New Capacity'!H$2:H$10000,'New Capacity'!$B$2:$B$10000,$A140) -> 0 | I140: =SUMIFS('New Capacity'!I$2:I$10000,'New Capacity'!$B$2:$B$10000,$A140) -> 0 | J140: =SUMIFS('New Capacity'!J$2:J$10000,'New Capacity'!$B$2:$B$10000,$A140) -> 0 | ... AG140: =SUMIFS('New Capacity'!AG$2:AG$10000,'New Capacity'!$B$2:$B$10000,$A140) -> 0
...

Sheet Variable
A1: REGION | B1: TECHNOLOGY | C1: 2020 | D1: 2021 | E1: 2022 | F1: 2023 | G1: 2024 | H1: 2025 | I1: 2026 | J1: 2027 | K1: 2028 | L1: 2029 | M1: 2030 | N1: 2031 | O1: 2032 | P1: 2033 | Q1: 2034 | R1: 2035 | S1: 2036 | T1: 2037 | U1: 2038 | V1: 2039 | W1: 2040 | X1: 2041 | Y1: 2042 | Z1: 2043 | AA1: 2044 | AB1: 2045 | AC1: 2046 | AD1: 2047 | AE1: 2048 | AF1: 2049 | AG1: 2050
B2: PHL_AGR_FAC | C2: 0.0009 | D2: 0.001 | E2: 0.001 | F2: 0.001 | G2: 0.001 | H2: 0.001 | I2: 0.0011 | J2: 0.0011 | K2: 0.0011 | L2: 0.0011 | M2: 0.0011 | N2: 0.0012 | O2: 0.0012 | P2: 0.0012 | Q2: 0.0013 | R2: 0.0013 | S2: 0.0013 | T2: 0.0013 | U2: 0.0014 | V2: 0.0014 | W2: 0.0014 | X2: 0.0011 | Y2: 0.001 | Z2: 0.001 | AA2: 0.0009 | AB2: 0.0008 | AC2: 0.0008 | AD2: 0.0007 | AE2: 0.0006 | AF2: 0.0006 | AG2: 0.0018 | AH2: 0.0019 | AI2: 0.0019 | AJ2: 0.0019 | AK2: 0.0394
B3: PHL_AGR_HEAT_BIOM | C3: 0 | D3: 0 | E3: 0 | F3: 0 | G3: 0 | H3: 0 | I3: 0 | J3: 0 | K3: 0 | L3: 0 | M3: 0 | N3: 0 | O3: 0 | P3: 0 | Q3: 0 | R3: 0 | S3: 0 | T3: 0 | U3: 0 | V3: 0 | W3: 0 | X3: 0 | Y3: 0 | Z3: 0 | AA3: 0 | AB3: 0 | AC3: 0 | AD3: 0 | AE3: 0 | AF3: 0 | AG3: 0 | AH3: 0 | AI3: 0 | AJ3: 0 | AK3: 0
B4: PHL_AGR_HEAT_COAL | C4: 0 | D4: 0 | E4: 0 | F4: 0 | G4: 0 | H4: 0 | I4: 0 | J4: 0 | K4: 0 | L4: 0 | M4: 0 | N4: 0 | O4: 0 | P4: 0 | Q4: 0 | R4: 0 | S4: 0 | T4: 0 | U4: 0 | V4: 0 | W4: 0 | X4: 0 | Y4: 0 | Z4: 0 | AA4: 0 | AB4: 0 | AC4: 0 | AD4: 0 | AE4: 0 | AF4: 0 | AG4: 0 | AH4: 0 | AI4: 0 | AJ4: 0 | AK4: 0
B5: PHL_AGR_HEAT_ELE | C5: 0 | D5: 0 | E5: 0 | F5: 0 | G5: 0 | H5: 0 | I5: 0 | J5: 0 | K5: 0 | L5: 0 | M5: 0 | N5: 0 | O5: 0 | P5: 0 | Q5: 0 | R5: 0 | S5: 0 | T5: 0 | U5: 0 | V5: 0 | W5: 0 | X5: 0 | Y5: 0 | Z5: 0 | AA5: 0 | AB5: 0 | AC5: 0 | AD5: 0 | AE5: 0 | AF5: 0 | AG5: 0 | AH5: 0 | AI5: 0 | AJ5: 0 | AK5: 0
B6: PHL_AGR_HEAT_NG | C6: 0.0008 | D6: 0.0008 | E6: 0.0008 | F6: 0.0008 | G6: 0.0009 | H6: 0.0009 | I6: 0.0009 | J6: 0.0009 | K6: 0.0009 | L6: 0.001 | M6: 0.001 | N6: 0.001 | O6: 0.001 | P6: 0.0011 | Q6: 0.0011 | R6: 0.0011 | S6: 0.0011 | T6: 0.0012 | U6: 0.0012 | V6: 0.0012 | W6: 0.0013 | X6: 0.0012 | Y6: 0.0011 | Z6: 0.001 | AA6: 0.0009 | AB6: 0.0009 | AC6: 0.0008 | AD6: 0.0008 | AE6: 0.0007 | AF6: 0.0006 | AG6: 0.0017 | AH6: 0.0018 | AI6: 0.0018 | AJ6: 0.0019 | AK6: 0.0362
B7: PHL_AGR_HEAT_OIL | C7: 0.0001 | D7: 0.0001 | E7: 0.0001 | F7: 0.0001 | G7: 0.0001 | H7: 0.0001 | I7: 0.0001 | J7: 0.0001 | K7: 0.0001 | L7: 0.0001 | M7: 0.0001 | N7: 0.0001 | O7: 0.0001 | P7: 0.0001 | Q7: 0.0001 | R7: 0.0001 | S7: 0.0001 | T7: 0.0001 | U7: 0.0001 | V7: 0.0001 | W7: 0.0001 | X7: 0 | Y7: 0.0001 | Z7: 0.0001 | AA7: 0.0001 | AB7: 0 | AC7: 0 | AD7: 0 | AE7: 0 | AF7: 0 | AG7: 0 | AH7: 0 | AI7: 0 | AJ7: 0 | AK7: 0.0024
B8: PHL_AGR_MOT_ELE | C8: 0 | D8: 0 | E8: 0 | F8: 0 | G8: 0 | H8: 0 | I8: 0 | J8: 0 | K8: 0 | L8: 0 | M8: 0 | N8: 0 | O8: 0 | P8: 0 | Q8: 0 | R8: 0 | S8: 0 | T8: 0 | U8: 0 | V8: 0 | W8: 0 | X8: 0 | Y8: 0 | Z8: 0 | AA8: 0 | AB8: 0 | AC8: 0 | AD8: 0 | AE8: 0 | AF8: 0 | AG8: 0 | AH8: 0 | AI8: 0 | AJ8: 0 | AK8: 0
B9: PHL_AGR_MOT_LIQ | C9: 0.0008 | D9: 0.0008 | E9: 0.0008 | F9: 0.0008 | G9: 0.0009 | H9: 0.0009 | I9: 0.0009 | J9: 0.0009 | K9: 0.0009 | L9: 0.001 | M9: 0.001 | N9: 0.001 | O9: 0.001 | P9: 0.001 | Q9: 0.0011 | R9: 0.0011 | S9: 0.0011 | T9: 0.0011 | U9: 0.0012 | V9: 0.0012 | W9: 0.0012 | X9: 0.0012 | Y9: 0.0013 | Z9: 0.0013 | AA9: 0.0013 | AB9: 0.0014 | AC9: 0.0014 | AD9: 0.0014 | AE9: 0.0015 | AF9: 0.0015 | AG9: 0.0015 | AH9: 0.0016 | AI9: 0.0016 | AJ9: 0.0017 | AK9: 0.0394
B10: PHL_AGR_UNIT | C10: 0.0009 | D10: 0.001 | E10: 0.001 | F10: 0.001 | G10: 0.001 | H10: 0.001 | I10: 0.0011 | J10: 0.0011 | K10: 0.0011 | L10: 0.0011 | M10: 0.0011 | N10: 0.0012 | O10: 0.0012 | P10: 0.0012 | Q10: 0.0013 | R10: 0.0013 | S10: 0.0013 | T10: 0.0013 | U10: 0.0014 | V10: 0.0014 | W10: 0.0014 | X10: 0.0015 | Y10: 0.0015 | Z10: 0.0015 | AA10: 0.0016 | AB10: 0.0016 | AC10: 0.0016 | AD10: 0.0017 | AE10: 0.0017 | AF10: 0.0018 | AG10: 0.0018 | AH10: 0.0019 | AI10: 0.0019 | AJ10: 0.0019 | AK10: 0.0464
B11: PHL_DEM_PUB_GWT_WAT | C11: 0 | D11: 0 | E11: 0 | F11: 0 | G11: 0 | H11: 0.0002 | I11: 0 | J11: 0.0001 | K11: 0 | L11: 0 | M11: 0.0001 | N11: 0 | O11: 0.0004 | P11: 0 | Q11: 0.0002 | R11: 0 | S11: 0 | T11: 0 | U11: 0.0001 | V11: 0 | W11: 0 | X11: 0.0001 | Y11: 0.0001 | Z11: 0.0001 | AA11: 0.0004 | AB11: 0 | AC11: 0 | AD11: 0.0006 | AE11: 0 | AF11: 0 | AG11: 0.0001 | AH11: 0 | AI11: 0 | AJ11: 0 | AK11: 0.0025
B12: PHL_DEM_PUB_SUR_WAT | C12: 0.002 | D12: 0.002 | E12: 0.0021 | F12: 0.0022 | G12: 0.0023 | H12: 0.0022 | I12: 0.0025 | J12: 0.0025 | K12: 0.0026 | L12: 0.0027 | M12: 0.0028 | N12: 0.003 | O12: 0.0027 | P12: 0.0032 | Q12: 0.0032 | R12: 0.0034 | S12: 0.0036 | T12: 0.0037 | U12: 0.0037 | V12: 0.004 | W12: 0.0041 | X12: 0.0042 | Y12: 0.0043 | Z12: 0.0046 | AA12: 0.0043 | AB12: 0.005 | AC12: 0.0052 | AD12: 0.0047 | AE12: 0.0055 | AF12: 0.0057 | AG12: 0.0058 | AH12: 0.0062 | AI12: 0.0064 | AJ12: 0.0066 | AK12: 0.129
B13: PHL_DEM_PWR_GWT_WAT | C13: 0.0002 | D13: 0.0005 | E13: 0.0003 | F13: 0.0003 | G13: 0.0005 | H13: 0.0003 | I13: 0.0004 | J13: 0.0004 | K13: 0.0005 | L13: 0.0005 | M13: 0.0004 | N13: 0.0005 | O13: 0.0001 | P13: 0.0005 | Q13: 0.0004 | R13: 0.0005 | S13: 0.0005 | T13: 0.0006 | U13: 0.0005 | V13: 0.0006 | W13: 0.0006 | X13: 0.0005 | Y13: 0.0006 | Z13: 0.0007 | AA13: 0.0003 | AB13: 0.0008 | AC13: 0.0008 | AD13: 0.0002 | AE13: 0.0009 | AF13: 0.0009 | AG13: 0.0008 | AH13: 0.001 | AI13: 0.001 | AJ13: 0.001 | AK13: 0.0186
... B133: PHL_TRA_VAN_PHEV | C133: 0 | D133: 0 | E133: 0 | F133: 0 | G133: 0 | H133: 0 | I133: 0 | J133: 0 | K133: 0 | L133: 0 | M133: 0 | N133: 0 | O133: 0 | P133: 0 | Q133: 0 | R133: 0 | S133: 0 | T133: 0 | U133: 0 | V133: 0 | W133: 0 | X133: 0 | Y133: 0 | Z133: 0 | AA133: 0 | AB133: 0 | AC133: 0 | AD133: 0 | AE133: 0 | AF133: 0 | AG133: 0 | AH133: 0 | AI133: 0 | AJ133: 0 | AK133: 0
B134: (blank)

Sheet Fixed
A1: REGION | B1: TECHNOLOGY | C1: 2020 | D1: 2021 | E1: 2022 | F1: 2023 | G1: 2024 | H1: 2025 | I1: 2026 | J1: 2027 | K1: 2028 | L1: 2029 | M1: 2030 | N1: 2031 | O1: 2032 | P1: 2033 | Q1: 2034 | R1: 2035 | S1: 2036 | T1: 2037 | U1: 2038 | V1: 2039 | W1: 2040 | X1: 2041 | Y1: 2042 | Z1: 2043 | AA1: 2044 | AB1: 2045 | AC1: 2046 | AD1: 2047 | AE1: 2048 | AF1: 2049 | AG1: 2050
A2: REGION | B2: PHL_AGR_FAC | C2: 0 | D2: 0 | E2: 0 | F2: 0 | G2: 0 | H2: 0 | I2: 0 | J2: 0 | K2: 0 | L2: 0 | M2: 0 | N2: 0 | O2: 0 | P2: 0 | Q2: 0 | R2: 0 | S2: 0 | T2: 0 | U2: 0 | V2: 0 | W2: 0 | X2: 0 | Y2: 0 | Z2: 0 | AA2: 0 | AB2: 0 | AC2: 0 | AD2: 0 | AE2: 0 | AF2: 0 | AG2: 0 | AH2: 0 | AI2: 0 | AJ2: 0 | AK2: 0
A3: REGION | B3: PHL_AGR_HEAT_BIOM | C3: 0.1835 | D3: 0.1825 | E3: 0.182 | F3: 0.181 | G3: 0.1805 | H3: 0.1799 | I3: 0.1789 | J3: 0.1784 | K3: 0.1774 | L3: 0.1769 | M3: 0.1759 | N3: 0.1753 | O3: 0.1748 | P3: 0.1738 | Q3: 0.1733 | R3: 0.1723 | S3: 0.1719 | T3: 0.1714 | U3: 0.1705 | V3: 0.1701 | W3: 0.1688 | X3: 0.1682 | Y3: 0.1673 | Z3: 0.1669 | AA3: 0.1665 | AB3: 0 | AC3: 0 | AD3: 0 | AE3: 0 | AF3: 0 | AG3: 0 | AH3: 0 | AI3: 0 | AJ3: 0 | AK3: 4.368
A4: REGION | B4: PHL_AGR_HEAT_COAL | C4: 0 | D4: 0 | E4: 0 | F4: 0 | G4: 0 | H4: 0 | I4: 0 | J4: 0 | K4: 0 | L4: 0 | M4: 0 | N4: 0 | O4: 0 | P4: 0 | Q4: 0 | R4: 0 | S4: 0 | T4: 0 | U4: 0 | V4: 0 | W4: 0 | X4: 0 | Y4: 0 | Z4: 0 | AA4: 0 | AB4: 0 | AC4: 0 | AD4: 0 | AE4: 0 | AF4: 0 | AG4: 0 | AH4: 0 | AI4: 0 | AJ4: 0 | AK4: 0
A5: REGION | B5: PHL_AGR_HEAT_ELE | C5: 0 | D5: 0 | E5: 0 | F5: 0 | G5: 0 | H5: 0 | I5: 0 | J5: 0 | K5: 0 | L5: 0 | M5: 0 | N5: 0 | O5: 0 | P5: 0 | Q5: 0 | R5: 0 | S5: 0 | T5: 0 | U5: 0 | V5: 0 | W5: 0 | X5: 0 | Y5: 0 | Z5: 0 | AA5: 0 | AB5: 0 | AC5: 0 | AD5: 0 | AE5: 0 | AF5: 0 | AG5: 0 | AH5: 0 | AI5: 0 | AJ5: 0 | AK5: 0
A6: REGION | B6: PHL_AGR_HEAT_NG | C6: 2.4405 | D6: 2.5553 | E6: 2.6389 | F6: 2.7214 | G6: 2.8028 | H6: 2.8833 | I6: 2.9682 | J6: 3.0524 | K6: 3.1358 | L6: 3.2185 | M6: 3.396 | N6: 3.4797 | O6: 3.5634 | P6: 3.6471 | Q6: 3.7308 | R6: 3.8145 | S6: 3.914 | T6: 4.0135 | U6: 4.1129 | V6: 4.2124 | W6: 4.2799 | X6: 4.2759 | Y6: 4.2719 | Z6: 4.2677 | AA6: 4.2677 | AB6: 3.0437 | AC6: 2.9389 | AD6: 2.8669 | AE6: 2.7948 | AF6: 2.7228 | AG6: 5.8518 | AH6: 5.9963 | AI6: 6.1409 | AJ6: 6.2854 | AK6: 126.306
A7: REGION | B7: PHL_AGR_HEAT_OIL | C7: 0.4512 | D7: 0.4548 | E7: 0.458 | F7: 0.4608 | G7: 0.4633 | H7: 0.4654 | I7: 0.4673 | J7: 0.4688 | K7: 0.4702 | L7: 0.4714 | M7: 0.487 | N7: 0.4863 | O7: 0.4856 | P7: 0.4849 | Q7: 0.4842 | R7: 0.4835 | S7: 0.4828 | T7: 0.4822 | U7: 0.4815 | V7: 0.4808 | W7: 0.4801 | X7: 0.4794 | Y7: 0.478 | Z7: 0.478 | AA7: 0.478 | AB7: 0 | AC7: 0 | AD7: 0 | AE7: 0 | AF7: 0 | AG7: 0 | AH7: 0 | AI7: 0 | AJ7: 0 | AK7: 11.8635
A8: REGION | B8: PHL_AGR_MOT_ELE | C8: 0 | D8: 0 | E8: 0 | F8: 0 | G8: 0 | H8: 0 | I8: 0 | J8: 0 | K8: 0 | L8: 0 | M8: 0 | N8: 0 | O8: 0 | P8: 0 | Q8: 0 | R8: 0 | S8: 0 | T8: 0 | U8: 0 | V8: 0 | W8: 0 | X8: 0 | Y8: 0 | Z8: 0 | AA8: 0 | AB8: 0 | AC8: 0 | AD8: 0 | AE8: 0 | AF8: 0 | AG8: 0 | AH8: 0 | AI8: 0 | AJ8: 0 | AK8: 0
A9: REGION | B9: PHL_AGR_MOT_LIQ | C9: 258.9921 | D9: 264.8225 | E9: 270.6529 | F9: 276.4833 | G9: 282.3137 | H9: 288.144 | I9: 294.4654 | J9: 300.7868 | K9: 307.1081 | L9: 313.4295 | M9: 319.7508 | N9: 326.9326 | O9: 334.1143 | P9: 341.296 | Q9: 348.4777 | R9: 355.6594 | S9: 364.2035 | T9: 372.7475 | U9: 381.2916 | V9: 389.8356 | W9: 398.3797 | X9: 408.3247 | Y9: 418.2698 | Z9: 428.2148 | AA9: 438.1599 | AB9: 448.105 | AC9: 459.4445 | AD9: 470.784 | AE9: 482.1235 | AF9: 493.463 | AG9: 504.8025 | AH9: 517.2698 | AI9: 529.737 | AJ9: 542.2043 | AK9: 12930.79
A10: REGION | B10: PHL_AGR_UNIT | C10: 0 | D10: 0 | E10: 0 | F10: 0 | G10: 0 | H10: 0 | I10: 0 | J10: 0 | K10: 0 | L10: 0 | M10: 0 | N10: 0 | O10: 0 | P10: 0 | Q10: 0 | R10: 0 | S10: 0 | T10: 0 | U10: 0 | V10: 0 | W10: 0 | X10: 0 | Y10: 0 | Z10: 0 | AA10: 0 | AB10: 0 | AC10: 0 | AD10: 0 | AE10: 0 | AF10: 0 | AG10: 0 | AH10: 0 | AI10: 0 | AJ10: 0 | AK10: 0
A11: REGION | B11: PHL_DEM_PUB_GWT_WAT | C11: 0 | D11: 0 | E11: 0 | F11: 0 | G11: 0 | H11: 0 | I11: 0 | J11: 0 | K11: 0 | L11: 0 | M11: 0 | N11: 0 | O11: 0 | P11: 0 | Q11: 0 | R11: 0 | S11: 0 | T11: 0 | U11: 0 | V11: 0 | W11: 0 | X11: 0 | Y11: 0 | Z11: 0 | AA11: 0 | AB11: 0 | AC11: 0 | AD11: 0 | AE11: 0 | AF11: 0 | AG11: 0 | AH11: 0 | AI11: 0 | AJ11: 0 | AK11: 0
A12: REGION | B12: PHL_DEM_PUB_SUR_WAT | C12: 0 | D12: 0 | E12: 0 | F12: 0 | G12: 0 | H12: 0 | I12: 0 | J12: 0 | K12: 0 | L12: 0 | M12: 0 | N12: 0 | O12: 0 | P12: 0 | Q12: 0 | R12: 0 | S12: 0 | T12: 0 | U12: 0 | V12: 0 | W12: 0 | X12: 0 | Y12: 0 | Z12: 0 | AA12: 0 | AB12: 0 | AC12: 0 | AD12: 0 | AE12: 0 | AF12: 0 | AG12: 0 | AH12: 0 | AI12: 0 | AJ12: 0 | AK12: 0
A13: REGION | B13: PHL_DEM_PWR_GWT_WAT | C13: 0 | D13: 0 | E13: 0 | F13: 0 | G13: 0 | H13: 0 | I13: 0 | J13: 0 | K13: 0 | L13: 0 | M13: 0 | N13: 0 | O13: 0 | P13: 0 | Q13: 0 | R13: 0 | S13: 0 | T13: 0 | U13: 0 | V13: 0 | W13: 0 | X13: 0 | Y13: 0 | Z13: 0 | AA13: 0 | AB13: 0 | AC13: 0 | AD13: 0 | AE13: 0 | AF13: 0 | AG13: 0 | AH13: 0 | AI13: 0 | AJ13: 0 | AK13: 0
... A132: REGION | B132: PHL_TRA_VAN_NG | C132: 0 | D132: 0 | E132: 0 | F132: 0 | G132: 0 | H132: 0 | I132: 0 | J132: 0 | K132: 0 | L132: 0 | M132: 0 | N132: 0 | O132: 0 | P132: 0 | Q132: 0 | R132: 0 | S132: 0 | T132: 0 | U132: 0 | V132: 0 | W132: 0 | X132: 0 | Y132: 0 | Z132: 0 | AA132: 0 | AB132: 0 | AC132: 0 | AD132: 0 | AE132: 0 | AF132: 0 | AG132: 0 | AH132: 0 | AI132: 0 | AJ132: 0 | AK132: 0
B133: PHL_TRA_VAN_PHEV | C133: 0 | D133: 0 | E133: 0 | F133: 0 | G133: 0 | H133: 0 | I133: 0 | J133: 0 | K133: 0 | L133: 0 | M133: 0 | N133: 0 | O133: 0 | P133: 0 | Q133: 0 | R133: 0 | S133: 0 | T133: 0 | U133: 0 | V133: 0 | W133: 0 | X133: 0 | Y133: 0 | Z133: 0 | AA133: 0 | AB133: 0 | AC133: 0 | AD133: 0 | AE133: 0 | AF133: 0 | AG133: 0 | AH133: 0 | AI133: 0 | AJ133: 0 | AK133: 0
B134: (blank)

Sheet Capital_Investments
A1: Million USD
A2: REGION | B2: TECHNOLOGY | C2: 2020 | D2: 2021 | E2: 2022 | F2: 2023 | G2: 2024 | H2: 2025 | I2: 2026 | J2: 2027 | K2: 2028 | L2: 2029 | M2: 2030 | N2: 2031 | O2: 2032 | P2: 2033 | Q2: 2034 | R2: 2035 | S2: 2036 | T2: 2037 | U2: 2038 | V2: 2039 | W2: 2040 | X2: 2041 | Y2: 2042 | Z2: 2043 | AA2: 2044 | AB2: 2045 | AC2: 2046 | AD2: 2047 | AE2: 2048 | AF2: 2049 | AG2: 2050
A3: REGION | B3: PHL_AGR_FAC | C3: 0 | D3: 0 | E3: 0 | F3: 0 | G3: 0 | H3: 0 | I3: 0 | J3: 0 | K3: 0 | L3: 0 | M3: 0 | N3: 0 | O3: 0 | P3: 0 | Q3: 0 | R3: 0 | S3: 0 | T3: 0 | U3: 0 | V3: 0 | W3: 0 | X3: 0 | Y3: 0 | Z3: 0 | AA3: 0 | AB3: 0 | AC3: 0 | AD3: 0 | AE3: 0 | AF3: 0 | AG3: 0 | AH3: 0 | AI3: 0 | AJ3: 0 | AK3: 0
A4: REGION | B4: PHL_AGR_HEAT_BIOM | C4: 2.999 | D4: 0 | E4: 0 | F4: 0 | G4: 0 | H4: 0 | I4: 0 | J4: 0 | K4: 0 | L4: 0 | M4: 0 | N4: 0 | O4: 0 | P4: 0 | Q4: 0 | R4: 0 | S4: 0 | T4: 0 | U4: 0 | V4: 0 | W4: 0 | X4: 0 | Y4: 0 | Z4: 0 | AA4: 0 | AB4: 0 | AC4: 0 | AD4: 0 | AE4: 0 | AF4: 0 | AG4: 0 | AH4: 0 | AI4: 0 | AJ4: 0 | AK4: 2.999
A5: REGION | B5: PHL_AGR_HEAT_COAL | C5: 0 | D5: 0 | E5: 0 | F5: 0 | G5: 0 | H5: 0 | I5: 0 | J5: 0 | K5: 0 | L5: 0 | M5: 0 | N5: 0 | O5: 0 | P5: 0 | Q5: 0 | R5: 0 | S5: 0 | T5: 0 | U5: 0 | V5: 0 | W5: 0 | X5: 0 | Y5: 0 | Z5: 0 | AA5: 0 | AB5: 0 | AC5: 0 | AD5: 0 | AE5: 0 | AF5: 0 | AG5: 0 | AH5: 0 | AI5: 0 | AJ5: 0 | AK5: 0
A6: REGION | B6: PHL_AGR_HEAT_ELE | C6: 0 | D6: 0 | E6: 0 | F6: 0 | G6: 0 | H6: 0 | I6: 0 | J6: 0 | K6: 0 | L6: 0 | M6: 0 | N6: 0 | O6: 0 | P6: 0 | Q6: 0 | R6: 0 | S6: 0 | T6: 0 | U6: 0 | V6: 0 | W6: 0 | X6: 0 | Y6: 0 | Z6: 0 | AA6: 0 | AB6: 0 | AC6: 0 | AD6: 0 | AE6: 0 | AF6: 0 | AG6: 0 | AH6: 0 | AI6: 0 | AJ6: 0 | AK6: 0
A7: REGION | B7: PHL_AGR_HEAT_NG | C7: 47.1147 | D7: 1.9432 | E7: 1.3465 | F7: 1.3559 | G7: 1.3643 | H7: 1.372 | I7: 1.4878 | J7: 1.4944 | K7: 1.5004 | L7: 1.5058 | M7: 1.5544 | N7: 1.7539 | O7: 1.7539 | P7: 1.7539 | Q7: 1.7539 | R7: 1.7539 | S7: 2.0697 | T7: 2.0697 | U7: 2.0697 | V7: 2.0697 | W7: 1.4297 | X7: 0 | Y7: 0 | Z7: 0 | AA7: 0 | AB7: 26.7657 | AC7: 0 | AD7: 0 | AE7: 0 | AF7: 0 | AG7: 64.0209 | AH7: 4.4449 | AI7: 4.4449 | AJ7: 4.4449 | AK7: 184.6387
A8: REGION | B8: PHL_AGR_HEAT_OIL | C8: 10.9168 | D8: 0 | E8: 0 | F8: 0 | G8: 0 | H8: 0 | I8: 0 | J8: 0 | K8: 0 | L8: 0 | M8: 0 | N8: 0 | O8: 0 | P8: 0 | Q8: 0 | R8: 0 | S8: 0 | T8: 0 | U8: 0 | V8: 0 | W8: 0 | X8: 0 | Y8: 0 | Z8: 0 | AA8: 0 | AB8: 0 | AC8: 0 | AD8: 0 | AE8: 0 | AF8: 0 | AG8: 0 | AH8: 0 | AI8: 0 | AJ8: 0 | AK8: 10.9168
A9: REGION | B9: PHL_AGR_MOT_ELE | C9: 0 | D9: 0 | E9: 0 | F9: 0 | G9: 0 | H9: 0 | I9: 0 | J9: 0 | K9: 0 | L9: 0 | M9: 0 | N9: 0 | O9: 0 | P9: 0 | Q9: 0 | R9: 0 | S9: 0 | T9: 0 | U9: 0 | V9: 0 | W9: 0 | X9: 0 | Y9: 0 | Z9: 0 | AA9: 0 | AB9: 0 | AC9: 0 | AD9: 0 | AE9: 0 | AF9: 0 | AG9: 0 | AH9: 0 | AI9: 0 | AJ9: 0 | AK9: 0
A10: REGION | B10: PHL_AGR_MOT_LIQ | C10: 14270.519 | D10: 369.9875 | E10: 369.9875 | F10: 376.4785 | G10: 382.9696 | H10: 389.4606 | I10: 425.9008 | J10: 432.8827 | K10: 439.8647 | L10: 453.8287 | M10: 460.8106 | N10: 525.4367 | O10: 533.279 | P10: 533.279 | Q10: 498.5774 | R10: 17770.378 | S10: 1037.4189 | T10: 1037.4189 | U10: 1052.454 | V10: 1052.454 | W10: 1052.454 | X10: 1184.893 | Y10: 1201.82 | Z10: 1201.82 | AA10: 1201.82 | AB10: 1201.82 | AC10: 1361.9114 | AD10: 1361.9114 | AE10: 1381.0932 | AF10: 1336.6995 | AG10: 19359.448 | AH10: 1980.1654 | AI10: 1980.1653 | AJ10: 1980.1654 | AK10: 80199.573
A11: REGION | B11: PHL_AGR_UNIT | C11: 0 | D11: 0 | E11: 0 | F11: 0 | G11: 0 | H11: 0 | I11: 0 | J11: 0 | K11: 0 | L11: 0 | M11: 0 | N11: 0 | O11: 0 | P11: 0 | Q11: 0 | R11: 0 | S11: 0 | T11: 0 | U11: 0 | V11: 0 | W11: 0 | X11: 0 | Y11: 0 | Z11: 0 | AA11: 0 | AB11: 0 | AC11: 0 | AD11: 0 | AE11: 0 | AF11: 0 | AG11: 0 | AH11: 0 | AI11: 0 | AJ11: 0 | AK11: 0
A12: REGION | B12: PHL_DEM_PUB_GWT_WAT | C12: 0 | D12: 0 | E12: 0 | F12: 0 | G12: 0 | H12: 0 | I12: 0 | J12: 0 | K12: 0 | L12: 0 | M12: 0 | N12: 0 | O12: 0 | P12: 0 | Q12: 0 | R12: 0 | S12: 0 | T12: 0 | U12: 0 | V12: 0 | W12: 0 | X12: 0 | Y12: 0 | Z12: 0 | AA12: 0 | AB12: 0 | AC12: 0 | AD12: 0 | AE12: 0 | AF12: 0 | AG12: 0 | AH12: 0 | AI12: 0 | AJ12: 0 | AK12: 0
A13: REGION | B13: PHL_DEM_PUB_SUR_WAT | C13: 0 | D13: 0 | E13: 0 | F13: 0 | G13: 0 | H13: 0 | I13: 0 | J13: 0 | K13: 0 | L13: 0 | M13: 0 | N13: 0 | O13: 0 | P13: 0 | Q13: 0 | R13: 0 | S13: 0 | T13: 0 | U13: 0 | V13: 0 | W13: 0 | X13: 0 | Y13: 0 | Z13: 0 | AA13: 0 | AB13: 0 | AC13: 0 | AD13: 0 | AE13: 0 | AF13: 0 | AG13: 0 | AH13: 0 | AI13: 0 | AJ13: 0 | AK13: 0
A14: REGION | B14: PHL_DEM_PWR_GWT_WAT | C14: 0 | D14: 0 | E14: 0 | F14: 0 | G14: 0 | H14: 0 | I14: 0 | J14: 0 | K14: 0 | L14: 0 | M14: 0 | N14: 0 | O14: 0 | P14: 0 | Q14: 0 | R14: 0 | S14: 0 | T14: 0 | U14: 0 | V14: 0 | W14: 0 | X14: 0 | Y14: 0 | Z14: 0 | AA14: 0 | AB14: 0 | AC14: 0 | AD14: 0 | AE14: 0 | AF14: 0 | AG14: 0 | AH14: 0 | AI14: 0 | AJ14: 0 | AK14: 0
... A133: REGION | B133: PHL_TRA_VAN_NG | C133: 0 | D133: 0 | E133: 0 | F133: 0 | G133: 0 | H133: 0 | I133: 0 | J133: 0 | K133: 0 | L133: 0 | M133: 0 | N133: 0 | O133: 0 | P133: 0 | Q133: 0 | R133: 0 | S133: 0 | T133: 0 | U133: 0 | V133: 0 | W133: 0 | X133: 0 | Y133: 0 | Z133: 0 | AA133: 0 | AB133: 0 | AC133: 0 | AD133: 0 | AE133: 0 | AF133: 0 | AG133: 0 | AH133: 0 | AI133: 0 | AJ133: 0 | AK133: 0
B134: PHL_TRA_VAN_PHEV | C134: 0 | D134: 0 | E134: 0 | F134: 0 | G134: 0 | H134: 0 | I134: 0 | J134: 0 | K134: 0 | L134: 0 | M134: 0 | N134: 0 | O134: 0 | P134: 0 | Q134: 0 | R134: 0 | S134: 0 | T134: 0 | U134: 0 | V134: 0 | W134: 0 | X134: 0 | Y134: 0 | Z134: 0 | AA134: 0 | AB134: 0 | AC134: 0 | AD134: 0 | AE134: 0 | AF134: 0 | AG134: 0 | AH134: 0 | AI134: 0 | AJ134: 0 | AK134: 0
B135: (blank)
A170: REGION | B170: GHA_PRO_BLEND_BIOF | C170: 0 | D170: 0 | E170: 0 | F170: 0 | G170: 0 | H170: 0 | I170: 0 | J170: 0 | K170: 0 | L170: 0 | M170: 0 | N170: 0 | O170: 0 | P170: 0 | Q170: 0 | R170: 0 | S170: 0 | T170: 0 | U170: 0 | V170: 0 | W170: 0 | X170: 0 | Y170: 0 | Z170: 0 | AA170: 0 | AB170: 0 | AC170: 0 | AD170: 0 | AE170: 0 | AF170: 0 | AG170: 0
A171: REGION | B171: GHA_PRO_BLEND_OIL | C171: 0 | D171: 0 | E171: 0 | F171: 0 | G171: 0 | H171: 0 | I171: 0 | J171: 0 | K171: 0 | L171: 0 | M171: 0 | N171: 0 | O171: 0 | P171: 0 | Q171: 0 | R171: 0 | S171: 0 | T171: 0 | U171: 0 | V171: 0 | W171: 0 | X171: 0 | Y171: 0 | Z171: 0 | AA171: 0 | AB171: 0 | AC171: 0 | AD171: 0 | AE171: 0 | AF171: 0 | AG171: 0
A172: REGION | B172: GHA_PRO_EXTR_COAL | C172: 0 | D172: 0 | E172: 0 | F172: 0 | G172: 0 | H172: 0 | I172: 0 | J172: 0 | K172: 0 | L172: 0 | M172: 0 | N172: 0 | O172: 0 | P172: 0 | Q172: 0 | R172: 0 | S172: 0 | T172: 0 | U172: 0 | V172: 0 | W172: 0 | X172: 0 | Y172: 0 | Z172: 0 | AA172: 0 | AB172: 0 | AC172: 0 | AD172: 0 | AE172: 0 | AF172: 0 | AG172: 0
A173: REGION | B173: GHA_PRO_EXTR_NG | C173: 0 | D173: 0 | E173: 0 | F173: 0 | G173: 0 | H173: 0 | I173: 0 | J173: 0 | K173: 0 | L173: 0 | M173: 0 | N173: 0 | O173: 0 | P173: 0 | Q173: 0 | R173: 0 | S173: 0 | T173: 0 | U173: 0 | V173: 0 | W173: 0 | X173: 0 | Y173: 0 | Z173: 0 | AA173: 0 | AB173: 0 | AC173: 0 | AD173: 0 | AE173: 0 | AF173: 0 | AG173: 0
A174: REGION | B174: GHA_PRO_EXTR_OIL | C174: 0 | D174: 0 | E174: 0 | F174: 0 | G174: 0 | H174: 0 | I174: 0 | J174: 0 | K174: 0 | L174: 0 | M174: 0 | N174: 0 | O174: 0 | P174: 0 | Q174: 0 | R174: 0 | S174: 0 | T174: 0 | U174: 0 | V174: 0 | W174: 0 | X174: 0 | Y174: 0 | Z174: 0 | AA174: 0 | AB174: 0 | AC174: 0 | AD174: 0 | AE174: 0 | AF174: 0 | AG174: 0
A175: REGION | B175: GHA_PRO_EXTR_UR | C175: 0 | D175: 0 | E175: 0 | F175: 0 | G175: 0 | H175: 0 | I175: 0 | J175: 0 | K175: 0 | L175: 0 | M175: 0 | N175: 0 | O175: 0 | P175: 0 | Q175: 0 | R175: 0 | S175: 0 | T175: 0 | U175: 0 | V175: 0 | W175: 0 | X175: 0 | Y175: 0 | Z175: 0 | AA175: 0 | AB175: 0 | AC175: 0 | AD175: 0 | AE175: 0 | AF175: 0 | AG175: 0
A176: REGION | B176: GHA_PRO_PROC_BIOF1 | C176: 0 | D176: 0 | E176: 0 | F176: 0 | G176: 0 | H176: 0 | I176: 0 | J176: 0 | K176: 0 | L176: 0 | M176: 0 | N176: 0 | O176: 0 | P176: 0 | Q176: 0 | R176: 0 | S176: 0 | T176: 0 | U176: 0 | V176: 0 | W176: 0 | X176: 0 | Y176: 0 | Z176: 0 | AA176: 0 | AB176: 0 | AC176: 0 | AD176: 0 | AE176: 0 | AF176: 8.93e-05 | AG176: 132.77715
A177: REGION | B177: GHA_PRO_PROC_BIOM | C177: 0 | D177: 0 | E177: 0 | F177: 0 | G177: 0 | H177: 0 | I177: 0 | J177: 0 | K177: 0 | L177: 0 | M177: 0 | N177: 0 | O177: 0 | P177: 0 | Q177: 0 | R177: 0 | S177: 0 | T177: 0 | U177: 0 | V177: 0 | W177: 0 | X177: 0 | Y177: 0 | Z177: 0 | AA177: 0 | AB177: 0 | AC177: 0 | AD177: 0 | AE177: 0 | AF177: 0 | AG177: 0
A178: REGION | B178: GHA_PRO_PROC_COAL | C178: 0 | D178: 0 | E178: 0 | F178: 0 | G178: 0 | H178: 0 | I178: 0 | J178: 0 | K178: 0 | L178: 0 | M178: 0 | N178: 0 | O178: 0 | P178: 0 | Q178: 0 | R178: 0 | S178: 0 | T178: 0 | U178: 0 | V178: 0 | W178: 0 | X178: 0 | Y178: 0 | Z178: 0 | AA178: 0 | AB178: 0 | AC178: 0 | AD178: 0 | AE178: 0 | AF178: 0 | AG178: 0
A179: REGION | B179: GHA_PRO_PROC_NG | C179: 0 | D179: 0 | E179: 0 | F179: 0 | G179: 0 | H179: 0 | I179: 0 | J179: 0 | K179: 0 | L179: 0 | M179: 0 | N179: 0 | O179: 0 | P179: 0 | Q179: 0 | R179: 0 | S179: 0 | T179: 0 | U179: 0 | V179: 0 | W179: 0 | X179: 0 | Y179: 0 | Z179: 0 | AA179: 0 | AB179: 0 | AC179: 0 | AD179: 0 | AE179: 0 | AF179: 0 | AG179: 0
A180: REGION | B180: GHA_PRO_PROC_OIL | C180: 0 | D180: 0 | E180: 0 | F180: 0 | G180: 0 | H180: 0 | I180: 0 | J180: 0 | K180: 0 | L180: 0 | M180: 0 | N180: 0 | O180: 0 | P180: 0 | Q180: 0 | R180: 0 | S180: 0 | T180: 0 | U180: 0 | V180: 0 | W180: 0 | X180: 0 | Y180: 0 | Z180: 0 | AA180: 0 | AB180: 0 | AC180: 0 | AD180: 0 | AE180: 0 | AF180: 0 | AG180: 0
A181: REGION | B181: GHA_PRO_PROC_TRADBIOM | C181: 0 | D181: 0 | E181: 0 | F181: 0 | G181: 0 | H181: 0 | I181: 0 | J181: 0 | K181: 0 | L181: 0 | M181: 0 | N181: 0 | O181: 0 | P181: 0 | Q181: 0 | R181: 0 | S181: 0 | T181: 0 | U181: 0 | V181: 0 | W181: 0 | X181: 0 | Y181: 0 | Z181: 0 | AA181: 0 | AB181: 0 | AC181: 0 | AD181: 0 | AE181: 0 | AF181: 0 | AG181: 0
... A220: REGION | B220: SLE_POST_UNIT | C220: 0 | D220: 0 | E220: 0 | F220: 0 | G220: 0 | H220: 0 | I220: 0 | J220: 0 | K220: 0 | L220: 0 | M220: 0 | N220: 0 | O220: 0 | P220: 0 | Q220: 0 | R220: 0 | S220: 0 | T220: 0 | U220: 0 | V220: 0 | W220: 0 | X220: 0 | Y220: 0 | Z220: 0 | AA220: 0 | AB220: 0 | AC220: 0 | AD220: 0 | AE220: 0 | AF220: 0 | AG220: 0

Sheet Annualized_Investments
A1: Million USD
B2: Year | C2: 2020 | D2: 2021 | E2: 2022 | F2: 2023 | G2: 2024 | H2: 2025 | I2: 2026 | J2: 2027 | K2: 2028 | L2: 2029 | M2: 2030 | N2: 2031 | O2: 2032 | P2: 2033 | Q2: 2034 | R2: 2035 | S2: 2036 | T2: 2037 | U2: 2038 | V2: 2039 | W2: 2040 | X2: 2041 | Y2: 2042 | Z2: 2043 | AA2: 2044 | AB2: 2045 | AC2: 2046 | AD2: 2047 | AE2: 2048 | AF2: 2049 | AG2: 2050 | AH2: 2051 | AI2: 2052 | AJ2: 2053
B3: PHL_AGR_HEAT_BIOM | C3: 0.20265373 | D3: 0.20265373 | E3: 0.20265373 | F3: 0.20265373 | G3: 0.20265373 | H3: 0.20265373 | I3: 0.20265373 | J3: 0.20265373 | K3: 0.20265373 | L3: 0.20265373 | M3: 0.20265373 | N3: 0.20265373 | O3: 0.20265373 | P3: 0.20265373 | Q3: 0.20265373 | R3: 0.20265373 | S3: 0.20265373 | T3: 0.20265373 | U3: 0.20265373 | V3: 0.20265373 | W3: 0.20265373 | X3: 0.20265373 | Y3: 0.20265373 | Z3: 0.20265373 | AA3: 0.20265373
B4: PHL_AGR_HEAT_NG | C4: 3.1837178 | D4: 3.3150272 | E4: 3.4060153 | F4: 3.4976385 | G4: 3.5898294 | H4: 3.6825407 | I4: 3.7830769 | J4: 3.8840591 | K4: 3.9854468 | L4: 4.0871994 | M4: 4.1922361 | N4: 4.3107537 | O4: 4.4292713 | P4: 4.547789 | Q4: 4.6663066 | R4: 4.7848242 | S4: 4.9246817 | T4: 5.0645391 | U4: 5.2043965 | V4: 5.344254 | W4: 5.4408642 | X4: 5.4408642 | Y4: 5.4408642 | Z4: 5.4408642 | AA4: 5.4408642 | AB4: 4.0658056 | AC4: 3.9344962 | AD4: 3.8435081 | AE4: 3.7518849 | AF4: 3.659694 | AG4: 7.8931162 | AH4: 8.0929386 | AI4: 8.292315 | AJ4: 8.491286
B5: PHL_AGR_HEAT_OIL | C5: 0.73768932 | D5: 0.73768932 | E5: 0.73768932 | F5: 0.73768932 | G5: 0.73768932 | H5: 0.73768932 | I5: 0.73768932 | J5: 0.73768932 | K5: 0.73768932 | L5: 0.73768932 | M5: 0.73768932 | N5: 0.73768932 | O5: 0.73768932 | P5: 0.73768932 | Q5: 0.73768932 | R5: 0.73768932 | S5: 0.73768932 | T5: 0.73768932 | U5: 0.73768932 | V5: 0.73768932 | W5: 0.73768932 | X5: 0.73768932 | Y5: 0.73768932 | Z5: 0.73768932 | AA5: 0.73768932
B6: PHL_AGR_MOT_LIQ | C6: 1309.3852 | D6: 1343.3332 | E6: 1377.2813 | F6: 1411.8249 | G6: 1446.9641 | H6: 1482.6989 | I6: 1521.7772 | J6: 1561.4962 | K6: 1601.8558 | L6: 1643.4966 | M6: 1685.7781 | N6: 1733.9893 | O6: 1782.9201 | P6: 1831.8509 | Q6: 1877.5976 | R6: 2198.7256 | S6: 2259.9655 | T6: 2321.2054 | U6: 2383.2292 | V6: 2444.6575 | W6: 2505.4901 | X6: 2575.1311 | Y6: 2645.6846 | Z6: 2715.5975 | AA6: 2784.2291 | AB6: 2852.2201 | AC6: 2928.9705 | AD6: 3005.0013 | AE6: 3082.7921 | AF6: 3159.6936 | AG6: 3305.498 | AH6: 3391.9993 | AI6: 3478.5006 | AJ6: 3563.6224
B7: PHL_HOU_COOK_BIOM | C7: 2083.34 | D7: 2083.34 | E7: 2083.34 | F7: 2083.34 | G7: 2083.34 | H7: 2083.34 | I7: 2083.34 | J7: 2083.34 | K7: 2083.34 | L7: 2083.34 | M7: 2083.34 | N7: 2083.34 | O7: 2083.34 | P7: 2083.34 | Q7: 2083.34
B8: PHL_HOU_COOK_COAL | D8: 2205.9097 | E8: 2239.8151 | F8: 2273.7113 | G8: 2308.647 | H8: 2371.8781 | I8: 2404.0009 | J8: 2436.0244 | K8: 2467.6978 | L8: 2500.1292 | M8: 2532.2476 | N8: 2561.8454 | O8: 2584.1201 | P8: 2613.7796 | Q8: 2642.8012 | R8: 2752.3885 | S8: 2778.612 | T8: 2804.8354 | U8: 2831.068 | V8: 2857.2915 | W8: 2883.5241 | X8: 2906.8206 | Y8: 2930.1171 | Z8: 2953.4135 | AA8: 2976.71 | AB8: 3000.0157 | AC8: 3020.1741 | AD8: 3040.3326 | AE8: 3060.4911 | AF8: 3080.6587 | AG8: 3100.8172 | AH8: 3118.2139 | AI8: 3135.6013 | AJ8: 3152.998
B9: PHL_HOU_COOK_ELE | C9: 101.97367 | D9: 101.97367 | E9: 101.97367 | F9: 101.97367 | G9: 101.97367 | H9: 101.97367 | I9: 101.97367 | J9: 101.97367 | K9: 101.97367 | L9: 101.97367 | M9: 101.97367 | N9: 101.97367 | O9: 101.97367 | P9: 101.97367 | Q9: 101.97367
B10: PHL_INDU_OTHHPH_BIOM | C10: 23.647988 | D10: 23.647988 | E10: 23.647988 | F10: 23.647988 | G10: 23.647988 | H10: 23.647988 | I10: 23.647988 | J10: 23.647988 | K10: 23.647988 | L10: 23.647988 | M10: 23.647988 | N10: 23.647988 | O10: 23.647988 | P10: 23.647988 | Q10: 23.647988 | R10: 23.647988 | S10: 23.647988 | T10: 23.647988 | U10: 23.647988 | V10: 23.647988 | W10: 23.647988 | X10: 23.647988 | Y10: 23.647988 | Z10: 23.647988 | AA10: 23.647988
B11: PHL_INDU_OTHHPH_COAL | C11: 46.682345 | D11: 137.70501 | E11: 140.83673 | F11: 143.9507 | G11: 147.04756 | H11: 150.12794 | I11: 153.44366 | J11: 156.74292 | K11: 160.02638 | L11: 163.29472 | M11: 166.51787 | N11: 170.15337 | O11: 173.77412 | P11: 177.38088 | Q11: 180.97443 | R11: 184.55551 | S11: 188.78726 | T11: 193.00596 | U11: 197.21242 | V11: 201.40743 | W11: 205.55182 | X11: 210.35264 | Y11: 215.14384 | Z11: 219.92939 | AA11: 224.6288 | AB11: 224.27074 | AC11: 220.1482 | AD11: 225.17262 | AE11: 230.20602 | AF11: 235.24864 | AG11: 240.2367 | AH11: 245.74307 | AI11: 251.2659 | AJ11: 256.80453
B12: PHL_INDU_OTHHPH_NG | C12: 0.2391233 | D12: 0.2391233 | E12: 0.2391233 | F12: 0.2391233 | G12: 0.2391233 | H12: 0.2391233 | I12: 0.2391233 | J12: 0.2391233 | K12: 0.2391233 | L12: 0.2391233 | M12: 0.2391233 | N12: 0.2391233 | O12: 0.2391233 | P12: 0.2391233 | Q12: 0.2391233 | R12: 0.2391233 | S12: 0.2391233 | T12: 0.2391233 | U12: 0.2391233 | V12: 0.2391233 | W12: 0.2391233 | X12: 0.2391233 | Y12: 0.2391233 | Z12: 0.2391233 | AA12: 0.2391233
B13: PHL_INDU_OTHHPH_OIL | C13: 30.260845 | D13: 30.260845 | E13: 30.260845 | F13: 30.260845 | G13: 30.260845 | H13: 30.260845 | I13: 30.260845 | J13: 30.260845 | K13: 30.260845 | L13: 30.260845 | M13: 30.260845 | N13: 30.260845 | O13: 30.260845 | P13: 30.260845 | Q13: 30.260845 | R13: 30.260845 | S13: 30.260845 | T13: 30.260845 | U13: 30.260845 | V13: 30.260845 | W13: 30.260845 | X13: 30.260845 | Y13: 30.260845 | Z13: 30.260845 | AA13: 30.260845
B14: PHL_INDU_OTHLPH_BIOM | C14: 23.647988 | D14: 23.647988 | E14: 23.647988 | F14: 23.647988 | G14: 23.647988 | H14: 23.647988 | I14: 23.647988 | J14: 23.647988 | K14: 23.647988 | L14: 23.647988 | M14: 23.647988 | N14: 23.647988 | O14: 23.647988 | P14: 23.647988 | Q14: 23.647988 | R14: 23.647988 | S14: 23.647988 | T14: 23.647988 | U14: 23.647988 | V14: 23.647988 | W14: 23.647988 | X14: 23.647988 | Y14: 23.647988 | Z14: 23.647988 | AA14: 23.647988
B15: PHL_INDU_OTHLPH_COAL | C15: 46.682345 | D15: 136.79113 | E15: 139.92285 | F15: 143.03683 | G15: 146.13369 | H15: 149.21407 | I15: 152.52979 | J15: 155.82904 | K15: 159.11251 | L15: 162.38085 | M15: 165.60399 | N15: 169.2395 | O15: 172.86024 | P15: 176.46701 | Q15: 180.06055 | R15: 183.64164 | S15: 187.87339 | T15: 192.09209 | U15: 196.29855 | V15: 200.49355 | W15: 204.63794 | X15: 209.43877 | Y15: 214.22996 | Z15: 219.01552 | AA15: 223.71493 | AB15: 224.17678 | AC15: 220.14928 | AD15: 225.1737 | AE15: 230.2071 | AF15: 235.24972 | AG15: 240.23778 | AH15: 245.74415 | AI15: 251.26698 | AJ15: 256.80561
B16: PHL_INDU_OTHLPH_ELE | D16: 1.3275948 | E16: 1.3275948 | F16: 1.3275948 | G16: 1.3275948 | H16: 1.3275948 | I16: 1.3275948 | J16: 1.3275948 | K16: 1.3275948 | L16: 1.3275948 | M16: 1.3275948 | N16: 1.3275948 | O16: 1.3275948 | P16: 1.3275948 | Q16: 1.3275948 | R16: 1.3275948 | S16: 1.3275948 | T16: 1.3275948 | U16: 1.3275948 | V16: 1.3275948 | W16: 1.3275948 | X16: 1.3275948 | Y16: 1.3275948 | Z16: 1.3275948 | AA16: 1.3275948 | AB16: 1.3275948
B17: PHL_INDU_OTHLPH_NG | C17: 0.21971611 | D17: 0.21971611 | E17: 0.21971611 | F17: 0.21971611 | G17: 0.21971611 | H17: 0.21971611 | I17: 0.21971611 | J17: 0.21971611 | K17: 0.21971611 | L17: 0.21971611 | M17: 0.21971611 | N17: 0.21971611 | O17: 0.21971611 | P17: 0.21971611 | Q17: 0.21971611 | R17: 0.21971611 | S17: 0.21971611 | T17: 0.21971611 | U17: 0.21971611 | V17: 0.21971611 | W17: 0.21971611 | X17: 0.21971611 | Y17: 0.21971611 | Z17: 0.21971611 | AA17: 0.21971611
B18: PHL_INDU_OTHLPH_OIL | C18: 34.242722 | D18: 34.242722 | E18: 34.242722 | F18: 34.242722 | G18: 34.242722 | H18: 34.242722 | I18: 34.242722 | J18: 34.242722 | K18: 34.242722 | L18: 34.242722 | M18: 34.242722 | N18: 34.242722 | O18: 34.242722 | P18: 34.242722 | Q18: 34.242722 | R18: 34.242722 | S18: 34.242722 | T18: 34.242722 | U18: 34.242722 | V18: 34.242722
B19: PHL_POW_CHP_BIOM_OLD | E19: 20.480611 | F19: 21.979192 | G19: 24.451851 | H19: 24.451851 | I19: 24.451851 | J19: 24.451851 | K19: 24.451851 | L19: 24.451851 | M19: 24.451851 | N19: 24.451851 | O19: 24.451851 | P19: 24.451851 | Q19: 24.451851 | R19: 24.451851 | S19: 24.451851 | T19: 24.451851 | U19: 24.451851 | V19: 24.451851 | W19: 24.451851 | X19: 24.451851 | Y19: 24.451851 | Z19: 24.451851 | AA19: 24.451851 | AB19: 24.451851 | AC19: 24.451851 | AD19: 24.451851 | AE19: 24.451851 | AF19: 24.451851 | AG19: 24.451851 | AH19: 24.451851 | AI19: 24.451851 | AJ19: 24.451851
B20: PHL_POW_CHP_OIL_OLD | D20: 12.973274 | E20: 19.99385 | F20: 19.99385 | G20: 20.801973 | H20: 20.801973 | I20: 20.801973 | J20: 20.801973 | K20: 20.801973 | L20: 20.801973 | M20: 20.801973 | N20: 20.801973 | O20: 20.801973 | P20: 20.801973 | Q20: 20.801973 | R20: 20.801973 | S20: 20.801973 | T20: 20.801973 | U20: 20.801973 | V20: 20.801973 | W20: 20.801973 | X20: 20.801973 | Y20: 20.801973 | Z20: 20.801973 | AA20: 20.801973 | AB20: 20.801973 | AC20: 20.801973 | AD20: 20.801973 | AE20: 20.801973 | AF20: 20.801973 | AG20: 20.801973 | AH20: 20.801973 | AI20: 20.801973 | AJ20: 20.801973
B21: PHL_POW_GEO_OLD | E21: 0.90358901 | F21: 69.548414 | G21: 71.190132 | H21: 79.908545 | I21: 283.54049 | J21: 488.63029 | K21: 698.77249 | L21: 746.15278 | M21: 746.15278 | N21: 746.15278 | O21: 746.15278 | P21: 780.34264 | Q21: 780.34264 | R21: 780.34264 | S21: 806.83977 | T21: 955.8587 | U21: 955.8587 | V21: 955.8587 | W21: 955.8587 | X21: 955.8587 | Y21: 955.8587 | Z21: 955.8587 | AA21: 955.8587 | AB21: 955.8587 | AC21: 955.8587 | AD21: 955.8587 | AE21: 955.8587 | AF21: 955.8587 | AG21: 956.97402 | AH21: 956.97402 | AI21: 956.97402 | AJ21: 956.97402
B22: PHL_POW_PP_COAL | D22: 107.78016 | E22: 222.16093 | F22: 222.16093 | G22: 311.3583 | H22: 311.3583 | I22: 311.3583 | J22: 311.3583 | K22: 311.3583 | L22: 311.3583 | M22: 311.3583 | N22: 439.77153 | O22: 903.90694 | P22: 1067.2985 | Q22: 1230.6901 | R22: 1394.0817 | S22: 1706.0797 | T22: 1904.4997 | U22: 2202.6845 | V22: 2491.7926 | W22: 2491.7926 | X22: 2580.0066 | Y22: 2760.2474 | Z22: 2940.8879 | AA22: 3121.9038 | AB22: 3308.467 | AC22: 3542.9885 | AD22: 3731.6843 | AE22: 3902.9327 | AF22: 3898.5044 | AG22: 3898.5044 | AH22: 4106.7128 | AI22: 4273.608 | AJ22: 4537.3715
B23: PHL_POW_PP_HY_LA | C23: 210.64731 | D23: 578.3826 | E23: 580.67144 | F23: 587.40838 | G23: 592.47549 | H23: 592.47549 | I23: 592.47549 | J23: 592.47549 | K23: 592.47549 | L23: 592.47549 | M23: 592.47549 | N23: 592.47549 | O23: 592.47549 | P23: 592.47549 | Q23: 592.47549 | R23: 592.47549 | S23: 592.47549 | T23: 592.47549 | U23: 592.47549 | V23: 592.47549 | W23: 592.47549 | X23: 592.47549 | Y23: 592.47549 | Z23: 592.47549 | AA23: 592.47549 | AB23: 592.47549 | AC23: 592.47549 | AD23: 592.47549 | AE23: 592.47549 | AF23: 592.47549 | AG23: 592.47549 | AH23: 592.47549 | AI23: 592.47549 | AJ23: 592.47549
B24: PHL_POW_PP_NGCC | H24: 71.3579 | I24: 71.3579 | J24: 71.3579 | K24: 71.3579 | L24: 71.3579 | M24: 71.3579 | N24: 71.3579 | O24: 71.3579 | P24: 71.3579 | Q24: 71.3579 | R24: 71.3579 | S24: 71.3579 | T24: 71.3579 | U24: 74.0352 | V24: 134.48044 | W24: 252.43431 | X24: 309.54631 | Y24: 324.87179 | Z24: 338.90418 | AA24: 358.23102 | AB24: 378.68358 | AC24: 445.38711 | AD24: 465.47093 | AE24: 495.35106 | AF24: 623.77278 | AG24: 832.4559 | AH24: 859.35934 | AI24: 887.86833 | AJ24: 914.89341
B25: PHL_POW_PP_SPV_T1 | D25: 17.87676 | E25: 35.182747 | F25: 43.737239 | G25: 96.293446 | H25: 110.19144 | I25: 110.19144 | J25: 110.19144 | K25: 110.19144 | L25: 110.19144 | M25: 455.58903 | N25: 455.58903 | O25: 455.58903 | P25: 455.58903 | Q25: 456.74671 | R25: 456.74671 | S25: 456.74671 | T25: 456.74671 | U25: 456.74671 | V25: 456.74671 | W25: 960.52234 | X25: 1003.6009 | Y25: 1048.6242 | Z25: 1092.6187 | AA25: 1136.2448 | AB25: 1181.964 | AC25: 1241.5087 | AD25: 1286.2506 | AE25: 1371.3036 | AF25: 1371.3036 | AG25: 1589.5034 | AH25: 1617.8316 | AI25: 1646.7806 | AJ25: 1681.5174
B26: PHL_POW_PP_WON_T1 | C26: 24.191247 | D26: 39.44785 | E26: 39.44785 | F26: 41.740986 | G26: 41.740986 | H26: 41.740986 | I26: 41.740986 | J26: 41.740986 | K26: 41.740986 | L26: 41.740986 | M26: 41.740986 | N26: 41.740986 | O26: 41.740986 | P26: 41.740986 | Q26: 41.740986 | R26: 41.740986 | S26: 41.740986 | T26: 41.740986 | U26: 41.740986 | V26: 41.740986 | W26: 41.740986 | X26: 41.740986 | Y26: 41.740986 | Z26: 41.740986 | AA26: 41.740986 | AB26: 17.549739 | AC26: 2.2931361 | AD26: 2.2931361
B27: PHL_POW_TD | H27: 23.98163 | I27: 92.675423 | J27: 161.36922 | K27: 230.06301 | L27: 298.7568 | M27: 367.45059 | N27: 449.53951 | O27: 531.62842 | P27: 613.71733 | Q27: 695.80624 | R27: 777.89515 | S27: 877.58254 | T27: 977.26994 | U27: 1076.9573 | V27: 1176.6447 | W27: 1276.3321 | X27: 1376.5677 | Y27: 1484.8453 | Z27: 1593.3639 | AA27: 1702.1089 | AB27: 1811.0661 | AC27: 1923.9257 | AD27: 2036.9537 | AE27: 2150.1401 | AF27: 2263.4756 | AG27: 2425.2209 | AH27: 2533.8501 | AI27: 2642.4794 | AJ27: 2751.1087
B28: PHL_PRO_PROC_BIOF | C28: 635.13228 | D28: 655.25975 | E28: 675.88904 | F28: 695.99032 | G28: 716.53678 | H28: 736.90565 | I28: 761.38787 | J28: 785.5472 | K28: 809.73749 | L28: 833.17026 | M28: 833.17026 | N28: 851.84471 | O28: 880.95083 | P28: 910.82849 | Q28: 939.56291 | R28: 969.13861 | S28: 1002.4587 | T28: 1035.6895 | U28: 1068.8716 | V28: 1101.217 | W28: 1132.2617 | X28: 1168.5355 | Y28: 1205.0146 | Z28: 1241.3978 | AA28: 1276.5853 | AB28: 1299.9992 | AC28: 1337.3574 | AD28: 1374.7543 | AE28: 1412.7891 | AF28: 1447.114 | AG28: 1477.2634 | AH28: 1516.2539 | AI28: 1555.0058 | AJ28: 1594.293
B29: PHL_SER_HEAT_BIOM | C29: 182.57059 | D29: 182.57059 | E29: 182.57059 | F29: 182.57059 | G29: 182.57059 | H29: 182.57059 | I29: 182.57059 | J29: 182.57059 | K29: 182.57059 | L29: 182.57059 | M29: 182.57059 | N29: 182.57059 | O29: 182.57059 | P29: 182.57059 | Q29: 182.57059
B30: PHL_SER_HEAT_NG | D30: 128.83128 | E30: 141.08394 | F30: 153.3676 | G30: 707.5684 | H30: 717.27681 | I30: 726.52879 | J30: 735.80357 | K30: 745.10092 | L30: 754.42056 | M30: 763.76567 | N30: 772.85538 | O30: 781.96754 | P30: 791.10192 | Q30: 816.36903 | R30: 961.26258 | S30: 998.81799 | T30: 1032.0554 | U30: 1065.3561 | V30: 1118.3228 | W30: 1151.7316 | X30: 1206.3931 | Y30: 1261.1706 | Z30: 1316.0507 | AA30: 1371.021 | AB30: 1426.0672 | AC30: 1494.6771 | AD30: 1563.3635 | AE30: 1632.1167 | AF30: 1701.409 | AG30: 1775.9358 | AH30: 1865.209 | AI30: 1950.1936 | AJ30: 2035.0839
B31: PHL_SER_HEAT_OIL | C31: 599.26102 | D31: 599.26102 | E31: 599.26102 | F31: 599.26102 | G31: 599.26102 | H31: 599.26102 | I31: 599.26102 | J31: 599.26102 | K31: 599.26102 | L31: 599.26102 | M31: 599.26102 | N31: 599.26102 | O31: 599.26102 | P31: 599.26102 | Q31: 599.26102
B32: PHL_SER_HEAT_RES | C32: 3421.7516
B33: PHL_TRA_23WHEEL_LIQ | C33: 2.981702 | D33: 21.647002 | E33: 40.038644 | F33: 58.509791 | G33: 77.135003 | H33: 95.373369 | I33: 113.62742 | J33: 131.88224 | K33: 150.21657 | L33: 170.6345 | M33: 182.68698 | N33: 204.85847 | O33: 222.9915 | P33: 240.54486 | Q33: 244.28017 | R33: 246.31943 | S33: 248.73301 | T33: 251.14582 | U33: 253.5594 | V33: 250.95147 | W33: 258.71616 | X33: 260.89929 | Y33: 262.73559 | Z33: 264.90972 | AA33: 267.08385 | AB33: 269.25876 | AC33: 271.17545 | AD33: 273.09215 | AE33: 274.3045 | AF33: 270.56919 | AG33: 278.84223 | AH33: 280.53072 | AI33: 282.21923 | AJ33: 283.90773
B34: PHL_TRA_AVI_LIQ | D34: 104.7431 | E34: 212.20702 | F34: 319.67095 | G34: 421.59163 | H34: 528.65793 | I34: 651.38586 | J34: 771.87264 | K34: 885.85313 | L34: 1004.9254 | M34: 1127.3526 | N34: 1271.5447 | O34: 1410.2956 | P34: 1553.0458 | Q34: 1693.2005 | R34: 1829.8513 | S34: 1988.5369 | T34: 2147.5794 | U34: 2300.2603 | V34: 2492.7162 | W34: 2492.7162 | X34: 2660.0334 | Y34: 2798.6482 | Z34: 2913.757 | AA34: 3008.1852 | AB34: 3081.4028 | AC34: 3166.7153 | AD34: 3232.7421 | AE34: 3284.0212 | AF34: 3467.6864 | AG34: 3345.2592 | AH34: 3201.0671 | AI34: 3062.3162 | AJ34: 2919.5661
B35: PHL_TRA_BUS_LIQ | C35: 0.010915386 | D35: 21.273618 | E35: 33.363733 | F35: 55.035066 | G35: 67.338494 | H35: 89.412265 | I35: 101.74769 | J35: 123.92285 | K35: 136.46817 | L35: 158.90769 | M35: 171.93558 | N35: 197.0659 | O35: 211.04644 | P35: 235.98887 | Q35: 239.53291 | R35: 243.76522 | S35: 246.91431 | T35: 250.66959 | U35: 253.78153 | V35: 257.3749 | W35: 260.0937 | X35: 263.34073 | Y35: 266.04537 | Z35: 269.27371 | AA35: 271.78283 | AB35: 274.51255 | AC35: 276.71958 | AD35: 279.07102 | AE35: 281.25836 | AF35: 283.62343 | AG35: 285.84791 | AH35: 288.59173 | AI35: 290.76978 | AJ35: 293.25555
B36: PHL_TRA_CAR_LIQ | C36: 47.200133 | D36: 181.40788 | E36: 316.13177 | F36: 450.07283 | G36: 585.70606 | H36: 721.71825 | I36: 861.0681 | J36: 999.47156 | K36: 1139.4647 | L36: 1279.7514 | M36: 1422.032 | N36: 1562.7688 | O36: 1704.9185 | P36: 1847.1371 | Q36: 1905.0929 | R36: 1965.2254 | S36: 2027.0755 | T36: 2088.5077 | U36: 2149.514 | V36: 2210.2368 | W36: 2270.9176 | X36: 2325.3194 | Y36: 2379.4242 | Z36: 2433.2773 | AA36: 2486.9086 | AB36: 2538.5907 | AC36: 2580.9132 | AD36: 2623.1632 | AE36: 2665.3754 | AF36: 2706.9713 | AG36: 2749.036 | AH36: 2781.8218 | AI36: 2814.5095 | AJ36: 2847.0975
B37: PHL_TRA_RAILF_ELE | C37: 2.323214 | D37: 2.323214 | E37: 2.323214 | F37: 2.323214 | G37: 2.323214 | H37: 2.323214 | I37: 2.323214 | J37: 2.323214 | K37: 2.323214 | L37: 2.323214 | M37: 2.323214 | N37: 2.323214 | O37: 2.323214 | P37: 2.323214 | Q37: 2.323214 | R37: 2.323214 | S37: 2.323214 | T37: 2.323214 | U37: 2.323214 | V37: 2.323214
B38: PHL_TRA_RAILF_LIQ | E38: 1.2227442 | F38: 1.2227442 | G38: 2.4454884 | H38: 2.6163287 | I38: 3.8390728 | J38: 5.061817 | K38: 5.061817 | L38: 6.3982917 | M38: 8.1111882 | N38: 8.8437801 | O38: 8.8437801 | P38: 10.066524 | Q38: 11.289268 | R38: 12.512013 | S38: 13.734757 | T38: 14.957501 | U38: 16.180245 | V38: 18.625734 | W38: 22.009388 | X38: 23.232132 | Y38: 25.67762 | Z38: 28.123109 | AA38: 29.345853 | AB38: 31.791341 | AC38: 34.23683 | AD38: 36.682318 | AE38: 39.127806 | AF38: 41.573295 | AG38: 44.018783 | AH38: 47.687016 | AI38: 50.132504 | AJ38: 53.800737
B39: PHL_TRA_RAILP_ELE | C39: 2.323214 | D39: 2.323214 | E39: 2.323214 | F39: 2.323214 | G39: 2.323214 | H39: 2.323214 | I39: 2.323214 | J39: 2.323214 | K39: 2.323214 | L39: 2.323214 | M39: 2.323214 | N39: 2.323214 | O39: 2.323214 | P39: 2.323214 | Q39: 2.323214 | R39: 2.323214 | S39: 2.323214 | T39: 2.323214 | U39: 2.323214 | V39: 2.323214
B40: PHL_TRA_RAILP_LIQ | E40: 1.2227442 | F40: 1.2227442 | G40: 2.4454884 | H40: 2.6163287 | I40: 3.8390728 | J40: 3.8390728 | K40: 5.061817 | L40: 5.1755475 | M40: 6.888444 | N40: 7.6210359 | O40: 7.6210359 | P40: 8.8437801 | Q40: 10.066524 | R40: 11.289268 | S40: 12.512013 | T40: 13.734757 | U40: 14.957501 | V40: 16.180245 | W40: 19.563899 | X40: 22.009388 | Y40: 23.232132 | Z40: 24.454876 | AA40: 26.900364 | AB40: 28.123109 | AC40: 30.568597 | AD40: 33.014085 | AE40: 35.459574 | AF40: 37.905062 | AG40: 40.35055 | AH40: 42.796039 | AI40: 45.241527 | AJ40: 48.90976
B41: PHL_TRA_SHIP_LIQ | D41: 1602006.3 | E41: 3204412.4 | F41: 4806787.9 | G41: 6407561 | H41: 8004007.7 | I41: 9725532.5 | J41: 11437407 | K41: 13132164 | L41: 14805350 | M41: 16544764 | N41: 18362007 | O41: 20179218 | P41: 21978288 | Q41: 23741646 | R41: 25463818 | S41: 27229196 | T41: 28931498 | U41: 30565708 | V41: 32602490 | W41: 32602490 | X41: 33952430 | Y41: 35007163 | Z41: 35796163 | AA41: 36347628 | AB41: 36688215 | AC41: 36842620 | AD41: 36820690 | AE41: 36646898 | AF41: 37711436 | AG41: 35972021 | AH41: 34154779 | AI41: 32337567 | AJ41: 30538497
B42: PHL_TRA_TRUH_LIQ | C42: 24.962268 | D42: 91.317432 | E42: 158.89242 | F42: 227.59307 | G42: 297.33362 | H42: 368.03571 | I42: 446.97959 | J42: 520.98412 | K42: 601.60614 | L42: 683.00856 | M42: 769.23305 | N42: 864.31159 | O42: 959.64849 | P42: 1055.3092 | Q42: 1106.9737 | R42: 1164.4692 | S42: 1241.4645 | T42: 1317.5568 | U42: 1392.9784 | V42: 1467.7144 | W42: 1542.7188 | X42: 1628.8011 | Y42: 1713.5898 | Z42: 1798.5766 | AA42: 1883.0659 | AB42: 1962.9878 | AC42: 2049.9082 | AD42: 2136.7139 | AE42: 2223.4807 | AF42: 2308.3842 | AG42: 2395.7724 | AH42: 2486.1156 | AI42: 2576.142 | AJ42: 2665.7961
B43: PHL_TRA_TRUL_LIQ | D43: 173.67997 | E43: 349.43166 | F43: 523.87773 | G43: 700.29704 | H43: 875.42706 | I43: 1070.0536 | J43: 1265.0144 | K43: 1458.717 | L43: 1654.2965 | M43: 1849.3856 | N43: 2065.121 | O43: 2279.5094 | P43: 2495.7794 | Q43: 2609.7393 | R43: 2723.7484 | S43: 2867.9538 | T43: 3012.0239 | U43: 3155.9917 | V43: 3299.8219 | W43: 3444.3758 | X43: 3612.2874 | Y43: 3779.9972 | Z43: 3947.589 | AA43: 4115.0684 | AB43: 4281.5083 | AC43: 4462.5904 | AD43: 4643.5918 | AE43: 4824.4944 | AF43: 5004.1388 | AG43: 5184.2819 | AH43: 5368.5962 | AI43: 5552.6014 | AJ43: 5736.3385
B44: PHL_TRA_VAN_LIQ | D44: 23.256166 | E44: 48.181696 | F44: 71.54048 | G44: 96.568931 | H44: 120.0193 | I44: 147.57016 | J44: 173.51267 | K44: 201.15578 | L44: 227.18062 | M44: 255.00569 | N44: 283.82013 | O44: 314.29307 | P44: 343.17102 | Q44: 358.84864 | R44: 374.51675 | S44: 394.33599 | T44: 414.15724 | U44: 433.94551 | V44: 453.732 | W44: 473.60078 | X44: 496.69897 | Y44: 519.73979 | Z44: 542.79675 | AA44: 565.82428 | AB44: 588.71594 | AC44: 613.60324 | AD44: 638.49533 | AE44: 663.37568 | AF44: 688.06864 | AG44: 712.83821 | AH44: 738.18236 | AI44: 763.48308 | AJ44: 788.73239

Sheet AnnualProduction
A1: PJ
A2: REGION | B2: TECHNOLOGY | C2: FUEL | D2: 2020 | E2: 2021 | F2: 2022 | G2: 2023 | H2: 2024 | I2: 2025 | J2: 2026 | K2: 2027 | L2: 2028 | M2: 2029 | N2: 2030 | O2: 2031 | P2: 2032 | Q2: 2033 | R2: 2034 | S2: 2035 | T2: 2036 | U2: 2037 | V2: 2038 | W2: 2039 | X2: 2040 | Y2: 2041 | Z2: 2042 | AA2: 2043 | AB2: 2044 | AC2: 2045 | AD2: 2046 | AE2: 2047 | AF2: 2048 | AG2: 2049 | AH2: 2050
A3: REGION | B3: PHL_POW_CHP_BIOM_OLD | D3: 4.5001 | E3: 5.2021 | F3: 4.7592 | G3: 5.072 | H3: 5.2059 | X3: 0.962 | Y3: 1.0598 | Z3: 1.1684 | AA3: 1.311 | AB3: 1.311 | AC3: 1.311 | AD3: 1.311 | AE3: 1.311 | AF3: 1.311 | AG3: 1.2306 | AH3: 1.1186 | AI3: 1.1186 | AJ3: 1.0748 | AK3: 1.0716
A4: REGION | B4: PHL_POW_CHP_COAL_OLD | D4: 209.4481 | E4: 223.3868 | F4: 239.1476 | G4: 265.5137 | H4: 285.6921 | I4: 262.5129 | J4: 258.4477 | K4: 254.247 | L4: 249.5755 | M4: 260.0242 | N4: 222.862 | O4: 220.9949 | P4: 177.466 | Q4: 172.6758 | R4: 167.8579 | S4: 155.0169 | T4: 132.1785 | U4: 127.109 | V4: 107.4686 | W4: 86.262 | X4: 89.1792 | Y4: 93.9641 | Z4: 92.5939 | AA4: 91.2201 | AB4: 89.843 | AC4: 88.3806 | AD4: 81.8079 | AE4: 80.4114 | AF4: 79.8117 | AG4: 90.6074 | AH4: 100.4414 | AI4: 94.9542 | AJ4: 94.4741 | AK4: 82.2555
A5: REGION | B5: PHL_POW_CHP_NG_OLD | D5: 70.2 | E5: 68.6158 | F5: 64.3818 | G5: 60.0051 | H5: 64.969 | I5: 1.1774 | J5: 1.4884 | K5: 1.773 | L5: 1.9664 | M5: 6.6182 | N5: 11.7512 | O5: 13.425 | P5: 1.2662 | Q5: 1.2662 | R5: 1.2662 | S5: 1.2662 | T5: 1.2662 | U5: 1.2662 | V5: 1.2662 | W5: 1.2662 | X5: 1.2662 | Y5: 1.2662 | Z5: 1.264 | AA5: 1.3 | AB5: 1.264 | AC5: 1.264
A6: REGION | B6: PHL_POW_CHP_OIL_OLD | D6: 8.8922 | E6: 5.818 | F6: 9.068 | G6: 4.6938 | H6: 4.831
A7: REGION | B7: PHL_POW_GEO_OLD | D7: 38.8084 | E7: 36.0582 | F7: 37.5303 | G7: 38.628 | H7: 38.8398 | I7: 39.9666 | J7: 66.261 | K7: 92.745 | L7: 119.8818 | M7: 126 | N7: 126 | O7: 126 | P7: 126 | Q7: 126 | R7: 126 | S7: 126 | T7: 126 | U7: 126 | V7: 126 | W7: 126 | X7: 126 | Y7: 126 | Z7: 126 | AA7: 126 | AB7: 126 | AC7: 126 | AD7: 126 | AE7: 126 | AF7: 126 | AG7: 126 | AH7: 126.0005 | AI7: 126.0005 | AJ7: 126.0005 | AK7: 126.0005
A8: REGION | B8: PHL_POW_PP_COAL | I8: 66.0492 | J8: 66.0492 | K8: 66.0492 | L8: 66.0492 | M8: 66.0492 | N8: 66.0492 | O8: 93.2898 | P8: 180.5974 | Q8: 212.617 | R8: 244.5568 | S8: 273.9812 | T8: 329.978 | U8: 368.2076 | V8: 420.79 | W8: 471.9094 | X8: 389.134 | Y8: 404.0066 | Z8: 430.3696 | AA8: 456.7898 | AB8: 483.2652 | AC8: 510.6266 | AD8: 543.8587 | AE8: 571.4491 | AF8: 590.018 | AG8: 601.1482 | AH8: 576.2554 | AI8: 604.9568 | AJ8: 628.651 | AK8: 664.0844
A9: REGION | B9: PHL_POW_PP_HY_LA | D9: 25.8852 | E9: 33.0658 | F9: 36.3061 | G9: 37.0338 | H9: 39.2718 | I9: 39.2718 | J9: 39.2718 | K9: 39.2718 | L9: 39.2718 | M9: 39.2718 | N9: 39.2718 | O9: 39.2718 | P9: 39.2718 | Q9: 39.2718 | R9: 39.2718 | S9: 39.2718 | T9: 39.2718 | U9: 39.2718 | V9: 39.2718 | W9: 39.2718 | X9: 39.2718 | Y9: 39.2718 | Z9: 39.2718 | AA9: 39.2718 | AB9: 39.2718 | AC9: 39.2718 | AD9: 39.2718 | AE9: 39.1566 | AF9: 39.1566 | AG9: 39.1566 | AH9: 39.1566 | AI9: 39.1566 | AJ9: 39.1566 | AK9: 39.1566
A10: REGION | B10: PHL_POW_PP_NGCC | I10: 5.5426 | J10: 5.6578 | K10: 5.7598 | L10: 5.8164 | M10: 7.1935 | N10: 7.6731 | O10: 7.7795 | P10: 4.203 | Q10: 4.0328 | R10: 3.8602 | S10: 3.69 | T10: 3.4832 | U10: 3.2764 | V10: 3.2876 | W10: 8.0192 | X10: 17.8052 | Y10: 22.325 | Z10: 23.4226 | AA10: 24.4515 | AB10: 25.6971 | AC10: 26.9633 | AD10: 29.4973 | AE10: 30.755 | AF10: 32.661 | AG10: 45.9039 | AH10: 65.1113 | AI10: 67.0911 | AJ10: 69.115 | AK10: 71.0988
A11: REGION | B11: PHL_POW_PP_SPV_T1 | D11: 4.957 | E11: 5.2922 | F11: 6.5591 | G11: 9.1579 | H11: 13.7201 | I11: 17.0982 | J11: 17.0982 | K11: 17.0982 | L11: 17.0982 | M11: 17.0982 | N11: 71.4016 | O11: 71.4016 | P11: 71.4016 | Q11: 71.4016 | R11: 71.5954 | S11: 71.5954 | T11: 71.5954 | U11: 71.5954 | V11: 71.5954 | W11: 71.5954 | X11: 173.777 | Y11: 182.7756 | Z11: 192.4404 | AA11: 202.1254 | AB11: 211.829 | AC11: 221.9404 | AD11: 232.2396 | AE11: 242.437 | AF11: 260.2838 | AG11: 262.8278 | AH11: 311.9987 | AI11: 323.0398 | AJ11: 334.0804 | AK11: 345.1211
A12: REGION | B12: PHL_POW_PP_WON_T1 | D12: 3.708 | E12: 4.5722 | F12: 3.7082 | G12: 4.7092 | H12: 4.4602 | I12: 4.7092 | J12: 4.7092 | K12: 4.7092 | L12: 4.7092 | M12: 4.7092 | N12: 4.525 | O12: 4.525 | P12: 4.525 | Q12: 4.525 | R12: 4.525 | S12: 4.525 | T12: 4.525 | U12: 4.525 | V12: 4.525 | W12: 2.8334 | X12: 2.3318 | Y12: 2.3318 | Z12: 2.3318 | AA12: 2.3318 | AB12: 2.3318 | AC12: 1.001 | AD12: 0.1372 | AE12: 0.1372
A13: REGION | B13: PHL_PRO_BLEND_BIOF | D13: 440.9859 | E13: 453.4509 | F13: 466.2607 | G13: 478.7299 | H13: 491.5885 | I13: 504.1727 | J13: 519.5923 | K13: 534.8081 | L13: 550.0577 | M13: 565.3444 | N13: 556.6327 | O13: 575.4974 | P13: 594.0882 | Q13: 612.9474 | R13: 631.7547 | S13: 650.5311 | T13: 672.0059 | U13: 693.4357 | V13: 714.8479 | W13: 736.4105 | X13: 755.8425 | Y13: 779.3991 | Z13: 802.9872 | AA13: 826.647 | AB13: 850.3606 | AC13: 874.121 | AD13: 899.6047 | AE13: 925.1267 | AF13: 950.7065 | AG13: 976.3176 | AH13: 995.2355 | AI13: 1021.9914 | AJ13: 1048.5684 | AK13: 1075.4968
A14: REGION | B14: PHL_PRO_EXTR_COAL | D14: 743.1913 | E14: 1183.9746 | F14: 1242.6016 | G14: 1334.6259 | H14: 1407.236 | I14: 1497.748 | J14: 1494.0393 | K14: 1489.8724 | L14: 1484.1655 | M14: 1526.1768 | N14: 1419.147 | O14: 1485.1382 | P14: 1556.769 | Q14: 1624.4906 | R14: 1067.8233
A15: REGION | B15: PHL_PRO_EXTR_NG | D15: 140.4442 | E15: 162.2445 | F15: 156.2115 | G15: 149.877 | H15: 271.055 | I15: 155.8977 | J15: 157.8027 | K15: 159.6605 | L15: 161.2847 | M15: 174.0544 | N15: 183.4574 | O15: 188.325 | P15: 159.4067 | Q15: 160.4732 | R15: 164.011 | S15: 175.2314 | T15: 180.0267 | U15: 184.8133 | V15: 189.9742 | W15: 203.3887 | X15: 225.2085 | Y15: 241.6058 | Z15: 252.0193 | AA15: 262.3948 | AB15: 273.0166 | AC15: 283.7012 | AD15: 296.3505 | AE15: 309.269 | AF15: 323.327 | AG15: 357.2274 | AH15: 399.2815 | AI15: 415.898 | AJ15: 432.591 | AK15: 449.2127
A16: REGION | B16: PHL_PRO_EXTR_OIL | D16: 244.7202
A17: REGION | B17: PHL_PRO_IMP_COAL | R17: 624.0437 | S17: 1736.9944 | T17: 1803.6576 | U17: 1885.5689 | V17: 1954.4731 | W17: 2015.0875 | X17: 1844.2937 | Y17: 1904.5224 | Z17: 1971.7222 | AA17: 2039.0644 | AB17: 2106.5408 | AC17: 2176.243 | AD17: 2244.1014 | AE17: 2315.0185 | AF17: 2367.7714 | AG17: 2439.3925 | AH17: 2423.6454 | AI17: 2485.1006 | AJ17: 2550.8518 | AK17: 2606.528
A18: REGION | B18: PHL_PRO_IMP_OIL | D18: 15.2005 | E18: 143.8235 | F18: 159.3693 | G18: 135.8633 | H18: 35.6929 | I18: 11.0006 | J18: 11.0836 | K18: 11.1692 | L18: 11.2568 | M18: 11.346 | N18: 11.225 | O18: 11.3302 | P18: 11.435 | Q18: 11.5392 | R18: 9.3394
A19: REGION | B19: PHL_PRO_PROC_BIOF | D19: 440.9859 | E19: 453.4509 | F19: 466.2607 | G19: 478.7299 | H19: 491.5885 | I19: 504.1727 | J19: 519.5923 | K19: 534.8081 | L19: 550.0577 | M19: 565.3444 | N19: 556.6327 | O19: 575.4974 | P19: 594.0882 | Q19: 612.9474 | R19: 631.7547 | S19: 650.5311 | T19: 672.0059 | U19: 693.4357 | V19: 714.8479 | W19: 736.4105 | X19: 755.8425 | Y19: 779.3991 | Z19: 802.9872 | AA19: 826.647 | AB19: 850.3606 | AC19: 874.121 | AD19: 899.6047 | AE19: 925.1267 | AF19: 950.7065 | AG19: 976.3176 | AH19: 995.2355 | AI19: 1021.9914 | AJ19: 1048.5684 | AK19: 1075.4968
A20: REGION | B20: PHL_PRO_PROC_BIOM | D20: 304.3033 | E20: 22.5644 | F20: 20.8063 | G20: 22.0733 | H20: 20.8274 | X20: 3.8588 | Y20: 4.24 | Z20: 4.675 | AA20: 5.246 | AB20: 5.246 | AC20: 5.2452 | AD20: 5.2452 | AE20: 5.2452 | AF20: 5.2452 | AG20: 4.9234 | AH20: 4.4748 | AI20: 4.4748 | AJ20: 4.3002 | AK20: 4.287
A21: REGION | B21: PHL_PRO_PROC_COAL | D21: 740.2597 | E21: 1179.3038 | F21: 1237.6988 | G21: 1329.3613 | H21: 1401.6855 | I21: 1491.8392 | J21: 1488.1458 | K21: 1483.9944 | L21: 1478.3102 | M21: 1520.1558 | N21: 1413.5487 | O21: 1479.2795 | P21: 1550.6274 | Q21: 1618.0815 | R21: 1685.1929 | S21: 1730.141 | T21: 1796.5422 | U21: 1878.1304 | V21: 1946.763 | W21: 2007.1376 | X21: 1837.0176 | Y21: 1897.0086 | Z21: 1963.9433 | AA21: 2031.0199 | AB21: 2098.2308 | AC21: 2167.6581 | AD21: 2235.2485 | AE21: 2305.8862 | AF21: 2358.431 | AG21: 2429.7689 | AH21: 2414.0846 | AI21: 2475.2967 | AJ21: 2540.7889 | AK21: 2596.2458
A22: REGION | B22: PHL_PRO_PROC_NG | D22: 132.8989 | E22: 153.5286 | F22: 147.8201 | G22: 141.8256 | H22: 256.4934 | I22: 147.5223 | J22: 149.3249 | K22: 151.0832 | L22: 152.6203 | M22: 164.704 | N22: 173.6013 | O22: 178.2076 | P22: 150.8427 | Q22: 151.8518 | R22: 155.2001 | S22: 165.8176 | T22: 170.3555 | U22: 174.8847 | V22: 179.7683 | W22: 192.4623 | X22: 213.1099 | Y22: 228.6261 | Z22: 238.4802 | AA22: 248.2985 | AB22: 258.3499 | AC22: 268.4599 | AD22: 280.43 | AE22: 292.6546 | AF22: 305.9574 | AG22: 338.0364 | AH22: 377.8312 | AI22: 393.5553 | AJ22: 409.3509 | AK22: 425.0802
A23: REGION | B23: PHL_PRO_PROC_OIL | D23: 264.4028 | E23: 146.3042 | F23: 162.1177 | G23: 138.2064 | H23: 36.3081 | I23: 11.1902 | J23: 11.275 | K23: 11.3618 | L23: 11.4506 | M23: 11.5418 | N23: 11.4186 | O23: 11.5256 | P23: 11.6322 | Q23: 11.7382 | R23: 9.5004

Sheet New Capacity
A1: GW
A2: REGION | B2: TECHNOLOGY | C2: 2020 | D2: 2021 | E2: 2022 | F2: 2023 | G2: 2024 | H2: 2025 | I2: 2026 | J2: 2027 | K2: 2028 | L2: 2029 | M2: 2030 | N2: 2031 | O2: 2032 | P2: 2033 | Q2: 2034 | R2: 2035 | S2: 2036 | T2: 2037 | U2: 2038 | V2: 2039 | W2: 2040 | X2: 2041 | Y2: 2042 | Z2: 2043 | AA2: 2044 | AB2: 2045 | AC2: 2046 | AD2: 2047 | AE2: 2048 | AF2: 2049 | AG2: 2050
A3: REGION | B3: PHL_AGR_FAC | C3: 999999 | D3: 999999 | E3: 999999 | F3: 999999 | G3: 999999 | H3: 999999 | I3: 999999 | J3: 999999 | K3: 999999 | L3: 999999 | M3: 999999 | N3: 999999 | O3: 999999 | P3: 999999 | Q3: 999999 | R3: 999999 | S3: 999999 | T3: 999999 | U3: 999999 | V3: 999999 | W3: 999999 | X3: 999999 | Y3: 999999 | Z3: 999999 | AA3: 999999 | AB3: 999999 | AC3: 999999 | AD3: 999999 | AE3: 999999 | AF3: 999999 | AG3: 999999 | AH3: 999999 | AI3: 999999 | AJ3: 999999 | AK3: 33999966
A4: REGION | B4: PHL_AGR_HEAT_BIOM | C4: 0.0039 | D4: 0 | E4: 0 | F4: 0 | G4: 0 | H4: 0 | I4: 0 | J4: 0 | K4: 0 | L4: 0 | M4: 0 | N4: 0 | O4: 0 | P4: 0 | Q4: 0 | R4: 0 | S4: 0 | T4: 0 | U4: 0 | V4: 0 | W4: 0 | X4: 0 | Y4: 0 | Z4: 0 | AA4: 0 | AB4: 0 | AC4: 0 | AD4: 0 | AE4: 0 | AF4: 0 | AG4: 0 | AH4: 0 | AI4: 0 | AJ4: 0 | AK4: 0.0039
A5: REGION | B5: PHL_AGR_HEAT_COAL | C5: 0 | D5: 0 | E5: 0 | F5: 0 | G5: 0 | H5: 0 | I5: 0 | J5: 0 | K5: 0 | L5: 0 | M5: 0 | N5: 0 | O5: 0 | P5: 0 | Q5: 0 | R5: 0 | S5: 0 | T5: 0 | U5: 0 | V5: 0 | W5: 0 | X5: 0 | Y5: 0 | Z5: 0 | AA5: 0 | AB5: 0 | AC5: 0 | AD5: 0 | AE5: 0 | AF5: 0 | AG5: 0 | AH5: 0 | AI5: 0 | AJ5: 0 | AK5: 0
A6: REGION | B6: PHL_AGR_HEAT_ELE | C6: 0 | D6: 0 | E6: 0 | F6: 0 | G6: 0 | H6: 0 | I6: 0 | J6: 0 | K6: 0 | L6: 0 | M6: 0 | N6: 0 | O6: 0 | P6: 0 | Q6: 0 | R6: 0 | S6: 0 | T6: 0 | U6: 0 | V6: 0 | W6: 0 | X6: 0 | Y6: 0 | Z6: 0 | AA6: 0 | AB6: 0 | AC6: 0 | AD6: 0 | AE6: 0 | AF6: 0 | AG6: 0 | AH6: 0 | AI6: 0 | AJ6: 0 | AK6: 0
A7: REGION | B7: PHL_AGR_HEAT_NG | C7: 0.315 | D7: 0.0129 | E7: 0.0089 | F7: 0.0089 | G7: 0.0089 | H7: 0.0089 | I7: 0.0096 | J7: 0.0096 | K7: 0.0096 | L7: 0.0096 | M7: 0.0096 | N7: 0.0108 | O7: 0.0108 | P7: 0.0108 | Q7: 0.0108 | R7: 0.0108 | S7: 0.0127 | T7: 0.0127 | U7: 0.0127 | V7: 0.0127 | W7: 0.0088 | X7: 0 | Y7: 0 | Z7: 0 | AA7: 0 | AB7: 0.1645 | AC7: 0 | AD7: 0 | AE7: 0 | AF7: 0 | AG7: 0.3935 | AH7: 0.0273 | AI7: 0.0273 | AJ7: 0.0273 | AK7: 1.165
A8: REGION | B8: PHL_AGR_HEAT_OIL | C8: 0.0375 | D8: 0 | E8: 0 | F8: 0 | G8: 0 | H8: 0 | I8: 0 | J8: 0 | K8: 0 | L8: 0 | M8: 0 | N8: 0 | O8: 0 | P8: 0 | Q8: 0 | R8: 0 | S8: 0 | T8: 0 | U8: 0 | V8: 0 | W8: 0 | X8: 0 | Y8: 0 | Z8: 0 | AA8: 0 | AB8: 0 | AC8: 0 | AD8: 0 | AE8: 0 | AF8: 0 | AG8: 0 | AH8: 0 | AI8: 0 | AJ8: 0 | AK8: 0.0375
A9: REGION | B9: PHL_AGR_MOT_ELE | C9: 0 | D9: 0 | E9: 0 | F9: 0 | G9: 0 | H9: 0 | I9: 0 | J9: 0 | K9: 0 | L9: 0 | M9: 0 | N9: 0 | O9: 0 | P9: 0 | Q9: 0 | R9: 0 | S9: 0 | T9: 0 | U9: 0 | V9: 0 | W9: 0 | X9: 0 | Y9: 0 | Z9: 0 | AA9: 0 | AB9: 0 | AC9: 0 | AD9: 0 | AE9: 0 | AF9: 0 | AG9: 0 | AH9: 0 | AI9: 0 | AJ9: 0 | AK9: 0
A10: REGION | B10: PHL_AGR_MOT_LIQ | C10: 250.36 | D10: 6.491 | E10: 6.491 | F10: 6.491 | G10: 6.491 | H10: 6.491 | I10: 6.982 | J10: 6.982 | K10: 6.982 | L10: 6.982 | M10: 6.982 | N10: 7.8423 | O10: 7.8423 | P10: 7.8423 | Q10: 7.2258 | R10: 257.5417 | S10: 15.0351 | T10: 15.0351 | U10: 15.0351 | V10: 15.0351 | W10: 15.0351 | X10: 16.927 | Y10: 16.927 | Z10: 16.927 | AA10: 16.927 | AB10: 16.927 | AC10: 19.1819 | AD10: 19.1819 | AE10: 19.1818 | AF10: 18.5653 | AG10: 268.8812 | AH10: 27.5023 | AI10: 27.5023 | AJ10: 27.5023 | AK10: 1193.3289
A11: REGION | B11: PHL_AGR_UNIT | C11: 999999 | D11: 999999 | E11: 999999 | F11: 999999 | G11: 999999 | H11: 999999 | I11: 999999 | J11: 999999 | K11: 999999 | L11: 999999 | M11: 999999 | N11: 999999 | O11: 999999 | P11: 999999 | Q11: 999999 | R11: 999999 | S11: 999999 | T11: 999999 | U11: 999999 | V11: 999999 | W11: 999999 | X11: 999999 | Y11: 999999 | Z11: 999999 | AA11: 999999 | AB11: 999999 | AC11: 999999 | AD11: 999999 | AE11: 999999 | AF11: 999999 | AG11: 999999 | AH11: 999999 | AI11: 999999 | AJ11: 999999 | AK11: 33999966
A12: REGION | B12: PHL_DEM_PUB_GWT_WAT | C12: 999999 | D12: 999999 | E12: 999999 | F12: 999999 | G12: 999999 | H12: 999999 | I12: 999999 | J12: 999999 | K12: 999999 | L12: 999999 | M12: 999999 | N12: 999999 | O12: 999999 | P12: 999999 | Q12: 999999 | R12: 999999 | S12: 999999 | T12: 999999 | U12: 999999 | V12: 999999 | W12: 999999 | X12: 999999 | Y12: 999999 | Z12: 999999 | AA12: 999999 | AB12: 999999 | AC12: 999999 | AD12: 999999 | AE12: 999999 | AF12: 999999 | AG12: 999999 | AH12: 999999 | AI12: 999999 | AJ12: 999999 | AK12: 33999966
A13: REGION | B13: PHL_DEM_PUB_SUR_WAT | C13: 999999 | D13: 999999 | E13: 999999 | F13: 999999 | G13: 999999 | H13: 999999 | I13: 999999 | J13: 999999 | K13: 999999 | L13: 999999 | M13: 999999 | N13: 999999 | O13: 999999 | P13: 999999 | Q13: 999999 | R13: 999999 | S13: 999999 | T13: 999999 | U13: 999999 | V13: 999999 | W13: 999999 | X13: 999999 | Y13: 999999 | Z13: 999999 | AA13: 999999 | AB13: 999999 | AC13: 999999 | AD13: 999999 | AE13: 999999 | AF13: 999999 | AG13: 999999 | AH13: 999999 | AI13: 999999 | AJ13: 999999 | AK13: 33999966
A14: REGION | B14: PHL_DEM_PWR_GWT_WAT | C14: 999999 | D14: 999999 | E14: 999999 | F14: 999999 | G14: 999999 | H14: 999999 | I14: 999999 | J14: 999999 | K14: 999999 | L14: 999999 | M14: 999999 | N14: 999999 | O14: 999999 | P14: 999999 | Q14: 999999 | R14: 999999 | S14: 999999 | T14: 999999 | U14: 999999 | V14: 999999 | W14: 999999 | X14: 999999 | Y14: 999999 | Z14: 999999 | AA14: 999999 | AB14: 999999 | AC14: 999999 | AD14: 999999 | AE14: 999999 | AF14: 999999 | AG14: 999999 | AH14: 999999 | AI14: 999999 | AJ14: 999999 | AK14: 33999966
... A133: REGION | B133: PHL_TRA_VAN_NG | C133: 0 | D133: 0 | E133: 0 | F133: 0 | G133: 0 | H133: 0 | I133: 0 | J133: 0 | K133: 0 | L133: 0 | M133: 0 | N133: 0 | O133: 0 | P133: 0 | Q133: 0 | R133: 0 | S133: 0 | T133: 0 | U133: 0 | V133: 0 | W133: 0 | X133: 0 | Y133: 0 | Z133: 0 | AA133: 0 | AB133: 0 | AC133: 0 | AD133: 0 | AE133: 0 | AF133: 0 | AG133: 0 | AH133: 0 | AI133: 0 | AJ133: 0 | AK133: 0
B134: PHL_TRA_VAN_PHEV | C134: 0 | D134: 0 | E134: 0 | F134: 0 | G134: 0 | H134: 0 | I134: 0 | J134: 0 | K134: 0 | L134: 0 | M134: 0 | N134: 0 | O134: 0 | P134: 0 | Q134: 0 | R134: 0 | S134: 0 | T134: 0 | U134: 0 | V134: 0 | W134: 0 | X134: 0 | Y134: 0 | Z134: 0 | AA134: 0 | AB134: 0 | AC134: 0 | AD134: 0 | AE134: 0 | AF134: 0 | AG134: 0 | AH134: 0 | AI134: 0 | AJ134: 0 | AK134: 0
B135: (blank)

Sheet UseByTech
A1: REGION | B1: TECHNOLOGY | C1: 2020 | D1: 2021 | E1: 2022 | F1: 2023 | G1: 2024 | H1: 2025 | I1: 2026 | J1: 2027 | K1: 2028 | L1: 2029 | M1: 2030 | N1: 2031 | O1: 2032 | P1: 2033 | Q1: 2034 | R1: 2035 | S1: 2036 | T1: 2037 | U1: 2038 | V1: 2039 | W1: 2040 | X1: 2041 | Y1: 2042 | Z1: 2043 | AA1: 2044 | AB1: 2045 | AC1: 2046 | AD1: 2047 | AE1: 2048 | AF1: 2049 | AG1: 2050
A2: REGION | B2: PHL_AGR_FAC | C2: 9.2938 | D2: 9.5034 | E2: 9.7123 | F2: 9.9217 | G2: 10.1309 | H2: 10.3402 | I2: 10.567 | J2: 10.794 | K2: 11.0206 | L2: 11.2478 | M2: 11.4744 | N2: 11.7322 | O2: 11.9903 | P2: 12.2473 | Q2: 12.5055 | R2: 12.763 | S2: 13.0696 | T2: 13.376 | U2: 13.6828 | V2: 13.9894 | W2: 14.2957 | X2: 11.2971 | Y2: 10.4153 | Z2: 9.5967 | AA2: 8.8376 | AB2: 8.134 | AC2: 7.506 | AD2: 6.9223 | AE2: 6.38 | AF2: 5.8771 | AG2: 18.1149 | AH2: 18.562 | AI2: 19.01 | AJ2: 19.457
A3: REGION | B3: PHL_AGR_HEAT_BIOM | C3: 0.139 | W3: 0.0098
A4: REGION | B4: PHL_AGR_MOT_LIQ | C4: 19.7328 | D4: 20.1771 | E4: 20.6217 | F4: 21.0655 | G4: 21.5095 | H4: 21.9541 | I4: 22.4358 | J4: 22.9171 | K4: 23.399 | L4: 23.8804 | M4: 24.3619 | N4: 24.909 | O4: 25.4562 | P4: 26.0035 | Q4: 26.5506 | R4: 27.0979 | S4: 27.7494 | T4: 28.4001 | U4: 29.051 | V4: 29.7018 | W4: 30.3527 | X4: 31.1107 | Y4: 31.8683 | Z4: 32.6257 | AA4: 33.3837 | AB4: 34.1412 | AC4: 35.0049 | AD4: 35.8695 | AE4: 36.7331 | AF4: 37.5974 | AG4: 38.4615 | AH4: 39.4112 | AI4: 40.3609 | AJ4: 41.3108
A5: REGION | B5: PHL_AGR_UNIT | C5: 18.1607 | D5: 18.57 | E5: 18.978 | F5: 19.3877 | G5: 19.7957 | H5: 20.2051 | I5: 20.6478 | J5: 21.0917 | K5: 21.5346 | L5: 21.978 | M5: 22.4216 | N5: 22.9249 | O5: 23.4292 | P5: 23.9321 | Q5: 24.4359 | R5: 24.9393 | S5: 25.5384 | T5: 26.1368 | U5: 26.7365 | V5: 27.3358 | W5: 27.9346 | X5: 23.7809 | Y5: 21.9246 | Z5: 20.2013 | AA5: 18.604 | AB5: 17.1227 | AC5: 15.8008 | AD5: 14.5714 | AE5: 13.43 | AF5: 12.3713 | AG5: 35.3972 | AH5: 36.2709 | AI5: 37.1461 | AJ5: 38.0196
A6: REGION | B6: PHL_DEM_PUB_GWT_WAT | H6: 1.7193 | J6: 0.9625 | M6: 0.9834 | O6: 4.0553 | Q6: 1.5131 | U6: 1.4782 | X6: 1.1753 | Y6: 1.2928 | Z6: 0.5516 | AA6: 4.4323 | AD6: 6.1326 | AG6: 1.3713
A7: REGION | B7: PHL_DEM_PUB_SUR_WAT | C7: 19.62 | D7: 20.37 | E7: 21.148 | F7: 21.955 | G7: 22.794 | H7: 21.9459 | I7: 24.568 | J7: 24.5435 | K7: 26.4789 | L7: 27.489 | M7: 27.5526 | N7: 29.6219 | O7: 26.6937 | P7: 31.917 | Q7: 31.6149 | R7: 34.383 | S7: 35.6849 | T7: 37.033 | U7: 36.9517 | V7: 39.8781 | W7: 41.377 | X7: 41.7547 | Y7: 43.2463 | Z7: 45.6525 | AA7: 43.4947 | AB7: 49.711 | AC7: 51.556 | AD7: 47.3324 | AE7: 55.439 | AF7: 57.4813 | AG7: 58.2206 | AH7: 61.7729 | AI7: 64.0279 | AJ7: 66.359
A8: REGION | B8: PHL_DEM_PWR_GWT_WAT | C8: 2.1732 | D8: 4.9309 | E8: 3.0309 | F8: 3.0579 | G8: 4.9517 | H8: 3.2403 | I8: 4.3324 | J8: 4.0128 | K8: 4.9837 | L8: 4.9923 | M8: 4.0176 | N8: 5.0107 | O8: 0.9652 | P8: 5.0305 | Q8: 3.5281 | R8: 5.1151 | S8: 5.4212 | T8: 5.7324 | U8: 4.5696 | V8: 6.3675 | W8: 6.2483 | X8: 5.3607 | Y8: 5.5553 | Z8: 6.6182 | AA8: 3.0487 | AB8: 7.8032 | AC8: 8.136 | AD8: 2.3394 | AE8: 8.7741 | AF8: 9.1298 | AG8: 7.9424 | AH8: 9.6643 | AI8: 10.0175 | AJ8: 10.3832
A9: REGION | B9: PHL_DEM_PWR_SUR_WAT | C9: 20.2484 | D9: 17.3106 | E9: 21.0892 | F9: 20.2877 | G9: 19.7771 | H9: 13.3895 | I9: 12.1067 | J9: 12.2279 | K9: 11.0311 | L9: 11.7256 | M9: 11.0105 | N9: 11.3397 | O9: 17.1024 | P9: 14.3928 | Q9: 17.2468 | R9: 16.4834 | S9: 17.829 | T9: 19.1697 | U9: 21.9798 | V9: 21.8195 | W9: 19.3364 | X9: 21.4538 | Y9: 22.665 | Z9: 23.0494 | AA9: 27.91 | AB9: 24.4885 | AC9: 25.527 | AD9: 32.6713 | AE9: 27.1915 | AF9: 28.238 | AG9: 29.121 | AH9: 28.619 | AI9: 29.4374 | AJ9: 30.2882
A10: REGION | B10: PHL_HOU_COOK_BIOM | C10: 236.7198
A11: REGION | B11: PHL_HOU_COOK_COAL | D11: 240.4152 | E11: 244.1082 | F11: 247.8036 | G11: 251.6112 | H11: 258.5028 | I11: 262.0038 | J11: 265.4934 | K11: 268.9458 | L11: 272.4804 | M11: 275.9808 | N11: 279.207 | O11: 281.634 | P11: 284.8662 | Q11: 288.03 | R11: 299.9736 | S11: 302.8314 | T11: 305.6886 | U11: 308.5488 | V11: 311.4054 | W11: 314.265 | X11: 316.8042 | Y11: 319.3416 | Z11: 321.882 | AA11: 324.4212 | AB11: 326.9604 | AC11: 329.1576 | AD11: 331.3548 | AE11: 333.5526 | AF11: 335.7498 | AG11: 337.947 | AH11: 339.8424 | AI11: 341.7378 | AJ11: 343.6332
A12: REGION | B12: PHL_HOU_COOK_ELE | C12: 12.3456 | D12: 12.2502 | E12: 12.1566 | F12: 12.0612 | G12: 11.8554 | H12: 8.5649 | I12: 8.4864 | J12: 8.4199 | K12: 8.3888 | L12: 8.2779 | M12: 8.2007 | N12: 8.1323 | O12: 8.8638 | P12: 8.79 | Q12: 8.784
A13: REGION | B13: PHL_HOU_UNIT | C13: 111.1048 | D13: 119.1777 | E13: 127.2505 | F13: 135.3235 | G13: 143.3961 | H13: 151.4688 | I13: 161.4651 | J13: 171.4613 | K13: 181.4575 | L13: 191.4534 | M13: 201.45 | N13: 213.1986 | O13: 224.9475 | P13: 236.6964 | Q13: 248.4452 | R13: 260.1939 | S13: 274.0119 | T13: 287.8296 | U13: 301.6478 | V13: 315.4657 | W13: 329.2837 | X13: 344.1332 | Y13: 358.983 | Z13: 373.8324 | AA13: 388.6818 | AB13: 403.5315 | AC13: 417.664 | AD13: 431.7965 | AE13: 445.929 | AF13: 460.0612 | AG13: 474.1937 | AH13: 485.8335 | AI13: 497.4735 | AJ13: 509.1135
A14: REGION | B14: PHL_INDU_OTHHPH_BIOM | C14: 16.8858
A15: REGION | B15: PHL_INDU_OTHHPH_COAL | C15: 41.3646 | D15: 119.19 | E15: 121.8012 | F15: 124.3998 | G15: 126.9846 | H15: 129.5586 | I15: 132.342 | J15: 135.1158 | K15: 137.8782 | L15: 140.6328 | M15: 143.9136 | N15: 146.982 | O15: 150.0432 | P15: 153.1014 | Q15: 156.1542 | R15: 159.2046 | S15: 162.8628 | T15: 166.521 | U15: 170.1768 | V15: 173.8338 | W15: 177.3096 | X15: 181.5366 | Y15: 185.7738 | Z15: 190.0218 | AA15: 194.2782 | AB15: 198.5454 | AC15: 203.4354 | AD15: 208.3344 | AE15: 213.2406 | AF15: 218.1504 | AG15: 222.207 | AH15: 227.6958 | AI15: 233.1828 | AJ15: 238.6716
A16: REGION | B16: PHL_INDU_OTHHPH_NG | C16: 0.8112
A17: REGION | B17: PHL_INDU_OTHHPH_OIL | C17: 54.42
A18: REGION | B18: PHL_INDU_OTHLPH_BIOM | C18: 16.8858 | W18: 0.0002 | X18: 0.0004 | Y18: 0.0008 | Z18: 0.0008 | AA18: 0.0008
A19: REGION | B19: PHL_INDU_OTHLPH_COAL | C19: 41.3646 | D19: 118.4094 | E19: 121.0194 | F19: 123.6186 | G19: 126.2034 | H19: 128.7774 | I19: 131.5608 | J19: 134.3346 | K19: 137.0988 | L19: 139.8546 | M19: 143.1312 | N19: 146.2008 | O19: 149.2638 | P19: 152.3214 | Q19: 155.3754 | R19: 158.427 | S19: 162.0864 | T19: 165.744 | U19: 169.4022 | V19: 173.058 | W19: 176.5368 | X19: 180.7644 | Y19: 185.0022 | Z19: 189.2502 | AA19: 193.5078 | AB19: 198.2152 | AC19: 203.4354 | AD19: 208.3344 | AE19: 213.2406 | AF19: 218.1504 | AG19: 222.207 | AH19: 227.6958 | AI19: 233.1828 | AJ19: 238.6716
A20: REGION | B20: PHL_INDU_OTHLPH_ELE | D20: 0.2346 | E20: 0.2346 | F20: 0.2346 | G20: 0.2322 | H20: 0.216 | I20: 0.2148 | J20: 0.2148 | K20: 0.2138 | L20: 0.2138 | M20: 0.2126 | N20: 0.2116 | O20: 0.2104 | P20: 0.2104 | Q20: 0.2104 | R20: 0.2092 | S20: 0.2082 | T20: 0.2082 | U20: 0.2082 | V20: 0.207 | W20: 0.2048 | X20: 0.2048 | Y20: 0.2048 | Z20: 0.2048 | AA20: 0.2048 | AB20: 0.0944
A21: REGION | B21: PHL_INDU_OTHLPH_NG | C21: 0.8112 | H21: 0.0526 | I21: 0.0526 | J21: 0.0526 | K21: 0.0526 | L21: 0.0524 | M21: 0.0522 | N21: 0.0522 | O21: 0.0522 | P21: 0.0522 | Q21: 0.0522 | R21: 0.0522 | S21: 0.0522 | T21: 0.0522 | U21: 0.0522 | V21: 0.0522 | W21: 0.052 | X21: 0.0518 | Y21: 0.0514 | Z21: 0.0514 | AA21: 0.0514
A22: REGION | B22: PHL_INDU_OTHLPH_OIL | C22: 54.42
A23: REGION | B23: PHL_INDU_PLANT_OTH | C23: 299.5284 | D23: 306.2718 | E23: 313.0146 | F23: 319.7562 | G23: 326.4996 | H23: 333.2436 | I23: 340.5516 | J23: 347.8626 | K23: 355.173 | L23: 362.4852 | M23: 369.7932 | N23: 378.0996 | O23: 386.4072 | P23: 394.7136 | Q23: 403.0176 | R23: 411.324 | S23: 421.206 | T23: 431.0868 | U23: 440.9676 | V23: 450.8526 | W23: 460.7298 | X23: 472.2306 | Y23: 483.7332 | Z23: 495.2352 | AA23: 506.7366 | AB23: 518.2398 | AC23: 531.3516 | AD23: 544.4682 | AE23: 557.58 | AF23: 570.696 | AG23: 583.8102 | AH23: 598.2288 | AI23: 612.645 | AJ23: 627.0654
A24: REGION | B24: PHL_LND_BLT | C24: 8.1777 | D24: 8.4835 | E24: 8.801 | F24: 9.1301 | G24: 9.4716 | H24: 9.8257 | I24: 10.1934 | J24: 10.5746 | K24: 10.97 | L24: 11.3804 | M24: 11.8056 | N24: 12.2476 | O24: 12.7056 | P24: 13.1808 | Q24: 13.6738 | R24: 14.1849 | S24: 14.7156 | T24: 15.2661 | U24: 15.8369 | V24: 16.4295 | W24: 17.0437 | X24: 17.6812 | Y24: 18.3424 | Z24: 19.0285 | AA24: 19.74 | AB24: 20.4785 | AC24: 21.2443 | AD24: 22.0387 | AE24: 22.8628 | AF24: 23.7181 | AG24: 24.6051 | AH24: 25.5253 | AI24: 26.4801 | AJ24: 27.4704
A25: REGION | B25: PHL_LND_FOR | C25: 142503.75 | D25: 168.658 | E25: 168.6579 | F25: 168.6578 | G25: 168.6577 | H25: 168.6582 | I25: 168.6578 | J25: 168.658 | K25: 168.6578 | L25: 168.6578 | M25: 168.6578 | N25: 168.6579 | O25: 168.6579 | P25: 168.6581 | Q25: 168.658 | R25: 168.6578 | S25: 168.6579 | T25: 168.6581 | U25: 168.6579 | V25: 168.658 | W25: 168.6577 | X25: 168.6577 | Y25: 168.6578 | Z25: 168.6579 | AA25: 168.6579 | AB25: 168.6576 | AC25: 168.6579 | AD25: 168.658 | AE25: 168.6577 | AF25: 168.658 | AG25: 168.6579 | AH25: 168.6577 | AI25: 168.6579 | AJ25: 168.658
A26: REGION | B26: PHL_LND_OTH | C26: 5.1489 | D26: 5.1489 | E26: 5.1489 | F26: 5.1489 | G26: 5.1488 | H26: 5.1488 | I26: 5.1489 | J26: 5.1489 | K26: 5.1488 | L26: 5.1489 | M26: 5.1489 | N26: 5.1489 | O26: 5.1487 | P26: 5.1489 | Q26: 5.1489 | R26: 5.1489 | S26: 5.1489 | T26: 5.1489 | U26: 5.1489 | V26: 5.149 | W26: 5.1489 | X26: 5.1489 | Y26: 5.1489 | Z26: 5.1489 | AA26: 5.1487 | AB26: 5.1488 | AC26: 5.149 | AD26: 5.1489 | AE26: 5.1489 | AF26: 5.1489 | AG26: 5.1489 | AH26: 5.1489 | AI26: 5.1489 | AJ26: 5.149
A27: REGION | B27: PHL_LND_WAT | C27: 34.6876 | D27: 34.6876 | E27: 34.6876 | F27: 34.6877 | G27: 34.6878 | H27: 34.6877 | I27: 34.6877 | J27: 34.6872 | K27: 34.6876 | L27: 34.6875 | M27: 34.6874 | N27: 34.6875 | O27: 34.6877 | P27: 34.6875 | Q27: 34.688 | R27: 35.9754 | S27: 41.9649 | T27: 48.0415 | U27: 54.2016 | V27: 60.4371 | W27: 57.7505 | X27: 63.3173 | Y27: 69.3654 | Z27: 75.6057 | AA27: 81.6242 | AB27: 87.8456 | AC27: 94.2631 | AD27: 100.7506 | AE27: 106.5266 | AF27: 113.3797 | AG27: 116.7317 | AH27: 123.4577 | AI27: 130.2189 | AJ27: 137.217
A28: REGION | B28: PHL_POW_CHP_BIOM_OLD | C28: 18.0031 | D28: 20.8116 | E28: 19.0391 | F28: 20.2913 | G28: 20.8274 | W28: 3.8488 | X28: 4.2396 | Y28: 4.6742 | Z28: 5.2452 | AA28: 5.2452 | AB28: 5.2452 | AC28: 5.2452 | AD28: 5.2452 | AE28: 5.2452 | AF28: 4.9234 | AG28: 4.4748 | AH28: 4.4748 | AI28: 4.3002 | AJ28: 4.287
A29: REGION | B29: PHL_POW_CHP_COAL_OLD | C29: 657.5302 | D29: 701.2898 | E29: 750.7694 | F29: 833.541 | G29: 896.8866 | H29: 824.1194 | I29: 811.3573 | J29: 798.1693 | K29: 783.505 | L29: 816.3047 | M29: 699.6414 | N29: 693.779 | O29: 557.1279 | P29: 542.0894 | Q29: 526.9661 | R29: 486.6519 | S29: 414.9552 | T29: 399.0388 | U29: 337.3817 | V29: 270.8062 | W29: 279.9646 | X29: 294.9864 | Y29: 290.6847 | Z29: 286.372 | AA29: 282.0481 | AB29: 277.4572 | AC29: 256.8231 | AD29: 252.4385 | AE29: 250.5565 | AF29: 284.4477 | AG29: 315.3186 | AH29: 298.0949 | AI29: 296.5875 | AJ29: 258.2284
A30: REGION | B30: PHL_POW_CHP_NG_OLD | C30: 131.277 | D30: 128.3149 | E30: 120.3972 | F30: 112.2118 | G30: 121.4947 | H30: 2.2016 | I30: 2.7832 | J30: 3.3156 | K30: 3.6776 | L30: 12.3768 | M30: 21.9754 | N30: 25.1057 | O30: 2.3678 | P30: 2.3678 | Q30: 2.3678 | R30: 2.3678 | S30: 2.3678 | T30: 2.3678 | U30: 2.3678 | V30: 2.3678 | W30: 2.3678 | X30: 2.3678 | Y30: 2.3636 | Z30: 2.431 | AA30: 2.3636 | AB30: 2.3636
A31: REGION | B31: PHL_POW_CHP_OIL_OLD | C31: 46.3982 | D31: 30.3581 | E31: 47.3163 | F31: 24.4933 | G31: 25.2079
A32: REGION | B32: PHL_POW_PP_COAL | H32: 150.882 | I32: 150.882 | J32: 150.882 | K32: 150.882 | L32: 150.882 | M32: 150.882 | N32: 213.1122 | O32: 412.5588 | P32: 485.704 | Q32: 558.6682 | R32: 625.8846 | S32: 753.8058 | T32: 841.1368 | U32: 961.2548 | V32: 1078.034 | W32: 888.941 | X32: 922.9174 | Y32: 983.1392 | Z32: 1043.4942 | AA32: 1103.9756 | AB32: 1166.4804 | AC32: 1242.3952 | AD32: 1305.424 | AE32: 1347.8432 | AF32: 1373.2686 | AG32: 1316.4028 | AH32: 1381.9676 | AI32: 1436.096 | AJ32: 1517.0408
A33: REGION | B33: PHL_POW_PP_NGCC | H33: 9.1762 | I33: 9.367 | J33: 9.5358 | K33: 9.6294 | L33: 11.9095 | M33: 12.7034 | N33: 12.8793 | O33: 6.9584 | P33: 6.6768 | Q33: 6.3906 | R33: 6.1092 | S33: 5.7668 | T33: 5.4242 | U33: 5.443 | V33: 13.2766 | W33: 29.4788 | X33: 36.9614 | Y33: 38.7796 | Z33: 40.4822 | AA33: 42.5448 | AB33: 44.6409 | AC33: 48.8368 | AD33: 50.9191 | AE33: 54.0744 | AF33: 76.0003 | AG33: 107.7998 | AH33: 111.0786 | AI33: 114.4293 | AJ33: 117.7132
A34: REGION | B34: PHL_POW_TD | C34: 366.3974 | D34: 366.8391 | E34: 385.2346 | F34: 403.6304 | G34: 421.8885 | H34: 436.3265 | I34: 458.9825 | J34: 481.6527 | K34: 504.3681 | L34: 526.9633 | M34: 549.5335 | N34: 576.6874 | O34: 604.7309 | P34: 631.7904 | Q34: 658.9347 | R34: 675.3465 | S34: 708.2993 | T34: 741.2521 | U34: 774.2044 | V34: 807.157 | W34: 839.7276 | X34: 873.0021 | Y34: 908.8629 | Z34: 944.8018 | AA34: 980.8139 | AB34: 1016.7588 | AC34: 1054.1231 | AD34: 1091.6574 | AE34: 1129.2427 | AF34: 1166.8752 | AG34: 1220.0817 | AH34: 1256.317 | AI34: 1292.5527 | AJ34: 1328.7885
A35: REGION | B35: PHL_POW_TD_AGR | C35: 9.2938 | D35: 9.5034 | E35: 9.7123 | F35: 9.9217 | G35: 10.1309 | H35: 10.3402 | I35: 10.567 | J35: 10.794 | K35: 11.0206 | L35: 11.2478 | M35: 11.4744 | N35: 11.7322 | O35: 11.9903 | P35: 12.2473 | Q35: 12.5055 | R35: 12.763 | S35: 13.0696 | T35: 13.376 | U35: 13.6828 | V35: 13.9894 | W35: 14.2957 | X35: 11.2971 | Y35: 10.4153 | Z35: 9.5967 | AA35: 8.8376 | AB35: 8.134 | AC35: 7.506 | AD35: 6.9223 | AE35: 6.38 | AF35: 5.8771 | AG35: 18.1149 | AH35: 18.562 | AI35: 19.01 | AJ35: 19.457
A36: REGION | B36: PHL_POW_TD_HOU | C36: 123.45 | D36: 131.4285 | E36: 139.4069 | F36: 147.3856 | G36: 155.2519 | H36: 160.0337 | I36: 169.9517 | J36: 179.8807 | K36: 189.8469 | L36: 199.7311 | M36: 209.6501 | N36: 221.3313 | O36: 233.8113 | P36: 245.4858 | Q36: 257.2296 | R36: 260.1939 | S36: 274.0119 | T36: 287.8296 | U36: 301.6478 | V36: 315.4657 | W36: 329.2837 | X36: 344.1332 | Y36: 358.983 | Z36: 373.8324 | AA36: 388.6818 | AB36: 403.5315 | AC36: 417.664 | AD36: 431.7965 | AE36: 445.929 | AF36: 460.0612 | AG36: 474.1937 | AH36: 485.8335 | AI36: 497.4735 | AJ36: 509.1135
A37: REGION | B37: PHL_POW_TD_INDU | C37: 92.0388 | D37: 94.3452 | E37: 96.4164 | F37: 98.4876 | G37: 100.5582 | H37: 102.6144 | I37: 104.8596 | J37: 107.1044 | K37: 109.3508 | L37: 111.5966 | M37: 113.8418 | N37: 116.393 | O37: 118.9456 | P37: 121.4968 | Q37: 124.0492 | R37: 126.6004 | S37: 129.6354 | T37: 132.6712 | U37: 135.7074 | V37: 138.743 | W37: 141.7778 | X37: 145.3118 | Y37: 148.8452 | Z37: 152.3794 | AA37: 155.9138 | AB37: 159.337 | AC37: 163.272 | AD37: 167.3034 | AE37: 171.3324 | AF37: 175.362 | AG37: 179.391 | AH37: 183.822 | AI37: 188.253 | AJ37: 192.6822
A38: REGION | B38: PHL_POW_TD_SER | C38: 74.6185 | D38: 64.4849 | E38: 69.2756 | F38: 74.0661 | G38: 78.8568 | H38: 83.6476 | I38: 89.7923 | J38: 95.9372 | K38: 102.0815 | L38: 108.2264 | M38: 114.371 | N38: 122.0248 | O38: 129.6784 | P38: 137.3313 | Q38: 144.9854 | R38: 152.6391 | S38: 162.437 | T38: 172.2355 | U38: 182.0342 | V38: 191.8324 | W38: 201.6307 | X38: 213.4681 | Y38: 225.3049 | Z38: 237.1419 | AA38: 248.9789 | AB38: 260.8157 | AC38: 273.9441 | AD38: 287.0726 | AE38: 300.2011 | AF38: 313.3303 | AG38: 326.4586 | AH38: 339.5855 | AI38: 352.7122 | AJ38: 365.8389
A39: REGION | B39: PHL_POW_TD_TRA | C39: 0.3528 | D39: 0.3528 | E39: 0.3528 | F39: 0.3528 | G39: 0.3528 | H39: 0.3282 | I39: 0.3282 | J39: 0.3282 | K39: 0.3282 | L39: 0.3114 | M39: 0.2406 | N39: 0.3114 | O39: 0.3114 | P39: 0.3114 | Q39: 0.3114 | R39: 0.3114 | S39: 0.3114 | T39: 0.3114 | U39: 0.3114 | V39: 0.3114
A40: REGION | B40: PHL_PRO_BLEND_BIOF | C40: 440.9859 | D40: 453.4509 | E40: 466.2607 | F40: 478.7299 | G40: 491.5885 | H40: 504.1727 | I40: 519.5923 | J40: 534.8081 | K40: 550.0577 | L40: 565.3444 | M40: 556.6327 | N40: 575.4974 | O40: 594.0882 | P40: 612.9474 | Q40: 631.7547 | R40: 650.5311 | S40: 672.0059 | T40: 693.4357 | U40: 714.8479 | V40: 736.4105 | W40: 755.8425 | X40: 779.3991 | Y40: 802.9872 | Z40: 826.647 | AA40: 850.3606 | AB40: 874.121 | AC40: 899.6047 | AD40: 925.1267 | AE40: 950.7065 | AF40: 976.3176 | AG40: 995.2355 | AH40: 1021.9914 | AI40: 1048.5684 | AJ40: 1075.4968
A41: REGION | B41: PHL_PRO_PROC_COAL | C41: 743.1913 | D41: 1183.9746 | E41: 1242.6016 | F41: 1334.6259 | G41: 1407.236 | H41: 1497.748 | I41: 1494.0393 | J41: 1489.8724 | K41: 1484.1655 | L41: 1526.1768 | M41: 1419.147 | N41: 1485.1382 | O41: 1556.769 | P41: 1624.4904 | Q41: 1691.867 | R41: 1736.9944 | S41: 1803.6574 | T41: 1885.5689 | U41: 1954.4731 | V41: 2015.0875 | W41: 1844.2937 | X41: 1904.5224 | Y41: 1971.7222 | Z41: 2039.0644 | AA41: 2106.5406 | AB41: 2176.2428 | AC41: 2244.1014 | AD41: 2315.0185 | AE41: 2367.7714 | AF41: 2439.3925 | AG41: 2423.645 | AH41: 2485.1006 | AI41: 2550.8518 | AJ41: 2606.528
A42: REGION | B42: PHL_PRO_PROC_NG | C42: 140.4442 | D42: 162.2445 | E42: 156.2115 | F42: 149.877 | G42: 271.0549 | H42: 155.8977 | I42: 157.8027 | J42: 159.6605 | K42: 161.2847 | L42: 174.0544 | M42: 183.4574 | N42: 188.325 | O42: 159.4067 | P42: 160.4732 | Q42: 164.011 | R42: 175.2314 | S42: 180.0269 | T42: 184.8133 | U42: 189.9742 | V42: 203.3887 | W42: 225.2085 | X42: 241.6058 | Y42: 252.0193 | Z42: 262.3948 | AA42: 273.0166 | AB42: 283.7012 | AC42: 296.3505 | AD42: 309.269 | AE42: 323.327 | AF42: 357.2272 | AG42: 399.2813 | AH42: 415.898 | AI42: 432.591 | AJ42: 449.2127
A43: REGION | B43: PHL_PRO_PROC_OIL | C43: 259.9208 | D43: 143.8235 | E43: 159.3693 | F43: 135.8633 | G43: 35.6929 | H43: 11.0006 | I43: 11.0836 | J43: 11.169 | K43: 11.2568 | L43: 11.346 | M43: 11.225 | N43: 11.3302 | O43: 11.435 | P43: 11.5392 | Q43: 9.3394
A44: REGION | B44: PHL_SER_HEAT_BIOM | C44: 15.669 | D44: 1.7528 | E44: 1.7672 | F44: 1.782
A45: REGION | B45: PHL_SER_HEAT_NG | D45: 25.2138 | E45: 27.423 | F45: 29.6136 | G45: 134.9985 | H45: 136.0921 | I45: 137.1219 | J45: 138.1794 | K45: 139.2611 | L45: 140.3657 | M45: 138.8699 | N45: 140.1701 | O45: 141.4643 | P45: 142.7548 | Q45: 146.3893 | R45: 157.2884 | S45: 162.1687 | T45: 167.0405 | U45: 171.9053 | V45: 176.7657 | W45: 181.2113 | X45: 189.2453 | Y45: 197.2858 | Z45: 205.3339 | AA45: 213.39 | AB45: 221.4552 | AC45: 231.5935 | AD45: 241.7355 | AE45: 251.8828 | AF45: 262.0362 | AG45: 270.0313 | AH45: 282.4768 | AI45: 294.9219 | AJ45: 307.3672
A46: REGION | B46: PHL_SER_HEAT_OIL | C46: 109.1647 | D46: 115.9461 | E46: 114.8014 | F46: 113.7132 | G46: 11.1002 | H46: 11.1902 | I46: 11.275 | J46: 11.3618 | K46: 11.4506 | L46: 11.5416 | M46: 11.4186 | N46: 11.5256 | O46: 11.6322 | P46: 11.7382 | Q46: 9.5004
A47: REGION | B47: PHL_SER_HEAT_RES | C47: 14.924
A48: REGION | B48: PHL_SER_UNIT | C48: 59.6946 | D48: 64.4849 | E48: 69.2756 | F48: 74.0661 | G48: 78.8568 | H48: 83.6476 | I48: 89.7923 | J48: 95.9372 | K48: 102.0815 | L48: 108.2264 | M48: 114.371 | N48: 122.0248 | O48: 129.6784 | P48: 137.3313 | Q48: 144.9854 | R48: 152.6391 | S48: 162.437 | T48: 172.2355 | U48: 182.0342 | V48: 191.8324 | W48: 201.6307 | X48: 213.4681 | Y48: 225.3049 | Z48: 237.1419 | AA48: 248.9789 | AB48: 260.8157 | AC48: 273.9441 | AD48: 287.0726 | AE48: 300.2011 | AF48: 313.3303 | AG48: 326.4586 | AH48: 339.5855 | AI48: 352.7122 | AJ48: 365.8389
A49: REGION | B49: PHL_TRA_23WHEEL_LIQ | C49: 113.5208 | D49: 115.1604 | E49: 116.803 | F49: 118.4428 | G49: 120.0844 | H49: 121.7254 | I49: 123.2853 | J49: 124.8458 | K49: 126.4054 | L49: 127.9657 | M49: 129.5244 | N49: 130.9648 | O49: 132.4047 | P49: 133.8447 | Q49: 135.2836 | R49: 136.7237 | S49: 138.0262 | T49: 139.3288 | U49: 140.6311 | V49: 141.9348 | W49: 143.237 | X49: 144.3947 | Y49: 145.5517 | Z49: 146.7097 | AA49: 147.8667 | AB49: 149.0239 | AC49: 150.0259 | AD49: 151.0274 | AE49: 152.0284 | AF49: 153.0288 | AG49: 154.0306 | AH49: 154.8948 | AI49: 155.759 | AJ49: 156.6233
A50: REGION | B50: PHL_TRA_AVI_LIQ | C50: 9.7596 | D50: 10.1928 | E50: 10.6152 | F50: 11.0364 | G50: 11.4696 | H50: 11.8914 | I50: 12.462 | J50: 13.0206 | K50: 13.5894 | L50: 14.16 | M50: 14.7186 | N50: 15.474 | O50: 16.2444 | P50: 16.9998 | Q50: 17.7558 | R50: 18.5136 | S50: 19.5906 | T50: 20.67 | U50: 21.75 | V50: 22.8286 | W50: 23.9076 | X50: 25.4334 | Y50: 26.946 | Z50: 28.4706 | AA50: 29.9952 | AB50: 31.521 | AC50: 33.6042 | AD50: 35.6886 | AE50: 37.77 | AF50: 39.8541 | AG50: 41.9376 | AH50: 44.652 | AI50: 47.3682 | AJ50: 50.0832
A51: REGION | B51: PHL_TRA_BUS_LIQ | C51: 37.8426 | D51: 37.1646 | E51: 36.5562 | F51: 36.0096 | G51: 35.52 | H51: 35.0928 | I51: 34.68 | J51: 34.3116 | K51: 33.9942 | L51: 33.705 | M51: 29.4186 | N51: 29.514 | O51: 29.6124 | P51: 29.7006 | Q51: 29.7882 | R51: 29.883 | S51: 29.9424 | T51: 30.0108 | U51: 30.084 | V51: 30.1638 | W51: 30.036 | X51: 30.0276 | Y51: 30.0348 | Z51: 30.066 | AA51: 30.117 | AB51: 30.183 | AC51: 30.2322 | AD51: 30.291 | AE51: 30.3672 | AF51: 30.4548 | AG51: 29.61 | AH51: 29.7822 | AI51: 29.9484 | AJ51: 30.1146
A52: REGION | B52: PHL_TRA_CAR_LIQ | C52: 75.6798 | D52: 77.928 | E52: 80.178 | F52: 82.4334 | G52: 84.6954 | H52: 86.9676 | I52: 89.4366 | J52: 91.9146 | K52: 94.4034 | L52: 96.9048 | M52: 93.1086 | N52: 96.0384 | O52: 98.9556 | P52: 101.8578 | Q52: 104.7534 | R52: 107.6388 | S52: 110.4246 | T52: 113.2068 | U52: 115.9854 | V52: 118.7628 | W52: 121.2948 | X52: 123.6666 | Y52: 126.0576 | Z52: 128.4648 | AA52: 130.887 | AB52: 133.3212 | AC52: 135.285 | AD52: 137.2614 | AE52: 139.2504 | AF52: 141.2502 | AG52: 142.0506 | AH52: 143.6706 | AI52: 145.2888 | AJ52: 146.9076
A53: REGION | B53: PHL_TRA_RAILF_ELE | C53: 0.1758 | D53: 0.1758 | E53: 0.1758 | F53: 0.1758 | G53: 0.1758 | H53: 0.1636 | I53: 0.1636 | J53: 0.1636 | K53: 0.1636 | L53: 0.1558 | M53: 0.1207 | N53: 0.1558 | O53: 0.1558 | P53: 0.1558 | Q53: 0.1558 | R53: 0.1558 | S53: 0.1558 | T53: 0.1558 | U53: 0.1558 | V53: 0.1558
A54: REGION | B54: PHL_TRA_RAILF_LIQ | E54: 0.1758 | F54: 0.1758 | G54: 0.3528 | H54: 0.3696 | I54: 0.5466 | J54: 0.7218 | K54: 0.7218 | L54: 0.9156 | M54: 1.1622 | N54: 1.2672 | O54: 1.2672 | P54: 1.443 | Q54: 1.62 | R54: 1.7952 | S54: 1.9722 | T54: 2.1468 | U54: 2.3226 | V54: 2.6748 | W54: 3.1686 | X54: 3.3444 | Y54: 3.6954 | Z54: 4.0482 | AA54: 4.224 | AB54: 4.575 | AC54: 4.9278 | AD54: 5.2794 | AE54: 5.6316 | AF54: 5.9832 | AG54: 6.336 | AH54: 6.864 | AI54: 7.2168 | AJ54: 7.7436
A55: REGION | B55: PHL_TRA_RAILP_ELE | C55: 0.1758 | D55: 0.1758 | E55: 0.1758 | F55: 0.1758 | G55: 0.1758 | H55: 0.1636 | I55: 0.1636 | J55: 0.1636 | K55: 0.1636 | L55: 0.1558 | M55: 0.1207 | N55: 0.1558 | O55: 0.1558 | P55: 0.1558 | Q55: 0.1558 | R55: 0.1558 | S55: 0.1558 | T55: 0.1558 | U55: 0.1558 | V55: 0.1558
A56: REGION | B56: PHL_TRA_RAILP_LIQ | E56: 0.1758 | F56: 0.1758 | G56: 0.3528 | H56: 0.3696 | I56: 0.5466 | J56: 0.5466 | K56: 0.7218 | L56: 0.7386 | M56: 0.9858 | N56: 1.0914 | O56: 1.0914 | P56: 1.2672 | Q56: 1.443 | R56: 1.62 | S56: 1.7952 | T56: 1.9722 | U56: 2.1468 | V56: 2.3226 | W56: 2.8158 | X56: 3.1686 | Y56: 3.3444 | Z56: 3.5208 | AA56: 3.8712 | AB56: 4.0482 | AC56: 4.3998 | AD56: 4.752 | AE56: 5.1048 | AF56: 5.4558 | AG56: 5.8086 | AH56: 6.1602 | AI56: 6.5124 | AJ56: 7.0398
A57: REGION | B57: PHL_TRA_SHIP_LIQ | C57: 33.0939 | D57: 35.6592 | E57: 38.2224 | F57: 40.7856 | G57: 43.3488 | H57: 45.912 | I57: 48.8532 | J57: 51.7932 | K57: 54.7338 | L57: 57.675 | M57: 60.615 | N57: 63.768 | O57: 66.9216 | P57: 70.077 | Q57: 73.23 | R57: 76.3836 | S57: 79.8258 | T57: 83.2674 | U57: 86.7102 | V57: 90.1513 | W57: 93.5934 | X57: 97.302 | Y57: 101.0106 | Z57: 104.721 | AA57: 108.4308 | AB57: 112.1406 | AC57: 116.0988 | AD57: 120.0564 | AE57: 124.0158 | AF57: 127.974 | AG57: 131.9328 | AH57: 136.0662 | AI57: 140.1996 | AJ57: 144.3336
A58: REGION | B58: PHL_TRA_TRUH_LIQ | C58: 75.6774 | D58: 78.5004 | E58: 81.2742 | F58: 84.006 | G58: 86.7042 | H58: 89.373 | I58: 92.9484 | J58: 96.4704 | K58: 99.9564 | L58: 103.4154 | M58: 100.0602 | N58: 104.6316 | O58: 109.1574 | P58: 113.652 | Q58: 118.119 | R58: 122.5716 | S58: 128.1192 | T58: 133.6332 | U58: 139.1322 | V58: 144.6174 | W58: 148.2288 | X58: 154.5726 | Y58: 160.9266 | Z58: 167.2914 | AA58: 173.667 | AB58: 180.054 | AC58: 187.0602 | AD58: 194.076 | AE58: 201.111 | AF58: 208.1478 | AG58: 212.1444 | AH58: 219.4908 | AI58: 226.845 | AJ58: 234.1986
A59: REGION | B59: PHL_TRA_TRUL_LIQ | C59: 56.76 | D59: 59.001 | E59: 61.2312 | F59: 63.45 | G59: 65.6628 | H59: 67.8762 | I59: 70.7892 | J59: 73.692 | K59: 76.5894 | L59: 79.4802 | M59: 76.9998 | N59: 80.8698 | O59: 84.7242 | P59: 88.5678 | Q59: 92.3994 | R59: 96.219 | S59: 100.911 | T59: 105.5922 | U59: 110.2662 | V59: 114.9312 | W59: 119.4066 | X59: 124.7844 | Y59: 130.1634 | Z59: 135.549 | AA59: 140.9388 | AB59: 146.3322 | AC59: 152.2236 | AD59: 158.1204 | AE59: 164.0214 | AF59: 169.9266 | AG59: 174.6942 | AH59: 180.75 | AI59: 186.8028 | AJ59: 192.8568
A60: REGION | B60: PHL_TRA_VAN_LIQ | C60: 18.9202 | D60: 19.668 | E60: 20.409 | F60: 21.1494 | G60: 21.8868 | H60: 22.6248 | I60: 23.598 | J60: 24.5634 | K60: 25.5306 | L60: 26.4936 | M60: 25.6656 | N60: 26.9568 | O60: 28.242 | P60: 29.5224 | Q60: 30.8016 | R60: 32.0736 | S60: 33.6378 | T60: 35.1972 | U60: 36.756 | V60: 38.3106 | W60: 39.8028 | X60: 41.5944 | Y60: 43.3872 | Z60: 45.1818 | AA60: 46.9794 | AB60: 48.7776 | AC60: 50.7414 | AD60: 52.7064 | AE60: 54.675 | AF60: 56.6424 | AG60: 58.2312 | AH60: 60.2502 | AI60: 62.2674 | AJ60: 64.2852

Sheet Operation Life Time
F2: Discount Rate | G2: 0.05 | J2: Convert PJ -->GWh | K2: 277.77778
B3: Operation Life Time
B4: Technology | C4: Parameter | D4: Life period | E4: CRF (Capital Recovery Factor)
B5: PHL_POW_CHP_BIOM_OLD | D5: 25 | E5: =$G$2*(1+$G$2)^D5/((1+$G$2)^D5-1) -> 0.070952457
B6: PHL_POW_CHP_COAL_OLD | D6: 25 | E6: =$G$2*(1+$G$2)^D6/((1+$G$2)^D6-1) -> 0.070952457
B7: PHL_POW_GEO_OLD | D7: 25 | E7: =$G$2*(1+$G$2)^D7/((1+$G$2)^D7-1) -> 0.070952457
B8: PHL_POW_PP_BIOM_CCS | D8: 25 | E8: =$G$2*(1+$G$2)^D8/((1+$G$2)^D8-1) -> 0.070952457
B9: PHL_POW_PP_COAL | D9: 25 | E9: =$G$2*(1+$G$2)^D9/((1+$G$2)^D9-1) -> 0.070952457
B10: PHL_POW_PP_COAL_CCS | D10: 25 | E10: =$G$2*(1+$G$2)^D10/((1+$G$2)^D10-1) -> 0.070952457
B11: PHL_POW_PP_H2 | D11: 25 | E11: =$G$2*(1+$G$2)^D11/((1+$G$2)^D11-1) -> 0.070952457
B12: PHL_POW_PP_HY_LA | D12: 50 | E12: =$G$2*(1+$G$2)^D12/((1+$G$2)^D12-1) -> 0.054776735
B13: PHL_POW_PP_NGCC | D13: 25 | E13: =$G$2*(1+$G$2)^D13/((1+$G$2)^D13-1) -> 0.070952457
B14: PHL_POW_PP_NGCC_CCS | D14: 25 | E14: =$G$2*(1+$G$2)^D14/((1+$G$2)^D14-1) -> 0.070952457
B15: PHL_POW_PP_NU | D15: 40 | E15: =$G$2*(1+$G$2)^D15/((1+$G$2)^D15-1) -> 0.058278161
B16: PHL_POW_PP_NUSMR | D16: 60 | E16: =$G$2*(1+$G$2)^D16/((1+$G$2)^D16-1) -> 0.052828185
... B21: PHL_POW_CHP_NG_OLD | D21: 1 | E21: =$G$2*(1+$G$2)^D21/((1+$G$2)^D21-1) -> 1.05
