Workbook

Sheet Grid_cost_PEP
A1: PEP Scenario
A2: =Cost_of_ELCgen!A149 -> Calculations | C2: =Cost_of_ELCgen!C149 -> 2020 | D2: =Cost_of_ELCgen!D149 -> 2021 | E2: =Cost_of_ELCgen!E149 -> 2022 | F2: =Cost_of_ELCgen!F149 -> 2023 | G2: =Cost_of_ELCgen!G149 -> 2024 | H2: =Cost_of_ELCgen!H149 -> 2025 | I2: =Cost_of_ELCgen!I149 -> 2026 | J2: =Cost_of_ELCgen!J149 -> 2027 | ... AG2: =Cost_of_ELCgen!AG149 -> 2050
A3: =Cost_of_ELCgen!A150 -> Operating O&M costs | C3: =Cost_of_ELCgen!C150 -> 3983.2703 | D3: =Cost_of_ELCgen!D150 -> 4094.6927 | E3: =Cost_of_ELCgen!E150 -> 4526.0569 | F3: =Cost_of_ELCgen!F150 -> 4486.033 | G3: =Cost_of_ELCgen!G150 -> 4730.4557 | H3: =Cost_of_ELCgen!H150 -> 4390.2596 | I3: =Cost_of_ELCgen!I150 -> 4385.722 | J3: =Cost_of_ELCgen!J150 -> 4587.073 | ... AG3: =Cost_of_ELCgen!AG150 -> 10875.82
A4: =Cost_of_ELCgen!A151 -> Annualized Investment costs | C4: =Cost_of_ELCgen!C151 -> 234.83856 | D4: =Cost_of_ELCgen!D151 -> 756.46065 | E4: =Cost_of_ELCgen!E151 -> 918.84101 | F4: =Cost_of_ELCgen!F151 -> 1006.569 | G4: =Cost_of_ELCgen!G151 -> 1158.3122 | H4: =Cost_of_ELCgen!H151 -> 1276.2681 | I4: =Cost_of_ELCgen!I151 -> 1551.5727 | J4: =Cost_of_ELCgen!J151 -> 1840.1869 | ... AG4: =Cost_of_ELCgen!AG151 -> 11615.939
A5: =Cost_of_ELCgen!A152 -> CO2 costs | C5: =Cost_of_ELCgen!C152 -> 0 | D5: =Cost_of_ELCgen!D152 -> 0 | E5: =Cost_of_ELCgen!E152 -> 0 | F5: =Cost_of_ELCgen!F152 -> 0 | G5: =Cost_of_ELCgen!G152 -> 0 | H5: =Cost_of_ELCgen!H152 -> 0 | I5: =Cost_of_ELCgen!I152 -> 0 | J5: =Cost_of_ELCgen!J152 -> 0 | ... AG5: =Cost_of_ELCgen!AG152 -> 0
A6: =Cost_of_ELCgen!A153 -> Total Costs (Million USD) | C6: =Cost_of_ELCgen!C153 -> 4218.1089 | D6: =Cost_of_ELCgen!D153 -> 4851.1533 | E6: =Cost_of_ELCgen!E153 -> 5444.8979 | F6: =Cost_of_ELCgen!F153 -> 5492.602 | G6: =Cost_of_ELCgen!G153 -> 5888.7679 | H6: =Cost_of_ELCgen!H153 -> 5666.5277 | I6: =Cost_of_ELCgen!I153 -> 5937.2946 | J6: =Cost_of_ELCgen!J153 -> 6427.2599 | ... AG6: =Cost_of_ELCgen!AG153 -> 22491.759
A7: =Cost_of_ELCgen!A154 -> Generation (PJ->GWh), Before Transmission losses | C7: =Cost_of_ELCgen!C154 -> 101777.42 | D7: =Cost_of_ELCgen!D154 -> 106114.28 | E7: =Cost_of_ELCgen!E154 -> 111516.69 | F7: =Cost_of_ELCgen!F154 -> 118003.67 | G7: =Cost_of_ELCgen!G154 -> 126941.67 | H7: =Cost_of_ELCgen!H154 -> 121134.36 | I7: =Cost_of_ELCgen!I154 -> 125377.36 | J7: =Cost_of_ELCgen!J154 -> 132378.08 | ... AG7: =Cost_of_ELCgen!AG154 -> 352549.08
A8: =Cost_of_ELCgen!A155 -> Average electricity cost (USD/kWh) | C8: =Cost_of_ELCgen!C155 -> 0.041444448 | D8: =Cost_of_ELCgen!D155 -> 0.045716311 | E8: =Cost_of_ELCgen!E155 -> 0.048825854 | F8: =Cost_of_ELCgen!F155 -> 0.046546029 | G8: =Cost_of_ELCgen!G155 -> 0.046389559 | H8: =Cost_of_ELCgen!H155 -> 0.046778863 | I8: =Cost_of_ELCgen!I155 -> 0.047355396 | J8: =Cost_of_ELCgen!J155 -> 0.048552296 | ... AG8: =Cost_of_ELCgen!AG155 -> 0.063797525

Sheet Investments_PEP
A1: PEP Scenario
A3: Variable | C3: 2020 | D3: 2021 | E3: 2022 | F3: 2023 | G3: 2024 | H3: 2025 | I3: 2026 | J3: 2027 | K3: 2028 | L3: 2029 | M3: 2030 | N3: 2031 | O3: 2032 | P3: 2033 | Q3: 2034 | R3: 2035 | S3: 2036 | T3: 2037 | U3: 2038 | V3: 2039 | W3: 2040 | X3: 2041 | Y3: 2042 | Z3: 2043 | AA3: 2044 | AB3: 2045 | AC3: 2046 | AD3: 2047 | AE3: 2048 | AF3: 2049 | AG3: 2050
A4: ='Capital Annualized Costs PEP'!A22 -> Total Capital Investments (Million USD) | B4: ='Capital Annualized Costs PEP'!B22 -> 0 | C4: ='Capital Annualized Costs PEP'!C22 -> 4747.952 | D4: ='Capital Annualized Costs PEP'!D22 -> 10006.783 | E4: ='Capital Annualized Costs PEP'!E22 -> 2531.4872 | F4: ='Capital Annualized Costs PEP'!F22 -> 1576.1906 | G4: ='Capital Annualized Costs PEP'!G22 -> 2362.6025 | H4: ='Capital Annualized Costs PEP'!H22 -> 1897.1058 | ... AG4: ='Capital Annualized Costs PEP'!AG22 -> 13589.976
A5: ='Capital Annualized Costs PEP'!A43 -> Total Annualized Investments (Million USD) | B5: ='Capital Annualized Costs PEP'!B43 -> 0 | C5: ='Capital Annualized Costs PEP'!C43 -> 234.83856 | D5: ='Capital Annualized Costs PEP'!D43 -> 756.46065 | E5: ='Capital Annualized Costs PEP'!E43 -> 918.84101 | F5: ='Capital Annualized Costs PEP'!F43 -> 1006.569 | G5: ='Capital Annualized Costs PEP'!G43 -> 1158.3122 | H5: ='Capital Annualized Costs PEP'!H43 -> 1276.2681 | ... AG5: ='Capital Annualized Costs PEP'!AG43 -> 11615.939

Sheet Capital Annualized Costs PEP
A1: PEP Scenario
A3: Capital Investments (M.USD) | C3: 2020 | D3: 2021 | E3: 2022 | F3: 2023 | G3: 2024 | H3: 2025 | I3: 2026 | J3: 2027 | K3: 2028 | L3: 2029 | M3: 2030 | N3: 2031 | O3: 2032 | P3: 2033 | Q3: 2034 | R3: 2035 | S3: 2036 | T3: 2037 | U3: 2038 | V3: 2039 | W3: 2040 | X3: 2041 | Y3: 2042 | Z3: 2043 | AA3: 2044 | AB3: 2045 | AC3: 2046 | AD3: 2047 | AE3: 2048 | AF3: 2049 | AG3: 2050
A4: PHL_POW_CHP_BIOM_OLD | C4: =SUMIFS(Capital_Investments!C$2:C$10000,Capital_Investments!$B$2:$B$10000,$A4) -> 0 | D4: =SUMIFS(Capital_Investments!D$2:D$10000,Capital_Investments!$B$2:$B$10000,$A4) -> 0 | E4: =SUMIFS(Capital_Investments!E$2:E$10000,Capital_Investments!$B$2:$B$10000,$A4) -> 369 | F4: =SUMIFS(Capital_Investments!F$2:F$10000,Capital_Investments!$B$2:$B$10000,$A4) -> 27 | G4: =SUMIFS(Capital_Investments!G$2:G$10000,Capital_Investments!$B$2:$B$10000,$A4) -> 44.55 | H4: =SUMIFS(Capital_Investments!H$2:H$10000,Capital_Investments!$B$2:$B$10000,$A4) -> 0 | I4: =SUMIFS(Capital_Investments!I$2:I$10000,Capital_Investments!$B$2:$B$10000,$A4) -> 0 | J4: =SUMIFS(Capital_Investments!J$2:J$10000,Capital_Investments!$B$2:$B$10000,$A4) -> 0 | ... AG4: =SUMIFS(Capital_Investments!AG$2:AG$10000,Capital_Investments!$B$2:$B$10000,$A4) -> 0
A5: PHL_POW_CHP_COAL_OLD | C5: =SUMIFS(Capital_Investments!C$2:C$10000,Capital_Investments!$B$2:$B$10000,$A5) -> 0 | D5: =SUMIFS(Capital_Investments!D$2:D$10000,Capital_Investments!$B$2:$B$10000,$A5) -> 0 | E5: =SUMIFS(Capital_Investments!E$2:E$10000,Capital_Investments!$B$2:$B$10000,$A5) -> 0 | F5: =SUMIFS(Capital_Investments!F$2:F$10000,Capital_Investments!$B$2:$B$10000,$A5) -> 0 | G5: =SUMIFS(Capital_Investments!G$2:G$10000,Capital_Investments!$B$2:$B$10000,$A5) -> 0 | H5: =SUMIFS(Capital_Investments!H$2:H$10000,Capital_Investments!$B$2:$B$10000,$A5) -> 0 | I5: =SUMIFS(Capital_Investments!I$2:I$10000,Capital_Investments!$B$2:$B$10000,$A5) -> 0 | J5: =SUMIFS(Capital_Investments!J$2:J$10000,Capital_Investments!$B$2:$B$10000,$A5) -> 0 | ... AG5: =SUMIFS(Capital_Investments!AG$2:AG$10000,Capital_Investments!$B$2:$B$10000,$A5) -> 0
A6: PHL_POW_GEO_OLD | C6: =SUMIFS(Capital_Investments!C$2:C$10000,Capital_Investments!$B$2:$B$10000,$A6) -> 0 | D6: =SUMIFS(Capital_Investments!D$2:D$10000,Capital_Investments!$B$2:$B$10000,$A6) -> 0 | E6: =SUMIFS(Capital_Investments!E$2:E$10000,Capital_Investments!$B$2:$B$10000,$A6) -> 16.28 | F6: =SUMIFS(Capital_Investments!F$2:F$10000,Capital_Investments!$B$2:$B$10000,$A6) -> 1236.7766 | G6: =SUMIFS(Capital_Investments!G$2:G$10000,Capital_Investments!$B$2:$B$10000,$A6) -> 29.5789 | H6: =SUMIFS(Capital_Investments!H$2:H$10000,Capital_Investments!$B$2:$B$10000,$A6) -> 157.08 | I6: =SUMIFS(Capital_Investments!I$2:I$10000,Capital_Investments!$B$2:$B$10000,$A6) -> 3722.5143 | J6: =SUMIFS(Capital_Investments!J$2:J$10000,Capital_Investments!$B$2:$B$10000,$A6) -> 0 | ... AG6: =SUMIFS(Capital_Investments!AG$2:AG$10000,Capital_Investments!$B$2:$B$10000,$A6) -> 0
A7: PHL_POW_PP_BIOM_CCS | C7: =SUMIFS(Capital_Investments!C$2:C$10000,Capital_Investments!$B$2:$B$10000,$A7) -> 0 | D7: =SUMIFS(Capital_Investments!D$2:D$10000,Capital_Investments!$B$2:$B$10000,$A7) -> 0 | E7: =SUMIFS(Capital_Investments!E$2:E$10000,Capital_Investments!$B$2:$B$10000,$A7) -> 0 | F7: =SUMIFS(Capital_Investments!F$2:F$10000,Capital_Investments!$B$2:$B$10000,$A7) -> 0 | G7: =SUMIFS(Capital_Investments!G$2:G$10000,Capital_Investments!$B$2:$B$10000,$A7) -> 0 | H7: =SUMIFS(Capital_Investments!H$2:H$10000,Capital_Investments!$B$2:$B$10000,$A7) -> 0 | I7: =SUMIFS(Capital_Investments!I$2:I$10000,Capital_Investments!$B$2:$B$10000,$A7) -> 0 | J7: =SUMIFS(Capital_Investments!J$2:J$10000,Capital_Investments!$B$2:$B$10000,$A7) -> 0 | ... AG7: =SUMIFS(Capital_Investments!AG$2:AG$10000,Capital_Investments!$B$2:$B$10000,$A7) -> 0
A8: PHL_POW_PP_COAL | C8: =SUMIFS(Capital_Investments!C$2:C$10000,Capital_Investments!$B$2:$B$10000,$A8) -> 0 | D8: =SUMIFS(Capital_Investments!D$2:D$10000,Capital_Investments!$B$2:$B$10000,$A8) -> 1595 | E8: =SUMIFS(Capital_Investments!E$2:E$10000,Capital_Investments!$B$2:$B$10000,$A8) -> 1692.68 | F8: =SUMIFS(Capital_Investments!F$2:F$10000,Capital_Investments!$B$2:$B$10000,$A8) -> 0 | G8: =SUMIFS(Capital_Investments!G$2:G$10000,Capital_Investments!$B$2:$B$10000,$A8) -> 1320 | H8: =SUMIFS(Capital_Investments!H$2:H$10000,Capital_Investments!$B$2:$B$10000,$A8) -> 0 | I8: =SUMIFS(Capital_Investments!I$2:I$10000,Capital_Investments!$B$2:$B$10000,$A8) -> 0 | J8: =SUMIFS(Capital_Investments!J$2:J$10000,Capital_Investments!$B$2:$B$10000,$A8) -> 3254.5245 | ... AG8: =SUMIFS(Capital_Investments!AG$2:AG$10000,Capital_Investments!$B$2:$B$10000,$A8) -> 0
A9: PHL_POW_PP_COAL_CCS | C9: =SUMIFS(Capital_Investments!C$2:C$10000,Capital_Investments!$B$2:$B$10000,$A9) -> 0 | D9: =SUMIFS(Capital_Investments!D$2:D$10000,Capital_Investments!$B$2:$B$10000,$A9) -> 0 | E9: =SUMIFS(Capital_Investments!E$2:E$10000,Capital_Investments!$B$2:$B$10000,$A9) -> 0 | F9: =SUMIFS(Capital_Investments!F$2:F$10000,Capital_Investments!$B$2:$B$10000,$A9) -> 0 | G9: =SUMIFS(Capital_Investments!G$2:G$10000,Capital_Investments!$B$2:$B$10000,$A9) -> 0 | H9: =SUMIFS(Capital_Investments!H$2:H$10000,Capital_Investments!$B$2:$B$10000,$A9) -> 0 | I9: =SUMIFS(Capital_Investments!I$2:I$10000,Capital_Investments!$B$2:$B$10000,$A9) -> 0 | J9: =SUMIFS(Capital_Investments!J$2:J$10000,Capital_Investments!$B$2:$B$10000,$A9) -> 0 | ... AG9: =SUMIFS(Capital_Investments!AG$2:AG$10000,Capital_Investments!$B$2:$B$10000,$A9) -> 0
A10: PHL_POW_PP_H2 | C10: =SUMIFS(Capital_Investments!C$2:C$10000,Capital_Investments!$B$2:$B$10000,$A10) -> 0 | D10: =SUMIFS(Capital_Investments!D$2:D$10000,Capital_Investments!$B$2:$B$10000,$A10) -> 0 | E10: =SUMIFS(Capital_Investments!E$2:E$10000,Capital_Investments!$B$2:$B$10000,$A10) -> 0 | F10: =SUMIFS(Capital_Investments!F$2:F$10000,Capital_Investments!$B$2:$B$10000,$A10) -> 0 | G10: =SUMIFS(Capital_Investments!G$2:G$10000,Capital_Investments!$B$2:$B$10000,$A10) -> 0 | H10: =SUMIFS(Capital_Investments!H$2:H$10000,Capital_Investments!$B$2:$B$10000,$A10) -> 0 | I10: =SUMIFS(Capital_Investments!I$2:I$10000,Capital_Investments!$B$2:$B$10000,$A10) -> 0 | J10: =SUMIFS(Capital_Investments!J$2:J$10000,Capital_Investments!$B$2:$B$10000,$A10) -> 0 | ... AG10: =SUMIFS(Capital_Investments!AG$2:AG$10000,Capital_Investments!$B$2:$B$10000,$A10) -> 0
A11: PHL_POW_PP_HY_LA | C11: =SUMIFS(Capital_Investments!C$2:C$10000,Capital_Investments!$B$2:$B$10000,$A11) -> 4389.9544 | D11: =SUMIFS(Capital_Investments!D$2:D$10000,Capital_Investments!$B$2:$B$10000,$A11) -> 7663.7159 | E11: =SUMIFS(Capital_Investments!E$2:E$10000,Capital_Investments!$B$2:$B$10000,$A11) -> 47.7 | F11: =SUMIFS(Capital_Investments!F$2:F$10000,Capital_Investments!$B$2:$B$10000,$A11) -> 140.4 | G11: =SUMIFS(Capital_Investments!G$2:G$10000,Capital_Investments!$B$2:$B$10000,$A11) -> 105.6 | H11: =SUMIFS(Capital_Investments!H$2:H$10000,Capital_Investments!$B$2:$B$10000,$A11) -> 0 | I11: =SUMIFS(Capital_Investments!I$2:I$10000,Capital_Investments!$B$2:$B$10000,$A11) -> 0 | J11: =SUMIFS(Capital_Investments!J$2:J$10000,Capital_Investments!$B$2:$B$10000,$A11) -> 0 | ... AG11: =SUMIFS(Capital_Investments!AG$2:AG$10000,Capital_Investments!$B$2:$B$10000,$A11) -> 0
A12: PHL_POW_PP_NGCC | C12: =SUMIFS(Capital_Investments!C$2:C$10000,Capital_Investments!$B$2:$B$10000,$A12) -> 0 | D12: =SUMIFS(Capital_Investments!D$2:D$10000,Capital_Investments!$B$2:$B$10000,$A12) -> 0 | E12: =SUMIFS(Capital_Investments!E$2:E$10000,Capital_Investments!$B$2:$B$10000,$A12) -> 0 | F12: =SUMIFS(Capital_Investments!F$2:F$10000,Capital_Investments!$B$2:$B$10000,$A12) -> 0 | G12: =SUMIFS(Capital_Investments!G$2:G$10000,Capital_Investments!$B$2:$B$10000,$A12) -> 0 | H12: =SUMIFS(Capital_Investments!H$2:H$10000,Capital_Investments!$B$2:$B$10000,$A12) -> 1056 | I12: =SUMIFS(Capital_Investments!I$2:I$10000,Capital_Investments!$B$2:$B$10000,$A12) -> 0 | J12: =SUMIFS(Capital_Investments!J$2:J$10000,Capital_Investments!$B$2:$B$10000,$A12) -> 0 | ... AG12: =SUMIFS(Capital_Investments!AG$2:AG$10000,Capital_Investments!$B$2:$B$10000,$A12) -> 2024.2701
A13: PHL_POW_PP_NGCC_CCS | C13: =SUMIFS(Capital_Investments!C$2:C$10000,Capital_Investments!$B$2:$B$10000,$A13) -> 0 | D13: =SUMIFS(Capital_Investments!D$2:D$10000,Capital_Investments!$B$2:$B$10000,$A13) -> 0 | E13: =SUMIFS(Capital_Investments!E$2:E$10000,Capital_Investments!$B$2:$B$10000,$A13) -> 0 | F13: =SUMIFS(Capital_Investments!F$2:F$10000,Capital_Investments!$B$2:$B$10000,$A13) -> 0 | G13: =SUMIFS(Capital_Investments!G$2:G$10000,Capital_Investments!$B$2:$B$10000,$A13) -> 0 | H13: =SUMIFS(Capital_Investments!H$2:H$10000,Capital_Investments!$B$2:$B$10000,$A13) -> 0 | I13: =SUMIFS(Capital_Investments!I$2:I$10000,Capital_Investments!$B$2:$B$10000,$A13) -> 0 | J13: =SUMIFS(Capital_Investments!J$2:J$10000,Capital_Investments!$B$2:$B$10000,$A13) -> 0 | ... AG13: =SUMIFS(Capital_Investments!AG$2:AG$10000,Capital_Investments!$B$2:$B$10000,$A13) -> 0
A14: PHL_POW_PP_NU | C14: =SUMIFS(Capital_Investments!C$2:C$10000,Capital_Investments!$B$2:$B$10000,$A14) -> 0 | D14: =SUMIFS(Capital_Investments!D$2:D$10000,Capital_Investments!$B$2:$B$10000,$A14) -> 0 | E14: =SUMIFS(Capital_Investments!E$2:E$10000,Capital_Investments!$B$2:$B$10000,$A14) -> 0 | F14: =SUMIFS(Capital_Investments!F$2:F$10000,Capital_Investments!$B$2:$B$10000,$A14) -> 0 | G14: =SUMIFS(Capital_Investments!G$2:G$10000,Capital_Investments!$B$2:$B$10000,$A14) -> 0 | H14: =SUMIFS(Capital_Investments!H$2:H$10000,Capital_Investments!$B$2:$B$10000,$A14) -> 0 | I14: =SUMIFS(Capital_Investments!I$2:I$10000,Capital_Investments!$B$2:$B$10000,$A14) -> 0 | J14: =SUMIFS(Capital_Investments!J$2:J$10000,Capital_Investments!$B$2:$B$10000,$A14) -> 0 | ... AG14: =SUMIFS(Capital_Investments!AG$2:AG$10000,Capital_Investments!$B$2:$B$10000,$A14) -> 0
A15: PHL_POW_PP_NUSMR | C15: =SUMIFS(Capital_Investments!C$2:C$10000,Capital_Investments!$B$2:$B$10000,$A15) -> 0 | D15: =SUMIFS(Capital_Investments!D$2:D$10000,Capital_Investments!$B$2:$B$10000,$A15) -> 0 | E15: =SUMIFS(Capital_Investments!E$2:E$10000,Capital_Investments!$B$2:$B$10000,$A15) -> 0 | F15: =SUMIFS(Capital_Investments!F$2:F$10000,Capital_Investments!$B$2:$B$10000,$A15) -> 0 | G15: =SUMIFS(Capital_Investments!G$2:G$10000,Capital_Investments!$B$2:$B$10000,$A15) -> 0 | H15: =SUMIFS(Capital_Investments!H$2:H$10000,Capital_Investments!$B$2:$B$10000,$A15) -> 0 | I15: =SUMIFS(Capital_Investments!I$2:I$10000,Capital_Investments!$B$2:$B$10000,$A15) -> 0 | J15: =SUMIFS(Capital_Investments!J$2:J$10000,Capital_Investments!$B$2:$B$10000,$A15) -> 0 | ... AG15: =SUMIFS(Capital_Investments!AG$2:AG$10000,Capital_Investments!$B$2:$B$10000,$A15) -> 5132.753
... A21: PHL_POW_TD | C21: =SUMIFS(Capital_Investments!C$2:C$10000,Capital_Investments!$B$2:$B$10000,$A21) -> 0 | D21: =SUMIFS(Capital_Investments!D$2:D$10000,Capital_Investments!$B$2:$B$10000,$A21) -> 0 | E21: =SUMIFS(Capital_Investments!E$2:E$10000,Capital_Investments!$B$2:$B$10000,$A21) -> 0 | F21: =SUMIFS(Capital_Investments!F$2:F$10000,Capital_Investments!$B$2:$B$10000,$A21) -> 0 | G21: =SUMIFS(Capital_Investments!G$2:G$10000,Capital_Investments!$B$2:$B$10000,$A21) -> 0 | H21: =SUMIFS(Capital_Investments!H$2:H$10000,Capital_Investments!$B$2:$B$10000,$A21) -> 459.6972 | I21: =SUMIFS(Capital_Investments!I$2:I$10000,Capital_Investments!$B$2:$B$10000,$A21) -> 1316.7722 | J21: =SUMIFS(Capital_Investments!J$2:J$10000,Capital_Investments!$B$2:$B$10000,$A21) -> 1316.7722 | ... AG21: =SUMIFS(Capital_Investments!AG$2:AG$10000,Capital_Investments!$B$2:$B$10000,$A21) -> 3107.0751
A22: Total Capital Investments (Million USD) | C22: =SUM(C4:C21) -> 4747.952 | D22: =SUM(D4:D21) -> 10006.783 | E22: =SUM(E4:E21) -> 2531.4872 | F22: =SUM(F4:F21) -> 1576.1906 | G22: =SUM(G4:G21) -> 2362.6025 | H22: =SUM(H4:H21) -> 1897.1058 | I22: =SUM(I4:I21) -> 5039.2865 | J22: =SUM(J4:J21) -> 4571.2967 | ... AG22: =SUM(AG4:AG21) -> 13589.976
A24: Annualized Investment Cost (M.USD) | C24: 2020 | D24: 2021 | E24: 2022 | F24: 2023 | G24: 2024 | H24: 2025 | I24: 2026 | J24: 2027 | K24: 2028 | L24: 2029 | M24: 2030 | N24: 2031 | O24: 2032 | P24: 2033 | Q24: 2034 | R24: 2035 | S24: 2036 | T24: 2037 | U24: 2038 | V24: 2039 | W24: 2040 | X24: 2041 | Y24: 2042 | Z24: 2043 | AA24: 2044 | AB24: 2045 | AC24: 2046 | AD24: 2047 | AE24: 2048 | AF24: 2049 | AG24: 2050
A25: PHL_POW_CHP_BIOM_OLD | C25: =SUMIFS(Annualized_Investments!C$2:C$9991,Annualized_Investments!$B$2:$B$9991,$A25) -> 0 | D25: =SUMIFS(Annualized_Investments!D$2:D$9991,Annualized_Investments!$B$2:$B$9991,$A25) -> 0 | E25: =SUMIFS(Annualized_Investments!E$2:E$9991,Annualized_Investments!$B$2:$B$9991,$A25) -> 20.480611 | F25: =SUMIFS(Annualized_Investments!F$2:F$9991,Annualized_Investments!$B$2:$B$9991,$A25) -> 21.979192 | G25: =SUMIFS(Annualized_Investments!G$2:G$9991,Annualized_Investments!$B$2:$B$9991,$A25) -> 24.451851 | H25: =SUMIFS(Annualized_Investments!H$2:H$9991,Annualized_Investments!$B$2:$B$9991,$A25) -> 24.451851 | I25: =SUMIFS(Annualized_Investments!I$2:I$9991,Annualized_Investments!$B$2:$B$9991,$A25) -> 24.451851 | J25: =SUMIFS(Annualized_Investments!J$2:J$9991,Annualized_Investments!$B$2:$B$9991,$A25) -> 24.451851 | ... AG25: =SUMIFS(Annualized_Investments!AG$2:AG$9991,Annualized_Investments!$B$2:$B$9991,$A25) -> 24.451851
A26: PHL_POW_CHP_COAL_OLD | C26: =SUMIFS(Annualized_Investments!C$2:C$9991,Annualized_Investments!$B$2:$B$9991,$A26) -> 0 | D26: =SUMIFS(Annualized_Investments!D$2:D$9991,Annualized_Investments!$B$2:$B$9991,$A26) -> 0 | E26: =SUMIFS(Annualized_Investments!E$2:E$9991,Annualized_Investments!$B$2:$B$9991,$A26) -> 0 | F26: =SUMIFS(Annualized_Investments!F$2:F$9991,Annualized_Investments!$B$2:$B$9991,$A26) -> 0 | G26: =SUMIFS(Annualized_Investments!G$2:G$9991,Annualized_Investments!$B$2:$B$9991,$A26) -> 0 | H26: =SUMIFS(Annualized_Investments!H$2:H$9991,Annualized_Investments!$B$2:$B$9991,$A26) -> 0 | I26: =SUMIFS(Annualized_Investments!I$2:I$9991,Annualized_Investments!$B$2:$B$9991,$A26) -> 0 | J26: =SUMIFS(Annualized_Investments!J$2:J$9991,Annualized_Investments!$B$2:$B$9991,$A26) -> 0 | ... AG26: =SUMIFS(Annualized_Investments!AG$2:AG$9991,Annualized_Investments!$B$2:$B$9991,$A26) -> 0
A27: PHL_POW_GEO_OLD | C27: =SUMIFS(Annualized_Investments!C$2:C$9991,Annualized_Investments!$B$2:$B$9991,$A27) -> 0 | D27: =SUMIFS(Annualized_Investments!D$2:D$9991,Annualized_Investments!$B$2:$B$9991,$A27) -> 0 | E27: =SUMIFS(Annualized_Investments!E$2:E$9991,Annualized_Investments!$B$2:$B$9991,$A27) -> 0.90358901 | F27: =SUMIFS(Annualized_Investments!F$2:F$9991,Annualized_Investments!$B$2:$B$9991,$A27) -> 69.548414 | G27: =SUMIFS(Annualized_Investments!G$2:G$9991,Annualized_Investments!$B$2:$B$9991,$A27) -> 71.190132 | H27: =SUMIFS(Annualized_Investments!H$2:H$9991,Annualized_Investments!$B$2:$B$9991,$A27) -> 79.908545 | I27: =SUMIFS(Annualized_Investments!I$2:I$9991,Annualized_Investments!$B$2:$B$9991,$A27) -> 286.5193 | J27: =SUMIFS(Annualized_Investments!J$2:J$9991,Annualized_Investments!$B$2:$B$9991,$A27) -> 286.5193 | ... AG27: =SUMIFS(Annualized_Investments!AG$2:AG$9991,Annualized_Investments!$B$2:$B$9991,$A27) -> 955.8587
A28: PHL_POW_PP_BIOM_CCS | C28: =SUMIFS(Annualized_Investments!C$2:C$9991,Annualized_Investments!$B$2:$B$9991,$A28) -> 0 | D28: =SUMIFS(Annualized_Investments!D$2:D$9991,Annualized_Investments!$B$2:$B$9991,$A28) -> 0 | E28: =SUMIFS(Annualized_Investments!E$2:E$9991,Annualized_Investments!$B$2:$B$9991,$A28) -> 0 | F28: =SUMIFS(Annualized_Investments!F$2:F$9991,Annualized_Investments!$B$2:$B$9991,$A28) -> 0 | G28: =SUMIFS(Annualized_Investments!G$2:G$9991,Annualized_Investments!$B$2:$B$9991,$A28) -> 0 | H28: =SUMIFS(Annualized_Investments!H$2:H$9991,Annualized_Investments!$B$2:$B$9991,$A28) -> 0 | I28: =SUMIFS(Annualized_Investments!I$2:I$9991,Annualized_Investments!$B$2:$B$9991,$A28) -> 0 | J28: =SUMIFS(Annualized_Investments!J$2:J$9991,Annualized_Investments!$B$2:$B$9991,$A28) -> 0 | ... AG28: =SUMIFS(Annualized_Investments!AG$2:AG$9991,Annualized_Investments!$B$2:$B$9991,$A28) -> 0
A29: PHL_POW_PP_COAL | C29: =SUMIFS(Annualized_Investments!C$2:C$9991,Annualized_Investments!$B$2:$B$9991,$A29) -> 0 | D29: =SUMIFS(Annualized_Investments!D$2:D$9991,Annualized_Investments!$B$2:$B$9991,$A29) -> 107.78016 | E29: =SUMIFS(Annualized_Investments!E$2:E$9991,Annualized_Investments!$B$2:$B$9991,$A29) -> 222.16093 | F29: =SUMIFS(Annualized_Investments!F$2:F$9991,Annualized_Investments!$B$2:$B$9991,$A29) -> 222.16093 | G29: =SUMIFS(Annualized_Investments!G$2:G$9991,Annualized_Investments!$B$2:$B$9991,$A29) -> 311.3583 | H29: =SUMIFS(Annualized_Investments!H$2:H$9991,Annualized_Investments!$B$2:$B$9991,$A29) -> 311.3583 | I29: =SUMIFS(Annualized_Investments!I$2:I$9991,Annualized_Investments!$B$2:$B$9991,$A29) -> 311.3583 | J29: =SUMIFS(Annualized_Investments!J$2:J$9991,Annualized_Investments!$B$2:$B$9991,$A29) -> 531.27879 | ... AG29: =SUMIFS(Annualized_Investments!AG$2:AG$9991,Annualized_Investments!$B$2:$B$9991,$A29) -> 1685.1947
A30: PHL_POW_PP_COAL_CCS | C30: =SUMIFS(Annualized_Investments!C$2:C$9991,Annualized_Investments!$B$2:$B$9991,$A30) -> 0 | D30: =SUMIFS(Annualized_Investments!D$2:D$9991,Annualized_Investments!$B$2:$B$9991,$A30) -> 0 | E30: =SUMIFS(Annualized_Investments!E$2:E$9991,Annualized_Investments!$B$2:$B$9991,$A30) -> 0 | F30: =SUMIFS(Annualized_Investments!F$2:F$9991,Annualized_Investments!$B$2:$B$9991,$A30) -> 0 | G30: =SUMIFS(Annualized_Investments!G$2:G$9991,Annualized_Investments!$B$2:$B$9991,$A30) -> 0 | H30: =SUMIFS(Annualized_Investments!H$2:H$9991,Annualized_Investments!$B$2:$B$9991,$A30) -> 0 | I30: =SUMIFS(Annualized_Investments!I$2:I$9991,Annualized_Investments!$B$2:$B$9991,$A30) -> 0 | J30: =SUMIFS(Annualized_Investments!J$2:J$9991,Annualized_Investments!$B$2:$B$9991,$A30) -> 0 | ... AG30: =SUMIFS(Annualized_Investments!AG$2:AG$9991,Annualized_Investments!$B$2:$B$9991,$A30) -> 0
A31: PHL_POW_PP_H2 | C31: =SUMIFS(Annualized_Investments!C$2:C$9991,Annualized_Investments!$B$2:$B$9991,$A31) -> 0 | D31: =SUMIFS(Annualized_Investments!D$2:D$9991,Annualized_Investments!$B$2:$B$9991,$A31) -> 0 | E31: =SUMIFS(Annualized_Investments!E$2:E$9991,Annualized_Investments!$B$2:$B$9991,$A31) -> 0 | F31: =SUMIFS(Annualized_Investments!F$2:F$9991,Annualized_Investments!$B$2:$B$9991,$A31) -> 0 | G31: =SUMIFS(Annualized_Investments!G$2:G$9991,Annualized_Investments!$B$2:$B$9991,$A31) -> 0 | H31: =SUMIFS(Annualized_Investments!H$2:H$9991,Annualized_Investments!$B$2:$B$9991,$A31) -> 0 | I31: =SUMIFS(Annualized_Investments!I$2:I$9991,Annualized_Investments!$B$2:$B$9991,$A31) -> 0 | J31: =SUMIFS(Annualized_Investments!J$2:J$9991,Annualized_Investments!$B$2:$B$9991,$A31) -> 0 | ... AG31: =SUMIFS(Annualized_Investments!AG$2:AG$9991,Annualized_Investments!$B$2:$B$9991,$A31) -> 0
A32: PHL_POW_PP_HY_LA | C32: =SUMIFS(Annualized_Investments!C$2:C$9991,Annualized_Investments!$B$2:$B$9991,$A32) -> 210.64731 | D32: =SUMIFS(Annualized_Investments!D$2:D$9991,Annualized_Investments!$B$2:$B$9991,$A32) -> 578.3826 | E32: =SUMIFS(Annualized_Investments!E$2:E$9991,Annualized_Investments!$B$2:$B$9991,$A32) -> 580.67144 | F32: =SUMIFS(Annualized_Investments!F$2:F$9991,Annualized_Investments!$B$2:$B$9991,$A32) -> 587.40838 | G32: =SUMIFS(Annualized_Investments!G$2:G$9991,Annualized_Investments!$B$2:$B$9991,$A32) -> 592.47549 | H32: =SUMIFS(Annualized_Investments!H$2:H$9991,Annualized_Investments!$B$2:$B$9991,$A32) -> 592.47549 | I32: =SUMIFS(Annualized_Investments!I$2:I$9991,Annualized_Investments!$B$2:$B$9991,$A32) -> 592.47549 | J32: =SUMIFS(Annualized_Investments!J$2:J$9991,Annualized_Investments!$B$2:$B$9991,$A32) -> 592.47549 | ... AG32: =SUMIFS(Annualized_Investments!AG$2:AG$9991,Annualized_Investments!$B$2:$B$9991,$A32) -> 592.47549
A33: PHL_POW_PP_NGCC | C33: =SUMIFS(Annualized_Investments!C$2:C$9991,Annualized_Investments!$B$2:$B$9991,$A33) -> 0 | D33: =SUMIFS(Annualized_Investments!D$2:D$9991,Annualized_Investments!$B$2:$B$9991,$A33) -> 0 | E33: =SUMIFS(Annualized_Investments!E$2:E$9991,Annualized_Investments!$B$2:$B$9991,$A33) -> 0 | F33: =SUMIFS(Annualized_Investments!F$2:F$9991,Annualized_Investments!$B$2:$B$9991,$A33) -> 0 | G33: =SUMIFS(Annualized_Investments!G$2:G$9991,Annualized_Investments!$B$2:$B$9991,$A33) -> 0 | H33: =SUMIFS(Annualized_Investments!H$2:H$9991,Annualized_Investments!$B$2:$B$9991,$A33) -> 71.3579 | I33: =SUMIFS(Annualized_Investments!I$2:I$9991,Annualized_Investments!$B$2:$B$9991,$A33) -> 71.3579 | J33: =SUMIFS(Annualized_Investments!J$2:J$9991,Annualized_Investments!$B$2:$B$9991,$A33) -> 71.3579 | ... AG33: =SUMIFS(Annualized_Investments!AG$2:AG$9991,Annualized_Investments!$B$2:$B$9991,$A33) -> 815.71985
A34: PHL_POW_PP_NGCC_CCS | C34: =SUMIFS(Annualized_Investments!C$2:C$9991,Annualized_Investments!$B$2:$B$9991,$A34) -> 0 | D34: =SUMIFS(Annualized_Investments!D$2:D$9991,Annualized_Investments!$B$2:$B$9991,$A34) -> 0 | E34: =SUMIFS(Annualized_Investments!E$2:E$9991,Annualized_Investments!$B$2:$B$9991,$A34) -> 0 | F34: =SUMIFS(Annualized_Investments!F$2:F$9991,Annualized_Investments!$B$2:$B$9991,$A34) -> 0 | G34: =SUMIFS(Annualized_Investments!G$2:G$9991,Annualized_Investments!$B$2:$B$9991,$A34) -> 0 | H34: =SUMIFS(Annualized_Investments!H$2:H$9991,Annualized_Investments!$B$2:$B$9991,$A34) -> 0 | I34: =SUMIFS(Annualized_Investments!I$2:I$9991,Annualized_Investments!$B$2:$B$9991,$A34) -> 0 | J34: =SUMIFS(Annualized_Investments!J$2:J$9991,Annualized_Investments!$B$2:$B$9991,$A34) -> 0 | ... AG34: =SUMIFS(Annualized_Investments!AG$2:AG$9991,Annualized_Investments!$B$2:$B$9991,$A34) -> 0
A35: PHL_POW_PP_NU | C35: =SUMIFS(Annualized_Investments!C$2:C$9991,Annualized_Investments!$B$2:$B$9991,$A35) -> 0 | D35: =SUMIFS(Annualized_Investments!D$2:D$9991,Annualized_Investments!$B$2:$B$9991,$A35) -> 0 | E35: =SUMIFS(Annualized_Investments!E$2:E$9991,Annualized_Investments!$B$2:$B$9991,$A35) -> 0 | F35: =SUMIFS(Annualized_Investments!F$2:F$9991,Annualized_Investments!$B$2:$B$9991,$A35) -> 0 | G35: =SUMIFS(Annualized_Investments!G$2:G$9991,Annualized_Investments!$B$2:$B$9991,$A35) -> 0 | H35: =SUMIFS(Annualized_Investments!H$2:H$9991,Annualized_Investments!$B$2:$B$9991,$A35) -> 0 | I35: =SUMIFS(Annualized_Investments!I$2:I$9991,Annualized_Investments!$B$2:$B$9991,$A35) -> 0 | J35: =SUMIFS(Annualized_Investments!J$2:J$9991,Annualized_Investments!$B$2:$B$9991,$A35) -> 0 | ... AG35: =SUMIFS(Annualized_Investments!AG$2:AG$9991,Annualized_Investments!$B$2:$B$9991,$A35) -> 0
A36: PHL_POW_PP_NUSMR | C36: =SUMIFS(Annualized_Investments!C$2:C$9991,Annualized_Investments!$B$2:$B$9991,$A36) -> 0 | D36: =SUMIFS(Annualized_Investments!D$2:D$9991,Annualized_Investments!$B$2:$B$9991,$A36) -> 0 | E36: =SUMIFS(Annualized_Investments!E$2:E$9991,Annualized_Investments!$B$2:$B$9991,$A36) -> 0 | F36: =SUMIFS(Annualized_Investments!F$2:F$9991,Annualized_Investments!$B$2:$B$9991,$A36) -> 0 | G36: =SUMIFS(Annualized_Investments!G$2:G$9991,Annualized_Investments!$B$2:$B$9991,$A36) -> 0 | H36: =SUMIFS(Annualized_Investments!H$2:H$9991,Annualized_Investments!$B$2:$B$9991,$A36) -> 0 | I36: =SUMIFS(Annualized_Investments!I$2:I$9991,Annualized_Investments!$B$2:$B$9991,$A36) -> 0 | J36: =SUMIFS(Annualized_Investments!J$2:J$9991,Annualized_Investments!$B$2:$B$9991,$A36) -> 0 | ... AG36: =SUMIFS(Annualized_Investments!AG$2:AG$9991,Annualized_Investments!$B$2:$B$9991,$A36) -> 4259.8242
... A42: PHL_POW_TD | C42: =SUMIFS(Annualized_Investments!C$2:C$9991,Annualized_Investments!$B$2:$B$9991,$A42) -> 0 | D42: =SUMIFS(Annualized_Investments!D$2:D$9991,Annualized_Investments!$B$2:$B$9991,$A42) -> 0 | E42: =SUMIFS(Annualized_Investments!E$2:E$9991,Annualized_Investments!$B$2:$B$9991,$A42) -> 0 | F42: =SUMIFS(Annualized_Investments!F$2:F$9991,Annualized_Investments!$B$2:$B$9991,$A42) -> 0 | G42: =SUMIFS(Annualized_Investments!G$2:G$9991,Annualized_Investments!$B$2:$B$9991,$A42) -> 0 | H42: =SUMIFS(Annualized_Investments!H$2:H$9991,Annualized_Investments!$B$2:$B$9991,$A42) -> 23.98163 | I42: =SUMIFS(Annualized_Investments!I$2:I$9991,Annualized_Investments!$B$2:$B$9991,$A42) -> 92.675423 | J42: =SUMIFS(Annualized_Investments!J$2:J$9991,Annualized_Investments!$B$2:$B$9991,$A42) -> 161.36922 | ... AG42: =SUMIFS(Annualized_Investments!AG$2:AG$9991,Annualized_Investments!$B$2:$B$9991,$A42) -> 2425.5664
A43: Total Annualized Investments (Million USD) | C43: =SUM(C25:C42) -> 234.83856 | D43: =SUM(D25:D42) -> 756.46065 | E43: =SUM(E25:E42) -> 918.84101 | F43: =SUM(F25:F42) -> 1006.569 | G43: =SUM(G25:G42) -> 1158.3122 | H43: =SUM(H25:H42) -> 1276.2681 | I43: =SUM(I25:I42) -> 1551.5727 | J43: =SUM(J25:J42) -> 1840.1869 | ... AG43: =SUM(AG25:AG42) -> 11615.939

Sheet Emissions PEP
A1: PEP Scenario
A2: Annual Technology Emission by Mode (Mton)
A3: Emission / Technology | B3: 2020 | C3: 2021 | D3: 2022 | E3: 2023 | F3: 2024 | G3: 2025 | H3: 2026 | I3: 2027 | J3: 2028 | K3: 2029 | L3: 2030 | M3: 2031 | N3: 2032 | O3: 2033 | P3: 2034 | Q3: 2035 | R3: 2036 | S3: 2037 | T3: 2038 | U3: 2039 | V3: 2040 | W3: 2041 | X3: 2042 | Y3: 2043 | Z3: 2044 | AA3: 2045 | AB3: 2046 | AC3: 2047 | AD3: 2048 | AE3: 2049 | AF3: 2050 | AG3: 2051 | AH3: 2052 | AI3: 2053
A4: CO2e | B4: 97.2368 | C4: 130.9558 | D4: 138.0291 | E4: 144.6563 | F4: 152.1883 | G4: 152.9749 | H4: 150.9351 | I4: 156.3485 | J4: 161.7406 | K4: 167.065 | L4: 160.7758 | M4: 170.8505 | N4: 180.1604 | O4: 190.0282 | P4: 184.3807 | Q4: 177.0234 | R4: 170.2539 | S4: 162.4349 | T4: 151.9248 | U4: 147.3548 | V4: 144.5833 | W4: 147.1184 | X4: 149.751 | Y4: 153.1202 | Z4: 155.7341 | AA4: 157.4759 | AB4: 154.8883 | AC4: 150.5416 | AD4: 149.9719 | AE4: 149.2755 | AF4: 145.2971 | AG4: 145.6345 | AH4: 144.8147 | AI4: 143.3112
A5: PHL_POW_BH2_NG | B5: 0 | C5: 0 | D5: 0 | E5: 0 | F5: 0 | G5: 0 | H5: 0 | I5: 0 | J5: 0 | K5: 0 | L5: 0 | M5: 0 | N5: 0 | O5: 0 | P5: 0 | Q5: 0 | R5: 0 | S5: 0 | T5: 0 | U5: 0 | V5: 0 | W5: 0 | X5: 0 | Y5: 0 | Z5: 0 | AA5: 0 | AB5: 0 | AC5: 0 | AD5: 0 | AE5: 0 | AF5: 0 | AG5: 0 | AH5: 0 | AI5: 0
A6: PHL_POW_DAC | B6: 0 | C6: 0 | D6: 0 | E6: 0 | F6: 0 | G6: 0 | H6: 0 | I6: 0 | J6: 0 | K6: 0 | L6: 0 | M6: 0 | N6: 0 | O6: 0 | P6: 0 | Q6: 0 | R6: 0 | S6: 0 | T6: 0 | U6: 0 | V6: 0 | W6: 0 | X6: 0 | Y6: 0 | Z6: 0 | AA6: 0 | AB6: 0 | AC6: 0 | AD6: 0 | AE6: 0 | AF6: 0 | AG6: 0 | AH6: 0 | AI6: 0
A7: PHL_POW_PP_BIOM_CCS | B7: 0 | C7: 0 | D7: 0 | E7: 0 | F7: 0 | G7: 0 | H7: 0 | I7: 0 | J7: 0 | K7: 0 | L7: 0 | M7: 0 | N7: 0 | O7: 0 | P7: 0 | Q7: 0 | R7: 0 | S7: 0 | T7: 0 | U7: 0 | V7: 0 | W7: 0 | X7: 0 | Y7: 0 | Z7: 0 | AA7: 0 | AB7: 0 | AC7: 0 | AD7: 0 | AE7: 0 | AF7: 0 | AG7: 0 | AH7: 0 | AI7: 0
A8: PHL_POW_PP_COAL_CCS | B8: 0 | C8: 0 | D8: 0 | E8: 0 | F8: 0 | G8: 0 | H8: 0 | I8: 0 | J8: 0 | K8: 0 | L8: 0 | M8: 0 | N8: 0 | O8: 0 | P8: 0 | Q8: 0 | R8: 0 | S8: 0 | T8: 0 | U8: 0 | V8: 0 | W8: 0 | X8: 0 | Y8: 0 | Z8: 0 | AA8: 0 | AB8: 0 | AC8: 0 | AD8: 0 | AE8: 0 | AF8: 0 | AG8: 0 | AH8: 0 | AI8: 0
A9: PHL_POW_PP_NGCC_CCS | B9: 0 | C9: 0 | D9: 0 | E9: 0 | F9: 0 | G9: 0 | H9: 0 | I9: 0 | J9: 0 | K9: 0 | L9: 0 | M9: 0 | N9: 0 | O9: 0 | P9: 0 | Q9: 0 | R9: 0 | S9: 0 | T9: 0 | U9: 0 | V9: 0 | W9: 0 | X9: 0 | Y9: 0 | Z9: 0 | AA9: 0 | AB9: 0 | AC9: 0 | AD9: 0 | AE9: 0 | AF9: 0 | AG9: 0 | AH9: 0 | AI9: 0
A10: PHL_PRO_PROC_COAL | B10: 70.5467 | C10: 110.0799 | D10: 118.0273 | E10: 126.249 | F10: 133.6535 | G10: 141.6708 | H10: 140.1513 | I10: 145.8409 | J10: 151.4712 | K10: 156.888 | L10: 150.7372 | M10: 160.7468 | N10: 170.4105 | O10: 181.073 | P10: 175.5778 | Q10: 168.3504 | R10: 158.6633 | S10: 150.888 | T10: 140.8871 | U10: 134.7674 | V10: 130.1214 | W10: 131.69 | X10: 133.3073 | Y10: 135.2845 | Z10: 136.8941 | AA10: 137.9203 | AB10: 134.6741 | AC10: 129.9811 | AD10: 129.1131 | AE10: 128.0754 | AF10: 123.0745 | AG10: 122.9684 | AH10: 121.2248 | AI10: 114.9555
A11: PHL_PRO_PROC_NG | B11: 7.3094 | C11: 8.0315 | D11: 8.0246 | E11: 7.3979 | F11: 8.4052 | G11: 2.1297 | H11: 2.5266 | I11: 2.4565 | J11: 2.282 | K11: 2.8785 | L11: 2.9381 | M11: 3.0524 | N11: 4.4241 | O11: 7.1202 | P11: 7.8858 | Q11: 8.673 | R11: 11.5906 | S11: 11.5469 | T11: 11.0377 | U11: 12.5874 | V11: 14.4619 | W11: 15.4284 | X11: 16.4437 | Y11: 17.8357 | Z11: 18.84 | AA11: 19.5556 | AB11: 20.2142 | AC11: 20.5605 | AD11: 20.8588 | AE11: 21.2001 | AF11: 22.2226 | AG11: 22.6661 | AH11: 23.5899 | AI11: 28.3557
A12: PHL_PRO_PROC_OIL | B12: 19.3807 | C12: 12.8444 | D12: 11.9772 | E12: 11.0094 | F12: 10.1296 | G12: 9.1744 | H12: 8.2572 | I12: 8.0511 | J12: 7.9874 | K12: 7.2985 | L12: 7.1005 | M12: 7.0513 | N12: 5.3258 | O12: 1.835 | P12: 0.9171 | Q12: 0 | R12: 0 | S12: 0 | T12: 0 | U12: 0 | V12: 0 | W12: 0 | X12: 0 | Y12: 0 | Z12: 0 | AA12: 0 | AB12: 0 | AC12: 0 | AD12: 0 | AE12: 0 | AF12: 0 | AG12: 0 | AH12: 0 | AI12: 0
A13: PM2_5 | B13: 64.8365 | C13: 67.0945 | D13: 69.3282 | E13: 71.561 | F13: 73.7941 | G13: 76.0273 | H13: 76.4112 | I13: 76.7932 | J13: 77.1773 | K13: 77.559 | L13: 77.9407 | M13: 78.6987 | N13: 79.4568 | O13: 80.2152 | P13: 80.9736 | Q13: 81.7317 | R13: 82.998 | S13: 84.263 | T13: 85.53 | U13: 86.7957 | V13: 88.063 | W13: 91.4029 | X13: 94.7412 | Y13: 98.0808 | Z13: 101.4212 | AA13: 104.7608 | AB13: 108.384 | AC13: 112.0074 | AD13: 115.633 | AE13: 119.2571 | AF13: 123.2576 | AG13: 127.2112 | AH13: 131.2236 | AI13: 136.0443
A14: PHL_HOU_COOK_BIOM | B14: 0.0026 | C14: 0 | D14: 0 | E14: 0 | F14: 0 | G14: 0 | H14: 0 | I14: 0 | J14: 0 | K14: 0 | L14: 0 | M14: 0 | N14: 0 | O14: 0 | P14: 0 | Q14: 0 | R14: 0 | S14: 0 | T14: 0 | U14: 0 | V14: 0 | W14: 0 | X14: 0 | Y14: 0 | Z14: 0 | AA14: 0 | AB14: 0 | AC14: 0 | AD14: 0 | AE14: 0 | AF14: 0 | AG14: 0 | AH14: 0 | AI14: 0
... A30: PHL_TRA_VAN_LIQ | B30: 5.773 | C30: 6.1101 | D30: 6.4472 | E30: 6.7844 | F30: 7.1215 | G30: 7.4586 | H30: 7.874 | I30: 8.2886 | J30: 8.704 | K30: 9.1186 | L30: 9.5333 | M30: 10.0308 | N30: 10.5276 | O30: 11.0252 | P30: 11.5227 | Q30: 12.0195 | R30: 12.6271 | S30: 13.2339 | T30: 13.8415 | U30: 14.4483 | V30: 15.0559 | W30: 15.7627 | X30: 16.4695 | Y30: 17.1763 | Z30: 17.8839 | AA30: 18.5907 | AB30: 19.3603 | AC30: 20.1298 | AD30: 20.9002 | AE30: 21.6698 | AF30: 22.4394 | AG30: 23.2174 | AH30: 23.9948 | AI30: 24.7721

Sheet Cost_of_ELCgen
A1: Philippines
A3: AnnualFixedOperatingCost + AnnualVariableOperating Cost (Million USD) | C3: 2020 | D3: 2021 | E3: 2022 | F3: 2023 | G3: 2024 | H3: 2025 | I3: 2026 | J3: 2027 | K3: 2028 | L3: 2029 | M3: 2030 | N3: 2031 | O3: 2032 | P3: 2033 | Q3: 2034 | R3: 2035 | S3: 2036 | T3: 2037 | U3: 2038 | V3: 2039 | W3: 2040 | X3: 2041 | Y3: 2042 | Z3: 2043 | AA3: 2044 | AB3: 2045 | AC3: 2046 | AD3: 2047 | AE3: 2048 | AF3: 2049 | AG3: 2050
A4: TOTAL (Fixed & Variable) | C4: =SUM(C6:C9)+SUM(C38:C54) -> 10162.893 | D4: =SUM(D6:D9)+SUM(D38:D54) -> 6155.3583 | E4: =SUM(E6:E9)+SUM(E38:E54) -> 6401.8118 | F4: =SUM(F6:F9)+SUM(F38:F54) -> 6582.7586 | G4: =SUM(G6:G9)+SUM(G38:G54) -> 6991.1589 | H4: =SUM(H6:H9)+SUM(H38:H54) -> 5841.0003 | I4: =SUM(I6:I9)+SUM(I38:I54) -> 5978.6581 | J4: =SUM(J6:J9)+SUM(J38:J54) -> 6331.6685 | ... AG4: =SUM(AG6:AG9)+SUM(AG38:AG54) -> 10572.196
A5: VARIABLE
A6: PHL_PRO_EXTR_NG | C6: =SUMIFS(Variable!C$2:C$9992,Variable!$B$2:$B$9992,$A6) -> 1261.3245 | D6: =SUMIFS(Variable!D$2:D$9992,Variable!$B$2:$B$9992,$A6) -> 1391.3286 | E6: =SUMIFS(Variable!E$2:E$9992,Variable!$B$2:$B$9992,$A6) -> 1395.6857 | F6: =SUMIFS(Variable!F$2:F$9992,Variable!$B$2:$B$9992,$A6) -> 1291.8042 | G6: =SUMIFS(Variable!G$2:G$9992,Variable!$B$2:$B$9992,$A6) -> 1473.504 | H6: =SUMIFS(Variable!H$2:H$9992,Variable!$B$2:$B$9992,$A6) -> 374.8344 | I6: =SUMIFS(Variable!I$2:I$9992,Variable!$B$2:$B$9992,$A6) -> 446.4331 | J6: =SUMIFS(Variable!J$2:J$9992,Variable!$B$2:$B$9992,$A6) -> 435.7027 | ... AG6: =SUMIFS(Variable!AG$2:AG$9992,Variable!$B$2:$B$9992,$A6) -> 4130.2355
A7: PHL_PRO_EXTR_OIL | C7: =SUMIFS(Variable!C$2:C$9992,Variable!$B$2:$B$9992,$A7) -> 955.7753 | D7: =SUMIFS(Variable!D$2:D$9992,Variable!$B$2:$B$9992,$A7) -> 0 | E7: =SUMIFS(Variable!E$2:E$9992,Variable!$B$2:$B$9992,$A7) -> 8.9153 | F7: =SUMIFS(Variable!F$2:F$9992,Variable!$B$2:$B$9992,$A7) -> 0 | G7: =SUMIFS(Variable!G$2:G$9992,Variable!$B$2:$B$9992,$A7) -> 6.9055 | H7: =SUMIFS(Variable!H$2:H$9992,Variable!$B$2:$B$9992,$A7) -> 0 | I7: =SUMIFS(Variable!I$2:I$9992,Variable!$B$2:$B$9992,$A7) -> 0 | J7: =SUMIFS(Variable!J$2:J$9992,Variable!$B$2:$B$9992,$A7) -> 135.264 | ... AG7: =SUMIFS(Variable!AG$2:AG$9992,Variable!$B$2:$B$9992,$A7) -> 0
A8: PHL_PRO_EXTR_COAL | C8: =SUMIFS(Variable!C$2:C$9992,Variable!$B$2:$B$9992,$A8) -> 2023.5934 | D8: =SUMIFS(Variable!D$2:D$9992,Variable!$B$2:$B$9992,$A8) -> 3168.6587 | E8: =SUMIFS(Variable!E$2:E$9992,Variable!$B$2:$B$9992,$A8) -> 3409.305 | F8: =SUMIFS(Variable!F$2:F$9992,Variable!$B$2:$B$9992,$A8) -> 3659.5005 | G8: =SUMIFS(Variable!G$2:G$9992,Variable!$B$2:$B$9992,$A8) -> 3887.5842 | H8: =SUMIFS(Variable!H$2:H$9992,Variable!$B$2:$B$9992,$A8) -> 4135.0404 | I8: =SUMIFS(Variable!I$2:I$9992,Variable!$B$2:$B$9992,$A8) -> 4104.7955 | J8: =SUMIFS(Variable!J$2:J$9992,Variable!$B$2:$B$9992,$A8) -> 4286.1149 | ... AG8: =SUMIFS(Variable!AG$2:AG$9992,Variable!$B$2:$B$9992,$A8) -> 0
A9: PHL_PRO_PROC_BIOM | C9: =SUMIFS(Variable!C$2:C$9992,Variable!$B$2:$B$9992,$A9) -> 4868.8589 | D9: =SUMIFS(Variable!D$2:D$9992,Variable!$B$2:$B$9992,$A9) -> 399.9788 | E9: =SUMIFS(Variable!E$2:E$9992,Variable!$B$2:$B$9992,$A9) -> 344.0609 | F9: =SUMIFS(Variable!F$2:F$9992,Variable!$B$2:$B$9992,$A9) -> 387.3222 | G9: =SUMIFS(Variable!G$2:G$9992,Variable!$B$2:$B$9992,$A9) -> 364.6882 | H9: =SUMIFS(Variable!H$2:H$9992,Variable!$B$2:$B$9992,$A9) -> 47.7259 | I9: =SUMIFS(Variable!I$2:I$9992,Variable!$B$2:$B$9992,$A9) -> 48.1232 | J9: =SUMIFS(Variable!J$2:J$9992,Variable!$B$2:$B$9992,$A9) -> 29.5016 | ... AG9: =SUMIFS(Variable!AG$2:AG$9992,Variable!$B$2:$B$9992,$A9) -> 0
A10: PHL_POW_CHP_BIOM_OLD | C10: =SUMIFS(Variable!C$2:C$9992,Variable!$B$2:$B$9992,$A10) -> 0.0004 | D10: =SUMIFS(Variable!D$2:D$9992,Variable!$B$2:$B$9992,$A10) -> 0.0005 | E10: =SUMIFS(Variable!E$2:E$9992,Variable!$B$2:$B$9992,$A10) -> 0.0005 | F10: =SUMIFS(Variable!F$2:F$9992,Variable!$B$2:$B$9992,$A10) -> 0.0005 | G10: =SUMIFS(Variable!G$2:G$9992,Variable!$B$2:$B$9992,$A10) -> 0.0005 | H10: =SUMIFS(Variable!H$2:H$9992,Variable!$B$2:$B$9992,$A10) -> 0 | I10: =SUMIFS(Variable!I$2:I$9992,Variable!$B$2:$B$9992,$A10) -> 0 | J10: =SUMIFS(Variable!J$2:J$9992,Variable!$B$2:$B$9992,$A10) -> 0 | ... AG10: =SUMIFS(Variable!AG$2:AG$9992,Variable!$B$2:$B$9992,$A10) -> 0
A11: PHL_POW_CHP_COAL_OLD | C11: =SUMIFS(Variable!C$2:C$9992,Variable!$B$2:$B$9992,$A11) -> 0.0209 | D11: =SUMIFS(Variable!D$2:D$9992,Variable!$B$2:$B$9992,$A11) -> 0.0223 | E11: =SUMIFS(Variable!E$2:E$9992,Variable!$B$2:$B$9992,$A11) -> 0.0239 | F11: =SUMIFS(Variable!F$2:F$9992,Variable!$B$2:$B$9992,$A11) -> 0.0266 | G11: =SUMIFS(Variable!G$2:G$9992,Variable!$B$2:$B$9992,$A11) -> 0.0286 | H11: =SUMIFS(Variable!H$2:H$9992,Variable!$B$2:$B$9992,$A11) -> 0.0262 | I11: =SUMIFS(Variable!I$2:I$9992,Variable!$B$2:$B$9992,$A11) -> 0.025 | J11: =SUMIFS(Variable!J$2:J$9992,Variable!$B$2:$B$9992,$A11) -> 0.0232 | ... AG11: =SUMIFS(Variable!AG$2:AG$9992,Variable!$B$2:$B$9992,$A11) -> 0
A12: PHL_POW_GEO_OLD | C12: =SUMIFS(Variable!C$2:C$9992,Variable!$B$2:$B$9992,$A12) -> 0.0039 | D12: =SUMIFS(Variable!D$2:D$9992,Variable!$B$2:$B$9992,$A12) -> 0.0036 | E12: =SUMIFS(Variable!E$2:E$9992,Variable!$B$2:$B$9992,$A12) -> 0.0038 | F12: =SUMIFS(Variable!F$2:F$9992,Variable!$B$2:$B$9992,$A12) -> 0.0039 | G12: =SUMIFS(Variable!G$2:G$9992,Variable!$B$2:$B$9992,$A12) -> 0.0039 | H12: =SUMIFS(Variable!H$2:H$9992,Variable!$B$2:$B$9992,$A12) -> 0.004 | I12: =SUMIFS(Variable!I$2:I$9992,Variable!$B$2:$B$9992,$A12) -> 0.0067 | J12: =SUMIFS(Variable!J$2:J$9992,Variable!$B$2:$B$9992,$A12) -> 0.0067 | ... AG12: =SUMIFS(Variable!AG$2:AG$9992,Variable!$B$2:$B$9992,$A12) -> 0.0097
A13: PHL_POW_PP_BIOM_CCS | C13: =SUMIFS(Variable!C$2:C$9992,Variable!$B$2:$B$9992,$A13) -> 0 | D13: =SUMIFS(Variable!D$2:D$9992,Variable!$B$2:$B$9992,$A13) -> 0 | E13: =SUMIFS(Variable!E$2:E$9992,Variable!$B$2:$B$9992,$A13) -> 0 | F13: =SUMIFS(Variable!F$2:F$9992,Variable!$B$2:$B$9992,$A13) -> 0 | G13: =SUMIFS(Variable!G$2:G$9992,Variable!$B$2:$B$9992,$A13) -> 0 | H13: =SUMIFS(Variable!H$2:H$9992,Variable!$B$2:$B$9992,$A13) -> 0 | I13: =SUMIFS(Variable!I$2:I$9992,Variable!$B$2:$B$9992,$A13) -> 0 | J13: =SUMIFS(Variable!J$2:J$9992,Variable!$B$2:$B$9992,$A13) -> 0 | ... AG13: =SUMIFS(Variable!AG$2:AG$9992,Variable!$B$2:$B$9992,$A13) -> 0
A14: PHL_POW_PP_COAL | C14: =SUMIFS(Variable!C$2:C$9992,Variable!$B$2:$B$9992,$A14) -> 0 | D14: =SUMIFS(Variable!D$2:D$9992,Variable!$B$2:$B$9992,$A14) -> 0 | E14: =SUMIFS(Variable!E$2:E$9992,Variable!$B$2:$B$9992,$A14) -> 0 | F14: =SUMIFS(Variable!F$2:F$9992,Variable!$B$2:$B$9992,$A14) -> 0 | G14: =SUMIFS(Variable!G$2:G$9992,Variable!$B$2:$B$9992,$A14) -> 0 | H14: =SUMIFS(Variable!H$2:H$9992,Variable!$B$2:$B$9992,$A14) -> 0.0066 | I14: =SUMIFS(Variable!I$2:I$9992,Variable!$B$2:$B$9992,$A14) -> 0.0066 | J14: =SUMIFS(Variable!J$2:J$9992,Variable!$B$2:$B$9992,$A14) -> 0.0113 | ... AG14: =SUMIFS(Variable!AG$2:AG$9992,Variable!$B$2:$B$9992,$A14) -> 0.0223
A15: PHL_POW_PP_COAL_CCS | C15: =SUMIFS(Variable!C$2:C$9992,Variable!$B$2:$B$9992,$A15) -> 0 | D15: =SUMIFS(Variable!D$2:D$9992,Variable!$B$2:$B$9992,$A15) -> 0 | E15: =SUMIFS(Variable!E$2:E$9992,Variable!$B$2:$B$9992,$A15) -> 0 | F15: =SUMIFS(Variable!F$2:F$9992,Variable!$B$2:$B$9992,$A15) -> 0 | G15: =SUMIFS(Variable!G$2:G$9992,Variable!$B$2:$B$9992,$A15) -> 0 | H15: =SUMIFS(Variable!H$2:H$9992,Variable!$B$2:$B$9992,$A15) -> 0 | I15: =SUMIFS(Variable!I$2:I$9992,Variable!$B$2:$B$9992,$A15) -> 0 | J15: =SUMIFS(Variable!J$2:J$9992,Variable!$B$2:$B$9992,$A15) -> 0 | ... AG15: =SUMIFS(Variable!AG$2:AG$9992,Variable!$B$2:$B$9992,$A15) -> 0
A16: PHL_POW_PP_H2 | C16: =SUMIFS(Variable!C$2:C$9992,Variable!$B$2:$B$9992,$A16) -> 0 | D16: =SUMIFS(Variable!D$2:D$9992,Variable!$B$2:$B$9992,$A16) -> 0 | E16: =SUMIFS(Variable!E$2:E$9992,Variable!$B$2:$B$9992,$A16) -> 0 | F16: =SUMIFS(Variable!F$2:F$9992,Variable!$B$2:$B$9992,$A16) -> 0 | G16: =SUMIFS(Variable!G$2:G$9992,Variable!$B$2:$B$9992,$A16) -> 0 | H16: =SUMIFS(Variable!H$2:H$9992,Variable!$B$2:$B$9992,$A16) -> 0 | I16: =SUMIFS(Variable!I$2:I$9992,Variable!$B$2:$B$9992,$A16) -> 0 | J16: =SUMIFS(Variable!J$2:J$9992,Variable!$B$2:$B$9992,$A16) -> 0 | ... AG16: =SUMIFS(Variable!AG$2:AG$9992,Variable!$B$2:$B$9992,$A16) -> 0
A17: PHL_POW_PP_HY_LA | C17: =SUMIFS(Variable!C$2:C$9992,Variable!$B$2:$B$9992,$A17) -> 0.0026 | D17: =SUMIFS(Variable!D$2:D$9992,Variable!$B$2:$B$9992,$A17) -> 0.0033 | E17: =SUMIFS(Variable!E$2:E$9992,Variable!$B$2:$B$9992,$A17) -> 0.0036 | F17: =SUMIFS(Variable!F$2:F$9992,Variable!$B$2:$B$9992,$A17) -> 0.0037 | G17: =SUMIFS(Variable!G$2:G$9992,Variable!$B$2:$B$9992,$A17) -> 0.0039 | H17: =SUMIFS(Variable!H$2:H$9992,Variable!$B$2:$B$9992,$A17) -> 0.0039 | I17: =SUMIFS(Variable!I$2:I$9992,Variable!$B$2:$B$9992,$A17) -> 0.0039 | J17: =SUMIFS(Variable!J$2:J$9992,Variable!$B$2:$B$9992,$A17) -> 0.0039 | ... AG17: =SUMIFS(Variable!AG$2:AG$9992,Variable!$B$2:$B$9992,$A17) -> 0.0032
... A27: PHL_POW_TD | C27: =SUMIFS(Variable!C$2:C$9992,Variable!$B$2:$B$9992,$A27) -> 0.03 | D27: =SUMIFS(Variable!D$2:D$9992,Variable!$B$2:$B$9992,$A27) -> 0.03 | E27: =SUMIFS(Variable!E$2:E$9992,Variable!$B$2:$B$9992,$A27) -> 0.0315 | F27: =SUMIFS(Variable!F$2:F$9992,Variable!$B$2:$B$9992,$A27) -> 0.033 | G27: =SUMIFS(Variable!G$2:G$9992,Variable!$B$2:$B$9992,$A27) -> 0.0345 | H27: =SUMIFS(Variable!H$2:H$9992,Variable!$B$2:$B$9992,$A27) -> 0.0357 | I27: =SUMIFS(Variable!I$2:I$9992,Variable!$B$2:$B$9992,$A27) -> 0.0369 | J27: =SUMIFS(Variable!J$2:J$9992,Variable!$B$2:$B$9992,$A27) -> 0.039 | ... AG27: =SUMIFS(Variable!AG$2:AG$9992,Variable!$B$2:$B$9992,$A27) -> 0.1038
A29: Only grid-connected
A30: Coal | C30: =SUM(C225,C228:C229)*C120 -> 1994.5146 | D30: =SUM(D225,D228:D229)*D120 -> 2135.6259 | E30: =SUM(E225,E228:E229)*E120 -> 2295.2716 | F30: =SUM(F225,F228:F229)*F120 -> 2558.2788 | G30: =SUM(G225,G228:G229)*G120 -> 2763.4075 | H30: =SUM(H225,H228:H229)*H120 -> 3013.7481 | I30: =SUM(I225,I228:I229)*I120 -> 2905.3081 | J30: =SUM(J225,J228:J229)*J120 -> 3073.9003 | ... AG30: =SUM(AG225,AG228:AG229)*AG120 -> 1836.0367
A31: Natural gas | C31: =SUM(C232:C233)*C122 -> 0 | D31: =SUM(D232:D233)*D122 -> 0 | E31: =SUM(E232:E233)*E122 -> 0 | F31: =SUM(F232:F233)*F122 -> 0 | G31: =SUM(G232:G233)*G122 -> 0 | H31: =SUM(H232:H233)*H122 -> 93.032588 | I31: =SUM(I232:I233)*I122 -> 101.02545 | J31: =SUM(J232:J233)*J122 -> 68.000747 | ... AG31: =SUM(AG232:AG233)*AG122 -> 1440.4149
A32: Oil | C32: =C239*C121 -> 647.30077 | D32: =D239*D121 -> 430.62557 | E32: =E239*E121 -> 682.24145 | F32: =F239*F121 -> 358.8861 | G32: =G239*G121 -> 375.2526 | H32: =H239*H121 -> 0 | I32: =I239*I121 -> 0 | J32: =J239*J121 -> 0 | ... AG32: =AG239*AG121 -> 0
A33: Biomass | C33: =SUM(C224,C227)*C123 -> 288.048 | D33: =SUM(D224,D227)*D123 -> 332.9808 | E33: =SUM(E224,E227)*E123 -> 304.6272 | F33: =SUM(F224,F227)*F123 -> 324.6608 | G33: =SUM(G224,G227)*G123 -> 333.2384 | H33: =SUM(H224,H227)*H123 -> 0 | I33: =SUM(I224,I227)*I123 -> 0 | J33: =SUM(J224,J227)*J123 -> 0 | ... AG33: =SUM(AG224,AG227)*AG123 -> 0
A34: Uranium | C34: =C241*C124 -> 0 | D34: =D241*D124 -> 0 | E34: =E241*E124 -> 0 | F34: =F241*F124 -> 0 | G34: =G241*G124 -> 0 | H34: =H241*H124 -> 0 | I34: =I241*I124 -> 0 | J34: =J241*J124 -> 0 | ... AG34: =AG241*AG124 -> 1157.177
A35: TOTAL (Fixed & Variable) | C35: =SUM(C38:C55)+SUM(C30:C34)+SUM(C10:C27) -> 3983.2703 | D35: =SUM(D38:D55)+SUM(D30:D34)+SUM(D10:D27) -> 4094.6927 | E35: =SUM(E38:E55)+SUM(E30:E34)+SUM(E10:E27) -> 4526.0569 | F35: =SUM(F38:F55)+SUM(F30:F34)+SUM(F10:F27) -> 4486.033 | G35: =SUM(G38:G55)+SUM(G30:G34)+SUM(G10:G27) -> 4730.4557 | H35: =SUM(H38:H55)+SUM(H30:H34)+SUM(H10:H27) -> 4390.2596 | I35: =SUM(I38:I55)+SUM(I30:I34)+SUM(I10:I27) -> 4385.722 | J35: =SUM(J38:J55)+SUM(J30:J34)+SUM(J10:J27) -> 4587.073 | ... AG35: =SUM(AG38:AG55)+SUM(AG30:AG34)+SUM(AG10:AG27) -> 10875.82
A37: FIXED | C37: 2020 | D37: 2021 | E37: 2022 | F37: 2023 | G37: 2024 | H37: 2025 | I37: 2026 | J37: 2027 | K37: 2028 | L37: 2029 | M37: 2030 | N37: 2031 | O37: 2032 | P37: 2033 | Q37: 2034 | R37: 2035 | S37: 2036 | T37: 2037 | U37: 2038 | V37: 2039 | W37: 2040 | X37: 2041 | Y37: 2042 | Z37: 2043 | AA37: 2044 | AB37: 2045 | AC37: 2046 | AD37: 2047 | AE37: 2048 | AF37: 2049 | AG37: 2050
A38: PHL_POW_CHP_BIOM_OLD | C38: =SUMIFS(Fixed!C$2:C$10000,Fixed!$B$2:$B$10000,$A38) -> 44.748 | D38: =SUMIFS(Fixed!D$2:D$10000,Fixed!$B$2:$B$10000,$A38) -> 44.748 | E38: =SUMIFS(Fixed!E$2:E$10000,Fixed!$B$2:$B$10000,$A38) -> 52.128 | F38: =SUMIFS(Fixed!F$2:F$10000,Fixed!$B$2:$B$10000,$A38) -> 52.668 | G38: =SUMIFS(Fixed!G$2:G$10000,Fixed!$B$2:$B$10000,$A38) -> 53.559 | H38: =SUMIFS(Fixed!H$2:H$10000,Fixed!$B$2:$B$10000,$A38) -> 53.559 | I38: =SUMIFS(Fixed!I$2:I$10000,Fixed!$B$2:$B$10000,$A38) -> 53.559 | J38: =SUMIFS(Fixed!J$2:J$10000,Fixed!$B$2:$B$10000,$A38) -> 53.559 | ... AG38: =SUMIFS(Fixed!AG$2:AG$10000,Fixed!$B$2:$B$10000,$A38) -> 45.693
A39: PHL_POW_CHP_COAL_OLD | C39: =SUMIFS(Fixed!C$2:C$10000,Fixed!$B$2:$B$10000,$A39) -> 491.0355 | D39: =SUMIFS(Fixed!D$2:D$10000,Fixed!$B$2:$B$10000,$A39) -> 491.0355 | E39: =SUMIFS(Fixed!E$2:E$10000,Fixed!$B$2:$B$10000,$A39) -> 491.0355 | F39: =SUMIFS(Fixed!F$2:F$10000,Fixed!$B$2:$B$10000,$A39) -> 491.0355 | G39: =SUMIFS(Fixed!G$2:G$10000,Fixed!$B$2:$B$10000,$A39) -> 464.0355 | H39: =SUMIFS(Fixed!H$2:H$10000,Fixed!$B$2:$B$10000,$A39) -> 464.0355 | I39: =SUMIFS(Fixed!I$2:I$10000,Fixed!$B$2:$B$10000,$A39) -> 464.0355 | J39: =SUMIFS(Fixed!J$2:J$10000,Fixed!$B$2:$B$10000,$A39) -> 464.0355 | ... AG39: =SUMIFS(Fixed!AG$2:AG$10000,Fixed!$B$2:$B$10000,$A39) -> 286.461
A40: PHL_POW_GEO_OLD | C40: =SUMIFS(Fixed!C$2:C$10000,Fixed!$B$2:$B$10000,$A40) -> 144.394 | D40: =SUMIFS(Fixed!D$2:D$10000,Fixed!$B$2:$B$10000,$A40) -> 144.394 | E40: =SUMIFS(Fixed!E$2:E$10000,Fixed!$B$2:$B$10000,$A40) -> 144.8195 | F40: =SUMIFS(Fixed!F$2:F$10000,Fixed!$B$2:$B$10000,$A40) -> 140.8618 | G40: =SUMIFS(Fixed!G$2:G$10000,Fixed!$B$2:$B$10000,$A40) -> 141.6349 | H40: =SUMIFS(Fixed!H$2:H$10000,Fixed!$B$2:$B$10000,$A40) -> 145.7404 | I40: =SUMIFS(Fixed!I$2:I$10000,Fixed!$B$2:$B$10000,$A40) -> 243.0334 | J40: =SUMIFS(Fixed!J$2:J$10000,Fixed!$B$2:$B$10000,$A40) -> 243.0334 | ... AG40: =SUMIFS(Fixed!AG$2:AG$10000,Fixed!$B$2:$B$10000,$A40) -> 459.4748
A41: PHL_POW_PP_BIOM_CCS | C41: =SUMIFS(Fixed!C$2:C$10000,Fixed!$B$2:$B$10000,$A41) -> 0 | D41: =SUMIFS(Fixed!D$2:D$10000,Fixed!$B$2:$B$10000,$A41) -> 0 | E41: =SUMIFS(Fixed!E$2:E$10000,Fixed!$B$2:$B$10000,$A41) -> 0 | F41: =SUMIFS(Fixed!F$2:F$10000,Fixed!$B$2:$B$10000,$A41) -> 0 | G41: =SUMIFS(Fixed!G$2:G$10000,Fixed!$B$2:$B$10000,$A41) -> 0 | H41: =SUMIFS(Fixed!H$2:H$10000,Fixed!$B$2:$B$10000,$A41) -> 0 | I41: =SUMIFS(Fixed!I$2:I$10000,Fixed!$B$2:$B$10000,$A41) -> 0 | J41: =SUMIFS(Fixed!J$2:J$10000,Fixed!$B$2:$B$10000,$A41) -> 0 | ... AG41: =SUMIFS(Fixed!AG$2:AG$10000,Fixed!$B$2:$B$10000,$A41) -> 0
A42: PHL_POW_PP_COAL | C42: =SUMIFS(Fixed!C$2:C$10000,Fixed!$B$2:$B$10000,$A42) -> 0 | D42: =SUMIFS(Fixed!D$2:D$10000,Fixed!$B$2:$B$10000,$A42) -> 32.877 | E42: =SUMIFS(Fixed!E$2:E$10000,Fixed!$B$2:$B$10000,$A42) -> 67.7675 | F42: =SUMIFS(Fixed!F$2:F$10000,Fixed!$B$2:$B$10000,$A42) -> 67.7675 | G42: =SUMIFS(Fixed!G$2:G$10000,Fixed!$B$2:$B$10000,$A42) -> 94.9761 | H42: =SUMIFS(Fixed!H$2:H$10000,Fixed!$B$2:$B$10000,$A42) -> 94.9761 | I42: =SUMIFS(Fixed!I$2:I$10000,Fixed!$B$2:$B$10000,$A42) -> 94.9761 | J42: =SUMIFS(Fixed!J$2:J$10000,Fixed!$B$2:$B$10000,$A42) -> 162.0602 | ... AG42: =SUMIFS(Fixed!AG$2:AG$10000,Fixed!$B$2:$B$10000,$A42) -> 514.0482
A43: PHL_POW_PP_COAL_CCS | C43: =SUMIFS(Fixed!C$2:C$10000,Fixed!$B$2:$B$10000,$A43) -> 0 | D43: =SUMIFS(Fixed!D$2:D$10000,Fixed!$B$2:$B$10000,$A43) -> 0 | E43: =SUMIFS(Fixed!E$2:E$10000,Fixed!$B$2:$B$10000,$A43) -> 0 | F43: =SUMIFS(Fixed!F$2:F$10000,Fixed!$B$2:$B$10000,$A43) -> 0 | G43: =SUMIFS(Fixed!G$2:G$10000,Fixed!$B$2:$B$10000,$A43) -> 0 | H43: =SUMIFS(Fixed!H$2:H$10000,Fixed!$B$2:$B$10000,$A43) -> 0 | I43: =SUMIFS(Fixed!I$2:I$10000,Fixed!$B$2:$B$10000,$A43) -> 0 | J43: =SUMIFS(Fixed!J$2:J$10000,Fixed!$B$2:$B$10000,$A43) -> 0 | ... AG43: =SUMIFS(Fixed!AG$2:AG$10000,Fixed!$B$2:$B$10000,$A43) -> 0
A44: PHL_POW_PP_H2 | C44: =SUMIFS(Fixed!C$2:C$10000,Fixed!$B$2:$B$10000,$A44) -> 0 | D44: =SUMIFS(Fixed!D$2:D$10000,Fixed!$B$2:$B$10000,$A44) -> 0 | E44: =SUMIFS(Fixed!E$2:E$10000,Fixed!$B$2:$B$10000,$A44) -> 0 | F44: =SUMIFS(Fixed!F$2:F$10000,Fixed!$B$2:$B$10000,$A44) -> 0 | G44: =SUMIFS(Fixed!G$2:G$10000,Fixed!$B$2:$B$10000,$A44) -> 0 | H44: =SUMIFS(Fixed!H$2:H$10000,Fixed!$B$2:$B$10000,$A44) -> 0 | I44: =SUMIFS(Fixed!I$2:I$10000,Fixed!$B$2:$B$10000,$A44) -> 0 | J44: =SUMIFS(Fixed!J$2:J$10000,Fixed!$B$2:$B$10000,$A44) -> 0 | ... AG44: =SUMIFS(Fixed!AG$2:AG$10000,Fixed!$B$2:$B$10000,$A44) -> 0
A45: PHL_POW_PP_HY_LA | C45: =SUMIFS(Fixed!C$2:C$10000,Fixed!$B$2:$B$10000,$A45) -> 191.6825 | D45: =SUMIFS(Fixed!D$2:D$10000,Fixed!$B$2:$B$10000,$A45) -> 287.1673 | E45: =SUMIFS(Fixed!E$2:E$10000,Fixed!$B$2:$B$10000,$A45) -> 287.7616 | F45: =SUMIFS(Fixed!F$2:F$10000,Fixed!$B$2:$B$10000,$A45) -> 289.5109 | G45: =SUMIFS(Fixed!G$2:G$10000,Fixed!$B$2:$B$10000,$A45) -> 290.8266 | H45: =SUMIFS(Fixed!H$2:H$10000,Fixed!$B$2:$B$10000,$A45) -> 290.8266 | I45: =SUMIFS(Fixed!I$2:I$10000,Fixed!$B$2:$B$10000,$A45) -> 290.8266 | J45: =SUMIFS(Fixed!J$2:J$10000,Fixed!$B$2:$B$10000,$A45) -> 290.8266 | ... AG45: =SUMIFS(Fixed!AG$2:AG$10000,Fixed!$B$2:$B$10000,$A45) -> 289.9744
A46: PHL_POW_PP_NGCC | C46: =SUMIFS(Fixed!C$2:C$10000,Fixed!$B$2:$B$10000,$A46) -> 0 | D46: =SUMIFS(Fixed!D$2:D$10000,Fixed!$B$2:$B$10000,$A46) -> 0 | E46: =SUMIFS(Fixed!E$2:E$10000,Fixed!$B$2:$B$10000,$A46) -> 0 | F46: =SUMIFS(Fixed!F$2:F$10000,Fixed!$B$2:$B$10000,$A46) -> 0 | G46: =SUMIFS(Fixed!G$2:G$10000,Fixed!$B$2:$B$10000,$A46) -> 0 | H46: =SUMIFS(Fixed!H$2:H$10000,Fixed!$B$2:$B$10000,$A46) -> 19.0192 | I46: =SUMIFS(Fixed!I$2:I$10000,Fixed!$B$2:$B$10000,$A46) -> 19.0192 | J46: =SUMIFS(Fixed!J$2:J$10000,Fixed!$B$2:$B$10000,$A46) -> 19.0192 | ... AG46: =SUMIFS(Fixed!AG$2:AG$10000,Fixed!$B$2:$B$10000,$A46) -> 217.4155
A47: PHL_POW_PP_NGCC_CCS | C47: =SUMIFS(Fixed!C$2:C$10000,Fixed!$B$2:$B$10000,$A47) -> 0 | D47: =SUMIFS(Fixed!D$2:D$10000,Fixed!$B$2:$B$10000,$A47) -> 0 | E47: =SUMIFS(Fixed!E$2:E$10000,Fixed!$B$2:$B$10000,$A47) -> 0 | F47: =SUMIFS(Fixed!F$2:F$10000,Fixed!$B$2:$B$10000,$A47) -> 0 | G47: =SUMIFS(Fixed!G$2:G$10000,Fixed!$B$2:$B$10000,$A47) -> 0 | H47: =SUMIFS(Fixed!H$2:H$10000,Fixed!$B$2:$B$10000,$A47) -> 0 | I47: =SUMIFS(Fixed!I$2:I$10000,Fixed!$B$2:$B$10000,$A47) -> 0 | J47: =SUMIFS(Fixed!J$2:J$10000,Fixed!$B$2:$B$10000,$A47) -> 0 | ... AG47: =SUMIFS(Fixed!AG$2:AG$10000,Fixed!$B$2:$B$10000,$A47) -> 0
A48: PHL_POW_PP_NU | C48: =SUMIFS(Fixed!C$2:C$10000,Fixed!$B$2:$B$10000,$A48) -> 0 | D48: =SUMIFS(Fixed!D$2:D$10000,Fixed!$B$2:$B$10000,$A48) -> 0 | E48: =SUMIFS(Fixed!E$2:E$10000,Fixed!$B$2:$B$10000,$A48) -> 0 | F48: =SUMIFS(Fixed!F$2:F$10000,Fixed!$B$2:$B$10000,$A48) -> 0 | G48: =SUMIFS(Fixed!G$2:G$10000,Fixed!$B$2:$B$10000,$A48) -> 0 | H48: =SUMIFS(Fixed!H$2:H$10000,Fixed!$B$2:$B$10000,$A48) -> 0 | I48: =SUMIFS(Fixed!I$2:I$10000,Fixed!$B$2:$B$10000,$A48) -> 0 | J48: =SUMIFS(Fixed!J$2:J$10000,Fixed!$B$2:$B$10000,$A48) -> 0 | ... AG48: =SUMIFS(Fixed!AG$2:AG$10000,Fixed!$B$2:$B$10000,$A48) -> 0
A49: PHL_POW_PP_NUSMR | C49: =SUMIFS(Fixed!C$2:C$10000,Fixed!$B$2:$B$10000,$A49) -> 0 | D49: =SUMIFS(Fixed!D$2:D$10000,Fixed!$B$2:$B$10000,$A49) -> 0 | E49: =SUMIFS(Fixed!E$2:E$10000,Fixed!$B$2:$B$10000,$A49) -> 0 | F49: =SUMIFS(Fixed!F$2:F$10000,Fixed!$B$2:$B$10000,$A49) -> 0 | G49: =SUMIFS(Fixed!G$2:G$10000,Fixed!$B$2:$B$10000,$A49) -> 0 | H49: =SUMIFS(Fixed!H$2:H$10000,Fixed!$B$2:$B$10000,$A49) -> 0 | I49: =SUMIFS(Fixed!I$2:I$10000,Fixed!$B$2:$B$10000,$A49) -> 0 | J49: =SUMIFS(Fixed!J$2:J$10000,Fixed!$B$2:$B$10000,$A49) -> 0 | ... AG49: =SUMIFS(Fixed!AG$2:AG$10000,Fixed!$B$2:$B$10000,$A49) -> 4436.4241
... A55: PHL_POW_TD | C55: =SUMIFS(Fixed!C$2:C$10000,Fixed!$B$2:$B$10000,$A55) -> 0 | D55: =SUMIFS(Fixed!D$2:D$10000,Fixed!$B$2:$B$10000,$A55) -> 0 | E55: =SUMIFS(Fixed!E$2:E$10000,Fixed!$B$2:$B$10000,$A55) -> 0 | F55: =SUMIFS(Fixed!F$2:F$10000,Fixed!$B$2:$B$10000,$A55) -> 0 | G55: =SUMIFS(Fixed!G$2:G$10000,Fixed!$B$2:$B$10000,$A55) -> 0 | H55: =SUMIFS(Fixed!H$2:H$10000,Fixed!$B$2:$B$10000,$A55) -> 0 | I55: =SUMIFS(Fixed!I$2:I$10000,Fixed!$B$2:$B$10000,$A55) -> 0 | J55: =SUMIFS(Fixed!J$2:J$10000,Fixed!$B$2:$B$10000,$A55) -> 0 | ... AG55: =SUMIFS(Fixed!AG$2:AG$10000,Fixed!$B$2:$B$10000,$A55) -> 0
A58: Capital Investments (M.USD) | C58: 2020 | D58: 2021 | E58: 2022 | F58: 2023 | G58: 2024 | H58: 2025 | I58: 2026 | J58: 2027 | K58: 2028 | L58: 2029 | M58: 2030 | N58: 2031 | O58: 2032 | P58: 2033 | Q58: 2034 | R58: 2035 | S58: 2036 | T58: 2037 | U58: 2038 | V58: 2039 | W58: 2040 | X58: 2041 | Y58: 2042 | Z58: 2043 | AA58: 2044 | AB58: 2045 | AC58: 2046 | AD58: 2047 | AE58: 2048 | AF58: 2049 | AG58: 2050
A59: PHL_POW_CHP_BIOM_OLD | C59: =SUMIFS(Capital_Investments!C$2:C$10000,Capital_Investments!$B$2:$B$10000,$A59) -> 0 | D59: =SUMIFS(Capital_Investments!D$2:D$10000,Capital_Investments!$B$2:$B$10000,$A59) -> 0 | E59: =SUMIFS(Capital_Investments!E$2:E$10000,Capital_Investments!$B$2:$B$10000,$A59) -> 369 | F59: =SUMIFS(Capital_Investments!F$2:F$10000,Capital_Investments!$B$2:$B$10000,$A59) -> 27 | G59: =SUMIFS(Capital_Investments!G$2:G$10000,Capital_Investments!$B$2:$B$10000,$A59) -> 44.55 | H59: =SUMIFS(Capital_Investments!H$2:H$10000,Capital_Investments!$B$2:$B$10000,$A59) -> 0 | I59: =SUMIFS(Capital_Investments!I$2:I$10000,Capital_Investments!$B$2:$B$10000,$A59) -> 0 | J59: =SUMIFS(Capital_Investments!J$2:J$10000,Capital_Investments!$B$2:$B$10000,$A59) -> 0 | ... AG59: =SUMIFS(Capital_Investments!AG$2:AG$10000,Capital_Investments!$B$2:$B$10000,$A59) -> 0
A60: PHL_POW_CHP_COAL_OLD | C60: =SUMIFS(Capital_Investments!C$2:C$10000,Capital_Investments!$B$2:$B$10000,$A60) -> 0 | D60: =SUMIFS(Capital_Investments!D$2:D$10000,Capital_Investments!$B$2:$B$10000,$A60) -> 0 | E60: =SUMIFS(Capital_Investments!E$2:E$10000,Capital_Investments!$B$2:$B$10000,$A60) -> 0 | F60: =SUMIFS(Capital_Investments!F$2:F$10000,Capital_Investments!$B$2:$B$10000,$A60) -> 0 | G60: =SUMIFS(Capital_Investments!G$2:G$10000,Capital_Investments!$B$2:$B$10000,$A60) -> 0 | H60: =SUMIFS(Capital_Investments!H$2:H$10000,Capital_Investments!$B$2:$B$10000,$A60) -> 0 | I60: =SUMIFS(Capital_Investments!I$2:I$10000,Capital_Investments!$B$2:$B$10000,$A60) -> 0 | J60: =SUMIFS(Capital_Investments!J$2:J$10000,Capital_Investments!$B$2:$B$10000,$A60) -> 0 | ... AG60: =SUMIFS(Capital_Investments!AG$2:AG$10000,Capital_Investments!$B$2:$B$10000,$A60) -> 0
A61: PHL_POW_GEO_OLD | C61: =SUMIFS(Capital_Investments!C$2:C$10000,Capital_Investments!$B$2:$B$10000,$A61) -> 0 | D61: =SUMIFS(Capital_Investments!D$2:D$10000,Capital_Investments!$B$2:$B$10000,$A61) -> 0 | E61: =SUMIFS(Capital_Investments!E$2:E$10000,Capital_Investments!$B$2:$B$10000,$A61) -> 16.28 | F61: =SUMIFS(Capital_Investments!F$2:F$10000,Capital_Investments!$B$2:$B$10000,$A61) -> 1236.7766 | G61: =SUMIFS(Capital_Investments!G$2:G$10000,Capital_Investments!$B$2:$B$10000,$A61) -> 29.5789 | H61: =SUMIFS(Capital_Investments!H$2:H$10000,Capital_Investments!$B$2:$B$10000,$A61) -> 157.08 | I61: =SUMIFS(Capital_Investments!I$2:I$10000,Capital_Investments!$B$2:$B$10000,$A61) -> 3722.5143 | J61: =SUMIFS(Capital_Investments!J$2:J$10000,Capital_Investments!$B$2:$B$10000,$A61) -> 0 | ... AG61: =SUMIFS(Capital_Investments!AG$2:AG$10000,Capital_Investments!$B$2:$B$10000,$A61) -> 0
A62: PHL_POW_PP_BIOM_CCS | C62: =SUMIFS(Capital_Investments!C$2:C$10000,Capital_Investments!$B$2:$B$10000,$A62) -> 0 | D62: =SUMIFS(Capital_Investments!D$2:D$10000,Capital_Investments!$B$2:$B$10000,$A62) -> 0 | E62: =SUMIFS(Capital_Investments!E$2:E$10000,Capital_Investments!$B$2:$B$10000,$A62) -> 0 | F62: =SUMIFS(Capital_Investments!F$2:F$10000,Capital_Investments!$B$2:$B$10000,$A62) -> 0 | G62: =SUMIFS(Capital_Investments!G$2:G$10000,Capital_Investments!$B$2:$B$10000,$A62) -> 0 | H62: =SUMIFS(Capital_Investments!H$2:H$10000,Capital_Investments!$B$2:$B$10000,$A62) -> 0 | I62: =SUMIFS(Capital_Investments!I$2:I$10000,Capital_Investments!$B$2:$B$10000,$A62) -> 0 | J62: =SUMIFS(Capital_Investments!J$2:J$10000,Capital_Investments!$B$2:$B$10000,$A62) -> 0 | ... AG62: =SUMIFS(Capital_Investments!AG$2:AG$10000,Capital_Investments!$B$2:$B$10000,$A62) -> 0
A63: PHL_POW_PP_COAL | C63: =SUMIFS(Capital_Investments!C$2:C$10000,Capital_Investments!$B$2:$B$10000,$A63) -> 0 | D63: =SUMIFS(Capital_Investments!D$2:D$10000,Capital_Investments!$B$2:$B$10000,$A63) -> 1595 | E63: =SUMIFS(Capital_Investments!E$2:E$10000,Capital_Investments!$B$2:$B$10000,$A63) -> 1692.68 | F63: =SUMIFS(Capital_Investments!F$2:F$10000,Capital_Investments!$B$2:$B$10000,$A63) -> 0 | G63: =SUMIFS(Capital_Investments!G$2:G$10000,Capital_Investments!$B$2:$B$10000,$A63) -> 1320 | H63: =SUMIFS(Capital_Investments!H$2:H$10000,Capital_Investments!$B$2:$B$10000,$A63) -> 0 | I63: =SUMIFS(Capital_Investments!I$2:I$10000,Capital_Investments!$B$2:$B$10000,$A63) -> 0 | J63: =SUMIFS(Capital_Investments!J$2:J$10000,Capital_Investments!$B$2:$B$10000,$A63) -> 3254.5245 | ... AG63: =SUMIFS(Capital_Investments!AG$2:AG$10000,Capital_Investments!$B$2:$B$10000,$A63) -> 0
A64: PHL_POW_PP_COAL_CCS | C64: =SUMIFS(Capital_Investments!C$2:C$10000,Capital_Investments!$B$2:$B$10000,$A64) -> 0 | D64: =SUMIFS(Capital_Investments!D$2:D$10000,Capital_Investments!$B$2:$B$10000,$A64) -> 0 | E64: =SUMIFS(Capital_Investments!E$2:E$10000,Capital_Investments!$B$2:$B$10000,$A64) -> 0 | F64: =SUMIFS(Capital_Investments!F$2:F$10000,Capital_Investments!$B$2:$B$10000,$A64) -> 0 | G64: =SUMIFS(Capital_Investments!G$2:G$10000,Capital_Investments!$B$2:$B$10000,$A64) -> 0 | H64: =SUMIFS(Capital_Investments!H$2:H$10000,Capital_Investments!$B$2:$B$10000,$A64) -> 0 | I64: =SUMIFS(Capital_Investments!I$2:I$10000,Capital_Investments!$B$2:$B$10000,$A64) -> 0 | J64: =SUMIFS(Capital_Investments!J$2:J$10000,Capital_Investments!$B$2:$B$10000,$A64) -> 0 | ... AG64: =SUMIFS(Capital_Investments!AG$2:AG$10000,Capital_Investments!$B$2:$B$10000,$A64) -> 0
A65: PHL_POW_PP_H2 | C65: =SUMIFS(Capital_Investments!C$2:C$10000,Capital_Investments!$B$2:$B$10000,$A65) -> 0 | D65: =SUMIFS(Capital_Investments!D$2:D$10000,Capital_Investments!$B$2:$B$10000,$A65) -> 0 | E65: =SUMIFS(Capital_Investments!E$2:E$10000,Capital_Investments!$B$2:$B$10000,$A65) -> 0 | F65: =SUMIFS(Capital_Investments!F$2:F$10000,Capital_Investments!$B$2:$B$10000,$A65) -> 0 | G65: =SUMIFS(Capital_Investments!G$2:G$10000,Capital_Investments!$B$2:$B$10000,$A65) -> 0 | H65: =SUMIFS(Capital_Investments!H$2:H$10000,Capital_Investments!$B$2:$B$10000,$A65) -> 0 | I65: =SUMIFS(Capital_Investments!I$2:I$10000,Capital_Investments!$B$2:$B$10000,$A65) -> 0 | J65: =SUMIFS(Capital_Investments!J$2:J$10000,Capital_Investments!$B$2:$B$10000,$A65) -> 0 | ... AG65: =SUMIFS(Capital_Investments!AG$2:AG$10000,Capital_Investments!$B$2:$B$10000,$A65) -> 0
A66: PHL_POW_PP_HY_LA | C66: =SUMIFS(Capital_Investments!C$2:C$10000,Capital_Investments!$B$2:$B$10000,$A66) -> 4389.9544 | D66: =SUMIFS(Capital_Investments!D$2:D$10000,Capital_Investments!$B$2:$B$10000,$A66) -> 7663.7159 | E66: =SUMIFS(Capital_Investments!E$2:E$10000,Capital_Investments!$B$2:$B$10000,$A66) -> 47.7 | F66: =SUMIFS(Capital_Investments!F$2:F$10000,Capital_Investments!$B$2:$B$10000,$A66) -> 140.4 | G66: =SUMIFS(Capital_Investments!G$2:G$10000,Capital_Investments!$B$2:$B$10000,$A66) -> 105.6 | H66: =SUMIFS(Capital_Investments!H$2:H$10000,Capital_Investments!$B$2:$B$10000,$A66) -> 0 | I66: =SUMIFS(Capital_Investments!I$2:I$10000,Capital_Investments!$B$2:$B$10000,$A66) -> 0 | J66: =SUMIFS(Capital_Investments!J$2:J$10000,Capital_Investments!$B$2:$B$10000,$A66) -> 0 | ... AG66: =SUMIFS(Capital_Investments!AG$2:AG$10000,Capital_Investments!$B$2:$B$10000,$A66) -> 0
A67: PHL_POW_PP_NGCC | C67: =SUMIFS(Capital_Investments!C$2:C$10000,Capital_Investments!$B$2:$B$10000,$A67) -> 0 | D67: =SUMIFS(Capital_Investments!D$2:D$10000,Capital_Investments!$B$2:$B$10000,$A67) -> 0 | E67: =SUMIFS(Capital_Investments!E$2:E$10000,Capital_Investments!$B$2:$B$10000,$A67) -> 0 | F67: =SUMIFS(Capital_Investments!F$2:F$10000,Capital_Investments!$B$2:$B$10000,$A67) -> 0 | G67: =SUMIFS(Capital_Investments!G$2:G$10000,Capital_Investments!$B$2:$B$10000,$A67) -> 0 | H67: =SUMIFS(Capital_Investments!H$2:H$10000,Capital_Investments!$B$2:$B$10000,$A67) -> 1056 | I67: =SUMIFS(Capital_Investments!I$2:I$10000,Capital_Investments!$B$2:$B$10000,$A67) -> 0 | J67: =SUMIFS(Capital_Investments!J$2:J$10000,Capital_Investments!$B$2:$B$10000,$A67) -> 0 | ... AG67: =SUMIFS(Capital_Investments!AG$2:AG$10000,Capital_Investments!$B$2:$B$10000,$A67) -> 2024.2701
A68: PHL_POW_PP_NGCC_CCS | C68: =SUMIFS(Capital_Investments!C$2:C$10000,Capital_Investments!$B$2:$B$10000,$A68) -> 0 | D68: =SUMIFS(Capital_Investments!D$2:D$10000,Capital_Investments!$B$2:$B$10000,$A68) -> 0 | E68: =SUMIFS(Capital_Investments!E$2:E$10000,Capital_Investments!$B$2:$B$10000,$A68) -> 0 | F68: =SUMIFS(Capital_Investments!F$2:F$10000,Capital_Investments!$B$2:$B$10000,$A68) -> 0 | G68: =SUMIFS(Capital_Investments!G$2:G$10000,Capital_Investments!$B$2:$B$10000,$A68) -> 0 | H68: =SUMIFS(Capital_Investments!H$2:H$10000,Capital_Investments!$B$2:$B$10000,$A68) -> 0 | I68: =SUMIFS(Capital_Investments!I$2:I$10000,Capital_Investments!$B$2:$B$10000,$A68) -> 0 | J68: =SUMIFS(Capital_Investments!J$2:J$10000,Capital_Investments!$B$2:$B$10000,$A68) -> 0 | ... AG68: =SUMIFS(Capital_Investments!AG$2:AG$10000,Capital_Investments!$B$2:$B$10000,$A68) -> 0
A69: PHL_POW_PP_NU | C69: =SUMIFS(Capital_Investments!C$2:C$10000,Capital_Investments!$B$2:$B$10000,$A69) -> 0 | D69: =SUMIFS(Capital_Investments!D$2:D$10000,Capital_Investments!$B$2:$B$10000,$A69) -> 0 | E69: =SUMIFS(Capital_Investments!E$2:E$10000,Capital_Investments!$B$2:$B$10000,$A69) -> 0 | F69: =SUMIFS(Capital_Investments!F$2:F$10000,Capital_Investments!$B$2:$B$10000,$A69) -> 0 | G69: =SUMIFS(Capital_Investments!G$2:G$10000,Capital_Investments!$B$2:$B$10000,$A69) -> 0 | H69: =SUMIFS(Capital_Investments!H$2:H$10000,Capital_Investments!$B$2:$B$10000,$A69) -> 0 | I69: =SUMIFS(Capital_Investments!I$2:I$10000,Capital_Investments!$B$2:$B$10000,$A69) -> 0 | J69: =SUMIFS(Capital_Investments!J$2:J$10000,Capital_Investments!$B$2:$B$10000,$A69) -> 0 | ... AG69: =SUMIFS(Capital_Investments!AG$2:AG$10000,Capital_Investments!$B$2:$B$10000,$A69) -> 0
A70: PHL_POW_PP_NUSMR | C70: =SUMIFS(Capital_Investments!C$2:C$10000,Capital_Investments!$B$2:$B$10000,$A70) -> 0 | D70: =SUMIFS(Capital_Investments!D$2:D$10000,Capital_Investments!$B$2:$B$10000,$A70) -> 0 | E70: =SUMIFS(Capital_Investments!E$2:E$10000,Capital_Investments!$B$2:$B$10000,$A70) -> 0 | F70: =SUMIFS(Capital_Investments!F$2:F$10000,Capital_Investments!$B$2:$B$10000,$A70) -> 0 | G70: =SUMIFS(Capital_Investments!G$2:G$10000,Capital_Investments!$B$2:$B$10000,$A70) -> 0 | H70: =SUMIFS(Capital_Investments!H$2:H$10000,Capital_Investments!$B$2:$B$10000,$A70) -> 0 | I70: =SUMIFS(Capital_Investments!I$2:I$10000,Capital_Investments!$B$2:$B$10000,$A70) -> 0 | J70: =SUMIFS(Capital_Investments!J$2:J$10000,Capital_Investments!$B$2:$B$10000,$A70) -> 0 | ... AG70: =SUMIFS(Capital_Investments!AG$2:AG$10000,Capital_Investments!$B$2:$B$10000,$A70) -> 5132.753
... A76: PHL_POW_TD | C76: =SUMIFS(Capital_Investments!C$2:C$10000,Capital_Investments!$B$2:$B$10000,$A76) -> 0 | D76: =SUMIFS(Capital_Investments!D$2:D$10000,Capital_Investments!$B$2:$B$10000,$A76) -> 0 | E76: =SUMIFS(Capital_Investments!E$2:E$10000,Capital_Investments!$B$2:$B$10000,$A76) -> 0 | F76: =SUMIFS(Capital_Investments!F$2:F$10000,Capital_Investments!$B$2:$B$10000,$A76) -> 0 | G76: =SUMIFS(Capital_Investments!G$2:G$10000,Capital_Investments!$B$2:$B$10000,$A76) -> 0 | H76: =SUMIFS(Capital_Investments!H$2:H$10000,Capital_Investments!$B$2:$B$10000,$A76) -> 459.6972 | I76: =SUMIFS(Capital_Investments!I$2:I$10000,Capital_Investments!$B$2:$B$10000,$A76) -> 1316.7722 | J76: =SUMIFS(Capital_Investments!J$2:J$10000,Capital_Investments!$B$2:$B$10000,$A76) -> 1316.7722 | ... AG76: =SUMIFS(Capital_Investments!AG$2:AG$10000,Capital_Investments!$B$2:$B$10000,$A76) -> 3107.0751
A79: Annualized Investment Cost (M.USD) | C79: 2020 | D79: 2021 | E79: 2022 | F79: 2023 | G79: 2024 | H79: 2025 | I79: 2026 | J79: 2027 | K79: 2028 | L79: 2029 | M79: 2030 | N79: 2031 | O79: 2032 | P79: 2033 | Q79: 2034 | R79: 2035 | S79: 2036 | T79: 2037 | U79: 2038 | V79: 2039 | W79: 2040 | X79: 2041 | Y79: 2042 | Z79: 2043 | AA79: 2044 | AB79: 2045 | AC79: 2046 | AD79: 2047 | AE79: 2048 | AF79: 2049 | AG79: 2050
A80: PHL_POW_CHP_BIOM_OLD | C80: =SUMIFS(Annualized_Investments!C$2:C$9991,Annualized_Investments!$B$2:$B$9991,$A80) -> 0 | D80: =SUMIFS(Annualized_Investments!D$2:D$9991,Annualized_Investments!$B$2:$B$9991,$A80) -> 0 | E80: =SUMIFS(Annualized_Investments!E$2:E$9991,Annualized_Investments!$B$2:$B$9991,$A80) -> 20.480611 | F80: =SUMIFS(Annualized_Investments!F$2:F$9991,Annualized_Investments!$B$2:$B$9991,$A80) -> 21.979192 | G80: =SUMIFS(Annualized_Investments!G$2:G$9991,Annualized_Investments!$B$2:$B$9991,$A80) -> 24.451851 | H80: =SUMIFS(Annualized_Investments!H$2:H$9991,Annualized_Investments!$B$2:$B$9991,$A80) -> 24.451851 | I80: =SUMIFS(Annualized_Investments!I$2:I$9991,Annualized_Investments!$B$2:$B$9991,$A80) -> 24.451851 | J80: =SUMIFS(Annualized_Investments!J$2:J$9991,Annualized_Investments!$B$2:$B$9991,$A80) -> 24.451851 | ... AG80: =SUMIFS(Annualized_Investments!AG$2:AG$9991,Annualized_Investments!$B$2:$B$9991,$A80) -> 24.451851
A81: PHL_POW_CHP_COAL_OLD | C81: =SUMIFS(Annualized_Investments!C$2:C$9991,Annualized_Investments!$B$2:$B$9991,$A81) -> 0 | D81: =SUMIFS(Annualized_Investments!D$2:D$9991,Annualized_Investments!$B$2:$B$9991,$A81) -> 0 | E81: =SUMIFS(Annualized_Investments!E$2:E$9991,Annualized_Investments!$B$2:$B$9991,$A81) -> 0 | F81: =SUMIFS(Annualized_Investments!F$2:F$9991,Annualized_Investments!$B$2:$B$9991,$A81) -> 0 | G81: =SUMIFS(Annualized_Investments!G$2:G$9991,Annualized_Investments!$B$2:$B$9991,$A81) -> 0 | H81: =SUMIFS(Annualized_Investments!H$2:H$9991,Annualized_Investments!$B$2:$B$9991,$A81) -> 0 | I81: =SUMIFS(Annualized_Investments!I$2:I$9991,Annualized_Investments!$B$2:$B$9991,$A81) -> 0 | J81: =SUMIFS(Annualized_Investments!J$2:J$9991,Annualized_Investments!$B$2:$B$9991,$A81) -> 0 | ... AG81: =SUMIFS(Annualized_Investments!AG$2:AG$9991,Annualized_Investments!$B$2:$B$9991,$A81) -> 0
A82: PHL_POW_GEO_OLD | C82: =SUMIFS(Annualized_Investments!C$2:C$9991,Annualized_Investments!$B$2:$B$9991,$A82) -> 0 | D82: =SUMIFS(Annualized_Investments!D$2:D$9991,Annualized_Investments!$B$2:$B$9991,$A82) -> 0 | E82: =SUMIFS(Annualized_Investments!E$2:E$9991,Annualized_Investments!$B$2:$B$9991,$A82) -> 0.90358901 | F82: =SUMIFS(Annualized_Investments!F$2:F$9991,Annualized_Investments!$B$2:$B$9991,$A82) -> 69.548414 | G82: =SUMIFS(Annualized_Investments!G$2:G$9991,Annualized_Investments!$B$2:$B$9991,$A82) -> 71.190132 | H82: =SUMIFS(Annualized_Investments!H$2:H$9991,Annualized_Investments!$B$2:$B$9991,$A82) -> 79.908545 | I82: =SUMIFS(Annualized_Investments!I$2:I$9991,Annualized_Investments!$B$2:$B$9991,$A82) -> 286.5193 | J82: =SUMIFS(Annualized_Investments!J$2:J$9991,Annualized_Investments!$B$2:$B$9991,$A82) -> 286.5193 | ... AG82: =SUMIFS(Annualized_Investments!AG$2:AG$9991,Annualized_Investments!$B$2:$B$9991,$A82) -> 955.8587
A83: PHL_POW_PP_BIOM_CCS | C83: =SUMIFS(Annualized_Investments!C$2:C$9991,Annualized_Investments!$B$2:$B$9991,$A83) -> 0 | D83: =SUMIFS(Annualized_Investments!D$2:D$9991,Annualized_Investments!$B$2:$B$9991,$A83) -> 0 | E83: =SUMIFS(Annualized_Investments!E$2:E$9991,Annualized_Investments!$B$2:$B$9991,$A83) -> 0 | F83: =SUMIFS(Annualized_Investments!F$2:F$9991,Annualized_Investments!$B$2:$B$9991,$A83) -> 0 | G83: =SUMIFS(Annualized_Investments!G$2:G$9991,Annualized_Investments!$B$2:$B$9991,$A83) -> 0 | H83: =SUMIFS(Annualized_Investments!H$2:H$9991,Annualized_Investments!$B$2:$B$9991,$A83) -> 0 | I83: =SUMIFS(Annualized_Investments!I$2:I$9991,Annualized_Investments!$B$2:$B$9991,$A83) -> 0 | J83: =SUMIFS(Annualized_Investments!J$2:J$9991,Annualized_Investments!$B$2:$B$9991,$A83) -> 0 | ... AG83: =SUMIFS(Annualized_Investments!AG$2:AG$9991,Annualized_Investments!$B$2:$B$9991,$A83) -> 0
A84: PHL_POW_PP_COAL | C84: =SUMIFS(Annualized_Investments!C$2:C$9991,Annualized_Investments!$B$2:$B$9991,$A84) -> 0 | D84: =SUMIFS(Annualized_Investments!D$2:D$9991,Annualized_Investments!$B$2:$B$9991,$A84) -> 107.78016 | E84: =SUMIFS(Annualized_Investments!E$2:E$9991,Annualized_Investments!$B$2:$B$9991,$A84) -> 222.16093 | F84: =SUMIFS(Annualized_Investments!F$2:F$9991,Annualized_Investments!$B$2:$B$9991,$A84) -> 222.16093 | G84: =SUMIFS(Annualized_Investments!G$2:G$9991,Annualized_Investments!$B$2:$B$9991,$A84) -> 311.3583 | H84: =SUMIFS(Annualized_Investments!H$2:H$9991,Annualized_Investments!$B$2:$B$9991,$A84) -> 311.3583 | I84: =SUMIFS(Annualized_Investments!I$2:I$9991,Annualized_Investments!$B$2:$B$9991,$A84) -> 311.3583 | J84: =SUMIFS(Annualized_Investments!J$2:J$9991,Annualized_Investments!$B$2:$B$9991,$A84) -> 531.27879 | ... AG84: =SUMIFS(Annualized_Investments!AG$2:AG$9991,Annualized_Investments!$B$2:$B$9991,$A84) -> 1685.1947
A85: PHL_POW_PP_COAL_CCS | C85: =SUMIFS(Annualized_Investments!C$2:C$9991,Annualized_Investments!$B$2:$B$9991,$A85) -> 0 | D85: =SUMIFS(Annualized_Investments!D$2:D$9991,Annualized_Investments!$B$2:$B$9991,$A85) -> 0 | E85: =SUMIFS(Annualized_Investments!E$2:E$9991,Annualized_Investments!$B$2:$B$9991,$A85) -> 0 | F85: =SUMIFS(Annualized_Investments!F$2:F$9991,Annualized_Investments!$B$2:$B$9991,$A85) -> 0 | G85: =SUMIFS(Annualized_Investments!G$2:G$9991,Annualized_Investments!$B$2:$B$9991,$A85) -> 0 | H85: =SUMIFS(Annualized_Investments!H$2:H$9991,Annualized_Investments!$B$2:$B$9991,$A85) -> 0 | I85: =SUMIFS(Annualized_Investments!I$2:I$9991,Annualized_Investments!$B$2:$B$9991,$A85) -> 0 | J85: =SUMIFS(Annualized_Investments!J$2:J$9991,Annualized_Investments!$B$2:$B$9991,$A85) -> 0 | ... AG85: =SUMIFS(Annualized_Investments!AG$2:AG$9991,Annualized_Investments!$B$2:$B$9991,$A85) -> 0
A86: PHL_POW_PP_H2 | C86: =SUMIFS(Annualized_Investments!C$2:C$9991,Annualized_Investments!$B$2:$B$9991,$A86) -> 0 | D86: =SUMIFS(Annualized_Investments!D$2:D$9991,Annualized_Investments!$B$2:$B$9991,$A86) -> 0 | E86: =SUMIFS(Annualized_Investments!E$2:E$9991,Annualized_Investments!$B$2:$B$9991,$A86) -> 0 | F86: =SUMIFS(Annualized_Investments!F$2:F$9991,Annualized_Investments!$B$2:$B$9991,$A86) -> 0 | G86: =SUMIFS(Annualized_Investments!G$2:G$9991,Annualized_Investments!$B$2:$B$9991,$A86) -> 0 | H86: =SUMIFS(Annualized_Investments!H$2:H$9991,Annualized_Investments!$B$2:$B$9991,$A86) -> 0 | I86: =SUMIFS(Annualized_Investments!I$2:I$9991,Annualized_Investments!$B$2:$B$9991,$A86) -> 0 | J86: =SUMIFS(Annualized_Investments!J$2:J$9991,Annualized_Investments!$B$2:$B$9991,$A86) -> 0 | ... AG86: =SUMIFS(Annualized_Investments!AG$2:AG$9991,Annualized_Investments!$B$2:$B$9991,$A86) -> 0
A87: PHL_POW_PP_HY_LA | C87: =SUMIFS(Annualized_Investments!C$2:C$9991,Annualized_Investments!$B$2:$B$9991,$A87) -> 210.64731 | D87: =SUMIFS(Annualized_Investments!D$2:D$9991,Annualized_Investments!$B$2:$B$9991,$A87) -> 578.3826 | E87: =SUMIFS(Annualized_Investments!E$2:E$9991,Annualized_Investments!$B$2:$B$9991,$A87) -> 580.67144 | F87: =SUMIFS(Annualized_Investments!F$2:F$9991,Annualized_Investments!$B$2:$B$9991,$A87) -> 587.40838 | G87: =SUMIFS(Annualized_Investments!G$2:G$9991,Annualized_Investments!$B$2:$B$9991,$A87) -> 592.47549 | H87: =SUMIFS(Annualized_Investments!H$2:H$9991,Annualized_Investments!$B$2:$B$9991,$A87) -> 592.47549 | I87: =SUMIFS(Annualized_Investments!I$2:I$9991,Annualized_Investments!$B$2:$B$9991,$A87) -> 592.47549 | J87: =SUMIFS(Annualized_Investments!J$2:J$9991,Annualized_Investments!$B$2:$B$9991,$A87) -> 592.47549 | ... AG87: =SUMIFS(Annualized_Investments!AG$2:AG$9991,Annualized_Investments!$B$2:$B$9991,$A87) -> 592.47549
A88: PHL_POW_PP_NGCC | C88: =SUMIFS(Annualized_Investments!C$2:C$9991,Annualized_Investments!$B$2:$B$9991,$A88) -> 0 | D88: =SUMIFS(Annualized_Investments!D$2:D$9991,Annualized_Investments!$B$2:$B$9991,$A88) -> 0 | E88: =SUMIFS(Annualized_Investments!E$2:E$9991,Annualized_Investments!$B$2:$B$9991,$A88) -> 0 | F88: =SUMIFS(Annualized_Investments!F$2:F$9991,Annualized_Investments!$B$2:$B$9991,$A88) -> 0 | G88: =SUMIFS(Annualized_Investments!G$2:G$9991,Annualized_Investments!$B$2:$B$9991,$A88) -> 0 | H88: =SUMIFS(Annualized_Investments!H$2:H$9991,Annualized_Investments!$B$2:$B$9991,$A88) -> 71.3579 | I88: =SUMIFS(Annualized_Investments!I$2:I$9991,Annualized_Investments!$B$2:$B$9991,$A88) -> 71.3579 | J88: =SUMIFS(Annualized_Investments!J$2:J$9991,Annualized_Investments!$B$2:$B$9991,$A88) -> 71.3579 | ... AG88: =SUMIFS(Annualized_Investments!AG$2:AG$9991,Annualized_Investments!$B$2:$B$9991,$A88) -> 815.71985
A89: PHL_POW_PP_NGCC_CCS | C89: =SUMIFS(Annualized_Investments!C$2:C$9991,Annualized_Investments!$B$2:$B$9991,$A89) -> 0 | D89: =SUMIFS(Annualized_Investments!D$2:D$9991,Annualized_Investments!$B$2:$B$9991,$A89) -> 0 | E89: =SUMIFS(Annualized_Investments!E$2:E$9991,Annualized_Investments!$B$2:$B$9991,$A89) -> 0 | F89: =SUMIFS(Annualized_Investments!F$2:F$9991,Annualized_Investments!$B$2:$B$9991,$A89) -> 0 | G89: =SUMIFS(Annualized_Investments!G$2:G$9991,Annualized_Investments!$B$2:$B$9991,$A89) -> 0 | H89: =SUMIFS(Annualized_Investments!H$2:H$9991,Annualized_Investments!$B$2:$B$9991,$A89) -> 0 | I89: =SUMIFS(Annualized_Investments!I$2:I$9991,Annualized_Investments!$B$2:$B$9991,$A89) -> 0 | J89: =SUMIFS(Annualized_Investments!J$2:J$9991,Annualized_Investments!$B$2:$B$9991,$A89) -> 0 | ... AG89: =SUMIFS(Annualized_Investments!AG$2:AG$9991,Annualized_Investments!$B$2:$B$9991,$A89) -> 0
A90: PHL_POW_PP_NU | C90: =SUMIFS(Annualized_Investments!C$2:C$9991,Annualized_Investments!$B$2:$B$9991,$A90) -> 0 | D90: =SUMIFS(Annualized_Investments!D$2:D$9991,Annualized_Investments!$B$2:$B$9991,$A90) -> 0 | E90: =SUMIFS(Annualized_Investments!E$2:E$9991,Annualized_Investments!$B$2:$B$9991,$A90) -> 0 | F90: =SUMIFS(Annualized_Investments!F$2:F$9991,Annualized_Investments!$B$2:$B$9991,$A90) -> 0 | G90: =SUMIFS(Annualized_Investments!G$2:G$9991,Annualized_Investments!$B$2:$B$9991,$A90) -> 0 | H90: =SUMIFS(Annualized_Investments!H$2:H$9991,Annualized_Investments!$B$2:$B$9991,$A90) -> 0 | I90: =SUMIFS(Annualized_Investments!I$2:I$9991,Annualized_Investments!$B$2:$B$9991,$A90) -> 0 | J90: =SUMIFS(Annualized_Investments!J$2:J$9991,Annualized_Investments!$B$2:$B$9991,$A90) -> 0 | ... AG90: =SUMIFS(Annualized_Investments!AG$2:AG$9991,Annualized_Investments!$B$2:$B$9991,$A90) -> 0
A91: PHL_POW_PP_NUSMR | C91: =SUMIFS(Annualized_Investments!C$2:C$9991,Annualized_Investments!$B$2:$B$9991,$A91) -> 0 | D91: =SUMIFS(Annualized_Investments!D$2:D$9991,Annualized_Investments!$B$2:$B$9991,$A91) -> 0 | E91: =SUMIFS(Annualized_Investments!E$2:E$9991,Annualized_Investments!$B$2:$B$9991,$A91) -> 0 | F91: =SUMIFS(Annualized_Investments!F$2:F$9991,Annualized_Investments!$B$2:$B$9991,$A91) -> 0 | G91: =SUMIFS(Annualized_Investments!G$2:G$9991,Annualized_Investments!$B$2:$B$9991,$A91) -> 0 | H91: =SUMIFS(Annualized_Investments!H$2:H$9991,Annualized_Investments!$B$2:$B$9991,$A91) -> 0 | I91: =SUMIFS(Annualized_Investments!I$2:I$9991,Annualized_Investments!$B$2:$B$9991,$A91) -> 0 | J91: =SUMIFS(Annualized_Investments!J$2:J$9991,Annualized_Investments!$B$2:$B$9991,$A91) -> 0 | ... AG91: =SUMIFS(Annualized_Investments!AG$2:AG$9991,Annualized_Investments!$B$2:$B$9991,$A91) -> 4259.8242
... A97: PHL_POW_TD | C97: =SUMIFS(Annualized_Investments!C$2:C$9991,Annualized_Investments!$B$2:$B$9991,$A97) -> 0 | D97: =SUMIFS(Annualized_Investments!D$2:D$9991,Annualized_Investments!$B$2:$B$9991,$A97) -> 0 | E97: =SUMIFS(Annualized_Investments!E$2:E$9991,Annualized_Investments!$B$2:$B$9991,$A97) -> 0 | F97: =SUMIFS(Annualized_Investments!F$2:F$9991,Annualized_Investments!$B$2:$B$9991,$A97) -> 0 | G97: =SUMIFS(Annualized_Investments!G$2:G$9991,Annualized_Investments!$B$2:$B$9991,$A97) -> 0 | H97: =SUMIFS(Annualized_Investments!H$2:H$9991,Annualized_Investments!$B$2:$B$9991,$A97) -> 23.98163 | I97: =SUMIFS(Annualized_Investments!I$2:I$9991,Annualized_Investments!$B$2:$B$9991,$A97) -> 92.675423 | J97: =SUMIFS(Annualized_Investments!J$2:J$9991,Annualized_Investments!$B$2:$B$9991,$A97) -> 161.36922 | ... AG97: =SUMIFS(Annualized_Investments!AG$2:AG$9991,Annualized_Investments!$B$2:$B$9991,$A97) -> 2425.5664
A100: Annual Production by Technology (PJ) | C100: 2020 | D100: 2021 | E100: 2022 | F100: 2023 | G100: 2024 | H100: 2025 | I100: 2026 | J100: 2027 | K100: 2028 | L100: 2029 | M100: 2030 | N100: 2031 | O100: 2032 | P100: 2033 | Q100: 2034 | R100: 2035 | S100: 2036 | T100: 2037 | U100: 2038 | V100: 2039 | W100: 2040 | X100: 2041 | Y100: 2042 | Z100: 2043 | AA100: 2044 | AB100: 2045 | AC100: 2046 | AD100: 2047 | AE100: 2048 | AF100: 2049 | AG100: 2050
A101: PHL_POW_CHP_BIOM_OLD | C101: =SUMIFS(AnnualProduction!D$2:D$9924,AnnualProduction!$B$2:$B$9924,$A101) -> 4.5001 | D101: =SUMIFS(AnnualProduction!E$2:E$9924,AnnualProduction!$B$2:$B$9924,$A101) -> 5.2021 | E101: =SUMIFS(AnnualProduction!F$2:F$9924,AnnualProduction!$B$2:$B$9924,$A101) -> 4.7591 | F101: =SUMIFS(AnnualProduction!G$2:G$9924,AnnualProduction!$B$2:$B$9924,$A101) -> 5.0719 | G101: =SUMIFS(AnnualProduction!H$2:H$9924,AnnualProduction!$B$2:$B$9924,$A101) -> 5.2059 | H101: =SUMIFS(AnnualProduction!I$2:I$9924,AnnualProduction!$B$2:$B$9924,$A101) -> 0 | I101: =SUMIFS(AnnualProduction!J$2:J$9924,AnnualProduction!$B$2:$B$9924,$A101) -> 0 | J101: =SUMIFS(AnnualProduction!K$2:K$9924,AnnualProduction!$B$2:$B$9924,$A101) -> 0 | ... AG101: =SUMIFS(AnnualProduction!AH$2:AH$9924,AnnualProduction!$B$2:$B$9924,$A101) -> 0
A102: PHL_POW_CHP_COAL_OLD | C102: =SUMIFS(AnnualProduction!D$2:D$9924,AnnualProduction!$B$2:$B$9924,$A102) -> 209.448 | D102: =SUMIFS(AnnualProduction!E$2:E$9924,AnnualProduction!$B$2:$B$9924,$A102) -> 223.3868 | E102: =SUMIFS(AnnualProduction!F$2:F$9924,AnnualProduction!$B$2:$B$9924,$A102) -> 239.1476 | F102: =SUMIFS(AnnualProduction!G$2:G$9924,AnnualProduction!$B$2:$B$9924,$A102) -> 265.5136 | G102: =SUMIFS(AnnualProduction!H$2:H$9924,AnnualProduction!$B$2:$B$9924,$A102) -> 285.6922 | H102: =SUMIFS(AnnualProduction!I$2:I$9924,AnnualProduction!$B$2:$B$9924,$A102) -> 262.3083 | I102: =SUMIFS(AnnualProduction!J$2:J$9924,AnnualProduction!$B$2:$B$9924,$A102) -> 249.9901 | J102: =SUMIFS(AnnualProduction!K$2:K$9924,AnnualProduction!$B$2:$B$9924,$A102) -> 232.1301 | ... AG102: =SUMIFS(AnnualProduction!AH$2:AH$9924,AnnualProduction!$B$2:$B$9924,$A102) -> 0
A103: PHL_POW_GEO_OLD | C103: =SUMIFS(AnnualProduction!D$2:D$9924,AnnualProduction!$B$2:$B$9924,$A103) -> 38.8084 | D103: =SUMIFS(AnnualProduction!E$2:E$9924,AnnualProduction!$B$2:$B$9924,$A103) -> 36.0582 | E103: =SUMIFS(AnnualProduction!F$2:F$9924,AnnualProduction!$B$2:$B$9924,$A103) -> 37.5303 | F103: =SUMIFS(AnnualProduction!G$2:G$9924,AnnualProduction!$B$2:$B$9924,$A103) -> 38.628 | G103: =SUMIFS(AnnualProduction!H$2:H$9924,AnnualProduction!$B$2:$B$9924,$A103) -> 38.8398 | H103: =SUMIFS(AnnualProduction!I$2:I$9924,AnnualProduction!$B$2:$B$9924,$A103) -> 39.9666 | I103: =SUMIFS(AnnualProduction!J$2:J$9924,AnnualProduction!$B$2:$B$9924,$A103) -> 66.645 | J103: =SUMIFS(AnnualProduction!K$2:K$9924,AnnualProduction!$B$2:$B$9924,$A103) -> 66.645 | ... AG103: =SUMIFS(AnnualProduction!AH$2:AH$9924,AnnualProduction!$B$2:$B$9924,$A103) -> 97.048
A104: PHL_POW_PP_BIOM_CCS | C104: =SUMIFS(AnnualProduction!D$2:D$9924,AnnualProduction!$B$2:$B$9924,$A104) -> 0 | D104: =SUMIFS(AnnualProduction!E$2:E$9924,AnnualProduction!$B$2:$B$9924,$A104) -> 0 | E104: =SUMIFS(AnnualProduction!F$2:F$9924,AnnualProduction!$B$2:$B$9924,$A104) -> 0 | F104: =SUMIFS(AnnualProduction!G$2:G$9924,AnnualProduction!$B$2:$B$9924,$A104) -> 0 | G104: =SUMIFS(AnnualProduction!H$2:H$9924,AnnualProduction!$B$2:$B$9924,$A104) -> 0 | H104: =SUMIFS(AnnualProduction!I$2:I$9924,AnnualProduction!$B$2:$B$9924,$A104) -> 0 | I104: =SUMIFS(AnnualProduction!J$2:J$9924,AnnualProduction!$B$2:$B$9924,$A104) -> 0 | J104: =SUMIFS(AnnualProduction!K$2:K$9924,AnnualProduction!$B$2:$B$9924,$A104) -> 0 | ... AG104: =SUMIFS(AnnualProduction!AH$2:AH$9924,AnnualProduction!$B$2:$B$9924,$A104) -> 0
A105: PHL_POW_PP_COAL | C105: =SUMIFS(AnnualProduction!D$2:D$9924,AnnualProduction!$B$2:$B$9924,$A105) -> 0 | D105: =SUMIFS(AnnualProduction!E$2:E$9924,AnnualProduction!$B$2:$B$9924,$A105) -> 0 | E105: =SUMIFS(AnnualProduction!F$2:F$9924,AnnualProduction!$B$2:$B$9924,$A105) -> 0 | F105: =SUMIFS(AnnualProduction!G$2:G$9924,AnnualProduction!$B$2:$B$9924,$A105) -> 0 | G105: =SUMIFS(AnnualProduction!H$2:H$9924,AnnualProduction!$B$2:$B$9924,$A105) -> 0 | H105: =SUMIFS(AnnualProduction!I$2:I$9924,AnnualProduction!$B$2:$B$9924,$A105) -> 66.0492 | I105: =SUMIFS(AnnualProduction!J$2:J$9924,AnnualProduction!$B$2:$B$9924,$A105) -> 66.0492 | J105: =SUMIFS(AnnualProduction!K$2:K$9924,AnnualProduction!$B$2:$B$9924,$A105) -> 112.7004 | ... AG105: =SUMIFS(AnnualProduction!AH$2:AH$9924,AnnualProduction!$B$2:$B$9924,$A105) -> 222.8498
A106: PHL_POW_PP_COAL_CCS | C106: =SUMIFS(AnnualProduction!D$2:D$9924,AnnualProduction!$B$2:$B$9924,$A106) -> 0 | D106: =SUMIFS(AnnualProduction!E$2:E$9924,AnnualProduction!$B$2:$B$9924,$A106) -> 0 | E106: =SUMIFS(AnnualProduction!F$2:F$9924,AnnualProduction!$B$2:$B$9924,$A106) -> 0 | F106: =SUMIFS(AnnualProduction!G$2:G$9924,AnnualProduction!$B$2:$B$9924,$A106) -> 0 | G106: =SUMIFS(AnnualProduction!H$2:H$9924,AnnualProduction!$B$2:$B$9924,$A106) -> 0 | H106: =SUMIFS(AnnualProduction!I$2:I$9924,AnnualProduction!$B$2:$B$9924,$A106) -> 0 | I106: =SUMIFS(AnnualProduction!J$2:J$9924,AnnualProduction!$B$2:$B$9924,$A106) -> 0 | J106: =SUMIFS(AnnualProduction!K$2:K$9924,AnnualProduction!$B$2:$B$9924,$A106) -> 0 | ... AG106: =SUMIFS(AnnualProduction!AH$2:AH$9924,AnnualProduction!$B$2:$B$9924,$A106) -> 0
A107: PHL_POW_PP_H2 | C107: =SUMIFS(AnnualProduction!D$2:D$9924,AnnualProduction!$B$2:$B$9924,$A107) -> 0 | D107: =SUMIFS(AnnualProduction!E$2:E$9924,AnnualProduction!$B$2:$B$9924,$A107) -> 0 | E107: =SUMIFS(AnnualProduction!F$2:F$9924,AnnualProduction!$B$2:$B$9924,$A107) -> 0 | F107: =SUMIFS(AnnualProduction!G$2:G$9924,AnnualProduction!$B$2:$B$9924,$A107) -> 0 | G107: =SUMIFS(AnnualProduction!H$2:H$9924,AnnualProduction!$B$2:$B$9924,$A107) -> 0 | H107: =SUMIFS(AnnualProduction!I$2:I$9924,AnnualProduction!$B$2:$B$9924,$A107) -> 0 | I107: =SUMIFS(AnnualProduction!J$2:J$9924,AnnualProduction!$B$2:$B$9924,$A107) -> 0 | J107: =SUMIFS(AnnualProduction!K$2:K$9924,AnnualProduction!$B$2:$B$9924,$A107) -> 0 | ... AG107: =SUMIFS(AnnualProduction!AH$2:AH$9924,AnnualProduction!$B$2:$B$9924,$A107) -> 0
A108: PHL_POW_PP_HY_LA | C108: =SUMIFS(AnnualProduction!D$2:D$9924,AnnualProduction!$B$2:$B$9924,$A108) -> 25.8852 | D108: =SUMIFS(AnnualProduction!E$2:E$9924,AnnualProduction!$B$2:$B$9924,$A108) -> 33.0659 | E108: =SUMIFS(AnnualProduction!F$2:F$9924,AnnualProduction!$B$2:$B$9924,$A108) -> 36.3061 | F108: =SUMIFS(AnnualProduction!G$2:G$9924,AnnualProduction!$B$2:$B$9924,$A108) -> 37.0338 | G108: =SUMIFS(AnnualProduction!H$2:H$9924,AnnualProduction!$B$2:$B$9924,$A108) -> 39.2718 | H108: =SUMIFS(AnnualProduction!I$2:I$9924,AnnualProduction!$B$2:$B$9924,$A108) -> 39.2718 | I108: =SUMIFS(AnnualProduction!J$2:J$9924,AnnualProduction!$B$2:$B$9924,$A108) -> 39.2718 | J108: =SUMIFS(AnnualProduction!K$2:K$9924,AnnualProduction!$B$2:$B$9924,$A108) -> 39.2718 | ... AG108: =SUMIFS(AnnualProduction!AH$2:AH$9924,AnnualProduction!$B$2:$B$9924,$A108) -> 31.6074
A109: PHL_POW_PP_NGCC | C109: =SUMIFS(AnnualProduction!D$2:D$9924,AnnualProduction!$B$2:$B$9924,$A109) -> 0 | D109: =SUMIFS(AnnualProduction!E$2:E$9924,AnnualProduction!$B$2:$B$9924,$A109) -> 0 | E109: =SUMIFS(AnnualProduction!F$2:F$9924,AnnualProduction!$B$2:$B$9924,$A109) -> 0 | F109: =SUMIFS(AnnualProduction!G$2:G$9924,AnnualProduction!$B$2:$B$9924,$A109) -> 0 | G109: =SUMIFS(AnnualProduction!H$2:H$9924,AnnualProduction!$B$2:$B$9924,$A109) -> 0 | H109: =SUMIFS(AnnualProduction!I$2:I$9924,AnnualProduction!$B$2:$B$9924,$A109) -> 5.5228 | I109: =SUMIFS(AnnualProduction!J$2:J$9924,AnnualProduction!$B$2:$B$9924,$A109) -> 5.975 | J109: =SUMIFS(AnnualProduction!K$2:K$9924,AnnualProduction!$B$2:$B$9924,$A109) -> 4.0064 | ... AG109: =SUMIFS(AnnualProduction!AH$2:AH$9924,AnnualProduction!$B$2:$B$9924,$A109) -> 80.9455
A110: PHL_POW_PP_NGCC_CCS | C110: =SUMIFS(AnnualProduction!D$2:D$9924,AnnualProduction!$B$2:$B$9924,$A110) -> 0 | D110: =SUMIFS(AnnualProduction!E$2:E$9924,AnnualProduction!$B$2:$B$9924,$A110) -> 0 | E110: =SUMIFS(AnnualProduction!F$2:F$9924,AnnualProduction!$B$2:$B$9924,$A110) -> 0 | F110: =SUMIFS(AnnualProduction!G$2:G$9924,AnnualProduction!$B$2:$B$9924,$A110) -> 0 | G110: =SUMIFS(AnnualProduction!H$2:H$9924,AnnualProduction!$B$2:$B$9924,$A110) -> 0 | H110: =SUMIFS(AnnualProduction!I$2:I$9924,AnnualProduction!$B$2:$B$9924,$A110) -> 0 | I110: =SUMIFS(AnnualProduction!J$2:J$9924,AnnualProduction!$B$2:$B$9924,$A110) -> 0 | J110: =SUMIFS(AnnualProduction!K$2:K$9924,AnnualProduction!$B$2:$B$9924,$A110) -> 0 | ... AG110: =SUMIFS(AnnualProduction!AH$2:AH$9924,AnnualProduction!$B$2:$B$9924,$A110) -> 0
A111: PHL_POW_PP_NU | C111: =SUMIFS(AnnualProduction!D$2:D$9924,AnnualProduction!$B$2:$B$9924,$A111) -> 0 | D111: =SUMIFS(AnnualProduction!E$2:E$9924,AnnualProduction!$B$2:$B$9924,$A111) -> 0 | E111: =SUMIFS(AnnualProduction!F$2:F$9924,AnnualProduction!$B$2:$B$9924,$A111) -> 0 | F111: =SUMIFS(AnnualProduction!G$2:G$9924,AnnualProduction!$B$2:$B$9924,$A111) -> 0 | G111: =SUMIFS(AnnualProduction!H$2:H$9924,AnnualProduction!$B$2:$B$9924,$A111) -> 0 | H111: =SUMIFS(AnnualProduction!I$2:I$9924,AnnualProduction!$B$2:$B$9924,$A111) -> 0 | I111: =SUMIFS(AnnualProduction!J$2:J$9924,AnnualProduction!$B$2:$B$9924,$A111) -> 0 | J111: =SUMIFS(AnnualProduction!K$2:K$9924,AnnualProduction!$B$2:$B$9924,$A111) -> 0 | ... AG111: =SUMIFS(AnnualProduction!AH$2:AH$9924,AnnualProduction!$B$2:$B$9924,$A111) -> 0
A112: PHL_POW_PP_NUSMR | C112: =SUMIFS(AnnualProduction!D$2:D$9924,AnnualProduction!$B$2:$B$9924,$A112) -> 0 | D112: =SUMIFS(AnnualProduction!E$2:E$9924,AnnualProduction!$B$2:$B$9924,$A112) -> 0 | E112: =SUMIFS(AnnualProduction!F$2:F$9924,AnnualProduction!$B$2:$B$9924,$A112) -> 0 | F112: =SUMIFS(AnnualProduction!G$2:G$9924,AnnualProduction!$B$2:$B$9924,$A112) -> 0 | G112: =SUMIFS(AnnualProduction!H$2:H$9924,AnnualProduction!$B$2:$B$9924,$A112) -> 0 | H112: =SUMIFS(AnnualProduction!I$2:I$9924,AnnualProduction!$B$2:$B$9924,$A112) -> 0 | I112: =SUMIFS(AnnualProduction!J$2:J$9924,AnnualProduction!$B$2:$B$9924,$A112) -> 0 | J112: =SUMIFS(AnnualProduction!K$2:K$9924,AnnualProduction!$B$2:$B$9924,$A112) -> 0 | ... AG112: =SUMIFS(AnnualProduction!AH$2:AH$9924,AnnualProduction!$B$2:$B$9924,$A112) -> 670.3158
... A117: PHL_POW_CHP_NG_OLD | C117: =SUMIFS(AnnualProduction!D$2:D$9924,AnnualProduction!$B$2:$B$9924,$A117) -> 70.1998 | D117: =SUMIFS(AnnualProduction!E$2:E$9924,AnnualProduction!$B$2:$B$9924,$A117) -> 68.6159 | E117: =SUMIFS(AnnualProduction!F$2:F$9924,AnnualProduction!$B$2:$B$9924,$A117) -> 64.382 | F117: =SUMIFS(AnnualProduction!G$2:G$9924,AnnualProduction!$B$2:$B$9924,$A117) -> 60.0049 | G117: =SUMIFS(AnnualProduction!H$2:H$9924,AnnualProduction!$B$2:$B$9924,$A117) -> 64.9691 | H117: =SUMIFS(AnnualProduction!I$2:I$9924,AnnualProduction!$B$2:$B$9924,$A117) -> 1.1576 | I117: =SUMIFS(AnnualProduction!J$2:J$9924,AnnualProduction!$B$2:$B$9924,$A117) -> 1.62 | J117: =SUMIFS(AnnualProduction!K$2:K$9924,AnnualProduction!$B$2:$B$9924,$A117) -> 0 | ... AG117: =SUMIFS(AnnualProduction!AH$2:AH$9924,AnnualProduction!$B$2:$B$9924,$A117) -> 0
A118: RE% | C118: =SUM(C101,C103,C104,C107:C108,C113:C115)/SUM(C101:C117) -> 0.21249748 | D118: =SUM(D101,D103,D104,D107:D108,D113:D115)/SUM(D101:D117) -> 0.22038793 | E118: =SUM(E101,E103,E104,E107:E108,E113:E115)/SUM(E101:E117) -> 0.22134877 | F118: =SUM(F101,F103,F104,F107:F108,F113:F115)/SUM(F101:F117) -> 0.222688 | G118: =SUM(G101,G103,G104,G107:G108,G113:G115)/SUM(G101:G117) -> 0.22210048 | H118: =SUM(H101,H103,H104,H107:H108,H113:H115)/SUM(H101:H117) -> 0.23171194 | I118: =SUM(I101,I103,I104,I107:I108,I113:I115)/SUM(I101:I117) -> 0.28297728 | J118: =SUM(J101,J103,J104,J107:J108,J113:J115)/SUM(J101:J117) -> 0.26801222 | ... AG118: =SUM(AG101,AG103,AG104,AG107:AG108,AG113:AG115)/SUM(AG101:AG117) -> 0.23248583
A119: Variable Cost of imported fuels
A120: Price of coal as commodity | B120: MUSD/PJ | C120: 3.0333429 | D120: 3.0452852 | E120: 3.0572275 | F120: 3.0691698 | G120: 3.0811121 | H120: 3.0930544 | I120: 3.1049967 | J120: 3.116939 | K120: 3.1288812 | L120: 3.1408235 | M120: 3.1527658 | N120: 3.1909812 | O120: 3.2291965 | P120: 3.2674119 | Q120: 3.3056272 | R120: 3.3438426 | S120: 3.3820579 | T120: 3.4202732 | U120: 3.4584886 | V120: 3.4967039 | W120: 3.5349193 | X120: 3.5420846 | Y120: 3.54925 | Z120: 3.5564154 | AA120: 3.5635808 | AB120: 3.5707462 | AC120: 3.5779115 | AD120: 3.5850769 | AE120: 3.5922423 | AF120: 3.5994077 | AG120: 3.606573
A121: Price of oil as commodity | B121: MUSD/PJ | C121: 13.950989 | D121: 14.184819 | E121: 14.418649 | F121: 14.652479 | G121: 14.886309 | H121: 15.120139 | I121: 15.35397 | J121: 15.5878 | K121: 15.82163 | L121: 16.05546 | M121: 16.28929 | N121: 16.643976 | O121: 16.998662 | P121: 17.353349 | Q121: 17.708035 | R121: 18.062721 | S121: 18.417407 | T121: 18.772093 | U121: 19.126779 | V121: 19.481466 | W121: 19.836152 | X121: 19.985908 | Y121: 20.135664 | Z121: 20.285421 | AA121: 20.435177 | AB121: 20.584934 | AC121: 20.73469 | AD121: 20.884446 | AE121: 21.034203 | AF121: 21.183959 | AG121: 21.333715
A122: Price of natural gas as commodity | B122: MUSD/PJ | C122: 9.9837585 | D122: 10.021974 | E122: 10.060189 | F122: 10.098405 | G122: 10.13662 | H122: 10.174835 | I122: 10.213051 | J122: 10.251266 | K122: 10.289481 | L122: 10.327697 | M122: 10.365912 | N122: 10.401739 | O122: 10.437566 | P122: 10.473393 | Q122: 10.509219 | R122: 10.545046 | S122: 10.580873 | T122: 10.6167 | U122: 10.652527 | V122: 10.688354 | W122: 10.724181 | X122: 10.726569 | Y122: 10.728958 | Z122: 10.731346 | AA122: 10.733735 | AB122: 10.736123 | AC122: 10.738512 | AD122: 10.7409 | AE122: 10.743288 | AF122: 10.745677 | AG122: 10.748065
A123: Price of biomass as commodity | B123: MUSD/PJ | C123: 16 | D123: 16 | E123: 16 | F123: 16 | G123: 16 | H123: 16 | I123: 16 | J123: 16 | K123: 16 | L123: 16 | M123: 16 | N123: 16 | O123: 16 | P123: 16 | Q123: 16 | R123: 16 | S123: 16 | T123: 16 | U123: 16 | V123: 16 | W123: 16 | X123: 16 | Y123: 16 | Z123: 16 | AA123: 16 | AB123: 16 | AC123: 16 | AD123: 16 | AE123: 16 | AF123: 16 | AG123: 16
A124: Price of urankium as a commodity | B124: MUSD/PJ | C124: 0.481 | D124: 0.481 | E124: 0.481 | F124: 0.481 | G124: 0.481 | H124: 0.481 | I124: 0.5004 | J124: 0.5198 | K124: 0.5392 | L124: 0.5586 | M124: 0.578 | N124: 0.5733 | O124: 0.5686 | P124: 0.5639 | Q124: 0.5592 | R124: 0.5545 | S124: 0.5498 | T124: 0.5451 | U124: 0.5404 | V124: 0.5357 | W124: 0.531 | X124: 0.5435 | Y124: 0.556 | Z124: 0.5685 | AA124: 0.581 | AB124: 0.5935 | AC124: 0.606 | AD124: 0.6185 | AE124: 0.631 | AF124: 0.6435 | AG124: 0.656 | AH124: 0.656 | AI124: 0.656 | AJ124: 0.656
A128: New Capacity (GW) | C128: 2020 | D128: 2021 | E128: 2022 | F128: 2023 | G128: 2024 | H128: 2025 | I128: 2026 | J128: 2027 | K128: 2028 | L128: 2029 | M128: 2030 | N128: 2031 | O128: 2032 | P128: 2033 | Q128: 2034 | R128: 2035 | S128: 2036 | T128: 2037 | U128: 2038 | V128: 2039 | W128: 2040 | X128: 2041 | Y128: 2042 | Z128: 2043 | AA128: 2044 | AB128: 2045 | AC128: 2046 | AD128: 2047 | AE128: 2048 | AF128: 2049 | AG128: 2050
A129: PHL_POW_CHP_BIOM_OLD | C129: =SUMIFS('New Capacity'!C$2:C$10000,'New Capacity'!$B$2:$B$10000,$A129) -> 0 | D129: =SUMIFS('New Capacity'!D$2:D$10000,'New Capacity'!$B$2:$B$10000,$A129) -> 0 | E129: =SUMIFS('New Capacity'!E$2:E$10000,'New Capacity'!$B$2:$B$10000,$A129) -> 0.082 | F129: =SUMIFS('New Capacity'!F$2:F$10000,'New Capacity'!$B$2:$B$10000,$A129) -> 0.006 | G129: =SUMIFS('New Capacity'!G$2:G$10000,'New Capacity'!$B$2:$B$10000,$A129) -> 0.0099 | H129: =SUMIFS('New Capacity'!H$2:H$10000,'New Capacity'!$B$2:$B$10000,$A129) -> 0 | I129: =SUMIFS('New Capacity'!I$2:I$10000,'New Capacity'!$B$2:$B$10000,$A129) -> 0 | J129: =SUMIFS('New Capacity'!J$2:J$10000,'New Capacity'!$B$2:$B$10000,$A129) -> 0 | ... AG129: =SUMIFS('New Capacity'!AG$2:AG$10000,'New Capacity'!$B$2:$B$10000,$A129) -> 0
A130: PHL_POW_CHP_COAL_OLD | C130: =SUMIFS('New Capacity'!C$2:C$10000,'New Capacity'!$B$2:$B$10000,$A130) -> 0 | D130: =SUMIFS('New Capacity'!D$2:D$10000,'New Capacity'!$B$2:$B$10000,$A130) -> 0 | E130: =SUMIFS('New Capacity'!E$2:E$10000,'New Capacity'!$B$2:$B$10000,$A130) -> 0 | F130: =SUMIFS('New Capacity'!F$2:F$10000,'New Capacity'!$B$2:$B$10000,$A130) -> 0 | G130: =SUMIFS('New Capacity'!G$2:G$10000,'New Capacity'!$B$2:$B$10000,$A130) -> 0 | H130: =SUMIFS('New Capacity'!H$2:H$10000,'New Capacity'!$B$2:$B$10000,$A130) -> 0 | I130: =SUMIFS('New Capacity'!I$2:I$10000,'New Capacity'!$B$2:$B$10000,$A130) -> 0 | J130: =SUMIFS('New Capacity'!J$2:J$10000,'New Capacity'!$B$2:$B$10000,$A130) -> 0 | ... AG130: =SUMIFS('New Capacity'!AG$2:AG$10000,'New Capacity'!$B$2:$B$10000,$A130) -> 0
A131: PHL_POW_GEO_OLD | C131: =SUMIFS('New Capacity'!C$2:C$10000,'New Capacity'!$B$2:$B$10000,$A131) -> 0 | D131: =SUMIFS('New Capacity'!D$2:D$10000,'New Capacity'!$B$2:$B$10000,$A131) -> 0 | E131: =SUMIFS('New Capacity'!E$2:E$10000,'New Capacity'!$B$2:$B$10000,$A131) -> 0.0037 | F131: =SUMIFS('New Capacity'!F$2:F$10000,'New Capacity'!$B$2:$B$10000,$A131) -> 0.2811 | G131: =SUMIFS('New Capacity'!G$2:G$10000,'New Capacity'!$B$2:$B$10000,$A131) -> 0.0067 | H131: =SUMIFS('New Capacity'!H$2:H$10000,'New Capacity'!$B$2:$B$10000,$A131) -> 0.0357 | I131: =SUMIFS('New Capacity'!I$2:I$10000,'New Capacity'!$B$2:$B$10000,$A131) -> 1.0224 | J131: =SUMIFS('New Capacity'!J$2:J$10000,'New Capacity'!$B$2:$B$10000,$A131) -> 1.3029 | ... AG131: =SUMIFS('New Capacity'!AG$2:AG$10000,'New Capacity'!$B$2:$B$10000,$A131) -> 0.0046
A132: PHL_POW_PP_BIOM_CCS | C132: =SUMIFS('New Capacity'!C$2:C$10000,'New Capacity'!$B$2:$B$10000,$A132) -> 0 | D132: =SUMIFS('New Capacity'!D$2:D$10000,'New Capacity'!$B$2:$B$10000,$A132) -> 0 | E132: =SUMIFS('New Capacity'!E$2:E$10000,'New Capacity'!$B$2:$B$10000,$A132) -> 0 | F132: =SUMIFS('New Capacity'!F$2:F$10000,'New Capacity'!$B$2:$B$10000,$A132) -> 0 | G132: =SUMIFS('New Capacity'!G$2:G$10000,'New Capacity'!$B$2:$B$10000,$A132) -> 0 | H132: =SUMIFS('New Capacity'!H$2:H$10000,'New Capacity'!$B$2:$B$10000,$A132) -> 0 | I132: =SUMIFS('New Capacity'!I$2:I$10000,'New Capacity'!$B$2:$B$10000,$A132) -> 0 | J132: =SUMIFS('New Capacity'!J$2:J$10000,'New Capacity'!$B$2:$B$10000,$A132) -> 0 | ... AG132: =SUMIFS('New Capacity'!AG$2:AG$10000,'New Capacity'!$B$2:$B$10000,$A132) -> 0
A133: PHL_POW_PP_COAL | C133: =SUMIFS('New Capacity'!C$2:C$10000,'New Capacity'!$B$2:$B$10000,$A133) -> 0 | D133: =SUMIFS('New Capacity'!D$2:D$10000,'New Capacity'!$B$2:$B$10000,$A133) -> 0.725 | E133: =SUMIFS('New Capacity'!E$2:E$10000,'New Capacity'!$B$2:$B$10000,$A133) -> 0.7694 | F133: =SUMIFS('New Capacity'!F$2:F$10000,'New Capacity'!$B$2:$B$10000,$A133) -> 0 | G133: =SUMIFS('New Capacity'!G$2:G$10000,'New Capacity'!$B$2:$B$10000,$A133) -> 0.6 | H133: =SUMIFS('New Capacity'!H$2:H$10000,'New Capacity'!$B$2:$B$10000,$A133) -> 0 | I133: =SUMIFS('New Capacity'!I$2:I$10000,'New Capacity'!$B$2:$B$10000,$A133) -> 0 | J133: =SUMIFS('New Capacity'!J$2:J$10000,'New Capacity'!$B$2:$B$10000,$A133) -> 0 | ... AG133: =SUMIFS('New Capacity'!AG$2:AG$10000,'New Capacity'!$B$2:$B$10000,$A133) -> 12.6337
A134: PHL_POW_PP_COAL_CCS | C134: =SUMIFS('New Capacity'!C$2:C$10000,'New Capacity'!$B$2:$B$10000,$A134) -> 0 | D134: =SUMIFS('New Capacity'!D$2:D$10000,'New Capacity'!$B$2:$B$10000,$A134) -> 0 | E134: =SUMIFS('New Capacity'!E$2:E$10000,'New Capacity'!$B$2:$B$10000,$A134) -> 0 | F134: =SUMIFS('New Capacity'!F$2:F$10000,'New Capacity'!$B$2:$B$10000,$A134) -> 0 | G134: =SUMIFS('New Capacity'!G$2:G$10000,'New Capacity'!$B$2:$B$10000,$A134) -> 0 | H134: =SUMIFS('New Capacity'!H$2:H$10000,'New Capacity'!$B$2:$B$10000,$A134) -> 0 | I134: =SUMIFS('New Capacity'!I$2:I$10000,'New Capacity'!$B$2:$B$10000,$A134) -> 0 | J134: =SUMIFS('New Capacity'!J$2:J$10000,'New Capacity'!$B$2:$B$10000,$A134) -> 0 | ... AG134: =SUMIFS('New Capacity'!AG$2:AG$10000,'New Capacity'!$B$2:$B$10000,$A134) -> 0
A135: PHL_POW_PP_H2 | C135: =SUMIFS('New Capacity'!C$2:C$10000,'New Capacity'!$B$2:$B$10000,$A135) -> 0 | D135: =SUMIFS('New Capacity'!D$2:D$10000,'New Capacity'!$B$2:$B$10000,$A135) -> 0 | E135: =SUMIFS('New Capacity'!E$2:E$10000,'New Capacity'!$B$2:$B$10000,$A135) -> 0 | F135: =SUMIFS('New Capacity'!F$2:F$10000,'New Capacity'!$B$2:$B$10000,$A135) -> 0 | G135: =SUMIFS('New Capacity'!G$2:G$10000,'New Capacity'!$B$2:$B$10000,$A135) -> 0 | H135: =SUMIFS('New Capacity'!H$2:H$10000,'New Capacity'!$B$2:$B$10000,$A135) -> 0 | I135: =SUMIFS('New Capacity'!I$2:I$10000,'New Capacity'!$B$2:$B$10000,$A135) -> 0 | J135: =SUMIFS('New Capacity'!J$2:J$10000,'New Capacity'!$B$2:$B$10000,$A135) -> 0 | ... AG135: =SUMIFS('New Capacity'!AG$2:AG$10000,'New Capacity'!$B$2:$B$10000,$A135) -> 0
A136: PHL_POW_PP_HY_LA | C136: =SUMIFS('New Capacity'!C$2:C$10000,'New Capacity'!$B$2:$B$10000,$A136) -> 1.4633 | D136: =SUMIFS('New Capacity'!D$2:D$10000,'New Capacity'!$B$2:$B$10000,$A136) -> 2.5546 | E136: =SUMIFS('New Capacity'!E$2:E$10000,'New Capacity'!$B$2:$B$10000,$A136) -> 0.0159 | F136: =SUMIFS('New Capacity'!F$2:F$10000,'New Capacity'!$B$2:$B$10000,$A136) -> 0.0468 | G136: =SUMIFS('New Capacity'!G$2:G$10000,'New Capacity'!$B$2:$B$10000,$A136) -> 0.0352 | H136: =SUMIFS('New Capacity'!H$2:H$10000,'New Capacity'!$B$2:$B$10000,$A136) -> 0 | I136: =SUMIFS('New Capacity'!I$2:I$10000,'New Capacity'!$B$2:$B$10000,$A136) -> 0 | J136: =SUMIFS('New Capacity'!J$2:J$10000,'New Capacity'!$B$2:$B$10000,$A136) -> 0 | ... AG136: =SUMIFS('New Capacity'!AG$2:AG$10000,'New Capacity'!$B$2:$B$10000,$A136) -> 0
A137: PHL_POW_PP_NGCC | C137: =SUMIFS('New Capacity'!C$2:C$10000,'New Capacity'!$B$2:$B$10000,$A137) -> 0 | D137: =SUMIFS('New Capacity'!D$2:D$10000,'New Capacity'!$B$2:$B$10000,$A137) -> 0 | E137: =SUMIFS('New Capacity'!E$2:E$10000,'New Capacity'!$B$2:$B$10000,$A137) -> 0 | F137: =SUMIFS('New Capacity'!F$2:F$10000,'New Capacity'!$B$2:$B$10000,$A137) -> 0 | G137: =SUMIFS('New Capacity'!G$2:G$10000,'New Capacity'!$B$2:$B$10000,$A137) -> 0 | H137: =SUMIFS('New Capacity'!H$2:H$10000,'New Capacity'!$B$2:$B$10000,$A137) -> 0.88 | I137: =SUMIFS('New Capacity'!I$2:I$10000,'New Capacity'!$B$2:$B$10000,$A137) -> 0 | J137: =SUMIFS('New Capacity'!J$2:J$10000,'New Capacity'!$B$2:$B$10000,$A137) -> 0 | ... AG137: =SUMIFS('New Capacity'!AG$2:AG$10000,'New Capacity'!$B$2:$B$10000,$A137) -> 5.0736
A138: PHL_POW_PP_NGCC_CCS | C138: =SUMIFS('New Capacity'!C$2:C$10000,'New Capacity'!$B$2:$B$10000,$A138) -> 0 | D138: =SUMIFS('New Capacity'!D$2:D$10000,'New Capacity'!$B$2:$B$10000,$A138) -> 0 | E138: =SUMIFS('New Capacity'!E$2:E$10000,'New Capacity'!$B$2:$B$10000,$A138) -> 0 | F138: =SUMIFS('New Capacity'!F$2:F$10000,'New Capacity'!$B$2:$B$10000,$A138) -> 0 | G138: =SUMIFS('New Capacity'!G$2:G$10000,'New Capacity'!$B$2:$B$10000,$A138) -> 0 | H138: =SUMIFS('New Capacity'!H$2:H$10000,'New Capacity'!$B$2:$B$10000,$A138) -> 0 | I138: =SUMIFS('New Capacity'!I$2:I$10000,'New Capacity'!$B$2:$B$10000,$A138) -> 0 | J138: =SUMIFS('New Capacity'!J$2:J$10000,'New Capacity'!$B$2:$B$10000,$A138) -> 0 | ... AG138: =SUMIFS('New Capacity'!AG$2:AG$10000,'New Capacity'!$B$2:$B$10000,$A138) -> 0
A139: PHL_POW_PP_NU | C139: =SUMIFS('New Capacity'!C$2:C$10000,'New Capacity'!$B$2:$B$10000,$A139) -> 0 | D139: =SUMIFS('New Capacity'!D$2:D$10000,'New Capacity'!$B$2:$B$10000,$A139) -> 0 | E139: =SUMIFS('New Capacity'!E$2:E$10000,'New Capacity'!$B$2:$B$10000,$A139) -> 0 | F139: =SUMIFS('New Capacity'!F$2:F$10000,'New Capacity'!$B$2:$B$10000,$A139) -> 0 | G139: =SUMIFS('New Capacity'!G$2:G$10000,'New Capacity'!$B$2:$B$10000,$A139) -> 0 | H139: =SUMIFS('New Capacity'!H$2:H$10000,'New Capacity'!$B$2:$B$10000,$A139) -> 0 | I139: =SUMIFS('New Capacity'!I$2:I$10000,'New Capacity'!$B$2:$B$10000,$A139) -> 0 | J139: =SUMIFS('New Capacity'!J$2:J$10000,'New Capacity'!$B$2:$B$10000,$A139) -> 0 | ... AG139: =SUMIFS('New Capacity'!AG$2:AG$10000,'New Capacity'!$B$2:$B$10000,$A139) -> 0
A140: PHL_POW_PP_NUSMR | C140: =SUMIFS('New Capacity'!C$2:C$10000,'New Capacity'!$B$2:$B$10000,$A140) -> 0 | D140: =SUMIFS('New Capacity'!D$2:D$10000,'New Capacity'!$B$2:$B$10000,$A140) -> 0 | E140: =SUMIFS('New Capacity'!E$2:E$10000,'New Capacity'!$B$2:$B$10000,$A140) -> 0 | F140: =SUMIFS('New Capacity'!F$2:F$10000,'New Capacity'!$B$2:$B$10000,$A140) -> 0 | G140: =SUMIFS('New Capacity'!G$2:G$10000,'New Capacity'!$B$2:$B$10000,$A140) -> 0 | H140: =SUMIFS('New Capacity'!H$2:H$10000,'New Capacity'!$B$2:$B$10000,$A140) -> 0 | I140: =SUMIFS('New Capacity'!I$2:I$10000,'New Capacity'!$B$2:$B$10000,$A140) -> 0 | J140: =SUMIFS('New Capacity'!J$2:J$10000,'New Capacity'!$B$2:$B$10000,$A140) -> 0 | ... AG140: =SUMIFS('New Capacity'!AG$2:AG$10000,'New Capacity'!$B$2:$B$10000,$A140) -> 0
...

Sheet Variable
A1: REGION | B1: TECHNOLOGY | C1: 2020 | D1: 2021 | E1: 2022 | F1: 2023 | G1: 2024 | H1: 2025 | I1: 2026 | J1: 2027 | K1: 2028 | L1: 2029 | M1: 2030 | N1: 2031 | O1: 2032 | P1: 2033 | Q1: 2034 | R1: 2035 | S1: 2036 | T1: 2037 | U1: 2038 | V1: 2039 | W1: 2040 | X1: 2041 | Y1: 2042 | Z1: 2043 | AA1: 2044 | AB1: 2045 | AC1: 2046 | AD1: 2047 | AE1: 2048 | AF1: 2049 | AG1: 2050
B2: PHL_AGR_FAC | C2: 0.0009 | D2: 0.001 | E2: 0.001 | F2: 0.001 | G2: 0.001 | H2: 0.001 | I2: 0.0011 | J2: 0.0011 | K2: 0.0011 | L2: 0.0011 | M2: 0.0011 | N2: 0.0012 | O2: 0.0012 | P2: 0.0012 | Q2: 0.0013 | R2: 0.0013 | S2: 0.0013 | T2: 0.0013 | U2: 0.0014 | V2: 0.0014 | W2: 0.0014 | X2: 0.0011 | Y2: 0.001 | Z2: 0.001 | AA2: 0.0009 | AB2: 0.0008 | AC2: 0.0008 | AD2: 0.0007 | AE2: 0.0006 | AF2: 0.0006 | AG2: 0.0018 | AH2: 0.0019 | AI2: 0.0019 | AJ2: 0.0019
B3: PHL_AGR_HEAT_BIOM | C3: 0 | D3: 0 | E3: 0 | F3: 0 | G3: 0 | H3: 0 | I3: 0 | J3: 0 | K3: 0 | L3: 0 | M3: 0 | N3: 0 | O3: 0 | P3: 0 | Q3: 0 | R3: 0 | S3: 0 | T3: 0 | U3: 0 | V3: 0 | W3: 0 | X3: 0 | Y3: 0 | Z3: 0 | AA3: 0 | AB3: 0 | AC3: 0 | AD3: 0 | AE3: 0 | AF3: 0 | AG3: 0 | AH3: 0 | AI3: 0 | AJ3: 0
B4: PHL_AGR_HEAT_COAL | C4: 0 | D4: 0 | E4: 0 | F4: 0 | G4: 0 | H4: 0 | I4: 0 | J4: 0 | K4: 0 | L4: 0 | M4: 0 | N4: 0 | O4: 0 | P4: 0 | Q4: 0 | R4: 0 | S4: 0 | T4: 0 | U4: 0 | V4: 0 | W4: 0 | X4: 0 | Y4: 0 | Z4: 0 | AA4: 0 | AB4: 0 | AC4: 0 | AD4: 0 | AE4: 0 | AF4: 0 | AG4: 0 | AH4: 0 | AI4: 0 | AJ4: 0
B5: PHL_AGR_HEAT_ELE | C5: 0 | D5: 0 | E5: 0 | F5: 0 | G5: 0 | H5: 0 | I5: 0 | J5: 0 | K5: 0 | L5: 0 | M5: 0 | N5: 0 | O5: 0 | P5: 0 | Q5: 0 | R5: 0 | S5: 0 | T5: 0 | U5: 0 | V5: 0 | W5: 0 | X5: 0 | Y5: 0 | Z5: 0 | AA5: 0 | AB5: 0 | AC5: 0 | AD5: 0 | AE5: 0 | AF5: 0 | AG5: 0 | AH5: 0 | AI5: 0 | AJ5: 0
B6: PHL_AGR_HEAT_NG | C6: 0.0008 | D6: 0.0008 | E6: 0.0008 | F6: 0.0008 | G6: 0.0009 | H6: 0.0009 | I6: 0.0009 | J6: 0.0009 | K6: 0.0009 | L6: 0.001 | M6: 0.001 | N6: 0.001 | O6: 0.001 | P6: 0.0011 | Q6: 0.0011 | R6: 0.0011 | S6: 0.0011 | T6: 0.0012 | U6: 0.0012 | V6: 0.0012 | W6: 0.0013 | X6: 0.0012 | Y6: 0.0011 | Z6: 0.001 | AA6: 0.0009 | AB6: 0.0009 | AC6: 0.0008 | AD6: 0.0008 | AE6: 0.0007 | AF6: 0.0006 | AG6: 0.0017 | AH6: 0.0018 | AI6: 0.0018 | AJ6: 0.0019
B7: PHL_AGR_HEAT_OIL | C7: 0.0001 | D7: 0.0001 | E7: 0.0001 | F7: 0.0001 | G7: 0.0001 | H7: 0.0001 | I7: 0.0001 | J7: 0.0001 | K7: 0.0001 | L7: 0.0001 | M7: 0.0001 | N7: 0.0001 | O7: 0.0001 | P7: 0.0001 | Q7: 0.0001 | R7: 0.0001 | S7: 0.0001 | T7: 0.0001 | U7: 0.0001 | V7: 0.0001 | W7: 0.0001 | X7: 0.0001 | Y7: 0.0001 | Z7: 0.0001 | AA7: 0.0001 | AB7: 0 | AC7: 0 | AD7: 0 | AE7: 0 | AF7: 0 | AG7: 0 | AH7: 0 | AI7: 0 | AJ7: 0
B8: PHL_AGR_MOT_ELE | C8: 0 | D8: 0 | E8: 0 | F8: 0 | G8: 0 | H8: 0 | I8: 0 | J8: 0 | K8: 0 | L8: 0 | M8: 0 | N8: 0 | O8: 0 | P8: 0 | Q8: 0 | R8: 0 | S8: 0 | T8: 0 | U8: 0 | V8: 0 | W8: 0 | X8: 0 | Y8: 0 | Z8: 0 | AA8: 0 | AB8: 0 | AC8: 0 | AD8: 0 | AE8: 0 | AF8: 0 | AG8: 0 | AH8: 0 | AI8: 0 | AJ8: 0
B9: PHL_AGR_MOT_LIQ | C9: 0.0008 | D9: 0.0008 | E9: 0.0008 | F9: 0.0008 | G9: 0.0009 | H9: 0.0009 | I9: 0.0009 | J9: 0.0009 | K9: 0.0009 | L9: 0.001 | M9: 0.001 | N9: 0.001 | O9: 0.001 | P9: 0.001 | Q9: 0.0011 | R9: 0.0011 | S9: 0.0011 | T9: 0.0011 | U9: 0.0012 | V9: 0.0012 | W9: 0.0012 | X9: 0.0012 | Y9: 0.0013 | Z9: 0.0013 | AA9: 0.0013 | AB9: 0.0014 | AC9: 0.0014 | AD9: 0.0014 | AE9: 0.0015 | AF9: 0.0015 | AG9: 0.0015 | AH9: 0.0016 | AI9: 0.0016 | AJ9: 0.0017
B10: PHL_AGR_UNIT | C10: 0.0009 | D10: 0.001 | E10: 0.001 | F10: 0.001 | G10: 0.001 | H10: 0.001 | I10: 0.0011 | J10: 0.0011 | K10: 0.0011 | L10: 0.0011 | M10: 0.0011 | N10: 0.0012 | O10: 0.0012 | P10: 0.0012 | Q10: 0.0013 | R10: 0.0013 | S10: 0.0013 | T10: 0.0013 | U10: 0.0014 | V10: 0.0014 | W10: 0.0014 | X10: 0.0015 | Y10: 0.0015 | Z10: 0.0015 | AA10: 0.0016 | AB10: 0.0016 | AC10: 0.0016 | AD10: 0.0017 | AE10: 0.0017 | AF10: 0.0018 | AG10: 0.0018 | AH10: 0.0019 | AI10: 0.0019 | AJ10: 0.0019
B11: PHL_DEM_PUB_GWT_WAT | C11: 0 | D11: 0 | E11: 0 | F11: 0 | G11: 0 | H11: 0 | I11: 0 | J11: 0.0001 | K11: 0 | L11: 0 | M11: 0 | N11: 0 | O11: 0 | P11: 0 | Q11: 0.0003 | R11: 0.0003 | S11: 0 | T11: 0 | U11: 0 | V11: 0 | W11: 0.0007 | X11: 0 | Y11: 0 | Z11: 0 | AA11: 0 | AB11: 0 | AC11: 0 | AD11: 0 | AE11: 0 | AF11: 0 | AG11: 0 | AH11: 0 | AI11: 0.0002 | AJ11: 0
B12: PHL_DEM_PUB_SUR_WAT | C12: 0.002 | D12: 0.002 | E12: 0.0021 | F12: 0.0022 | G12: 0.0023 | H12: 0.0024 | I12: 0.0025 | J12: 0.0024 | K12: 0.0026 | L12: 0.0027 | M12: 0.0029 | N12: 0.003 | O12: 0.0031 | P12: 0.0032 | Q12: 0.003 | R12: 0.0031 | S12: 0.0036 | T12: 0.0037 | U12: 0.0038 | V12: 0.004 | W12: 0.0035 | X12: 0.0043 | Y12: 0.0045 | Z12: 0.0046 | AA12: 0.0048 | AB12: 0.005 | AC12: 0.0052 | AD12: 0.0053 | AE12: 0.0055 | AF12: 0.0057 | AG12: 0.006 | AH12: 0.0062 | AI12: 0.0062 | AJ12: 0.0066
B13: PHL_DEM_PWR_GWT_WAT | C13: 0.0001 | D13: 0.0005 | E13: 0.0005 | F13: 0.0005 | G13: 0.0005 | H13: 0.0004 | I13: 0.0004 | J13: 0.0004 | K13: 0.0005 | L13: 0.0005 | M13: 0.0002 | N13: 0.0005 | O13: 0.0005 | P13: 0.0005 | Q13: 0.0003 | R13: 0.0002 | S13: 0.0007 | T13: 0.0012 | U13: 0.0018 | V13: 0.0022 | W13: 0.0018 | X13: 0.0027 | Y13: 0.0029 | Z13: 0.0031 | AA13: 0.0033 | AB13: 0.0036 | AC13: 0.0041 | AD13: 0.0046 | AE13: 0.005 | AF13: 0.0055 | AG13: 0.0057 | AH13: 0.0059 | AI13: 0.0063 | AJ13: 0.0063
... B133: PHL_TRA_VAN_PHEV | C133: 0 | D133: 0 | E133: 0 | F133: 0 | G133: 0 | H133: 0 | I133: 0 | J133: 0 | K133: 0 | L133: 0 | M133: 0 | N133: 0 | O133: 0 | P133: 0 | Q133: 0 | R133: 0 | S133: 0 | T133: 0 | U133: 0 | V133: 0 | W133: 0 | X133: 0 | Y133: 0 | Z133: 0 | AA133: 0 | AB133: 0 | AC133: 0 | AD133: 0 | AE133: 0 | AF133: 0 | AG133: 0 | AH133: 0 | AI133: 0 | AJ133: 0
B134: (blank)

Sheet Fixed
A1: REGION | B1: TECHNOLOGY | C1: 2020 | D1: 2021 | E1: 2022 | F1: 2023 | G1: 2024 | H1: 2025 | I1: 2026 | J1: 2027 | K1: 2028 | L1: 2029 | M1: 2030 | N1: 2031 | O1: 2032 | P1: 2033 | Q1: 2034 | R1: 2035 | S1: 2036 | T1: 2037 | U1: 2038 | V1: 2039 | W1: 2040 | X1: 2041 | Y1: 2042 | Z1: 2043 | AA1: 2044 | AB1: 2045 | AC1: 2046 | AD1: 2047 | AE1: 2048 | AF1: 2049 | AG1: 2050
A2: REGION | B2: PHL_AGR_FAC | C2: 0 | D2: 0 | E2: 0 | F2: 0 | G2: 0 | H2: 0 | I2: 0 | J2: 0 | K2: 0 | L2: 0 | M2: 0 | N2: 0 | O2: 0 | P2: 0 | Q2: 0 | R2: 0 | S2: 0 | T2: 0 | U2: 0 | V2: 0 | W2: 0 | X2: 0 | Y2: 0 | Z2: 0 | AA2: 0 | AB2: 0 | AC2: 0 | AD2: 0 | AE2: 0 | AF2: 0 | AG2: 0 | AH2: 0 | AI2: 0 | AJ2: 0
A3: REGION | B3: PHL_AGR_HEAT_BIOM | C3: 0.1835 | D3: 0.1825 | E3: 0.182 | F3: 0.181 | G3: 0.1805 | H3: 0.1799 | I3: 0.1789 | J3: 0.1784 | K3: 0.1774 | L3: 0.1769 | M3: 0.1759 | N3: 0.1753 | O3: 0.1748 | P3: 0.1738 | Q3: 0.1733 | R3: 0.1723 | S3: 0.1719 | T3: 0.1714 | U3: 0.1705 | V3: 0.1701 | W3: 0.1688 | X3: 0.1682 | Y3: 0.1673 | Z3: 0.1669 | AA3: 0.1665 | AB3: 0 | AC3: 0 | AD3: 0 | AE3: 0 | AF3: 0 | AG3: 0 | AH3: 0 | AI3: 0 | AJ3: 0
A4: REGION | B4: PHL_AGR_HEAT_COAL | C4: 0 | D4: 0 | E4: 0 | F4: 0 | G4: 0 | H4: 0 | I4: 0 | J4: 0 | K4: 0 | L4: 0 | M4: 0 | N4: 0 | O4: 0 | P4: 0 | Q4: 0 | R4: 0 | S4: 0 | T4: 0 | U4: 0 | V4: 0 | W4: 0 | X4: 0 | Y4: 0 | Z4: 0 | AA4: 0 | AB4: 0 | AC4: 0 | AD4: 0 | AE4: 0 | AF4: 0 | AG4: 0 | AH4: 0 | AI4: 0 | AJ4: 0
A5: REGION | B5: PHL_AGR_HEAT_ELE | C5: 0 | D5: 0 | E5: 0 | F5: 0 | G5: 0 | H5: 0 | I5: 0 | J5: 0 | K5: 0 | L5: 0 | M5: 0 | N5: 0 | O5: 0 | P5: 0 | Q5: 0 | R5: 0 | S5: 0 | T5: 0 | U5: 0 | V5: 0 | W5: 0 | X5: 0 | Y5: 0 | Z5: 0 | AA5: 0 | AB5: 0 | AC5: 0 | AD5: 0 | AE5: 0 | AF5: 0 | AG5: 0 | AH5: 0 | AI5: 0 | AJ5: 0
A6: REGION | B6: PHL_AGR_HEAT_NG | C6: 2.4405 | D6: 2.5553 | E6: 2.6389 | F6: 2.7214 | G6: 2.8028 | H6: 2.8833 | I6: 2.9682 | J6: 3.0524 | K6: 3.1358 | L6: 3.2185 | M6: 3.396 | N6: 3.4797 | O6: 3.5634 | P6: 3.6471 | Q6: 3.7308 | R6: 3.8145 | S6: 3.914 | T6: 4.0135 | U6: 4.1129 | V6: 4.2124 | W6: 4.2799 | X6: 4.2759 | Y6: 4.2719 | Z6: 4.2677 | AA6: 4.2677 | AB6: 3.0437 | AC6: 2.9389 | AD6: 2.8669 | AE6: 2.7948 | AF6: 2.7228 | AG6: 5.8518 | AH6: 5.9963 | AI6: 6.1409 | AJ6: 6.2854
A7: REGION | B7: PHL_AGR_HEAT_OIL | C7: 0.4512 | D7: 0.4548 | E7: 0.458 | F7: 0.4608 | G7: 0.4633 | H7: 0.4654 | I7: 0.4673 | J7: 0.4688 | K7: 0.4702 | L7: 0.4714 | M7: 0.487 | N7: 0.4863 | O7: 0.4856 | P7: 0.4849 | Q7: 0.4842 | R7: 0.4835 | S7: 0.4828 | T7: 0.4822 | U7: 0.4815 | V7: 0.4808 | W7: 0.4801 | X7: 0.4794 | Y7: 0.478 | Z7: 0.478 | AA7: 0.478 | AB7: 0 | AC7: 0 | AD7: 0 | AE7: 0 | AF7: 0 | AG7: 0 | AH7: 0 | AI7: 0 | AJ7: 0
A8: REGION | B8: PHL_AGR_MOT_ELE | C8: 0 | D8: 0 | E8: 0 | F8: 0 | G8: 0 | H8: 0 | I8: 0 | J8: 0 | K8: 0 | L8: 0 | M8: 0 | N8: 0 | O8: 0 | P8: 0 | Q8: 0 | R8: 0 | S8: 0 | T8: 0 | U8: 0 | V8: 0 | W8: 0 | X8: 0 | Y8: 0 | Z8: 0 | AA8: 0 | AB8: 0 | AC8: 0 | AD8: 0 | AE8: 0 | AF8: 0 | AG8: 0 | AH8: 0 | AI8: 0 | AJ8: 0
A9: REGION | B9: PHL_AGR_MOT_LIQ | C9: 258.9921 | D9: 264.8225 | E9: 270.6529 | F9: 276.4833 | G9: 282.3137 | H9: 288.144 | I9: 294.4654 | J9: 300.7868 | K9: 307.1081 | L9: 313.4295 | M9: 319.7508 | N9: 326.9326 | O9: 334.1143 | P9: 341.296 | Q9: 348.4777 | R9: 355.6594 | S9: 364.2035 | T9: 372.7475 | U9: 381.2916 | V9: 389.8356 | W9: 398.3797 | X9: 408.3247 | Y9: 418.2698 | Z9: 428.2148 | AA9: 438.1599 | AB9: 448.105 | AC9: 459.4445 | AD9: 470.784 | AE9: 482.1235 | AF9: 493.463 | AG9: 504.8025 | AH9: 517.2698 | AI9: 529.737 | AJ9: 542.2043
A10: REGION | B10: PHL_AGR_UNIT | C10: 0 | D10: 0 | E10: 0 | F10: 0 | G10: 0 | H10: 0 | I10: 0 | J10: 0 | K10: 0 | L10: 0 | M10: 0 | N10: 0 | O10: 0 | P10: 0 | Q10: 0 | R10: 0 | S10: 0 | T10: 0 | U10: 0 | V10: 0 | W10: 0 | X10: 0 | Y10: 0 | Z10: 0 | AA10: 0 | AB10: 0 | AC10: 0 | AD10: 0 | AE10: 0 | AF10: 0 | AG10: 0 | AH10: 0 | AI10: 0 | AJ10: 0
A11: REGION | B11: PHL_DEM_PUB_GWT_WAT | C11: 0 | D11: 0 | E11: 0 | F11: 0 | G11: 0 | H11: 0 | I11: 0 | J11: 0 | K11: 0 | L11: 0 | M11: 0 | N11: 0 | O11: 0 | P11: 0 | Q11: 0 | R11: 0 | S11: 0 | T11: 0 | U11: 0 | V11: 0 | W11: 0 | X11: 0 | Y11: 0 | Z11: 0 | AA11: 0 | AB11: 0 | AC11: 0 | AD11: 0 | AE11: 0 | AF11: 0 | AG11: 0 | AH11: 0 | AI11: 0 | AJ11: 0
A12: REGION | B12: PHL_DEM_PUB_SUR_WAT | C12: 0 | D12: 0 | E12: 0 | F12: 0 | G12: 0 | H12: 0 | I12: 0 | J12: 0 | K12: 0 | L12: 0 | M12: 0 | N12: 0 | O12: 0 | P12: 0 | Q12: 0 | R12: 0 | S12: 0 | T12: 0 | U12: 0 | V12: 0 | W12: 0 | X12: 0 | Y12: 0 | Z12: 0 | AA12: 0 | AB12: 0 | AC12: 0 | AD12: 0 | AE12: 0 | AF12: 0 | AG12: 0 | AH12: 0 | AI12: 0 | AJ12: 0
A13: REGION | B13: PHL_DEM_PWR_GWT_WAT | C13: 0 | D13: 0 | E13: 0 | F13: 0 | G13: 0 | H13: 0 | I13: 0 | J13: 0 | K13: 0 | L13: 0 | M13: 0 | N13: 0 | O13: 0 | P13: 0 | Q13: 0 | R13: 0 | S13: 0 | T13: 0 | U13: 0 | V13: 0 | W13: 0 | X13: 0 | Y13: 0 | Z13: 0 | AA13: 0 | AB13: 0 | AC13: 0 | AD13: 0 | AE13: 0 | AF13: 0 | AG13: 0 | AH13: 0 | AI13: 0 | AJ13: 0
... A132: REGION | B132: PHL_TRA_VAN_NG | C132: 0 | D132: 0 | E132: 0 | F132: 0 | G132: 0 | H132: 0 | I132: 0 | J132: 0 | K132: 0 | L132: 0 | M132: 0 | N132: 0 | O132: 0 | P132: 0 | Q132: 0 | R132: 0 | S132: 0 | T132: 0 | U132: 0 | V132: 0 | W132: 0 | X132: 0 | Y132: 0 | Z132: 0 | AA132: 0 | AB132: 0 | AC132: 0 | AD132: 0 | AE132: 0 | AF132: 0 | AG132: 0 | AH132: 0 | AI132: 0 | AJ132: 0
B133: PHL_TRA_VAN_PHEV | C133: 0 | D133: 0 | E133: 0 | F133: 0 | G133: 0 | H133: 0 | I133: 0 | J133: 0 | K133: 0 | L133: 0 | M133: 0 | N133: 0 | O133: 0 | P133: 0 | Q133: 0 | R133: 0 | S133: 0 | T133: 0 | U133: 0 | V133: 0 | W133: 0 | X133: 0 | Y133: 0 | Z133: 0 | AA133: 0 | AB133: 0 | AC133: 0 | AD133: 0 | AE133: 0 | AF133: 0 | AG133: 0 | AH133: 0 | AI133: 0 | AJ133: 0
B134: (blank)

Sheet Capital_Investments
A1: Million USD
A2: REGION | B2: TECHNOLOGY | C2: 2020 | D2: 2021 | E2: 2022 | F2: 2023 | G2: 2024 | H2: 2025 | I2: 2026 | J2: 2027 | K2: 2028 | L2: 2029 | M2: 2030 | N2: 2031 | O2: 2032 | P2: 2033 | Q2: 2034 | R2: 2035 | S2: 2036 | T2: 2037 | U2: 2038 | V2: 2039 | W2: 2040 | X2: 2041 | Y2: 2042 | Z2: 2043 | AA2: 2044 | AB2: 2045 | AC2: 2046 | AD2: 2047 | AE2: 2048 | AF2: 2049 | AG2: 2050
A3: REGION | B3: PHL_AGR_FAC | C3: 0 | D3: 0 | E3: 0 | F3: 0 | G3: 0 | H3: 0 | I3: 0 | J3: 0 | K3: 0 | L3: 0 | M3: 0 | N3: 0 | O3: 0 | P3: 0 | Q3: 0 | R3: 0 | S3: 0 | T3: 0 | U3: 0 | V3: 0 | W3: 0 | X3: 0 | Y3: 0 | Z3: 0 | AA3: 0 | AB3: 0 | AC3: 0 | AD3: 0 | AE3: 0 | AF3: 0 | AG3: 0 | AH3: 0 | AI3: 0 | AJ3: 0
A4: REGION | B4: PHL_AGR_HEAT_BIOM | C4: 2.999 | D4: 0 | E4: 0 | F4: 0 | G4: 0 | H4: 0 | I4: 0 | J4: 0 | K4: 0 | L4: 0 | M4: 0 | N4: 0 | O4: 0 | P4: 0 | Q4: 0 | R4: 0 | S4: 0 | T4: 0 | U4: 0 | V4: 0 | W4: 0 | X4: 0 | Y4: 0 | Z4: 0 | AA4: 0 | AB4: 0 | AC4: 0 | AD4: 0 | AE4: 0 | AF4: 0 | AG4: 0 | AH4: 0 | AI4: 0 | AJ4: 0
A5: REGION | B5: PHL_AGR_HEAT_COAL | C5: 0 | D5: 0 | E5: 0 | F5: 0 | G5: 0 | H5: 0 | I5: 0 | J5: 0 | K5: 0 | L5: 0 | M5: 0 | N5: 0 | O5: 0 | P5: 0 | Q5: 0 | R5: 0 | S5: 0 | T5: 0 | U5: 0 | V5: 0 | W5: 0 | X5: 0 | Y5: 0 | Z5: 0 | AA5: 0 | AB5: 0 | AC5: 0 | AD5: 0 | AE5: 0 | AF5: 0 | AG5: 0 | AH5: 0 | AI5: 0 | AJ5: 0
A6: REGION | B6: PHL_AGR_HEAT_ELE | C6: 0 | D6: 0 | E6: 0 | F6: 0 | G6: 0 | H6: 0 | I6: 0 | J6: 0 | K6: 0 | L6: 0 | M6: 0 | N6: 0 | O6: 0 | P6: 0 | Q6: 0 | R6: 0 | S6: 0 | T6: 0 | U6: 0 | V6: 0 | W6: 0 | X6: 0 | Y6: 0 | Z6: 0 | AA6: 0 | AB6: 0 | AC6: 0 | AD6: 0 | AE6: 0 | AF6: 0 | AG6: 0 | AH6: 0 | AI6: 0 | AJ6: 0
A7: REGION | B7: PHL_AGR_HEAT_NG | C7: 47.1147 | D7: 1.9432 | E7: 1.3465 | F7: 1.3559 | G7: 1.3643 | H7: 1.372 | I7: 1.4878 | J7: 1.4944 | K7: 1.5004 | L7: 1.5058 | M7: 1.5544 | N7: 1.7539 | O7: 1.7539 | P7: 1.7539 | Q7: 1.7539 | R7: 1.7539 | S7: 2.0697 | T7: 2.0697 | U7: 2.0697 | V7: 2.0697 | W7: 1.4297 | X7: 0 | Y7: 0 | Z7: 0 | AA7: 0 | AB7: 26.7657 | AC7: 0 | AD7: 0 | AE7: 0 | AF7: 0 | AG7: 64.0209 | AH7: 4.4449 | AI7: 4.4449 | AJ7: 4.4449
A8: REGION | B8: PHL_AGR_HEAT_OIL | C8: 10.9168 | D8: 0 | E8: 0 | F8: 0 | G8: 0 | H8: 0 | I8: 0 | J8: 0 | K8: 0 | L8: 0 | M8: 0 | N8: 0 | O8: 0 | P8: 0 | Q8: 0 | R8: 0 | S8: 0 | T8: 0 | U8: 0 | V8: 0 | W8: 0 | X8: 0 | Y8: 0 | Z8: 0 | AA8: 0 | AB8: 0 | AC8: 0 | AD8: 0 | AE8: 0 | AF8: 0 | AG8: 0 | AH8: 0 | AI8: 0 | AJ8: 0
A9: REGION | B9: PHL_AGR_MOT_ELE | C9: 0 | D9: 0 | E9: 0 | F9: 0 | G9: 0 | H9: 0 | I9: 0 | J9: 0 | K9: 0 | L9: 0 | M9: 0 | N9: 0 | O9: 0 | P9: 0 | Q9: 0 | R9: 0 | S9: 0 | T9: 0 | U9: 0 | V9: 0 | W9: 0 | X9: 0 | Y9: 0 | Z9: 0 | AA9: 0 | AB9: 0 | AC9: 0 | AD9: 0 | AE9: 0 | AF9: 0 | AG9: 0 | AH9: 0 | AI9: 0 | AJ9: 0
A10: REGION | B10: PHL_AGR_MOT_LIQ | C10: 14270.519 | D10: 369.9875 | E10: 369.9875 | F10: 376.4785 | G10: 382.9696 | H10: 389.4606 | I10: 425.9008 | J10: 432.8827 | K10: 439.8647 | L10: 453.8287 | M10: 460.8106 | N10: 525.4367 | O10: 533.279 | P10: 533.279 | Q10: 498.5774 | R10: 17770.378 | S10: 1037.4189 | T10: 1037.4189 | U10: 1052.454 | V10: 1052.454 | W10: 1052.454 | X10: 1184.893 | Y10: 1201.82 | Z10: 1201.82 | AA10: 1201.82 | AB10: 1201.82 | AC10: 1361.9114 | AD10: 1361.9114 | AE10: 1381.0932 | AF10: 1336.6995 | AG10: 19359.448 | AH10: 1980.1654 | AI10: 1980.1653 | AJ10: 1980.1654
A11: REGION | B11: PHL_AGR_UNIT | C11: 0 | D11: 0 | E11: 0 | F11: 0 | G11: 0 | H11: 0 | I11: 0 | J11: 0 | K11: 0 | L11: 0 | M11: 0 | N11: 0 | O11: 0 | P11: 0 | Q11: 0 | R11: 0 | S11: 0 | T11: 0 | U11: 0 | V11: 0 | W11: 0 | X11: 0 | Y11: 0 | Z11: 0 | AA11: 0 | AB11: 0 | AC11: 0 | AD11: 0 | AE11: 0 | AF11: 0 | AG11: 0 | AH11: 0 | AI11: 0 | AJ11: 0
A12: REGION | B12: PHL_DEM_PUB_GWT_WAT | C12: 0 | D12: 0 | E12: 0 | F12: 0 | G12: 0 | H12: 0 | I12: 0 | J12: 0 | K12: 0 | L12: 0 | M12: 0 | N12: 0 | O12: 0 | P12: 0 | Q12: 0 | R12: 0 | S12: 0 | T12: 0 | U12: 0 | V12: 0 | W12: 0 | X12: 0 | Y12: 0 | Z12: 0 | AA12: 0 | AB12: 0 | AC12: 0 | AD12: 0 | AE12: 0 | AF12: 0 | AG12: 0 | AH12: 0 | AI12: 0 | AJ12: 0
A13: REGION | B13: PHL_DEM_PUB_SUR_WAT | C13: 0 | D13: 0 | E13: 0 | F13: 0 | G13: 0 | H13: 0 | I13: 0 | J13: 0 | K13: 0 | L13: 0 | M13: 0 | N13: 0 | O13: 0 | P13: 0 | Q13: 0 | R13: 0 | S13: 0 | T13: 0 | U13: 0 | V13: 0 | W13: 0 | X13: 0 | Y13: 0 | Z13: 0 | AA13: 0 | AB13: 0 | AC13: 0 | AD13: 0 | AE13: 0 | AF13: 0 | AG13: 0 | AH13: 0 | AI13: 0 | AJ13: 0
A14: REGION | B14: PHL_DEM_PWR_GWT_WAT | C14: 0 | D14: 0 | E14: 0 | F14: 0 | G14: 0 | H14: 0 | I14: 0 | J14: 0 | K14: 0 | L14: 0 | M14: 0 | N14: 0 | O14: 0 | P14: 0 | Q14: 0 | R14: 0 | S14: 0 | T14: 0 | U14: 0 | V14: 0 | W14: 0 | X14: 0 | Y14: 0 | Z14: 0 | AA14: 0 | AB14: 0 | AC14: 0 | AD14: 0 | AE14: 0 | AF14: 0 | AG14: 0 | AH14: 0 | AI14: 0 | AJ14: 0
... A133: REGION | B133: PHL_TRA_VAN_NG | C133: 0 | D133: 0 | E133: 0 | F133: 0 | G133: 0 | H133: 0 | I133: 0 | J133: 0 | K133: 0 | L133: 0 | M133: 0 | N133: 0 | O133: 0 | P133: 0 | Q133: 0 | R133: 0 | S133: 0 | T133: 0 | U133: 0 | V133: 0 | W133: 0 | X133: 0 | Y133: 0 | Z133: 0 | AA133: 0 | AB133: 0 | AC133: 0 | AD133: 0 | AE133: 0 | AF133: 0 | AG133: 0 | AH133: 0 | AI133: 0 | AJ133: 0
B134: PHL_TRA_VAN_PHEV | C134: 0 | D134: 0 | E134: 0 | F134: 0 | G134: 0 | H134: 0 | I134: 0 | J134: 0 | K134: 0 | L134: 0 | M134: 0 | N134: 0 | O134: 0 | P134: 0 | Q134: 0 | R134: 0 | S134: 0 | T134: 0 | U134: 0 | V134: 0 | W134: 0 | X134: 0 | Y134: 0 | Z134: 0 | AA134: 0 | AB134: 0 | AC134: 0 | AD134: 0 | AE134: 0 | AF134: 0 | AG134: 0 | AH134: 0 | AI134: 0 | AJ134: 0
B135: (blank)
A170: REGION | B170: GHA_PRO_BLEND_BIOF | C170: 0 | D170: 0 | E170: 0 | F170: 0 | G170: 0 | H170: 0 | I170: 0 | J170: 0 | K170: 0 | L170: 0 | M170: 0 | N170: 0 | O170: 0 | P170: 0 | Q170: 0 | R170: 0 | S170: 0 | T170: 0 | U170: 0 | V170: 0 | W170: 0 | X170: 0 | Y170: 0 | Z170: 0 | AA170: 0 | AB170: 0 | AC170: 0 | AD170: 0 | AE170: 0 | AF170: 0 | AG170: 0
A171: REGION | B171: GHA_PRO_BLEND_OIL | C171: 0 | D171: 0 | E171: 0 | F171: 0 | G171: 0 | H171: 0 | I171: 0 | J171: 0 | K171: 0 | L171: 0 | M171: 0 | N171: 0 | O171: 0 | P171: 0 | Q171: 0 | R171: 0 | S171: 0 | T171: 0 | U171: 0 | V171: 0 | W171: 0 | X171: 0 | Y171: 0 | Z171: 0 | AA171: 0 | AB171: 0 | AC171: 0 | AD171: 0 | AE171: 0 | AF171: 0 | AG171: 0
A172: REGION | B172: GHA_PRO_EXTR_COAL | C172: 0 | D172: 0 | E172: 0 | F172: 0 | G172: 0 | H172: 0 | I172: 0 | J172: 0 | K172: 0 | L172: 0 | M172: 0 | N172: 0 | O172: 0 | P172: 0 | Q172: 0 | R172: 0 | S172: 0 | T172: 0 | U172: 0 | V172: 0 | W172: 0 | X172: 0 | Y172: 0 | Z172: 0 | AA172: 0 | AB172: 0 | AC172: 0 | AD172: 0 | AE172: 0 | AF172: 0 | AG172: 0
A173: REGION | B173: GHA_PRO_EXTR_NG | C173: 0 | D173: 0 | E173: 0 | F173: 0 | G173: 0 | H173: 0 | I173: 0 | J173: 0 | K173: 0 | L173: 0 | M173: 0 | N173: 0 | O173: 0 | P173: 0 | Q173: 0 | R173: 0 | S173: 0 | T173: 0 | U173: 0 | V173: 0 | W173: 0 | X173: 0 | Y173: 0 | Z173: 0 | AA173: 0 | AB173: 0 | AC173: 0 | AD173: 0 | AE173: 0 | AF173: 0 | AG173: 0
A174: REGION | B174: GHA_PRO_EXTR_OIL | C174: 0 | D174: 0 | E174: 0 | F174: 0 | G174: 0 | H174: 0 | I174: 0 | J174: 0 | K174: 0 | L174: 0 | M174: 0 | N174: 0 | O174: 0 | P174: 0 | Q174: 0 | R174: 0 | S174: 0 | T174: 0 | U174: 0 | V174: 0 | W174: 0 | X174: 0 | Y174: 0 | Z174: 0 | AA174: 0 | AB174: 0 | AC174: 0 | AD174: 0 | AE174: 0 | AF174: 0 | AG174: 0
A175: REGION | B175: GHA_PRO_EXTR_UR | C175: 0 | D175: 0 | E175: 0 | F175: 0 | G175: 0 | H175: 0 | I175: 0 | J175: 0 | K175: 0 | L175: 0 | M175: 0 | N175: 0 | O175: 0 | P175: 0 | Q175: 0 | R175: 0 | S175: 0 | T175: 0 | U175: 0 | V175: 0 | W175: 0 | X175: 0 | Y175: 0 | Z175: 0 | AA175: 0 | AB175: 0 | AC175: 0 | AD175: 0 | AE175: 0 | AF175: 0 | AG175: 0
A176: REGION | B176: GHA_PRO_PROC_BIOF1 | C176: 0 | D176: 0 | E176: 0 | F176: 0 | G176: 0 | H176: 0 | I176: 0 | J176: 0 | K176: 0 | L176: 0 | M176: 0 | N176: 0 | O176: 0 | P176: 0 | Q176: 0 | R176: 0 | S176: 0 | T176: 0 | U176: 0 | V176: 0 | W176: 0 | X176: 0 | Y176: 0 | Z176: 0 | AA176: 0 | AB176: 0 | AC176: 0 | AD176: 0 | AE176: 0 | AF176: 8.93e-05 | AG176: 132.77715
A177: REGION | B177: GHA_PRO_PROC_BIOM | C177: 0 | D177: 0 | E177: 0 | F177: 0 | G177: 0 | H177: 0 | I177: 0 | J177: 0 | K177: 0 | L177: 0 | M177: 0 | N177: 0 | O177: 0 | P177: 0 | Q177: 0 | R177: 0 | S177: 0 | T177: 0 | U177: 0 | V177: 0 | W177: 0 | X177: 0 | Y177: 0 | Z177: 0 | AA177: 0 | AB177: 0 | AC177: 0 | AD177: 0 | AE177: 0 | AF177: 0 | AG177: 0
A178: REGION | B178: GHA_PRO_PROC_COAL | C178: 0 | D178: 0 | E178: 0 | F178: 0 | G178: 0 | H178: 0 | I178: 0 | J178: 0 | K178: 0 | L178: 0 | M178: 0 | N178: 0 | O178: 0 | P178: 0 | Q178: 0 | R178: 0 | S178: 0 | T178: 0 | U178: 0 | V178: 0 | W178: 0 | X178: 0 | Y178: 0 | Z178: 0 | AA178: 0 | AB178: 0 | AC178: 0 | AD178: 0 | AE178: 0 | AF178: 0 | AG178: 0
A179: REGION | B179: GHA_PRO_PROC_NG | C179: 0 | D179: 0 | E179: 0 | F179: 0 | G179: 0 | H179: 0 | I179: 0 | J179: 0 | K179: 0 | L179: 0 | M179: 0 | N179: 0 | O179: 0 | P179: 0 | Q179: 0 | R179: 0 | S179: 0 | T179: 0 | U179: 0 | V179: 0 | W179: 0 | X179: 0 | Y179: 0 | Z179: 0 | AA179: 0 | AB179: 0 | AC179: 0 | AD179: 0 | AE179: 0 | AF179: 0 | AG179: 0
A180: REGION | B180: GHA_PRO_PROC_OIL | C180: 0 | D180: 0 | E180: 0 | F180: 0 | G180: 0 | H180: 0 | I180: 0 | J180: 0 | K180: 0 | L180: 0 | M180: 0 | N180: 0 | O180: 0 | P180: 0 | Q180: 0 | R180: 0 | S180: 0 | T180: 0 | U180: 0 | V180: 0 | W180: 0 | X180: 0 | Y180: 0 | Z180: 0 | AA180: 0 | AB180: 0 | AC180: 0 | AD180: 0 | AE180: 0 | AF180: 0 | AG180: 0
A181: REGION | B181: GHA_PRO_PROC_TRADBIOM | C181: 0 | D181: 0 | E181: 0 | F181: 0 | G181: 0 | H181: 0 | I181: 0 | J181: 0 | K181: 0 | L181: 0 | M181: 0 | N181: 0 | O181: 0 | P181: 0 | Q181: 0 | R181: 0 | S181: 0 | T181: 0 | U181: 0 | V181: 0 | W181: 0 | X181: 0 | Y181: 0 | Z181: 0 | AA181: 0 | AB181: 0 | AC181: 0 | AD181: 0 | AE181: 0 | AF181: 0 | AG181: 0
... A220: REGION | B220: SLE_POST_UNIT | C220: 0 | D220: 0 | E220: 0 | F220: 0 | G220: 0 | H220: 0 | I220: 0 | J220: 0 | K220: 0 | L220: 0 | M220: 0 | N220: 0 | O220: 0 | P220: 0 | Q220: 0 | R220: 0 | S220: 0 | T220: 0 | U220: 0 | V220: 0 | W220: 0 | X220: 0 | Y220: 0 | Z220: 0 | AA220: 0 | AB220: 0 | AC220: 0 | AD220: 0 | AE220: 0 | AF220: 0 | AG220: 0

Sheet Annualized_Investments
A1: Million USD
B2: Year | C2: 2020 | D2: 2021 | E2: 2022 | F2: 2023 | G2: 2024 | H2: 2025 | I2: 2026 | J2: 2027 | K2: 2028 | L2: 2029 | M2: 2030 | N2: 2031 | O2: 2032 | P2: 2033 | Q2: 2034 | R2: 2035 | S2: 2036 | T2: 2037 | U2: 2038 | V2: 2039 | W2: 2040 | X2: 2041 | Y2: 2042 | Z2: 2043 | AA2: 2044 | AB2: 2045 | AC2: 2046 | AD2: 2047 | AE2: 2048 | AF2: 2049 | AG2: 2050 | AH2: 2051 | AI2: 2052 | AJ2: 2053
B3: PHL_AGR_HEAT_BIOM | C3: 0.20265373 | D3: 0.20265373 | E3: 0.20265373 | F3: 0.20265373 | G3: 0.20265373 | H3: 0.20265373 | I3: 0.20265373 | J3: 0.20265373 | K3: 0.20265373 | L3: 0.20265373 | M3: 0.20265373 | N3: 0.20265373 | O3: 0.20265373 | P3: 0.20265373 | Q3: 0.20265373 | R3: 0.20265373 | S3: 0.20265373 | T3: 0.20265373 | U3: 0.20265373 | V3: 0.20265373 | W3: 0.20265373 | X3: 0.20265373 | Y3: 0.20265373 | Z3: 0.20265373 | AA3: 0.20265373
B4: PHL_AGR_HEAT_NG | C4: 3.1837178 | D4: 3.3150272 | E4: 3.4060153 | F4: 3.4976385 | G4: 3.5898294 | H4: 3.6825407 | I4: 3.7830769 | J4: 3.8840591 | K4: 3.9854468 | L4: 4.0871994 | M4: 4.1922361 | N4: 4.3107537 | O4: 4.4292713 | P4: 4.547789 | Q4: 4.6663066 | R4: 4.7848242 | S4: 4.9246817 | T4: 5.0645391 | U4: 5.2043965 | V4: 5.344254 | W4: 5.4408642 | X4: 5.4408642 | Y4: 5.4408642 | Z4: 5.4408642 | AA4: 5.4408642 | AB4: 4.0658056 | AC4: 3.9344962 | AD4: 3.8435081 | AE4: 3.7518849 | AF4: 3.659694 | AG4: 7.8931162 | AH4: 8.0929386 | AI4: 8.292315 | AJ4: 8.491286
B5: PHL_AGR_HEAT_OIL | C5: 0.73768932 | D5: 0.73768932 | E5: 0.73768932 | F5: 0.73768932 | G5: 0.73768932 | H5: 0.73768932 | I5: 0.73768932 | J5: 0.73768932 | K5: 0.73768932 | L5: 0.73768932 | M5: 0.73768932 | N5: 0.73768932 | O5: 0.73768932 | P5: 0.73768932 | Q5: 0.73768932 | R5: 0.73768932 | S5: 0.73768932 | T5: 0.73768932 | U5: 0.73768932 | V5: 0.73768932 | W5: 0.73768932 | X5: 0.73768932 | Y5: 0.73768932 | Z5: 0.73768932 | AA5: 0.73768932
B6: PHL_AGR_MOT_LIQ | C6: 1309.3852 | D6: 1343.3332 | E6: 1377.2813 | F6: 1411.8249 | G6: 1446.9641 | H6: 1482.6989 | I6: 1521.7772 | J6: 1561.4962 | K6: 1601.8558 | L6: 1643.4966 | M6: 1685.7781 | N6: 1733.9893 | O6: 1782.9201 | P6: 1831.8509 | Q6: 1877.5976 | R6: 2198.7256 | S6: 2259.9655 | T6: 2321.2054 | U6: 2383.2292 | V6: 2444.6575 | W6: 2505.4901 | X6: 2575.1311 | Y6: 2645.6846 | Z6: 2715.5975 | AA6: 2784.2291 | AB6: 2852.2201 | AC6: 2928.9705 | AD6: 3005.0013 | AE6: 3082.7921 | AF6: 3159.6936 | AG6: 3305.498 | AH6: 3391.9993 | AI6: 3478.5006 | AJ6: 3563.6224
B7: PHL_HOU_COOK_BIOM | C7: 2083.34 | D7: 2083.34 | E7: 2083.34 | F7: 2083.34 | G7: 2083.34 | H7: 2083.34 | I7: 2083.34 | J7: 2083.34 | K7: 2083.34 | L7: 2083.34 | M7: 2083.34 | N7: 2083.34 | O7: 2083.34 | P7: 2083.34 | Q7: 2083.34
B8: PHL_HOU_COOK_COAL | D8: 2205.9097 | E8: 2239.8151 | F8: 2273.7113 | G8: 2308.4977 | H8: 2371.7282 | I8: 2479.7634 | J8: 2513.2762 | K8: 2544.6746 | L8: 2560.5955 | M8: 2560.5955 | N8: 2560.5955 | O8: 2582.3262 | P8: 2612.6276 | Q8: 2696.6311 | R8: 2752.3885 | S8: 2778.6119 | T8: 2804.8354 | U8: 2831.068 | V8: 2857.2915 | W8: 2883.5241 | X8: 2906.8206 | Y8: 2930.117 | Z8: 2953.4135 | AA8: 2976.71 | AB8: 3000.0157 | AC8: 3020.1741 | AD8: 3040.3326 | AE8: 3060.4911 | AF8: 3080.6587 | AG8: 3100.8172 | AH8: 3118.2139 | AI8: 3135.6014 | AJ8: 3152.998
B9: PHL_HOU_COOK_ELE | C9: 101.97367 | D9: 101.97367 | E9: 101.97367 | F9: 101.97367 | G9: 101.97367 | H9: 101.97367 | I9: 101.97367 | J9: 101.97367 | K9: 101.97367 | L9: 101.97367 | M9: 101.97367 | N9: 101.97367 | O9: 101.97367 | P9: 101.97367 | Q9: 101.97367
B10: PHL_INDU_OTHHPH_BIOM | C10: 23.647988 | D10: 23.647988 | E10: 23.647988 | F10: 23.647988 | G10: 23.647988 | H10: 23.647988 | I10: 23.647988 | J10: 23.647988 | K10: 23.647988 | L10: 23.647988 | M10: 23.647988 | N10: 23.647988 | O10: 23.647988 | P10: 23.647988 | Q10: 23.647988 | R10: 23.647988 | S10: 23.647988 | T10: 23.647988 | U10: 23.647988 | V10: 23.647988 | W10: 23.647988 | X10: 23.647988 | Y10: 23.647988 | Z10: 23.647988 | AA10: 23.647988
B11: PHL_INDU_OTHHPH_COAL | C11: 46.682345 | D11: 137.70501 | E11: 140.83673 | F11: 140.83673 | G11: 147.03045 | H11: 147.03045 | I11: 153.41071 | J11: 156.70996 | K11: 159.99343 | L11: 163.26177 | M11: 166.48491 | N11: 170.12042 | O11: 173.74116 | P11: 177.34792 | Q11: 180.94147 | R11: 184.52256 | S11: 188.75431 | T11: 192.97301 | U11: 197.17947 | V11: 201.37447 | W11: 205.51886 | X11: 210.31969 | Y11: 215.11088 | Z11: 219.89644 | AA11: 224.59585 | AB11: 224.23778 | AC11: 220.11525 | AD11: 225.13967 | AE11: 230.47093 | AF11: 235.23007 | AG11: 240.50968 | AH11: 245.74034 | AI11: 251.26318 | AJ11: 256.80181
B12: PHL_INDU_OTHHPH_NG | C12: 0.2391233 | D12: 0.2391233 | E12: 0.2391233 | F12: 0.2391233 | G12: 0.2391233 | H12: 0.2391233 | I12: 0.2391233 | J12: 0.2391233 | K12: 0.2391233 | L12: 0.2391233 | M12: 0.2391233 | N12: 0.2391233 | O12: 0.2391233 | P12: 0.2391233 | Q12: 0.2391233 | R12: 0.2391233 | S12: 0.2391233 | T12: 0.2391233 | U12: 0.2391233 | V12: 0.2391233 | W12: 0.2391233 | X12: 0.2391233 | Y12: 0.2391233 | Z12: 0.2391233 | AA12: 0.2391233
B13: PHL_INDU_OTHHPH_OIL | C13: 30.260845 | D13: 30.260845 | E13: 30.260845 | F13: 30.260845 | G13: 30.260845 | H13: 30.260845 | I13: 30.260845 | J13: 30.260845 | K13: 30.260845 | L13: 30.260845 | M13: 30.260845 | N13: 30.260845 | O13: 30.260845 | P13: 30.260845 | Q13: 30.260845 | R13: 30.260845 | S13: 30.260845 | T13: 30.260845 | U13: 30.260845 | V13: 30.260845 | W13: 30.260845 | X13: 30.260845 | Y13: 30.260845 | Z13: 30.260845 | AA13: 30.260845
B14: PHL_INDU_OTHLPH_BIOM | C14: 23.647988 | D14: 23.647988 | E14: 23.647988 | F14: 23.647988 | G14: 23.647988 | H14: 23.647988 | I14: 23.647988 | J14: 23.647988 | K14: 23.647988 | L14: 23.647988 | M14: 23.647988 | N14: 23.647988 | O14: 23.647988 | P14: 23.647988 | Q14: 23.647988 | R14: 23.647988 | S14: 23.647988 | T14: 23.647988 | U14: 23.647988 | V14: 23.647988 | W14: 23.647988 | X14: 23.647988 | Y14: 23.647988 | Z14: 23.647988 | AA14: 23.647988
B15: PHL_INDU_OTHLPH_COAL | C15: 46.682345 | D15: 108.49525 | E15: 140.66629 | F15: 140.66629 | G15: 146.86001 | H15: 146.86001 | I15: 153.24027 | J15: 156.53952 | K15: 159.82298 | L15: 163.09133 | M15: 166.31447 | N15: 169.94997 | O15: 173.57072 | P15: 177.17748 | Q15: 180.77103 | R15: 184.35211 | S15: 188.58387 | T15: 192.80257 | U15: 197.00903 | V15: 201.20403 | W15: 205.34842 | X15: 210.14924 | Y15: 214.94044 | Z15: 219.726 | AA15: 224.42541 | AB15: 224.06734 | AC15: 222.98248 | AD15: 225.10844 | AE15: 230.4397 | AF15: 235.19883 | AG15: 240.47845 | AH15: 245.70911 | AI15: 251.23195 | AJ15: 256.77058
B16: PHL_INDU_OTHLPH_NG | C16: 0.21971611 | D16: 0.21971611 | E16: 0.21971611 | F16: 0.21971611 | G16: 0.21971611 | H16: 0.21971611 | I16: 0.21971611 | J16: 0.21971611 | K16: 0.21971611 | L16: 0.21971611 | M16: 0.21971611 | N16: 0.21971611 | O16: 0.21971611 | P16: 0.21971611 | Q16: 0.21971611 | R16: 0.21971611 | S16: 0.21971611 | T16: 0.21971611 | U16: 0.21971611 | V16: 0.21971611 | W16: 0.21971611 | X16: 0.21971611 | Y16: 0.21971611 | Z16: 0.21971611 | AA16: 0.21971611
B17: PHL_INDU_OTHLPH_OIL | C17: 34.242722 | D17: 34.242722 | E17: 34.242722 | F17: 34.242722 | G17: 34.242722 | H17: 34.242722 | I17: 34.242722 | J17: 34.242722 | K17: 34.242722 | L17: 34.242722 | M17: 34.242722 | N17: 34.242722 | O17: 34.242722 | P17: 34.242722 | Q17: 34.242722 | R17: 34.242722 | S17: 34.242722 | T17: 34.242722 | U17: 34.242722 | V17: 34.242722
B18: PHL_POW_CHP_BIOM_OLD | E18: 20.480611 | F18: 21.979192 | G18: 24.451851 | H18: 24.451851 | I18: 24.451851 | J18: 24.451851 | K18: 24.451851 | L18: 24.451851 | M18: 24.451851 | N18: 24.451851 | O18: 24.451851 | P18: 24.451851 | Q18: 24.451851 | R18: 24.451851 | S18: 24.451851 | T18: 24.451851 | U18: 24.451851 | V18: 24.451851 | W18: 24.451851 | X18: 24.451851 | Y18: 24.451851 | Z18: 24.451851 | AA18: 24.451851 | AB18: 24.451851 | AC18: 24.451851 | AD18: 24.451851 | AE18: 24.451851 | AF18: 24.451851 | AG18: 24.451851 | AH18: 24.451851 | AI18: 24.451851 | AJ18: 24.451851
B19: PHL_POW_CHP_OIL_OLD | D19: 12.973274 | E19: 19.99385 | F19: 19.99385 | G19: 20.801973 | H19: 20.801973 | I19: 20.801973 | J19: 20.801973 | K19: 20.801973 | L19: 20.801973 | M19: 20.801973 | N19: 20.801973 | O19: 20.801973 | P19: 20.801973 | Q19: 20.801973 | R19: 20.801973 | S19: 20.801973 | T19: 20.801973 | U19: 20.801973 | V19: 20.801973 | W19: 20.801973 | X19: 20.801973 | Y19: 20.801973 | Z19: 20.801973 | AA19: 20.801973 | AB19: 20.801973 | AC19: 20.801973 | AD19: 20.801973 | AE19: 20.801973 | AF19: 20.801973 | AG19: 20.801973 | AH19: 20.801973 | AI19: 20.801973 | AJ19: 20.801973
B20: PHL_POW_GEO_OLD | E20: 0.90358901 | F20: 69.548414 | G20: 71.190132 | H20: 79.908545 | I20: 286.5193 | J20: 286.5193 | K20: 286.5193 | L20: 286.5193 | M20: 286.5193 | N20: 286.5193 | O20: 286.5193 | P20: 286.5193 | Q20: 331.82664 | R20: 780.34264 | S20: 806.83978 | T20: 955.8587 | U20: 955.8587 | V20: 955.8587 | W20: 955.8587 | X20: 955.8587 | Y20: 955.8587 | Z20: 955.8587 | AA20: 955.8587 | AB20: 955.8587 | AC20: 955.8587 | AD20: 955.8587 | AE20: 955.8587 | AF20: 955.8587 | AG20: 955.8587 | AH20: 955.8587 | AI20: 955.8587 | AJ20: 955.8587
B21: PHL_POW_PP_COAL | D21: 107.78016 | E21: 222.16093 | F21: 222.16093 | G21: 311.3583 | H21: 311.3583 | I21: 311.3583 | J21: 531.27879 | K21: 750.36335 | L21: 968.40546 | M21: 1996.553 | N21: 1996.553 | O21: 1996.553 | P21: 1996.553 | Q21: 1996.553 | R21: 1996.553 | S21: 1996.553 | T21: 1996.553 | U21: 1996.553 | V21: 1996.553 | W21: 1996.553 | X21: 1996.553 | Y21: 1996.553 | Z21: 1996.553 | AA21: 1996.553 | AB21: 1996.553 | AC21: 1888.7728 | AD21: 1774.3921 | AE21: 1774.3921 | AF21: 1685.1947 | AG21: 1685.1947 | AH21: 1685.1947 | AI21: 1465.2742 | AJ21: 1246.1896
B22: PHL_POW_PP_HY_LA | C22: 210.64731 | D22: 578.3826 | E22: 580.67144 | F22: 587.40838 | G22: 592.47549 | H22: 592.47549 | I22: 592.47549 | J22: 592.47549 | K22: 592.47549 | L22: 592.47549 | M22: 592.47549 | N22: 592.47549 | O22: 592.47549 | P22: 592.47549 | Q22: 592.47549 | R22: 592.47549 | S22: 592.47549 | T22: 592.47549 | U22: 592.47549 | V22: 592.47549 | W22: 592.47549 | X22: 592.47549 | Y22: 592.47549 | Z22: 592.47549 | AA22: 592.47549 | AB22: 592.47549 | AC22: 592.47549 | AD22: 592.47549 | AE22: 592.47549 | AF22: 592.47549 | AG22: 592.47549 | AH22: 592.47549 | AI22: 592.47549 | AJ22: 592.47549
B23: PHL_POW_PP_NGCC | H23: 71.3579 | I23: 71.3579 | J23: 71.3579 | K23: 71.3579 | L23: 71.3579 | M23: 71.3579 | N23: 71.3579 | O23: 71.3579 | P23: 71.3579 | Q23: 71.3579 | R23: 71.3579 | S23: 71.3579 | T23: 71.3579 | U23: 71.3579 | V23: 223.85146 | W23: 450.99133 | X23: 493.33598 | Y23: 539.7593 | Z23: 609.24538 | AA23: 654.91428 | AB23: 683.78508 | AC23: 750.29019 | AD23: 750.29019 | AE23: 750.29019 | AF23: 750.29019 | AG23: 815.71985 | AH23: 815.71985 | AI23: 840.08964 | AJ23: 1082.574
B24: PHL_POW_PP_NUSMR | S24: 106.32382 | T24: 558.57955 | U24: 1104.0659 | V24: 1409.7263 | W24: 1636.2562 | X24: 1795.7481 | Y24: 1966.1465 | Z24: 2081.518 | AA24: 2253.9602 | AB24: 2475.8748 | AC24: 2864.8021 | AD24: 3304.1085 | AE24: 3595.8298 | AF24: 4001.5823 | AG24: 4259.8242 | AH24: 4534.446 | AI24: 5033.2327 | AJ24: 5033.2327
B25: PHL_POW_PP_SPV_T1 | D25: 17.87676 | E25: 35.182747 | F25: 43.737239 | G25: 96.293446 | H25: 110.19144 | I25: 110.19144 | J25: 110.19144 | K25: 110.19144 | L25: 110.19144 | M25: 110.19144 | N25: 110.19144 | O25: 110.19144 | P25: 110.19144 | Q25: 377.05034 | R25: 377.05034 | S25: 559.70048 | T25: 559.70048 | U25: 559.70048 | V25: 559.70048 | W25: 559.70048 | X25: 559.70048 | Y25: 559.70048 | Z25: 574.23525 | AA25: 574.23525 | AB25: 574.23525 | AC25: 574.23525 | AD25: 574.23525 | AE25: 625.38534 | AF25: 629.99542 | AG25: 836.04599 | AH25: 886.65421 | AI25: 869.34822 | AJ25: 860.79373
B26: PHL_POW_PP_WON_T1 | C26: 24.191247 | D26: 39.44785 | E26: 39.44785 | F26: 41.740986 | G26: 41.740986 | H26: 41.740986 | I26: 41.740986 | J26: 41.740986 | K26: 41.740986 | L26: 41.740986 | M26: 41.740986 | N26: 41.740986 | O26: 41.740986 | P26: 41.740986 | Q26: 41.740986 | R26: 41.740986 | S26: 41.740986 | T26: 41.740986 | U26: 41.740986 | V26: 41.740986 | W26: 41.740986 | X26: 41.740986 | Y26: 41.740986 | Z26: 41.740986 | AA26: 41.740986 | AB26: 17.549739 | AC26: 2.2931361 | AD26: 2.2931361
B27: PHL_POW_TD | H27: 23.98163 | I27: 92.675423 | J27: 161.36922 | K27: 230.06301 | L27: 298.7568 | M27: 367.45059 | N27: 449.53951 | O27: 531.62842 | P27: 616.15981 | Q27: 701.26251 | R27: 787.26529 | S27: 890.31272 | T27: 993.35979 | U27: 1090.6442 | V27: 1193.4141 | W27: 1276.3321 | X27: 1376.5677 | Y27: 1484.8453 | Z27: 1593.3639 | AA27: 1702.1089 | AB27: 1811.0661 | AC27: 1923.9257 | AD27: 2036.9537 | AE27: 2150.1401 | AF27: 2263.4756 | AG27: 2425.5664 | AH27: 2533.8501 | AI27: 2642.4794 | AJ27: 2755.7569
B28: PHL_PRO_IMP_UR | S28: 0.0045 | T28: 0.0235 | U28: 0.0466 | V28: 0.0595 | W28: 0.0691 | X28: 0.0759 | Y28: 0.0832 | Z28: 0.0882 | AA28: 0.0956 | AB28: 0.1051 | AC28: 0.1219 | AD28: 0.1409 | AE28: 0.1535 | AF28: 0.1711 | AG28: 0.1824 | AH28: 0.1944 | AI28: 0.2163 | AJ28: 0.2163
B29: PHL_PRO_PROC_BIOF | C29: 634.46997 | D29: 654.58254 | E29: 675.7681 | F29: 693.69749 | G29: 716.53389 | H29: 731.96099 | I29: 749.67701 | J29: 762.14171 | K29: 774.64554 | L29: 787.00487 | M29: 787.00487 | N29: 787.00487 | O29: 799.60439 | P29: 823.20103 | Q29: 833.09511 | R29: 850.66198 | S29: 872.95596 | T29: 895.82956 | U29: 917.636 | V29: 938.38858 | W29: 957.64745 | X29: 990.80968 | Y29: 1024.1801 | Z29: 1057.4559 | AA29: 1089.5378 | AB29: 1109.2666 | AC29: 1144.2378 | AD29: 1179.1824 | AE29: 1213.4039 | AF29: 1245.0495 | AG29: 1268.6787 | AH29: 1302.6139 | AI29: 1335.6276 | AJ29: 1361.8135
B30: PHL_SER_HEAT_BIOM | C30: 182.57059 | D30: 182.57059 | E30: 182.57059 | F30: 182.57059 | G30: 182.57059 | H30: 182.57059 | I30: 182.57059 | J30: 182.57059 | K30: 182.57059 | L30: 182.57059 | M30: 182.57059 | N30: 182.57059 | O30: 182.57059 | P30: 182.57059 | Q30: 182.57059
B31: PHL_SER_HEAT_NG | D31: 105.83222 | E31: 131.25409 | F31: 132.11074 | G31: 163.39775 | H31: 163.39775 | I31: 175.0509 | J31: 201.95984 | K31: 213.86087 | L31: 281.64297 | M31: 294.28789 | N31: 306.63468 | O31: 447.94619 | P31: 726.73586 | Q31: 807.96877 | R31: 972.84492 | S31: 1009.5354 | T31: 1043.263 | U31: 1076.1438 | V31: 1110.1902 | W31: 1143.2336 | X31: 1197.9852 | Y31: 1253.4201 | Z31: 1308.3959 | AA31: 1365.4772 | AB31: 1420.6386 | AC31: 1489.3587 | AD31: 1562.3528 | AE31: 1639.5327 | AF31: 1710.4955 | AG31: 1785.7609 | AH31: 1874.2076 | AI31: 1959.6347 | AJ31: 2044.1665
B32: PHL_SER_HEAT_OIL | C32: 599.26102 | D32: 599.26102 | E32: 599.26102 | F32: 599.26102 | G32: 599.26102 | H32: 599.26102 | I32: 599.26102 | J32: 599.26102 | K32: 599.26102 | L32: 599.26102 | M32: 599.26102 | N32: 599.26102 | O32: 599.26102 | P32: 599.26102 | Q32: 599.26102
B33: PHL_SER_HEAT_RES | C33: 3421.7516
B34: PHL_TRA_23WHEEL_ELE | I34: 58.770347 | J34: 117.53738 | K34: 176.30773 | L34: 235.07477 | M34: 293.84511 | N34: 352.61215 | O34: 411.3825 | P34: 468.59962 | Q34: 525.45754 | R34: 581.74099 | S34: 638.37919 | T34: 695.0143 | U34: 759.56036 | V34: 816.57584 | W34: 918.08634 | X34: 931.50523 | Y34: 944.45713 | Z34: 957.39905 | AA34: 970.32793 | AB34: 983.23366 | AC34: 995.26813 | AD34: 1007.2961 | AE34: 1019.3216 | AF34: 1031.3358 | AG34: 1032.3816 | AH34: 1037.9886 | AI34: 1041.8203 | AJ34: 1021.8435
B35: PHL_TRA_23WHEEL_LIQ | C35: 4.7691084 | D35: 23.474643 | E35: 40.262561 | F35: 55.81406 | G35: 77.135003 | H35: 91.66175 | I35: 99.828025 | J35: 104.28424 | K35: 108.81919 | L35: 113.69162 | M35: 113.69162 | N35: 118.99879 | O35: 125.91004 | P35: 127.14384 | Q35: 127.14384 | R35: 122.37474 | S35: 103.6692 | T35: 86.881282 | U35: 74.172101 | V35: 57.765569 | W35: 51.730881 | X35: 50.202388 | Y35: 48.327851 | Z35: 46.790348 | AA35: 45.252844 | AB35: 45.252844 | AC35: 42.067438 | AD35: 39.731752 | AE35: 38.497947 | AF35: 38.497947 | AG35: 38.497947 | AH35: 38.502865 | AI35: 39.342272 | AJ35: 45.771964
B36: PHL_TRA_AVI_LIQ | D36: 104.7431 | E36: 212.20702 | F36: 319.67095 | G36: 421.59163 | H36: 528.65793 | I36: 651.38586 | J36: 771.87264 | K36: 885.85313 | L36: 1004.9254 | M36: 1127.3526 | N36: 1271.5447 | O36: 1410.2956 | P36: 1553.0458 | Q36: 1693.2005 | R36: 1829.8513 | S36: 1988.5369 | T36: 2147.5794 | U36: 2300.2603 | V36: 2492.7162 | W36: 2492.7162 | X36: 2660.0334 | Y36: 2798.6482 | Z36: 2913.757 | AA36: 3008.1852 | AB36: 3081.4028 | AC36: 3166.7153 | AD36: 3232.7421 | AE36: 3284.0212 | AF36: 3467.6864 | AG36: 3345.2592 | AH36: 3201.0671 | AI36: 3062.3162 | AJ36: 2919.5661
B37: PHL_TRA_BUS_LIQ | C37: 0.010915386 | D37: 21.273618 | E37: 33.363733 | F37: 55.035066 | G37: 67.338494 | H37: 89.412265 | I37: 101.74769 | J37: 123.92285 | K37: 136.46817 | L37: 158.90769 | M37: 171.93558 | N37: 197.0659 | O37: 211.04644 | P37: 235.98887 | Q37: 239.53291 | R37: 243.76522 | S37: 246.91431 | T37: 250.66959 | U37: 253.78153 | V37: 257.3749 | W37: 260.0937 | X37: 263.34073 | Y37: 266.04537 | Z37: 269.27371 | AA37: 271.78283 | AB37: 274.51255 | AC37: 276.71958 | AD37: 279.07102 | AE37: 281.25836 | AF37: 283.62343 | AG37: 285.84791 | AH37: 288.59173 | AI37: 290.76978 | AJ37: 293.25555
B38: PHL_TRA_CAR_ELE | AG38: 78.474766 | AH38: 140.38226 | AI38: 214.34185 | AJ38: 450.22562
B39: PHL_TRA_CAR_LIQ | C39: 47.200133 | D39: 181.40788 | E39: 316.13177 | F39: 450.07283 | G39: 585.70606 | H39: 721.71825 | I39: 861.0681 | J39: 999.47156 | K39: 1139.4647 | L39: 1279.7514 | M39: 1422.032 | N39: 1562.7688 | O39: 1704.9185 | P39: 1847.1371 | Q39: 1905.0929 | R39: 1965.2254 | S39: 2027.0755 | T39: 2088.5077 | U39: 2149.514 | V39: 2210.2368 | W39: 2270.9176 | X39: 2325.3194 | Y39: 2379.4242 | Z39: 2433.2773 | AA39: 2486.9086 | AB39: 2538.5907 | AC39: 2580.9132 | AD39: 2623.1632 | AE39: 2665.3754 | AF39: 2706.9713 | AG39: 2675.1667 | AH39: 2650.6194 | AI39: 2614.1838 | AJ39: 2419.2364
B40: PHL_TRA_RAILF_ELE | C40: 2.323214 | D40: 2.323214 | E40: 2.323214 | F40: 2.323214 | G40: 2.323214 | H40: 2.323214 | I40: 2.323214 | J40: 2.323214 | K40: 2.323214 | L40: 2.323214 | M40: 2.323214 | N40: 2.323214 | O40: 2.323214 | P40: 2.323214 | Q40: 2.323214 | R40: 2.323214 | S40: 2.323214 | T40: 2.323214 | U40: 2.323214 | V40: 2.323214
B41: PHL_TRA_RAILF_LIQ | E41: 1.2227442 | F41: 1.2227442 | G41: 2.4454884 | H41: 2.6163287 | I41: 3.8390728 | J41: 5.061817 | K41: 5.061817 | L41: 6.3982917 | M41: 7.6210359 | N41: 8.8437801 | O41: 8.8437801 | P41: 10.066524 | Q41: 11.451565 | R41: 12.674309 | S41: 14.899612 | T41: 16.121271 | U41: 16.671475 | V41: 19.113708 | W41: 22.00938 | X41: 23.232124 | Y41: 25.677613 | Z41: 28.123101 | AA41: 29.345845 | AB41: 31.791334 | AC41: 34.236822 | AD41: 36.68231 | AE41: 39.127799 | AF41: 41.573287 | AG41: 44.018775 | AH41: 47.687008 | AI41: 50.132496 | AJ41: 53.800729
B42: PHL_TRA_RAILP_ELE | C42: 2.323214 | D42: 2.323214 | E42: 2.323214 | F42: 2.323214 | G42: 2.323214 | H42: 2.323214 | I42: 2.323214 | J42: 2.323214 | K42: 2.323214 | L42: 2.323214 | M42: 2.323214 | N42: 2.323214 | O42: 2.323214 | P42: 2.323214 | Q42: 2.323214 | R42: 2.323214 | S42: 2.323214 | T42: 2.323214 | U42: 2.323214 | V42: 2.323214
B43: PHL_TRA_RAILP_LIQ | E43: 1.2227442 | F43: 1.2227442 | G43: 2.4454884 | H43: 2.6163287 | I43: 3.8390728 | J43: 3.8390728 | K43: 5.061817 | L43: 5.1755475 | M43: 6.3982917 | N43: 7.6210359 | O43: 7.6210359 | P43: 8.8437801 | Q43: 10.228821 | R43: 11.451565 | S43: 13.676868 | T43: 14.898527 | U43: 15.448731 | V43: 16.668219 | W43: 19.563892 | X43: 22.00938 | Y43: 23.232124 | Z43: 24.454868 | AA43: 26.900357 | AB43: 28.123101 | AC43: 30.568589 | AD43: 33.014078 | AE43: 35.459566 | AF43: 37.905054 | AG43: 40.350543 | AH43: 42.796031 | AI43: 45.24152 | AJ43: 48.909752
B44: PHL_TRA_SHIP_LIQ | D44: 1602006.3 | E44: 3204412.4 | F44: 4806787.9 | G44: 6407561 | H44: 8004007.7 | I44: 9725532.5 | J44: 11437407 | K44: 13132164 | L44: 14805350 | M44: 16544764 | N44: 18362007 | O44: 20179218 | P44: 21978288 | Q44: 23741646 | R44: 25463818 | S44: 27229196 | T44: 28931498 | U44: 30565708 | V44: 32602490 | W44: 32602490 | X44: 33952430 | Y44: 35007163 | Z44: 35796163 | AA44: 36347628 | AB44: 36688215 | AC44: 36842620 | AD44: 36820690 | AE44: 36646898 | AF44: 37711436 | AG44: 35972021 | AH44: 34154779 | AI44: 32337567 | AJ44: 30538497
B45: PHL_TRA_TRUH_LIQ | C45: 24.962268 | D45: 91.317432 | E45: 158.89242 | F45: 227.59307 | G45: 297.33362 | H45: 368.03571 | I45: 446.97959 | J45: 520.98412 | K45: 601.60614 | L45: 683.00856 | M45: 769.23305 | N45: 864.31159 | O45: 959.64849 | P45: 1055.3092 | Q45: 1106.9737 | R45: 1164.4692 | S45: 1241.4645 | T45: 1317.5568 | U45: 1392.9784 | V45: 1467.7144 | W45: 1542.7188 | X45: 1628.8011 | Y45: 1713.5898 | Z45: 1798.5766 | AA45: 1883.0659 | AB45: 1962.9878 | AC45: 2049.9082 | AD45: 2136.7139 | AE45: 2223.4807 | AF45: 2308.3842 | AG45: 2395.7724 | AH45: 2486.1156 | AI45: 2576.142 | AJ45: 2665.7961
B46: PHL_TRA_TRUL_LIQ | D46: 173.67997 | E46: 349.43166 | F46: 523.87773 | G46: 700.29704 | H46: 875.42706 | I46: 1070.0536 | J46: 1265.0144 | K46: 1458.717 | L46: 1654.2965 | M46: 1849.3856 | N46: 2065.121 | O46: 2279.5094 | P46: 2495.7794 | Q46: 2609.7393 | R46: 2723.7484 | S46: 2867.9538 | T46: 3012.0239 | U46: 3155.9917 | V46: 3299.8219 | W46: 3444.3758 | X46: 3612.2874 | Y46: 3779.9972 | Z46: 3947.589 | AA46: 4115.0684 | AB46: 4281.5083 | AC46: 4462.5904 | AD46: 4643.5918 | AE46: 4824.4944 | AF46: 5004.1388 | AG46: 5184.2819 | AH46: 5368.5962 | AI46: 5552.6014 | AJ46: 5736.3385
B47: PHL_TRA_VAN_LIQ | D47: 23.256166 | E47: 48.181696 | F47: 71.54048 | G47: 96.568931 | H47: 120.0193 | I47: 147.57016 | J47: 173.51267 | K47: 201.15578 | L47: 227.18062 | M47: 255.00569 | N47: 283.82013 | O47: 314.29307 | P47: 343.17102 | Q47: 358.84864 | R47: 374.51675 | S47: 394.33599 | T47: 414.15724 | U47: 433.94551 | V47: 453.732 | W47: 473.60078 | X47: 496.69897 | Y47: 519.73979 | Z47: 542.79675 | AA47: 565.82428 | AB47: 588.71594 | AC47: 613.60324 | AD47: 638.49533 | AE47: 663.37568 | AF47: 688.06864 | AG47: 712.83821 | AH47: 738.18236 | AI47: 763.48308 | AJ47: 788.73239

Sheet AnnualProduction
A1: PJ
A2: REGION | B2: TECHNOLOGY | C2: FUEL | D2: 2020 | E2: 2021 | F2: 2022 | G2: 2023 | H2: 2024 | I2: 2025 | J2: 2026 | K2: 2027 | L2: 2028 | M2: 2029 | N2: 2030 | O2: 2031 | P2: 2032 | Q2: 2033 | R2: 2034 | S2: 2035 | T2: 2036 | U2: 2037 | V2: 2038 | W2: 2039 | X2: 2040 | Y2: 2041 | Z2: 2042 | AA2: 2043 | AB2: 2044 | AC2: 2045 | AD2: 2046 | AE2: 2047 | AF2: 2048 | AG2: 2049 | AH2: 2050
A3: REGION | B3: PHL_POW_CHP_BIOM_OLD | D3: 4.5001 | E3: 5.2021 | F3: 4.7591 | G3: 5.0719 | H3: 5.2059
A4: REGION | B4: PHL_POW_CHP_COAL_OLD | D4: 209.448 | E4: 223.3868 | F4: 239.1476 | G4: 265.5136 | H4: 285.6922 | I4: 262.3083 | J4: 249.9901 | K4: 232.1301 | L4: 214.2802 | M4: 196.4197 | N4: 33.49 | O4: 59.0043 | P4: 85.2494 | Q4: 113.9312 | R4: 107.1399 | S4: 89.28 | T4: 71.4303 | U4: 53.57 | V4: 35.7098 | W4: 17.86
A5: REGION | B5: PHL_POW_CHP_NG_OLD | D5: 70.1998 | E5: 68.6159 | F5: 64.382 | G5: 60.0049 | H5: 64.9691 | I5: 1.1576 | J5: 1.62 | T5: 10.3516 | U5: 8.9188 | V5: 5.0988 | W5: 5.0703 | X5: 2.5324 | Y5: 2.5324 | Z5: 2.528 | AA5: 2.528 | AB5: 2.528 | AC5: 2.528
A6: REGION | B6: PHL_POW_CHP_OIL_OLD | D6: 8.8921 | E6: 5.818 | F6: 9.0678 | G6: 4.6939 | H6: 4.831
A7: REGION | B7: PHL_POW_GEO_OLD | D7: 38.8084 | E7: 36.0582 | F7: 37.5303 | G7: 38.628 | H7: 38.8398 | I7: 39.9666 | J7: 66.645 | K7: 66.645 | L7: 66.645 | M7: 66.645 | N7: 66.645 | O7: 66.645 | P7: 66.645 | Q7: 62.2308 | R7: 68.082 | S7: 126 | T7: 126 | U7: 126 | V7: 126 | W7: 126 | X7: 126 | Y7: 126 | Z7: 126 | AA7: 126 | AB7: 126 | AC7: 126 | AD7: 126 | AE7: 119.0511 | AF7: 109.1404 | AG7: 96.0306 | AH7: 97.048 | AI7: 92.0888 | AJ7: 71.656 | AK7: 126
A8: REGION | B8: PHL_POW_PP_COAL | I8: 66.0492 | J8: 66.0492 | K8: 112.7004 | L8: 159.1758 | M8: 205.4298 | N8: 398.2124 | O8: 406.441 | P8: 411.0452 | Q8: 416.484 | R8: 393.895 | S8: 379.9096 | T8: 355.4892 | U8: 339.8656 | V8: 314.0186 | W8: 305.9865 | X8: 304.8945 | Y8: 307.2876 | Z8: 309.8948 | AA8: 314.1471 | AB8: 316.7023 | AC8: 316.5696 | AD8: 296.4136 | AE8: 269.606 | AF8: 260.3628 | AG8: 250.334 | AH8: 222.8498 | AI8: 216.7281 | AJ8: 203.0843 | AK8: 168.6533
A9: REGION | B9: PHL_POW_PP_HY_LA | D9: 25.8852 | E9: 33.0659 | F9: 36.3061 | G9: 37.0338 | H9: 39.2718 | I9: 39.2718 | J9: 39.2718 | K9: 39.2718 | L9: 39.2718 | M9: 39.2718 | N9: 39.2718 | O9: 39.2718 | P9: 39.2718 | Q9: 39.2718 | R9: 39.2718 | S9: 39.2718 | T9: 39.2718 | U9: 39.2718 | V9: 39.2718 | W9: 39.2718 | X9: 39.2718 | Y9: 39.2718 | Z9: 39.2718 | AA9: 39.2718 | AB9: 39.2718 | AC9: 39.2718 | AD9: 39.2718 | AE9: 39.0986 | AF9: 39.1566 | AG9: 35.382 | AH9: 31.6074 | AI9: 31.6074 | AJ9: 28.8704 | AK9: 39.1566
A10: REGION | B10: PHL_POW_PP_NGCC | I10: 5.5228 | J10: 5.975 | K10: 4.0064 | L10: 0.8662 | S10: 0.2434 | T10: 17.6452 | U10: 15.841 | V10: 11.6244 | W10: 25.7394 | X10: 46.5067 | Y10: 52.2682 | Z10: 58.5658 | AA10: 68.9917 | AB10: 75.1544 | AC10: 78.1417 | AD10: 82.107 | AE10: 79.7835 | AF10: 76.931 | AG10: 74.5455 | AH10: 80.9455 | AI10: 78.2993 | AJ10: 80.9278 | AK10: 125.7479
A11: REGION | B11: PHL_POW_PP_NUSMR | T11: 16.9794 | U11: 89.385 | V11: 176.9316 | W11: 226.1034 | X11: 262.7172 | Y11: 288.5718 | Z11: 316.2672 | AA11: 335.064 | AB11: 363.2178 | AC11: 398.9236 | AD11: 460.3694 | AE11: 535.3578 | AF11: 583.3056 | AG11: 650.0808 | AH11: 670.3158 | AI11: 703.8012 | AJ11: 777.4734 | AK11: 743.057
A12: REGION | B12: PHL_POW_PP_SPV_T1 | D12: 4.9571 | E12: 5.2923 | F12: 6.559 | G12: 9.1579 | H12: 13.72 | I12: 17.0982 | J12: 17.0982 | K12: 17.0982 | L12: 17.0982 | M12: 17.0982 | N12: 17.0982 | O12: 17.0982 | P12: 17.0982 | Q12: 17.0982 | R12: 63.1514 | S12: 63.1514 | T12: 96.199 | U12: 96.199 | V12: 96.199 | W12: 96.199 | X12: 96.199 | Y12: 96.199 | Z12: 96.199 | AA12: 99.3986 | AB12: 99.273 | AC12: 98.8606 | AD12: 95.1824 | AE12: 94.6862 | AF12: 107.1146 | AG12: 107.9766 | AH12: 166.4102 | AI12: 184.2488 | AJ12: 182.5054 | AK12: 181.609
A13: REGION | B13: PHL_POW_PP_WON_T1 | D13: 3.708 | E13: 4.5722 | F13: 3.7082 | G13: 4.7092 | H13: 4.4602 | I13: 4.7092 | J13: 4.7092 | K13: 4.7092 | L13: 4.7092 | M13: 4.7092 | N13: 4.525 | O13: 4.525 | P13: 4.525 | Q13: 4.525 | R13: 4.525 | S13: 4.525 | T13: 4.525 | U13: 4.525 | V13: 4.525 | W13: 2.8334 | X13: 2.3318 | Y13: 2.3318 | Z13: 2.3318 | AA13: 2.3318 | AB13: 2.3318 | AC13: 1.001 | AD13: 0.1372 | AE13: 0.1372
A14: REGION | B14: PHL_PRO_BLEND_BIOF | D14: 440.9853 | E14: 453.4507 | F14: 466.2603 | G14: 477.2044 | H14: 491.5885 | I14: 501.2472 | J14: 511.7878 | K14: 519.1995 | L14: 526.6438 | M14: 534.1262 | N14: 517.4688 | O14: 528.6712 | P14: 539.4568 | Q14: 550.5117 | R14: 561.5612 | S14: 572.532 | T14: 586.4914 | U14: 600.1163 | V14: 613.531 | W14: 627.2889 | X14: 638.7741 | Y14: 660.2318 | Z14: 681.7217 | AA14: 703.2822 | AB14: 724.8963 | AC14: 746.5573 | AD14: 770.0235 | AE14: 793.5303 | AF14: 817.0943 | AG14: 840.6882 | AH14: 855.2609 | AI14: 878.3474 | AJ14: 900.8838 | AK14: 918.7748
A15: REGION | B15: PHL_PRO_BLEND_OIL | G15: 1.5247 | I15: 2.9256
A16: REGION | B16: PHL_PRO_EXTR_COAL | D16: 743.1913 | E16: 1159.6625 | F16: 1243.3869 | G16: 1329.9997 | H16: 1408.0054 | I16: 1492.4646 | J16: 1476.457 | K16: 1536.3958 | L16: 1595.7098 | M16: 1652.7744 | N16: 1587.9765 | O16: 1693.4257 | P16: 1795.2294 | Q16: 1842.3222
A17: REGION | B17: PHL_PRO_EXTR_NG | D17: 140.4442 | E17: 154.3177 | F17: 154.1851 | G17: 142.1441 | H17: 161.4981 | I17: 40.9207 | J17: 48.5465 | K17: 47.1998 | L17: 43.8466 | M17: 55.308 | N17: 56.4528 | O17: 58.6482 | P17: 85.0056 | Q17: 136.8083 | R17: 151.5174 | S17: 166.6433 | T17: 222.7032 | U17: 221.8628 | V17: 212.0779 | W17: 241.8552 | X17: 277.8725 | Y17: 296.4426 | Z17: 315.9498 | AA17: 342.696 | AB17: 361.9922 | AC17: 375.7419 | AD17: 388.3969 | AE17: 395.0496 | AF17: 400.7825 | AG17: 407.3389 | AH17: 426.9861 | AI17: 435.5076 | AJ17: 453.2581 | AK17: 544.8281
A18: REGION | B18: PHL_PRO_EXTR_OIL | D18: 75.3605 | F18: 0.6801 | H18: 0.5103 | K18: 9.5453 | L18: 20.9913 | M18: 24.0625 | N18: 33.7069 | O18: 45.3472 | P18: 34.5157
A19: REGION | B19: PHL_PRO_IMP_COAL | Q19: 65.2352 | R19: 1849.6669 | S19: 1773.5271 | T19: 1671.4767 | U19: 1589.5663 | V19: 1484.2084 | W19: 1419.7394 | X19: 1370.7954 | Y19: 1387.3201 | Z19: 1404.357 | AA19: 1425.1866 | AB19: 1442.1436 | AC19: 1452.9547 | AD19: 1418.7565 | AE19: 1369.3166 | AF19: 1360.1728 | AG19: 1349.2405 | AH19: 1296.5574 | AI19: 1295.4398 | AJ19: 1277.0714 | AK19: 1211.0263
A20: REGION | B20: PHL_PRO_IMP_OIL | D20: 184.5603 | E20: 172.2606 | F20: 159.95 | G20: 147.6504 | H20: 135.3399 | I20: 123.0397 | J20: 110.74 | K20: 98.4299 | L20: 86.1301 | M20: 73.8198 | N20: 61.52 | O20: 49.2201 | P20: 36.9101 | Q20: 24.6102 | R20: 12.2998
A21: REGION | B21: PHL_PRO_IMP_UR | T21: 44.6814 | U21: 235.2228 | V21: 465.609 | W21: 595.0098 | X21: 691.3638 | Y21: 759.402 | Z21: 832.284 | AA21: 881.7474 | AB21: 955.839 | AC21: 1049.7976 | AD21: 1211.498 | AE21: 1408.8354 | AF21: 1535.016 | AG21: 1710.7392 | AH21: 1763.9894 | AI21: 1852.11 | AJ21: 2045.9798 | AK21: 1955.4106
A22: REGION | B22: PHL_PRO_PROC_BIOF | D22: 440.9853 | E22: 453.4507 | F22: 466.2603 | G22: 477.2044 | H22: 491.5885 | I22: 501.2472 | J22: 511.7878 | K22: 519.1995 | L22: 526.6438 | M22: 534.1262 | N22: 517.4688 | O22: 528.6712 | P22: 539.4568 | Q22: 550.5117 | R22: 561.5612 | S22: 572.532 | T22: 586.4914 | U22: 600.1163 | V22: 613.531 | W22: 627.2889 | X22: 638.7741 | Y22: 660.2318 | Z22: 681.7217 | AA22: 703.2822 | AB22: 724.8963 | AC22: 746.5573 | AD22: 770.0235 | AE22: 793.5303 | AF22: 817.0943 | AG22: 840.6882 | AH22: 855.2609 | AI22: 878.3474 | AJ22: 900.8838 | AK22: 918.7748
A23: REGION | B23: PHL_PRO_PROC_BIOM | D23: 304.3034 | E23: 24.9987 | F23: 21.5038 | G23: 24.2076 | H23: 22.7928 | I23: 2.983 | J23: 3.0078 | K23: 1.8438 | L23: 1.8598 | X23: 0.0098
A24: REGION | B24: PHL_PRO_PROC_COAL | D24: 740.2595 | E24: 1155.088 | F24: 1238.4814 | G24: 1324.7535 | H24: 1402.4501 | I24: 1486.5768 | J24: 1470.6325 | K24: 1530.3352 | L24: 1589.4148 | M24: 1646.2538 | N24: 1581.712 | O24: 1686.7452 | P24: 1788.1476 | Q24: 1900.0315 | R24: 1842.3691 | S24: 1766.5306 | T24: 1664.8827 | U24: 1583.2952 | V24: 1478.3539 | W24: 1414.1386 | X24: 1365.3875 | Y24: 1381.8467 | Z24: 1398.8168 | AA24: 1419.5646 | AB24: 1436.454 | AC24: 1447.2232 | AD24: 1413.1588 | AE24: 1363.9146 | AF24: 1354.8066 | AG24: 1343.918 | AH24: 1291.4431 | AI24: 1290.3297 | AJ24: 1272.0339 | AK24: 1206.2487
A25: REGION | B25: PHL_PRO_PROC_NG | D25: 132.899 | E25: 146.0278 | F25: 145.9018 | G25: 134.508 | H25: 152.8223 | I25: 38.7224 | J25: 45.9386 | K25: 44.6646 | L25: 41.491 | M25: 52.3362 | N25: 53.4198 | O25: 55.4976 | P25: 80.4384 | Q25: 129.4589 | R25: 143.3781 | S25: 157.6909 | T25: 210.7385 | U25: 209.9439 | V25: 200.6845 | W25: 228.862 | X25: 262.9444 | Y25: 280.517 | Z25: 298.9764 | AA25: 324.2861 | AB25: 342.5448 | AC25: 355.5563 | AD25: 367.5313 | AE25: 373.8269 | AF25: 379.2514 | AG25: 385.4559 | AH25: 404.0476 | AI25: 412.1113 | AJ25: 428.9081 | AK25: 515.559
A26: REGION | B26: PHL_PRO_PROC_OIL | D26: 264.4028 | E26: 175.2305 | F26: 163.4002 | G26: 150.1957 | H26: 138.1932 | I26: 125.1618 | J26: 112.6502 | K26: 109.8376 | L26: 108.9687 | M26: 99.5705 | N26: 96.8691 | O26: 96.1982 | P26: 72.6577 | Q26: 25.0343 | R26: 12.5122

Sheet New Capacity
A1: GW
A2: REGION | B2: TECHNOLOGY | C2: 2020 | D2: 2021 | E2: 2022 | F2: 2023 | G2: 2024 | H2: 2025 | I2: 2026 | J2: 2027 | K2: 2028 | L2: 2029 | M2: 2030 | N2: 2031 | O2: 2032 | P2: 2033 | Q2: 2034 | R2: 2035 | S2: 2036 | T2: 2037 | U2: 2038 | V2: 2039 | W2: 2040 | X2: 2041 | Y2: 2042 | Z2: 2043 | AA2: 2044 | AB2: 2045 | AC2: 2046 | AD2: 2047 | AE2: 2048 | AF2: 2049 | AG2: 2050
A3: REGION | B3: PHL_AGR_FAC | C3: 999999 | D3: 999999 | E3: 999999 | F3: 999999 | G3: 999999 | H3: 999999 | I3: 999999 | J3: 999999 | K3: 999999 | L3: 999999 | M3: 999999 | N3: 999999 | O3: 999999 | P3: 999999 | Q3: 999999 | R3: 999999 | S3: 999999 | T3: 999999 | U3: 999999 | V3: 999999 | W3: 999999 | X3: 999999 | Y3: 999999 | Z3: 999999 | AA3: 999999 | AB3: 999999 | AC3: 999999 | AD3: 999999 | AE3: 999999 | AF3: 999999 | AG3: 999999 | AH3: 999999 | AI3: 999999 | AJ3: 999999
A4: REGION | B4: PHL_AGR_HEAT_BIOM | C4: 0.0039 | D4: 0 | E4: 0 | F4: 0 | G4: 0 | H4: 0 | I4: 0 | J4: 0 | K4: 0 | L4: 0 | M4: 0 | N4: 0 | O4: 0 | P4: 0 | Q4: 0 | R4: 0 | S4: 0 | T4: 0 | U4: 0 | V4: 0 | W4: 0 | X4: 0 | Y4: 0 | Z4: 0 | AA4: 0 | AB4: 0 | AC4: 0 | AD4: 0 | AE4: 0 | AF4: 0 | AG4: 0 | AH4: 0 | AI4: 0 | AJ4: 0
A5: REGION | B5: PHL_AGR_HEAT_COAL | C5: 0 | D5: 0 | E5: 0 | F5: 0 | G5: 0 | H5: 0 | I5: 0 | J5: 0 | K5: 0 | L5: 0 | M5: 0 | N5: 0 | O5: 0 | P5: 0 | Q5: 0 | R5: 0 | S5: 0 | T5: 0 | U5: 0 | V5: 0 | W5: 0 | X5: 0 | Y5: 0 | Z5: 0 | AA5: 0 | AB5: 0 | AC5: 0 | AD5: 0 | AE5: 0 | AF5: 0 | AG5: 0 | AH5: 0 | AI5: 0 | AJ5: 0
A6: REGION | B6: PHL_AGR_HEAT_ELE | C6: 0 | D6: 0 | E6: 0 | F6: 0 | G6: 0 | H6: 0 | I6: 0 | J6: 0 | K6: 0 | L6: 0 | M6: 0 | N6: 0 | O6: 0 | P6: 0 | Q6: 0 | R6: 0 | S6: 0 | T6: 0 | U6: 0 | V6: 0 | W6: 0 | X6: 0 | Y6: 0 | Z6: 0 | AA6: 0 | AB6: 0 | AC6: 0 | AD6: 0 | AE6: 0 | AF6: 0 | AG6: 0 | AH6: 0 | AI6: 0 | AJ6: 0
A7: REGION | B7: PHL_AGR_HEAT_NG | C7: 0.315 | D7: 0.0129 | E7: 0.0089 | F7: 0.0089 | G7: 0.0089 | H7: 0.0089 | I7: 0.0096 | J7: 0.0096 | K7: 0.0096 | L7: 0.0096 | M7: 0.0096 | N7: 0.0108 | O7: 0.0108 | P7: 0.0108 | Q7: 0.0108 | R7: 0.0108 | S7: 0.0127 | T7: 0.0127 | U7: 0.0127 | V7: 0.0127 | W7: 0.0088 | X7: 0 | Y7: 0 | Z7: 0 | AA7: 0 | AB7: 0.1645 | AC7: 0 | AD7: 0 | AE7: 0 | AF7: 0 | AG7: 0.3935 | AH7: 0.0273 | AI7: 0.0273 | AJ7: 0.0273
A8: REGION | B8: PHL_AGR_HEAT_OIL | C8: 0.0375 | D8: 0 | E8: 0 | F8: 0 | G8: 0 | H8: 0 | I8: 0 | J8: 0 | K8: 0 | L8: 0 | M8: 0 | N8: 0 | O8: 0 | P8: 0 | Q8: 0 | R8: 0 | S8: 0 | T8: 0 | U8: 0 | V8: 0 | W8: 0 | X8: 0 | Y8: 0 | Z8: 0 | AA8: 0 | AB8: 0 | AC8: 0 | AD8: 0 | AE8: 0 | AF8: 0 | AG8: 0 | AH8: 0 | AI8: 0 | AJ8: 0
A9: REGION | B9: PHL_AGR_MOT_ELE | C9: 0 | D9: 0 | E9: 0 | F9: 0 | G9: 0 | H9: 0 | I9: 0 | J9: 0 | K9: 0 | L9: 0 | M9: 0 | N9: 0 | O9: 0 | P9: 0 | Q9: 0 | R9: 0 | S9: 0 | T9: 0 | U9: 0 | V9: 0 | W9: 0 | X9: 0 | Y9: 0 | Z9: 0 | AA9: 0 | AB9: 0 | AC9: 0 | AD9: 0 | AE9: 0 | AF9: 0 | AG9: 0 | AH9: 0 | AI9: 0 | AJ9: 0
A10: REGION | B10: PHL_AGR_MOT_LIQ | C10: 250.36 | D10: 6.491 | E10: 6.491 | F10: 6.491 | G10: 6.491 | H10: 6.491 | I10: 6.982 | J10: 6.982 | K10: 6.982 | L10: 6.982 | M10: 6.982 | N10: 7.8423 | O10: 7.8423 | P10: 7.8423 | Q10: 7.2258 | R10: 257.5417 | S10: 15.0351 | T10: 15.0351 | U10: 15.0351 | V10: 15.0351 | W10: 15.0351 | X10: 16.927 | Y10: 16.927 | Z10: 16.927 | AA10: 16.927 | AB10: 16.927 | AC10: 19.1819 | AD10: 19.1819 | AE10: 19.1818 | AF10: 18.5653 | AG10: 268.8812 | AH10: 27.5023 | AI10: 27.5023 | AJ10: 27.5023
A11: REGION | B11: PHL_AGR_UNIT | C11: 999999 | D11: 999999 | E11: 999999 | F11: 999999 | G11: 999999 | H11: 999999 | I11: 999999 | J11: 999999 | K11: 999999 | L11: 999999 | M11: 999999 | N11: 999999 | O11: 999999 | P11: 999999 | Q11: 999999 | R11: 999999 | S11: 999999 | T11: 999999 | U11: 999999 | V11: 999999 | W11: 999999 | X11: 999999 | Y11: 999999 | Z11: 999999 | AA11: 999999 | AB11: 999999 | AC11: 999999 | AD11: 999999 | AE11: 999999 | AF11: 999999 | AG11: 999999 | AH11: 999999 | AI11: 999999 | AJ11: 999999
A12: REGION | B12: PHL_DEM_PUB_GWT_WAT | C12: 999999 | D12: 999999 | E12: 999999 | F12: 999999 | G12: 999999 | H12: 999999 | I12: 999999 | J12: 999999 | K12: 999999 | L12: 999999 | M12: 999999 | N12: 999999 | O12: 999999 | P12: 999999 | Q12: 999999 | R12: 999999 | S12: 999999 | T12: 999999 | U12: 999999 | V12: 999999 | W12: 999999 | X12: 999999 | Y12: 999999 | Z12: 999999 | AA12: 999999 | AB12: 999999 | AC12: 999999 | AD12: 999999 | AE12: 999999 | AF12: 999999 | AG12: 999999 | AH12: 999999 | AI12: 999999 | AJ12: 999999
A13: REGION | B13: PHL_DEM_PUB_SUR_WAT | C13: 999999 | D13: 999999 | E13: 999999 | F13: 999999 | G13: 999999 | H13: 999999 | I13: 999999 | J13: 999999 | K13: 999999 | L13: 999999 | M13: 999999 | N13: 999999 | O13: 999999 | P13: 999999 | Q13: 999999 | R13: 999999 | S13: 999999 | T13: 999999 | U13: 999999 | V13: 999999 | W13: 999999 | X13: 999999 | Y13: 999999 | Z13: 999999 | AA13: 999999 | AB13: 999999 | AC13: 999999 | AD13: 999999 | AE13: 999999 | AF13: 999999 | AG13: 999999 | AH13: 999999 | AI13: 999999 | AJ13: 999999
A14: REGION | B14: PHL_DEM_PWR_GWT_WAT | C14: 999999 | D14: 999999 | E14: 999999 | F14: 999999 | G14: 999999 | H14: 999999 | I14: 999999 | J14: 999999 | K14: 999999 | L14: 999999 | M14: 999999 | N14: 999999 | O14: 999999 | P14: 999999 | Q14: 999999 | R14: 999999 | S14: 999999 | T14: 999999 | U14: 999999 | V14: 999999 | W14: 999999 | X14: 999999 | Y14: 999999 | Z14: 999999 | AA14: 999999 | AB14: 999999 | AC14: 999999 | AD14: 999999 | AE14: 999999 | AF14: 999999 | AG14: 999999 | AH14: 999999 | AI14: 999999 | AJ14: 999999
... A133: REGION | B133: PHL_TRA_VAN_NG | C133: 0 | D133: 0 | E133: 0 | F133: 0 | G133: 0 | H133: 0 | I133: 0 | J133: 0 | K133: 0 | L133: 0 | M133: 0 | N133: 0 | O133: 0 | P133: 0 | Q133: 0 | R133: 0 | S133: 0 | T133: 0 | U133: 0 | V133: 0 | W133: 0 | X133: 0 | Y133: 0 | Z133: 0 | AA133: 0 | AB133: 0 | AC133: 0 | AD133: 0 | AE133: 0 | AF133: 0 | AG133: 0 | AH133: 0 | AI133: 0 | AJ133: 0
B134: PHL_TRA_VAN_PHEV | C134: 0 | D134: 0 | E134: 0 | F134: 0 | G134: 0 | H134: 0 | I134: 0 | J134: 0 | K134: 0 | L134: 0 | M134: 0 | N134: 0 | O134: 0 | P134: 0 | Q134: 0 | R134: 0 | S134: 0 | T134: 0 | U134: 0 | V134: 0 | W134: 0 | X134: 0 | Y134: 0 | Z134: 0 | AA134: 0 | AB134: 0 | AC134: 0 | AD134: 0 | AE134: 0 | AF134: 0 | AG134: 0 | AH134: 0 | AI134: 0 | AJ134: 0
B135: (blank)

Sheet UseByTech
A1: REGION | B1: TECHNOLOGY | C1: 2020 | D1: 2021 | E1: 2022 | F1: 2023 | G1: 2024 | H1: 2025 | I1: 2026 | J1: 2027 | K1: 2028 | L1: 2029 | M1: 2030 | N1: 2031 | O1: 2032 | P1: 2033 | Q1: 2034 | R1: 2035 | S1: 2036 | T1: 2037 | U1: 2038 | V1: 2039 | W1: 2040 | X1: 2041 | Y1: 2042 | Z1: 2043 | AA1: 2044 | AB1: 2045 | AC1: 2046 | AD1: 2047 | AE1: 2048 | AF1: 2049 | AG1: 2050
A2: REGION | B2: PHL_AGR_FAC | C2: 9.2938 | D2: 9.5034 | E2: 9.7123 | F2: 9.9217 | G2: 10.1309 | H2: 10.3402 | I2: 10.567 | J2: 10.794 | K2: 11.0206 | L2: 11.2478 | M2: 11.4744 | N2: 11.7322 | O2: 11.9903 | P2: 12.2473 | Q2: 12.5055 | R2: 12.763 | S2: 13.0696 | T2: 13.376 | U2: 13.6828 | V2: 13.9894 | W2: 14.2957 | X2: 11.2971 | Y2: 10.4153 | Z2: 9.5967 | AA2: 8.8376 | AB2: 8.134 | AC2: 7.506 | AD2: 6.9223 | AE2: 6.38 | AF2: 5.8771 | AG2: 18.1149 | AH2: 18.562 | AI2: 19.01 | AJ2: 19.457
A3: REGION | B3: PHL_AGR_HEAT_BIOM | C3: 0.139 | W3: 0.0098
A4: REGION | B4: PHL_AGR_MOT_LIQ | C4: 19.7328 | D4: 20.1771 | E4: 20.6217 | F4: 21.0655 | G4: 21.5095 | H4: 21.9541 | I4: 22.4358 | J4: 22.9171 | K4: 23.399 | L4: 23.8804 | M4: 24.3619 | N4: 24.909 | O4: 25.4562 | P4: 26.0035 | Q4: 26.5506 | R4: 27.0979 | S4: 27.7494 | T4: 28.4001 | U4: 29.051 | V4: 29.7018 | W4: 30.3527 | X4: 31.1107 | Y4: 31.8683 | Z4: 32.6257 | AA4: 33.3837 | AB4: 34.1412 | AC4: 35.0049 | AD4: 35.8695 | AE4: 36.7331 | AF4: 37.5974 | AG4: 38.4615 | AH4: 39.4112 | AI4: 40.3609 | AJ4: 41.3108
A5: REGION | B5: PHL_AGR_UNIT | C5: 18.1607 | D5: 18.57 | E5: 18.978 | F5: 19.3877 | G5: 19.7957 | H5: 20.2051 | I5: 20.6478 | J5: 21.0917 | K5: 21.5346 | L5: 21.978 | M5: 22.4216 | N5: 22.9249 | O5: 23.4292 | P5: 23.9321 | Q5: 24.4359 | R5: 24.9393 | S5: 25.5384 | T5: 26.1368 | U5: 26.7365 | V5: 27.3358 | W5: 27.9346 | X5: 23.7809 | Y5: 21.9246 | Z5: 20.2013 | AA5: 18.604 | AB5: 17.1227 | AC5: 15.8008 | AD5: 14.5714 | AE5: 13.43 | AF5: 12.3713 | AG5: 35.3972 | AH5: 36.2709 | AI5: 37.1461 | AJ5: 38.0196
A6: REGION | B6: PHL_DEM_PUB_GWT_WAT | J6: 1.1513 | Q6: 2.8247 | R6: 3.0193 | W6: 6.5211 | AG6: 0.0647 | AI6: 2.1659
A7: REGION | B7: PHL_DEM_PUB_SUR_WAT | C7: 19.62 | D7: 20.3701 | E7: 21.1479 | F7: 21.9549 | G7: 22.794 | H7: 23.665 | I7: 24.568 | J7: 24.3547 | K7: 26.479 | L7: 27.4889 | M7: 28.536 | N7: 29.6219 | O7: 30.7491 | P7: 31.917 | Q7: 30.303 | R7: 31.3638 | S7: 35.6851 | T7: 37.0331 | U7: 38.43 | V7: 39.878 | W7: 34.8557 | X7: 42.93 | Y7: 44.539 | Z7: 46.204 | AA7: 47.927 | AB7: 49.711 | AC7: 51.5559 | AD7: 53.465 | AE7: 55.439 | AF7: 57.481 | AG7: 59.5272 | AH7: 61.7731 | AI7: 61.8622 | AJ7: 66.359
A8: REGION | B8: PHL_DEM_PWR_GWT_WAT | C8: 1.0758 | D8: 4.9311 | E8: 4.9377 | F8: 4.9445 | G8: 4.9518 | H8: 3.5785 | I8: 4.2703 | J8: 3.824 | K8: 4.9838 | L8: 4.9924 | M8: 1.706 | N8: 5.0105 | O8: 5.0804 | P8: 5.3786 | Q8: 2.5235 | R8: 2.2916 | S8: 6.5729 | T8: 11.911 | U8: 18.3112 | V8: 22.0254 | W8: 18.3393 | X8: 26.9729 | Y8: 29.2311 | Z8: 30.8545 | AA8: 33.1576 | AB8: 36.0044 | AC8: 40.6626 | AD8: 46.2875 | AE8: 49.9983 | AF8: 55.114 | AG8: 56.6462 | AH8: 59.3846 | AI8: 62.8658 | AJ8: 62.6704
A9: REGION | B9: PHL_DEM_PWR_SUR_WAT | C9: 21.3455 | D9: 17.3109 | E9: 19.1827 | F9: 18.401 | G9: 19.7772 | H9: 13.0397 | I9: 11.7595 | J9: 13.5377 | K9: 13.7149 | L9: 15.1 | M9: 19.8792 | N9: 18.2614 | O9: 19.7344 | P9: 21.1419 | Q9: 22.5279 | R9: 21.1751 | S9: 27.6678 | T9: 71.9667 | U9: 125.2982 | V9: 155.6247 | W9: 184.9066 | X9: 194.9216 | Y9: 212.6464 | Z9: 224.8941 | AA9: 242.8933 | AB9: 265.4795 | AC9: 303.4836 | AD9: 349.6905 | AE9: 379.4744 | AF9: 421.1964 | AG9: 432.8487 | AH9: 453.5002 | AI9: 501.722 | AJ9: 477.105
A10: REGION | B10: PHL_HOU_COOK_BIOM | C10: 236.7198
A11: REGION | B11: PHL_HOU_COOK_COAL | D11: 240.4152 | E11: 244.1082 | F11: 247.8036 | G11: 251.5944 | H11: 258.486 | I11: 270.2598 | J11: 273.9132 | K11: 277.3344 | L11: 279.0696 | M11: 279.0696 | N11: 279.0696 | O11: 281.4378 | P11: 284.7414 | Q11: 293.8968 | R11: 299.9736 | S11: 302.8314 | T11: 305.6886 | U11: 308.5488 | V11: 311.4054 | W11: 314.265 | X11: 316.8042 | Y11: 319.3416 | Z11: 321.882 | AA11: 324.4212 | AB11: 326.9604 | AC11: 329.1576 | AD11: 331.3548 | AE11: 333.5526 | AF11: 335.7498 | AG11: 337.947 | AH11: 339.8424 | AI11: 341.7378 | AJ11: 343.6332
A12: REGION | B12: PHL_HOU_COOK_ELE | C12: 12.3456 | D12: 12.2502 | E12: 12.1566 | F12: 12.0612 | G12: 11.8716 | H12: 8.5812 | I12: 0.2294 | L12: 1.6878 | M12: 5.111 | N12: 8.2686 | O12: 9.0594 | P12: 8.9156 | Q12: 2.9176
A13: REGION | B13: PHL_HOU_UNIT | C13: 111.1048 | D13: 119.1777 | E13: 127.2505 | F13: 135.3235 | G13: 143.3961 | H13: 151.4688 | I13: 161.4651 | J13: 171.4613 | K13: 181.4575 | L13: 191.4534 | M13: 201.45 | N13: 213.1986 | O13: 224.9475 | P13: 236.6964 | Q13: 248.4452 | R13: 260.1939 | S13: 274.0119 | T13: 287.8296 | U13: 301.6478 | V13: 315.4657 | W13: 329.2837 | X13: 344.1332 | Y13: 358.983 | Z13: 373.8324 | AA13: 388.6818 | AB13: 403.5315 | AC13: 417.664 | AD13: 431.7965 | AE13: 445.929 | AF13: 460.0612 | AG13: 474.1937 | AH13: 485.8335 | AI13: 497.4735 | AJ13: 509.1135
A14: REGION | B14: PHL_INDU_OTHHPH_BIOM | C14: 16.8858
A15: REGION | B15: PHL_INDU_OTHHPH_COAL | C15: 41.3646 | D15: 119.19 | E15: 121.8012 | F15: 121.704 | G15: 126.9846 | H15: 126.8652 | I15: 132.342 | J15: 135.1158 | K15: 137.8782 | L15: 140.6328 | M15: 143.9136 | N15: 146.982 | O15: 150.0432 | P15: 153.1014 | Q15: 156.1542 | R15: 159.2046 | S15: 162.8628 | T15: 166.521 | U15: 170.1768 | V15: 173.8338 | W15: 177.3096 | X15: 181.5366 | Y15: 185.7738 | Z15: 190.0218 | AA15: 194.2782 | AB15: 198.5454 | AC15: 203.4354 | AD15: 208.3344 | AE15: 213.2406 | AF15: 218.1504 | AG15: 222.207 | AH15: 227.6958 | AI15: 233.1828 | AJ15: 238.6716
A16: REGION | B16: PHL_INDU_OTHHPH_NG | C16: 0.8112
A17: REGION | B17: PHL_INDU_OTHHPH_OIL | C17: 54.42 | F17: 2.5452 | H17: 2.5392
A18: REGION | B18: PHL_INDU_OTHLPH_BIOM | C18: 16.8858
A19: REGION | B19: PHL_INDU_OTHLPH_COAL | C19: 41.3646 | D19: 94.194 | E19: 121.8012 | F19: 121.704 | G19: 126.9846 | H19: 126.8652 | I19: 132.342 | J19: 135.1158 | K19: 137.8782 | L19: 140.6328 | M19: 143.9136 | N19: 146.982 | O19: 150.0432 | P19: 153.1014 | Q19: 156.1542 | R19: 159.2046 | S19: 162.8628 | T19: 166.521 | U19: 170.1768 | V19: 173.8338 | W19: 177.3096 | X19: 181.5366 | Y19: 185.7738 | Z19: 190.0218 | AA19: 194.2782 | AB19: 198.5454 | AC19: 203.4354 | AD19: 208.3344 | AE19: 213.2406 | AF19: 218.1504 | AG19: 222.207 | AH19: 227.6958 | AI19: 233.1828 | AJ19: 238.6716
A20: REGION | B20: PHL_INDU_OTHLPH_NG | C20: 0.8112
A21: REGION | B21: PHL_INDU_OTHLPH_OIL | C21: 54.42 | D21: 23.6436 | F21: 2.5452 | H21: 2.5392
A22: REGION | B22: PHL_INDU_PLANT_OTH | C22: 299.5284 | D22: 306.2718 | E22: 313.0146 | F22: 319.7562 | G22: 326.4996 | H22: 333.2436 | I22: 340.5516 | J22: 347.8626 | K22: 355.173 | L22: 362.4852 | M22: 369.7932 | N22: 378.0996 | O22: 386.4072 | P22: 394.7136 | Q22: 403.0176 | R22: 411.324 | S22: 421.206 | T22: 431.0868 | U22: 440.9676 | V22: 450.8526 | W22: 460.7298 | X22: 472.2306 | Y22: 483.7332 | Z22: 495.2352 | AA22: 506.7366 | AB22: 518.2398 | AC22: 531.3516 | AD22: 544.4682 | AE22: 557.58 | AF22: 570.696 | AG22: 583.8102 | AH22: 598.2288 | AI22: 612.645 | AJ22: 627.0654
A23: REGION | B23: PHL_LND_BLT | C23: 8.1778 | D23: 8.4837 | E23: 8.8009 | F23: 9.1301 | G23: 9.4716 | H23: 9.8259 | I23: 10.1933 | J23: 10.5746 | K23: 10.9701 | L23: 11.3803 | M23: 11.806 | N23: 12.2475 | O23: 12.7057 | P23: 13.1807 | Q23: 13.6737 | R23: 14.185 | S23: 14.7156 | T23: 15.266 | U23: 15.8369 | V23: 16.4293 | W23: 17.0436 | X23: 17.6812 | Y23: 18.3424 | Z23: 19.0284 | AA23: 19.7401 | AB23: 20.4783 | AC23: 21.2443 | AD23: 22.0388 | AE23: 22.8631 | AF23: 23.7181 | AG23: 24.6051 | AH23: 25.5253 | AI23: 26.4801 | AJ23: 27.4704
A24: REGION | B24: PHL_LND_FOR | C24: 142503.75 | D24: 168.658 | E24: 168.6578 | F24: 168.6578 | G24: 168.6578 | H24: 168.6581 | I24: 168.6579 | J24: 168.6579 | K24: 168.6581 | L24: 168.6581 | M24: 168.6579 | N24: 168.658 | O24: 168.658 | P24: 168.6581 | Q24: 168.658 | R24: 168.6581 | S24: 168.6576 | T24: 168.6579 | U24: 168.6579 | V24: 168.658 | W24: 168.658 | X24: 168.6579 | Y24: 168.6579 | Z24: 168.6579 | AA24: 168.6579 | AB24: 168.6578 | AC24: 168.6578 | AD24: 168.6579 | AE24: 168.6578 | AF24: 168.6578 | AG24: 168.6579 | AH24: 168.6579 | AI24: 168.6579 | AJ24: 168.6579
A25: REGION | B25: PHL_LND_OTH | C25: 5.1489 | D25: 5.1489 | E25: 5.1489 | F25: 5.1489 | G25: 5.1489 | H25: 5.1489 | I25: 5.1489 | J25: 5.1489 | K25: 5.1489 | L25: 5.1489 | M25: 5.1488 | N25: 5.1489 | O25: 5.1488 | P25: 5.1489 | Q25: 5.1488 | R25: 5.1489 | S25: 5.1489 | T25: 5.1489 | U25: 5.1489 | V25: 5.1489 | W25: 5.1489 | X25: 5.1489 | Y25: 5.1489 | Z25: 5.1489 | AA25: 5.1489 | AB25: 5.1489 | AC25: 5.1489 | AD25: 5.1489 | AE25: 5.1489 | AF25: 5.1489 | AG25: 5.1489 | AH25: 5.1489 | AI25: 5.1489 | AJ25: 5.1489
A26: REGION | B26: PHL_LND_WAT | C26: 34.6876 | D26: 34.6876 | E26: 34.6872 | F26: 34.6875 | G26: 34.6873 | H26: 34.6877 | I26: 34.6876 | J26: 34.688 | K26: 34.6877 | L26: 34.6876 | M26: 34.6877 | N26: 34.6873 | O26: 35.9038 | P26: 41.7543 | Q26: 40.933 | R26: 39.9486 | S26: 65.3412 | T26: 173.4807 | U26: 303.1854 | V26: 378.3423 | W26: 435.6329 | X26: 478.2504 | Y26: 523.8104 | Z26: 556.476 | AA26: 602.9307 | AB26: 660.4132 | AC26: 754.6553 | AD26: 868.5236 | AE26: 943.5096 | AF26: 1047.0038 | AG26: 1079.0472 | AH26: 1132.9264 | AI26: 1247.1675 | AJ26: 1198.802
A27: REGION | B27: PHL_POW_CHP_BIOM_OLD | C27: 18.003 | D27: 20.8113 | E27: 19.0392 | F27: 20.2913 | G27: 20.8274
A28: REGION | B28: PHL_POW_CHP_COAL_OLD | C28: 657.5302 | D28: 701.2893 | E28: 750.769 | F28: 833.541 | G28: 896.8864 | H28: 823.4779 | I28: 784.806 | J28: 728.7368 | K28: 672.6995 | L28: 616.6304 | M28: 105.1367 | N28: 185.2344 | O28: 267.6274 | P28: 357.6703 | Q28: 336.3501 | R28: 280.2808 | S28: 224.2439 | T28: 168.1747 | U28: 112.1061 | V28: 56.0688
A29: REGION | B29: PHL_POW_CHP_NG_OLD | C29: 131.277 | D29: 128.3149 | E29: 120.397 | F29: 112.2118 | G29: 121.4947 | H29: 2.1646 | I29: 3.0294 | S29: 19.3575 | T29: 16.6781 | U29: 9.5344 | V29: 9.4815 | W29: 4.7356 | X29: 4.7356 | Y29: 4.7272 | Z29: 4.7272 | AA29: 4.7272 | AB29: 4.7272
A30: REGION | B30: PHL_POW_CHP_OIL_OLD | C30: 46.3982 | D30: 30.3582 | E30: 47.3166 | F30: 24.4932 | G30: 25.2079
A31: REGION | B31: PHL_POW_PP_COAL | H31: 150.882 | I31: 150.882 | J31: 257.4552 | K31: 363.6222 | L31: 469.2852 | M31: 909.6785 | N31: 928.4759 | O31: 938.993 | P31: 951.4182 | Q31: 899.8152 | R31: 867.8666 | S31: 812.081 | T31: 776.3902 | U31: 717.3452 | V31: 698.9973 | W31: 696.5017 | X31: 701.9693 | Y31: 707.9255 | Z31: 717.639 | AA31: 723.4766 | AB31: 723.1728 | AC31: 677.1296 | AD31: 615.8906 | AE31: 594.7752 | AF31: 571.8655 | AG31: 509.0807 | AH31: 495.0958 | AI31: 463.929 | AJ31: 385.272
A32: REGION | B32: PHL_POW_PP_NGCC | H32: 9.1434 | I32: 9.8918 | J32: 6.6334 | K32: 1.434 | R32: 0.4024 | S32: 29.2122 | T32: 26.2254 | U32: 19.2448 | V32: 42.6147 | W32: 76.9975 | X32: 86.5365 | Y32: 96.9634 | Z32: 114.2246 | AA32: 124.4278 | AB32: 129.3735 | AC32: 135.9382 | AD32: 132.0916 | AE32: 127.3688 | AF32: 123.4196 | AG32: 134.0162 | AH32: 129.6346 | AI32: 133.9864 | AJ32: 208.1918
A33: REGION | B33: PHL_POW_PP_NUSMR | S33: 44.6814 | T33: 235.2228 | U33: 465.609 | V33: 595.0098 | W33: 691.3638 | X33: 759.4008 | Y33: 832.284 | Z33: 881.7474 | AA33: 955.8378 | AB33: 1049.7976 | AC33: 1211.498 | AD33: 1408.8354 | AE33: 1535.016 | AF33: 1710.7392 | AG33: 1763.9894 | AH33: 1852.11 | AI33: 2045.9798 | AJ33: 1955.4106
A34: REGION | B34: PHL_POW_TD | C34: 366.3974 | D34: 366.5515 | E34: 384.9479 | F34: 403.3447 | G34: 421.6239 | H34: 436.0827 | I34: 451.3581 | J34: 476.5626 | K34: 502.0472 | L34: 529.5746 | M34: 559.243 | N34: 592.986 | O34: 623.8354 | P34: 653.5414 | Q34: 676.0647 | R34: 702.3803 | S34: 737.8892 | T34: 773.574 | U34: 809.3776 | V34: 845.064 | W34: 880.4544 | X34: 914.4631 | Y34: 951.0595 | Z34: 987.733 | AA34: 1024.4799 | AB34: 1061.2951 | AC34: 1099.4809 | AD34: 1137.7199 | AE34: 1176.0116 | AF34: 1214.3498 | AG34: 1269.1771 | AH34: 1306.7747 | AI34: 1344.5173 | AJ34: 1384.2229
A35: REGION | B35: PHL_POW_TD_AGR | C35: 9.2938 | D35: 9.5034 | E35: 9.7123 | F35: 9.9217 | G35: 10.1309 | H35: 10.3402 | I35: 10.567 | J35: 10.794 | K35: 11.0206 | L35: 11.2478 | M35: 11.4744 | N35: 11.7322 | O35: 11.9903 | P35: 12.2473 | Q35: 12.5055 | R35: 12.763 | S35: 13.0696 | T35: 13.376 | U35: 13.6828 | V35: 13.9894 | W35: 14.2957 | X35: 11.2971 | Y35: 10.4153 | Z35: 9.5967 | AA35: 8.8376 | AB35: 8.134 | AC35: 7.506 | AD35: 6.9223 | AE35: 6.38 | AF35: 5.8771 | AG35: 18.1149 | AH35: 18.562 | AI35: 19.01 | AJ35: 19.457
A36: REGION | B36: PHL_POW_TD_HOU | C36: 123.45 | D36: 131.4285 | E36: 139.4069 | F36: 147.3856 | G36: 155.2681 | H36: 160.05 | I36: 161.6946 | J36: 171.4613 | K36: 181.4575 | L36: 193.1412 | M36: 206.5606 | N36: 221.4673 | O36: 234.0069 | P36: 245.6114 | Q36: 251.3628 | R36: 260.1939 | S36: 274.0119 | T36: 287.8296 | U36: 301.6478 | V36: 315.4657 | W36: 329.2837 | X36: 344.1332 | Y36: 358.983 | Z36: 373.8324 | AA36: 388.6818 | AB36: 403.5315 | AC36: 417.664 | AD36: 431.7965 | AE36: 445.929 | AF36: 460.0612 | AG36: 474.1937 | AH36: 485.8335 | AI36: 497.4735 | AJ36: 509.1135
A37: REGION | B37: PHL_POW_TD_INDU | C37: 92.0388 | D37: 94.1106 | E37: 96.1818 | F37: 98.2542 | G37: 100.326 | H37: 102.3984 | I37: 104.6436 | J37: 106.8906 | K37: 109.137 | L37: 111.3828 | M37: 113.6292 | N37: 116.1816 | O37: 118.734 | P37: 121.2864 | Q37: 123.8388 | R37: 126.39 | S37: 129.4272 | T37: 132.4632 | U37: 135.4992 | V37: 138.537 | W37: 141.5718 | X37: 145.107 | Y37: 148.6404 | Z37: 152.1756 | AA37: 155.709 | AB37: 159.243 | AC37: 163.272 | AD37: 167.3034 | AE37: 171.3324 | AF37: 175.362 | AG37: 179.391 | AH37: 183.822 | AI37: 188.253 | AJ37: 192.6822
A38: REGION | B38: PHL_POW_TD_SER | C38: 74.6185 | D38: 64.4849 | E38: 69.2756 | F38: 74.0661 | G38: 78.8568 | H38: 83.6476 | I38: 89.7923 | J38: 95.9372 | K38: 102.0815 | L38: 108.2264 | M38: 114.371 | N38: 122.0248 | O38: 129.6784 | P38: 137.3313 | Q38: 144.9854 | R38: 152.6391 | S38: 162.437 | T38: 172.2355 | U38: 182.0342 | V38: 191.8324 | W38: 201.6307 | X38: 213.4681 | Y38: 225.3049 | Z38: 237.1419 | AA38: 248.9789 | AB38: 260.8157 | AC38: 273.9441 | AD38: 287.0726 | AE38: 300.2011 | AF38: 313.3303 | AG38: 326.4586 | AH38: 339.5855 | AI38: 352.7122 | AJ38: 365.8389
A39: REGION | B39: PHL_POW_TD_TRA | C39: 0.3528 | D39: 0.3528 | E39: 0.3528 | F39: 0.3528 | G39: 0.3528 | H39: 0.3282 | I39: 2.5622 | J39: 4.7972 | K39: 7.0324 | L39: 9.2508 | M39: 11.4854 | N39: 13.7216 | O39: 15.9556 | P39: 18.1906 | Q39: 20.4024 | R39: 22.6372 | S39: 24.7284 | T39: 26.9631 | U39: 29.2936 | V39: 31.5297 | W39: 33.5234 | X39: 34.1258 | Y39: 34.7264 | Z39: 35.328 | AA39: 35.9284 | AB39: 36.5296 | AC39: 37.1068 | AD39: 37.6838 | AE39: 38.2616 | AF39: 38.84 | AG39: 40.165 | AH39: 41.2794 | AI39: 42.513 | AJ39: 45.3512
A40: REGION | B40: PHL_PRO_BLEND_BIOF | C40: 440.9853 | D40: 453.4507 | E40: 466.2603 | F40: 477.2044 | G40: 491.5885 | H40: 501.2472 | I40: 511.7878 | J40: 519.1995 | K40: 526.6438 | L40: 534.1262 | M40: 517.4688 | N40: 528.6712 | O40: 539.4568 | P40: 550.5117 | Q40: 561.5612 | R40: 572.532 | S40: 586.4914 | T40: 600.1163 | U40: 613.531 | V40: 627.2889 | W40: 638.7741 | X40: 660.2318 | Y40: 681.7217 | Z40: 703.2822 | AA40: 724.8963 | AB40: 746.5573 | AC40: 770.0235 | AD40: 793.5303 | AE40: 817.0943 | AF40: 840.6882 | AG40: 855.2609 | AH40: 878.3474 | AI40: 900.8838 | AJ40: 918.7748
A41: REGION | B41: PHL_PRO_BLEND_OIL | F41: 1.5247 | H41: 2.9256
A42: REGION | B42: PHL_PRO_PROC_COAL | C42: 743.1913 | D42: 1159.6625 | E42: 1243.3869 | F42: 1329.9996 | G42: 1408.0054 | H42: 1492.4646 | I42: 1476.4572 | J42: 1536.3958 | K42: 1595.7098 | L42: 1652.7744 | M42: 1587.9765 | N42: 1693.4257 | O42: 1795.2294 | P42: 1907.5574 | Q42: 1849.6669 | R42: 1773.5271 | S42: 1671.4767 | T42: 1589.5663 | U42: 1484.2084 | V42: 1419.7394 | W42: 1370.7954 | X42: 1387.3201 | Y42: 1404.357 | Z42: 1425.1866 | AA42: 1442.1436 | AB42: 1452.9547 | AC42: 1418.7565 | AD42: 1369.3166 | AE42: 1360.1728 | AF42: 1349.2405 | AG42: 1296.557 | AH42: 1295.4398 | AI42: 1277.0714 | AJ42: 1211.0263
A43: REGION | B43: PHL_PRO_PROC_NG | C43: 140.4442 | D43: 154.3177 | E43: 154.1851 | F43: 142.1438 | G43: 161.4981 | H43: 40.9207 | I43: 48.5465 | J43: 47.1998 | K43: 43.8466 | L43: 55.308 | M43: 56.4528 | N43: 58.6482 | O43: 85.0056 | P43: 136.8083 | Q43: 151.5174 | R43: 166.6433 | S43: 222.7032 | T43: 221.8628 | U43: 212.0779 | V43: 241.855 | W43: 277.8725 | X43: 296.4426 | Y43: 315.9498 | Z43: 342.6962 | AA43: 361.9922 | AB43: 375.7419 | AC43: 388.3969 | AD43: 395.0496 | AE43: 400.7825 | AF43: 407.3387 | AG43: 426.9861 | AH43: 435.5076 | AI43: 453.2581 | AJ43: 544.8281
A44: REGION | B44: PHL_PRO_PROC_OIL | C44: 259.9209 | D44: 172.2606 | E44: 160.6301 | F44: 147.6504 | G44: 135.8502 | H44: 123.0397 | I44: 110.74 | J44: 107.9753 | K44: 107.1214 | L44: 97.8824 | M44: 95.2269 | N44: 94.5674 | O44: 71.4258 | P44: 24.6102 | Q44: 12.2998
A45: REGION | B45: PHL_SER_HEAT_BIOM | C45: 15.669 | D45: 4.1874 | E45: 2.4646 | F45: 3.9162 | G45: 1.9654 | H45: 2.983 | I45: 3.0078 | J45: 1.8438 | K45: 1.8598
A46: REGION | B46: PHL_SER_HEAT_NG | D46: 17.7129 | E46: 25.5048 | F46: 22.2956 | G46: 31.326 | H46: 27.4144 | I46: 33.0174 | J46: 38.031 | K46: 40.0566 | L46: 52.3362 | M46: 53.4198 | N46: 55.4976 | O46: 80.4384 | P46: 129.4589 | Q46: 143.3781 | R46: 157.2884 | S46: 162.1687 | T46: 167.0405 | U46: 171.9053 | V46: 176.7657 | W46: 181.2113 | X46: 189.2453 | Y46: 197.2858 | Z46: 205.3339 | AA46: 213.39 | AB46: 221.4552 | AC46: 231.5935 | AD46: 241.7355 | AE46: 251.8828 | AF46: 262.0362 | AG46: 270.0313 | AH46: 282.4768 | AI46: 294.9219 | AJ46: 307.3672
A47: REGION | B47: PHL_SER_HEAT_OIL | C47: 109.1647 | D47: 121.2298 | E47: 116.0838 | F47: 119.0898 | G47: 112.9852 | H47: 117.1582 | I47: 112.6502 | J47: 109.8376 | K47: 108.9687 | L47: 99.5703 | M47: 96.8691 | N47: 96.1982 | O47: 72.6577 | P47: 25.0343 | Q47: 12.5122
A48: REGION | B48: PHL_SER_HEAT_RES | C48: 14.924
A49: REGION | B49: PHL_SER_UNIT | C49: 59.6946 | D49: 64.4849 | E49: 69.2756 | F49: 74.0661 | G49: 78.8568 | H49: 83.6476 | I49: 89.7923 | J49: 95.9372 | K49: 102.0815 | L49: 108.2264 | M49: 114.371 | N49: 122.0248 | O49: 129.6784 | P49: 137.3313 | Q49: 144.9854 | R49: 152.6391 | S49: 162.437 | T49: 172.2355 | U49: 182.0342 | V49: 191.8324 | W49: 201.6307 | X49: 213.4681 | Y49: 225.3049 | Z49: 237.1419 | AA49: 248.9789 | AB49: 260.8157 | AC49: 273.9441 | AD49: 287.0726 | AE49: 300.2011 | AF49: 313.3303 | AG49: 326.4586 | AH49: 339.5855 | AI49: 352.7122 | AJ49: 365.8389
A50: REGION | B50: PHL_TRA_23WHEEL_ELE | I50: 2.234 | J50: 4.4702 | K50: 6.7048 | L50: 8.94 | M50: 11.174 | N50: 13.4102 | O50: 15.6442 | P50: 17.8792 | Q50: 20.1144 | R50: 22.3492 | S50: 24.585 | T50: 26.8196 | U50: 29.0534 | V50: 31.2892 | W50: 33.5234 | X50: 34.1258 | Y50: 34.7264 | Z50: 35.328 | AA50: 35.9284 | AB50: 36.5296 | AC50: 37.1068 | AD50: 37.6838 | AE50: 38.2616 | AF50: 38.84 | AG50: 38.9944 | AH50: 39.2 | AI50: 39.3374 | AJ50: 38.5694
A51: REGION | B51: PHL_TRA_23WHEEL_LIQ | C51: 113.5206 | D51: 115.1606 | E51: 116.8029 | F51: 118.4431 | G51: 120.0844 | H51: 121.7256 | I51: 115.4803 | J51: 109.2366 | K51: 102.9918 | L51: 96.748 | M51: 90.5028 | N51: 84.138 | O51: 77.7732 | P51: 71.4076 | Q51: 65.0431 | R51: 58.6782 | S51: 52.1769 | T51: 45.6747 | U51: 39.1733 | V51: 32.6712 | W51: 26.1696 | X51: 25.2275 | Y51: 24.2867 | Z51: 23.3445 | AA51: 22.4023 | AB51: 21.4607 | AC51: 20.4453 | AD51: 19.4314 | AE51: 18.4151 | AF51: 17.4003 | AG51: 17.8598 | AH51: 18.0086 | AI51: 18.3918 | AJ51: 21.9374
A52: REGION | B52: PHL_TRA_AVI_LIQ | C52: 9.7595 | D52: 10.1928 | E52: 10.6152 | F52: 11.0364 | G52: 11.4696 | H52: 11.8914 | I52: 12.462 | J52: 13.0206 | K52: 13.5894 | L52: 14.16 | M52: 14.7186 | N52: 15.474 | O52: 16.2444 | P52: 16.9998 | Q52: 17.7558 | R52: 18.5136 | S52: 19.5906 | T52: 20.67 | U52: 21.75 | V52: 22.8287 | W52: 23.9076 | X52: 25.4334 | Y52: 26.946 | Z52: 28.4706 | AA52: 29.9952 | AB52: 31.521 | AC52: 33.6042 | AD52: 35.6886 | AE52: 37.77 | AF52: 39.8539 | AG52: 41.9376 | AH52: 44.652 | AI52: 47.3682 | AJ52: 50.0832
A53: REGION | B53: PHL_TRA_BUS_LIQ | C53: 37.8426 | D53: 37.1646 | E53: 36.5562 | F53: 36.0096 | G53: 35.52 | H53: 35.0928 | I53: 34.68 | J53: 34.3116 | K53: 33.9942 | L53: 33.705 | M53: 29.4186 | N53: 29.514 | O53: 29.6124 | P53: 29.7006 | Q53: 29.7882 | R53: 29.883 | S53: 29.9424 | T53: 30.0108 | U53: 30.084 | V53: 30.1638 | W53: 30.036 | X53: 30.0276 | Y53: 30.0348 | Z53: 30.066 | AA53: 30.117 | AB53: 30.183 | AC53: 30.2322 | AD53: 30.291 | AE53: 30.3672 | AF53: 30.4548 | AG53: 29.61 | AH53: 29.7822 | AI53: 29.9484 | AJ53: 30.1146
A54: REGION | B54: PHL_TRA_CAR_ELE | AG54: 1.1714 | AH54: 2.0794 | AI54: 3.1756 | AJ54: 6.7818
A55: REGION | B55: PHL_TRA_CAR_LIQ | C55: 75.6798 | D55: 77.928 | E55: 80.178 | F55: 82.4334 | G55: 84.6954 | H55: 86.9676 | I55: 89.4366 | J55: 91.9146 | K55: 94.4034 | L55: 96.9048 | M55: 93.1086 | N55: 96.0384 | O55: 98.9556 | P55: 101.8578 | Q55: 104.7534 | R55: 107.6388 | S55: 110.4246 | T55: 113.2068 | U55: 115.9854 | V55: 118.7628 | W55: 121.2948 | X55: 123.6666 | Y55: 126.0576 | Z55: 128.4648 | AA55: 130.887 | AB55: 133.3212 | AC55: 135.285 | AD55: 137.2614 | AE55: 139.2504 | AF55: 141.2502 | AG55: 138.2454 | AH55: 136.9122 | AI55: 134.9712 | AJ55: 124.8726
A56: REGION | B56: PHL_TRA_RAILF_ELE | C56: 0.1758 | D56: 0.1758 | E56: 0.1758 | F56: 0.1758 | G56: 0.1758 | H56: 0.1636 | I56: 0.1636 | J56: 0.1636 | K56: 0.1636 | L56: 0.1558 | M56: 0.1558 | N56: 0.1558 | O56: 0.1558 | P56: 0.1558 | Q56: 0.1442 | R56: 0.1442 | S56: 0.0718 | T56: 0.0719 | U56: 0.1206 | V56: 0.1209
A57: REGION | B57: PHL_TRA_RAILF_LIQ | E57: 0.1758 | F57: 0.1758 | G57: 0.3528 | H57: 0.3696 | I57: 0.5466 | J57: 0.7218 | K57: 0.7218 | L57: 0.9156 | M57: 1.0914 | N57: 1.2672 | O57: 1.2672 | P57: 1.443 | Q57: 1.6548 | R57: 1.8306 | S57: 2.1468 | T57: 2.3226 | U57: 2.3934 | V57: 2.7462 | W57: 3.1686 | X57: 3.3444 | Y57: 3.6954 | Z57: 4.0482 | AA57: 4.224 | AB57: 4.575 | AC57: 4.9278 | AD57: 5.2794 | AE57: 5.6316 | AF57: 5.9832 | AG57: 6.336 | AH57: 6.864 | AI57: 7.2168 | AJ57: 7.7436
A58: REGION | B58: PHL_TRA_RAILP_ELE | C58: 0.1758 | D58: 0.1758 | E58: 0.1758 | F58: 0.1758 | G58: 0.1758 | H58: 0.1636 | I58: 0.1636 | J58: 0.1636 | K58: 0.1636 | L58: 0.1558 | M58: 0.1558 | N58: 0.1558 | O58: 0.1558 | P58: 0.1558 | Q58: 0.1442 | R58: 0.1442 | S58: 0.0718 | T58: 0.0719 | U58: 0.1206 | V58: 0.1209
A59: REGION | B59: PHL_TRA_RAILP_LIQ | E59: 0.1758 | F59: 0.1758 | G59: 0.3528 | H59: 0.3696 | I59: 0.5466 | J59: 0.5466 | K59: 0.7218 | L59: 0.7386 | M59: 0.9156 | N59: 1.0914 | O59: 1.0914 | P59: 1.2672 | Q59: 1.4778 | R59: 1.6548 | S59: 1.9722 | T59: 2.1468 | U59: 2.2176 | V59: 2.3934 | W59: 2.8158 | X59: 3.1686 | Y59: 3.3444 | Z59: 3.5208 | AA59: 3.8712 | AB59: 4.0482 | AC59: 4.3998 | AD59: 4.752 | AE59: 5.1048 | AF59: 5.4558 | AG59: 5.8086 | AH59: 6.1602 | AI59: 6.5124 | AJ59: 7.0398
A60: REGION | B60: PHL_TRA_SHIP_LIQ | C60: 33.0938 | D60: 35.6592 | E60: 38.2224 | F60: 40.7856 | G60: 43.3488 | H60: 45.912 | I60: 48.8532 | J60: 51.7932 | K60: 54.7338 | L60: 57.675 | M60: 60.615 | N60: 63.768 | O60: 66.9216 | P60: 70.077 | Q60: 73.23 | R60: 76.3836 | S60: 79.8258 | T60: 83.2674 | U60: 86.7102 | V60: 90.1511 | W60: 93.5934 | X60: 97.302 | Y60: 101.0106 | Z60: 104.721 | AA60: 108.4308 | AB60: 112.1406 | AC60: 116.0988 | AD60: 120.0564 | AE60: 124.0158 | AF60: 127.9743 | AG60: 131.9328 | AH60: 136.0662 | AI60: 140.1996 | AJ60: 144.3336
A61: REGION | B61: PHL_TRA_TRUH_LIQ | C61: 75.6774 | D61: 78.5004 | E61: 81.2742 | F61: 84.006 | G61: 86.7042 | H61: 89.373 | I61: 92.9484 | J61: 96.4704 | K61: 99.9564 | L61: 103.4154 | M61: 100.0602 | N61: 104.6316 | O61: 109.1574 | P61: 113.652 | Q61: 118.119 | R61: 122.5716 | S61: 128.1192 | T61: 133.6332 | U61: 139.1322 | V61: 144.6174 | W61: 148.2288 | X61: 154.5726 | Y61: 160.9266 | Z61: 167.2914 | AA61: 173.667 | AB61: 180.054 | AC61: 187.0602 | AD61: 194.076 | AE61: 201.111 | AF61: 208.1478 | AG61: 212.1444 | AH61: 219.4908 | AI61: 226.845 | AJ61: 234.1986
A62: REGION | B62: PHL_TRA_TRUL_LIQ | C62: 56.76 | D62: 59.001 | E62: 61.2312 | F62: 63.45 | G62: 65.6628 | H62: 67.8762 | I62: 70.7892 | J62: 73.692 | K62: 76.5894 | L62: 79.4802 | M62: 76.9998 | N62: 80.8698 | O62: 84.7242 | P62: 88.5678 | Q62: 92.3994 | R62: 96.219 | S62: 100.911 | T62: 105.5922 | U62: 110.2662 | V62: 114.9312 | W62: 119.4066 | X62: 124.7844 | Y62: 130.1634 | Z62: 135.549 | AA62: 140.9388 | AB62: 146.3322 | AC62: 152.2236 | AD62: 158.1204 | AE62: 164.0214 | AF62: 169.9266 | AG62: 174.6942 | AH62: 180.75 | AI62: 186.8028 | AJ62: 192.8568
A63: REGION | B63: PHL_TRA_VAN_LIQ | C63: 18.9202 | D63: 19.668 | E63: 20.409 | F63: 21.1494 | G63: 21.8868 | H63: 22.6248 | I63: 23.598 | J63: 24.5634 | K63: 25.5306 | L63: 26.4936 | M63: 25.6656 | N63: 26.9568 | O63: 28.242 | P63: 29.5224 | Q63: 30.8016 | R63: 32.0736 | S63: 33.6378 | T63: 35.1972 | U63: 36.756 | V63: 38.3106 | W63: 39.8028 | X63: 41.5944 | Y63: 43.3872 | Z63: 45.1818 | AA63: 46.9794 | AB63: 48.7776 | AC63: 50.7414 | AD63: 52.7064 | AE63: 54.675 | AF63: 56.6424 | AG63: 58.2312 | AH63: 60.2502 | AI63: 62.2674 | AJ63: 64.2852

Sheet Operation Life Time
F2: Discount Rate | G2: 0.05 | J2: Convert PJ -->GWh | K2: 277.77778
B3: Operation Life Time
B4: Technology | C4: Parameter | D4: Life period | E4: CRF (Capital Recovery Factor)
B5: PHL_POW_CHP_BIOM_OLD | D5: 25 | E5: =$G$2*(1+$G$2)^D5/((1+$G$2)^D5-1) -> 0.070952457
B6: PHL_POW_CHP_COAL_OLD | D6: 25 | E6: =$G$2*(1+$G$2)^D6/((1+$G$2)^D6-1) -> 0.070952457
B7: PHL_POW_GEO_OLD | D7: 25 | E7: =$G$2*(1+$G$2)^D7/((1+$G$2)^D7-1) -> 0.070952457
B8: PHL_POW_PP_BIOM_CCS | D8: 25 | E8: =$G$2*(1+$G$2)^D8/((1+$G$2)^D8-1) -> 0.070952457
B9: PHL_POW_PP_COAL | D9: 25 | E9: =$G$2*(1+$G$2)^D9/((1+$G$2)^D9-1) -> 0.070952457
B10: PHL_POW_PP_COAL_CCS | D10: 25 | E10: =$G$2*(1+$G$2)^D10/((1+$G$2)^D10-1) -> 0.070952457
B11: PHL_POW_PP_H2 | D11: 25 | E11: =$G$2*(1+$G$2)^D11/((1+$G$2)^D11-1) -> 0.070952457
B12: PHL_POW_PP_HY_LA | D12: 50 | E12: =$G$2*(1+$G$2)^D12/((1+$G$2)^D12-1) -> 0.054776735
B13: PHL_POW_PP_NGCC | D13: 25 | E13: =$G$2*(1+$G$2)^D13/((1+$G$2)^D13-1) -> 0.070952457
B14: PHL_POW_PP_NGCC_CCS | D14: 25 | E14: =$G$2*(1+$G$2)^D14/((1+$G$2)^D14-1) -> 0.070952457
B15: PHL_POW_PP_NU | D15: 40 | E15: =$G$2*(1+$G$2)^D15/((1+$G$2)^D15-1) -> 0.058278161
B16: PHL_POW_PP_NUSMR | D16: 60 | E16: =$G$2*(1+$G$2)^D16/((1+$G$2)^D16-1) -> 0.052828185
... B21: PHL_POW_CHP_NG_OLD | D21: 1 | E21: =$G$2*(1+$G$2)^D21/((1+$G$2)^D21-1) -> 1.05
