Workbook

Sheet Grid_cost_Base
A1: =Cost_of_ELCgen!A149 -> Calculations | C1: =Cost_of_ELCgen!C149 -> 2020 | D1: =Cost_of_ELCgen!D149 -> 2021 | E1: =Cost_of_ELCgen!E149 -> 2022 | F1: =Cost_of_ELCgen!F149 -> 2023 | G1: =Cost_of_ELCgen!G149 -> 2024 | H1: =Cost_of_ELCgen!H149 -> 2025 | I1: =Cost_of_ELCgen!I149 -> 2026 | J1: =Cost_of_ELCgen!J149 -> 2027 | ... AG1: =Cost_of_ELCgen!AG149 -> 2050
A2: =Cost_of_ELCgen!A150 -> Operating O&M costs | C2: =Cost_of_ELCgen!C150 -> 4162.8638 | D2: =Cost_of_ELCgen!D150 -> 3853.8406 | E2: =Cost_of_ELCgen!E150 -> 4014.6511 | F2: =Cost_of_ELCgen!F150 -> 4210.1257 | G2: =Cost_of_ELCgen!G150 -> 4252.9125 | H2: =Cost_of_ELCgen!H150 -> 4518.7706 | I2: =Cost_of_ELCgen!I150 -> 4679.6315 | J2: =Cost_of_ELCgen!J150 -> 4872.7074 | ... AG2: =Cost_of_ELCgen!AG150 -> 10472.025
A3: =Cost_of_ELCgen!A151 -> Annualized Investment costs | C3: =Cost_of_ELCgen!C151 -> 143.48784 | D3: =Cost_of_ELCgen!D151 -> 337.45956 | E3: =Cost_of_ELCgen!E151 -> 538.60559 | F3: =Cost_of_ELCgen!F151 -> 554.30562 | G3: =Cost_of_ELCgen!G151 -> 684.58792 | H3: =Cost_of_ELCgen!H151 -> 757.97001 | I3: =Cost_of_ELCgen!I151 -> 757.97001 | J3: =Cost_of_ELCgen!J151 -> 826.35984 | ... AG3: =Cost_of_ELCgen!AG151 -> 7599.7526
A4: =Cost_of_ELCgen!A152 -> CO2 costs | C4: =Cost_of_ELCgen!C152 -> 0 | D4: =Cost_of_ELCgen!D152 -> 0 | E4: =Cost_of_ELCgen!E152 -> 0 | F4: =Cost_of_ELCgen!F152 -> 0 | G4: =Cost_of_ELCgen!G152 -> 0 | H4: =Cost_of_ELCgen!H152 -> 0 | I4: =Cost_of_ELCgen!I152 -> 0 | J4: =Cost_of_ELCgen!J152 -> 0 | ... AG4: =Cost_of_ELCgen!AG152 -> 0
A5: =Cost_of_ELCgen!A153 -> Total Costs (Million USD) | C5: =Cost_of_ELCgen!C153 -> 4306.3517 | D5: =Cost_of_ELCgen!D153 -> 4191.3001 | E5: =Cost_of_ELCgen!E153 -> 4553.2567 | F5: =Cost_of_ELCgen!F153 -> 4764.4313 | G5: =Cost_of_ELCgen!G153 -> 4937.5004 | H5: =Cost_of_ELCgen!H153 -> 5276.7406 | I5: =Cost_of_ELCgen!I153 -> 5437.6015 | J5: =Cost_of_ELCgen!J153 -> 5699.0672 | ... AG5: =Cost_of_ELCgen!AG153 -> 18071.778
A6: =Cost_of_ELCgen!A154 -> Generation (PJ->GWh), Before Transmission losses | C6: =Cost_of_ELCgen!C154 -> 101777.47 | D6: =Cost_of_ELCgen!D154 -> 101856.03 | E6: =Cost_of_ELCgen!E154 -> 107092.5 | F6: =Cost_of_ELCgen!F154 -> 111523.03 | G6: =Cost_of_ELCgen!G154 -> 116469.06 | H6: =Cost_of_ELCgen!H154 -> 121697.72 | I6: =Cost_of_ELCgen!I154 -> 127969 | J6: =Cost_of_ELCgen!J154 -> 134326.11 | ... AG6: =Cost_of_ELCgen!AG154 -> 346335.28
A7: =Cost_of_ELCgen!A155 -> Average electricity cost (USD/kWh) - Base | C7: =Cost_of_ELCgen!C155 -> 0.042311443 | D7: =Cost_of_ELCgen!D155 -> 0.04114926 | E7: =Cost_of_ELCgen!E155 -> 0.042517046 | F7: =Cost_of_ELCgen!F155 -> 0.042721503 | G7: =Cost_of_ELCgen!G155 -> 0.042393238 | H7: =Cost_of_ELCgen!H155 -> 0.043359403 | I7: =Cost_of_ELCgen!I155 -> 0.042491553 | J7: =Cost_of_ELCgen!J155 -> 0.042427099 | ... AG7: =Cost_of_ELCgen!AG155 -> 0.052180008

Sheet Investments_Base
A1: Base Scenario
A3: Variable | C3: 2020 | D3: 2021 | E3: 2022 | F3: 2023 | G3: 2024 | H3: 2025 | I3: 2026 | J3: 2027 | K3: 2028 | L3: 2029 | M3: 2030 | N3: 2031 | O3: 2032 | P3: 2033 | Q3: 2034 | R3: 2035 | S3: 2036 | T3: 2037 | U3: 2038 | V3: 2039 | W3: 2040 | X3: 2041 | Y3: 2042 | Z3: 2043 | AA3: 2044 | AB3: 2045 | AC3: 2046 | AD3: 2047 | AE3: 2048 | AF3: 2049 | AG3: 2050
A4: =Cost_of_ELCgen!A77 -> Total Capital Investment (Million USD) | C4: =Cost_of_ELCgen!C77 -> 2844.1751 | D4: =Cost_of_ELCgen!D77 -> 3215.6945 | E4: =Cost_of_ELCgen!E77 -> 3334.6461 | F4: =Cost_of_ELCgen!F77 -> 277.5919 | G4: =Cost_of_ELCgen!G77 -> 2053.5828 | H4: =Cost_of_ELCgen!H77 -> 1168.3836 | I4: =Cost_of_ELCgen!I77 -> 0 | J4: =Cost_of_ELCgen!J77 -> 1012.0767 | ... AG4: =Cost_of_ELCgen!AG77 -> 33451.744
A5: =Cost_of_ELCgen!A98 -> Total Annualized Investments (Million USD) | C5: =Cost_of_ELCgen!C98 -> 143.48784 | D5: =Cost_of_ELCgen!D98 -> 337.45956 | E5: =Cost_of_ELCgen!E98 -> 538.60559 | F5: =Cost_of_ELCgen!F98 -> 554.30562 | G5: =Cost_of_ELCgen!G98 -> 684.58792 | H5: =Cost_of_ELCgen!H98 -> 757.97001 | I5: =Cost_of_ELCgen!I98 -> 757.97001 | J5: =Cost_of_ELCgen!J98 -> 826.35984 | ... AG5: =Cost_of_ELCgen!AG98 -> 7599.7526

Sheet Cost_of_ELCgen
A1: Philippines
A3: AnnualFixedOperatingCost + AnnualVariableOperating Cost (Million USD) | C3: 2020 | D3: 2021 | E3: 2022 | F3: 2023 | G3: 2024 | H3: 2025 | I3: 2026 | J3: 2027 | K3: 2028 | L3: 2029 | M3: 2030 | N3: 2031 | O3: 2032 | P3: 2033 | Q3: 2034 | R3: 2035 | S3: 2036 | T3: 2037 | U3: 2038 | V3: 2039 | W3: 2040 | X3: 2041 | Y3: 2042 | Z3: 2043 | AA3: 2044 | AB3: 2045 | AC3: 2046 | AD3: 2047 | AE3: 2048 | AF3: 2049 | AG3: 2050
A4: TOTAL (Fixed & Variable) | C4: =SUM(C6:C9)+SUM(C38:C54) -> 12310.832 | D4: =SUM(D6:D9)+SUM(D38:D54) -> 5122.5043 | E4: =SUM(E6:E9)+SUM(E38:E54) -> 5319.9663 | F4: =SUM(F6:F9)+SUM(F38:F54) -> 5592.5476 | G4: =SUM(G6:G9)+SUM(G38:G54) -> 6742.4957 | H4: =SUM(H6:H9)+SUM(H38:H54) -> 7004.6527 | I4: =SUM(I6:I9)+SUM(I38:I54) -> 7332.7254 | J4: =SUM(J6:J9)+SUM(J38:J54) -> 7591.662 | ... AG4: =SUM(AG6:AG9)+SUM(AG38:AG54) -> 6227.5159
A5: VARIABLE
A6: PHL_PRO_EXTR_NG | C6: =SUMIFS(Variable!C$2:C$10000,Variable!$B$2:$B$10000,$A6) -> 1261.3245 | D6: =SUMIFS(Variable!D$2:D$10000,Variable!$B$2:$B$10000,$A6) -> 240.2289 | E6: =SUMIFS(Variable!E$2:E$10000,Variable!$B$2:$B$10000,$A6) -> 262.3222 | F6: =SUMIFS(Variable!F$2:F$10000,Variable!$B$2:$B$10000,$A6) -> 330.6415 | G6: =SUMIFS(Variable!G$2:G$10000,Variable!$B$2:$B$10000,$A6) -> 1439.8781 | H6: =SUMIFS(Variable!H$2:H$10000,Variable!$B$2:$B$10000,$A6) -> 1550.1288 | I6: =SUMIFS(Variable!I$2:I$10000,Variable!$B$2:$B$10000,$A6) -> 1709.9739 | J6: =SUMIFS(Variable!J$2:J$10000,Variable!$B$2:$B$10000,$A6) -> 1766.589 | ... AG6: =SUMIFS(Variable!AG$2:AG$10000,Variable!$B$2:$B$10000,$A6) -> 3569.0526
A7: PHL_PRO_EXTR_OIL | C7: =SUMIFS(Variable!C$2:C$10000,Variable!$B$2:$B$10000,$A7) -> 3103.7145 | D7: =SUMIFS(Variable!D$2:D$10000,Variable!$B$2:$B$10000,$A7) -> 0 | E7: =SUMIFS(Variable!E$2:E$10000,Variable!$B$2:$B$10000,$A7) -> 0 | F7: =SUMIFS(Variable!F$2:F$10000,Variable!$B$2:$B$10000,$A7) -> 0 | G7: =SUMIFS(Variable!G$2:G$10000,Variable!$B$2:$B$10000,$A7) -> 0 | H7: =SUMIFS(Variable!H$2:H$10000,Variable!$B$2:$B$10000,$A7) -> 0 | I7: =SUMIFS(Variable!I$2:I$10000,Variable!$B$2:$B$10000,$A7) -> 0 | J7: =SUMIFS(Variable!J$2:J$10000,Variable!$B$2:$B$10000,$A7) -> 0 | ... AG7: =SUMIFS(Variable!AG$2:AG$10000,Variable!$B$2:$B$10000,$A7) -> 0
A8: PHL_PRO_EXTR_COAL | C8: =SUMIFS(Variable!C$2:C$10000,Variable!$B$2:$B$10000,$A8) -> 2023.5934 | D8: =SUMIFS(Variable!D$2:D$10000,Variable!$B$2:$B$10000,$A8) -> 3760.7493 | E8: =SUMIFS(Variable!E$2:E$10000,Variable!$B$2:$B$10000,$A8) -> 3887.391 | F8: =SUMIFS(Variable!F$2:F$10000,Variable!$B$2:$B$10000,$A8) -> 4124.4119 | G8: =SUMIFS(Variable!G$2:G$10000,Variable!$B$2:$B$10000,$A8) -> 4180.0101 | H8: =SUMIFS(Variable!H$2:H$10000,Variable!$B$2:$B$10000,$A8) -> 4306.9405 | I8: =SUMIFS(Variable!I$2:I$10000,Variable!$B$2:$B$10000,$A8) -> 4476.501 | J8: =SUMIFS(Variable!J$2:J$10000,Variable!$B$2:$B$10000,$A8) -> 4650.6059 | ... AG8: =SUMIFS(Variable!AG$2:AG$10000,Variable!$B$2:$B$10000,$A8) -> 0
A9: PHL_PRO_PROC_BIOM | C9: =SUMIFS(Variable!C$2:C$10000,Variable!$B$2:$B$10000,$A9) -> 4868.8589 | D9: =SUMIFS(Variable!D$2:D$10000,Variable!$B$2:$B$10000,$A9) -> 28.0453 | E9: =SUMIFS(Variable!E$2:E$10000,Variable!$B$2:$B$10000,$A9) -> 28.2742 | F9: =SUMIFS(Variable!F$2:F$10000,Variable!$B$2:$B$10000,$A9) -> 28.5122 | G9: =SUMIFS(Variable!G$2:G$10000,Variable!$B$2:$B$10000,$A9) -> 0 | H9: =SUMIFS(Variable!H$2:H$10000,Variable!$B$2:$B$10000,$A9) -> 0 | I9: =SUMIFS(Variable!I$2:I$10000,Variable!$B$2:$B$10000,$A9) -> 0 | J9: =SUMIFS(Variable!J$2:J$10000,Variable!$B$2:$B$10000,$A9) -> 0 | ... AG9: =SUMIFS(Variable!AG$2:AG$10000,Variable!$B$2:$B$10000,$A9) -> 0
A10: PHL_POW_CHP_BIOM_OLD | C10: =SUMIFS(Variable!C$2:C$10000,Variable!$B$2:$B$10000,$A10) -> 0.0004 | D10: =SUMIFS(Variable!D$2:D$10000,Variable!$B$2:$B$10000,$A10) -> 0 | E10: =SUMIFS(Variable!E$2:E$10000,Variable!$B$2:$B$10000,$A10) -> 0 | F10: =SUMIFS(Variable!F$2:F$10000,Variable!$B$2:$B$10000,$A10) -> 0 | G10: =SUMIFS(Variable!G$2:G$10000,Variable!$B$2:$B$10000,$A10) -> 0 | H10: =SUMIFS(Variable!H$2:H$10000,Variable!$B$2:$B$10000,$A10) -> 0 | I10: =SUMIFS(Variable!I$2:I$10000,Variable!$B$2:$B$10000,$A10) -> 0 | J10: =SUMIFS(Variable!J$2:J$10000,Variable!$B$2:$B$10000,$A10) -> 0 | ... AG10: =SUMIFS(Variable!AG$2:AG$10000,Variable!$B$2:$B$10000,$A10) -> 0
A11: PHL_POW_CHP_COAL_OLD | C11: =SUMIFS(Variable!C$2:C$10000,Variable!$B$2:$B$10000,$A11) -> 0.0209 | D11: =SUMIFS(Variable!D$2:D$10000,Variable!$B$2:$B$10000,$A11) -> 0.0267 | E11: =SUMIFS(Variable!E$2:E$10000,Variable!$B$2:$B$10000,$A11) -> 0.026 | F11: =SUMIFS(Variable!F$2:F$10000,Variable!$B$2:$B$10000,$A11) -> 0.0282 | G11: =SUMIFS(Variable!G$2:G$10000,Variable!$B$2:$B$10000,$A11) -> 0.027 | H11: =SUMIFS(Variable!H$2:H$10000,Variable!$B$2:$B$10000,$A11) -> 0.028 | I11: =SUMIFS(Variable!I$2:I$10000,Variable!$B$2:$B$10000,$A11) -> 0.0295 | J11: =SUMIFS(Variable!J$2:J$10000,Variable!$B$2:$B$10000,$A11) -> 0.0295 | ... AG11: =SUMIFS(Variable!AG$2:AG$10000,Variable!$B$2:$B$10000,$A11) -> 0.0082
A12: PHL_POW_GEO_OLD | C12: =SUMIFS(Variable!C$2:C$10000,Variable!$B$2:$B$10000,$A12) -> 0.0039 | D12: =SUMIFS(Variable!D$2:D$10000,Variable!$B$2:$B$10000,$A12) -> 0.004 | E12: =SUMIFS(Variable!E$2:E$10000,Variable!$B$2:$B$10000,$A12) -> 0.004 | F12: =SUMIFS(Variable!F$2:F$10000,Variable!$B$2:$B$10000,$A12) -> 0.003 | G12: =SUMIFS(Variable!G$2:G$10000,Variable!$B$2:$B$10000,$A12) -> 0.003 | H12: =SUMIFS(Variable!H$2:H$10000,Variable!$B$2:$B$10000,$A12) -> 0.0031 | I12: =SUMIFS(Variable!I$2:I$10000,Variable!$B$2:$B$10000,$A12) -> 0.0031 | J12: =SUMIFS(Variable!J$2:J$10000,Variable!$B$2:$B$10000,$A12) -> 0.0031 | ... AG12: =SUMIFS(Variable!AG$2:AG$10000,Variable!$B$2:$B$10000,$A12) -> 0.0004
A13: PHL_POW_PP_BIOM_CCS | C13: =SUMIFS(Variable!C$2:C$10000,Variable!$B$2:$B$10000,$A13) -> 0 | D13: =SUMIFS(Variable!D$2:D$10000,Variable!$B$2:$B$10000,$A13) -> 0 | E13: =SUMIFS(Variable!E$2:E$10000,Variable!$B$2:$B$10000,$A13) -> 0 | F13: =SUMIFS(Variable!F$2:F$10000,Variable!$B$2:$B$10000,$A13) -> 0 | G13: =SUMIFS(Variable!G$2:G$10000,Variable!$B$2:$B$10000,$A13) -> 0 | H13: =SUMIFS(Variable!H$2:H$10000,Variable!$B$2:$B$10000,$A13) -> 0 | I13: =SUMIFS(Variable!I$2:I$10000,Variable!$B$2:$B$10000,$A13) -> 0 | J13: =SUMIFS(Variable!J$2:J$10000,Variable!$B$2:$B$10000,$A13) -> 0 | ... AG13: =SUMIFS(Variable!AG$2:AG$10000,Variable!$B$2:$B$10000,$A13) -> 0
A14: PHL_POW_PP_COAL | C14: =SUMIFS(Variable!C$2:C$10000,Variable!$B$2:$B$10000,$A14) -> 0 | D14: =SUMIFS(Variable!D$2:D$10000,Variable!$B$2:$B$10000,$A14) -> 0.0023 | E14: =SUMIFS(Variable!E$2:E$10000,Variable!$B$2:$B$10000,$A14) -> 0.0047 | F14: =SUMIFS(Variable!F$2:F$10000,Variable!$B$2:$B$10000,$A14) -> 0.0047 | G14: =SUMIFS(Variable!G$2:G$10000,Variable!$B$2:$B$10000,$A14) -> 0.0066 | H14: =SUMIFS(Variable!H$2:H$10000,Variable!$B$2:$B$10000,$A14) -> 0.0066 | I14: =SUMIFS(Variable!I$2:I$10000,Variable!$B$2:$B$10000,$A14) -> 0.0066 | J14: =SUMIFS(Variable!J$2:J$10000,Variable!$B$2:$B$10000,$A14) -> 0.0087 | ... AG14: =SUMIFS(Variable!AG$2:AG$10000,Variable!$B$2:$B$10000,$A14) -> 0.0713
A15: PHL_POW_PP_COAL_CCS | C15: =SUMIFS(Variable!C$2:C$10000,Variable!$B$2:$B$10000,$A15) -> 0 | D15: =SUMIFS(Variable!D$2:D$10000,Variable!$B$2:$B$10000,$A15) -> 0 | E15: =SUMIFS(Variable!E$2:E$10000,Variable!$B$2:$B$10000,$A15) -> 0 | F15: =SUMIFS(Variable!F$2:F$10000,Variable!$B$2:$B$10000,$A15) -> 0 | G15: =SUMIFS(Variable!G$2:G$10000,Variable!$B$2:$B$10000,$A15) -> 0 | H15: =SUMIFS(Variable!H$2:H$10000,Variable!$B$2:$B$10000,$A15) -> 0 | I15: =SUMIFS(Variable!I$2:I$10000,Variable!$B$2:$B$10000,$A15) -> 0 | J15: =SUMIFS(Variable!J$2:J$10000,Variable!$B$2:$B$10000,$A15) -> 0 | ... AG15: =SUMIFS(Variable!AG$2:AG$10000,Variable!$B$2:$B$10000,$A15) -> 0
A16: PHL_POW_PP_H2 | C16: =SUMIFS(Variable!C$2:C$10000,Variable!$B$2:$B$10000,$A16) -> 0 | D16: =SUMIFS(Variable!D$2:D$10000,Variable!$B$2:$B$10000,$A16) -> 0 | E16: =SUMIFS(Variable!E$2:E$10000,Variable!$B$2:$B$10000,$A16) -> 0 | F16: =SUMIFS(Variable!F$2:F$10000,Variable!$B$2:$B$10000,$A16) -> 0 | G16: =SUMIFS(Variable!G$2:G$10000,Variable!$B$2:$B$10000,$A16) -> 0 | H16: =SUMIFS(Variable!H$2:H$10000,Variable!$B$2:$B$10000,$A16) -> 0 | I16: =SUMIFS(Variable!I$2:I$10000,Variable!$B$2:$B$10000,$A16) -> 0 | J16: =SUMIFS(Variable!J$2:J$10000,Variable!$B$2:$B$10000,$A16) -> 0 | ... AG16: =SUMIFS(Variable!AG$2:AG$10000,Variable!$B$2:$B$10000,$A16) -> 0
A17: PHL_POW_PP_HY_LA | C17: =SUMIFS(Variable!C$2:C$10000,Variable!$B$2:$B$10000,$A17) -> 0.0026 | D17: =SUMIFS(Variable!D$2:D$10000,Variable!$B$2:$B$10000,$A17) -> 0.0026 | E17: =SUMIFS(Variable!E$2:E$10000,Variable!$B$2:$B$10000,$A17) -> 0.0026 | F17: =SUMIFS(Variable!F$2:F$10000,Variable!$B$2:$B$10000,$A17) -> 0.0026 | G17: =SUMIFS(Variable!G$2:G$10000,Variable!$B$2:$B$10000,$A17) -> 0.0026 | H17: =SUMIFS(Variable!H$2:H$10000,Variable!$B$2:$B$10000,$A17) -> 0.0026 | I17: =SUMIFS(Variable!I$2:I$10000,Variable!$B$2:$B$10000,$A17) -> 0.0026 | J17: =SUMIFS(Variable!J$2:J$10000,Variable!$B$2:$B$10000,$A17) -> 0.0026 | ... AG17: =SUMIFS(Variable!AG$2:AG$10000,Variable!$B$2:$B$10000,$A17) -> 0.0024
... A27: PHL_POW_TD | C27: =SUMIFS(Variable!C$2:C$10000,Variable!$B$2:$B$10000,$A27) -> 0.03 | D27: =SUMIFS(Variable!D$2:D$10000,Variable!$B$2:$B$10000,$A27) -> 0.03 | E27: =SUMIFS(Variable!E$2:E$10000,Variable!$B$2:$B$10000,$A27) -> 0.0315 | F27: =SUMIFS(Variable!F$2:F$10000,Variable!$B$2:$B$10000,$A27) -> 0.0328 | G27: =SUMIFS(Variable!G$2:G$10000,Variable!$B$2:$B$10000,$A27) -> 0.0343 | H27: =SUMIFS(Variable!H$2:H$10000,Variable!$B$2:$B$10000,$A27) -> 0.0358 | I27: =SUMIFS(Variable!I$2:I$10000,Variable!$B$2:$B$10000,$A27) -> 0.0377 | J27: =SUMIFS(Variable!J$2:J$10000,Variable!$B$2:$B$10000,$A27) -> 0.0396 | ... AG27: =SUMIFS(Variable!AG$2:AG$10000,Variable!$B$2:$B$10000,$A27) -> 0.102
A29: Only grid-connected
A30: Coal | C30: =SUM(C225,C228:C229)*C120 -> 2026.2812 | D30: =SUM(D225,D228:D229)*D120 -> 2760.2931 | E30: =SUM(E225,E228:E229)*E120 -> 2872.6021 | F30: =SUM(F225,F228:F229)*F120 -> 3101.0707 | G30: =SUM(G225,G228:G229)*G120 -> 3130.2287 | H30: =SUM(H225,H228:H229)*H120 -> 3241.6725 | I30: =SUM(I225,I228:I229)*I120 -> 3399.1631 | J30: =SUM(J225,J228:J229)*J120 -> 3563.4373 | ... AG30: =SUM(AG225,AG228:AG229)*AG120 -> 6947.5685
A31: Natural gas | C31: =SUM(C232:C233)*C122 -> 0 | D31: =SUM(D232:D233)*D122 -> 0 | E31: =SUM(E232:E233)*E122 -> 0 | F31: =SUM(F232:F233)*F122 -> 0 | G31: =SUM(G232:G233)*G122 -> 0 | H31: =SUM(H232:H233)*H122 -> 129.4351 | I31: =SUM(I232:I233)*I122 -> 134.13412 | J31: =SUM(J232:J233)*J122 -> 134.71496 | ... AG31: =SUM(AG232:AG233)*AG122 -> 865.76634
A32: Oil | C32: =C239*C121 -> 713.04759 | D32: =D239*D121 -> 0 | E32: =E239*E121 -> 0 | F32: =F239*F121 -> 0 | G32: =G239*G121 -> 0 | H32: =H239*H121 -> 0 | I32: =I239*I121 -> 0 | J32: =J239*J121 -> 0 | ... AG32: =AG239*AG121 -> 0
A33: Biomass | C33: =SUM(C224,C227)*C123 -> 370.128 | D33: =SUM(D224,D227)*D123 -> 0 | E33: =SUM(E224,E227)*E123 -> 0 | F33: =SUM(F224,F227)*F123 -> 0 | G33: =SUM(G224,G227)*G123 -> 0 | H33: =SUM(H224,H227)*H123 -> 0 | I33: =SUM(I224,I227)*I123 -> 0 | J33: =SUM(J224,J227)*J123 -> 0 | ... AG33: =SUM(AG224,AG227)*AG123 -> 0
A34: Uranium | C34: =C241*C124 -> 0 | D34: =D241*D124 -> 0 | E34: =E241*E124 -> 0 | F34: =F241*F124 -> 0 | G34: =G241*G124 -> 0 | H34: =H241*H124 -> 0 | I34: =I241*I124 -> 0 | J34: =J241*J124 -> 0 | ... AG34: =AG241*AG124 -> 0
A35: TOTAL (Fixed & Variable) | C35: =SUM(C38:C55)+SUM(C30:C34)+SUM(C10:C27) -> 4162.8638 | D35: =SUM(D38:D55)+SUM(D30:D34)+SUM(D10:D27) -> 3853.8406 | E35: =SUM(E38:E55)+SUM(E30:E34)+SUM(E10:E27) -> 4014.6511 | F35: =SUM(F38:F55)+SUM(F30:F34)+SUM(F10:F27) -> 4210.1257 | G35: =SUM(G38:G55)+SUM(G30:G34)+SUM(G10:G27) -> 4252.9125 | H35: =SUM(H38:H55)+SUM(H30:H34)+SUM(H10:H27) -> 4518.7706 | I35: =SUM(I38:I55)+SUM(I30:I34)+SUM(I10:I27) -> 4679.6315 | J35: =SUM(J38:J55)+SUM(J30:J34)+SUM(J10:J27) -> 4872.7074 | ... AG35: =SUM(AG38:AG55)+SUM(AG30:AG34)+SUM(AG10:AG27) -> 10472.025
A37: FIXED | C37: 2020 | D37: 2021 | E37: 2022 | F37: 2023 | G37: 2024 | H37: 2025 | I37: 2026 | J37: 2027 | K37: 2028 | L37: 2029 | M37: 2030 | N37: 2031 | O37: 2032 | P37: 2033 | Q37: 2034 | R37: 2035 | S37: 2036 | T37: 2037 | U37: 2038 | V37: 2039 | W37: 2040 | X37: 2041 | Y37: 2042 | Z37: 2043 | AA37: 2044 | AB37: 2045 | AC37: 2046 | AD37: 2047 | AE37: 2048 | AF37: 2049 | AG37: 2050
A38: PHL_POW_CHP_BIOM_OLD | C38: =SUMIFS(Fixed!C$2:C$10000,Fixed!$B$2:$B$10000,$A38) -> 44.748 | D38: =SUMIFS(Fixed!D$2:D$10000,Fixed!$B$2:$B$10000,$A38) -> 44.748 | E38: =SUMIFS(Fixed!E$2:E$10000,Fixed!$B$2:$B$10000,$A38) -> 52.128 | F38: =SUMIFS(Fixed!F$2:F$10000,Fixed!$B$2:$B$10000,$A38) -> 52.668 | G38: =SUMIFS(Fixed!G$2:G$10000,Fixed!$B$2:$B$10000,$A38) -> 53.559 | H38: =SUMIFS(Fixed!H$2:H$10000,Fixed!$B$2:$B$10000,$A38) -> 53.559 | I38: =SUMIFS(Fixed!I$2:I$10000,Fixed!$B$2:$B$10000,$A38) -> 53.559 | J38: =SUMIFS(Fixed!J$2:J$10000,Fixed!$B$2:$B$10000,$A38) -> 53.559 | ... AG38: =SUMIFS(Fixed!AG$2:AG$10000,Fixed!$B$2:$B$10000,$A38) -> 45.693
A39: PHL_POW_CHP_COAL_OLD | C39: =SUMIFS(Fixed!C$2:C$10000,Fixed!$B$2:$B$10000,$A39) -> 491.0355 | D39: =SUMIFS(Fixed!D$2:D$10000,Fixed!$B$2:$B$10000,$A39) -> 491.0355 | E39: =SUMIFS(Fixed!E$2:E$10000,Fixed!$B$2:$B$10000,$A39) -> 491.0355 | F39: =SUMIFS(Fixed!F$2:F$10000,Fixed!$B$2:$B$10000,$A39) -> 491.0355 | G39: =SUMIFS(Fixed!G$2:G$10000,Fixed!$B$2:$B$10000,$A39) -> 464.0355 | H39: =SUMIFS(Fixed!H$2:H$10000,Fixed!$B$2:$B$10000,$A39) -> 464.0355 | I39: =SUMIFS(Fixed!I$2:I$10000,Fixed!$B$2:$B$10000,$A39) -> 464.0355 | J39: =SUMIFS(Fixed!J$2:J$10000,Fixed!$B$2:$B$10000,$A39) -> 464.0355 | ... AG39: =SUMIFS(Fixed!AG$2:AG$10000,Fixed!$B$2:$B$10000,$A39) -> 286.461
A40: PHL_POW_GEO_OLD | C40: =SUMIFS(Fixed!C$2:C$10000,Fixed!$B$2:$B$10000,$A40) -> 144.394 | D40: =SUMIFS(Fixed!D$2:D$10000,Fixed!$B$2:$B$10000,$A40) -> 144.394 | E40: =SUMIFS(Fixed!E$2:E$10000,Fixed!$B$2:$B$10000,$A40) -> 144.8195 | F40: =SUMIFS(Fixed!F$2:F$10000,Fixed!$B$2:$B$10000,$A40) -> 108.537 | G40: =SUMIFS(Fixed!G$2:G$10000,Fixed!$B$2:$B$10000,$A40) -> 108.537 | H40: =SUMIFS(Fixed!H$2:H$10000,Fixed!$B$2:$B$10000,$A40) -> 112.6425 | I40: =SUMIFS(Fixed!I$2:I$10000,Fixed!$B$2:$B$10000,$A40) -> 112.6425 | J40: =SUMIFS(Fixed!J$2:J$10000,Fixed!$B$2:$B$10000,$A40) -> 112.6425 | ... AG40: =SUMIFS(Fixed!AG$2:AG$10000,Fixed!$B$2:$B$10000,$A40) -> 13.892
A41: PHL_POW_PP_BIOM_CCS | C41: =SUMIFS(Fixed!C$2:C$10000,Fixed!$B$2:$B$10000,$A41) -> 0 | D41: =SUMIFS(Fixed!D$2:D$10000,Fixed!$B$2:$B$10000,$A41) -> 0 | E41: =SUMIFS(Fixed!E$2:E$10000,Fixed!$B$2:$B$10000,$A41) -> 0 | F41: =SUMIFS(Fixed!F$2:F$10000,Fixed!$B$2:$B$10000,$A41) -> 0 | G41: =SUMIFS(Fixed!G$2:G$10000,Fixed!$B$2:$B$10000,$A41) -> 0 | H41: =SUMIFS(Fixed!H$2:H$10000,Fixed!$B$2:$B$10000,$A41) -> 0 | I41: =SUMIFS(Fixed!I$2:I$10000,Fixed!$B$2:$B$10000,$A41) -> 0 | J41: =SUMIFS(Fixed!J$2:J$10000,Fixed!$B$2:$B$10000,$A41) -> 0 | ... AG41: =SUMIFS(Fixed!AG$2:AG$10000,Fixed!$B$2:$B$10000,$A41) -> 0
A42: PHL_POW_PP_COAL | C42: =SUMIFS(Fixed!C$2:C$10000,Fixed!$B$2:$B$10000,$A42) -> 0 | D42: =SUMIFS(Fixed!D$2:D$10000,Fixed!$B$2:$B$10000,$A42) -> 32.877 | E42: =SUMIFS(Fixed!E$2:E$10000,Fixed!$B$2:$B$10000,$A42) -> 67.7675 | F42: =SUMIFS(Fixed!F$2:F$10000,Fixed!$B$2:$B$10000,$A42) -> 67.7675 | G42: =SUMIFS(Fixed!G$2:G$10000,Fixed!$B$2:$B$10000,$A42) -> 94.9761 | H42: =SUMIFS(Fixed!H$2:H$10000,Fixed!$B$2:$B$10000,$A42) -> 94.9761 | I42: =SUMIFS(Fixed!I$2:I$10000,Fixed!$B$2:$B$10000,$A42) -> 94.9761 | J42: =SUMIFS(Fixed!J$2:J$10000,Fixed!$B$2:$B$10000,$A42) -> 124.4445 | ... AG42: =SUMIFS(Fixed!AG$2:AG$10000,Fixed!$B$2:$B$10000,$A42) -> 1503.4432
A43: PHL_POW_PP_COAL_CCS | C43: =SUMIFS(Fixed!C$2:C$10000,Fixed!$B$2:$B$10000,$A43) -> 0 | D43: =SUMIFS(Fixed!D$2:D$10000,Fixed!$B$2:$B$10000,$A43) -> 0 | E43: =SUMIFS(Fixed!E$2:E$10000,Fixed!$B$2:$B$10000,$A43) -> 0 | F43: =SUMIFS(Fixed!F$2:F$10000,Fixed!$B$2:$B$10000,$A43) -> 0 | G43: =SUMIFS(Fixed!G$2:G$10000,Fixed!$B$2:$B$10000,$A43) -> 0 | H43: =SUMIFS(Fixed!H$2:H$10000,Fixed!$B$2:$B$10000,$A43) -> 0 | I43: =SUMIFS(Fixed!I$2:I$10000,Fixed!$B$2:$B$10000,$A43) -> 0 | J43: =SUMIFS(Fixed!J$2:J$10000,Fixed!$B$2:$B$10000,$A43) -> 0 | ... AG43: =SUMIFS(Fixed!AG$2:AG$10000,Fixed!$B$2:$B$10000,$A43) -> 0
A44: PHL_POW_PP_H2 | C44: =SUMIFS(Fixed!C$2:C$10000,Fixed!$B$2:$B$10000,$A44) -> 0 | D44: =SUMIFS(Fixed!D$2:D$10000,Fixed!$B$2:$B$10000,$A44) -> 0 | E44: =SUMIFS(Fixed!E$2:E$10000,Fixed!$B$2:$B$10000,$A44) -> 0 | F44: =SUMIFS(Fixed!F$2:F$10000,Fixed!$B$2:$B$10000,$A44) -> 0 | G44: =SUMIFS(Fixed!G$2:G$10000,Fixed!$B$2:$B$10000,$A44) -> 0 | H44: =SUMIFS(Fixed!H$2:H$10000,Fixed!$B$2:$B$10000,$A44) -> 0 | I44: =SUMIFS(Fixed!I$2:I$10000,Fixed!$B$2:$B$10000,$A44) -> 0 | J44: =SUMIFS(Fixed!J$2:J$10000,Fixed!$B$2:$B$10000,$A44) -> 0 | ... AG44: =SUMIFS(Fixed!AG$2:AG$10000,Fixed!$B$2:$B$10000,$A44) -> 0
A45: PHL_POW_PP_HY_LA | C45: =SUMIFS(Fixed!C$2:C$10000,Fixed!$B$2:$B$10000,$A45) -> 191.6825 | D45: =SUMIFS(Fixed!D$2:D$10000,Fixed!$B$2:$B$10000,$A45) -> 191.6825 | E45: =SUMIFS(Fixed!E$2:E$10000,Fixed!$B$2:$B$10000,$A45) -> 192.2768 | F45: =SUMIFS(Fixed!F$2:F$10000,Fixed!$B$2:$B$10000,$A45) -> 194.0261 | G45: =SUMIFS(Fixed!G$2:G$10000,Fixed!$B$2:$B$10000,$A45) -> 195.3418 | H45: =SUMIFS(Fixed!H$2:H$10000,Fixed!$B$2:$B$10000,$A45) -> 195.3418 | I45: =SUMIFS(Fixed!I$2:I$10000,Fixed!$B$2:$B$10000,$A45) -> 195.3418 | J45: =SUMIFS(Fixed!J$2:J$10000,Fixed!$B$2:$B$10000,$A45) -> 195.3418 | ... AG45: =SUMIFS(Fixed!AG$2:AG$10000,Fixed!$B$2:$B$10000,$A45) -> 194.4896
A46: PHL_POW_PP_NGCC | C46: =SUMIFS(Fixed!C$2:C$10000,Fixed!$B$2:$B$10000,$A46) -> 0 | D46: =SUMIFS(Fixed!D$2:D$10000,Fixed!$B$2:$B$10000,$A46) -> 0 | E46: =SUMIFS(Fixed!E$2:E$10000,Fixed!$B$2:$B$10000,$A46) -> 0 | F46: =SUMIFS(Fixed!F$2:F$10000,Fixed!$B$2:$B$10000,$A46) -> 0 | G46: =SUMIFS(Fixed!G$2:G$10000,Fixed!$B$2:$B$10000,$A46) -> 0 | H46: =SUMIFS(Fixed!H$2:H$10000,Fixed!$B$2:$B$10000,$A46) -> 19.0192 | I46: =SUMIFS(Fixed!I$2:I$10000,Fixed!$B$2:$B$10000,$A46) -> 19.0192 | J46: =SUMIFS(Fixed!J$2:J$10000,Fixed!$B$2:$B$10000,$A46) -> 19.0192 | ... AG46: =SUMIFS(Fixed!AG$2:AG$10000,Fixed!$B$2:$B$10000,$A46) -> 194.0733
A47: PHL_POW_PP_NGCC_CCS | C47: =SUMIFS(Fixed!C$2:C$10000,Fixed!$B$2:$B$10000,$A47) -> 0 | D47: =SUMIFS(Fixed!D$2:D$10000,Fixed!$B$2:$B$10000,$A47) -> 0 | E47: =SUMIFS(Fixed!E$2:E$10000,Fixed!$B$2:$B$10000,$A47) -> 0 | F47: =SUMIFS(Fixed!F$2:F$10000,Fixed!$B$2:$B$10000,$A47) -> 0 | G47: =SUMIFS(Fixed!G$2:G$10000,Fixed!$B$2:$B$10000,$A47) -> 0 | H47: =SUMIFS(Fixed!H$2:H$10000,Fixed!$B$2:$B$10000,$A47) -> 0 | I47: =SUMIFS(Fixed!I$2:I$10000,Fixed!$B$2:$B$10000,$A47) -> 0 | J47: =SUMIFS(Fixed!J$2:J$10000,Fixed!$B$2:$B$10000,$A47) -> 0 | ... AG47: =SUMIFS(Fixed!AG$2:AG$10000,Fixed!$B$2:$B$10000,$A47) -> 0
A48: PHL_POW_PP_NU | C48: =SUMIFS(Fixed!C$2:C$10000,Fixed!$B$2:$B$10000,$A48) -> 0 | D48: =SUMIFS(Fixed!D$2:D$10000,Fixed!$B$2:$B$10000,$A48) -> 0 | E48: =SUMIFS(Fixed!E$2:E$10000,Fixed!$B$2:$B$10000,$A48) -> 0 | F48: =SUMIFS(Fixed!F$2:F$10000,Fixed!$B$2:$B$10000,$A48) -> 0 | G48: =SUMIFS(Fixed!G$2:G$10000,Fixed!$B$2:$B$10000,$A48) -> 0 | H48: =SUMIFS(Fixed!H$2:H$10000,Fixed!$B$2:$B$10000,$A48) -> 0 | I48: =SUMIFS(Fixed!I$2:I$10000,Fixed!$B$2:$B$10000,$A48) -> 0 | J48: =SUMIFS(Fixed!J$2:J$10000,Fixed!$B$2:$B$10000,$A48) -> 0 | ... AG48: =SUMIFS(Fixed!AG$2:AG$10000,Fixed!$B$2:$B$10000,$A48) -> 0
A49: PHL_POW_PP_NUSMR | C49: =SUMIFS(Fixed!C$2:C$10000,Fixed!$B$2:$B$10000,$A49) -> 0 | D49: =SUMIFS(Fixed!D$2:D$10000,Fixed!$B$2:$B$10000,$A49) -> 0 | E49: =SUMIFS(Fixed!E$2:E$10000,Fixed!$B$2:$B$10000,$A49) -> 0 | F49: =SUMIFS(Fixed!F$2:F$10000,Fixed!$B$2:$B$10000,$A49) -> 0 | G49: =SUMIFS(Fixed!G$2:G$10000,Fixed!$B$2:$B$10000,$A49) -> 0 | H49: =SUMIFS(Fixed!H$2:H$10000,Fixed!$B$2:$B$10000,$A49) -> 0 | I49: =SUMIFS(Fixed!I$2:I$10000,Fixed!$B$2:$B$10000,$A49) -> 0 | J49: =SUMIFS(Fixed!J$2:J$10000,Fixed!$B$2:$B$10000,$A49) -> 0 | ... AG49: =SUMIFS(Fixed!AG$2:AG$10000,Fixed!$B$2:$B$10000,$A49) -> 0
... A55: PHL_POW_TD | C55: =SUMIFS(Fixed!C$2:C$10000,Fixed!$B$2:$B$10000,$A55) -> 0 | D55: =SUMIFS(Fixed!D$2:D$10000,Fixed!$B$2:$B$10000,$A55) -> 0 | E55: =SUMIFS(Fixed!E$2:E$10000,Fixed!$B$2:$B$10000,$A55) -> 0 | F55: =SUMIFS(Fixed!F$2:F$10000,Fixed!$B$2:$B$10000,$A55) -> 0 | G55: =SUMIFS(Fixed!G$2:G$10000,Fixed!$B$2:$B$10000,$A55) -> 0 | H55: =SUMIFS(Fixed!H$2:H$10000,Fixed!$B$2:$B$10000,$A55) -> 0 | I55: =SUMIFS(Fixed!I$2:I$10000,Fixed!$B$2:$B$10000,$A55) -> 0 | J55: =SUMIFS(Fixed!J$2:J$10000,Fixed!$B$2:$B$10000,$A55) -> 0 | ... AG55: =SUMIFS(Fixed!AG$2:AG$10000,Fixed!$B$2:$B$10000,$A55) -> 0
A58: Capital Investments (M.USD) | C58: 2020 | D58: 2021 | E58: 2022 | F58: 2023 | G58: 2024 | H58: 2025 | I58: 2026 | J58: 2027 | K58: 2028 | L58: 2029 | M58: 2030 | N58: 2031 | O58: 2032 | P58: 2033 | Q58: 2034 | R58: 2035 | S58: 2036 | T58: 2037 | U58: 2038 | V58: 2039 | W58: 2040 | X58: 2041 | Y58: 2042 | Z58: 2043 | AA58: 2044 | AB58: 2045 | AC58: 2046 | AD58: 2047 | AE58: 2048 | AF58: 2049 | AG58: 2050
A59: PHL_POW_CHP_BIOM_OLD | C59: =SUMIFS(Capital_Investments!C$2:C$10000,Capital_Investments!$B$2:$B$10000,$A59) -> 0 | D59: =SUMIFS(Capital_Investments!D$2:D$10000,Capital_Investments!$B$2:$B$10000,$A59) -> 0 | E59: =SUMIFS(Capital_Investments!E$2:E$10000,Capital_Investments!$B$2:$B$10000,$A59) -> 820 | F59: =SUMIFS(Capital_Investments!F$2:F$10000,Capital_Investments!$B$2:$B$10000,$A59) -> 60 | G59: =SUMIFS(Capital_Investments!G$2:G$10000,Capital_Investments!$B$2:$B$10000,$A59) -> 99 | H59: =SUMIFS(Capital_Investments!H$2:H$10000,Capital_Investments!$B$2:$B$10000,$A59) -> 0 | I59: =SUMIFS(Capital_Investments!I$2:I$10000,Capital_Investments!$B$2:$B$10000,$A59) -> 0 | J59: =SUMIFS(Capital_Investments!J$2:J$10000,Capital_Investments!$B$2:$B$10000,$A59) -> 0 | ... AG59: =SUMIFS(Capital_Investments!AG$2:AG$10000,Capital_Investments!$B$2:$B$10000,$A59) -> 0
A60: PHL_POW_CHP_COAL_OLD | C60: =SUMIFS(Capital_Investments!C$2:C$10000,Capital_Investments!$B$2:$B$10000,$A60) -> 0 | D60: =SUMIFS(Capital_Investments!D$2:D$10000,Capital_Investments!$B$2:$B$10000,$A60) -> 0 | E60: =SUMIFS(Capital_Investments!E$2:E$10000,Capital_Investments!$B$2:$B$10000,$A60) -> 0 | F60: =SUMIFS(Capital_Investments!F$2:F$10000,Capital_Investments!$B$2:$B$10000,$A60) -> 0 | G60: =SUMIFS(Capital_Investments!G$2:G$10000,Capital_Investments!$B$2:$B$10000,$A60) -> 0 | H60: =SUMIFS(Capital_Investments!H$2:H$10000,Capital_Investments!$B$2:$B$10000,$A60) -> 0 | I60: =SUMIFS(Capital_Investments!I$2:I$10000,Capital_Investments!$B$2:$B$10000,$A60) -> 0 | J60: =SUMIFS(Capital_Investments!J$2:J$10000,Capital_Investments!$B$2:$B$10000,$A60) -> 0 | ... AG60: =SUMIFS(Capital_Investments!AG$2:AG$10000,Capital_Investments!$B$2:$B$10000,$A60) -> 0
A61: PHL_POW_GEO_OLD | C61: =SUMIFS(Capital_Investments!C$2:C$10000,Capital_Investments!$B$2:$B$10000,$A61) -> 0 | D61: =SUMIFS(Capital_Investments!D$2:D$10000,Capital_Investments!$B$2:$B$10000,$A61) -> 0 | E61: =SUMIFS(Capital_Investments!E$2:E$10000,Capital_Investments!$B$2:$B$10000,$A61) -> 37 | F61: =SUMIFS(Capital_Investments!F$2:F$10000,Capital_Investments!$B$2:$B$10000,$A61) -> 0 | G61: =SUMIFS(Capital_Investments!G$2:G$10000,Capital_Investments!$B$2:$B$10000,$A61) -> 0 | H61: =SUMIFS(Capital_Investments!H$2:H$10000,Capital_Investments!$B$2:$B$10000,$A61) -> 357 | I61: =SUMIFS(Capital_Investments!I$2:I$10000,Capital_Investments!$B$2:$B$10000,$A61) -> 0 | J61: =SUMIFS(Capital_Investments!J$2:J$10000,Capital_Investments!$B$2:$B$10000,$A61) -> 0 | ... AG61: =SUMIFS(Capital_Investments!AG$2:AG$10000,Capital_Investments!$B$2:$B$10000,$A61) -> 0
A62: PHL_POW_PP_BIOM_CCS | C62: =SUMIFS(Capital_Investments!C$2:C$10000,Capital_Investments!$B$2:$B$10000,$A62) -> 0 | D62: =SUMIFS(Capital_Investments!D$2:D$10000,Capital_Investments!$B$2:$B$10000,$A62) -> 0 | E62: =SUMIFS(Capital_Investments!E$2:E$10000,Capital_Investments!$B$2:$B$10000,$A62) -> 0 | F62: =SUMIFS(Capital_Investments!F$2:F$10000,Capital_Investments!$B$2:$B$10000,$A62) -> 0 | G62: =SUMIFS(Capital_Investments!G$2:G$10000,Capital_Investments!$B$2:$B$10000,$A62) -> 0 | H62: =SUMIFS(Capital_Investments!H$2:H$10000,Capital_Investments!$B$2:$B$10000,$A62) -> 0 | I62: =SUMIFS(Capital_Investments!I$2:I$10000,Capital_Investments!$B$2:$B$10000,$A62) -> 0 | J62: =SUMIFS(Capital_Investments!J$2:J$10000,Capital_Investments!$B$2:$B$10000,$A62) -> 0 | ... AG62: =SUMIFS(Capital_Investments!AG$2:AG$10000,Capital_Investments!$B$2:$B$10000,$A62) -> 0
A63: PHL_POW_PP_COAL | C63: =SUMIFS(Capital_Investments!C$2:C$10000,Capital_Investments!$B$2:$B$10000,$A63) -> 0 | D63: =SUMIFS(Capital_Investments!D$2:D$10000,Capital_Investments!$B$2:$B$10000,$A63) -> 1129.1444 | E63: =SUMIFS(Capital_Investments!E$2:E$10000,Capital_Investments!$B$2:$B$10000,$A63) -> 1198.2948 | F63: =SUMIFS(Capital_Investments!F$2:F$10000,Capital_Investments!$B$2:$B$10000,$A63) -> 0 | G63: =SUMIFS(Capital_Investments!G$2:G$10000,Capital_Investments!$B$2:$B$10000,$A63) -> 934.4644 | H63: =SUMIFS(Capital_Investments!H$2:H$10000,Capital_Investments!$B$2:$B$10000,$A63) -> 0 | I63: =SUMIFS(Capital_Investments!I$2:I$10000,Capital_Investments!$B$2:$B$10000,$A63) -> 0 | J63: =SUMIFS(Capital_Investments!J$2:J$10000,Capital_Investments!$B$2:$B$10000,$A63) -> 1012.0767 | ... AG63: =SUMIFS(Capital_Investments!AG$2:AG$10000,Capital_Investments!$B$2:$B$10000,$A63) -> 20928.814
A64: PHL_POW_PP_COAL_CCS | C64: =SUMIFS(Capital_Investments!C$2:C$10000,Capital_Investments!$B$2:$B$10000,$A64) -> 0 | D64: =SUMIFS(Capital_Investments!D$2:D$10000,Capital_Investments!$B$2:$B$10000,$A64) -> 0 | E64: =SUMIFS(Capital_Investments!E$2:E$10000,Capital_Investments!$B$2:$B$10000,$A64) -> 0 | F64: =SUMIFS(Capital_Investments!F$2:F$10000,Capital_Investments!$B$2:$B$10000,$A64) -> 0 | G64: =SUMIFS(Capital_Investments!G$2:G$10000,Capital_Investments!$B$2:$B$10000,$A64) -> 0 | H64: =SUMIFS(Capital_Investments!H$2:H$10000,Capital_Investments!$B$2:$B$10000,$A64) -> 0 | I64: =SUMIFS(Capital_Investments!I$2:I$10000,Capital_Investments!$B$2:$B$10000,$A64) -> 0 | J64: =SUMIFS(Capital_Investments!J$2:J$10000,Capital_Investments!$B$2:$B$10000,$A64) -> 0 | ... AG64: =SUMIFS(Capital_Investments!AG$2:AG$10000,Capital_Investments!$B$2:$B$10000,$A64) -> 0
A65: PHL_POW_PP_H2 | C65: =SUMIFS(Capital_Investments!C$2:C$10000,Capital_Investments!$B$2:$B$10000,$A65) -> 0 | D65: =SUMIFS(Capital_Investments!D$2:D$10000,Capital_Investments!$B$2:$B$10000,$A65) -> 0 | E65: =SUMIFS(Capital_Investments!E$2:E$10000,Capital_Investments!$B$2:$B$10000,$A65) -> 0 | F65: =SUMIFS(Capital_Investments!F$2:F$10000,Capital_Investments!$B$2:$B$10000,$A65) -> 0 | G65: =SUMIFS(Capital_Investments!G$2:G$10000,Capital_Investments!$B$2:$B$10000,$A65) -> 0 | H65: =SUMIFS(Capital_Investments!H$2:H$10000,Capital_Investments!$B$2:$B$10000,$A65) -> 0 | I65: =SUMIFS(Capital_Investments!I$2:I$10000,Capital_Investments!$B$2:$B$10000,$A65) -> 0 | J65: =SUMIFS(Capital_Investments!J$2:J$10000,Capital_Investments!$B$2:$B$10000,$A65) -> 0 | ... AG65: =SUMIFS(Capital_Investments!AG$2:AG$10000,Capital_Investments!$B$2:$B$10000,$A65) -> 0
A66: PHL_POW_PP_HY_LA | C66: =SUMIFS(Capital_Investments!C$2:C$10000,Capital_Investments!$B$2:$B$10000,$A66) -> 2486.1775 | D66: =SUMIFS(Capital_Investments!D$2:D$10000,Capital_Investments!$B$2:$B$10000,$A66) -> 0 | E66: =SUMIFS(Capital_Investments!E$2:E$10000,Capital_Investments!$B$2:$B$10000,$A66) -> 27.0141 | F66: =SUMIFS(Capital_Investments!F$2:F$10000,Capital_Investments!$B$2:$B$10000,$A66) -> 79.5132 | G66: =SUMIFS(Capital_Investments!G$2:G$10000,Capital_Investments!$B$2:$B$10000,$A66) -> 59.8048 | H66: =SUMIFS(Capital_Investments!H$2:H$10000,Capital_Investments!$B$2:$B$10000,$A66) -> 0 | I66: =SUMIFS(Capital_Investments!I$2:I$10000,Capital_Investments!$B$2:$B$10000,$A66) -> 0 | J66: =SUMIFS(Capital_Investments!J$2:J$10000,Capital_Investments!$B$2:$B$10000,$A66) -> 0 | ... AG66: =SUMIFS(Capital_Investments!AG$2:AG$10000,Capital_Investments!$B$2:$B$10000,$A66) -> 0
A67: PHL_POW_PP_NGCC | C67: =SUMIFS(Capital_Investments!C$2:C$10000,Capital_Investments!$B$2:$B$10000,$A67) -> 0 | D67: =SUMIFS(Capital_Investments!D$2:D$10000,Capital_Investments!$B$2:$B$10000,$A67) -> 0 | E67: =SUMIFS(Capital_Investments!E$2:E$10000,Capital_Investments!$B$2:$B$10000,$A67) -> 0 | F67: =SUMIFS(Capital_Investments!F$2:F$10000,Capital_Investments!$B$2:$B$10000,$A67) -> 0 | G67: =SUMIFS(Capital_Investments!G$2:G$10000,Capital_Investments!$B$2:$B$10000,$A67) -> 0 | H67: =SUMIFS(Capital_Investments!H$2:H$10000,Capital_Investments!$B$2:$B$10000,$A67) -> 587.055 | I67: =SUMIFS(Capital_Investments!I$2:I$10000,Capital_Investments!$B$2:$B$10000,$A67) -> 0 | J67: =SUMIFS(Capital_Investments!J$2:J$10000,Capital_Investments!$B$2:$B$10000,$A67) -> 0 | ... AG67: =SUMIFS(Capital_Investments!AG$2:AG$10000,Capital_Investments!$B$2:$B$10000,$A67) -> 3393.9581
A68: PHL_POW_PP_NGCC_CCS | C68: =SUMIFS(Capital_Investments!C$2:C$10000,Capital_Investments!$B$2:$B$10000,$A68) -> 0 | D68: =SUMIFS(Capital_Investments!D$2:D$10000,Capital_Investments!$B$2:$B$10000,$A68) -> 0 | E68: =SUMIFS(Capital_Investments!E$2:E$10000,Capital_Investments!$B$2:$B$10000,$A68) -> 0 | F68: =SUMIFS(Capital_Investments!F$2:F$10000,Capital_Investments!$B$2:$B$10000,$A68) -> 0 | G68: =SUMIFS(Capital_Investments!G$2:G$10000,Capital_Investments!$B$2:$B$10000,$A68) -> 0 | H68: =SUMIFS(Capital_Investments!H$2:H$10000,Capital_Investments!$B$2:$B$10000,$A68) -> 0 | I68: =SUMIFS(Capital_Investments!I$2:I$10000,Capital_Investments!$B$2:$B$10000,$A68) -> 0 | J68: =SUMIFS(Capital_Investments!J$2:J$10000,Capital_Investments!$B$2:$B$10000,$A68) -> 0 | ... AG68: =SUMIFS(Capital_Investments!AG$2:AG$10000,Capital_Investments!$B$2:$B$10000,$A68) -> 0
A69: PHL_POW_PP_NU | C69: =SUMIFS(Capital_Investments!C$2:C$10000,Capital_Investments!$B$2:$B$10000,$A69) -> 0 | D69: =SUMIFS(Capital_Investments!D$2:D$10000,Capital_Investments!$B$2:$B$10000,$A69) -> 0 | E69: =SUMIFS(Capital_Investments!E$2:E$10000,Capital_Investments!$B$2:$B$10000,$A69) -> 0 | F69: =SUMIFS(Capital_Investments!F$2:F$10000,Capital_Investments!$B$2:$B$10000,$A69) -> 0 | G69: =SUMIFS(Capital_Investments!G$2:G$10000,Capital_Investments!$B$2:$B$10000,$A69) -> 0 | H69: =SUMIFS(Capital_Investments!H$2:H$10000,Capital_Investments!$B$2:$B$10000,$A69) -> 0 | I69: =SUMIFS(Capital_Investments!I$2:I$10000,Capital_Investments!$B$2:$B$10000,$A69) -> 0 | J69: =SUMIFS(Capital_Investments!J$2:J$10000,Capital_Investments!$B$2:$B$10000,$A69) -> 0 | ... AG69: =SUMIFS(Capital_Investments!AG$2:AG$10000,Capital_Investments!$B$2:$B$10000,$A69) -> 0
A70: PHL_POW_PP_NUSMR | C70: =SUMIFS(Capital_Investments!C$2:C$10000,Capital_Investments!$B$2:$B$10000,$A70) -> 0 | D70: =SUMIFS(Capital_Investments!D$2:D$10000,Capital_Investments!$B$2:$B$10000,$A70) -> 0 | E70: =SUMIFS(Capital_Investments!E$2:E$10000,Capital_Investments!$B$2:$B$10000,$A70) -> 0 | F70: =SUMIFS(Capital_Investments!F$2:F$10000,Capital_Investments!$B$2:$B$10000,$A70) -> 0 | G70: =SUMIFS(Capital_Investments!G$2:G$10000,Capital_Investments!$B$2:$B$10000,$A70) -> 0 | H70: =SUMIFS(Capital_Investments!H$2:H$10000,Capital_Investments!$B$2:$B$10000,$A70) -> 0 | I70: =SUMIFS(Capital_Investments!I$2:I$10000,Capital_Investments!$B$2:$B$10000,$A70) -> 0 | J70: =SUMIFS(Capital_Investments!J$2:J$10000,Capital_Investments!$B$2:$B$10000,$A70) -> 0 | ... AG70: =SUMIFS(Capital_Investments!AG$2:AG$10000,Capital_Investments!$B$2:$B$10000,$A70) -> 0
... A76: PHL_POW_TD | C76: =SUMIFS(Capital_Investments!C$2:C$10000,Capital_Investments!$B$2:$B$10000,$A76) -> 0 | D76: =SUMIFS(Capital_Investments!D$2:D$10000,Capital_Investments!$B$2:$B$10000,$A76) -> 0 | E76: =SUMIFS(Capital_Investments!E$2:E$10000,Capital_Investments!$B$2:$B$10000,$A76) -> 0 | F76: =SUMIFS(Capital_Investments!F$2:F$10000,Capital_Investments!$B$2:$B$10000,$A76) -> 0 | G76: =SUMIFS(Capital_Investments!G$2:G$10000,Capital_Investments!$B$2:$B$10000,$A76) -> 0 | H76: =SUMIFS(Capital_Investments!H$2:H$10000,Capital_Investments!$B$2:$B$10000,$A76) -> 0 | I76: =SUMIFS(Capital_Investments!I$2:I$10000,Capital_Investments!$B$2:$B$10000,$A76) -> 0 | J76: =SUMIFS(Capital_Investments!J$2:J$10000,Capital_Investments!$B$2:$B$10000,$A76) -> 0 | ... AG76: =SUMIFS(Capital_Investments!AG$2:AG$10000,Capital_Investments!$B$2:$B$10000,$A76) -> 0
A77: Total Capital Investment (Million USD) | C77: =SUM(C59:C76) -> 2844.1751 | D77: =SUM(D59:D76) -> 3215.6945 | E77: =SUM(E59:E76) -> 3334.6461 | F77: =SUM(F59:F76) -> 277.5919 | G77: =SUM(G59:G76) -> 2053.5828 | H77: =SUM(H59:H76) -> 1168.3836 | I77: =SUM(I59:I76) -> 0 | J77: =SUM(J59:J76) -> 1012.0767 | ... AG77: =SUM(AG59:AG76) -> 33451.744
A79: Annualized Investment Cost (M.USD) | C79: 2020 | D79: 2021 | E79: 2022 | F79: 2023 | G79: 2024 | H79: 2025 | I79: 2026 | J79: 2027 | K79: 2028 | L79: 2029 | M79: 2030 | N79: 2031 | O79: 2032 | P79: 2033 | Q79: 2034 | R79: 2035 | S79: 2036 | T79: 2037 | U79: 2038 | V79: 2039 | W79: 2040 | X79: 2041 | Y79: 2042 | Z79: 2043 | AA79: 2044 | AB79: 2045 | AC79: 2046 | AD79: 2047 | AE79: 2048 | AF79: 2049 | AG79: 2050
A80: PHL_POW_CHP_BIOM_OLD | C80: =SUMIFS(Annualized_Investments!C$2:C$9989,Annualized_Investments!$B$2:$B$9989,$A80) -> 0 | D80: =SUMIFS(Annualized_Investments!D$2:D$9989,Annualized_Investments!$B$2:$B$9989,$A80) -> 0 | E80: =SUMIFS(Annualized_Investments!E$2:E$9989,Annualized_Investments!$B$2:$B$9989,$A80) -> 45.512469 | F80: =SUMIFS(Annualized_Investments!F$2:F$9989,Annualized_Investments!$B$2:$B$9989,$A80) -> 48.842649 | G80: =SUMIFS(Annualized_Investments!G$2:G$9989,Annualized_Investments!$B$2:$B$9989,$A80) -> 54.337447 | H80: =SUMIFS(Annualized_Investments!H$2:H$9989,Annualized_Investments!$B$2:$B$9989,$A80) -> 54.337447 | I80: =SUMIFS(Annualized_Investments!I$2:I$9989,Annualized_Investments!$B$2:$B$9989,$A80) -> 54.337447 | J80: =SUMIFS(Annualized_Investments!J$2:J$9989,Annualized_Investments!$B$2:$B$9989,$A80) -> 54.337447 | ... AG80: =SUMIFS(Annualized_Investments!AG$2:AG$9989,Annualized_Investments!$B$2:$B$9989,$A80) -> 54.337447
A81: PHL_POW_CHP_COAL_OLD | C81: =SUMIFS(Annualized_Investments!C$2:C$9989,Annualized_Investments!$B$2:$B$9989,$A81) -> 0 | D81: =SUMIFS(Annualized_Investments!D$2:D$9989,Annualized_Investments!$B$2:$B$9989,$A81) -> 0 | E81: =SUMIFS(Annualized_Investments!E$2:E$9989,Annualized_Investments!$B$2:$B$9989,$A81) -> 0 | F81: =SUMIFS(Annualized_Investments!F$2:F$9989,Annualized_Investments!$B$2:$B$9989,$A81) -> 0 | G81: =SUMIFS(Annualized_Investments!G$2:G$9989,Annualized_Investments!$B$2:$B$9989,$A81) -> 0 | H81: =SUMIFS(Annualized_Investments!H$2:H$9989,Annualized_Investments!$B$2:$B$9989,$A81) -> 0 | I81: =SUMIFS(Annualized_Investments!I$2:I$9989,Annualized_Investments!$B$2:$B$9989,$A81) -> 0 | J81: =SUMIFS(Annualized_Investments!J$2:J$9989,Annualized_Investments!$B$2:$B$9989,$A81) -> 0 | ... AG81: =SUMIFS(Annualized_Investments!AG$2:AG$9989,Annualized_Investments!$B$2:$B$9989,$A81) -> 0
A82: PHL_POW_GEO_OLD | C82: =SUMIFS(Annualized_Investments!C$2:C$9989,Annualized_Investments!$B$2:$B$9989,$A82) -> 0 | D82: =SUMIFS(Annualized_Investments!D$2:D$9989,Annualized_Investments!$B$2:$B$9989,$A82) -> 0 | E82: =SUMIFS(Annualized_Investments!E$2:E$9989,Annualized_Investments!$B$2:$B$9989,$A82) -> 2.0536114 | F82: =SUMIFS(Annualized_Investments!F$2:F$9989,Annualized_Investments!$B$2:$B$9989,$A82) -> 2.0536114 | G82: =SUMIFS(Annualized_Investments!G$2:G$9989,Annualized_Investments!$B$2:$B$9989,$A82) -> 2.0536114 | H82: =SUMIFS(Annualized_Investments!H$2:H$9989,Annualized_Investments!$B$2:$B$9989,$A82) -> 21.868186 | I82: =SUMIFS(Annualized_Investments!I$2:I$9989,Annualized_Investments!$B$2:$B$9989,$A82) -> 21.868186 | J82: =SUMIFS(Annualized_Investments!J$2:J$9989,Annualized_Investments!$B$2:$B$9989,$A82) -> 21.868186 | ... AG82: =SUMIFS(Annualized_Investments!AG$2:AG$9989,Annualized_Investments!$B$2:$B$9989,$A82) -> 21.868186
A83: PHL_POW_PP_BIOM_CCS | C83: =SUMIFS(Annualized_Investments!C$2:C$9989,Annualized_Investments!$B$2:$B$9989,$A83) -> 0 | D83: =SUMIFS(Annualized_Investments!D$2:D$9989,Annualized_Investments!$B$2:$B$9989,$A83) -> 0 | E83: =SUMIFS(Annualized_Investments!E$2:E$9989,Annualized_Investments!$B$2:$B$9989,$A83) -> 0 | F83: =SUMIFS(Annualized_Investments!F$2:F$9989,Annualized_Investments!$B$2:$B$9989,$A83) -> 0 | G83: =SUMIFS(Annualized_Investments!G$2:G$9989,Annualized_Investments!$B$2:$B$9989,$A83) -> 0 | H83: =SUMIFS(Annualized_Investments!H$2:H$9989,Annualized_Investments!$B$2:$B$9989,$A83) -> 0 | I83: =SUMIFS(Annualized_Investments!I$2:I$9989,Annualized_Investments!$B$2:$B$9989,$A83) -> 0 | J83: =SUMIFS(Annualized_Investments!J$2:J$9989,Annualized_Investments!$B$2:$B$9989,$A83) -> 0 | ... AG83: =SUMIFS(Annualized_Investments!AG$2:AG$9989,Annualized_Investments!$B$2:$B$9989,$A83) -> 0
A84: PHL_POW_PP_COAL | C84: =SUMIFS(Annualized_Investments!C$2:C$9989,Annualized_Investments!$B$2:$B$9989,$A84) -> 0 | D84: =SUMIFS(Annualized_Investments!D$2:D$9989,Annualized_Investments!$B$2:$B$9989,$A84) -> 76.300543 | E84: =SUMIFS(Annualized_Investments!E$2:E$9989,Annualized_Investments!$B$2:$B$9989,$A84) -> 157.27384 | F84: =SUMIFS(Annualized_Investments!F$2:F$9989,Annualized_Investments!$B$2:$B$9989,$A84) -> 157.27384 | G84: =SUMIFS(Annualized_Investments!G$2:G$9989,Annualized_Investments!$B$2:$B$9989,$A84) -> 220.41912 | H84: =SUMIFS(Annualized_Investments!H$2:H$9989,Annualized_Investments!$B$2:$B$9989,$A84) -> 220.41912 | I84: =SUMIFS(Annualized_Investments!I$2:I$9989,Annualized_Investments!$B$2:$B$9989,$A84) -> 220.41912 | J84: =SUMIFS(Annualized_Investments!J$2:J$9989,Annualized_Investments!$B$2:$B$9989,$A84) -> 288.80896 | ... AG84: =SUMIFS(Annualized_Investments!AG$2:AG$9989,Annualized_Investments!$B$2:$B$9989,$A84) -> 2021.1857
A85: PHL_POW_PP_COAL_CCS | C85: =SUMIFS(Annualized_Investments!C$2:C$9989,Annualized_Investments!$B$2:$B$9989,$A85) -> 0 | D85: =SUMIFS(Annualized_Investments!D$2:D$9989,Annualized_Investments!$B$2:$B$9989,$A85) -> 0 | E85: =SUMIFS(Annualized_Investments!E$2:E$9989,Annualized_Investments!$B$2:$B$9989,$A85) -> 0 | F85: =SUMIFS(Annualized_Investments!F$2:F$9989,Annualized_Investments!$B$2:$B$9989,$A85) -> 0 | G85: =SUMIFS(Annualized_Investments!G$2:G$9989,Annualized_Investments!$B$2:$B$9989,$A85) -> 0 | H85: =SUMIFS(Annualized_Investments!H$2:H$9989,Annualized_Investments!$B$2:$B$9989,$A85) -> 0 | I85: =SUMIFS(Annualized_Investments!I$2:I$9989,Annualized_Investments!$B$2:$B$9989,$A85) -> 0 | J85: =SUMIFS(Annualized_Investments!J$2:J$9989,Annualized_Investments!$B$2:$B$9989,$A85) -> 0 | ... AG85: =SUMIFS(Annualized_Investments!AG$2:AG$9989,Annualized_Investments!$B$2:$B$9989,$A85) -> 0
A86: PHL_POW_PP_H2 | C86: =SUMIFS(Annualized_Investments!C$2:C$9989,Annualized_Investments!$B$2:$B$9989,$A86) -> 0 | D86: =SUMIFS(Annualized_Investments!D$2:D$9989,Annualized_Investments!$B$2:$B$9989,$A86) -> 0 | E86: =SUMIFS(Annualized_Investments!E$2:E$9989,Annualized_Investments!$B$2:$B$9989,$A86) -> 0 | F86: =SUMIFS(Annualized_Investments!F$2:F$9989,Annualized_Investments!$B$2:$B$9989,$A86) -> 0 | G86: =SUMIFS(Annualized_Investments!G$2:G$9989,Annualized_Investments!$B$2:$B$9989,$A86) -> 0 | H86: =SUMIFS(Annualized_Investments!H$2:H$9989,Annualized_Investments!$B$2:$B$9989,$A86) -> 0 | I86: =SUMIFS(Annualized_Investments!I$2:I$9989,Annualized_Investments!$B$2:$B$9989,$A86) -> 0 | J86: =SUMIFS(Annualized_Investments!J$2:J$9989,Annualized_Investments!$B$2:$B$9989,$A86) -> 0 | ... AG86: =SUMIFS(Annualized_Investments!AG$2:AG$9989,Annualized_Investments!$B$2:$B$9989,$A86) -> 0
A87: PHL_POW_PP_HY_LA | C87: =SUMIFS(Annualized_Investments!C$2:C$9989,Annualized_Investments!$B$2:$B$9989,$A87) -> 119.29659 | D87: =SUMIFS(Annualized_Investments!D$2:D$9989,Annualized_Investments!$B$2:$B$9989,$A87) -> 119.29659 | E87: =SUMIFS(Annualized_Investments!E$2:E$9989,Annualized_Investments!$B$2:$B$9989,$A87) -> 120.59284 | F87: =SUMIFS(Annualized_Investments!F$2:F$9989,Annualized_Investments!$B$2:$B$9989,$A87) -> 124.40819 | G87: =SUMIFS(Annualized_Investments!G$2:G$9989,Annualized_Investments!$B$2:$B$9989,$A87) -> 127.27786 | H87: =SUMIFS(Annualized_Investments!H$2:H$9989,Annualized_Investments!$B$2:$B$9989,$A87) -> 127.27786 | I87: =SUMIFS(Annualized_Investments!I$2:I$9989,Annualized_Investments!$B$2:$B$9989,$A87) -> 127.27786 | J87: =SUMIFS(Annualized_Investments!J$2:J$9989,Annualized_Investments!$B$2:$B$9989,$A87) -> 127.27786 | ... AG87: =SUMIFS(Annualized_Investments!AG$2:AG$9989,Annualized_Investments!$B$2:$B$9989,$A87) -> 127.27786
A88: PHL_POW_PP_NGCC | C88: =SUMIFS(Annualized_Investments!C$2:C$9989,Annualized_Investments!$B$2:$B$9989,$A88) -> 0 | D88: =SUMIFS(Annualized_Investments!D$2:D$9989,Annualized_Investments!$B$2:$B$9989,$A88) -> 0 | E88: =SUMIFS(Annualized_Investments!E$2:E$9989,Annualized_Investments!$B$2:$B$9989,$A88) -> 0 | F88: =SUMIFS(Annualized_Investments!F$2:F$9989,Annualized_Investments!$B$2:$B$9989,$A88) -> 0 | G88: =SUMIFS(Annualized_Investments!G$2:G$9989,Annualized_Investments!$B$2:$B$9989,$A88) -> 0 | H88: =SUMIFS(Annualized_Investments!H$2:H$9989,Annualized_Investments!$B$2:$B$9989,$A88) -> 39.669519 | I88: =SUMIFS(Annualized_Investments!I$2:I$9989,Annualized_Investments!$B$2:$B$9989,$A88) -> 39.669519 | J88: =SUMIFS(Annualized_Investments!J$2:J$9989,Annualized_Investments!$B$2:$B$9989,$A88) -> 39.669519 | ... AG88: =SUMIFS(Annualized_Investments!AG$2:AG$9989,Annualized_Investments!$B$2:$B$9989,$A88) -> 300.29201
A89: PHL_POW_PP_NGCC_CCS | C89: =SUMIFS(Annualized_Investments!C$2:C$9989,Annualized_Investments!$B$2:$B$9989,$A89) -> 0 | D89: =SUMIFS(Annualized_Investments!D$2:D$9989,Annualized_Investments!$B$2:$B$9989,$A89) -> 0 | E89: =SUMIFS(Annualized_Investments!E$2:E$9989,Annualized_Investments!$B$2:$B$9989,$A89) -> 0 | F89: =SUMIFS(Annualized_Investments!F$2:F$9989,Annualized_Investments!$B$2:$B$9989,$A89) -> 0 | G89: =SUMIFS(Annualized_Investments!G$2:G$9989,Annualized_Investments!$B$2:$B$9989,$A89) -> 0 | H89: =SUMIFS(Annualized_Investments!H$2:H$9989,Annualized_Investments!$B$2:$B$9989,$A89) -> 0 | I89: =SUMIFS(Annualized_Investments!I$2:I$9989,Annualized_Investments!$B$2:$B$9989,$A89) -> 0 | J89: =SUMIFS(Annualized_Investments!J$2:J$9989,Annualized_Investments!$B$2:$B$9989,$A89) -> 0 | ... AG89: =SUMIFS(Annualized_Investments!AG$2:AG$9989,Annualized_Investments!$B$2:$B$9989,$A89) -> 0
A90: PHL_POW_PP_NU | C90: =SUMIFS(Annualized_Investments!C$2:C$9989,Annualized_Investments!$B$2:$B$9989,$A90) -> 0 | D90: =SUMIFS(Annualized_Investments!D$2:D$9989,Annualized_Investments!$B$2:$B$9989,$A90) -> 0 | E90: =SUMIFS(Annualized_Investments!E$2:E$9989,Annualized_Investments!$B$2:$B$9989,$A90) -> 0 | F90: =SUMIFS(Annualized_Investments!F$2:F$9989,Annualized_Investments!$B$2:$B$9989,$A90) -> 0 | G90: =SUMIFS(Annualized_Investments!G$2:G$9989,Annualized_Investments!$B$2:$B$9989,$A90) -> 0 | H90: =SUMIFS(Annualized_Investments!H$2:H$9989,Annualized_Investments!$B$2:$B$9989,$A90) -> 0 | I90: =SUMIFS(Annualized_Investments!I$2:I$9989,Annualized_Investments!$B$2:$B$9989,$A90) -> 0 | J90: =SUMIFS(Annualized_Investments!J$2:J$9989,Annualized_Investments!$B$2:$B$9989,$A90) -> 0 | ... AG90: =SUMIFS(Annualized_Investments!AG$2:AG$9989,Annualized_Investments!$B$2:$B$9989,$A90) -> 0
A91: PHL_POW_PP_NUSMR | C91: =SUMIFS(Annualized_Investments!C$2:C$9989,Annualized_Investments!$B$2:$B$9989,$A91) -> 0 | D91: =SUMIFS(Annualized_Investments!D$2:D$9989,Annualized_Investments!$B$2:$B$9989,$A91) -> 0 | E91: =SUMIFS(Annualized_Investments!E$2:E$9989,Annualized_Investments!$B$2:$B$9989,$A91) -> 0 | F91: =SUMIFS(Annualized_Investments!F$2:F$9989,Annualized_Investments!$B$2:$B$9989,$A91) -> 0 | G91: =SUMIFS(Annualized_Investments!G$2:G$9989,Annualized_Investments!$B$2:$B$9989,$A91) -> 0 | H91: =SUMIFS(Annualized_Investments!H$2:H$9989,Annualized_Investments!$B$2:$B$9989,$A91) -> 0 | I91: =SUMIFS(Annualized_Investments!I$2:I$9989,Annualized_Investments!$B$2:$B$9989,$A91) -> 0 | J91: =SUMIFS(Annualized_Investments!J$2:J$9989,Annualized_Investments!$B$2:$B$9989,$A91) -> 0 | ... AG91: =SUMIFS(Annualized_Investments!AG$2:AG$9989,Annualized_Investments!$B$2:$B$9989,$A91) -> 0
... A97: PHL_POW_TD | C97: =SUMIFS(Annualized_Investments!C$2:C$9989,Annualized_Investments!$B$2:$B$9989,$A97) -> 0 | D97: =SUMIFS(Annualized_Investments!D$2:D$9989,Annualized_Investments!$B$2:$B$9989,$A97) -> 0 | E97: =SUMIFS(Annualized_Investments!E$2:E$9989,Annualized_Investments!$B$2:$B$9989,$A97) -> 0 | F97: =SUMIFS(Annualized_Investments!F$2:F$9989,Annualized_Investments!$B$2:$B$9989,$A97) -> 0 | G97: =SUMIFS(Annualized_Investments!G$2:G$9989,Annualized_Investments!$B$2:$B$9989,$A97) -> 0 | H97: =SUMIFS(Annualized_Investments!H$2:H$9989,Annualized_Investments!$B$2:$B$9989,$A97) -> 0 | I97: =SUMIFS(Annualized_Investments!I$2:I$9989,Annualized_Investments!$B$2:$B$9989,$A97) -> 0 | J97: =SUMIFS(Annualized_Investments!J$2:J$9989,Annualized_Investments!$B$2:$B$9989,$A97) -> 0 | ... AG97: =SUMIFS(Annualized_Investments!AG$2:AG$9989,Annualized_Investments!$B$2:$B$9989,$A97) -> 0
A98: Total Annualized Investments (Million USD) | C98: =SUM(C80:C97) -> 143.48784 | D98: =SUM(D80:D97) -> 337.45956 | E98: =SUM(E80:E97) -> 538.60559 | F98: =SUM(F80:F97) -> 554.30562 | G98: =SUM(G80:G97) -> 684.58792 | H98: =SUM(H80:H97) -> 757.97001 | I98: =SUM(I80:I97) -> 757.97001 | J98: =SUM(J80:J97) -> 826.35984 | ... AG98: =SUM(AG80:AG97) -> 7599.7526
A100: Annual Production by Technology (PJ) | C100: 2020 | D100: 2021 | E100: 2022 | F100: 2023 | G100: 2024 | H100: 2025 | I100: 2026 | J100: 2027 | K100: 2028 | L100: 2029 | M100: 2030 | N100: 2031 | O100: 2032 | P100: 2033 | Q100: 2034 | R100: 2035 | S100: 2036 | T100: 2037 | U100: 2038 | V100: 2039 | W100: 2040 | X100: 2041 | Y100: 2042 | Z100: 2043 | AA100: 2044 | AB100: 2045 | AC100: 2046 | AD100: 2047 | AE100: 2048 | AF100: 2049 | AG100: 2050
A101: PHL_POW_CHP_BIOM_OLD | C101: =SUMIFS(AnnualProduction!D$2:D$9924,AnnualProduction!$B$2:$B$9924,$A101) -> 4.5001 | D101: =SUMIFS(AnnualProduction!E$2:E$9924,AnnualProduction!$B$2:$B$9924,$A101) -> 0 | E101: =SUMIFS(AnnualProduction!F$2:F$9924,AnnualProduction!$B$2:$B$9924,$A101) -> 0 | F101: =SUMIFS(AnnualProduction!G$2:G$9924,AnnualProduction!$B$2:$B$9924,$A101) -> 0 | G101: =SUMIFS(AnnualProduction!H$2:H$9924,AnnualProduction!$B$2:$B$9924,$A101) -> 0 | H101: =SUMIFS(AnnualProduction!I$2:I$9924,AnnualProduction!$B$2:$B$9924,$A101) -> 0 | I101: =SUMIFS(AnnualProduction!J$2:J$9924,AnnualProduction!$B$2:$B$9924,$A101) -> 0 | J101: =SUMIFS(AnnualProduction!K$2:K$9924,AnnualProduction!$B$2:$B$9924,$A101) -> 0 | ... AG101: =SUMIFS(AnnualProduction!AH$2:AH$9924,AnnualProduction!$B$2:$B$9924,$A101) -> 0
A102: PHL_POW_CHP_COAL_OLD | C102: =SUMIFS(AnnualProduction!D$2:D$9924,AnnualProduction!$B$2:$B$9924,$A102) -> 209.448 | D102: =SUMIFS(AnnualProduction!E$2:E$9924,AnnualProduction!$B$2:$B$9924,$A102) -> 267.4663 | E102: =SUMIFS(AnnualProduction!F$2:F$9924,AnnualProduction!$B$2:$B$9924,$A102) -> 260.1144 | F102: =SUMIFS(AnnualProduction!G$2:G$9924,AnnualProduction!$B$2:$B$9924,$A102) -> 282.3083 | G102: =SUMIFS(AnnualProduction!H$2:H$9924,AnnualProduction!$B$2:$B$9924,$A102) -> 270.198 | H102: =SUMIFS(AnnualProduction!I$2:I$9924,AnnualProduction!$B$2:$B$9924,$A102) -> 280.2652 | I102: =SUMIFS(AnnualProduction!J$2:J$9924,AnnualProduction!$B$2:$B$9924,$A102) -> 294.9046 | J102: =SUMIFS(AnnualProduction!K$2:K$9924,AnnualProduction!$B$2:$B$9924,$A102) -> 295.1153 | ... AG102: =SUMIFS(AnnualProduction!AH$2:AH$9924,AnnualProduction!$B$2:$B$9924,$A102) -> 82.2351
A103: PHL_POW_GEO_OLD | C103: =SUMIFS(AnnualProduction!D$2:D$9924,AnnualProduction!$B$2:$B$9924,$A103) -> 38.8084 | D103: =SUMIFS(AnnualProduction!E$2:E$9924,AnnualProduction!$B$2:$B$9924,$A103) -> 39.597 | E103: =SUMIFS(AnnualProduction!F$2:F$9924,AnnualProduction!$B$2:$B$9924,$A103) -> 39.7134 | F103: =SUMIFS(AnnualProduction!G$2:G$9924,AnnualProduction!$B$2:$B$9924,$A103) -> 29.763 | G103: =SUMIFS(AnnualProduction!H$2:H$9924,AnnualProduction!$B$2:$B$9924,$A103) -> 29.763 | H103: =SUMIFS(AnnualProduction!I$2:I$9924,AnnualProduction!$B$2:$B$9924,$A103) -> 30.8892 | I103: =SUMIFS(AnnualProduction!J$2:J$9924,AnnualProduction!$B$2:$B$9924,$A103) -> 30.8892 | J103: =SUMIFS(AnnualProduction!K$2:K$9924,AnnualProduction!$B$2:$B$9924,$A103) -> 30.8892 | ... AG103: =SUMIFS(AnnualProduction!AH$2:AH$9924,AnnualProduction!$B$2:$B$9924,$A103) -> 3.6265
A104: PHL_POW_PP_BIOM_CCS | C104: =SUMIFS(AnnualProduction!D$2:D$9924,AnnualProduction!$B$2:$B$9924,$A104) -> 0 | D104: =SUMIFS(AnnualProduction!E$2:E$9924,AnnualProduction!$B$2:$B$9924,$A104) -> 0 | E104: =SUMIFS(AnnualProduction!F$2:F$9924,AnnualProduction!$B$2:$B$9924,$A104) -> 0 | F104: =SUMIFS(AnnualProduction!G$2:G$9924,AnnualProduction!$B$2:$B$9924,$A104) -> 0 | G104: =SUMIFS(AnnualProduction!H$2:H$9924,AnnualProduction!$B$2:$B$9924,$A104) -> 0 | H104: =SUMIFS(AnnualProduction!I$2:I$9924,AnnualProduction!$B$2:$B$9924,$A104) -> 0 | I104: =SUMIFS(AnnualProduction!J$2:J$9924,AnnualProduction!$B$2:$B$9924,$A104) -> 0 | J104: =SUMIFS(AnnualProduction!K$2:K$9924,AnnualProduction!$B$2:$B$9924,$A104) -> 0 | ... AG104: =SUMIFS(AnnualProduction!AH$2:AH$9924,AnnualProduction!$B$2:$B$9924,$A104) -> 0
A105: PHL_POW_PP_COAL | C105: =SUMIFS(AnnualProduction!D$2:D$9924,AnnualProduction!$B$2:$B$9924,$A105) -> 0 | D105: =SUMIFS(AnnualProduction!E$2:E$9924,AnnualProduction!$B$2:$B$9924,$A105) -> 22.863 | E105: =SUMIFS(AnnualProduction!F$2:F$9924,AnnualProduction!$B$2:$B$9924,$A105) -> 47.1276 | F105: =SUMIFS(AnnualProduction!G$2:G$9924,AnnualProduction!$B$2:$B$9924,$A105) -> 47.1276 | G105: =SUMIFS(AnnualProduction!H$2:H$9924,AnnualProduction!$B$2:$B$9924,$A105) -> 66.0492 | H105: =SUMIFS(AnnualProduction!I$2:I$9924,AnnualProduction!$B$2:$B$9924,$A105) -> 66.0492 | I105: =SUMIFS(AnnualProduction!J$2:J$9924,AnnualProduction!$B$2:$B$9924,$A105) -> 66.0492 | J105: =SUMIFS(AnnualProduction!K$2:K$9924,AnnualProduction!$B$2:$B$9924,$A105) -> 86.5416 | ... AG105: =SUMIFS(AnnualProduction!AH$2:AH$9924,AnnualProduction!$B$2:$B$9924,$A105) -> 712.8526
A106: PHL_POW_PP_COAL_CCS | C106: =SUMIFS(AnnualProduction!D$2:D$9924,AnnualProduction!$B$2:$B$9924,$A106) -> 0 | D106: =SUMIFS(AnnualProduction!E$2:E$9924,AnnualProduction!$B$2:$B$9924,$A106) -> 0 | E106: =SUMIFS(AnnualProduction!F$2:F$9924,AnnualProduction!$B$2:$B$9924,$A106) -> 0 | F106: =SUMIFS(AnnualProduction!G$2:G$9924,AnnualProduction!$B$2:$B$9924,$A106) -> 0 | G106: =SUMIFS(AnnualProduction!H$2:H$9924,AnnualProduction!$B$2:$B$9924,$A106) -> 0 | H106: =SUMIFS(AnnualProduction!I$2:I$9924,AnnualProduction!$B$2:$B$9924,$A106) -> 0 | I106: =SUMIFS(AnnualProduction!J$2:J$9924,AnnualProduction!$B$2:$B$9924,$A106) -> 0 | J106: =SUMIFS(AnnualProduction!K$2:K$9924,AnnualProduction!$B$2:$B$9924,$A106) -> 0 | ... AG106: =SUMIFS(AnnualProduction!AH$2:AH$9924,AnnualProduction!$B$2:$B$9924,$A106) -> 0
A107: PHL_POW_PP_H2 | C107: =SUMIFS(AnnualProduction!D$2:D$9924,AnnualProduction!$B$2:$B$9924,$A107) -> 0 | D107: =SUMIFS(AnnualProduction!E$2:E$9924,AnnualProduction!$B$2:$B$9924,$A107) -> 0 | E107: =SUMIFS(AnnualProduction!F$2:F$9924,AnnualProduction!$B$2:$B$9924,$A107) -> 0 | F107: =SUMIFS(AnnualProduction!G$2:G$9924,AnnualProduction!$B$2:$B$9924,$A107) -> 0 | G107: =SUMIFS(AnnualProduction!H$2:H$9924,AnnualProduction!$B$2:$B$9924,$A107) -> 0 | H107: =SUMIFS(AnnualProduction!I$2:I$9924,AnnualProduction!$B$2:$B$9924,$A107) -> 0 | I107: =SUMIFS(AnnualProduction!J$2:J$9924,AnnualProduction!$B$2:$B$9924,$A107) -> 0 | J107: =SUMIFS(AnnualProduction!K$2:K$9924,AnnualProduction!$B$2:$B$9924,$A107) -> 0 | ... AG107: =SUMIFS(AnnualProduction!AH$2:AH$9924,AnnualProduction!$B$2:$B$9924,$A107) -> 0
A108: PHL_POW_PP_HY_LA | C108: =SUMIFS(AnnualProduction!D$2:D$9924,AnnualProduction!$B$2:$B$9924,$A108) -> 25.8852 | D108: =SUMIFS(AnnualProduction!E$2:E$9924,AnnualProduction!$B$2:$B$9924,$A108) -> 25.8852 | E108: =SUMIFS(AnnualProduction!F$2:F$9924,AnnualProduction!$B$2:$B$9924,$A108) -> 25.9644 | F108: =SUMIFS(AnnualProduction!G$2:G$9924,AnnualProduction!$B$2:$B$9924,$A108) -> 26.2002 | G108: =SUMIFS(AnnualProduction!H$2:H$9924,AnnualProduction!$B$2:$B$9924,$A108) -> 26.3784 | H108: =SUMIFS(AnnualProduction!I$2:I$9924,AnnualProduction!$B$2:$B$9924,$A108) -> 26.3784 | I108: =SUMIFS(AnnualProduction!J$2:J$9924,AnnualProduction!$B$2:$B$9924,$A108) -> 26.3784 | J108: =SUMIFS(AnnualProduction!K$2:K$9924,AnnualProduction!$B$2:$B$9924,$A108) -> 26.3784 | ... AG108: =SUMIFS(AnnualProduction!AH$2:AH$9924,AnnualProduction!$B$2:$B$9924,$A108) -> 23.731
A109: PHL_POW_PP_NGCC | C109: =SUMIFS(AnnualProduction!D$2:D$9924,AnnualProduction!$B$2:$B$9924,$A109) -> 0 | D109: =SUMIFS(AnnualProduction!E$2:E$9924,AnnualProduction!$B$2:$B$9924,$A109) -> 0 | E109: =SUMIFS(AnnualProduction!F$2:F$9924,AnnualProduction!$B$2:$B$9924,$A109) -> 0 | F109: =SUMIFS(AnnualProduction!G$2:G$9924,AnnualProduction!$B$2:$B$9924,$A109) -> 0 | G109: =SUMIFS(AnnualProduction!H$2:H$9924,AnnualProduction!$B$2:$B$9924,$A109) -> 0 | H109: =SUMIFS(AnnualProduction!I$2:I$9924,AnnualProduction!$B$2:$B$9924,$A109) -> 7.547 | I109: =SUMIFS(AnnualProduction!J$2:J$9924,AnnualProduction!$B$2:$B$9924,$A109) -> 7.7919 | J109: =SUMIFS(AnnualProduction!K$2:K$9924,AnnualProduction!$B$2:$B$9924,$A109) -> 7.7964 | ... AG109: =SUMIFS(AnnualProduction!AH$2:AH$9924,AnnualProduction!$B$2:$B$9924,$A109) -> 47.7869
A110: PHL_POW_PP_NGCC_CCS | C110: =SUMIFS(AnnualProduction!D$2:D$9924,AnnualProduction!$B$2:$B$9924,$A110) -> 0 | D110: =SUMIFS(AnnualProduction!E$2:E$9924,AnnualProduction!$B$2:$B$9924,$A110) -> 0 | E110: =SUMIFS(AnnualProduction!F$2:F$9924,AnnualProduction!$B$2:$B$9924,$A110) -> 0 | F110: =SUMIFS(AnnualProduction!G$2:G$9924,AnnualProduction!$B$2:$B$9924,$A110) -> 0 | G110: =SUMIFS(AnnualProduction!H$2:H$9924,AnnualProduction!$B$2:$B$9924,$A110) -> 0 | H110: =SUMIFS(AnnualProduction!I$2:I$9924,AnnualProduction!$B$2:$B$9924,$A110) -> 0 | I110: =SUMIFS(AnnualProduction!J$2:J$9924,AnnualProduction!$B$2:$B$9924,$A110) -> 0 | J110: =SUMIFS(AnnualProduction!K$2:K$9924,AnnualProduction!$B$2:$B$9924,$A110) -> 0 | ... AG110: =SUMIFS(AnnualProduction!AH$2:AH$9924,AnnualProduction!$B$2:$B$9924,$A110) -> 0
A111: PHL_POW_PP_NU | C111: =SUMIFS(AnnualProduction!D$2:D$9924,AnnualProduction!$B$2:$B$9924,$A111) -> 0 | D111: =SUMIFS(AnnualProduction!E$2:E$9924,AnnualProduction!$B$2:$B$9924,$A111) -> 0 | E111: =SUMIFS(AnnualProduction!F$2:F$9924,AnnualProduction!$B$2:$B$9924,$A111) -> 0 | F111: =SUMIFS(AnnualProduction!G$2:G$9924,AnnualProduction!$B$2:$B$9924,$A111) -> 0 | G111: =SUMIFS(AnnualProduction!H$2:H$9924,AnnualProduction!$B$2:$B$9924,$A111) -> 0 | H111: =SUMIFS(AnnualProduction!I$2:I$9924,AnnualProduction!$B$2:$B$9924,$A111) -> 0 | I111: =SUMIFS(AnnualProduction!J$2:J$9924,AnnualProduction!$B$2:$B$9924,$A111) -> 0 | J111: =SUMIFS(AnnualProduction!K$2:K$9924,AnnualProduction!$B$2:$B$9924,$A111) -> 0 | ... AG111: =SUMIFS(AnnualProduction!AH$2:AH$9924,AnnualProduction!$B$2:$B$9924,$A111) -> 0
A112: PHL_POW_PP_NUSMR | C112: =SUMIFS(AnnualProduction!D$2:D$9924,AnnualProduction!$B$2:$B$9924,$A112) -> 0 | D112: =SUMIFS(AnnualProduction!E$2:E$9924,AnnualProduction!$B$2:$B$9924,$A112) -> 0 | E112: =SUMIFS(AnnualProduction!F$2:F$9924,AnnualProduction!$B$2:$B$9924,$A112) -> 0 | F112: =SUMIFS(AnnualProduction!G$2:G$9924,AnnualProduction!$B$2:$B$9924,$A112) -> 0 | G112: =SUMIFS(AnnualProduction!H$2:H$9924,AnnualProduction!$B$2:$B$9924,$A112) -> 0 | H112: =SUMIFS(AnnualProduction!I$2:I$9924,AnnualProduction!$B$2:$B$9924,$A112) -> 0 | I112: =SUMIFS(AnnualProduction!J$2:J$9924,AnnualProduction!$B$2:$B$9924,$A112) -> 0 | J112: =SUMIFS(AnnualProduction!K$2:K$9924,AnnualProduction!$B$2:$B$9924,$A112) -> 0 | ... AG112: =SUMIFS(AnnualProduction!AH$2:AH$9924,AnnualProduction!$B$2:$B$9924,$A112) -> 0
... A117: PHL_POW_CHP_NG_OLD | C117: =SUMIFS(AnnualProduction!D$2:D$9924,AnnualProduction!$B$2:$B$9924,$A117) -> 70.1999 | D117: =SUMIFS(AnnualProduction!E$2:E$9924,AnnualProduction!$B$2:$B$9924,$A117) -> 0 | E117: =SUMIFS(AnnualProduction!F$2:F$9924,AnnualProduction!$B$2:$B$9924,$A117) -> 0 | F117: =SUMIFS(AnnualProduction!G$2:G$9924,AnnualProduction!$B$2:$B$9924,$A117) -> 2.5742 | G117: =SUMIFS(AnnualProduction!H$2:H$9924,AnnualProduction!$B$2:$B$9924,$A117) -> 7.6658 | H117: =SUMIFS(AnnualProduction!I$2:I$9924,AnnualProduction!$B$2:$B$9924,$A117) -> 6.1766 | I117: =SUMIFS(AnnualProduction!J$2:J$9924,AnnualProduction!$B$2:$B$9924,$A117) -> 13.8689 | J117: =SUMIFS(AnnualProduction!K$2:K$9924,AnnualProduction!$B$2:$B$9924,$A117) -> 16.0469 | ... AG117: =SUMIFS(AnnualProduction!AH$2:AH$9924,AnnualProduction!$B$2:$B$9924,$A117) -> 0
A119: Variable Cost of imported fuels
A120: Price of coal as commodity | B120: MUSD/PJ | C120: 3.0333429 | D120: 3.0452852 | E120: 3.0572275 | F120: 3.0691698 | G120: 3.0811121 | H120: 3.0930544 | I120: 3.1049967 | J120: 3.116939 | K120: 3.1288812 | L120: 3.1408235 | M120: 3.1527658 | N120: 3.1909812 | O120: 3.2291965 | P120: 3.2674119 | Q120: 3.3056272 | R120: 3.3438426 | S120: 3.3820579 | T120: 3.4202732 | U120: 3.4584886 | V120: 3.4967039 | W120: 3.5349193 | X120: 3.5420846 | Y120: 3.54925 | Z120: 3.5564154 | AA120: 3.5635808 | AB120: 3.5707462 | AC120: 3.5779115 | AD120: 3.5850769 | AE120: 3.5922423 | AF120: 3.5994077 | AG120: 3.606573
A121: Price of oil as commodity | B121: MUSD/PJ | C121: 13.950989 | D121: 14.184819 | E121: 14.418649 | F121: 14.652479 | G121: 14.886309 | H121: 15.120139 | I121: 15.35397 | J121: 15.5878 | K121: 15.82163 | L121: 16.05546 | M121: 16.28929 | N121: 16.643976 | O121: 16.998662 | P121: 17.353349 | Q121: 17.708035 | R121: 18.062721 | S121: 18.417407 | T121: 18.772093 | U121: 19.126779 | V121: 19.481466 | W121: 19.836152 | X121: 19.985908 | Y121: 20.135664 | Z121: 20.285421 | AA121: 20.435177 | AB121: 20.584934 | AC121: 20.73469 | AD121: 20.884446 | AE121: 21.034203 | AF121: 21.183959 | AG121: 21.333715
A122: Price of natural gas as commodity | B122: MUSD/PJ | C122: 9.9837585 | D122: 10.021974 | E122: 10.060189 | F122: 10.098405 | G122: 10.13662 | H122: 10.174835 | I122: 10.213051 | J122: 10.251266 | K122: 10.289481 | L122: 10.327697 | M122: 10.365912 | N122: 10.401739 | O122: 10.437566 | P122: 10.473393 | Q122: 10.509219 | R122: 10.545046 | S122: 10.580873 | T122: 10.6167 | U122: 10.652527 | V122: 10.688354 | W122: 10.724181 | X122: 10.726569 | Y122: 10.728958 | Z122: 10.731346 | AA122: 10.733735 | AB122: 10.736123 | AC122: 10.738512 | AD122: 10.7409 | AE122: 10.743288 | AF122: 10.745677 | AG122: 10.748065
A123: Price of biomass as commodity | B123: MUSD/PJ | C123: 16 | D123: 16 | E123: 16 | F123: 16 | G123: 16 | H123: 16 | I123: 16 | J123: 16 | K123: 16 | L123: 16 | M123: 16 | N123: 16 | O123: 16 | P123: 16 | Q123: 16 | R123: 16 | S123: 16 | T123: 16 | U123: 16 | V123: 16 | W123: 16 | X123: 16 | Y123: 16 | Z123: 16 | AA123: 16 | AB123: 16 | AC123: 16 | AD123: 16 | AE123: 16 | AF123: 16 | AG123: 16
A124: Price of urankium as a commodity | B124: MUSD/PJ | C124: 0.481 | D124: 0.481 | E124: 0.481 | F124: 0.481 | G124: 0.481 | H124: 0.481 | I124: 0.5004 | J124: 0.5198 | K124: 0.5392 | L124: 0.5586 | M124: 0.578 | N124: 0.5733 | O124: 0.5686 | P124: 0.5639 | Q124: 0.5592 | R124: 0.5545 | S124: 0.5498 | T124: 0.5451 | U124: 0.5404 | V124: 0.5357 | W124: 0.531 | X124: 0.5435 | Y124: 0.556 | Z124: 0.5685 | AA124: 0.581 | AB124: 0.5935 | AC124: 0.606 | AD124: 0.6185 | AE124: 0.631 | AF124: 0.6435 | AG124: 0.656 | AH124: 0.656 | AI124: 0.656 | AJ124: 0.656
A128: New Capacity (GW) | C128: 2020 | D128: 2021 | E128: 2022 | F128: 2023 | G128: 2024 | H128: 2025 | I128: 2026 | J128: 2027 | K128: 2028 | L128: 2029 | M128: 2030 | N128: 2031 | O128: 2032 | P128: 2033 | Q128: 2034 | R128: 2035 | S128: 2036 | T128: 2037 | U128: 2038 | V128: 2039 | W128: 2040 | X128: 2041 | Y128: 2042 | Z128: 2043 | AA128: 2044 | AB128: 2045 | AC128: 2046 | AD128: 2047 | AE128: 2048 | AF128: 2049 | AG128: 2050
A129: PHL_POW_CHP_BIOM_OLD | C129: =SUMIFS('New Capacity'!C$2:C$10000,'New Capacity'!$B$2:$B$10000,$A129) -> 0 | D129: =SUMIFS('New Capacity'!D$2:D$10000,'New Capacity'!$B$2:$B$10000,$A129) -> 0 | E129: =SUMIFS('New Capacity'!E$2:E$10000,'New Capacity'!$B$2:$B$10000,$A129) -> 0.082 | F129: =SUMIFS('New Capacity'!F$2:F$10000,'New Capacity'!$B$2:$B$10000,$A129) -> 0.006 | G129: =SUMIFS('New Capacity'!G$2:G$10000,'New Capacity'!$B$2:$B$10000,$A129) -> 0.0099 | H129: =SUMIFS('New Capacity'!H$2:H$10000,'New Capacity'!$B$2:$B$10000,$A129) -> 0 | I129: =SUMIFS('New Capacity'!I$2:I$10000,'New Capacity'!$B$2:$B$10000,$A129) -> 0 | J129: =SUMIFS('New Capacity'!J$2:J$10000,'New Capacity'!$B$2:$B$10000,$A129) -> 0 | ... AG129: =SUMIFS('New Capacity'!AG$2:AG$10000,'New Capacity'!$B$2:$B$10000,$A129) -> 0
A130: PHL_POW_CHP_COAL_OLD | C130: =SUMIFS('New Capacity'!C$2:C$10000,'New Capacity'!$B$2:$B$10000,$A130) -> 0 | D130: =SUMIFS('New Capacity'!D$2:D$10000,'New Capacity'!$B$2:$B$10000,$A130) -> 0 | E130: =SUMIFS('New Capacity'!E$2:E$10000,'New Capacity'!$B$2:$B$10000,$A130) -> 0 | F130: =SUMIFS('New Capacity'!F$2:F$10000,'New Capacity'!$B$2:$B$10000,$A130) -> 0 | G130: =SUMIFS('New Capacity'!G$2:G$10000,'New Capacity'!$B$2:$B$10000,$A130) -> 0 | H130: =SUMIFS('New Capacity'!H$2:H$10000,'New Capacity'!$B$2:$B$10000,$A130) -> 0 | I130: =SUMIFS('New Capacity'!I$2:I$10000,'New Capacity'!$B$2:$B$10000,$A130) -> 0 | J130: =SUMIFS('New Capacity'!J$2:J$10000,'New Capacity'!$B$2:$B$10000,$A130) -> 0 | ... AG130: =SUMIFS('New Capacity'!AG$2:AG$10000,'New Capacity'!$B$2:$B$10000,$A130) -> 0
A131: PHL_POW_GEO_OLD | C131: =SUMIFS('New Capacity'!C$2:C$10000,'New Capacity'!$B$2:$B$10000,$A131) -> 0 | D131: =SUMIFS('New Capacity'!D$2:D$10000,'New Capacity'!$B$2:$B$10000,$A131) -> 0 | E131: =SUMIFS('New Capacity'!E$2:E$10000,'New Capacity'!$B$2:$B$10000,$A131) -> 0.0037 | F131: =SUMIFS('New Capacity'!F$2:F$10000,'New Capacity'!$B$2:$B$10000,$A131) -> 0 | G131: =SUMIFS('New Capacity'!G$2:G$10000,'New Capacity'!$B$2:$B$10000,$A131) -> 0 | H131: =SUMIFS('New Capacity'!H$2:H$10000,'New Capacity'!$B$2:$B$10000,$A131) -> 0.0357 | I131: =SUMIFS('New Capacity'!I$2:I$10000,'New Capacity'!$B$2:$B$10000,$A131) -> 0 | J131: =SUMIFS('New Capacity'!J$2:J$10000,'New Capacity'!$B$2:$B$10000,$A131) -> 0 | ... AG131: =SUMIFS('New Capacity'!AG$2:AG$10000,'New Capacity'!$B$2:$B$10000,$A131) -> 0
A132: PHL_POW_PP_BIOM_CCS | C132: =SUMIFS('New Capacity'!C$2:C$10000,'New Capacity'!$B$2:$B$10000,$A132) -> 0 | D132: =SUMIFS('New Capacity'!D$2:D$10000,'New Capacity'!$B$2:$B$10000,$A132) -> 0 | E132: =SUMIFS('New Capacity'!E$2:E$10000,'New Capacity'!$B$2:$B$10000,$A132) -> 0 | F132: =SUMIFS('New Capacity'!F$2:F$10000,'New Capacity'!$B$2:$B$10000,$A132) -> 0 | G132: =SUMIFS('New Capacity'!G$2:G$10000,'New Capacity'!$B$2:$B$10000,$A132) -> 0 | H132: =SUMIFS('New Capacity'!H$2:H$10000,'New Capacity'!$B$2:$B$10000,$A132) -> 0 | I132: =SUMIFS('New Capacity'!I$2:I$10000,'New Capacity'!$B$2:$B$10000,$A132) -> 0 | J132: =SUMIFS('New Capacity'!J$2:J$10000,'New Capacity'!$B$2:$B$10000,$A132) -> 0 | ... AG132: =SUMIFS('New Capacity'!AG$2:AG$10000,'New Capacity'!$B$2:$B$10000,$A132) -> 0
A133: PHL_POW_PP_COAL | C133: =SUMIFS('New Capacity'!C$2:C$10000,'New Capacity'!$B$2:$B$10000,$A133) -> 0 | D133: =SUMIFS('New Capacity'!D$2:D$10000,'New Capacity'!$B$2:$B$10000,$A133) -> 0.725 | E133: =SUMIFS('New Capacity'!E$2:E$10000,'New Capacity'!$B$2:$B$10000,$A133) -> 0.7694 | F133: =SUMIFS('New Capacity'!F$2:F$10000,'New Capacity'!$B$2:$B$10000,$A133) -> 0 | G133: =SUMIFS('New Capacity'!G$2:G$10000,'New Capacity'!$B$2:$B$10000,$A133) -> 0.6 | H133: =SUMIFS('New Capacity'!H$2:H$10000,'New Capacity'!$B$2:$B$10000,$A133) -> 0 | I133: =SUMIFS('New Capacity'!I$2:I$10000,'New Capacity'!$B$2:$B$10000,$A133) -> 0 | J133: =SUMIFS('New Capacity'!J$2:J$10000,'New Capacity'!$B$2:$B$10000,$A133) -> 0.6498 | ... AG133: =SUMIFS('New Capacity'!AG$2:AG$10000,'New Capacity'!$B$2:$B$10000,$A133) -> 13.438
A134: PHL_POW_PP_COAL_CCS | C134: =SUMIFS('New Capacity'!C$2:C$10000,'New Capacity'!$B$2:$B$10000,$A134) -> 0 | D134: =SUMIFS('New Capacity'!D$2:D$10000,'New Capacity'!$B$2:$B$10000,$A134) -> 0 | E134: =SUMIFS('New Capacity'!E$2:E$10000,'New Capacity'!$B$2:$B$10000,$A134) -> 0 | F134: =SUMIFS('New Capacity'!F$2:F$10000,'New Capacity'!$B$2:$B$10000,$A134) -> 0 | G134: =SUMIFS('New Capacity'!G$2:G$10000,'New Capacity'!$B$2:$B$10000,$A134) -> 0 | H134: =SUMIFS('New Capacity'!H$2:H$10000,'New Capacity'!$B$2:$B$10000,$A134) -> 0 | I134: =SUMIFS('New Capacity'!I$2:I$10000,'New Capacity'!$B$2:$B$10000,$A134) -> 0 | J134: =SUMIFS('New Capacity'!J$2:J$10000,'New Capacity'!$B$2:$B$10000,$A134) -> 0 | ... AG134: =SUMIFS('New Capacity'!AG$2:AG$10000,'New Capacity'!$B$2:$B$10000,$A134) -> 0
A135: PHL_POW_PP_H2 | C135: =SUMIFS('New Capacity'!C$2:C$10000,'New Capacity'!$B$2:$B$10000,$A135) -> 0 | D135: =SUMIFS('New Capacity'!D$2:D$10000,'New Capacity'!$B$2:$B$10000,$A135) -> 0 | E135: =SUMIFS('New Capacity'!E$2:E$10000,'New Capacity'!$B$2:$B$10000,$A135) -> 0 | F135: =SUMIFS('New Capacity'!F$2:F$10000,'New Capacity'!$B$2:$B$10000,$A135) -> 0 | G135: =SUMIFS('New Capacity'!G$2:G$10000,'New Capacity'!$B$2:$B$10000,$A135) -> 0 | H135: =SUMIFS('New Capacity'!H$2:H$10000,'New Capacity'!$B$2:$B$10000,$A135) -> 0 | I135: =SUMIFS('New Capacity'!I$2:I$10000,'New Capacity'!$B$2:$B$10000,$A135) -> 0 | J135: =SUMIFS('New Capacity'!J$2:J$10000,'New Capacity'!$B$2:$B$10000,$A135) -> 0 | ... AG135: =SUMIFS('New Capacity'!AG$2:AG$10000,'New Capacity'!$B$2:$B$10000,$A135) -> 0
A136: PHL_POW_PP_HY_LA | C136: =SUMIFS('New Capacity'!C$2:C$10000,'New Capacity'!$B$2:$B$10000,$A136) -> 1.4633 | D136: =SUMIFS('New Capacity'!D$2:D$10000,'New Capacity'!$B$2:$B$10000,$A136) -> 0 | E136: =SUMIFS('New Capacity'!E$2:E$10000,'New Capacity'!$B$2:$B$10000,$A136) -> 0.0159 | F136: =SUMIFS('New Capacity'!F$2:F$10000,'New Capacity'!$B$2:$B$10000,$A136) -> 0.0468 | G136: =SUMIFS('New Capacity'!G$2:G$10000,'New Capacity'!$B$2:$B$10000,$A136) -> 0.0352 | H136: =SUMIFS('New Capacity'!H$2:H$10000,'New Capacity'!$B$2:$B$10000,$A136) -> 0 | I136: =SUMIFS('New Capacity'!I$2:I$10000,'New Capacity'!$B$2:$B$10000,$A136) -> 0 | J136: =SUMIFS('New Capacity'!J$2:J$10000,'New Capacity'!$B$2:$B$10000,$A136) -> 0 | ... AG136: =SUMIFS('New Capacity'!AG$2:AG$10000,'New Capacity'!$B$2:$B$10000,$A136) -> 0
A137: PHL_POW_PP_NGCC | C137: =SUMIFS('New Capacity'!C$2:C$10000,'New Capacity'!$B$2:$B$10000,$A137) -> 0 | D137: =SUMIFS('New Capacity'!D$2:D$10000,'New Capacity'!$B$2:$B$10000,$A137) -> 0 | E137: =SUMIFS('New Capacity'!E$2:E$10000,'New Capacity'!$B$2:$B$10000,$A137) -> 0 | F137: =SUMIFS('New Capacity'!F$2:F$10000,'New Capacity'!$B$2:$B$10000,$A137) -> 0 | G137: =SUMIFS('New Capacity'!G$2:G$10000,'New Capacity'!$B$2:$B$10000,$A137) -> 0 | H137: =SUMIFS('New Capacity'!H$2:H$10000,'New Capacity'!$B$2:$B$10000,$A137) -> 0.88 | I137: =SUMIFS('New Capacity'!I$2:I$10000,'New Capacity'!$B$2:$B$10000,$A137) -> 0 | J137: =SUMIFS('New Capacity'!J$2:J$10000,'New Capacity'!$B$2:$B$10000,$A137) -> 0 | ... AG137: =SUMIFS('New Capacity'!AG$2:AG$10000,'New Capacity'!$B$2:$B$10000,$A137) -> 5.0876
A138: PHL_POW_PP_NGCC_CCS | C138: =SUMIFS('New Capacity'!C$2:C$10000,'New Capacity'!$B$2:$B$10000,$A138) -> 0 | D138: =SUMIFS('New Capacity'!D$2:D$10000,'New Capacity'!$B$2:$B$10000,$A138) -> 0 | E138: =SUMIFS('New Capacity'!E$2:E$10000,'New Capacity'!$B$2:$B$10000,$A138) -> 0 | F138: =SUMIFS('New Capacity'!F$2:F$10000,'New Capacity'!$B$2:$B$10000,$A138) -> 0 | G138: =SUMIFS('New Capacity'!G$2:G$10000,'New Capacity'!$B$2:$B$10000,$A138) -> 0 | H138: =SUMIFS('New Capacity'!H$2:H$10000,'New Capacity'!$B$2:$B$10000,$A138) -> 0 | I138: =SUMIFS('New Capacity'!I$2:I$10000,'New Capacity'!$B$2:$B$10000,$A138) -> 0 | J138: =SUMIFS('New Capacity'!J$2:J$10000,'New Capacity'!$B$2:$B$10000,$A138) -> 0 | ... AG138: =SUMIFS('New Capacity'!AG$2:AG$10000,'New Capacity'!$B$2:$B$10000,$A138) -> 0
A139: PHL_POW_PP_NU | C139: =SUMIFS('New Capacity'!C$2:C$10000,'New Capacity'!$B$2:$B$10000,$A139) -> 0 | D139: =SUMIFS('New Capacity'!D$2:D$10000,'New Capacity'!$B$2:$B$10000,$A139) -> 0 | E139: =SUMIFS('New Capacity'!E$2:E$10000,'New Capacity'!$B$2:$B$10000,$A139) -> 0 | F139: =SUMIFS('New Capacity'!F$2:F$10000,'New Capacity'!$B$2:$B$10000,$A139) -> 0 | G139: =SUMIFS('New Capacity'!G$2:G$10000,'New Capacity'!$B$2:$B$10000,$A139) -> 0 | H139: =SUMIFS('New Capacity'!H$2:H$10000,'New Capacity'!$B$2:$B$10000,$A139) -> 0 | I139: =SUMIFS('New Capacity'!I$2:I$10000,'New Capacity'!$B$2:$B$10000,$A139) -> 0 | J139: =SUMIFS('New Capacity'!J$2:J$10000,'New Capacity'!$B$2:$B$10000,$A139) -> 0 | ... AG139: =SUMIFS('New Capacity'!AG$2:AG$10000,'New Capacity'!$B$2:$B$10000,$A139) -> 0
...

Sheet Variable
A1: REGION | B1: TECHNOLOGY | C1: 2020 | D1: 2021 | E1: 2022 | F1: 2023 | G1: 2024 | H1: 2025 | I1: 2026 | J1: 2027 | K1: 2028 | L1: 2029 | M1: 2030 | N1: 2031 | O1: 2032 | P1: 2033 | Q1: 2034 | R1: 2035 | S1: 2036 | T1: 2037 | U1: 2038 | V1: 2039 | W1: 2040 | X1: 2041 | Y1: 2042 | Z1: 2043 | AA1: 2044 | AB1: 2045 | AC1: 2046 | AD1: 2047 | AE1: 2048 | AF1: 2049 | AG1: 2050
B2: PHL_AGR_FAC | C2: 0.0009 | D2: 0.001 | E2: 0.001 | F2: 0.001 | G2: 0.001 | H2: 0.001 | I2: 0.0011 | J2: 0.0011 | K2: 0.0011 | L2: 0.0011 | M2: 0.0011 | N2: 0.0012 | O2: 0.0012 | P2: 0.0012 | Q2: 0.0013 | R2: 0.0013 | S2: 0.0013 | T2: 0.0013 | U2: 0.0014 | V2: 0.0014 | W2: 0.0014 | X2: 0.0011 | Y2: 0.001 | Z2: 0.001 | AA2: 0.0009 | AB2: 0.0008 | AC2: 0.0008 | AD2: 0.0007 | AE2: 0.0006 | AF2: 0.0006 | AG2: 0.0018 | AH2: 0.0019 | AI2: 0.0019 | AJ2: 0.0019 | AL2: 0.0394
B3: PHL_AGR_HEAT_BIOM | C3: 0 | D3: 0 | E3: 0 | F3: 0 | G3: 0 | H3: 0 | I3: 0 | J3: 0 | K3: 0 | L3: 0 | M3: 0 | N3: 0 | O3: 0 | P3: 0 | Q3: 0 | R3: 0 | S3: 0 | T3: 0 | U3: 0 | V3: 0 | W3: 0 | X3: 0 | Y3: 0 | Z3: 0 | AA3: 0 | AB3: 0 | AC3: 0 | AD3: 0 | AE3: 0 | AF3: 0 | AG3: 0 | AH3: 0 | AI3: 0 | AJ3: 0 | AL3: 0
B4: PHL_AGR_HEAT_COAL | C4: 0 | D4: 0 | E4: 0 | F4: 0 | G4: 0 | H4: 0 | I4: 0 | J4: 0 | K4: 0 | L4: 0 | M4: 0 | N4: 0 | O4: 0 | P4: 0 | Q4: 0 | R4: 0 | S4: 0 | T4: 0 | U4: 0 | V4: 0 | W4: 0 | X4: 0 | Y4: 0 | Z4: 0 | AA4: 0 | AB4: 0 | AC4: 0 | AD4: 0 | AE4: 0 | AF4: 0 | AG4: 0 | AH4: 0 | AI4: 0 | AJ4: 0 | AL4: 0
B5: PHL_AGR_HEAT_ELE | C5: 0 | D5: 0 | E5: 0 | F5: 0 | G5: 0 | H5: 0 | I5: 0 | J5: 0 | K5: 0 | L5: 0 | M5: 0 | N5: 0 | O5: 0 | P5: 0 | Q5: 0 | R5: 0 | S5: 0 | T5: 0 | U5: 0 | V5: 0 | W5: 0 | X5: 0 | Y5: 0 | Z5: 0 | AA5: 0 | AB5: 0 | AC5: 0 | AD5: 0 | AE5: 0 | AF5: 0 | AG5: 0 | AH5: 0 | AI5: 0 | AJ5: 0 | AL5: 0
B6: PHL_AGR_HEAT_NG | C6: 0.0008 | D6: 0.0008 | E6: 0.0008 | F6: 0.0008 | G6: 0.0009 | H6: 0.0009 | I6: 0.0009 | J6: 0.0009 | K6: 0.0009 | L6: 0.001 | M6: 0.001 | N6: 0.001 | O6: 0.001 | P6: 0.0011 | Q6: 0.0011 | R6: 0.0011 | S6: 0.0011 | T6: 0.0012 | U6: 0.0012 | V6: 0.0012 | W6: 0.0013 | X6: 0.0012 | Y6: 0.0011 | Z6: 0.001 | AA6: 0.0009 | AB6: 0.0009 | AC6: 0.0008 | AD6: 0.0008 | AE6: 0.0007 | AF6: 0.0006 | AG6: 0.0017 | AH6: 0.0018 | AI6: 0.0018 | AJ6: 0.0019 | AL6: 0.0362
B7: PHL_AGR_HEAT_OIL | C7: 0.0001 | D7: 0.0001 | E7: 0.0001 | F7: 0.0001 | G7: 0.0001 | H7: 0.0001 | I7: 0.0001 | J7: 0.0001 | K7: 0.0001 | L7: 0.0001 | M7: 0.0001 | N7: 0.0001 | O7: 0.0001 | P7: 0.0001 | Q7: 0.0001 | R7: 0.0001 | S7: 0.0001 | T7: 0.0001 | U7: 0.0001 | V7: 0.0001 | W7: 0.0001 | X7: 0 | Y7: 0.0001 | Z7: 0 | AA7: 0.0001 | AB7: 0 | AC7: 0 | AD7: 0 | AE7: 0 | AF7: 0 | AG7: 0 | AH7: 0 | AI7: 0 | AJ7: 0 | AL7: 0.0023
B8: PHL_AGR_MOT_ELE | C8: 0 | D8: 0 | E8: 0 | F8: 0 | G8: 0 | H8: 0 | I8: 0 | J8: 0 | K8: 0 | L8: 0 | M8: 0 | N8: 0 | O8: 0 | P8: 0 | Q8: 0 | R8: 0 | S8: 0 | T8: 0 | U8: 0 | V8: 0 | W8: 0 | X8: 0 | Y8: 0 | Z8: 0 | AA8: 0 | AB8: 0 | AC8: 0 | AD8: 0 | AE8: 0 | AF8: 0 | AG8: 0 | AH8: 0 | AI8: 0 | AJ8: 0 | AL8: 0
B9: PHL_AGR_MOT_LIQ | C9: 0.0008 | D9: 0.0008 | E9: 0.0008 | F9: 0.0008 | G9: 0.0009 | H9: 0.0009 | I9: 0.0009 | J9: 0.0009 | K9: 0.0009 | L9: 0.001 | M9: 0.001 | N9: 0.001 | O9: 0.001 | P9: 0.001 | Q9: 0.0011 | R9: 0.0011 | S9: 0.0011 | T9: 0.0011 | U9: 0.0012 | V9: 0.0012 | W9: 0.0012 | X9: 0.0012 | Y9: 0.0013 | Z9: 0.0013 | AA9: 0.0013 | AB9: 0.0014 | AC9: 0.0014 | AD9: 0.0014 | AE9: 0.0015 | AF9: 0.0015 | AG9: 0.0015 | AH9: 0.0016 | AI9: 0.0016 | AJ9: 0.0017 | AL9: 0.0394
B10: PHL_AGR_UNIT | C10: 0.0009 | D10: 0.001 | E10: 0.001 | F10: 0.001 | G10: 0.001 | H10: 0.001 | I10: 0.0011 | J10: 0.0011 | K10: 0.0011 | L10: 0.0011 | M10: 0.0011 | N10: 0.0012 | O10: 0.0012 | P10: 0.0012 | Q10: 0.0013 | R10: 0.0013 | S10: 0.0013 | T10: 0.0013 | U10: 0.0014 | V10: 0.0014 | W10: 0.0014 | X10: 0.0015 | Y10: 0.0015 | Z10: 0.0015 | AA10: 0.0016 | AB10: 0.0016 | AC10: 0.0016 | AD10: 0.0017 | AE10: 0.0017 | AF10: 0.0018 | AG10: 0.0018 | AH10: 0.0019 | AI10: 0.0019 | AJ10: 0.0019 | AL10: 0.0464
B11: PHL_DEM_PUB_GWT_WAT | C11: 0 | D11: 0 | E11: 0 | F11: 0 | G11: 0 | H11: 0 | I11: 0 | J11: 0 | K11: 0 | L11: 0 | M11: 0.0004 | N11: 0 | O11: 0 | P11: 0 | Q11: 0 | R11: 0 | S11: 0 | T11: 0 | U11: 0 | V11: 0 | W11: 0 | X11: 0 | Y11: 0.0003 | Z11: 0 | AA11: 0.0002 | AB11: 0.0004 | AC11: 0 | AD11: 0 | AE11: 0.0005 | AF11: 0.0006 | AG11: 0.0007 | AH11: 0.0002 | AI11: 0 | AJ11: 0.0009 | AL11: 0.0042
B12: PHL_DEM_PUB_SUR_WAT | C12: 0.002 | D12: 0.002 | E12: 0.0021 | F12: 0.0022 | G12: 0.0023 | H12: 0.0024 | I12: 0.0025 | J12: 0.0026 | K12: 0.0026 | L12: 0.0027 | M12: 0.0024 | N12: 0.003 | O12: 0.0031 | P12: 0.0032 | Q12: 0.0033 | R12: 0.0034 | S12: 0.0036 | T12: 0.0037 | U12: 0.0038 | V12: 0.004 | W12: 0.0041 | X12: 0.0043 | Y12: 0.0041 | Z12: 0.0046 | AA12: 0.0046 | AB12: 0.0046 | AC12: 0.0052 | AD12: 0.0053 | AE12: 0.005 | AF12: 0.0051 | AG12: 0.0052 | AH12: 0.006 | AI12: 0.0064 | AJ12: 0.0057 | AL12: 0.1271
B13: PHL_DEM_PWR_GWT_WAT | C13: 0.0003 | D13: 0.0003 | E13: 0.0002 | F13: 0.0005 | G13: 0.0002 | H13: 0.0005 | I13: 0.0005 | J13: 0.0003 | K13: 0.0005 | L13: 0.0005 | M13: 0.0001 | N13: 0.0005 | O13: 0.0005 | P13: 0.0005 | Q13: 0.0006 | R13: 0.0006 | S13: 0.0006 | T13: 0.0007 | U13: 0.0007 | V13: 0.0007 | W13: 0.0007 | X13: 0.0007 | Y13: 0.0004 | Z13: 0.0007 | AA13: 0.0006 | AB13: 0.0004 | AC13: 0.0008 | AD13: 0.0008 | AE13: 0.0003 | AF13: 0.0002 | AG13: 0.0002 | AH13: 0.0008 | AI13: 0.001 | AJ13: 0.0001 | AL13: 0.017
... B133: PHL_TRA_VAN_PHEV | C133: 0 | D133: 0 | E133: 0 | F133: 0 | G133: 0 | H133: 0 | I133: 0 | J133: 0 | K133: 0 | L133: 0 | M133: 0 | N133: 0 | O133: 0 | P133: 0 | Q133: 0 | R133: 0 | S133: 0 | T133: 0 | U133: 0 | V133: 0 | W133: 0 | X133: 0 | Y133: 0 | Z133: 0 | AA133: 0 | AB133: 0 | AC133: 0 | AD133: 0 | AE133: 0 | AF133: 0 | AG133: 0 | AH133: 0 | AI133: 0 | AJ133: 0 | AL133: 0
B134: (blank)

Sheet Fixed
A1: REGION | B1: TECHNOLOGY | C1: 2020 | D1: 2021 | E1: 2022 | F1: 2023 | G1: 2024 | H1: 2025 | I1: 2026 | J1: 2027 | K1: 2028 | L1: 2029 | M1: 2030 | N1: 2031 | O1: 2032 | P1: 2033 | Q1: 2034 | R1: 2035 | S1: 2036 | T1: 2037 | U1: 2038 | V1: 2039 | W1: 2040 | X1: 2041 | Y1: 2042 | Z1: 2043 | AA1: 2044 | AB1: 2045 | AC1: 2046 | AD1: 2047 | AE1: 2048 | AF1: 2049 | AG1: 2050
A2: REGION | B2: PHL_AGR_FAC | C2: 0 | D2: 0 | E2: 0 | F2: 0 | G2: 0 | H2: 0 | I2: 0 | J2: 0 | K2: 0 | L2: 0 | M2: 0 | N2: 0 | O2: 0 | P2: 0 | Q2: 0 | R2: 0 | S2: 0 | T2: 0 | U2: 0 | V2: 0 | W2: 0 | X2: 0 | Y2: 0 | Z2: 0 | AA2: 0 | AB2: 0 | AC2: 0 | AD2: 0 | AE2: 0 | AF2: 0 | AG2: 0 | AH2: 0 | AI2: 0 | AJ2: 0
A3: REGION | B3: PHL_AGR_HEAT_BIOM | C3: 0.1835 | D3: 0.1825 | E3: 0.182 | F3: 0.181 | G3: 0.1805 | H3: 0.1799 | I3: 0.1789 | J3: 0.1784 | K3: 0.1774 | L3: 0.1769 | M3: 0.1759 | N3: 0.1753 | O3: 0.1748 | P3: 0.1738 | Q3: 0.1733 | R3: 0.1723 | S3: 0.1719 | T3: 0.1714 | U3: 0.1705 | V3: 0.1701 | W3: 0.1688 | X3: 0.1682 | Y3: 0.1673 | Z3: 0.1669 | AA3: 0.1665 | AB3: 0 | AC3: 0 | AD3: 0 | AE3: 0 | AF3: 0 | AG3: 0 | AH3: 0 | AI3: 0 | AJ3: 0
A4: REGION | B4: PHL_AGR_HEAT_COAL | C4: 0 | D4: 0 | E4: 0 | F4: 0 | G4: 0 | H4: 0 | I4: 0 | J4: 0 | K4: 0 | L4: 0 | M4: 0 | N4: 0 | O4: 0 | P4: 0 | Q4: 0 | R4: 0 | S4: 0 | T4: 0 | U4: 0 | V4: 0 | W4: 0 | X4: 0 | Y4: 0 | Z4: 0 | AA4: 0 | AB4: 0 | AC4: 0 | AD4: 0 | AE4: 0 | AF4: 0 | AG4: 0 | AH4: 0 | AI4: 0 | AJ4: 0
A5: REGION | B5: PHL_AGR_HEAT_ELE | C5: 0 | D5: 0 | E5: 0 | F5: 0 | G5: 0 | H5: 0 | I5: 0 | J5: 0 | K5: 0 | L5: 0 | M5: 0 | N5: 0 | O5: 0 | P5: 0 | Q5: 0 | R5: 0 | S5: 0 | T5: 0 | U5: 0 | V5: 0 | W5: 0 | X5: 0 | Y5: 0 | Z5: 0 | AA5: 0 | AB5: 0 | AC5: 0 | AD5: 0 | AE5: 0 | AF5: 0 | AG5: 0 | AH5: 0 | AI5: 0 | AJ5: 0
A6: REGION | B6: PHL_AGR_HEAT_NG | C6: 2.4405 | D6: 2.5553 | E6: 2.6389 | F6: 2.7214 | G6: 2.8028 | H6: 2.8833 | I6: 2.9682 | J6: 3.0524 | K6: 3.1358 | L6: 3.2185 | M6: 3.396 | N6: 3.4797 | O6: 3.5634 | P6: 3.6471 | Q6: 3.7308 | R6: 3.8145 | S6: 3.914 | T6: 4.0135 | U6: 4.1129 | V6: 4.2124 | W6: 4.2799 | X6: 4.2759 | Y6: 4.2719 | Z6: 4.2677 | AA6: 4.2677 | AB6: 3.0437 | AC6: 2.9389 | AD6: 2.8669 | AE6: 2.7948 | AF6: 2.7228 | AG6: 5.8518 | AH6: 5.9963 | AI6: 6.1409 | AJ6: 6.2854
A7: REGION | B7: PHL_AGR_HEAT_OIL | C7: 0.4512 | D7: 0.4548 | E7: 0.458 | F7: 0.4608 | G7: 0.4633 | H7: 0.4654 | I7: 0.4673 | J7: 0.4688 | K7: 0.4702 | L7: 0.4714 | M7: 0.487 | N7: 0.4863 | O7: 0.4856 | P7: 0.4849 | Q7: 0.4842 | R7: 0.4835 | S7: 0.4828 | T7: 0.4822 | U7: 0.4815 | V7: 0.4808 | W7: 0.4801 | X7: 0.4794 | Y7: 0.478 | Z7: 0.478 | AA7: 0.478 | AB7: 0 | AC7: 0 | AD7: 0 | AE7: 0 | AF7: 0 | AG7: 0 | AH7: 0 | AI7: 0 | AJ7: 0
A8: REGION | B8: PHL_AGR_MOT_ELE | C8: 0 | D8: 0 | E8: 0 | F8: 0 | G8: 0 | H8: 0 | I8: 0 | J8: 0 | K8: 0 | L8: 0 | M8: 0 | N8: 0 | O8: 0 | P8: 0 | Q8: 0 | R8: 0 | S8: 0 | T8: 0 | U8: 0 | V8: 0 | W8: 0 | X8: 0 | Y8: 0 | Z8: 0 | AA8: 0 | AB8: 0 | AC8: 0 | AD8: 0 | AE8: 0 | AF8: 0 | AG8: 0 | AH8: 0 | AI8: 0 | AJ8: 0
A9: REGION | B9: PHL_AGR_MOT_LIQ | C9: 258.9921 | D9: 264.8225 | E9: 270.6529 | F9: 276.4833 | G9: 282.3137 | H9: 288.144 | I9: 294.4654 | J9: 300.7868 | K9: 307.1081 | L9: 313.4295 | M9: 319.7508 | N9: 326.9326 | O9: 334.1143 | P9: 341.296 | Q9: 348.4777 | R9: 355.6594 | S9: 364.2035 | T9: 372.7475 | U9: 381.2916 | V9: 389.8356 | W9: 398.3797 | X9: 408.3247 | Y9: 418.2698 | Z9: 428.2148 | AA9: 438.1599 | AB9: 448.105 | AC9: 459.4445 | AD9: 470.784 | AE9: 482.1235 | AF9: 493.463 | AG9: 504.8025 | AH9: 517.2698 | AI9: 529.737 | AJ9: 542.2043
A10: REGION | B10: PHL_AGR_UNIT | C10: 0 | D10: 0 | E10: 0 | F10: 0 | G10: 0 | H10: 0 | I10: 0 | J10: 0 | K10: 0 | L10: 0 | M10: 0 | N10: 0 | O10: 0 | P10: 0 | Q10: 0 | R10: 0 | S10: 0 | T10: 0 | U10: 0 | V10: 0 | W10: 0 | X10: 0 | Y10: 0 | Z10: 0 | AA10: 0 | AB10: 0 | AC10: 0 | AD10: 0 | AE10: 0 | AF10: 0 | AG10: 0 | AH10: 0 | AI10: 0 | AJ10: 0
A11: REGION | B11: PHL_DEM_PUB_GWT_WAT | C11: 0 | D11: 0 | E11: 0 | F11: 0 | G11: 0 | H11: 0 | I11: 0 | J11: 0 | K11: 0 | L11: 0 | M11: 0 | N11: 0 | O11: 0 | P11: 0 | Q11: 0 | R11: 0 | S11: 0 | T11: 0 | U11: 0 | V11: 0 | W11: 0 | X11: 0 | Y11: 0 | Z11: 0 | AA11: 0 | AB11: 0 | AC11: 0 | AD11: 0 | AE11: 0 | AF11: 0 | AG11: 0 | AH11: 0 | AI11: 0 | AJ11: 0
A12: REGION | B12: PHL_DEM_PUB_SUR_WAT | C12: 0 | D12: 0 | E12: 0 | F12: 0 | G12: 0 | H12: 0 | I12: 0 | J12: 0 | K12: 0 | L12: 0 | M12: 0 | N12: 0 | O12: 0 | P12: 0 | Q12: 0 | R12: 0 | S12: 0 | T12: 0 | U12: 0 | V12: 0 | W12: 0 | X12: 0 | Y12: 0 | Z12: 0 | AA12: 0 | AB12: 0 | AC12: 0 | AD12: 0 | AE12: 0 | AF12: 0 | AG12: 0 | AH12: 0 | AI12: 0 | AJ12: 0
A13: REGION | B13: PHL_DEM_PWR_GWT_WAT | C13: 0 | D13: 0 | E13: 0 | F13: 0 | G13: 0 | H13: 0 | I13: 0 | J13: 0 | K13: 0 | L13: 0 | M13: 0 | N13: 0 | O13: 0 | P13: 0 | Q13: 0 | R13: 0 | S13: 0 | T13: 0 | U13: 0 | V13: 0 | W13: 0 | X13: 0 | Y13: 0 | Z13: 0 | AA13: 0 | AB13: 0 | AC13: 0 | AD13: 0 | AE13: 0 | AF13: 0 | AG13: 0 | AH13: 0 | AI13: 0 | AJ13: 0
... A132: REGION | B132: PHL_TRA_VAN_NG | C132: 0 | D132: 0 | E132: 0 | F132: 0 | G132: 0 | H132: 0 | I132: 0 | J132: 0 | K132: 0 | L132: 0 | M132: 0 | N132: 0 | O132: 0 | P132: 0 | Q132: 0 | R132: 0 | S132: 0 | T132: 0 | U132: 0 | V132: 0 | W132: 0 | X132: 0 | Y132: 0 | Z132: 0 | AA132: 0 | AB132: 0 | AC132: 0 | AD132: 0 | AE132: 0 | AF132: 0 | AG132: 0 | AH132: 0 | AI132: 0 | AJ132: 0
B133: PHL_TRA_VAN_PHEV | C133: 0 | D133: 0 | E133: 0 | F133: 0 | G133: 0 | H133: 0 | I133: 0 | J133: 0 | K133: 0 | L133: 0 | M133: 0 | N133: 0 | O133: 0 | P133: 0 | Q133: 0 | R133: 0 | S133: 0 | T133: 0 | U133: 0 | V133: 0 | W133: 0 | X133: 0 | Y133: 0 | Z133: 0 | AA133: 0 | AB133: 0 | AC133: 0 | AD133: 0 | AE133: 0 | AF133: 0 | AG133: 0 | AH133: 0 | AI133: 0 | AJ133: 0
B134: (blank)

Sheet Capital_Investments
A1: Million USD
A2: REGION | B2: TECHNOLOGY | C2: 2020 | D2: 2021 | E2: 2022 | F2: 2023 | G2: 2024 | H2: 2025 | I2: 2026 | J2: 2027 | K2: 2028 | L2: 2029 | M2: 2030 | N2: 2031 | O2: 2032 | P2: 2033 | Q2: 2034 | R2: 2035 | S2: 2036 | T2: 2037 | U2: 2038 | V2: 2039 | W2: 2040 | X2: 2041 | Y2: 2042 | Z2: 2043 | AA2: 2044 | AB2: 2045 | AC2: 2046 | AD2: 2047 | AE2: 2048 | AF2: 2049 | AG2: 2050
A3: REGION | B3: PHL_AGR_FAC | C3: 0 | D3: 0 | E3: 0 | F3: 0 | G3: 0 | H3: 0 | I3: 0 | J3: 0 | K3: 0 | L3: 0 | M3: 0 | N3: 0 | O3: 0 | P3: 0 | Q3: 0 | R3: 0 | S3: 0 | T3: 0 | U3: 0 | V3: 0 | W3: 0 | X3: 0 | Y3: 0 | Z3: 0 | AA3: 0 | AB3: 0 | AC3: 0 | AD3: 0 | AE3: 0 | AF3: 0 | AG3: 0 | AH3: 0 | AI3: 0 | AJ3: 0
A4: REGION | B4: PHL_AGR_HEAT_BIOM | C4: 2.999 | D4: 0 | E4: 0 | F4: 0 | G4: 0 | H4: 0 | I4: 0 | J4: 0 | K4: 0 | L4: 0 | M4: 0 | N4: 0 | O4: 0 | P4: 0 | Q4: 0 | R4: 0 | S4: 0 | T4: 0 | U4: 0 | V4: 0 | W4: 0 | X4: 0 | Y4: 0 | Z4: 0 | AA4: 0 | AB4: 0 | AC4: 0 | AD4: 0 | AE4: 0 | AF4: 0 | AG4: 0 | AH4: 0 | AI4: 0 | AJ4: 0
A5: REGION | B5: PHL_AGR_HEAT_COAL | C5: 0 | D5: 0 | E5: 0 | F5: 0 | G5: 0 | H5: 0 | I5: 0 | J5: 0 | K5: 0 | L5: 0 | M5: 0 | N5: 0 | O5: 0 | P5: 0 | Q5: 0 | R5: 0 | S5: 0 | T5: 0 | U5: 0 | V5: 0 | W5: 0 | X5: 0 | Y5: 0 | Z5: 0 | AA5: 0 | AB5: 0 | AC5: 0 | AD5: 0 | AE5: 0 | AF5: 0 | AG5: 0 | AH5: 0 | AI5: 0 | AJ5: 0
A6: REGION | B6: PHL_AGR_HEAT_ELE | C6: 0 | D6: 0 | E6: 0 | F6: 0 | G6: 0 | H6: 0 | I6: 0 | J6: 0 | K6: 0 | L6: 0 | M6: 0 | N6: 0 | O6: 0 | P6: 0 | Q6: 0 | R6: 0 | S6: 0 | T6: 0 | U6: 0 | V6: 0 | W6: 0 | X6: 0 | Y6: 0 | Z6: 0 | AA6: 0 | AB6: 0 | AC6: 0 | AD6: 0 | AE6: 0 | AF6: 0 | AG6: 0 | AH6: 0 | AI6: 0 | AJ6: 0
A7: REGION | B7: PHL_AGR_HEAT_NG | C7: 47.1147 | D7: 1.9432 | E7: 1.3465 | F7: 1.3559 | G7: 1.3643 | H7: 1.372 | I7: 1.4878 | J7: 1.4944 | K7: 1.5004 | L7: 1.5058 | M7: 1.5544 | N7: 1.7539 | O7: 1.7539 | P7: 1.7539 | Q7: 1.7539 | R7: 1.7539 | S7: 2.0697 | T7: 2.0697 | U7: 2.0697 | V7: 2.0697 | W7: 1.4297 | X7: 0 | Y7: 0 | Z7: 0 | AA7: 0 | AB7: 26.7657 | AC7: 0 | AD7: 0 | AE7: 0 | AF7: 0 | AG7: 64.0209 | AH7: 4.4449 | AI7: 4.4449 | AJ7: 4.4449
A8: REGION | B8: PHL_AGR_HEAT_OIL | C8: 10.9168 | D8: 0 | E8: 0 | F8: 0 | G8: 0 | H8: 0 | I8: 0 | J8: 0 | K8: 0 | L8: 0 | M8: 0 | N8: 0 | O8: 0 | P8: 0 | Q8: 0 | R8: 0 | S8: 0 | T8: 0 | U8: 0 | V8: 0 | W8: 0 | X8: 0 | Y8: 0 | Z8: 0 | AA8: 0 | AB8: 0 | AC8: 0 | AD8: 0 | AE8: 0 | AF8: 0 | AG8: 0 | AH8: 0 | AI8: 0 | AJ8: 0
A9: REGION | B9: PHL_AGR_MOT_ELE | C9: 0 | D9: 0 | E9: 0 | F9: 0 | G9: 0 | H9: 0 | I9: 0 | J9: 0 | K9: 0 | L9: 0 | M9: 0 | N9: 0 | O9: 0 | P9: 0 | Q9: 0 | R9: 0 | S9: 0 | T9: 0 | U9: 0 | V9: 0 | W9: 0 | X9: 0 | Y9: 0 | Z9: 0 | AA9: 0 | AB9: 0 | AC9: 0 | AD9: 0 | AE9: 0 | AF9: 0 | AG9: 0 | AH9: 0 | AI9: 0 | AJ9: 0
A10: REGION | B10: PHL_AGR_MOT_LIQ | C10: 14270.519 | D10: 369.9875 | E10: 369.9875 | F10: 376.4785 | G10: 382.9696 | H10: 389.4606 | I10: 425.9008 | J10: 432.8827 | K10: 439.8647 | L10: 453.8287 | M10: 460.8106 | N10: 525.4367 | O10: 533.279 | P10: 533.279 | Q10: 498.5774 | R10: 17770.378 | S10: 1037.4189 | T10: 1037.4189 | U10: 1052.454 | V10: 1052.454 | W10: 1052.454 | X10: 1184.893 | Y10: 1201.82 | Z10: 1201.82 | AA10: 1201.82 | AB10: 1201.82 | AC10: 1361.9114 | AD10: 1361.9114 | AE10: 1381.0932 | AF10: 1336.6995 | AG10: 19359.448 | AH10: 1980.1654 | AI10: 1980.1653 | AJ10: 1980.1654
A11: REGION | B11: PHL_AGR_UNIT | C11: 0 | D11: 0 | E11: 0 | F11: 0 | G11: 0 | H11: 0 | I11: 0 | J11: 0 | K11: 0 | L11: 0 | M11: 0 | N11: 0 | O11: 0 | P11: 0 | Q11: 0 | R11: 0 | S11: 0 | T11: 0 | U11: 0 | V11: 0 | W11: 0 | X11: 0 | Y11: 0 | Z11: 0 | AA11: 0 | AB11: 0 | AC11: 0 | AD11: 0 | AE11: 0 | AF11: 0 | AG11: 0 | AH11: 0 | AI11: 0 | AJ11: 0
A12: REGION | B12: PHL_DEM_PUB_GWT_WAT | C12: 0 | D12: 0 | E12: 0 | F12: 0 | G12: 0 | H12: 0 | I12: 0 | J12: 0 | K12: 0 | L12: 0 | M12: 0 | N12: 0 | O12: 0 | P12: 0 | Q12: 0 | R12: 0 | S12: 0 | T12: 0 | U12: 0 | V12: 0 | W12: 0 | X12: 0 | Y12: 0 | Z12: 0 | AA12: 0 | AB12: 0 | AC12: 0 | AD12: 0 | AE12: 0 | AF12: 0 | AG12: 0 | AH12: 0 | AI12: 0 | AJ12: 0
A13: REGION | B13: PHL_DEM_PUB_SUR_WAT | C13: 0 | D13: 0 | E13: 0 | F13: 0 | G13: 0 | H13: 0 | I13: 0 | J13: 0 | K13: 0 | L13: 0 | M13: 0 | N13: 0 | O13: 0 | P13: 0 | Q13: 0 | R13: 0 | S13: 0 | T13: 0 | U13: 0 | V13: 0 | W13: 0 | X13: 0 | Y13: 0 | Z13: 0 | AA13: 0 | AB13: 0 | AC13: 0 | AD13: 0 | AE13: 0 | AF13: 0 | AG13: 0 | AH13: 0 | AI13: 0 | AJ13: 0
A14: REGION | B14: PHL_DEM_PWR_GWT_WAT | C14: 0 | D14: 0 | E14: 0 | F14: 0 | G14: 0 | H14: 0 | I14: 0 | J14: 0 | K14: 0 | L14: 0 | M14: 0 | N14: 0 | O14: 0 | P14: 0 | Q14: 0 | R14: 0 | S14: 0 | T14: 0 | U14: 0 | V14: 0 | W14: 0 | X14: 0 | Y14: 0 | Z14: 0 | AA14: 0 | AB14: 0 | AC14: 0 | AD14: 0 | AE14: 0 | AF14: 0 | AG14: 0 | AH14: 0 | AI14: 0 | AJ14: 0
... A133: REGION | B133: PHL_TRA_VAN_NG | C133: 0 | D133: 0 | E133: 0 | F133: 0 | G133: 0 | H133: 0 | I133: 0 | J133: 0 | K133: 0 | L133: 0 | M133: 0 | N133: 0 | O133: 0 | P133: 0 | Q133: 0 | R133: 0 | S133: 0 | T133: 0 | U133: 0 | V133: 0 | W133: 0 | X133: 0 | Y133: 0 | Z133: 0 | AA133: 0 | AB133: 0 | AC133: 0 | AD133: 0 | AE133: 0 | AF133: 0 | AG133: 0 | AH133: 0 | AI133: 0 | AJ133: 0
B134: PHL_TRA_VAN_PHEV | C134: 0 | D134: 0 | E134: 0 | F134: 0 | G134: 0 | H134: 0 | I134: 0 | J134: 0 | K134: 0 | L134: 0 | M134: 0 | N134: 0 | O134: 0 | P134: 0 | Q134: 0 | R134: 0 | S134: 0 | T134: 0 | U134: 0 | V134: 0 | W134: 0 | X134: 0 | Y134: 0 | Z134: 0 | AA134: 0 | AB134: 0 | AC134: 0 | AD134: 0 | AE134: 0 | AF134: 0 | AG134: 0 | AH134: 0 | AI134: 0 | AJ134: 0
B135: (blank)
A170: REGION | B170: GHA_PRO_BLEND_BIOF | C170: 0 | D170: 0 | E170: 0 | F170: 0 | G170: 0 | H170: 0 | I170: 0 | J170: 0 | K170: 0 | L170: 0 | M170: 0 | N170: 0 | O170: 0 | P170: 0 | Q170: 0 | R170: 0 | S170: 0 | T170: 0 | U170: 0 | V170: 0 | W170: 0 | X170: 0 | Y170: 0 | Z170: 0 | AA170: 0 | AB170: 0 | AC170: 0 | AD170: 0 | AE170: 0 | AF170: 0 | AG170: 0
A171: REGION | B171: GHA_PRO_BLEND_OIL | C171: 0 | D171: 0 | E171: 0 | F171: 0 | G171: 0 | H171: 0 | I171: 0 | J171: 0 | K171: 0 | L171: 0 | M171: 0 | N171: 0 | O171: 0 | P171: 0 | Q171: 0 | R171: 0 | S171: 0 | T171: 0 | U171: 0 | V171: 0 | W171: 0 | X171: 0 | Y171: 0 | Z171: 0 | AA171: 0 | AB171: 0 | AC171: 0 | AD171: 0 | AE171: 0 | AF171: 0 | AG171: 0
A172: REGION | B172: GHA_PRO_EXTR_COAL | C172: 0 | D172: 0 | E172: 0 | F172: 0 | G172: 0 | H172: 0 | I172: 0 | J172: 0 | K172: 0 | L172: 0 | M172: 0 | N172: 0 | O172: 0 | P172: 0 | Q172: 0 | R172: 0 | S172: 0 | T172: 0 | U172: 0 | V172: 0 | W172: 0 | X172: 0 | Y172: 0 | Z172: 0 | AA172: 0 | AB172: 0 | AC172: 0 | AD172: 0 | AE172: 0 | AF172: 0 | AG172: 0
A173: REGION | B173: GHA_PRO_EXTR_NG | C173: 0 | D173: 0 | E173: 0 | F173: 0 | G173: 0 | H173: 0 | I173: 0 | J173: 0 | K173: 0 | L173: 0 | M173: 0 | N173: 0 | O173: 0 | P173: 0 | Q173: 0 | R173: 0 | S173: 0 | T173: 0 | U173: 0 | V173: 0 | W173: 0 | X173: 0 | Y173: 0 | Z173: 0 | AA173: 0 | AB173: 0 | AC173: 0 | AD173: 0 | AE173: 0 | AF173: 0 | AG173: 0
A174: REGION | B174: GHA_PRO_EXTR_OIL | C174: 0 | D174: 0 | E174: 0 | F174: 0 | G174: 0 | H174: 0 | I174: 0 | J174: 0 | K174: 0 | L174: 0 | M174: 0 | N174: 0 | O174: 0 | P174: 0 | Q174: 0 | R174: 0 | S174: 0 | T174: 0 | U174: 0 | V174: 0 | W174: 0 | X174: 0 | Y174: 0 | Z174: 0 | AA174: 0 | AB174: 0 | AC174: 0 | AD174: 0 | AE174: 0 | AF174: 0 | AG174: 0
A175: REGION | B175: GHA_PRO_EXTR_UR | C175: 0 | D175: 0 | E175: 0 | F175: 0 | G175: 0 | H175: 0 | I175: 0 | J175: 0 | K175: 0 | L175: 0 | M175: 0 | N175: 0 | O175: 0 | P175: 0 | Q175: 0 | R175: 0 | S175: 0 | T175: 0 | U175: 0 | V175: 0 | W175: 0 | X175: 0 | Y175: 0 | Z175: 0 | AA175: 0 | AB175: 0 | AC175: 0 | AD175: 0 | AE175: 0 | AF175: 0 | AG175: 0
A176: REGION | B176: GHA_PRO_PROC_BIOF1 | C176: 0 | D176: 0 | E176: 0 | F176: 0 | G176: 0 | H176: 0 | I176: 0 | J176: 0 | K176: 0 | L176: 0 | M176: 0 | N176: 0 | O176: 0 | P176: 0 | Q176: 0 | R176: 0 | S176: 0 | T176: 0 | U176: 0 | V176: 0 | W176: 0 | X176: 0 | Y176: 0 | Z176: 0 | AA176: 0 | AB176: 0 | AC176: 0 | AD176: 0 | AE176: 0 | AF176: 8.93e-05 | AG176: 132.77715
A177: REGION | B177: GHA_PRO_PROC_BIOM | C177: 0 | D177: 0 | E177: 0 | F177: 0 | G177: 0 | H177: 0 | I177: 0 | J177: 0 | K177: 0 | L177: 0 | M177: 0 | N177: 0 | O177: 0 | P177: 0 | Q177: 0 | R177: 0 | S177: 0 | T177: 0 | U177: 0 | V177: 0 | W177: 0 | X177: 0 | Y177: 0 | Z177: 0 | AA177: 0 | AB177: 0 | AC177: 0 | AD177: 0 | AE177: 0 | AF177: 0 | AG177: 0
A178: REGION | B178: GHA_PRO_PROC_COAL | C178: 0 | D178: 0 | E178: 0 | F178: 0 | G178: 0 | H178: 0 | I178: 0 | J178: 0 | K178: 0 | L178: 0 | M178: 0 | N178: 0 | O178: 0 | P178: 0 | Q178: 0 | R178: 0 | S178: 0 | T178: 0 | U178: 0 | V178: 0 | W178: 0 | X178: 0 | Y178: 0 | Z178: 0 | AA178: 0 | AB178: 0 | AC178: 0 | AD178: 0 | AE178: 0 | AF178: 0 | AG178: 0
A179: REGION | B179: GHA_PRO_PROC_NG | C179: 0 | D179: 0 | E179: 0 | F179: 0 | G179: 0 | H179: 0 | I179: 0 | J179: 0 | K179: 0 | L179: 0 | M179: 0 | N179: 0 | O179: 0 | P179: 0 | Q179: 0 | R179: 0 | S179: 0 | T179: 0 | U179: 0 | V179: 0 | W179: 0 | X179: 0 | Y179: 0 | Z179: 0 | AA179: 0 | AB179: 0 | AC179: 0 | AD179: 0 | AE179: 0 | AF179: 0 | AG179: 0
A180: REGION | B180: GHA_PRO_PROC_OIL | C180: 0 | D180: 0 | E180: 0 | F180: 0 | G180: 0 | H180: 0 | I180: 0 | J180: 0 | K180: 0 | L180: 0 | M180: 0 | N180: 0 | O180: 0 | P180: 0 | Q180: 0 | R180: 0 | S180: 0 | T180: 0 | U180: 0 | V180: 0 | W180: 0 | X180: 0 | Y180: 0 | Z180: 0 | AA180: 0 | AB180: 0 | AC180: 0 | AD180: 0 | AE180: 0 | AF180: 0 | AG180: 0
A181: REGION | B181: GHA_PRO_PROC_TRADBIOM | C181: 0 | D181: 0 | E181: 0 | F181: 0 | G181: 0 | H181: 0 | I181: 0 | J181: 0 | K181: 0 | L181: 0 | M181: 0 | N181: 0 | O181: 0 | P181: 0 | Q181: 0 | R181: 0 | S181: 0 | T181: 0 | U181: 0 | V181: 0 | W181: 0 | X181: 0 | Y181: 0 | Z181: 0 | AA181: 0 | AB181: 0 | AC181: 0 | AD181: 0 | AE181: 0 | AF181: 0 | AG181: 0
... A220: REGION | B220: SLE_POST_UNIT | C220: 0 | D220: 0 | E220: 0 | F220: 0 | G220: 0 | H220: 0 | I220: 0 | J220: 0 | K220: 0 | L220: 0 | M220: 0 | N220: 0 | O220: 0 | P220: 0 | Q220: 0 | R220: 0 | S220: 0 | T220: 0 | U220: 0 | V220: 0 | W220: 0 | X220: 0 | Y220: 0 | Z220: 0 | AA220: 0 | AB220: 0 | AC220: 0 | AD220: 0 | AE220: 0 | AF220: 0 | AG220: 0

Sheet Annualized_Investments
A1: Million USD
B2: Year | C2: 2020 | D2: 2021 | E2: 2022 | F2: 2023 | G2: 2024 | H2: 2025 | I2: 2026 | J2: 2027 | K2: 2028 | L2: 2029 | M2: 2030 | N2: 2031 | O2: 2032 | P2: 2033 | Q2: 2034 | R2: 2035 | S2: 2036 | T2: 2037 | U2: 2038 | V2: 2039 | W2: 2040 | X2: 2041 | Y2: 2042 | Z2: 2043 | AA2: 2044 | AB2: 2045 | AC2: 2046 | AD2: 2047 | AE2: 2048 | AF2: 2049 | AG2: 2050 | AH2: 2051 | AI2: 2052 | AJ2: 2053
B3: PHL_AGR_HEAT_BIOM | C3: 0.20265373 | D3: 0.20265373 | E3: 0.20265373 | F3: 0.20265373 | G3: 0.20265373 | H3: 0.20265373 | I3: 0.20265373 | J3: 0.20265373 | K3: 0.20265373 | L3: 0.20265373 | M3: 0.20265373 | N3: 0.20265373 | O3: 0.20265373 | P3: 0.20265373 | Q3: 0.20265373 | R3: 0.20265373 | S3: 0.20265373 | T3: 0.20265373 | U3: 0.20265373 | V3: 0.20265373 | W3: 0.20265373 | X3: 0.20265373 | Y3: 0.20265373 | Z3: 0.20265373 | AA3: 0.20265373
B4: PHL_AGR_HEAT_NG | C4: 3.1837178 | D4: 3.3150272 | E4: 3.4060153 | F4: 3.4976385 | G4: 3.5898294 | H4: 3.6825407 | I4: 3.7830769 | J4: 3.8840591 | K4: 3.9854468 | L4: 4.0871994 | M4: 4.1922361 | N4: 4.3107537 | O4: 4.4292713 | P4: 4.547789 | Q4: 4.6663066 | R4: 4.7848242 | S4: 4.9246817 | T4: 5.0645391 | U4: 5.2043965 | V4: 5.344254 | W4: 5.4408642 | X4: 5.4408642 | Y4: 5.4408642 | Z4: 5.4408642 | AA4: 5.4408642 | AB4: 4.0658056 | AC4: 3.9344962 | AD4: 3.8435081 | AE4: 3.7518849 | AF4: 3.659694 | AG4: 7.8931162 | AH4: 8.0929386 | AI4: 8.292315 | AJ4: 8.491286
B5: PHL_AGR_HEAT_OIL | C5: 0.73768932 | D5: 0.73768932 | E5: 0.73768932 | F5: 0.73768932 | G5: 0.73768932 | H5: 0.73768932 | I5: 0.73768932 | J5: 0.73768932 | K5: 0.73768932 | L5: 0.73768932 | M5: 0.73768932 | N5: 0.73768932 | O5: 0.73768932 | P5: 0.73768932 | Q5: 0.73768932 | R5: 0.73768932 | S5: 0.73768932 | T5: 0.73768932 | U5: 0.73768932 | V5: 0.73768932 | W5: 0.73768932 | X5: 0.73768932 | Y5: 0.73768932 | Z5: 0.73768932 | AA5: 0.73768932
B6: PHL_AGR_MOT_LIQ | C6: 1309.3852 | D6: 1343.3332 | E6: 1377.2813 | F6: 1411.8249 | G6: 1446.9641 | H6: 1482.6989 | I6: 1521.7772 | J6: 1561.4962 | K6: 1601.8558 | L6: 1643.4966 | M6: 1685.7781 | N6: 1733.9893 | O6: 1782.9201 | P6: 1831.8509 | Q6: 1877.5976 | R6: 2198.7256 | S6: 2259.9655 | T6: 2321.2054 | U6: 2383.2292 | V6: 2444.6575 | W6: 2505.4901 | X6: 2575.1311 | Y6: 2645.6846 | Z6: 2715.5975 | AA6: 2784.2291 | AB6: 2852.2201 | AC6: 2928.9705 | AD6: 3005.0013 | AE6: 3082.7921 | AF6: 3159.6936 | AG6: 3305.498 | AH6: 3391.9993 | AI6: 3478.5006 | AJ6: 3563.6224
B7: PHL_HOU_COOK_BIOM | C7: 2083.34 | D7: 2083.34 | E7: 2083.34 | F7: 2083.34 | G7: 2083.34 | H7: 2083.34 | I7: 2083.34 | J7: 2083.34 | K7: 2083.34 | L7: 2083.34 | M7: 2083.34 | N7: 2083.34 | O7: 2083.34 | P7: 2083.34 | Q7: 2083.34
B8: PHL_HOU_COOK_COAL | D8: 2208.019 | E8: 2241.5777 | F8: 2296.9071 | G8: 2338.3289 | H8: 2372.106 | I8: 2407.9074 | J8: 2441.3928 | K8: 2483.2534 | L8: 2498.9036 | M8: 2527.0201 | N8: 2561.715 | O8: 2584.1201 | P8: 2613.7796 | Q8: 2642.8012 | R8: 2752.3885 | S8: 2778.612 | T8: 2804.8354 | U8: 2831.068 | V8: 2857.2915 | W8: 2883.5241 | X8: 2906.8206 | Y8: 2930.117 | Z8: 2953.4135 | AA8: 2976.71 | AB8: 3000.0157 | AC8: 3020.1741 | AD8: 3040.3326 | AE8: 3060.4911 | AF8: 3080.6587 | AG8: 3100.8172 | AH8: 3118.2139 | AI8: 3135.6013 | AJ8: 3152.998
B9: PHL_HOU_COOK_ELE | C9: 101.97367 | D9: 101.97367 | E9: 101.97367 | F9: 101.97367 | G9: 101.97367 | H9: 101.97367 | I9: 101.97367 | J9: 101.97367 | K9: 101.97367 | L9: 101.97367 | M9: 101.97367 | N9: 101.97367 | O9: 101.97367 | P9: 101.97367 | Q9: 101.97367
B10: PHL_INDU_OTHHPH_BIOM | C10: 23.647988 | D10: 23.647988 | E10: 23.647988 | F10: 23.647988 | G10: 23.647988 | H10: 23.647988 | I10: 23.647988 | J10: 23.647988 | K10: 23.647988 | L10: 23.647988 | M10: 23.647988 | N10: 23.647988 | O10: 23.647988 | P10: 23.647988 | Q10: 23.647988 | R10: 23.647988 | S10: 23.647988 | T10: 23.647988 | U10: 23.647988 | V10: 23.647988 | W10: 23.647988 | X10: 23.647988 | Y10: 23.647988 | Z10: 23.647988 | AA10: 23.647988
B11: PHL_INDU_OTHHPH_COAL | C11: 46.682345 | D11: 137.70501 | E11: 140.83673 | F11: 143.9507 | G11: 147.04756 | H11: 150.12794 | I11: 153.44366 | J11: 156.74292 | K11: 160.02638 | L11: 163.29472 | M11: 166.51787 | N11: 170.15337 | O11: 173.77412 | P11: 177.38088 | Q11: 180.97443 | R11: 184.55551 | S11: 188.78726 | T11: 193.00596 | U11: 197.21242 | V11: 201.40743 | W11: 205.55182 | X11: 210.35264 | Y11: 215.14384 | Z11: 219.92939 | AA11: 224.6288 | AB11: 224.25299 | AC11: 220.13046 | AD11: 225.46746 | AE11: 230.20299 | AF11: 235.24561 | AG11: 240.23367 | AH11: 245.74004 | AI11: 251.26288 | AJ11: 256.80151
B12: PHL_INDU_OTHHPH_NG | C12: 0.2391233 | D12: 0.2391233 | E12: 0.2391233 | F12: 0.2391233 | G12: 0.2391233 | H12: 0.2391233 | I12: 0.2391233 | J12: 0.2391233 | K12: 0.2391233 | L12: 0.2391233 | M12: 0.2391233 | N12: 0.2391233 | O12: 0.2391233 | P12: 0.2391233 | Q12: 0.2391233 | R12: 0.2391233 | S12: 0.2391233 | T12: 0.2391233 | U12: 0.2391233 | V12: 0.2391233 | W12: 0.2391233 | X12: 0.2391233 | Y12: 0.2391233 | Z12: 0.2391233 | AA12: 0.2391233
B13: PHL_INDU_OTHHPH_OIL | C13: 30.260845 | D13: 30.260845 | E13: 30.260845 | F13: 30.260845 | G13: 30.260845 | H13: 30.260845 | I13: 30.260845 | J13: 30.260845 | K13: 30.260845 | L13: 30.260845 | M13: 30.260845 | N13: 30.260845 | O13: 30.260845 | P13: 30.260845 | Q13: 30.260845 | R13: 30.260845 | S13: 30.260845 | T13: 30.260845 | U13: 30.260845 | V13: 30.260845 | W13: 30.260845 | X13: 30.260845 | Y13: 30.260845 | Z13: 30.260845 | AA13: 30.260845
B14: PHL_INDU_OTHLPH_BIOM | C14: 23.647988 | D14: 23.647988 | E14: 23.647988 | F14: 23.647988 | G14: 23.647988 | H14: 23.647988 | I14: 23.647988 | J14: 23.647988 | K14: 23.647988 | L14: 23.647988 | M14: 23.647988 | N14: 23.647988 | O14: 23.647988 | P14: 23.647988 | Q14: 23.647988 | R14: 23.647988 | S14: 23.647988 | T14: 23.647988 | U14: 23.647988 | V14: 23.647988 | W14: 23.647988 | X14: 23.647988 | Y14: 23.647988 | Z14: 23.647988 | AA14: 23.647988
B15: PHL_INDU_OTHLPH_COAL | C15: 46.682345 | D15: 137.70501 | E15: 140.83673 | F15: 143.9507 | G15: 147.04756 | H15: 150.12794 | I15: 153.44366 | J15: 156.74292 | K15: 160.02638 | L15: 163.29472 | M15: 166.51787 | N15: 170.15337 | O15: 173.77412 | P15: 177.38088 | Q15: 180.97443 | R15: 184.55551 | S15: 188.78726 | T15: 193.00596 | U15: 197.21242 | V15: 201.40743 | W15: 205.55182 | X15: 210.35264 | Y15: 215.14384 | Z15: 219.92939 | AA15: 224.6288 | AB15: 223.21648 | AC15: 226.03197 | AD15: 229.3487 | AE15: 233.34245 | AF15: 237.10246 | AG15: 240.76432 | AH15: 245.40163 | AI15: 250.92447 | AJ15: 256.4631
B16: PHL_INDU_OTHLPH_NG | C16: 0.21971611 | D16: 0.21971611 | E16: 0.21971611 | F16: 0.21971611 | G16: 0.21971611 | H16: 0.21971611 | I16: 0.21971611 | J16: 0.21971611 | K16: 0.21971611 | L16: 0.21971611 | M16: 0.21971611 | N16: 0.21971611 | O16: 0.21971611 | P16: 0.21971611 | Q16: 0.21971611 | R16: 0.21971611 | S16: 0.21971611 | T16: 0.21971611 | U16: 0.21971611 | V16: 0.21971611 | W16: 0.21971611 | X16: 0.21971611 | Y16: 0.21971611 | Z16: 0.21971611 | AA16: 0.21971611
B17: PHL_INDU_OTHLPH_OIL | C17: 34.242722 | D17: 34.242722 | E17: 34.242722 | F17: 34.242722 | G17: 34.242722 | H17: 34.242722 | I17: 34.242722 | J17: 34.242722 | K17: 34.242722 | L17: 34.242722 | M17: 34.242722 | N17: 34.242722 | O17: 34.242722 | P17: 34.242722 | Q17: 34.242722 | R17: 34.242722 | S17: 34.242722 | T17: 34.242722 | U17: 34.242722 | V17: 34.242722
B18: PHL_POW_CHP_BIOM_OLD | E18: 45.512469 | F18: 48.842649 | G18: 54.337447 | H18: 54.337447 | I18: 54.337447 | J18: 54.337447 | K18: 54.337447 | L18: 54.337447 | M18: 54.337447 | N18: 54.337447 | O18: 54.337447 | P18: 54.337447 | Q18: 54.337447 | R18: 54.337447 | S18: 54.337447 | T18: 54.337447 | U18: 54.337447 | V18: 54.337447 | W18: 54.337447 | X18: 54.337447 | Y18: 54.337447 | Z18: 54.337447 | AA18: 54.337447 | AB18: 54.337447 | AC18: 54.337447 | AD18: 54.337447 | AE18: 54.337447 | AF18: 54.337447 | AG18: 54.337447 | AH18: 54.337447 | AI18: 54.337447 | AJ18: 54.337447
B19: PHL_POW_CHP_OIL_OLD | D19: 99.794413 | E19: 153.79884 | F19: 153.79884 | G19: 160.01518 | H19: 160.01518 | I19: 160.01518 | J19: 160.01518 | K19: 160.01518 | L19: 160.01518 | M19: 160.01518 | N19: 160.01518 | O19: 160.01518 | P19: 160.01518 | Q19: 160.01518 | R19: 160.01518 | S19: 160.01518 | T19: 160.01518 | U19: 160.01518 | V19: 160.01518 | W19: 160.01518 | X19: 160.01518 | Y19: 160.01518 | Z19: 160.01518 | AA19: 160.01518 | AB19: 160.01518 | AC19: 160.01518 | AD19: 160.01518 | AE19: 160.01518 | AF19: 160.01518 | AG19: 160.01518 | AH19: 160.01518 | AI19: 160.01518 | AJ19: 160.01518
B20: PHL_POW_GEO_OLD | E20: 2.0536114 | F20: 2.0536114 | G20: 2.0536114 | H20: 21.868186 | I20: 21.868186 | J20: 21.868186 | K20: 21.868186 | L20: 21.868186 | M20: 21.868186 | N20: 21.868186 | O20: 21.868186 | P20: 21.868186 | Q20: 21.868186 | R20: 21.868186 | S20: 21.868186 | T20: 21.868186 | U20: 21.868186 | V20: 21.868186 | W20: 21.868186 | X20: 21.868186 | Y20: 21.868186 | Z20: 21.868186 | AA20: 21.868186 | AB20: 21.868186 | AC20: 21.868186 | AD20: 21.868186 | AE20: 21.868186 | AF20: 21.868186 | AG20: 21.868186 | AH20: 21.868186 | AI20: 21.868186 | AJ20: 21.868186
B21: PHL_POW_PP_COAL | D21: 76.300543 | E21: 157.27384 | F21: 157.27384 | G21: 220.41912 | H21: 220.41912 | I21: 220.41912 | J21: 288.80896 | K21: 340.51505 | L21: 669.18394 | M21: 734.33536 | N21: 808.93657 | O21: 1020.5949 | P21: 1139.182 | Q21: 1266.5553 | R21: 1391.2376 | S21: 1630.0599 | T21: 1841.2372 | U21: 2051.163 | V21: 2262.5834 | W21: 2262.5834 | X21: 2262.5834 | Y21: 2262.5834 | Z21: 2262.5834 | AA21: 2262.5834 | AB21: 2275.7998 | AC21: 2199.4992 | AD21: 2118.5259 | AE21: 2098.0278 | AF21: 2034.8825 | AG21: 2021.1857 | AH21: 1858.2996 | AI21: 1747.5721 | AJ21: 1734.7027
B22: PHL_POW_PP_HY_LA | C22: 119.29659 | D22: 119.29659 | E22: 120.59284 | F22: 124.40819 | G22: 127.27786 | H22: 127.27786 | I22: 127.27786 | J22: 127.27786 | K22: 127.27786 | L22: 127.27786 | M22: 127.27786 | N22: 127.27786 | O22: 127.27786 | P22: 127.27786 | Q22: 127.27786 | R22: 127.27786 | S22: 127.27786 | T22: 127.27786 | U22: 127.27786 | V22: 127.27786 | W22: 127.27786 | X22: 127.27786 | Y22: 127.27786 | Z22: 127.27786 | AA22: 127.27786 | AB22: 127.27786 | AC22: 127.27786 | AD22: 127.27786 | AE22: 127.27786 | AF22: 127.27786 | AG22: 127.27786 | AH22: 127.27786 | AI22: 127.27786 | AJ22: 127.27786
B23: PHL_POW_PP_NGCC | H23: 39.669519 | I23: 39.669519 | J23: 39.669519 | K23: 39.669519 | L23: 39.669519 | M23: 39.669519 | N23: 39.669519 | O23: 39.669519 | P23: 39.669519 | Q23: 39.669519 | R23: 39.669519 | S23: 39.669519 | T23: 39.669519 | U23: 39.669519 | V23: 75.660957 | W23: 89.31102 | X23: 89.31102 | Y23: 89.31102 | Z23: 89.31102 | AA23: 89.31102 | AB23: 182.7285 | AC23: 182.7285 | AD23: 182.7285 | AE23: 182.7285 | AF23: 182.7285 | AG23: 300.29201 | AH23: 332.49584 | AI23: 332.49584 | AJ23: 334.05845
B24: PHL_POW_PP_SPV_T1 | D24: 17.87676 | E24: 35.182747 | F24: 43.737239 | G24: 96.293446 | H24: 110.19144 | I24: 110.19144 | J24: 110.19144 | K24: 110.19144 | L24: 110.19144 | M24: 373.66013 | N24: 373.66013 | O24: 373.66013 | P24: 373.66013 | Q24: 448.99732 | R24: 448.99732 | S24: 448.99732 | T24: 448.99732 | U24: 448.99732 | V24: 448.99732 | W24: 1178.7439 | X24: 1178.7439 | Y24: 1180.0775 | Z24: 1181.3251 | AA24: 1182.4248 | AD24: 62.764779 | AE24: 130.86508 | AF24: 317.39635 | AG24: 2553.4477 | AH24: 2945.8834 | AI24: 3445.2015 | AJ24: 3716.6355
B25: PHL_POW_PP_WON_T1 | C25: 24.191247 | D25: 24.191247 | E25: 24.191247 | F25: 24.191247 | G25: 24.191247 | H25: 24.191247 | I25: 24.191247 | J25: 24.191247 | K25: 24.191247 | L25: 24.191247 | M25: 24.191247 | N25: 24.191247 | O25: 24.191247 | P25: 24.191247 | Q25: 24.191247 | R25: 24.191247 | S25: 24.191247 | T25: 24.191247 | U25: 24.191247 | V25: 24.191247 | W25: 24.191247 | X25: 24.191247 | Y25: 24.191247 | Z25: 24.191247 | AA25: 24.191247 | AB25: 2222.151 | AC25: 2255.2683 | AD25: 2255.2683 | AE25: 2307.6895 | AF25: 2310.3359 | AG25: 2361.3286 | AH25: 2343.4518 | AI25: 2326.1458 | AJ25: 2367.9285
B26: PHL_PRO_PROC_BIOF | C26: 635.13228 | D26: 653.49715 | E26: 672.36587 | F26: 690.70727 | G26: 709.4952 | H26: 728.03374 | I26: 750.76014 | J26: 773.16563 | K26: 795.60276 | L26: 817.28734 | M26: 817.28734 | N26: 832.4644 | O26: 859.89259 | P26: 888.02458 | Q26: 914.39225 | R26: 937.4606 | S26: 963.2388 | T26: 988.96999 | U26: 1012.6473 | V26: 1035.3206 | W26: 1055.2255 | X26: 1085.9558 | Y26: 1114.0766 | Z26: 1144.9622 | AA26: 1178.6895 | AB26: 1884.1066 | AC26: 2154.3378 | AD26: 2272.252 | AE26: 2452.905 | AF26: 2452.905 | AG26: 3049.6728 | AH26: 3049.6728 | AI26: 3091.0889 | AJ26: 3126.4557
B27: PHL_SER_HEAT_BIOM | C27: 182.57059 | D27: 182.57059 | E27: 182.57059 | F27: 182.57059 | G27: 182.57059 | H27: 182.57059 | I27: 182.57059 | J27: 182.57059 | K27: 182.57059 | L27: 182.57059 | M27: 182.57059 | N27: 182.57059 | O27: 182.57059 | P27: 182.57059 | Q27: 182.57059 | AD27: 0.0027 | AE27: 0.0057 | AF27: 0.0137 | AG27: 0.1117 | AH27: 0.1289 | AI27: 0.1508 | AJ27: 0.1627
B28: PHL_SER_HEAT_NG | D28: 128.83128 | E28: 141.08394 | F28: 153.3676 | G28: 707.5684 | H28: 717.27681 | I28: 726.52879 | J28: 735.80357 | K28: 745.10092 | L28: 754.42056 | M28: 763.76567 | N28: 772.85538 | O28: 781.96754 | P28: 791.10192 | Q28: 816.36903 | R28: 961.26258 | S28: 998.81799 | T28: 1032.0554 | U28: 1065.3561 | V28: 1118.3228 | W28: 1151.7316 | X28: 1206.3931 | Y28: 1261.1706 | Z28: 1316.0507 | AA28: 1371.021 | AB28: 1009.7987 | AC28: 1035.8324 | AD28: 1061.8604 | AE28: 1088.5363 | AF28: 1118.2937 | AG28: 1145.652 | AH28: 1178.6912 | AI28: 1213.4025 | AJ28: 1248.6425
B29: PHL_SER_HEAT_OIL | C29: 599.26102 | D29: 599.26102 | E29: 599.26102 | F29: 599.26102 | G29: 599.26102 | H29: 599.26102 | I29: 599.26102 | J29: 599.26102 | K29: 599.26102 | L29: 599.26102 | M29: 599.26102 | N29: 599.26102 | O29: 599.26102 | P29: 599.26102 | Q29: 599.26102
B30: PHL_SER_HEAT_RES | C30: 3421.7516 | AB30: 1420.722 | AC30: 1489.4422 | AD30: 1562.3321 | AE30: 1639.6121 | AF30: 1710.5749 | AG30: 1785.8403 | AH30: 1874.287 | AI30: 1959.3013 | AJ30: 2044.2195
B31: PHL_TRA_23WHEEL_ELE | D31: 8.2006238 | E31: 16.398166 | F31: 24.59879 | G31: 32.799413 | H31: 40.996955 | I31: 49.197579 | J31: 57.395121 | K31: 65.595745 | L31: 73.796369 | M31: 81.993911 | N31: 90.194534 | O31: 98.395158 | P31: 112.5297 | Q31: 116.07552 | R31: 107.8749 | S31: 99.677354 | T31: 91.47673 | U31: 83.276106 | V31: 66.877941 | W31: 50.479775 | X31: 34.078527 | Y31: 11.743361
B32: PHL_TRA_23WHEEL_LIQ | C32: 2.981702 | D32: 19.576863 | E32: 35.899146 | F32: 52.300154 | G32: 68.855227 | H32: 85.024225 | I32: 101.20813 | J32: 117.39359 | K32: 133.65778 | L32: 152.00557 | M32: 161.98869 | N32: 182.09004 | O32: 198.15294 | P32: 213.63693 | Q32: 217.10836 | R32: 219.08782 | S32: 223.57077 | T32: 228.05371 | U32: 234.00603 | V32: 235.09345 | W32: 247.75364 | X32: 252.89759 | Y32: 259.77113 | Z32: 264.90972 | AA32: 267.08385
B33: PHL_TRA_AVI_LIQ | D33: 104.7431 | E33: 212.20702 | F33: 319.67095 | G33: 421.59163 | H33: 528.65793 | I33: 651.38586 | J33: 771.87264 | K33: 885.85313 | L33: 1004.9254 | M33: 1127.3526 | N33: 1271.5447 | O33: 1410.2956 | P33: 1553.0458 | Q33: 1693.2005 | R33: 1829.8513 | S33: 1988.5369 | T33: 2147.5794 | U33: 2300.2603 | V33: 2492.7162 | W33: 2492.7162 | X33: 2660.0334 | Y33: 2798.6482 | Z33: 2913.757 | AA33: 3008.1852 | AB33: 606.79962 | AC33: 620.27178 | AD33: 618.9559 | AE33: 580.55469 | AF33: 580.55469 | AG33: 629.36748 | AH33: 632.43395 | AI33: 641.59696 | AJ33: 650.83571
B34: PHL_TRA_BUS_LIQ | C34: 0.010915386 | D34: 21.273618 | E34: 33.363733 | F34: 55.035066 | G34: 67.338494 | H34: 89.412265 | I34: 101.74769 | J34: 123.92285 | K34: 136.46817 | L34: 158.90769 | M34: 171.93558 | N34: 197.0659 | O34: 211.04644 | P34: 235.98887 | Q34: 239.53291 | R34: 243.76522 | S34: 246.91431 | T34: 250.66959 | U34: 253.78153 | V34: 257.3749 | W34: 260.0937 | X34: 263.34073 | Y34: 266.04537 | Z34: 269.27371 | AA34: 271.78283 | AB34: 117.17088 | AC34: 121.99434 | AD34: 126.86475 | AE34: 131.02927 | AF34: 131.02927 | AG34: 131.34971 | AH34: 132.31535 | AI34: 131.82479 | AJ34: 131.33423
B35: PHL_TRA_CAR_ELE | R35: 111.66253 | S35: 232.4809 | T35: 353.02535 | U35: 515.92863 | V35: 683.0415 | W35: 964.65146 | X35: 989.26353 | Y35: 1154.6184 | Z35: 1260.5171 | AA35: 1281.6936 | AB35: 3081.4028 | AC35: 3166.7153 | AD35: 3232.7421 | AE35: 3284.0212 | AF35: 3467.6864 | AG35: 3345.2592 | AH35: 3201.0671 | AI35: 3062.3162 | AJ35: 2919.5661
B36: PHL_TRA_CAR_LIQ | C36: 47.200133 | D36: 181.40788 | E36: 316.13177 | F36: 450.07283 | G36: 585.70606 | H36: 721.71825 | I36: 861.0681 | J36: 999.47156 | K36: 1139.4647 | L36: 1279.7514 | M36: 1422.032 | N36: 1562.7688 | O36: 1704.9185 | P36: 1847.1371 | Q36: 1905.0929 | R36: 1857.8928 | S36: 1803.2438 | T36: 1748.0965 | U36: 1651.1195 | V36: 1549.3538 | W36: 1413.3417 | X36: 1363.1432 | Y36: 1253.9423 | Z36: 1203.0292 | AA36: 1235.6781 | AB36: 274.51255 | AC36: 276.71958 | AD36: 279.07102 | AE36: 281.25836 | AF36: 283.62343 | AG36: 285.84791 | AH36: 288.59173 | AI36: 290.76978 | AJ36: 293.25555
B37: PHL_TRA_RAILF_ELE | C37: 2.323214 | D37: 2.323214 | E37: 2.323214 | F37: 2.323214 | G37: 2.323214 | H37: 2.323214 | I37: 2.323214 | J37: 2.323214 | K37: 2.323214 | L37: 2.323214 | M37: 2.323214 | N37: 2.323214 | O37: 2.323214 | P37: 2.323214 | Q37: 2.323214 | R37: 2.323214 | S37: 2.323214 | T37: 2.323214 | U37: 2.323214 | V37: 2.323214 | AB37: 2117.6991 | AC37: 2304.37 | AD37: 2490.9335 | AE37: 2676.5 | AF37: 2715.8381 | AG37: 2751.9935 | AH37: 2818.9799 | AI37: 2843.3903 | AJ37: 2868.6412
B38: PHL_TRA_RAILF_LIQ | E38: 1.2227442 | F38: 1.2227442 | G38: 2.4454884 | H38: 2.4454884 | I38: 3.6682326 | J38: 4.8909767 | K38: 4.8909767 | L38: 6.2359953 | M38: 7.9456363 | N38: 8.6814837 | O38: 8.8437801 | P38: 10.066524 | Q38: 11.289268 | R38: 12.512013 | S38: 13.734757 | T38: 14.957501 | U38: 16.180245 | V38: 18.625734 | W38: 22.009388 | X38: 23.232132 | Y38: 25.67762 | Z38: 28.123109 | AA38: 29.345853 | AB38: 466.10923 | AC38: 325.37246 | AD38: 183.22269 | AE38: 41.004168 | AF38: 41.004168 | AG38: 41.004168
B39: PHL_TRA_RAILP_ELE | C39: 2.323214 | D39: 2.323214 | E39: 2.323214 | F39: 2.323214 | G39: 2.323214 | H39: 2.323214 | I39: 2.323214 | J39: 2.323214 | K39: 2.323214 | L39: 2.323214 | M39: 2.323214 | N39: 2.323214 | O39: 2.323214 | P39: 2.323214 | Q39: 2.323214 | R39: 2.323214 | S39: 2.323214 | T39: 2.323214 | U39: 2.323214 | V39: 2.323214
B40: PHL_TRA_RAILP_LIQ | E40: 1.2227442 | F40: 1.2227442 | G40: 2.4454884 | H40: 2.4454884 | I40: 3.6682326 | J40: 3.6682326 | K40: 4.8909767 | L40: 5.0132512 | M40: 6.7228921 | N40: 7.4587395 | O40: 7.6210359 | P40: 8.8437801 | Q40: 10.066524 | R40: 11.289268 | S40: 12.512013 | T40: 13.734757 | U40: 14.957501 | V40: 16.180245 | W40: 19.563899 | X40: 22.009388 | Y40: 23.232132 | Z40: 24.454876 | AA40: 26.900364 | AB40: 31.791349 | AC40: 34.236837 | AD40: 36.682326 | AE40: 39.127814 | AF40: 41.573302 | AG40: 44.018791 | AH40: 47.687023 | AI40: 50.132512 | AJ40: 53.800744
B41: PHL_TRA_SHIP_LIQ | D41: 1602006.3 | E41: 3204412.4 | F41: 4806787.9 | G41: 6407561 | H41: 8004007.7 | I41: 9725532.5 | J41: 11437407 | K41: 13132164 | L41: 14805350 | M41: 16544764 | N41: 18362007 | O41: 20179218 | P41: 21978288 | Q41: 23741646 | R41: 25463818 | S41: 27229196 | T41: 28931498 | U41: 30565708 | V41: 32602490 | W41: 32602490 | X41: 33952430 | Y41: 35007163 | Z41: 35796163 | AA41: 36347628
B42: PHL_TRA_TRUH_LIQ | C42: 24.962268 | D42: 91.317432 | E42: 158.89242 | F42: 227.59307 | G42: 297.33362 | H42: 368.03571 | I42: 446.97959 | J42: 520.98412 | K42: 601.60614 | L42: 683.00856 | M42: 769.23305 | N42: 864.31159 | O42: 959.64849 | P42: 1055.3092 | Q42: 1106.9737 | R42: 1164.4692 | S42: 1241.4645 | T42: 1317.5568 | U42: 1392.9784 | V42: 1467.7144 | W42: 1542.7188 | X42: 1628.8011 | Y42: 1713.5898 | Z42: 1798.5766 | AA42: 1883.0659 | AB42: 28.123124 | AC42: 30.568612 | AD42: 33.014101 | AE42: 35.459589 | AF42: 37.905077 | AG42: 40.350566 | AH42: 42.796054 | AI42: 45.241543 | AJ42: 48.909775
B43: PHL_TRA_TRUL_LIQ | D43: 173.67997 | E43: 349.43166 | F43: 523.87773 | G43: 700.29704 | H43: 875.42706 | I43: 1070.0536 | J43: 1265.0144 | K43: 1458.717 | L43: 1654.2965 | M43: 1849.3856 | N43: 2065.121 | O43: 2279.5094 | P43: 2495.7794 | Q43: 2609.7393 | R43: 2723.7484 | S43: 2867.9538 | T43: 3012.0239 | U43: 3155.9917 | V43: 3299.8219 | W43: 3444.3758 | X43: 3612.2874 | Y43: 3779.9972 | Z43: 3947.589 | AA43: 4115.0684 | AB43: 36688215 | AC43: 36842620 | AD43: 36820690 | AE43: 36646898 | AF43: 37711436 | AG43: 35972021 | AH43: 34154779 | AI43: 32337567 | AJ43: 30538497
B44: PHL_TRA_VAN_LIQ | D44: 23.256166 | E44: 48.181696 | F44: 71.54048 | G44: 96.568931 | H44: 120.0193 | I44: 147.57016 | J44: 173.51267 | K44: 201.15578 | L44: 227.18062 | M44: 255.00569 | N44: 283.82013 | O44: 314.29307 | P44: 343.17102 | Q44: 358.84864 | R44: 374.51675 | S44: 394.33599 | T44: 414.15724 | U44: 433.94551 | V44: 453.732 | W44: 473.60078 | X44: 496.69897 | Y44: 519.73979 | Z44: 542.79675 | AA44: 565.82428 | AB44: 1962.9878 | AC44: 2049.9082 | AD44: 2136.7139 | AE44: 2223.4807 | AF44: 2308.3842 | AG44: 2395.7724 | AH44: 2486.1156 | AI44: 2576.142 | AJ44: 2665.7961

Sheet AnnualProduction
A1: PJ
A2: REGION | B2: TECHNOLOGY | C2: FUEL | D2: 2020 | E2: 2021 | F2: 2022 | G2: 2023 | H2: 2024 | I2: 2025 | J2: 2026 | K2: 2027 | L2: 2028 | M2: 2029 | N2: 2030 | O2: 2031 | P2: 2032 | Q2: 2033 | R2: 2034 | S2: 2035 | T2: 2036 | U2: 2037 | V2: 2038 | W2: 2039 | X2: 2040 | Y2: 2041 | Z2: 2042 | AA2: 2043 | AB2: 2044 | AC2: 2045 | AD2: 2046 | AE2: 2047 | AF2: 2048 | AG2: 2049 | AH2: 2050
A3: REGION | B3: PHL_POW_CHP_BIOM_OLD | D3: 4.5001 | X3: 2.622
A4: REGION | B4: PHL_POW_CHP_COAL_OLD | D4: 209.448 | E4: 267.4663 | F4: 260.1144 | G4: 282.3083 | H4: 270.198 | I4: 280.2652 | J4: 294.9046 | K4: 295.1153 | L4: 297.8016 | M4: 244.0884 | N4: 205.5552 | O4: 207.5043 | P4: 183.2414 | Q4: 180.99 | R4: 168.1629 | S4: 154.7733 | T4: 131.9355 | U4: 126.8662 | V4: 108.6501 | W4: 87.6324 | X4: 89.5062 | Y4: 74.4149 | Z4: 73.9025 | AA4: 73.2537 | AB4: 72.5562 | AC4: 72.7884 | AD4: 80.3926 | AE4: 90.3477 | AF4: 91.8448 | AG4: 96.9765 | AH4: 82.2351
A5: REGION | B5: PHL_POW_CHP_NG_OLD | D5: 70.1999 | G5: 2.5742 | H5: 7.6658 | I5: 6.1766 | J5: 13.8689 | K5: 16.0469 | L5: 19.6313 | M5: 2.082 | N5: 3.369 | O5: 5.9496 | P5: 1.2662 | Q5: 1.2662 | R5: 1.2662 | S5: 1.2662 | T5: 1.2662 | U5: 1.2662 | V5: 1.2662 | W5: 1.2662 | X5: 2.5324 | Y5: 1.2662 | Z5: 1.1196 | AA5: 0.8868 | AB5: 0.6616 | AC5: 0.629
A6: REGION | B6: PHL_POW_CHP_OIL_OLD | D6: 8.8922 | X6: 1.2252
A7: REGION | B7: PHL_POW_GEO_OLD | D7: 38.8084 | E7: 39.597 | F7: 39.7134 | G7: 29.763 | H7: 29.763 | I7: 30.8892 | J7: 30.8892 | K7: 30.8892 | L7: 30.8892 | M7: 30.8892 | N7: 30.8892 | O7: 30.8892 | P7: 30.8892 | Q7: 26.4756 | R7: 26.4756 | S7: 26.4756 | T7: 23.0532 | U7: 3.81 | V7: 3.81 | W7: 3.81 | X7: 3.81 | Y7: 3.81 | Z7: 3.81 | AA7: 3.81 | AB7: 3.81 | AC7: 3.81 | AD7: 3.81 | AE7: 3.81 | AF7: 3.81 | AG7: 3.81 | AH7: 3.6265
A8: REGION | B8: PHL_POW_PP_COAL | E8: 22.863 | F8: 47.1276 | G8: 47.1276 | H8: 66.0492 | I8: 66.0492 | J8: 66.0492 | K8: 86.5416 | L8: 102.036 | M8: 200.5224 | N8: 220.0458 | O8: 242.3994 | P8: 301.2118 | Q8: 334.9236 | R8: 363.1336 | S8: 395.0822 | T8: 456.459 | U8: 515.8758 | V8: 569.151 | W8: 622.4308 | X8: 499.2266 | Y8: 484.0198 | Z8: 483.6206 | AA8: 483.27 | AB8: 482.934 | AC8: 482.9252 | AD8: 469.9854 | AE8: 456.3914 | AF8: 456.781 | AG8: 452.101 | AH8: 712.8526
A9: REGION | B9: PHL_POW_PP_HY_LA | D9: 25.8852 | E9: 25.8852 | F9: 25.9644 | G9: 26.2002 | H9: 26.3784 | I9: 26.3784 | J9: 26.3784 | K9: 26.3784 | L9: 26.3784 | M9: 26.3784 | N9: 26.3784 | O9: 26.3784 | P9: 26.3784 | Q9: 26.3784 | R9: 26.3784 | S9: 26.3784 | T9: 26.3784 | U9: 26.3784 | V9: 26.3784 | W9: 26.3784 | X9: 26.3784 | Y9: 26.3784 | Z9: 26.3784 | AA9: 26.3784 | AB9: 26.3784 | AC9: 26.3784 | AD9: 26.3784 | AE9: 26.2626 | AF9: 26.2626 | AG9: 26.2626 | AH9: 23.731
A10: REGION | B10: PHL_POW_PP_NGCC | I10: 7.547 | J10: 7.7919 | K10: 7.7964 | L10: 7.8004 | M10: 5.8164 | N10: 5.8164 | O10: 5.8164 | P10: 4.359 | Q10: 4.7826 | R10: 3.9576 | S10: 3.6596 | T10: 3.4528 | U10: 3.246 | V10: 3.6208 | W10: 8.5266 | X10: 12.7114 | Y10: 8.2622 | Z10: 7.782 | AA10: 7.5726 | AB10: 7.3676 | AC10: 7.3518 | AD10: 14.5172 | AE10: 20.2026 | AF10: 21.0484 | AG10: 24.0716 | AH10: 47.7869
A11: REGION | B11: PHL_POW_PP_SPV_T1 | D11: 4.9571 | E11: 7.1622 | F11: 8.9052 | G11: 9.8016 | H11: 15.5262 | I11: 17.0982 | J11: 17.0982 | K11: 17.0982 | L11: 17.0982 | M11: 17.0982 | N11: 58.5204 | O11: 58.5204 | P11: 58.5204 | Q11: 58.5204 | R11: 71.5178 | S11: 71.5178 | T11: 71.5178 | U11: 71.5178 | V11: 71.5178 | W11: 71.5178 | X11: 219.5332 | Y11: 219.5332 | Z11: 219.8198 | AA11: 220.0942 | AB11: 220.2162 | AC11: 220.9704 | AD11: 222.0966 | AE11: 223.5318 | AF11: 225.19 | AG11: 227.1056 | AH11: 376.5749
A12: REGION | B12: PHL_POW_PP_WON_T1 | D12: 3.708 | E12: 3.708 | F12: 3.708 | G12: 3.708 | H12: 3.708 | I12: 3.708 | J12: 3.708 | K12: 3.708 | L12: 3.708 | M12: 3.708 | N12: 3.5244 | O12: 3.5244 | P12: 3.5244 | Q12: 3.5244 | R12: 3.5244 | S12: 3.5244 | T12: 3.5244 | U12: 3.5244 | V12: 3.5244 | W12: 1.8324 | X12: 1.3314 | Y12: 1.3314 | Z12: 1.3314 | AA12: 1.3314 | AB12: 1.3314
A13: REGION | B13: PHL_PRO_EXTR_COAL | D13: 743.1914 | E13: 1376.3553 | F13: 1417.7464 | G13: 1498.9662 | H13: 1513.9154 | I13: 1554.5084 | J13: 1610.1561 | K13: 1667.0517 | L13: 1721.1818 | M13: 1785.0093 | N13: 1717.9964 | O13: 1785.3666 | P13: 1852.3785 | Q13: 313.1769
A14: REGION | B14: PHL_PRO_EXTR_NG | D14: 140.4442 | E14: 26.6454 | F14: 28.9794 | G14: 36.382 | H14: 157.8122 | I14: 169.2283 | J14: 185.9475 | K14: 191.3757 | L14: 199.6093 | M14: 162.6245 | N14: 163.5878 | O14: 170.0618 | P14: 159.6241 | Q14: 161.7292 | R14: 164.1264 | S14: 175.123 | T14: 179.9185 | U14: 184.7049 | V14: 190.5016 | W14: 204.2217 | X14: 218.7435 | Y14: 216.9469 | Z14: 224.3138 | AA14: 231.9927 | AB14: 239.7029 | AC14: 248.1342 | AD14: 270.1406 | AE14: 290.806 | AF14: 303.0095 | AG14: 319.0285 | AH14: 368.9707
A15: REGION | B15: PHL_PRO_EXTR_OIL | D15: 244.7203
A16: REGION | B16: PHL_PRO_IMP_COAL | Q16: 1618.8072 | R16: 1965.5583 | S16: 2014.7458 | T16: 2093.7476 | U16: 2224.2532 | V16: 2299.2351 | W16: 2365.3999 | X16: 2098.5935 | Y16: 2027.1901 | Z16: 2035.7156 | AA16: 2043.945 | AB16: 2052.073 | AC16: 2063.9002 | AD16: 2070.2158 | AE16: 2082.4571 | AF16: 2100.1246 | AG16: 2117.6315 | AH16: 2679.5424
A17: REGION | B17: PHL_PRO_IMP_OIL | D17: 15.2004 | E17: 113.9802 | F17: 112.8551 | G17: 111.7855 | H17: 10.9122 | I17: 11.0006 | J17: 11.0836 | K17: 11.1692 | L17: 11.2568 | M17: 11.346 | N17: 11.225 | O17: 11.3302 | P17: 11.435 | Q17: 11.5392 | R17: 9.3394 | X17: 6.2846
A18: REGION | B18: PHL_PRO_PROC_BIOF | D18: 440.9859 | E18: 452.281 | F18: 463.9193 | G18: 475.2173 | H18: 486.9053 | I18: 498.2698 | J18: 512.5187 | K18: 526.5652 | L18: 540.6425 | M18: 554.762 | N18: 544.8781 | O18: 562.5742 | P18: 580.0402 | Q18: 597.7284 | R18: 615.3657 | S18: 629.3549 | T18: 645.7625 | U18: 662.1499 | V18: 677.1664 | W18: 692.2167 | X18: 704.1387 | Y18: 723.9541 | Z18: 741.9002 | AA18: 761.846 | AB18: 784.5724 | AC18: 807.338 | AD18: 831.8618 | AE18: 856.4187 | AF18: 881.0267 | AG18: 905.6598 | AH18: 924.2015
A19: REGION | B19: PHL_PRO_PROC_BIOM | D19: 304.3034 | E19: 1.7528 | F19: 1.7672 | G19: 1.782 | X19: 10.5
A20: REGION | B20: PHL_PRO_PROC_COAL | D20: 740.2592 | E20: 1370.9258 | F20: 1412.1534 | G20: 1493.0529 | H20: 1507.9431 | I20: 1548.3761 | J20: 1603.8037 | K20: 1660.4746 | L20: 1714.3919 | M20: 1777.968 | N20: 1711.2184 | O20: 1778.3234 | P20: 1845.071 | Q20: 1924.3623 | R20: 1957.8044 | S20: 2006.7983 | T20: 2085.4878 | U20: 2215.4788 | V20: 2290.1651 | W20: 2356.0692 | X20: 2090.3147 | Y20: 2019.1926 | Z20: 2027.6846 | AA20: 2035.8814 | AB20: 2043.9766 | AC20: 2055.7588 | AD20: 2062.0489 | AE20: 2074.2418 | AF20: 2091.8397 | AG20: 2109.278 | AH20: 2668.9719
A21: REGION | B21: PHL_PRO_PROC_NG | D21: 132.899 | E21: 25.2138 | F21: 27.423 | G21: 34.4278 | H21: 149.3343 | I21: 160.1371 | J21: 175.9578 | K21: 181.0947 | L21: 188.8861 | M21: 153.8885 | N21: 154.7997 | O21: 160.9255 | P21: 151.0489 | Q21: 153.0406 | R21: 155.3095 | S21: 165.715 | T21: 170.2529 | U21: 174.7823 | V21: 180.2675 | W21: 193.2503 | X21: 206.9923 | Y21: 205.2923 | Z21: 212.2636 | AA21: 219.5299 | AB21: 226.8254 | AC21: 234.8034 | AD21: 255.6281 | AE21: 275.1834 | AF21: 286.7311 | AG21: 301.8898 | AH21: 349.1489
A22: REGION | B22: PHL_PRO_PROC_OIL | D22: 264.4028 | E22: 115.9461 | F22: 114.8014 | G22: 113.7132 | H22: 11.1002 | I22: 11.1902 | J22: 11.275 | K22: 11.3618 | L22: 11.4506 | M22: 11.5418 | N22: 11.4186 | O22: 11.5256 | P22: 11.6322 | Q22: 11.7382 | R22: 9.5004 | X22: 6.393

Sheet New Capacity
A1: GW
A2: REGION | B2: TECHNOLOGY | C2: 2020 | D2: 2021 | E2: 2022 | F2: 2023 | G2: 2024 | H2: 2025 | I2: 2026 | J2: 2027 | K2: 2028 | L2: 2029 | M2: 2030 | N2: 2031 | O2: 2032 | P2: 2033 | Q2: 2034 | R2: 2035 | S2: 2036 | T2: 2037 | U2: 2038 | V2: 2039 | W2: 2040 | X2: 2041 | Y2: 2042 | Z2: 2043 | AA2: 2044 | AB2: 2045 | AC2: 2046 | AD2: 2047 | AE2: 2048 | AF2: 2049 | AG2: 2050
A3: REGION | B3: PHL_AGR_FAC | C3: 999999 | D3: 999999 | E3: 999999 | F3: 999999 | G3: 999999 | H3: 999999 | I3: 999999 | J3: 999999 | K3: 999999 | L3: 999999 | M3: 999999 | N3: 999999 | O3: 999999 | P3: 999999 | Q3: 999999 | R3: 999999 | S3: 999999 | T3: 999999 | U3: 999999 | V3: 999999 | W3: 999999 | X3: 999999 | Y3: 999999 | Z3: 999999 | AA3: 999999 | AB3: 999999 | AC3: 999999 | AD3: 999999 | AE3: 999999 | AF3: 999999 | AG3: 999999 | AH3: 999999 | AI3: 999999 | AJ3: 999999
A4: REGION | B4: PHL_AGR_HEAT_BIOM | C4: 0.0039 | D4: 0 | E4: 0 | F4: 0 | G4: 0 | H4: 0 | I4: 0 | J4: 0 | K4: 0 | L4: 0 | M4: 0 | N4: 0 | O4: 0 | P4: 0 | Q4: 0 | R4: 0 | S4: 0 | T4: 0 | U4: 0 | V4: 0 | W4: 0 | X4: 0 | Y4: 0 | Z4: 0 | AA4: 0 | AB4: 0 | AC4: 0 | AD4: 0 | AE4: 0 | AF4: 0 | AG4: 0 | AH4: 0 | AI4: 0 | AJ4: 0
A5: REGION | B5: PHL_AGR_HEAT_COAL | C5: 0 | D5: 0 | E5: 0 | F5: 0 | G5: 0 | H5: 0 | I5: 0 | J5: 0 | K5: 0 | L5: 0 | M5: 0 | N5: 0 | O5: 0 | P5: 0 | Q5: 0 | R5: 0 | S5: 0 | T5: 0 | U5: 0 | V5: 0 | W5: 0 | X5: 0 | Y5: 0 | Z5: 0 | AA5: 0 | AB5: 0 | AC5: 0 | AD5: 0 | AE5: 0 | AF5: 0 | AG5: 0 | AH5: 0 | AI5: 0 | AJ5: 0
A6: REGION | B6: PHL_AGR_HEAT_ELE | C6: 0 | D6: 0 | E6: 0 | F6: 0 | G6: 0 | H6: 0 | I6: 0 | J6: 0 | K6: 0 | L6: 0 | M6: 0 | N6: 0 | O6: 0 | P6: 0 | Q6: 0 | R6: 0 | S6: 0 | T6: 0 | U6: 0 | V6: 0 | W6: 0 | X6: 0 | Y6: 0 | Z6: 0 | AA6: 0 | AB6: 0 | AC6: 0 | AD6: 0 | AE6: 0 | AF6: 0 | AG6: 0 | AH6: 0 | AI6: 0 | AJ6: 0
A7: REGION | B7: PHL_AGR_HEAT_NG | C7: 0.315 | D7: 0.0129 | E7: 0.0089 | F7: 0.0089 | G7: 0.0089 | H7: 0.0089 | I7: 0.0096 | J7: 0.0096 | K7: 0.0096 | L7: 0.0096 | M7: 0.0096 | N7: 0.0108 | O7: 0.0108 | P7: 0.0108 | Q7: 0.0108 | R7: 0.0108 | S7: 0.0127 | T7: 0.0127 | U7: 0.0127 | V7: 0.0127 | W7: 0.0088 | X7: 0 | Y7: 0 | Z7: 0 | AA7: 0 | AB7: 0.1645 | AC7: 0 | AD7: 0 | AE7: 0 | AF7: 0 | AG7: 0.3935 | AH7: 0.0273 | AI7: 0.0273 | AJ7: 0.0273
A8: REGION | B8: PHL_AGR_HEAT_OIL | C8: 0.0375 | D8: 0 | E8: 0 | F8: 0 | G8: 0 | H8: 0 | I8: 0 | J8: 0 | K8: 0 | L8: 0 | M8: 0 | N8: 0 | O8: 0 | P8: 0 | Q8: 0 | R8: 0 | S8: 0 | T8: 0 | U8: 0 | V8: 0 | W8: 0 | X8: 0 | Y8: 0 | Z8: 0 | AA8: 0 | AB8: 0 | AC8: 0 | AD8: 0 | AE8: 0 | AF8: 0 | AG8: 0 | AH8: 0 | AI8: 0 | AJ8: 0
A9: REGION | B9: PHL_AGR_MOT_ELE | C9: 0 | D9: 0 | E9: 0 | F9: 0 | G9: 0 | H9: 0 | I9: 0 | J9: 0 | K9: 0 | L9: 0 | M9: 0 | N9: 0 | O9: 0 | P9: 0 | Q9: 0 | R9: 0 | S9: 0 | T9: 0 | U9: 0 | V9: 0 | W9: 0 | X9: 0 | Y9: 0 | Z9: 0 | AA9: 0 | AB9: 0 | AC9: 0 | AD9: 0 | AE9: 0 | AF9: 0 | AG9: 0 | AH9: 0 | AI9: 0 | AJ9: 0
A10: REGION | B10: PHL_AGR_MOT_LIQ | C10: 250.36 | D10: 6.491 | E10: 6.491 | F10: 6.491 | G10: 6.491 | H10: 6.491 | I10: 6.982 | J10: 6.982 | K10: 6.982 | L10: 6.982 | M10: 6.982 | N10: 7.8423 | O10: 7.8423 | P10: 7.8423 | Q10: 7.2258 | R10: 257.5417 | S10: 15.0351 | T10: 15.0351 | U10: 15.0351 | V10: 15.0351 | W10: 15.0351 | X10: 16.927 | Y10: 16.927 | Z10: 16.927 | AA10: 16.927 | AB10: 16.927 | AC10: 19.1819 | AD10: 19.1819 | AE10: 19.1818 | AF10: 18.5653 | AG10: 268.8812 | AH10: 27.5023 | AI10: 27.5023 | AJ10: 27.5023
A11: REGION | B11: PHL_AGR_UNIT | C11: 999999 | D11: 999999 | E11: 999999 | F11: 999999 | G11: 999999 | H11: 999999 | I11: 999999 | J11: 999999 | K11: 999999 | L11: 999999 | M11: 999999 | N11: 999999 | O11: 999999 | P11: 999999 | Q11: 999999 | R11: 999999 | S11: 999999 | T11: 999999 | U11: 999999 | V11: 999999 | W11: 999999 | X11: 999999 | Y11: 999999 | Z11: 999999 | AA11: 999999 | AB11: 999999 | AC11: 999999 | AD11: 999999 | AE11: 999999 | AF11: 999999 | AG11: 999999 | AH11: 999999 | AI11: 999999 | AJ11: 999999
A12: REGION | B12: PHL_DEM_PUB_GWT_WAT | C12: 999999 | D12: 999999 | E12: 999999 | F12: 999999 | G12: 999999 | H12: 999999 | I12: 999999 | J12: 999999 | K12: 999999 | L12: 999999 | M12: 999999 | N12: 999999 | O12: 999999 | P12: 999999 | Q12: 999999 | R12: 999999 | S12: 999999 | T12: 999999 | U12: 999999 | V12: 999999 | W12: 999999 | X12: 999999 | Y12: 999999 | Z12: 999999 | AA12: 999999 | AB12: 999999 | AC12: 999999 | AD12: 999999 | AE12: 999999 | AF12: 999999 | AG12: 999999 | AH12: 999999 | AI12: 999999 | AJ12: 999999
A13: REGION | B13: PHL_DEM_PUB_SUR_WAT | C13: 999999 | D13: 999999 | E13: 999999 | F13: 999999 | G13: 999999 | H13: 999999 | I13: 999999 | J13: 999999 | K13: 999999 | L13: 999999 | M13: 999999 | N13: 999999 | O13: 999999 | P13: 999999 | Q13: 999999 | R13: 999999 | S13: 999999 | T13: 999999 | U13: 999999 | V13: 999999 | W13: 999999 | X13: 999999 | Y13: 999999 | Z13: 999999 | AA13: 999999 | AB13: 999999 | AC13: 999999 | AD13: 999999 | AE13: 999999 | AF13: 999999 | AG13: 999999 | AH13: 999999 | AI13: 999999 | AJ13: 999999
A14: REGION | B14: PHL_DEM_PWR_GWT_WAT | C14: 999999 | D14: 999999 | E14: 999999 | F14: 999999 | G14: 999999 | H14: 999999 | I14: 999999 | J14: 999999 | K14: 999999 | L14: 999999 | M14: 999999 | N14: 999999 | O14: 999999 | P14: 999999 | Q14: 999999 | R14: 999999 | S14: 999999 | T14: 999999 | U14: 999999 | V14: 999999 | W14: 999999 | X14: 999999 | Y14: 999999 | Z14: 999999 | AA14: 999999 | AB14: 999999 | AC14: 999999 | AD14: 999999 | AE14: 999999 | AF14: 999999 | AG14: 999999 | AH14: 999999 | AI14: 999999 | AJ14: 999999
... A133: REGION | B133: PHL_TRA_VAN_NG | C133: 0 | D133: 0 | E133: 0 | F133: 0 | G133: 0 | H133: 0 | I133: 0 | J133: 0 | K133: 0 | L133: 0 | M133: 0 | N133: 0 | O133: 0 | P133: 0 | Q133: 0 | R133: 0 | S133: 0 | T133: 0 | U133: 0 | V133: 0 | W133: 0 | X133: 0 | Y133: 0 | Z133: 0 | AA133: 0 | AB133: 0 | AC133: 0 | AD133: 0 | AE133: 0 | AF133: 0 | AG133: 0 | AH133: 0 | AI133: 0 | AJ133: 0
B134: PHL_TRA_VAN_PHEV | C134: 0 | D134: 0 | E134: 0 | F134: 0 | G134: 0 | H134: 0 | I134: 0 | J134: 0 | K134: 0 | L134: 0 | M134: 0 | N134: 0 | O134: 0 | P134: 0 | Q134: 0 | R134: 0 | S134: 0 | T134: 0 | U134: 0 | V134: 0 | W134: 0 | X134: 0 | Y134: 0 | Z134: 0 | AA134: 0 | AB134: 0 | AC134: 0 | AD134: 0 | AE134: 0 | AF134: 0 | AG134: 0 | AH134: 0 | AI134: 0 | AJ134: 0
B135: (blank)

Sheet Operation Life Time
F2: Discount Rate | G2: 0.05 | J2: Convert PJ -->GWh | K2: 277.77778
B3: Operation Life Time
B4: Technology | C4: Parameter | D4: Life period | E4: CRF (Capital Recovery Factor)
B5: PHL_POW_CHP_BIOM_OLD | D5: 25 | E5: =$G$2*(1+$G$2)^D5/((1+$G$2)^D5-1) -> 0.070952457
B6: PHL_POW_CHP_COAL_OLD | D6: 25 | E6: =$G$2*(1+$G$2)^D6/((1+$G$2)^D6-1) -> 0.070952457
B7: PHL_POW_GEO_OLD | D7: 25 | E7: =$G$2*(1+$G$2)^D7/((1+$G$2)^D7-1) -> 0.070952457
B8: PHL_POW_PP_BIOM_CCS | D8: 25 | E8: =$G$2*(1+$G$2)^D8/((1+$G$2)^D8-1) -> 0.070952457
B9: PHL_POW_PP_COAL | D9: 25 | E9: =$G$2*(1+$G$2)^D9/((1+$G$2)^D9-1) -> 0.070952457
B10: PHL_POW_PP_COAL_CCS | D10: 25 | E10: =$G$2*(1+$G$2)^D10/((1+$G$2)^D10-1) -> 0.070952457
B11: PHL_POW_PP_H2 | D11: 25 | E11: =$G$2*(1+$G$2)^D11/((1+$G$2)^D11-1) -> 0.070952457
B12: PHL_POW_PP_HY_LA | D12: 50 | E12: =$G$2*(1+$G$2)^D12/((1+$G$2)^D12-1) -> 0.054776735
B13: PHL_POW_PP_NGCC | D13: 25 | E13: =$G$2*(1+$G$2)^D13/((1+$G$2)^D13-1) -> 0.070952457
B14: PHL_POW_PP_NGCC_CCS | D14: 25 | E14: =$G$2*(1+$G$2)^D14/((1+$G$2)^D14-1) -> 0.070952457
B15: PHL_POW_PP_NU | D15: 40 | E15: =$G$2*(1+$G$2)^D15/((1+$G$2)^D15-1) -> 0.058278161
B16: PHL_POW_PP_NUSMR | D16: 60 | E16: =$G$2*(1+$G$2)^D16/((1+$G$2)^D16-1) -> 0.052828185
... B21: PHL_POW_CHP_NG_OLD | D21: 1 | E21: =$G$2*(1+$G$2)^D21/((1+$G$2)^D21-1) -> 1.05
